Workbook

Sheet Compras
A1: Total: | B1: =C2+C8+C13+C18+C23+C28+C32+C34+C38+C50 -> 0 | E1: Deck | F1: =A2 -> Marcelo | G1: =B3 -> Victor | H1: =B4 -> Hamster | I1: =B5 -> Marcelo | J1: =B6 -> Liga | L1: Deck | M1: Entra | N1: Sai | O1: Fonte
A2: Marcelo | B2: Total Lojas: | C2: =SUM(C3:C6) -> 0 | F2: Jhoira | L2: Arabella | M2: Take Up The Shield | O2: Leilão 3
A3: =COUNTA(F2:F215) -> 4 | B3: Victor | C3: =SUM(G:G) -> 0 | F3: JhoiraB | L3: Hivelord | M3: Avenge | O3: Leilão 3
B4: Hamster | C4: =SUM(H:H) -> 0 | F4: 4cRash | L4: Inalla | M4: Gilded Lotus | N4: Mana Echoes | O4: Leilão 3
B5: Marcelo | C5: =SUM(I:I) -> 0 | F5: Baylen | L5: Oona | M5: The Great Mound | N5: Island | O5: Leilão 3
B6: Liga | C6: =SUM(J:J) -> 0 | L6: Sisay | M6: Freyalise, Llanowar's Fury | N6: Life Insurance | O6: Elfos
L7: Thrakiri | M7: Plaza of Heroes | N7: Kessig Wolf Run | O7: Leilão 3
L8: Oona | M8: Arc Reactor | N8: Spell Stuter | O8: Rei
L9: Oona | M9: Shuri, Wakandan Inventor | N9: Liliana of the Dark Realms | O9: Rei
L10: Toph | M10: Coin of Mastery | N10: Harrow | O10: Rei
L11: Toph | M11: The Ooze | N11: Costume Closet | O11: Rei
L12: Spara | M12: Kellan, the Kid | N12: Omnivorous Flytrap | O12: Rei
L13: Arabella | M13: Battle Screech | O13: Rei
L14: Sisay | M14: The Peregrine Dynamo | N14: Urza Assembles the Titans | O14: Rei
L15: Arabella | M15: Genasi Enforcers | O15: Rei
L16: Arabella | M16: Wyrm's Crossing Patrol | O16: Rei
L17: Arabella | M17: Clowning Around | O17: Rei
L18: Arabella | M18: Blacksmith's Skill | O18: Rei
L19: Baylen | M19: Artifact Mutation | N19: Chatterstorm | O19: Rei
L20: Arabella | M20: Goblin Smuggler | O20: Rei
L21: Arabella | M21: Goblin Instigator | O21: Rei
L22: Alela | M22: Damping Sphere | N22: Dispeller's Capsule | O22: Rei
L23: Arabella | M23: Pathmaker Initiate | O23: Rei
L24: Yorion | M24: Ephara, God of the Polis | N24: Ellyn Harbreeze, Busybody | O24: Rei
L25: Pests | M25: Nuisance Engine | N25: Tablet of the Guilds | O25: Rei
L26: Arabella | M26: Goblin Tunneler | O26: Rei
L27: Arabella | M27: Gold Myr | O27: Rei

Sheet Missing
A1: Nome da Origem | B1: Carta Ideal | C1: Em Uso | D1: Deck | F1: Alterações | H1: Cores | M1: =COUNTA(F3:F5000) & " Decks" -> 37 Decks
A2: Narset.xlsx | B2: Abandoned Air Temple | C2: =IF(COUNTIF(Substitutas!$B:$B, B2) > 0, "✅ Tenho", "❌ Faltando") -> ❌ Faltando | D2: =_xlfn.XLOOKUP(B2, Substitutas!$B:$B, Substitutas!$A:$A, "-") -> - | F2: Total | G2: =SUM(G3:G62) -> 410 | H2: =COUNTIF(H3:H5000,"Sim") -> 23 | I2: =COUNTIF(I3:I5000,"Sim") -> 27 | J2: =COUNTIF(J3:J5000,"Sim") -> 27 | K2: =COUNTIF(K3:K5000,"Sim") -> 27 | L2: =COUNTIF(L3:L5000,"Sim") -> 23 | M2: Wincon | N2: Sub Plan | O2: Descrição | P2: Prioridade
A3: Spara.xlsx | B3: Abandoned Air Temple | C3: =IF(COUNTIF(Substitutas!$B:$B, B3) > 0, "✅ Tenho", "❌ Faltando") -> ❌ Faltando | D3: =_xlfn.XLOOKUP(B3, Substitutas!$B:$B, Substitutas!$A:$A, "-") -> - | G3: =COUNTIF(A:A,F3&".xlsx") -> 0 | H3: Não | I3: Não | J3: Não | K3: Não | L3: Não | P3: =IF(G3<6,"1",IF(G3<11,"2",IF(G3<16,"3",IF(G3<31,"4","5")))) -> 1
A4: Kadena.xlsx | B4: Abhorrent Oculus | C4: =IF(COUNTIF(Substitutas!$B:$B, B4) > 0, "✅ Tenho", "❌ Faltando") -> ❌ Faltando | D4: =_xlfn.XLOOKUP(B4, Substitutas!$B:$B, Substitutas!$A:$A, "-") -> - | G4: =COUNTIF(A:A,F4&".xlsx") -> 0 | H4: Sim | I4: Não | J4: Não | K4: Não | L4: Não | P4: =IF(G4<6,"1",IF(G4<11,"2",IF(G4<16,"3",IF(G4<31,"4","5")))) -> 1
A5: Arabella.xlsx | B5: Abraded Bluffs | C5: =IF(COUNTIF(Substitutas!$B:$B, B5) > 0, "✅ Tenho", "❌ Faltando") -> ❌ Faltando | D5: =_xlfn.XLOOKUP(B5, Substitutas!$B:$B, Substitutas!$A:$A, "-") -> - | F5: Muzzio | G5: =COUNTIF(A:A,F5&".xlsx") -> 4 | H5: Não | I5: Sim | J5: Não | K5: Não | L5: Não | M5: Combo | N5: - | O5: Engrenagens para Combar | P5: =IF(G5<6,"1",IF(G5<11,"2",IF(G5<16,"3",IF(G5<31,"4","5")))) -> 1
A6: Pé.xlsx | B6: Abrupt Decay | C6: =IF(COUNTIF(Substitutas!$B:$B, B6) > 0, "✅ Tenho", "❌ Faltando") -> ❌ Faltando | D6: =_xlfn.XLOOKUP(B6, Substitutas!$B:$B, Substitutas!$A:$A, "-") -> - | G6: =COUNTIF(A:A,F6&".xlsx") -> 0 | H6: Não | I6: Não | J6: Sim | K6: Não | L6: Não | P6: =IF(G6<6,"1",IF(G6<11,"2",IF(G6<16,"3",IF(G6<31,"4","5")))) -> 1
A7: Elfos.xlsx | B7: Abundant Countryside | C7: =IF(COUNTIF(Substitutas!$B:$B, B7) > 0, "✅ Tenho", "❌ Faltando") -> ❌ Faltando | D7: =_xlfn.XLOOKUP(B7, Substitutas!$B:$B, Substitutas!$A:$A, "-") -> - | G7: =COUNTIF(A:A,F7&".xlsx") -> 0 | H7: Não | I7: Não | J7: Não | K7: Sim | L7: Não | P7: =IF(G7<6,"1",IF(G7<11,"2",IF(G7<16,"3",IF(G7<31,"4","5")))) -> 1
A8: Fractius.xlsx | B8: Abundant Countryside | C8: =IF(COUNTIF(Substitutas!$B:$B, B8) > 0, "✅ Tenho", "❌ Faltando") -> ❌ Faltando | D8: =_xlfn.XLOOKUP(B8, Substitutas!$B:$B, Substitutas!$A:$A, "-") -> - | G8: =COUNTIF(A:A,F8&".xlsx") -> 0 | H8: Não | I8: Não | J8: Não | K8: Não | L8: Sim | P8: =IF(G8<6,"1",IF(G8<11,"2",IF(G8<16,"3",IF(G8<31,"4","5")))) -> 1
A9: Rani.xlsx | B9: Access Tunnel | C9: =IF(COUNTIF(Substitutas!$B:$B, B9) > 0, "✅ Tenho", "❌ Faltando") -> ❌ Faltando | D9: =_xlfn.XLOOKUP(B9, Substitutas!$B:$B, Substitutas!$A:$A, "-") -> - | F9: Yorion | G9: =COUNTIF(A:A,F9&".xlsx") -> 11 | H9: Sim | I9: Sim | J9: Não | K9: Não | L9: Não | P9: =IF(G9<6,"1",IF(G9<11,"2",IF(G9<16,"3",IF(G9<31,"4","5")))) -> 3
A10: Narset.xlsx | B10: Adarkar Wastes | C10: =IF(COUNTIF(Substitutas!$B:$B, B10) > 0, "✅ Tenho", "❌ Faltando") -> ❌ Faltando | D10: =_xlfn.XLOOKUP(B10, Substitutas!$B:$B, Substitutas!$A:$A, "-") -> - | F10: Arabella | G10: =COUNTIF(A:A,F10&".xlsx") -> 75 | H10: Sim | I10: Não | J10: Sim | K10: Não | L10: Não | M10: Combate | N10: Ping | O10: PauperEDH Aggro | P10: =IF(G10<6,"1",IF(G10<11,"2",IF(G10<16,"3",IF(G10<31,"4","5")))) -> 5
A11: Jhoira.xlsx | B11: Agna Qel'a | C11: =IF(COUNTIF(Substitutas!$B:$B, B11) > 0, "✅ Tenho", "❌ Faltando") -> ❌ Faltando | D11: =_xlfn.XLOOKUP(B11, Substitutas!$B:$B, Substitutas!$A:$A, "-") -> - | F11: Akiri | G11: =COUNTIF(A:A,F11&".xlsx") -> 12 | H11: Sim | I11: Não | J11: Sim | K11: Não | L11: Não | M11: Combate | N11: Voltron | O11: Equipamentos | P11: =IF(G11<6,"1",IF(G11<11,"2",IF(G11<16,"3",IF(G11<31,"4","5")))) -> 3
A12: JhoiraBichao.xlsx | B12: Agna Qel'a | C12: =IF(COUNTIF(Substitutas!$B:$B, B12) > 0, "✅ Tenho", "❌ Faltando") -> ❌ Faltando | D12: =_xlfn.XLOOKUP(B12, Substitutas!$B:$B, Substitutas!$A:$A, "-") -> - | F12: Carlos | G12: =COUNTIF(A:A,F12&".xlsx") -> 5 | H12: Sim | I12: Não | J12: Não | K12: Sim | L12: Não | M12: Voltron | N12: Dano Direto | O12: Ganhar Vida e Reanimate | P12: =IF(G12<6,"1",IF(G12<11,"2",IF(G12<16,"3",IF(G12<31,"4","5")))) -> 1
A13: Rielle.xlsx | B13: Agna Qel'a | C13: =IF(COUNTIF(Substitutas!$B:$B, B13) > 0, "✅ Tenho", "❌ Faltando") -> ❌ Faltando | D13: =_xlfn.XLOOKUP(B13, Substitutas!$B:$B, Substitutas!$A:$A, "-") -> - | G13: =COUNTIF(A:A,F13&".xlsx") -> 0 | H13: Sim | I13: Não | J13: Não | K13: Não | L13: Sim | P13: =IF(G13<6,"1",IF(G13<11,"2",IF(G13<16,"3",IF(G13<31,"4","5")))) -> 1
A14: Littles.xlsx | B14: Ainok Strike Leader | C14: =IF(COUNTIF(Substitutas!$B:$B, B14) > 0, "✅ Tenho", "❌ Faltando") -> ❌ Faltando | D14: =_xlfn.XLOOKUP(B14, Substitutas!$B:$B, Substitutas!$A:$A, "-") -> - | F14: JhoiraBichao | G14: =COUNTIF(A:A,F14&".xlsx") -> 9 | H14: Não | I14: Sim | J14: Sim | K14: Não | L14: Não | M14: Combo | N14: Combate | O14: Big Mana | P14: =IF(G14<6,"1",IF(G14<11,"2",IF(G14<16,"3",IF(G14<31,"4","5")))) -> 2
A15: Arcades.xlsx | B15: Alchemist's Refuge | C15: =IF(COUNTIF(Substitutas!$B:$B, B15) > 0, "✅ Tenho", "❌ Faltando") -> ❌ Faltando | D15: =_xlfn.XLOOKUP(B15, Substitutas!$B:$B, Substitutas!$A:$A, "-") -> - | F15: Jhoira | G15: =COUNTIF(A:A,F15&".xlsx") -> 5 | H15: Não | I15: Sim | J15: Sim | K15: Não | L15: Não | M15: Combo | N15: Combate | O15: Destruição em Massa | P15: =IF(G15<6,"1",IF(G15<11,"2",IF(G15<16,"3",IF(G15<31,"4","5")))) -> 1
A16: Spara.xlsx | B16: Alchemist's Refuge | C16: =IF(COUNTIF(Substitutas!$B:$B, B16) > 0, "✅ Tenho", "❌ Faltando") -> ❌ Faltando | D16: =_xlfn.XLOOKUP(B16, Substitutas!$B:$B, Substitutas!$A:$A, "-") -> - | F16: Rielle | G16: =COUNTIF(A:A,F16&".xlsx") -> 9 | H16: Não | I16: Sim | J16: Sim | K16: Não | L16: Não | M16: Voltron | N16: Dano Direto | O16: Controle Voltron x1 | P16: =IF(G16<6,"1",IF(G16<11,"2",IF(G16<16,"3",IF(G16<31,"4","5")))) -> 2
A17: Arabella.xlsx | B17: Alpine Meadow | C17: =IF(COUNTIF(Substitutas!$B:$B, B17) > 0, "✅ Tenho", "❌ Faltando") -> ❌ Faltando | D17: =_xlfn.XLOOKUP(B17, Substitutas!$B:$B, Substitutas!$A:$A, "-") -> - | F17: Yuriko | G17: =COUNTIF(A:A,F17&".xlsx") -> 9 | H17: Não | I17: Sim | J17: Não | K17: Sim | L17: Não | M17: Ping | N17: - | O17: Turnos Extras | P17: =IF(G17<6,"1",IF(G17<11,"2",IF(G17<16,"3",IF(G17<31,"4","5")))) -> 2
A18: VialIshai.xlsx | B18: Amphibian Downpour | C18: =IF(COUNTIF(Substitutas!$B:$B, B18) > 0, "✅ Tenho", "❌ Faltando") -> ❌ Faltando | D18: =_xlfn.XLOOKUP(B18, Substitutas!$B:$B, Substitutas!$A:$A, "-") -> - | F18: Oona | G18: =COUNTIF(A:A,F18&".xlsx") -> 3 | H18: Não | I18: Sim | J18: Não | K18: Sim | L18: Não | M18: Mill | N18: Combate | O18: Mill e Tokens | P18: =IF(G18<6,"1",IF(G18<11,"2",IF(G18<16,"3",IF(G18<31,"4","5")))) -> 1
A19: Spara.xlsx | B19: An Offer You Can't Refuse | C19: =IF(COUNTIF(Substitutas!$B:$B, B19) > 0, "✅ Tenho", "❌ Faltando") -> ❌ Faltando | D19: =_xlfn.XLOOKUP(B19, Substitutas!$B:$B, Substitutas!$A:$A, "-") -> - | F19: Kumena | G19: =COUNTIF(A:A,F19&".xlsx") -> 0 | H19: Não | I19: Sim | J19: Não | K19: Não | L19: Sim | M19: Combate | N19: Voltron | O19: Tribal de Tritões | P19: =IF(G19<6,"1",IF(G19<11,"2",IF(G19<16,"3",IF(G19<31,"4","5")))) -> 1
A20: Yorion.xlsx | B20: An Offer You Can't Refuse | C20: =IF(COUNTIF(Substitutas!$B:$B, B20) > 0, "✅ Tenho", "❌ Faltando") -> ❌ Faltando | D20: =_xlfn.XLOOKUP(B20, Substitutas!$B:$B, Substitutas!$A:$A, "-") -> - | G20: =COUNTIF(A:A,F20&".xlsx") -> 0 | H20: Não | I20: Não | J20: Sim | K20: Sim | L20: Não | P20: =IF(G20<6,"1",IF(G20<11,"2",IF(G20<16,"3",IF(G20<31,"4","5")))) -> 1
A21: Littles.xlsx | B21: Anguished Unmaking | C21: =IF(COUNTIF(Substitutas!$B:$B, B21) > 0, "✅ Tenho", "❌ Faltando") -> ❌ Faltando | D21: =_xlfn.XLOOKUP(B21, Substitutas!$B:$B, Substitutas!$A:$A, "-") -> - | G21: =COUNTIF(A:A,F21&".xlsx") -> 0 | H21: Não | I21: Não | J21: Sim | K21: Não | L21: Sim | P21: =IF(G21<6,"1",IF(G21<11,"2",IF(G21<16,"3",IF(G21<31,"4","5")))) -> 1
A22: Necrobloom.xlsx | B22: Anguished Unmaking | C22: =IF(COUNTIF(Substitutas!$B:$B, B22) > 0, "✅ Tenho", "❌ Faltando") -> ❌ Faltando | D22: =_xlfn.XLOOKUP(B22, Substitutas!$B:$B, Substitutas!$A:$A, "-") -> - | F22: Pé | G22: =COUNTIF(A:A,F22&".xlsx") -> 29 | H22: Não | I22: Não | J22: Não | K22: Sim | L22: Sim | M22: Ping | N22: Combate | O22: Aristocrata | P22: =IF(G22<6,"1",IF(G22<11,"2",IF(G22<16,"3",IF(G22<31,"4","5")))) -> 4
A23: Inalla.xlsx | B23: Apprentice Necromancer | C23: =IF(COUNTIF(Substitutas!$B:$B, B23) > 0, "✅ Tenho", "❌ Faltando") -> ❌ Faltando | D23: =_xlfn.XLOOKUP(B23, Substitutas!$B:$B, Substitutas!$A:$A, "-") -> - | F23: Pests | G23: =COUNTIF(A:A,F23&".xlsx") -> 19 | H23: Não | I23: Não | J23: Não | K23: Sim | L23: Sim | M23: Combate | N23: Voltron | O23: Tribal de Pestes | P23: =IF(G23<6,"1",IF(G23<11,"2",IF(G23<16,"3",IF(G23<31,"4","5")))) -> 4
A24: Pests.xlsx | B24: Arasta of the Endless Web | C24: =IF(COUNTIF(Substitutas!$B:$B, B24) > 0, "✅ Tenho", "❌ Faltando") -> ❌ Faltando | D24: =_xlfn.XLOOKUP(B24, Substitutas!$B:$B, Substitutas!$A:$A, "-") -> - | F24: Narset | G24: =COUNTIF(A:A,F24&".xlsx") -> 15 | H24: Sim | I24: Sim | J24: Sim | K24: Não | L24: Não | M24: Mill | N24: Combate | O24: Mill e Tokens | P24: =IF(G24<6,"1",IF(G24<11,"2",IF(G24<16,"3",IF(G24<31,"4","5")))) -> 3
A25: Muzzio.xlsx | B25: Arc Reactor | C25: =IF(COUNTIF(Substitutas!$B:$B, B25) > 0, "✅ Tenho", "❌ Faltando") -> ❌ Faltando | D25: =_xlfn.XLOOKUP(B25, Substitutas!$B:$B, Substitutas!$A:$A, "-") -> - | F25: Zedruu | G25: =COUNTIF(A:A,F25&".xlsx") -> 1 | H25: Sim | I25: Sim | J25: Sim | K25: Não | L25: Não | M25: Dano Direto | N25: Combo | O25: Caos | P25: =IF(G25<6,"1",IF(G25<11,"2",IF(G25<16,"3",IF(G25<31,"4","5")))) -> 1
A26: Oona.xlsx | B26: Arc Reactor | C26: =IF(COUNTIF(Substitutas!$B:$B, B26) > 0, "✅ Tenho", "❌ Faltando") -> ❌ Faltando | D26: =_xlfn.XLOOKUP(B26, Substitutas!$B:$B, Substitutas!$A:$A, "-") -> - | F26: Alela | G26: =COUNTIF(A:A,F26&".xlsx") -> 6 | H26: Sim | I26: Sim | J26: Não | K26: Sim | L26: Não | M26: Combate | N26: Voltron | O26: Stax e Tokens | P26: =IF(G26<6,"1",IF(G26<11,"2",IF(G26<16,"3",IF(G26<31,"4","5")))) -> 2
A27: Spara.xlsx | B27: Arcane Denial | C27: =IF(COUNTIF(Substitutas!$B:$B, B27) > 0, "✅ Tenho", "❌ Faltando") -> ❌ Faltando | D27: =_xlfn.XLOOKUP(B27, Substitutas!$B:$B, Substitutas!$A:$A, "-") -> - | F27: Arcades | G27: =COUNTIF(A:A,F27&".xlsx") -> 1 | H27: Sim | I27: Sim | J27: Não | K27: Não | L27: Sim | M27: Combate | N27: Voltron | O27: Bater sem Apanhar | P27: =IF(G27<6,"1",IF(G27<11,"2",IF(G27<16,"3",IF(G27<31,"4","5")))) -> 1
A28: Pé.xlsx | B28: Arcane Signet | C28: =IF(COUNTIF(Substitutas!$B:$B, B28) > 0, "✅ Tenho", "❌ Faltando") -> ❌ Faltando | D28: =_xlfn.XLOOKUP(B28, Substitutas!$B:$B, Substitutas!$A:$A, "-") -> - | F28: Littles | G28: =COUNTIF(A:A,F28&".xlsx") -> 23 | H28: Sim | I28: Não | J28: Sim | K28: Sim | L28: Não | M28: Combate | N28: Ping | O28: Aggro Small Creatures | P28: =IF(G28<6,"1",IF(G28<11,"2",IF(G28<16,"3",IF(G28<31,"4","5")))) -> 4
A29: VialIshai.xlsx | B29: Arid Mesa | C29: =IF(COUNTIF(Substitutas!$B:$B, B29) > 0, "✅ Tenho", "❌ Faltando") -> ❌ Faltando | D29: =_xlfn.XLOOKUP(B29, Substitutas!$B:$B, Substitutas!$A:$A, "-") -> - | F29: Zuko | G29: =COUNTIF(A:A,F29&".xlsx") -> 19 | H29: Sim | I29: Não | J29: Sim | K29: Sim | L29: Não | M29: Combate | N29: Voltron | O29: Sunforge Exile | P29: =IF(G29<6,"1",IF(G29<11,"2",IF(G29<16,"3",IF(G29<31,"4","5")))) -> 4
A30: Baylen.xlsx | B30: Artifact Mutation | C30: =IF(COUNTIF(Substitutas!$B:$B, B30) > 0, "✅ Tenho", "❌ Faltando") -> ❌ Faltando | D30: =_xlfn.XLOOKUP(B30, Substitutas!$B:$B, Substitutas!$A:$A, "-") -> - | F30: Baylen | G30: =COUNTIF(A:A,F30&".xlsx") -> 15 | H30: Sim | I30: Não | J30: Sim | K30: Não | L30: Sim | M30: Voltron | N30: Combate | O30: Muitos Tokens | P30: =IF(G30<6,"1",IF(G30<11,"2",IF(G30<16,"3",IF(G30<31,"4","5")))) -> 3
A31: Spara.xlsx | B31: Arwen, Weaver of Hope | C31: =IF(COUNTIF(Substitutas!$B:$B, B31) > 0, "✅ Tenho", "❌ Faltando") -> ❌ Faltando | D31: =_xlfn.XLOOKUP(B31, Substitutas!$B:$B, Substitutas!$A:$A, "-") -> - | F31: Toph | G31: =COUNTIF(A:A,F31&".xlsx") -> 10 | H31: Sim | I31: Não | J31: Sim | K31: Não | L31: Sim | M31: Combate | N31: - | O31: Marcador e Modular | P31: =IF(G31<6,"1",IF(G31<11,"2",IF(G31<16,"3",IF(G31<31,"4","5")))) -> 2
A32: Hivelord.xlsx | B32: Asceticism | C32: =IF(COUNTIF(Substitutas!$B:$B, B32) > 0, "✅ Tenho", "❌ Faltando") -> ❌ Faltando | D32: =_xlfn.XLOOKUP(B32, Substitutas!$B:$B, Substitutas!$A:$A, "-") -> - | G32: =COUNTIF(A:A,F32&".xlsx") -> 0 | H32: Sim | I32: Não | J32: Não | K32: Sim | L32: Sim | P32: =IF(G32<6,"1",IF(G32<11,"2",IF(G32<16,"3",IF(G32<31,"4","5")))) -> 1
A33: Baylen.xlsx | B33: Aura Mutation | C33: =IF(COUNTIF(Substitutas!$B:$B, B33) > 0, "✅ Tenho", "❌ Faltando") -> ❌ Faltando | D33: =_xlfn.XLOOKUP(B33, Substitutas!$B:$B, Substitutas!$A:$A, "-") -> - | F33: OWA | G33: =COUNTIF(A:A,F33&".xlsx") -> 5 | H33: Sim | I33: Não | J33: Não | K33: Sim | L33: Sim | M33: Combate | N33: Dano Direto | O33: Tokens e Reanimate | P33: =IF(G33<6,"1",IF(G33<11,"2",IF(G33<16,"3",IF(G33<31,"4","5")))) -> 1
A34: Carlos.xlsx | B34: Authority of the Consuls | C34: =IF(COUNTIF(Substitutas!$B:$B, B34) > 0, "✅ Tenho", "❌ Faltando") -> ❌ Faltando | D34: =_xlfn.XLOOKUP(B34, Substitutas!$B:$B, Substitutas!$A:$A, "-") -> - | F34: Piratas | G34: =COUNTIF(A:A,F34&".xlsx") -> 2 | H34: Não | I34: Sim | J34: Sim | K34: Sim | L34: Não | M34: Combate | N34: Combo | O34: Tesouros e Roubos | P34: =IF(G34<6,"1",IF(G34<11,"2",IF(G34<16,"3",IF(G34<31,"4","5")))) -> 1
A35: Yorion.xlsx | B35: Avatar's Wrath | C35: =IF(COUNTIF(Substitutas!$B:$B, B35) > 0, "✅ Tenho", "❌ Faltando") -> ❌ Faltando | D35: =_xlfn.XLOOKUP(B35, Substitutas!$B:$B, Substitutas!$A:$A, "-") -> - | F35: Rani | G35: =COUNTIF(A:A,F35&".xlsx") -> 4 | H35: Não | I35: Sim | J35: Sim | K35: Sim | L35: Não | M35: Combate | N35: Voltron | O35: Atiçar e Investigar | P35: =IF(G35<6,"1",IF(G35<11,"2",IF(G35<16,"3",IF(G35<31,"4","5")))) -> 1
A36: Zuko.xlsx | B36: Avatar's Wrath | C36: =IF(COUNTIF(Substitutas!$B:$B, B36) > 0, "✅ Tenho", "❌ Faltando") -> ❌ Faltando | D36: =_xlfn.XLOOKUP(B36, Substitutas!$B:$B, Substitutas!$A:$A, "-") -> - | F36: Inalla | G36: =COUNTIF(A:A,F36&".xlsx") -> 13 | H36: Não | I36: Sim | J36: Sim | K36: Sim | L36: Não | M36: Combo | N36: Dano Direto | O36: Magos e Combos | P36: =IF(G36<6,"1",IF(G36<11,"2",IF(G36<16,"3",IF(G36<31,"4","5")))) -> 3
A37: Zuko.xlsx | B37: Axgard Armory | C37: =IF(COUNTIF(Substitutas!$B:$B, B37) > 0, "✅ Tenho", "❌ Faltando") -> ❌ Faltando | D37: =_xlfn.XLOOKUP(B37, Substitutas!$B:$B, Substitutas!$A:$A, "-") -> - | G37: =COUNTIF(A:A,F37&".xlsx") -> 0 | H37: Não | I37: Sim | J37: Sim | K37: Não | L37: Sim | P37: =IF(G37<6,"1",IF(G37<11,"2",IF(G37<16,"3",IF(G37<31,"4","5")))) -> 1
A38: Hivelord.xlsx | B38: Azorius Signet | C38: =IF(COUNTIF(Substitutas!$B:$B, B38) > 0, "✅ Tenho", "❌ Faltando") -> ❌ Faltando | D38: =_xlfn.XLOOKUP(B38, Substitutas!$B:$B, Substitutas!$A:$A, "-") -> - | F38: Kadena | G38: =COUNTIF(A:A,F38&".xlsx") -> 8 | H38: Não | I38: Sim | J38: Não | K38: Sim | L38: Sim | M38: Combate | N38: - | O38: Morph Control | P38: =IF(G38<6,"1",IF(G38<11,"2",IF(G38<16,"3",IF(G38<31,"4","5")))) -> 2
A39: Rani.xlsx | B39: Baeloth Barrityl, Entertainer | C39: =IF(COUNTIF(Substitutas!$B:$B, B39) > 0, "✅ Tenho", "❌ Faltando") -> ❌ Faltando | D39: =_xlfn.XLOOKUP(B39, Substitutas!$B:$B, Substitutas!$A:$A, "-") -> - | F39: Zimone | G39: =COUNTIF(A:A,F39&".xlsx") -> 7 | H39: Não | I39: Sim | J39: Não | K39: Sim | L39: Sim | M39: Combate | N39: Dano Direto | O39: Terrenos e Valor | P39: =IF(G39<6,"1",IF(G39<11,"2",IF(G39<16,"3",IF(G39<31,"4","5")))) -> 2
A40: Pé.xlsx | B40: Bala Ged Recovery | C40: =IF(COUNTIF(Substitutas!$B:$B, B40) > 0, "✅ Tenho", "❌ Faltando") -> ❌ Faltando | D40: =_xlfn.XLOOKUP(B40, Substitutas!$B:$B, Substitutas!$A:$A, "-") -> - | F40: Elfos | G40: =COUNTIF(A:A,F40&".xlsx") -> 8 | H40: Não | I40: Sim | J40: Não | K40: Sim | L40: Sim | M40: Combo | N40: Combate | O40: Muita Mana | P40: =IF(G40<6,"1",IF(G40<11,"2",IF(G40<16,"3",IF(G40<31,"4","5")))) -> 2
A41: Zuko.xlsx | B41: Ballroom | C41: =IF(COUNTIF(Substitutas!$B:$B, B41) > 0, "✅ Tenho", "❌ Faltando") -> ❌ Faltando | D41: =_xlfn.XLOOKUP(B41, Substitutas!$B:$B, Substitutas!$A:$A, "-") -> - | F41: Kresh | G41: =COUNTIF(A:A,F41&".xlsx") -> 7 | H41: Não | I41: Não | J41: Sim | K41: Sim | L41: Sim | M41: Voltron | N41: Dano Direto | O41: Controle Voltron | P41: =IF(G41<6,"1",IF(G41<11,"2",IF(G41<16,"3",IF(G41<31,"4","5")))) -> 2
A42: Spara.xlsx | B42: Bant Charm | C42: =IF(COUNTIF(Substitutas!$B:$B, B42) > 0, "✅ Tenho", "❌ Faltando") -> ✅ Tenho | D42: =_xlfn.XLOOKUP(B42, Substitutas!$B:$B, Substitutas!$A:$A, "-") -> Sisay.xlsx | F42: Ool | G42: =COUNTIF(A:A,F42&".xlsx") -> 4 | H42: Não | I42: Não | J42: Sim | K42: Sim | L42: Sim | M42: Ping | N42: Combate | O42: -1/-1 Control | P42: =IF(G42<6,"1",IF(G42<11,"2",IF(G42<16,"3",IF(G42<31,"4","5")))) -> 1
A43: Pests.xlsx | B43: Basilica Screecher | C43: =IF(COUNTIF(Substitutas!$B:$B, B43) > 0, "✅ Tenho", "❌ Faltando") -> ❌ Faltando | D43: =_xlfn.XLOOKUP(B43, Substitutas!$B:$B, Substitutas!$A:$A, "-") -> - | F43: VialIshai | G43: =COUNTIF(A:A,F43&".xlsx") -> 9 | H43: Sim | I43: Sim | J43: Sim | K43: Sim | L43: Não | M43: Ping | N43: Voltron | O43: Controlar e Punir | P43: =IF(G43<6,"1",IF(G43<11,"2",IF(G43<16,"3",IF(G43<31,"4","5")))) -> 2
A44: Arabella.xlsx | B44: Battle Screech | C44: =IF(COUNTIF(Substitutas!$B:$B, B44) > 0, "✅ Tenho", "❌ Faltando") -> ❌ Faltando | D44: =_xlfn.XLOOKUP(B44, Substitutas!$B:$B, Substitutas!$A:$A, "-") -> - | F44: Breya | G44: =COUNTIF(A:A,F44&".xlsx") -> 2 | H44: Sim | I44: Sim | J44: Sim | K44: Sim | L44: Não | M44: Combate | N44: Dano Direto | O44: Thopteros e Blink | P44: =IF(G44<6,"1",IF(G44<11,"2",IF(G44<16,"3",IF(G44<31,"4","5")))) -> 1
A45: 4cRash.xlsx | B45: Beast Within | C45: =IF(COUNTIF(Substitutas!$B:$B, B45) > 0, "✅ Tenho", "❌ Faltando") -> ❌ Faltando | D45: =_xlfn.XLOOKUP(B45, Substitutas!$B:$B, Substitutas!$A:$A, "-") -> - | F45: Thrakiri | G45: =COUNTIF(A:A,F45&".xlsx") -> 1 | H45: Sim | I45: Sim | J45: Sim | K45: Não | L45: Sim | M45: Combo | N45: Voltron | O45: Engrenagens para Combar | P45: =IF(G45<6,"1",IF(G45<11,"2",IF(G45<16,"3",IF(G45<31,"4","5")))) -> 1
A46: Kresh.xlsx | B46: Beast Within | C46: =IF(COUNTIF(Substitutas!$B:$B, B46) > 0, "✅ Tenho", "❌ Faltando") -> ❌ Faltando | D46: =_xlfn.XLOOKUP(B46, Substitutas!$B:$B, Substitutas!$A:$A, "-") -> - | G46: =COUNTIF(A:A,F46&".xlsx") -> 0 | H46: Sim | I46: Sim | J46: Não | K46: Sim | L46: Sim | P46: =IF(G46<6,"1",IF(G46<11,"2",IF(G46<16,"3",IF(G46<31,"4","5")))) -> 1
A47: Pé.xlsx | B47: Beast Within | C47: =IF(COUNTIF(Substitutas!$B:$B, B47) > 0, "✅ Tenho", "❌ Faltando") -> ❌ Faltando | D47: =_xlfn.XLOOKUP(B47, Substitutas!$B:$B, Substitutas!$A:$A, "-") -> - | F47: 4cRash | G47: =COUNTIF(A:A,F47&".xlsx") -> 10 | H47: Não | I47: Sim | J47: Sim | K47: Sim | L47: Sim | M47: Ping | N47: Spellslinger | O47: Instant Ramp Control | P47: =IF(G47<6,"1",IF(G47<11,"2",IF(G47<16,"3",IF(G47<31,"4","5")))) -> 2
A48: Spara.xlsx | B48: Benevolent Hydra | C48: =IF(COUNTIF(Substitutas!$B:$B, B48) > 0, "✅ Tenho", "❌ Faltando") -> ❌ Faltando | D48: =_xlfn.XLOOKUP(B48, Substitutas!$B:$B, Substitutas!$A:$A, "-") -> - | F48: Sisay | G48: =COUNTIF(A:A,F48&".xlsx") -> 9 | H48: Sim | I48: Sim | J48: Sim | K48: Sim | L48: Sim | M48: Combate | N48: Dano Direto | O48: Super-Amigos | P48: =IF(G48<6,"1",IF(G48<11,"2",IF(G48<16,"3",IF(G48<31,"4","5")))) -> 2
A49: Baylen.xlsx | B49: Big Apple, 3 a.m. | C49: =IF(COUNTIF(Substitutas!$B:$B, B49) > 0, "✅ Tenho", "❌ Faltando") -> ❌ Faltando | D49: =_xlfn.XLOOKUP(B49, Substitutas!$B:$B, Substitutas!$A:$A, "-") -> - | F49: Fractius | G49: =COUNTIF(A:A,F49&".xlsx") -> 14 | H49: Sim | I49: Sim | J49: Sim | K49: Sim | L49: Sim | M49: Combate | N49: Voltron | O49: Tribal de Fractius | P49: =IF(G49<6,"1",IF(G49<11,"2",IF(G49<16,"3",IF(G49<31,"4","5")))) -> 3
A50: Arabella.xlsx | B50: Big Score | C50: =IF(COUNTIF(Substitutas!$B:$B, B50) > 0, "✅ Tenho", "❌ Faltando") -> ❌ Faltando | D50: =_xlfn.XLOOKUP(B50, Substitutas!$B:$B, Substitutas!$A:$A, "-") -> - | F50: Hivelord | G50: =COUNTIF(A:A,F50&".xlsx") -> 27 | H50: Sim | I50: Sim | J50: Sim | K50: Sim | L50: Sim | M50: Voltron | N50: Ping | O50: Pilha de Mutates | P50: =IF(G50<6,"1",IF(G50<11,"2",IF(G50<16,"3",IF(G50<31,"4","5")))) -> 4
A51: Zuko.xlsx | B51: Billiard Room | C51: =IF(COUNTIF(Substitutas!$B:$B, B51) > 0, "✅ Tenho", "❌ Faltando") -> ❌ Faltando | D51: =_xlfn.XLOOKUP(B51, Substitutas!$B:$B, Substitutas!$A:$A, "-") -> -
A52: Zimone.xlsx | B52: Bitterbloom Bearer | C52: =IF(COUNTIF(Substitutas!$B:$B, B52) > 0, "✅ Tenho", "❌ Faltando") -> ❌ Faltando | D52: =_xlfn.XLOOKUP(B52, Substitutas!$B:$B, Substitutas!$A:$A, "-") -> -
A53: Littles.xlsx | B53: Bitterblossom | C53: =IF(COUNTIF(Substitutas!$B:$B, B53) > 0, "✅ Tenho", "❌ Faltando") -> ❌ Faltando | D53: =_xlfn.XLOOKUP(B53, Substitutas!$B:$B, Substitutas!$A:$A, "-") -> -
A54: Pé.xlsx | B54: Black Market | C54: =IF(COUNTIF(Substitutas!$B:$B, B54) > 0, "✅ Tenho", "❌ Faltando") -> ❌ Faltando | D54: =_xlfn.XLOOKUP(B54, Substitutas!$B:$B, Substitutas!$A:$A, "-") -> -
A55: Carlos.xlsx | B55: Black Market Connections | C55: =IF(COUNTIF(Substitutas!$B:$B, B55) > 0, "✅ Tenho", "❌ Faltando") -> ❌ Faltando | D55: =_xlfn.XLOOKUP(B55, Substitutas!$B:$B, Substitutas!$A:$A, "-") -> -
A56: Arabella.xlsx | B56: Blacksmith's Skill | C56: =IF(COUNTIF(Substitutas!$B:$B, B56) > 0, "✅ Tenho", "❌ Faltando") -> ❌ Faltando | D56: =_xlfn.XLOOKUP(B56, Substitutas!$B:$B, Substitutas!$A:$A, "-") -> -
A57: 4cRash.xlsx | B57: Blasphemous Act | C57: =IF(COUNTIF(Substitutas!$B:$B, B57) > 0, "✅ Tenho", "❌ Faltando") -> ❌ Faltando | D57: =_xlfn.XLOOKUP(B57, Substitutas!$B:$B, Substitutas!$A:$A, "-") -> -
A58: Kresh.xlsx | B58: Blasphemous Act | C58: =IF(COUNTIF(Substitutas!$B:$B, B58) > 0, "✅ Tenho", "❌ Faltando") -> ❌ Faltando | D58: =_xlfn.XLOOKUP(B58, Substitutas!$B:$B, Substitutas!$A:$A, "-") -> -
A59: Pests.xlsx | B59: Blex, Vexing Pest | C59: =IF(COUNTIF(Substitutas!$B:$B, B59) > 0, "✅ Tenho", "❌ Faltando") -> ❌ Faltando | D59: =_xlfn.XLOOKUP(B59, Substitutas!$B:$B, Substitutas!$A:$A, "-") -> -
A60: Elfos.xlsx | B60: Bloom Tender | C60: =IF(COUNTIF(Substitutas!$B:$B, B60) > 0, "✅ Tenho", "❌ Faltando") -> ❌ Faltando | D60: =_xlfn.XLOOKUP(B60, Substitutas!$B:$B, Substitutas!$A:$A, "-") -> -
A61: Toph.xlsx | B61: Blossoming Tortoise | C61: =IF(COUNTIF(Substitutas!$B:$B, B61) > 0, "✅ Tenho", "❌ Faltando") -> ❌ Faltando | D61: =_xlfn.XLOOKUP(B61, Substitutas!$B:$B, Substitutas!$A:$A, "-") -> -
A62: Pé.xlsx | B62: Body Count | C62: =IF(COUNTIF(Substitutas!$B:$B, B62) > 0, "✅ Tenho", "❌ Faltando") -> ❌ Faltando | D62: =_xlfn.XLOOKUP(B62, Substitutas!$B:$B, Substitutas!$A:$A, "-") -> -
... A438: Narset.xlsx | B438: Zellix, Sanity Flayer | C438: =IF(COUNTIF(Substitutas!$B:$B, B438) > 0, "✅ Tenho", "❌ Faltando") -> ❌ Faltando | D438: =_xlfn.XLOOKUP(B438, Substitutas!$B:$B, Substitutas!$A:$A, "-") -> -

Sheet Prices
A1: Nome da Origem | B1: Carta Ideal | C1: API.prices.usd | D1: Faixa
A2: Arabella.xlsx | B2: Pathmaker Initiate | C2: 0.03 | D2: Baratera
A3: Arabella.xlsx | B3: Plains | C3: 0.11 | D3: Baratera
A4: Arabella.xlsx | B4: Decommission | C4: 0.11 | D4: Baratera
A5: Arabella.xlsx | B5: Boros Guildgate | C5: 0.12 | D5: Baratera
A6: Arabella.xlsx | B6: Goblin Smuggler | C6: 0.12 | D6: Baratera
A7: Arabella.xlsx | B7: Cursebreak | C7: 0.12 | D7: Baratera
A8: Arabella.xlsx | B8: Thraben Inspector | C8: 0.14 | D8: Baratera
A9: Arabella.xlsx | B9: Dimension X | C9: 0.17 | D9: Baratera
A10: Arabella.xlsx | B10: Clowning Around | C10: 0.17 | D10: Baratera
A11: Arabella.xlsx | B11: Mountain | C11: 0.18 | D11: Baratera
A12: Arabella.xlsx | B12: Molten Gatekeeper | C12: 0.18 | D12: Baratera
A13: Arabella.xlsx | B13: Pursue the Past | C13: 0.19 | D13: Baratera
... A355: Toph.xlsx | B355: The Great Henge | C355: 63.98 | D355: Facada
A356: 4cRash.xlsx | B356: Blasphemous Act | D356: Não Encontrada
A357: Alela.xlsx | B357: Monologue Tax | D357: Não Encontrada
A358: Arabella.xlsx | B358: Impact Tremors | D358: Não Encontrada
A359: Baylen.xlsx | B359: The Shire | D359: Não Encontrada
A360: Carlos.xlsx | B360: Black Market Connections | D360: Não Encontrada
A361: Elfos.xlsx | B361: Watery Grave | D361: Não Encontrada
A362: Fractius.xlsx | B362: Steam Vents | D362: Não Encontrada
A363: Fractius.xlsx | B363: Overgrown Tomb | D363: Não Encontrada
A364: Fractius.xlsx | B364: Fetch n WG WU | D364: Não Encontrada
A365: Fractius.xlsx | B365: Sliver Gravemother | D365: Não Encontrada
A366: Jhoira.xlsx | B366: Valfenda | D366: Não Encontrada
A367: JhoiraBichao.xlsx | B367: Rivendell | D367: Não Encontrada
... A377: Zuko.xlsx | B377: Prosper, Tome-Bound | D377: Não Encontrada

Sheet Substitutas
A1: Nome da Origem | B1: Carta Atual
A2: Jhoira.xlsx | B2: ?
A3: Yorion.xlsx | B3: Abdel Adrian, Gorion's Ward
A4: Spara.xlsx | B4: Abzan Falconeer
A5: JhoiraBichao.xlsx | B5: Aeon Chronicler
A6: Inalla.xlsx | B6: Aether Adept
A7: Narset.xlsx | B7: Antecipar
A8: Kadena.xlsx | B8: Aphetto Exterminator
A9: Zuko.xlsx | B9: Aranã, Heart of the Spider
A10: Toph.xlsx | B10: Arcbound Slith
A11: Toph.xlsx | B11: Ark of Hunger
A12: Alela.xlsx | B12: Artificer of Curiosity
... A309: 4cRash.xlsx | B309: Zhur-Taa Druid

Sheet Decks
A1: Nome da Origem | B1: Carta Atual
A2: Carlos.xlsx | B2: Abigale, Eloquent First-Year
A3: Yuriko.xlsx | B3: Abjure
A4: Necrobloom.xlsx | B4: Abrupt Decay
A5: Ool.xlsx | B5: Abrupt Decay
A6: Zimone.xlsx | B6: Abrupt Decay
A7: Breya.xlsx | B7: Abstruse Appropriation
A8: Jhoira.xlsx | B8: Academy Loremaster
A9: JhoiraBichao.xlsx | B9: Academy Loremaster
A10: Baylen.xlsx | B10: Academy Manufactor
A11: OwA.xlsx | B11: Academy Manufactor
A12: Piratas.xlsx | B12: Academy Manufactor
... A2801: Littles.xlsx | B2801: Zurgo, Thunder's Decree

Sheet Watch
A1: Carta | B1: Identidade | G1: Tipo | H1: Categoria | I1: Classe
A2: Weathered Runestone | B2: Não | C2: Não | D2: Não | E2: Não | F2: Não | G2: Artefato | H2: Stax | I2: Cemitério
A3: Shivan Harvest | B3: Não | C3: Não | D3: Sim | E3: Não | F3: Não | G3: Encantamento | H3: Remoção | I3: Terreno
A4: Scouting Trek | B4: Não | C4: Não | D4: Não | E4: Não | F4: Sim | G4: Feitiço | H4: Combo | I4: Tutor
A5: Overabundance | B5: Não | C5: Não | D5: Sim | E5: Não | F5: Não | G5: Encantamento | H5: Ramp | I5: Punição
A6: Spreading Plague | B6: Não | C6: Não | D6: Não | E6: Sim | F6: Não | G6: Encantamento | H6: Stax | I6: Criaturas
A7: Explosão da Alma | B7: Não | C7: Não | D7: Sim | E7: Não | F7: Não | G7: Instantânea | H7: Wincon | I7: Dano
A8: Interdict | B8: Não | C8: Sim | D8: Não | E8: Não | F8: Não | G8: Instantânea | H8: Anule | I8: Habilidade
A9: Mogg Infestation | B9: Não | C9: Não | D9: Sim | E9: Não | F9: Não | G9: Feitiço | H9: Remoção | I9: Criaturas
A10: Life // Death | B10: Não | C10: Não | D10: Não | E10: Não | F10: Sim | G10: Feitiço | H10: Combo | I10: Terreno
A11: Debt of Loyalt | B11: Sim | C11: Não | D11: Não | E11: Não | F11: Não | G11: Instantânea | H11: Remoção | I11: Roubo
A12: Yavimaya Hollow | B12: Não | C12: Não | D12: Não | E12: Não | F12: Sim | G12: Terreno | H12: Proteção | I12: Criaturas
A13: Dreams of the Dead | B13: Não | C13: Sim | D13: Não | E13: Não | F13: Não | G13: Encantamento | H13: Combo | I13: Cemitério
... A25: The Infamous Cruelclaw | B25: Não | C25: Não | D25: Sim | E25: Sim | F25: Não | G25: Criatura | H25: Commander | I25: Voltron

Sheet Tokens
A1: Nome | B1: Tipo | C1: Cor | D1: Cor 2 | E1: Poder | F1: Resistência | G1: Keyword | H1: Keyword | I1: Texto | J1: Possuídos | K1: Necessários | L1: 4c Rash | M1: Akiri | N1: Alela | O1: Arcades | P1: Baylen | Q1: Breya | R1: Carlos | S1: Elfos | T1: Fractius | U1: Gitrog | V1: Inalla | W1: Jhoira | X1: JhoiraB | Y1: Kresh | Z1: Kumena | AA1: Little | AB1: Modular | AC1: Muzzio | AD1: Narset | AE1: Ool | AF1: Oona | AG1: OWA | AH1: Piratas | AI1: Rani | AJ1: Rielle | AK1: Sisay | AL1: Tayam | AM1: Thrakiri | AN1: VialIshai | AO1: Yorion | AP1: Yuriko | AQ1: Zedruu | AR1: Zimone | AS1: Zuko
A2: Alien Warrior | B2: Creature | C2: Red | D2: - | E2: 2 | F2: 2 | G2: - | H2: - | I2: - | K2: =COUNTIF(L2:BD2,">0") -> 0
A3: Ally | B3: Creature | C3: Colorless | D3: - | E3: 1 | F3: 1 | G3: - | H3: - | I3: - | K3: =COUNTIF(L3:BD3,">0") -> 0
A4: Angel | B4: Creature | C4: White | D4: - | E4: 4 | F4: 4 | G4: Fly | H4: - | I4: - | K4: =COUNTIF(L4:BD4,">0") -> 0
A5: Ape | B5: Creature | C5: Green | D5: - | E5: 3 | F5: 3 | G5: - | H5: - | I5: - | K5: =COUNTIF(L5:BD5,">0") -> 0
A6: Assassin | B6: Creature | C6: Black | D6: - | E6: 1 | F6: 1 | G6: - | H6: - | I6: HK | K6: =COUNTIF(L6:BD6,">0") -> 0
A7: Bat | B7: Creature | C7: Black | D7: - | E7: 1 | F7: 1 | G7: Fly | H7: - | I7: - | K7: =COUNTIF(L7:BD7,">0") -> 0
A8: Bear | B8: Creature | C8: Green | D8: - | E8: 2 | F8: 2 | G8: - | H8: - | I8: - | K8: =COUNTIF(L8:BD8,">0") -> 0
A9: Bear | B9: Creature | C9: Green | D9: - | E9: 4 | F9: 4 | G9: - | H9: - | I9: - | K9: =COUNTIF(L9:BD9,">0") -> 0
A10: Beast | B10: Creature | C10: Green | D10: - | E10: 3 | F10: 3 | G10: - | H10: - | I10: - | K10: =COUNTIF(L10:BD10,">0") -> 0
A11: Bird | B11: Creature | C11: Blue | D11: - | E11: 2 | F11: 2 | G11: Fly | H11: - | I11: - | K11: =COUNTIF(L11:BD11,">0") -> 0
A12: Bird | B12: Creature | C12: White | D12: - | E12: 1 | F12: 1 | G12: Fly | H12: - | I12: - | K12: =COUNTIF(L12:BD12,">0") -> 0
A13: Cat | B13: Creature | C13: Green | D13: - | E13: 2 | F13: 2 | G13: - | H13: - | I13: - | K13: =COUNTIF(L13:BD13,">0") -> 0
A14: Chandra, Awakened Inferno | B14: Emblem | C14: - | D14: - | E14: - | F14: - | G14: - | H14: - | I14: - | K14: =COUNTIF(L14:BD14,">0") -> 0
A15: Citizen | B15: Creature | C15: Green | D15: White | E15: 1 | F15: 1 | G15: - | H15: - | I15: - | K15: =COUNTIF(L15:BD15,">0") -> 0
A16: Clone | B16: Creature | C16: Colorless | D16: - | E16: X | F16: X | G16: - | H16: - | I16: - | K16: =COUNTIF(L16:BD16,">0") -> 1 | AO16: 2
A17: Clue | B17: Artifact | C17: Colorless | D17: - | E17: - | F17: - | G17: - | H17: - | I17: - | K17: =COUNTIF(L17:BD17,">0") -> 0
A18: Construct | B18: Creature | C18: Colorless | D18: - | E18: 0 | F18: 0 | G18: - | H18: - | I18: +1/+1 por Artefato | K18: =COUNTIF(L18:BD18,">0") -> 0
A19: Construct | B19: Creature | C19: Colorless | D19: - | E19: 1 | F19: 1 | G19: - | H19: - | I19: - | K19: =COUNTIF(L19:BD19,">0") -> 0
A20: Construct | B20: Creature | C20: Colorless | D20: - | E20: 1 | F20: 1 | G20: Defender | H20: - | I20: - | K20: =COUNTIF(L20:BD20,">0") -> 0
A21: Construct | B21: Creature | C21: Colorless | D21: - | E21: 4 | F21: 4 | G21: - | H21: - | I21: - | K21: =COUNTIF(L21:BD21,">0") -> 0
A22: Construct | B22: Creature | C22: Colorless | D22: - | E22: 2 | F22: 2 | G22: - | H22: - | I22: - | K22: =COUNTIF(L22:BD22,">0") -> 0
A23: Coruscation Mage | B23: Creature | C23: Red | D23: - | E23: 1 | F23: 1 | G23: - | H23: - | I23: - | K23: =COUNTIF(L23:BD23,">0") -> 1 | L23: 1
A24: Crab | B24: Creature | C24: Blue | D24: - | E24: 0 | F24: 3 | G24: - | H24: - | I24: - | K24: =COUNTIF(L24:BD24,">0") -> 0
A25: Darkstar Augur | B25: Creature | C25: Black | D25: - | E25: 1 | F25: 1 | G25: Fly | H25: - | I25: - | K25: =COUNTIF(L25:BD25,">0") -> 0
A26: Demon | B26: Creature | C26: Black | D26: - | E26: 3 | F26: 3 | G26: - | H26: - | I26: - | K26: =COUNTIF(L26:BD26,">0") -> 0
A27: Demon Vampire | B27: Creature | C27: White | D27: Black | E27: 4 | F27: 3 | G27: Fly | H27: - | I27: - | K27: =COUNTIF(L27:BD27,">0") -> 0
A28: Dragon | B28: Creature | C28: Red | D28: - | E28: 4 | F28: 4 | G28: Fly | H28: - | I28: - | K28: =COUNTIF(L28:BD28,">0") -> 0
A29: Dragon | B29: Creature | C29: Red | D29: - | E29: 4 | F29: 4 | G29: Fly | H29: Firebending 4 | I29: - | K29: =COUNTIF(L29:BD29,">0") -> 0
A30: Dragon Scorpion | B30: Creature | C30: Red | D30: - | E30: 4 | F30: 4 | G30: Fly | H30: Haste | I30: - | K30: =COUNTIF(L30:BD30,">0") -> 0
A31: Drake | B31: Creature | C31: Blue | D31: - | E31: 2 | F31: 2 | G31: Fly | H31: - | I31: - | K31: =COUNTIF(L31:BD31,">0") -> 0
A32: Dungeon of the Mad Mage | B32: Emblem | C32: - | D32: - | E32: - | F32: - | G32: - | H32: - | I32: - | K32: =COUNTIF(L32:BD32,">0") -> 0
A33: Dwarf | B33: Creature | C33: Red | D33: - | E33: 1 | F33: 1 | G33: - | H33: - | I33: - | K33: =COUNTIF(L33:BD33,">0") -> 0
A34: Eldrazi Spawn | B34: Creature | C34: Colorless | D34: - | E34: 0 | F34: 1 | G34: - | H34: - | I34: sac: I | K34: =COUNTIF(L34:BD34,">0") -> 0
A35: Elemental | B35: Creature | C35: White | D35: Green | E35: 8 | F35: 8 | G35: Vigilance | H35: - | I35: - | K35: =COUNTIF(L35:BD35,">0") -> 0
A36: Elemental | B36: Creature | C36: Red | D36: - | E36: 1 | F36: 1 | G36: - | H36: - | I36: Dano LTB | K36: =COUNTIF(L36:BD36,">0") -> 0
A37: Elemental | B37: Creature | C37: Red | D37: - | E37: 2 | F37: 1 | G37: Haste | H37: Trample | I37: - | K37: =COUNTIF(L37:BD37,">0") -> 0
A38: Elephant | B38: Creature | C38: Green | D38: - | E38: 3 | F38: 3 | G38: - | H38: - | I38: - | K38: =COUNTIF(L38:BD38,">0") -> 0
A39: Elf | B39: Creature | C39: Green | D39: - | E39: 1 | F39: 1 | G39: - | H39: - | K39: =COUNTIF(L39:BD39,">0") -> 0
A40: Elf Druid | B40: Creature | C40: Green | D40: - | E40: 1 | F40: 1 | G40: - | H40: - | I40: t: G | K40: =COUNTIF(L40:BD40,">0") -> 0
A41: Elf Warrior | B41: Creature | C41: Green | D41: - | E41: 1 | F41: 1 | G41: - | H41: - | I41: - | K41: =COUNTIF(L41:BD41,">0") -> 0
A42: Energy | B42: Emblem | C42: - | D42: - | E42: - | F42: - | G42: - | H42: - | I42: - | K42: =COUNTIF(L42:BD42,">0") -> 0
A43: Faerie | B43: Creature | C43: Blue | D43: Black | E43: 1 | F43: 1 | G43: Fly | H43: - | I43: - | K43: =COUNTIF(L43:BD43,">0") -> 0
A44: Faerie | B44: Creature | C44: Blue | D44: - | E44: 1 | F44: 1 | G44: Fly | H44: - | I44: - | K44: =COUNTIF(L44:BD44,">0") -> 0
A45: Faerie Dragon | B45: Creature | C45: Blue | D45: - | E45: 1 | F45: 1 | G45: Fly | H45: - | I45: - | K45: =COUNTIF(L45:BD45,">0") -> 0
A46: Faerie Rogue | B46: Creature | C46: Black | D46: - | E46: 1 | F46: 1 | G46: Fly | H46: - | I46: - | K46: =COUNTIF(L46:BD46,">0") -> 0
A47: Food | B47: Artifact | C47: Colorless | D47: - | E47: - | F47: - | G47: - | H47: - | I47: - | K47: =COUNTIF(L47:BD47,">0") -> 0
A48: Fractal | B48: Creature | C48: Blue | D48: Green | E48: 0 | F48: 0 | G48: - | H48: - | I48: - | K48: =COUNTIF(L48:BD48,">0") -> 0
A49: Frog | B49: Creature | C49: Green | D49: - | E49: 1 | F49: 1 | G49: - | H49: - | I49: - | K49: =COUNTIF(L49:BD49,">0") -> 0
A50: Gnome | B50: Creature | C50: Colorless | D50: - | E50: 1 | F50: 1 | G50: - | H50: - | I50: - | K50: =COUNTIF(L50:BD50,">0") -> 0
A51: Gnome Soldier | B51: Creature | C51: White | D51: - | E51: X | F51: X | G51: - | H51: - | I51: X = Artefatos | K51: =COUNTIF(L51:BD51,">0") -> 0
A52: Goat | B52: Creature | C52: White | D52: - | E52: 0 | F52: 1 | G52: - | H52: - | I52: - | K52: =COUNTIF(L52:BD52,">0") -> 0
A53: Goblin | B53: Creature | C53: Red | D53: - | E53: 1 | F53: 1 | G53: - | H53: - | I53: - | K53: =COUNTIF(L53:BD53,">0") -> 0
A54: Goblin | B54: Creature | C54: Red | D54: - | E54: 1 | F54: 1 | G54: - | H54: - | I54: Criaturas Atacam | K54: =COUNTIF(L54:BD54,">0") -> 0
A55: Gold | B55: Artifact | C55: Colorless | D55: - | E55: - | F55: - | G55: - | H55: - | I55: - | K55: =COUNTIF(L55:BD55,">0") -> 0
A56: Halfling | B56: Creature | C56: White | D56: - | E56: 1 | F56: 1 | G56: - | H56: - | I56: - | K56: =COUNTIF(L56:BD56,">0") -> 0
A57: Hero | B57: Creature | C57: Colorless | D57: - | E57: 1 | F57: 1 | G57: - | H57: - | I57: - | K57: =COUNTIF(L57:BD57,">0") -> 0
A58: Homunculos Horde | B58: Creature | C58: Blue | D58: - | E58: - | F58: - | G58: - | H58: - | I58: - | K58: =COUNTIF(L58:BD58,">0") -> 0
A59: Horror | B59: Creature | C59: Black | D59: - | E59: 1 | F59: 1 | G59: - | H59: - | I59: - | K59: =COUNTIF(L59:BD59,">0") -> 0
A60: Human | B60: Creature | C60: White | D60: - | E60: 1 | F60: 1 | G60: - | H60: - | I60: - | K60: =COUNTIF(L60:BD60,">0") -> 0
A61: Human Cleric | B61: Creature | C61: White | D61: Black | E61: 1 | F61: 1 | G61: - | H61: - | I61: - | K61: =COUNTIF(L61:BD61,">0") -> 0
A62: Human Soldier | B62: Creature | C62: White | D62: - | E62: 1 | F62: 1 | G62: - | H62: - | I62: - | K62: =COUNTIF(L62:BD62,">0") -> 0
A63: Illusion | B63: Creature | C63: Blue | D63: - | E63: 1 | F63: 1 | G63: - | H63: - | I63: +1/+1 por Ilusão | K63: =COUNTIF(L63:BD63,">0") -> 0
A64: Insect | B64: Creature | C64: Green | D64: - | E64: 1 | F64: 1 | G64: - | H64: - | I64: - | K64: =COUNTIF(L64:BD64,">0") -> 0
A65: Insect | B65: Creature | C65: Green | D65: Black | E65: 1 | F65: 1 | G65: - | H65: - | I65: - | K65: =COUNTIF(L65:BD65,">0") -> 0
A66: Insect | B66: Creature | C66: Black | D66: - | E66: 1 | F66: 1 | G66: - | H66: - | I66: - | K66: =COUNTIF(L66:BD66,">0") -> 0
A67: Junk | B67: Artifact | C67: Colorless | D67: - | E67: - | F67: - | G67: - | H67: - | I67: - | K67: =COUNTIF(L67:BD67,">0") -> 0
A68: Kithkin | B68: Creature | C68: White | D68: Green | E68: 1 | F68: 1 | G68: - | H68: - | I68: - | K68: =COUNTIF(L68:BD68,">0") -> 0
A69: Knight | B69: Creature | C69: White | D69: - | E69: 2 | F69: 2 | G69: Vigilance | H69: - | I69: - | K69: =COUNTIF(L69:BD69,">0") -> 0
A70: Kobold | B70: Creature | C70: Red | D70: - | E70: 0 | F70: 1 | G70: - | H70: - | I70: - | K70: =COUNTIF(L70:BD70,">0") -> 0
A71: Kor Ally | B71: Creature | C71: White | D71: - | E71: 1 | F71: 1 | G71: - | H71: - | I71: - | K71: =COUNTIF(L71:BD71,">0") -> 0
A72: Kraken | B72: Creature | C72: Blue | D72: - | E72: 1 | F72: 1 | G72: Trample | H72: - | I72: - | K72: =COUNTIF(L72:BD72,">0") -> 0
A73: Kraken | B73: Creature | C73: Blue | D73: - | E73: 8 | F73: 8 | G73: - | H73: - | I73: - | K73: =COUNTIF(L73:BD73,">0") -> 0
A74: Lander | B74: Artifact | C74: Colorless | D74: - | E74: - | F74: - | G74: - | H74: - | I74: - | K74: =COUNTIF(L74:BD74,">0") -> 0
A75: Lizard Frog | B75: Creature | C75: Green | D75: - | E75: 3 | F75: 3 | G75: - | H75: - | I75: - | K75: =COUNTIF(L75:BD75,">0") -> 0
A76: Lost Mine of Phandelver | B76: Emblem | C76: - | D76: - | E76: - | F76: - | G76: - | H76: - | I76: - | K76: =COUNTIF(L76:BD76,">0") -> 0
A77: Map | B77: Artifact | C77: Colorless | D77: - | E77: - | F77: - | G77: - | H77: - | I77: - | K77: =COUNTIF(L77:BD77,">0") -> 0
A78: Mark of the Rani | B78: Enchantment | C78: Red | D78: - | E78: - | F78: - | G78: - | H78: - | I78: Goaded | K78: =COUNTIF(L78:BD78,">0") -> 0
A79: Merfolk | B79: Creature | C79: Blue | D79: - | E79: 1 | F79: 1 | G79: Hexproof | H79: - | I79: - | K79: =COUNTIF(L79:BD79,">0") -> 0
A80: Merfolk | B80: Creature | C80: Blue | D80: - | E80: 1 | F80: 1 | G80: - | H80: - | I80: - | K80: =COUNTIF(L80:BD80,">0") -> 0
A81: Monk | B81: Creature | C81: White | D81: - | E81: 1 | F81: 1 | G81: - | H81: - | I81: Prowess | K81: =COUNTIF(L81:BD81,">0") -> 0
A82: Munition | B82: Artifact | C82: Colorless | D82: - | E82: - | F82: - | G82: - | H82: - | I82: - | K82: =COUNTIF(L82:BD82,">0") -> 0
A83: Mutavault | B83: Land | C83: Colorless | D83: - | E83: - | F83: - | G83: - | H83: - | I83: - | K83: =COUNTIF(L83:BD83,">0") -> 0
A84: Necron Warrior | B84: Creature | C84: Black | D84: - | E84: 2 | F84: 2 | G84: - | H84: - | I84: - | K84: =COUNTIF(L84:BD84,">0") -> 0
A85: Ogre | B85: Creature | C85: Red | D85: - | E85: 3 | F85: 3 | G85: - | H85: - | I85: - | K85: =COUNTIF(L85:BD85,">0") -> 0
A86: Pest | B86: Creature | C86: Black | D86: Green | E86: 1 | F86: 1 | G86: - | H86: - | I86: Morre 1 Vida | K86: =COUNTIF(L86:BD86,">0") -> 0
A87: Phyrexian Mite | B87: Creature | C87: Colorless | D87: - | E87: 1 | F87: 1 | G87: - | H87: - | I87: - | K87: =COUNTIF(L87:BD87,">0") -> 0
A88: Phyrexian Myr | B88: Creature | C88: Blue | D88: - | E88: 2 | F88: 1 | G88: - | H88: - | I88: - | K88: =COUNTIF(L88:BD88,">0") -> 0
A89: Pilot | B89: Creature | C89: Colorless | D89: - | E89: 1 | F89: 1 | G89: - | H89: - | I89: Tripular 2 | K89: =COUNTIF(L89:BD89,">0") -> 0
A90: Pincher | B90: Creature | C90: Colorless | D90: - | E90: 2 | F90: 2 | G90: - | H90: - | I90: - | K90: =COUNTIF(L90:BD90,">0") -> 0
A91: Plant | B91: Creature | C91: Green | D91: - | E91: 0 | F91: 1 | G91: - | H91: - | I91: - | K91: =COUNTIF(L91:BD91,">0") -> 0
A92: Plant | B92: Creature | C92: Green | D92: - | E92: 1 | F92: 1 | G92: - | H92: - | I92: - | K92: =COUNTIF(L92:BD92,">0") -> 0
A93: Powerstone | B93: Artifact | C93: Colorless | D93: - | E93: - | F93: - | G93: - | H93: - | I93: - | K93: =COUNTIF(L93:BD93,">0") -> 0
A94: Rabbit | B94: Creature | C94: White | D94: - | E94: 1 | F94: 1 | G94: - | H94: - | I94: - | J94: 1 | K94: =COUNTIF(L94:BD94,">0") -> 1 | AO94: 2
A95: Rat | B95: Creature | C95: Black | D95: - | E95: 1 | F95: 1 | G95: - | H95: - | I95: - | K95: =COUNTIF(L95:BD95,">0") -> 0
A96: Rebel | B96: Creature | C96: Red | D96: - | E96: 2 | F96: 2 | G96: - | H96: - | I96: - | K96: =COUNTIF(L96:BD96,">0") -> 0
A97: Rhino Warrior | B97: Creature | C97: Green | D97: - | E97: 4 | F97: 4 | G97: - | H97: - | I97: - | K97: =COUNTIF(L97:BD97,">0") -> 0
A98: Salamander Warrior | B98: Creature | C98: Blue | D98: - | E98: 4 | F98: 3 | G98: - | H98: - | I98: - | K98: =COUNTIF(L98:BD98,">0") -> 0
A99: Saproling | B99: Creature | C99: Green | D99: - | E99: 1 | F99: 1 | G99: - | H99: - | I99: - | K99: =COUNTIF(L99:BD99,">0") -> 0
A100: Scarecrow | B100: Creature | C100: Colorless | D100: - | E100: 2 | F100: 2 | G100: - | H100: - | I100: - | K100: =COUNTIF(L100:BD100,">0") -> 0
...

Sheet Lands
A1: Edição | B1: Planície | C1: Ilha | D1: Montanha | E1: Pântano | F1: Floresta | H1: Edição | I1: Oath 1 | J1: Oath 2 | K1: Love Your LGS | L1: FF | M1: MH3 Snow | O1: Warhammer 1 | P1: Warhammer 2 | Q1: Fallout 1 | R1: Fallout 2
A2: Aetherdrift | B2: 272 | C2: 273 | D2: 275 | E2: 274 | F2: 276 | H2: Wastes | I2: s | J2: s | K2: 1 | L2: 309 | M2: 309
A3: Aetherdrift Drivers | B3: 507 | C3: 508 | D3: 510 | E3: 509 | F3: 511
A4: Aetherdrift Rotes | B4: 512 | C4: 513 | D4: 515 | E4: 514 | F4: 516
A5: Amonkhet | B5: s | C5: s | D5: s | E5: s | F5: s
A6: Assassin's Creed 1 | B6: s | C6: s | D6: s | E6: s | F6: s
A7: Assassin's Creed 2 | B7: s | C7: s | D7: s | E7: s | F7: s
A8: Avatar - Appa Lands | B8: s | C8: s | D8: s | E8: s | F8: s
A9: Avatar - Momo Lands | B9: 292 | C9: s | D9: 295 | E9: s | F9: s
A10: Battle for Zendikar 1 | B10: s | C10: s | D10: s | E10: s | F10: s
A11: Battle for Zendikar 2 | B11: s | C11: s | D11: s | E11: s | F11: s
A12: Battle for Zendikar 3 | B12: s | C12: s | D12: s | E12: s | F12: s
A13: Battle for Zendikar 4 | B13: s | C13: s | D13: s | E13: s | F13: s
A14: Battle for Zendikar 5 | B14: s | C14: s | D14: s | E14: s | F14: 274
A15: Bloomburrow Fall | B15: 264 | C15: 268 | D15: 276 | E15: 273 | F15: 280
A16: Bloomburrow Spring | B16: 263 | C16: 267 | D16: 275 | E16: 272 | F16: 279
A17: Bloomburrow Summer | B17: 262 | C17: 266 | D17: 274 | E17: 271 | F17: 278
A18: Bloomburrow Winter | B18: 265 | C18: 269 | D18: 277 | E18: 274 | F18: 281
A19: Cappena 1 | B19: 272 | C19: 274 | D19: 278 | E19: s | F19: 280
A20: Cappena 2 | B20: 273 | C20: 275 | D20: 279 | E20: 277 | F20: 281
A21: Dominaria United | B21: s | C21: 278 | D21: s | E21: s | F21: s
A22: Double Masters VIP 1 | B22: 373 | C22: 375 | D22: 379 | E22: 377 | F22: 381
A23: Double Masters VIP 2 | B23: 374 | C23: 376 | D23: 380 | E23: 378 | F23: 382
A24: Dragonstorm Eyes | B24: 287 | C24: 288 | D24: 290 | E24: 289 | F24: 291
A25: Dragonstorm Shades | B25: 272 | C25: 273 | D25: 275 | E25: 274 | F25: 276
A26: Duskmourn | B26: 272 | C26: 273 | D26: 275 | E26: 274 | F26: 276
A27: Edges of Eternities Celestial | B27: 262 | C27: 263 | D27: 265 | E27: 264 | F27: s
A28: Fallout 1 | B28: s | C28: 319 | D28: s | E28: s | F28: s
A29: Fallout 2 | B29: s | C29: 320 | D29: s | E29: s | F29: s
A30: Final Fantasy 1 | B30: s | C30: s | D30: 303 | E30: s | F30: 306
A31: Final Fantasy 2 | B31: 295 | C31: 298 | D31: s | E31: s | F31: 307
A32: Final Fantasy 3 | B32: 296 | C32: 299 | D32: 305 | E32: 302 | F32: 308
A33: Foundations 1 | B33: 282 | C33: 284 | D33: 288 | E33: 286 | F33: 290
A34: Foundations 2 | B34: 283 | C34: 285 | D34: 289 | E34: 287 | F34: 291
A35: Hora da Devastação | B35: 185 | C35: 186 | D35: 188 | E35: s | F35: 189
A36: Innistrad Crimson 1 | B36: 268 | C36: 270 | D36: s | E36: 272 | F36: 276
A37: Innistrad Crimson 2 | B37: 269 | C37: 271 | D37: 275 | E37: 273 | F37: 277
A38: Innistrad Midnight 1 | B38: s | C38: s | D38: s | E38: s | F38: s
A39: Innistrad Midnight 2 | B39: s | C39: 271 | D39: s | E39: 273 | F39: s
A40: Jurassic World Collection | B40: 21 | C40: 22 | D40: 24 | E40: 23 | F40: 25
A41: Kamigawa Neon 1 | B41: 293 | C41: 295 | D41: s | E41: 297 | F41: 231
A42: Kamigawa Neon 2 | B42: 294 | C42: 296 | D42: 300 | E42: 298 | F42: s
A43: Lorwyn Eclipsed 1 | B43: s | C43: s | D43: s | E43: s | F43: s
A44: Lorwyn Eclipsed 2 | B44: s | C44: s | D44: s | E44: s | F44: s
A45: Lost Caverns Ixalan | B45: 287 | C45: 288 | D45: 290 | E45: 289 | F45: 291
A46: LotR 1 | B46: 272 | C46: 274 | D46: 278 | E46: s | F46: 280
A47: LotR 2 | B47: 273 | C47: 275 | D47: 279 | E47: 277 | F47: 281
A48: March of the Machine 1 | B48: 282 | C48: 284 | D48: 288 | E48: 286 | F48: 290
A49: March of the Machine 2 | B49: 283 | C49: 285 | D49: 289 | E49: s | F49: 291
A50: Marvel Super Heroes 1 | B50: 277 | C50: 279 | D50: 283 | E50: 281 | F50: 285
A51: Marvel Super Heroes 2 | B51: 278 | C51: 280 | D51: 284 | E51: 282 | F51: 286
A52: MH1 Snow | B52: s | C52: s | E52: s | F52: s
A53: MH3 | B53: 304 | C53: 305 | D53: 307 | E53: s | F53: 306
A54: Murders at Karlov Manor | B54: 272 | C54: 273 | D54: 275 | E54: 274 | F54: 276
A55: Outlaws | B55: 272 | C55: 273 | D55: 275 | E55: 274 | F55: 276
A56: Phyrexia One Black | B56: 369 | C56: 366 | D56: 368 | E56: 367 | F56: 365
A57: Phyrexia One Lands | B57: s | C57: s | D57: s | E57: s | F57: s
A58: Phyrexia One Symbols | B58: 267 | C58: 268 | D58: s | E58: s | F58: s
A59: Secrets of Strixhaven | B59: s | C59: s | D59: s | E59: s | F59: s
A60: Spider Man | B60: s | C60: s | D60: s | E60: s | F60: s
A61: The Brother's Wars 1 | B61: s | C61: 280 | D61: 284 | E61: 282 | F61: 286
A62: The Brother's Wars 2 | B62: s | C62: 281 | D62: 285 | E62: s | F62: 287
A63: Theros Beyond Death | B63: s | C63: s | D63: s | E63: s | F63: s
A64: TMNT | B64: s | C64: s | D64: s | E64: s | F64: s
A65: TMNT Pizza Lands | B65: s | C65: 254 | D65: 256 | E65: 255 | F65: 257
A66: Unfinity 1 | B66: 235 | C66: s | D66: 238 | E66: s | F66: 239
A67: Unfinity 2 | B67: s | C67: 241 | D67: 243 | E67: 242 | F67: 244
A68: Unglued | B68: 84 | C68: 85 | D68: 87 | E68: 86 | F68: 88
A69: Unhinged | B69: 136 | C69: 137 | D69: 139 | E69: 138 | F69: 140
A70: Unsanctioned | B70: 88 | C70: 90 | D70: 94 | E70: 92 | F70: 96
A71: Unstable | B71: s | C71: s | D71: s | E71: s | F71: s
A72: Wilds of Eldraine | B72: s | C72: 263 | D72: s | E72: 264 | F72: 266
A73: Zendikar 1 | B73: 230 | C73: 234 | D73: 242 | E73: 238 | F73: 246
A74: Zendikar 2 | B74: 231 | C74: 235 | D74: 243 | E74: 239 | F74: 247
A75: Zendikar 3 | B75: s | C75: 236 | D75: 244 | E75: 240 | F75: s
A76: Zendikar 4 | B76: 233 | C76: 237 | D76: s | E76: 241 | F76: 249
A77: Zendikar Rising 1 | B77: 266 | C77: s | D77: s | E77: s | F77: s
A78: Zendikar Rising 2 | B78: s | C78: s | D78: s | E78: s | F78: s
A79: Zendikar Rising 3 | B79: s | C79: s | D79: s | E79: 274 | F79: s
A81: Judge Promo 2023 | B81: N | C81: N | D81: N | E81: N | F81: N
A82: Judge Promo 2014 | B82: N | C82: N | D82: N | E82: N | F82: N
A83: MKM Showdown | B83: N | C83: N | D83: N | E83: N | F83: N
A85: SL MSCHF 670 | B85: X | C85: X | D85: N | E85: X | F85: X
A86: SL Snow Windows (325 - 329) | B86: N | C86: N | D86: N | E86: N | F86: N
A87: SL Dracula (359 - 363) | B87: N | C87: N | D87: N | E87: N | F87: N
A88: SL SyFy (415 - 419) | B88: N | C88: N | D88: N | E88: N | F88: N
A89: SL Tokyo (46 - 50) | B89: N | C89: N | D89: N | E89: N | F89: N
A90: SL Fortnite (448 - 452) | B90: N | C90: N | D90: N | E90: N | F90: N
A91: SL Bands (2076 - 2080) | B91: N | C91: N | D91: N | E91: N | F91: N
A92: SL Seb Mickon 119 | B92: X | C92: X | D92: X | E92: N | F92: X
A93: SL Tarot (239 - 243) | B93: N | C93: N | D93: N | E93: N | F93: N
... A115: Secret Lair Showdown (31 - 35) | B115: N | C115: N | D115: N | E115: N | F115: N
