Workbook

Sheet COMPRAS
A1: Total: | B1: =C2+C8+C13+C18+C23+C28+C32+C34+C38+C50 -> 0 | E1: Deck | F1: =A2 -> Marcelo | G1: =B3 -> Overrun | H1: =B4 -> Base | I1: =B5 -> 0 | J1: =B6 -> Liga | L1: Deck | M1: Entra | N1: Sai | O1: Fonte
A2: Marcelo | B2: Total Lojas: | C2: =SUM(C3:C6) -> 0 | F2: Defesa Engenhosa | L2: Coleção | M2: Command Tower
A3: =COUNTA(F2:F216) -> 12 | B3: Overrun | C3: =SUM(G:G) -> 0 | F3: Horizon Explorer | L3: Baylen | M3: Canopy Vista | N3: Montanha
B4: Base | C4: =SUM(H:H) -> 0 | F4: Aguaceiro Anfíbio | L4: Baylen | M4: Cinder Glade | N4: Planície
C5: =SUM(I:I) -> 0 | F5: Dever Além da Morte | L5: Baylen | M5: Mossfire Valley | N5: Vatidão Morfoterrena
B6: Liga | C6: =SUM(J:J) -> 0 | F6: Comando Incendiário | L6: Gitrog | M6: Broodheart Engine | N6: Nyx Weaver
F7: Reyhan, Última dos Abzan | L7: Gitrog | M7: Hedge Shredder | N7: Cemetery Tampering
F8: Druida Devotado | L8: Inalla | M8: Dour-Port Mage | N8: Riverwise Augur
F9: Hidra Devoradora de Mana | L9: Modular | M9: Arcbound Crusher
F10: Pátio Reservado | L10: Modular | M10: Arcbound Javelineer
F11: Os Jardins Micossintéticos | L11: Modular | M11: Arcbound Mouser
F12: Pain for All | L12: Modular | M12: Arcbound Ravager
F13: Ressonador Estriônico | L13: Modular | M13: Arcbound Reclaimer
L14: Modular | M14: Arcbound Shikari
L15: Modular | M15: Arcbound Slith
L16: Modular | M16: Arcbound Stinger
L17: Modular | M17: Arcbound Tracker
L18: Modular | M18: Arcbound Whelp
L19: Modular | M19: Boros Signet
L20: Modular | M20: Command Tower
L21: Modular | M21: Darksteel Citadel
L22: Modular | M22: Hamza, Guardian of Arashin
L23: Modular | M23: Hangarback Walker
L24: Modular | M24: Long-Range Sensor
L25: Modular | M25: Marketback Walker
... L36: Modular | M36: Trading Post
L37: Muzzio | M37: Academy Ruins | N37: Ilha
L38: Narset | M38: Spark Double | N38: Mask of the Schemer
L39: Piratas | M39: Bident of Thassa
L40: Piratas | M40: Coastline Marauders
L41: Piratas | M41: Deadeye Tracker
L42: Piratas | M42: Forerunner of the Coalition
L43: Piratas | M43: Malcoln, Alluring Scoundrel
L44: Piratas | M44: Reckless Fireweaver
L45: Piratas | M45: Seething Landscape
L46: Piratas | M46: Siren Stormtamer
L47: Piratas | M47: Spyglass Siren
L48: Piratas | M48: Warkite Marauder
L49: Piratas | M49: Xorn
L50: Rani | M50: Powerbalance | N50: Afogar no Lago
L51: Tayam | M51: Botanical Brawler
L52: Tayam | M52: Branching Evolution
L53: Tayam | M53: Bulwark Ox
L54: Tayam | M54: Conclave Mentor
L55: Tayam | M55: Exotic Orchard
L56: Tayam | M56: Llanowar Reborn
L57: Tayam | M57: Retribution of the Ancients
L58: Tayam | M58: Rishkar, Peema Renegade
L59: Tayam | M59: Sakura-Tribe Elder
L60: Tayam | M60: Scholar of new Horizons
L61: Tayam | M61: Stocking the Pantry
L62: Tayam | M62: Warden of the Grove
L63: Tayam | M63: Winding Constrictor
L64: Zimone | M64: Bloodstained Mire | N64: Myriad Landscape
L65: Zimone | M65: Fabled Passage | N65: Campos de Demolição
L66: Piratas | M66: Ilha
L67: Piratas | M67: Montanha
L68: Coleção | M68: Arboria | O68: Legacy | P68: Felipe
L69: Oona | M69: Arco da Inovação | N69: Ilha | O69: Legacy | P69: Felipe
L70: VialIshai | M70: Cordões Prismáticos | N70: Equilíbrio de Poderes | O70: Legacy | P70: Felipe
L71: Coleção | M71: Imskir Papa-Ferro | O71: Legacy | P71: Felipe
L72: Baylen | M72: Sabedoria da Natureza | N72: Floresta | O72: Legacy | P72: Felipe
L73: Carlos | M73: Sorin da Casa Markov | N73: Boas-vindas de Ajani | O73: Legacy | P73: Felipe
L74: Tayam | M74: Syr Vondam, Sunlight Exemplar | O74: Legacy | P74: Felipe
L75: Elfos | M75: Breeding Pool | N75: Floresta | O75: Legacy | P75: Alexsander
M76: Aminatou, Veil Piercer
M77: Sol Ring
L78: Dexter | M78: Azure Beastbinder
L79: Tayam | M79: Spymaster's Vault
L80: Modular | M80: Arcane Signet
L81: Tayam | M81: Deceptive Landscape
M82: Fellwar Stone
M83: Generous Gift
M84: Monumental Henge
M85: Mandate of Peace
M86: Rogue's Passage
M87: Scour for Scrap
M88: Thought Vessel
M89: Sevinne's Reclamation
L90: Dexter | M90: Inquisitive Glimmer | N90: -
M91: Reality Shift
L92: Carlos | M92: Darkstar Augur | N92: Darkstar Augur
M93: Bojuka Bog
M94: Sol Ring
M95: Arcane Signet
L96: Modular | M96: Annie Joins Up | N96: - | O96: Francati
L97: Modular | M97: Scrap Welder | N97: -
L98: Modular | M98: Osgir, the Reconstructor | N98: - | O98: Francati
L99: Modular | M99: The Jolly Balloon Man | N99: -

Sheet STATS
A1: Dia | B1: Player 1 | C1: Deck 1 | D1: Player 2 | E1: Deck 2 | F1: Player 3 | G1: Deck 3 | H1: Player 4 | I1: Deck 4 | J1: Vitória | M1: Deck | N1: Partidas | O1: Winrate | Q1: Player | R1: Partidas | S1: Winrate
A2: 45587 | B2: Marcelo | C2: Elfos | D2: Vivian | E2: Zimone | F2: Renato | G2: Raffine | H2: Dexter | I2: Kaalia | J2: Marcelo | K2: Elfos | M2: Akiri | N2: =COUNTIF(C:C,M2)+COUNTIF(E:E,M2)+COUNTIF(G:G,M2)+COUNTIF(I:I,M2) -> 2 | O2: =IF(N2>=10,(COUNTIF(K:K,M2)/N2),"Insuficiente") -> Insuficiente | Q2: Marcelo | R2: =COUNTIF(B:B,Q2)+COUNTIF(D:D,Q2)+COUNTIF(F:F,Q2)+COUNTIF(H:H,Q2) -> 11 | S2: =IF(R2>=10, (COUNTIF(J:J,Q2)/R2), "Insuficiente") -> 0.36363636
A3: 45594 | B3: Marcelo | C3: Breya | D3: Vivian | E3: Zimone | F3: Renato | G3: Raffine | H3: Dexter | I3: Tovolar | J3: Vivian | K3: Zimone | M3: Arcades | N3: =COUNTIF(C:C,M3)+COUNTIF(E:E,M3)+COUNTIF(G:G,M3)+COUNTIF(I:I,M3) -> 1 | O3: =IF(N3>=10,(COUNTIF(K:K,M3)/N3),"Insuficiente") -> Insuficiente | Q3: Vivian | R3: =COUNTIF(B:B,Q3)+COUNTIF(D:D,Q3)+COUNTIF(F:F,Q3)+COUNTIF(H:H,Q3) -> 11 | S3: =IF(R3>=10, (COUNTIF(J:J,Q3)/R3), "Insuficiente") -> 0.27272727
A4: 45594 | B4: Marcelo | C4: Trakiri | D4: Vivian | E4: Zimone | F4: Renato | G4: Raffine | H4: Hamster | I4: Muzzio | J4: Marcelo | K4: Trakiri | M4: Baylen | N4: =COUNTIF(C:C,M4)+COUNTIF(E:E,M4)+COUNTIF(G:G,M4)+COUNTIF(I:I,M4) -> 1 | O4: =IF(N4>=10,(COUNTIF(K:K,M4)/N4),"Insuficiente") -> Insuficiente | Q4: Renato | R4: =COUNTIF(B:B,Q4)+COUNTIF(D:D,Q4)+COUNTIF(F:F,Q4)+COUNTIF(H:H,Q4) -> 6 | S4: =IF(R4>=10, (COUNTIF(J:J,Q4)/R4), "Insuficiente") -> Insuficiente
A5: 45594 | B5: Marcelo | C5: Akiri | D5: Vivian | E5: Zimone | F5: Renato | G5: Baylen | H5: Hamster | I5: Kumena | J5: Marcelo | K5: Akiri | M5: Breya | N5: =COUNTIF(C:C,M5)+COUNTIF(E:E,M5)+COUNTIF(G:G,M5)+COUNTIF(I:I,M5) -> 1 | O5: =IF(N5>=10,(COUNTIF(K:K,M5)/N5),"Insuficiente") -> Insuficiente | Q5: Dexter | R5: =COUNTIF(B:B,Q5)+COUNTIF(D:D,Q5)+COUNTIF(F:F,Q5)+COUNTIF(H:H,Q5) -> 5 | S5: =IF(R5>=10, (COUNTIF(J:J,Q5)/R5), "Insuficiente") -> Insuficiente
A6: 45597 | B6: Marcelo | C6: Inalla | D6: Vivian | E6: Zimone | F6: Renato | G6: Raffine | H6: João | I6: Winota | J6: João | K6: Winota | M6: Elfos | N6: =COUNTIF(C:C,M6)+COUNTIF(E:E,M6)+COUNTIF(G:G,M6)+COUNTIF(I:I,M6) -> 1 | O6: =IF(N6>=10,(COUNTIF(K:K,M6)/N6),"Insuficiente") -> Insuficiente | Q6: Hamster | R6: =COUNTIF(B:B,Q6)+COUNTIF(D:D,Q6)+COUNTIF(F:F,Q6)+COUNTIF(H:H,Q6) -> 2 | S6: =IF(R6>=10, (COUNTIF(J:J,Q6)/R6), "Insuficiente") -> Insuficiente
A7: 45597 | B7: Marcelo | C7: Yuriko | D7: Vivian | E7: Zimone | F7: Renato | G7: Raffine | H7: João | I7: Winota | J7: Vivian | K7: Zimone | M7: FF Counters | N7: =COUNTIF(C:C,M7)+COUNTIF(E:E,M7)+COUNTIF(G:G,M7)+COUNTIF(I:I,M7) -> 2 | O7: =IF(N7>=10,(COUNTIF(K:K,M7)/N7),"Insuficiente") -> Insuficiente | Q7: Talita | R7: =COUNTIF(B:B,Q7)+COUNTIF(D:D,Q7)+COUNTIF(F:F,Q7)+COUNTIF(H:H,Q7) -> 3 | S7: =IF(R7>=10, (COUNTIF(J:J,Q7)/R7), "Insuficiente") -> Insuficiente
A8: 45599 | B8: Marcelo | C8: Narset | D8: Vivian | E8: Arcades | F8: Dexter | G8: Who Villains | H8: Talita | I8: Who Time | J8: Vivian | K8: Arcades | M8: Hashaton | N8: =COUNTIF(C:C,M8)+COUNTIF(E:E,M8)+COUNTIF(G:G,M8)+COUNTIF(I:I,M8) -> 1 | O8: =IF(N8>=10,(COUNTIF(K:K,M8)/N8),"Insuficiente") -> Insuficiente | Q8: João | R8: =COUNTIF(B:B,Q8)+COUNTIF(D:D,Q8)+COUNTIF(F:F,Q8)+COUNTIF(H:H,Q8) -> 4 | S8: =IF(R8>=10, (COUNTIF(J:J,Q8)/R8), "Insuficiente") -> Insuficiente
A9: 45599 | B9: Marcelo | C9: Thantis | D9: Vivian | E9: Akiri | F9: Dexter | G9: Who Villains | H9: Talita | I9: Ladinos | J9: Talita | K9: Ladinos | M9: Inalla | N9: =COUNTIF(C:C,M9)+COUNTIF(E:E,M9)+COUNTIF(G:G,M9)+COUNTIF(I:I,M9) -> 1 | O9: =IF(N9>=10,(COUNTIF(K:K,M9)/N9),"Insuficiente") -> Insuficiente | Q9: Philips | R9: =COUNTIF(B:B,Q9)+COUNTIF(D:D,Q9)+COUNTIF(F:F,Q9)+COUNTIF(H:H,Q9) -> 2 | S9: =IF(R9>=10, (COUNTIF(J:J,Q9)/R9), "Insuficiente") -> Insuficiente
A10: 45835 | B10: Marcelo | C10: Zedruu | D10: Vivian | E10: Jhoira | F10: Dexter | G10: Who Villains | H10: Talita | I10: Who Time | J10: Dexter | K10: Who Villains | M10: Jhoira | N10: =COUNTIF(C:C,M10)+COUNTIF(E:E,M10)+COUNTIF(G:G,M10)+COUNTIF(I:I,M10) -> 1 | O10: =IF(N10>=10,(COUNTIF(K:K,M10)/N10),"Insuficiente") -> Insuficiente
A11: 45864 | B11: Marcelo | C11: Muzzio | D11: Vivian | E11: Zimone | F11: Philips | G11: Hashaton | H11: João | I11: FF Counters | J11: Marcelo | K11: Muzzio | M11: Kaalia | N11: =COUNTIF(C:C,M11)+COUNTIF(E:E,M11)+COUNTIF(G:G,M11)+COUNTIF(I:I,M11) -> 2 | O11: =IF(N11>=10,(COUNTIF(K:K,M11)/N11),"Insuficiente") -> Insuficiente
A12: 45864 | B12: Marcelo | C12: Sisay | D12: Vivian | E12: Zimone | F12: Philips | G12: Kaalia | H12: João | I12: FF Counters | J12: Philips | K12: Kaalia | M12: Kumena | N12: =COUNTIF(C:C,M12)+COUNTIF(E:E,M12)+COUNTIF(G:G,M12)+COUNTIF(I:I,M12) -> 1 | O12: =IF(N12>=10,(COUNTIF(K:K,M12)/N12),"Insuficiente") -> Insuficiente
M13: Ladinos | N13: =COUNTIF(C:C,M13)+COUNTIF(E:E,M13)+COUNTIF(G:G,M13)+COUNTIF(I:I,M13) -> 1 | O13: =IF(N13>=10,(COUNTIF(K:K,M13)/N13),"Insuficiente") -> Insuficiente
M14: Muzzio | N14: =COUNTIF(C:C,M14)+COUNTIF(E:E,M14)+COUNTIF(G:G,M14)+COUNTIF(I:I,M14) -> 2 | O14: =IF(N14>=10,(COUNTIF(K:K,M14)/N14),"Insuficiente") -> Insuficiente
M15: Narset | N15: =COUNTIF(C:C,M15)+COUNTIF(E:E,M15)+COUNTIF(G:G,M15)+COUNTIF(I:I,M15) -> 1 | O15: =IF(N15>=10,(COUNTIF(K:K,M15)/N15),"Insuficiente") -> Insuficiente
M16: Raffine | N16: =COUNTIF(C:C,M16)+COUNTIF(E:E,M16)+COUNTIF(G:G,M16)+COUNTIF(I:I,M16) -> 5 | O16: =IF(N16>=10,(COUNTIF(K:K,M16)/N16),"Insuficiente") -> Insuficiente
M17: Sisay | N17: =COUNTIF(C:C,M17)+COUNTIF(E:E,M17)+COUNTIF(G:G,M17)+COUNTIF(I:I,M17) -> 1 | O17: =IF(N17>=10,(COUNTIF(K:K,M17)/N17),"Insuficiente") -> Insuficiente
M18: Thantis | N18: =COUNTIF(C:C,M18)+COUNTIF(E:E,M18)+COUNTIF(G:G,M18)+COUNTIF(I:I,M18) -> 1 | O18: =IF(N18>=10,(COUNTIF(K:K,M18)/N18),"Insuficiente") -> Insuficiente
M19: Tovolar | N19: =COUNTIF(C:C,M19)+COUNTIF(E:E,M19)+COUNTIF(G:G,M19)+COUNTIF(I:I,M19) -> 1 | O19: =IF(N19>=10,(COUNTIF(K:K,M19)/N19),"Insuficiente") -> Insuficiente
M20: Trakiri | N20: =COUNTIF(C:C,M20)+COUNTIF(E:E,M20)+COUNTIF(G:G,M20)+COUNTIF(I:I,M20) -> 1 | O20: =IF(N20>=10,(COUNTIF(K:K,M20)/N20),"Insuficiente") -> Insuficiente
M21: Who Time | N21: =COUNTIF(C:C,M21)+COUNTIF(E:E,M21)+COUNTIF(G:G,M21)+COUNTIF(I:I,M21) -> 2 | O21: =IF(N21>=10,(COUNTIF(K:K,M21)/N21),"Insuficiente") -> Insuficiente
M22: Who Villains | N22: =COUNTIF(C:C,M22)+COUNTIF(E:E,M22)+COUNTIF(G:G,M22)+COUNTIF(I:I,M22) -> 3 | O22: =IF(N22>=10,(COUNTIF(K:K,M22)/N22),"Insuficiente") -> Insuficiente
M23: Winota | N23: =COUNTIF(C:C,M23)+COUNTIF(E:E,M23)+COUNTIF(G:G,M23)+COUNTIF(I:I,M23) -> 2 | O23: =IF(N23>=10,(COUNTIF(K:K,M23)/N23),"Insuficiente") -> Insuficiente
M24: Yuriko | N24: =COUNTIF(C:C,M24)+COUNTIF(E:E,M24)+COUNTIF(G:G,M24)+COUNTIF(I:I,M24) -> 1 | O24: =IF(N24>=10,(COUNTIF(K:K,M24)/N24),"Insuficiente") -> Insuficiente
... M26: Zimone | N26: =COUNTIF(C:C,M26)+COUNTIF(E:E,M26)+COUNTIF(G:G,M26)+COUNTIF(I:I,M26) -> 8 | O26: =IF(N26>=10,(COUNTIF(K:K,M26)/N26),"Insuficiente") -> Insuficiente

Sheet WATCH
A1: Carta | B1: Identidade | G1: Tipo | H1: Categoria | I1: Classe
A2: Weathered Runestone | B2: Não | C2: Não | D2: Não | E2: Não | F2: Não | G2: Artefato | H2: Stax | I2: Cemitério
A3: Shivan Harvest | B3: Não | C3: Não | D3: Sim | E3: Não | F3: Não | G3: Encantamento | H3: Remoção | I3: Terreno
A4: Scouting Trek | B4: Não | C4: Não | D4: Não | E4: Não | F4: Sim | G4: Feitiço | H4: Combo | I4: Tutor
A5: Overabundance | B5: Não | C5: Não | D5: Sim | E5: Não | F5: Não | G5: Encantamento | H5: Ramp | I5: Punição
A6: Spreading Plague | B6: Não | C6: Não | D6: Não | E6: Sim | F6: Não | G6: Encantamento | H6: Stax | I6: Criaturas
A7: Explosão da Alma | B7: Não | C7: Não | D7: Sim | E7: Não | F7: Não | G7: Instantânea | H7: Wincon | I7: Dano
A8: Obsidian Fireheat | B8: Não | C8: Não | D8: Sim | E8: Não | F8: Não | G8: Criatura | H8: Wincon | I8: Punição
A9: Interdict | B9: Não | C9: Sim | D9: Não | E9: Não | F9: Não | G9: Instantânea | H9: Anule | I9: Habilidade
A10: Mogg Infestation | B10: Não | C10: Não | D10: Sim | E10: Não | F10: Não | G10: Feitiço | H10: Remoção | I10: Criaturas
A11: Life // Death | B11: Não | C11: Não | D11: Não | E11: Não | F11: Sim | G11: Feitiço | H11: Combo | I11: Terreno
A12: Debt of Loyalt | B12: Sim | C12: Não | D12: Não | E12: Não | F12: Não | G12: Instantânea | H12: Remoção | I12: Roubo
A13: Yavimaya Hollow | B13: Não | C13: Não | D13: Não | E13: Não | F13: Sim | G13: Terreno | H13: Proteção | I13: Criaturas
... A23: Preferência de Cineréia | B23: Não | C23: Não | D23: Sim | E23: Não | F23: Não | G23: Encantamento | H23: Stax | I23: Criaturas

Sheet RESUMO
A1: Prioridade | B1: Faltam | C1: Deck 1 | D1: Deck 2 | E1: Deck 3 | F1: Deck 4 | G1: Carta | J1: Alterações | K1: Cores | P1: =COUNTA(I3:I5000) & " Decks" -> 30 Decks | U1: Piratas | V1: Baylen | W1: Narset | X1: Tayam | Y1: Carlos | Z1: Rani | AA1: Kumena | AB1: Zimone | AC1: JhoiraB | AD1: Gritrog | AE1: Muzzio | AF1: VialIshai | AG1: Yuriko | AH1: Inalla | AI1: Akiri | AJ1: Sisay | AK1: Thrakiri | AL1: Elfos | AM1: Jhoira | AN1: Fractius | AO1: Rielle | AP1: Oona | AQ1: Kresh | AR1: Breya | AS1: OWA | AT1: Alela | AU1: Arcades | AV1: Zedruu | AW1: Exaltado | AX1: Modular | AY1: Holder 1 | AZ1: Holder 2
A2: =IFERROR(INDEX($S$3:$S$200, MATCH($C2, $I$3:$I$200, 0)), "") -> 3 | B2: =COUNTIF(U:AX,G2) -> 1 | C2: =IFERROR( INDEX($U$1:$AX$1, MATCH(TRUE, CHOOSE({1;2;3;4;5;6;7;8;9;10;11;12;13;14;15;16;17;18;19;20;21;22;23;24;25;26;27;28;29;30;31;32}, COUNTIFS($U$2:$U$200,$G2)>0, COUNTIFS($V$2:$V$200,$G2)>0, COUNTIFS($W$2:$W$200,$G2)>0, COUNTIFS($X$2:$X$200,$G2)>0, COUNTIFS($Y$2:$Y$200,$G2)>0, COUNTIFS($Z$2:$Z$200,$G2)>0, COUNTIFS($AA$2:$AA$200,$G2)>0, COUNTIFS($AB$2:$AB$200,$G2)>0, COUNTIFS($AC$2:$AC$200,$G2)>0, COUNTIFS($AD$2:$AD$200,$G2)>0, COUNTIFS($AE$2:$AE$200,$G2)>0, COUNTIFS($AF$2:$AF$200,$G2)>0, COUNTIFS($AG$2:$AG$200,$G2)>0, COUNTIFS($AH$2:$AH$200,$G2)>0, COUNTIFS($AI$2:$AI$200,$G2)>0, COUNTIFS($AJ$2:$AJ$200,$G2)>0, COUNTIFS($AK$2:$AK$200,$G2)>0, COUNTIFS($AL$2:$AL$200,$G2)>0, COUNTIFS($AM$2:$AM$200,$G2)>0, COUNTIFS($AN$2:$AN$200,$G2)>0, COUNTIFS($AO$2:$AO$200,$G2)>0, COUNTIFS($AP$2:$AP$200,$G2)>0, COUNTIFS($AQ$2:$AQ$200,$G2)>0, COUNTIFS($AR$2:$AR$200,$G2)>0, COUNTIFS($AS$2:$AS$200,$G2)>0, COUNTIFS($AT$2:$AT$200,$G2)>0, COUNTIFS($AU$2:$AU$200,$G2)>0, COUNTIFS($AV$2:$AV$200,$G2)>0, COUNTIFS($AW$2:$AW$200,$G2)>0, COUNTIFS($AX$2:$AX$200,$G2)>0 ), 0) ), "") -> Muzzio | D2: {=IFERROR( INDEX( _xlfn._xlws.FILTER($U$1:$AX$1, TRANSPOSE( CHOOSE({1;2;3;4;5;6;7;8;9;10;11;12;13;14;15;16;17;18;19;20;21;22;23;24;25;26;27;28;29;30}, COUNTIFS($U$2:$U$200,$G2)>0, COUNTIFS($V$2:$V$200,$G2)>0, COUNTIFS($W$2:$W$200,$G2)>0, COUNTIFS($X$2:$X$200,$G2)>0, COUNTIFS($Y$2:$Y$200,$G2)>0, COUNTIFS($Z$2:$Z$200,$G2)>0, COUNTIFS($AA$2:$AA$200,$G2)>0, COUNTIFS($AB$2:$AB$200,$G2)>0, COUNTIFS($AC$2:$AC$200,$G2)>0, COUNTIFS($AD$2:$AD$200,$G2)>0, COUNTIFS($AE$2:$AE$200,$G2)>0, COUNTIFS($AF$2:$AF$200,$G2)>0, COUNTIFS($AG$2:$AG$200,$G2)>0, COUNTIFS($AH$2:$AH$200,$G2)>0, COUNTIFS($AI$2:$AI$200,$G2)>0, COUNTIFS($AJ$2:$AJ$200,$G2)>0, COUNTIFS($AK$2:$AK$200,$G2)>0, COUNTIFS($AL$2:$AL$200,$G2)>0, COUNTIFS($AM$2:$AM$200,$G2)>0, COUNTIFS($AN$2:$AN$200,$G2)>0, COUNTIFS($AO$2:$AO$200,$G2)>0, COUNTIFS($AP$2:$AP$200,$G2)>0, COUNTIFS($AQ$2:$AQ$200,$G2)>0, COUNTIFS($AR$2:$AR$200,$G2)>0, COUNTIFS($AS$2:$AS$200,$G2)>0, COUNTIFS($AT$2:$AT$200,$G2)>0, COUNTIFS($AU$2:$AU$200,$G2)>0, COUNTIFS($AV$2:$AV$200,$G2)>0, COUNTIFS($AW$2:$AW$200,$G2)>0, COUNTIFS($AX$2:$AX$200,$G2)>0 )), ), 2 ), "")} | E2: {=IFERROR( INDEX( _xlfn._xlws.FILTER($U$1:$AX$1, TRANSPOSE( CHOOSE({1;2;3;4;5;6;7;8;9;10;11;12;13;14;15;16;17;18;19;20;21;22;23;24;25;26;27;28;29;30}, COUNTIFS($U$2:$U$200,$G2)>0, COUNTIFS($V$2:$V$200,$G2)>0, COUNTIFS($W$2:$W$200,$G2)>0, COUNTIFS($X$2:$X$200,$G2)>0, COUNTIFS($Y$2:$Y$200,$G2)>0, COUNTIFS($Z$2:$Z$200,$G2)>0, COUNTIFS($AA$2:$AA$200,$G2)>0, COUNTIFS($AB$2:$AB$200,$G2)>0, COUNTIFS($AC$2:$AC$200,$G2)>0, COUNTIFS($AD$2:$AD$200,$G2)>0, COUNTIFS($AE$2:$AE$200,$G2)>0, COUNTIFS($AF$2:$AF$200,$G2)>0, COUNTIFS($AG$2:$AG$200,$G2)>0, COUNTIFS($AH$2:$AH$200,$G2)>0, COUNTIFS($AI$2:$AI$200,$G2)>0, COUNTIFS($AJ$2:$AJ$200,$G2)>0, COUNTIFS($AK$2:$AK$200,$G2)>0, COUNTIFS($AL$2:$AL$200,$G2)>0, COUNTIFS($AM$2:$AM$200,$G2)>0, COUNTIFS($AN$2:$AN$200,$G2)>0, COUNTIFS($AO$2:$AO$200,$G2)>0, COUNTIFS($AP$2:$AP$200,$G2)>0, COUNTIFS($AQ$2:$AQ$200,$G2)>0, COUNTIFS($AR$2:$AR$200,$G2)>0, COUNTIFS($AS$2:$AS$200,$G2)>0, COUNTIFS($AT$2:$AT$200,$G2)>0, COUNTIFS($AU$2:$AU$200,$G2)>0, COUNTIFS($AV$2:$AV$200,$G2)>0, COUNTIFS($AW$2:$AW$200,$G2)>0, COUNTIFS($AX$2:$AX$200,$G2)>0 )), ), 3 ), "")} | F2: {=IFERROR( INDEX( _xlfn._xlws.FILTER($U$1:$AX$1, TRANSPOSE( CHOOSE({1;2;3;4;5;6;7;8;9;10;11;12;13;14;15;16;17;18;19;20;21;22;23;24;25;26;27;28;29;30}, COUNTIFS($U$2:$U$200,$G2)>0, COUNTIFS($V$2:$V$200,$G2)>0, COUNTIFS($W$2:$W$200,$G2)>0, COUNTIFS($X$2:$X$200,$G2)>0, COUNTIFS($Y$2:$Y$200,$G2)>0, COUNTIFS($Z$2:$Z$200,$G2)>0, COUNTIFS($AA$2:$AA$200,$G2)>0, COUNTIFS($AB$2:$AB$200,$G2)>0, COUNTIFS($AC$2:$AC$200,$G2)>0, COUNTIFS($AD$2:$AD$200,$G2)>0, COUNTIFS($AE$2:$AE$200,$G2)>0, COUNTIFS($AF$2:$AF$200,$G2)>0, COUNTIFS($AG$2:$AG$200,$G2)>0, COUNTIFS($AH$2:$AH$200,$G2)>0, COUNTIFS($AI$2:$AI$200,$G2)>0, COUNTIFS($AJ$2:$AJ$200,$G2)>0, COUNTIFS($AK$2:$AK$200,$G2)>0, COUNTIFS($AL$2:$AL$200,$G2)>0, COUNTIFS($AM$2:$AM$200,$G2)>0, COUNTIFS($AN$2:$AN$200,$G2)>0, COUNTIFS($AO$2:$AO$200,$G2)>0, COUNTIFS($AP$2:$AP$200,$G2)>0, COUNTIFS($AQ$2:$AQ$200,$G2)>0, COUNTIFS($AR$2:$AR$200,$G2)>0, COUNTIFS($AS$2:$AS$200,$G2)>0, COUNTIFS($AT$2:$AT$200,$G2)>0, COUNTIFS($AU$2:$AU$200,$G2)>0, COUNTIFS($AV$2:$AV$200,$G2)>0, COUNTIFS($AW$2:$AW$200,$G2)>0, COUNTIFS($AX$2:$AX$200,$G2)>0 )), ), 4 ), "")} | G2: {=IF(COUNTA(_xlfn.ANCHORARRAY($CJ$2))=0,"",_xlfn._xlws.SORT(_xlfn.UNIQUE(_xlfn.ANCHORARRAY($CJ$2)),1,1))} -> A Joia do Enigma | I2: Total | J2: =SUM(J3:J30) -> 327 | K2: =COUNTIF(K3:K5000,"Sim") -> 16 | L2: =COUNTIF(L3:L5000,"Sim") -> 22 | M2: =COUNTIF(M3:M5000,"Sim") -> 17 | N2: =COUNTIF(N3:N5000,"Sim") -> 17 | O2: =COUNTIF(O3:O5000,"Sim") -> 14 | P2: Wincon | Q2: Sub Plan | R2: Descrição | S2: Prioridade | U2: {=IF(COUNTA(_xlfn._xlws.FILTER(Piratas!C3:C200,(Piratas!B3:B200<>Piratas!C3:C200)*(Piratas!C3:C200<>"")))=0,"",_xlfn._xlws.SORT(_xlfn._xlws.FILTER(Piratas!C3:C200,(Piratas!B3:B200<>Piratas!C3:C200)*(Piratas!C3:C200<>"")),1,1))} -> Back in Town | V2: {=IF(COUNTA(_xlfn._xlws.FILTER(Baylen!C3:C200,(Baylen!B3:B200<>Baylen!C3:C200)*(Baylen!C3:C200<>"")))=0,"",_xlfn._xlws.SORT(_xlfn._xlws.FILTER(Baylen!C3:C200,(Baylen!B3:B200<>Baylen!C3:C200)*(Baylen!C3:C200<>"")),1,1))} -> Artifact Mutation | W2: {=IF(COUNTA(_xlfn._xlws.FILTER(Narset!C3:C200,(Narset!B3:B200<>Narset!C3:C200)*(Narset!C3:C200<>"")))=0,"",_xlfn._xlws.SORT(_xlfn._xlws.FILTER(Narset!C3:C200,(Narset!B3:B200<>Narset!C3:C200)*(Narset!C3:C200<>"")),1,1))} -> Adarkar Wastes | X2: {=IF(COUNTA(_xlfn._xlws.FILTER(Tayam!C3:C200,(Tayam!B3:B200<>Tayam!C3:C200)*(Tayam!C3:C200<>"")))=0,"",_xlfn._xlws.SORT(_xlfn._xlws.FILTER(Tayam!C3:C200,(Tayam!B3:B200<>Tayam!C3:C200)*(Tayam!C3:C200<>"")),1,1))} -> Ardbert, Warrior of Darkness | Y2: {=IF(COUNTA(_xlfn._xlws.FILTER(Carlos!C3:C200,(Carlos!B3:B200<>Carlos!C3:C200)*(Carlos!C3:C200<>"")))=0,"",_xlfn._xlws.SORT(_xlfn._xlws.FILTER(Carlos!C3:C200,(Carlos!B3:B200<>Carlos!C3:C200)*(Carlos!C3:C200<>"")),1,1))} -> Ascensão do Avernus | Z2: {=IF(COUNTA(_xlfn._xlws.FILTER(Rani!C3:C200,(Rani!B3:B200<>Rani!C3:C200)*(Rani!C3:C200<>"")))=0,"",_xlfn._xlws.SORT(_xlfn._xlws.FILTER(Rani!C3:C200,(Rani!B3:B200<>Rani!C3:C200)*(Rani!C3:C200<>"")),1,1))} -> Access Tunnel | AA2: {=IF(COUNTA(_xlfn._xlws.FILTER(Kumena!C3:C200,(Kumena!B3:B200<>Kumena!C3:C200)*(Kumena!C3:C200<>"")))=0,"",_xlfn._xlws.SORT(_xlfn._xlws.FILTER(Kumena!C3:C200,(Kumena!B3:B200<>Kumena!C3:C200)*(Kumena!C3:C200<>"")),1,1))} -> Beast Within | AB2: {=IF(COUNTA(_xlfn._xlws.FILTER(Zimone!C3:C200,(Zimone!B3:B200<>Zimone!C3:C200)*(Zimone!C3:C200<>"")))=0,"",_xlfn._xlws.SORT(_xlfn._xlws.FILTER(Zimone!C3:C200,(Zimone!B3:B200<>Zimone!C3:C200)*(Zimone!C3:C200<>"")),1,1))} -> Ancient Greenwarden | AC2: {=IF(COUNTA(_xlfn._xlws.FILTER(JhoiraB!C3:C200,(JhoiraB!B3:B200<>JhoiraB!C3:C200)*(JhoiraB!C3:C200<>"")))=0,"",_xlfn._xlws.SORT(_xlfn._xlws.FILTER(JhoiraB!C3:C200,(JhoiraB!B3:B200<>JhoiraB!C3:C200)*(JhoiraB!C3:C200<>"")),1,1))} -> Emrakul, um Novo Mundo | AD2: {=IF(COUNTA(_xlfn._xlws.FILTER(Gitrog!C3:C200,(Gitrog!B3:B200<>Gitrog!C3:C200)*(Gitrog!C3:C200<>"")))=0,"",_xlfn._xlws.SORT(_xlfn._xlws.FILTER(Gitrog!C3:C200,(Gitrog!B3:B200<>Gitrog!C3:C200)*(Gitrog!C3:C200<>"")),1,1))} -> Ancient Tomb | AE2: {=IF(COUNTA(_xlfn._xlws.FILTER(Muzzio!C3:C200,(Muzzio!B3:B200<>Muzzio!C3:C200)*(Muzzio!C3:C200<>"")))=0,"",_xlfn._xlws.SORT(_xlfn._xlws.FILTER(Muzzio!C3:C200,(Muzzio!B3:B200<>Muzzio!C3:C200)*(Muzzio!C3:C200<>"")),1,1))} -> A Joia do Enigma | AF2: {=IF(COUNTA(_xlfn._xlws.FILTER(VialIshai!C3:C200,(VialIshai!B3:B200<>VialIshai!C3:C200)*(VialIshai!C3:C200<>"")))=0,"",_xlfn._xlws.SORT(_xlfn._xlws.FILTER(VialIshai!C3:C200,(VialIshai!B3:B200<>VialIshai!C3:C200)*(VialIshai!C3:C200<>"")),1,1))} -> Amphibian Downpour | AG2: {=IF(COUNTA(_xlfn._xlws.FILTER(Yuriko!C3:C200,(Yuriko!B3:B200<>Yuriko!C3:C200)*(Yuriko!C3:C200<>"")))=0,"",_xlfn._xlws.SORT(_xlfn._xlws.FILTER(Yuriko!C3:C200,(Yuriko!B3:B200<>Yuriko!C3:C200)*(Yuriko!C3:C200<>"")),1,1))} -> Creeping Tar Pit | AH2: {=IF(COUNTA(_xlfn._xlws.FILTER(Inalla!C3:C200,(Inalla!B3:B200<>Inalla!C3:C200)*(Inalla!C3:C200<>"")))=0,"",_xlfn._xlws.SORT(_xlfn._xlws.FILTER(Inalla!C3:C200,(Inalla!B3:B200<>Inalla!C3:C200)*(Inalla!C3:C200<>"")),1,1))} -> Arcane Lighthouse | AI2: {=IF(COUNTA(_xlfn._xlws.FILTER(Akiri!C3:C200,(Akiri!B3:B200<>Akiri!C3:C200)*(Akiri!C3:C200<>"")))=0,"",_xlfn._xlws.SORT(_xlfn._xlws.FILTER(Akiri!C3:C200,(Akiri!B3:B200<>Akiri!C3:C200)*(Akiri!C3:C200<>"")),1,1))} -> Cid, Freeflier Pilot | AJ2: {=IF(COUNTA(_xlfn._xlws.FILTER(Sisay!C3:C200,(Sisay!B3:B200<>Sisay!C3:C200)*(Sisay!C3:C200<>"")))=0,"",_xlfn._xlws.SORT(_xlfn._xlws.FILTER(Sisay!C3:C200,(Sisay!B3:B200<>Sisay!C3:C200)*(Sisay!C3:C200<>"")),1,1))} -> Commodore Guff | AK2: {=IF(COUNTA(_xlfn._xlws.FILTER(Thrakiri!C3:C200,(Thrakiri!B3:B200<>Thrakiri!C3:C200)*(Thrakiri!C3:C200<>"")))=0,"",_xlfn._xlws.SORT(_xlfn._xlws.FILTER(Thrakiri!C3:C200,(Thrakiri!B3:B200<>Thrakiri!C3:C200)*(Thrakiri!C3:C200<>"")),1,1))} -> Matoya, Archon Elder | AL2: {=IF(COUNTA(_xlfn._xlws.FILTER(Elfos!C3:C200,(Elfos!B3:B200<>Elfos!C3:C200)*(Elfos!C3:C200<>"")))=0,"",_xlfn._xlws.SORT(_xlfn._xlws.FILTER(Elfos!C3:C200,(Elfos!B3:B200<>Elfos!C3:C200)*(Elfos!C3:C200<>"")),1,1))} -> Alchemist's Refuge | AM2: {=IF(COUNTA(_xlfn._xlws.FILTER(Jhoira!C3:C200,(Jhoira!B3:B200<>Jhoira!C3:C200)*(Jhoira!C3:C200<>"")))=0,"",_xlfn._xlws.SORT(_xlfn._xlws.FILTER(Jhoira!C3:C200,(Jhoira!B3:B200<>Jhoira!C3:C200)*(Jhoira!C3:C200<>"")),1,1))} -> Emrakul, um Novo Mundo | AN2: {=IF(COUNTA(_xlfn._xlws.FILTER(Fractius!C3:C200,(Fractius!B3:B200<>Fractius!C3:C200)*(Fractius!C3:C200<>"")))=0,"",_xlfn._xlws.SORT(_xlfn._xlws.FILTER(Fractius!C3:C200,(Fractius!B3:B200<>Fractius!C3:C200)*(Fractius!C3:C200<>"")),1,1))} -> Caverna das Almas | AO2: {=IF(COUNTA(_xlfn._xlws.FILTER(Rielle!C3:C200,(Rielle!B3:B200<>Rielle!C3:C200)*(Rielle!C3:C200<>"")))=0,"",_xlfn._xlws.SORT(_xlfn._xlws.FILTER(Rielle!C3:C200,(Rielle!B3:B200<>Rielle!C3:C200)*(Rielle!C3:C200<>"")),1,1))} -> Afundar em Estupor | AP2: {=IF(COUNTA(_xlfn._xlws.FILTER(Oona!C3:C200,(Oona!B3:B200<>Oona!C3:C200)*(Oona!C3:C200<>"")))=0,"",_xlfn._xlws.SORT(_xlfn._xlws.FILTER(Oona!C3:C200,(Oona!B3:B200<>Oona!C3:C200)*(Oona!C3:C200<>"")),1,1))} -> Invasion of Segovia | AQ2: {=IF(COUNTA(_xlfn._xlws.FILTER(Kresh!C3:C200,(Kresh!B3:B200<>Kresh!C3:C200)*(Kresh!C3:C200<>"")))=0,"",_xlfn._xlws.SORT(_xlfn._xlws.FILTER(Kresh!C3:C200,(Kresh!B3:B200<>Kresh!C3:C200)*(Kresh!C3:C200<>"")),1,1))} -> Bugenhagen, Wise Elder | AR2: {=IF(COUNTA(_xlfn._xlws.FILTER(Breya!C3:C200,(Breya!B3:B200<>Breya!C3:C200)*(Breya!C3:C200<>"")))=0,"",_xlfn._xlws.SORT(_xlfn._xlws.FILTER(Breya!C3:C200,(Breya!B3:B200<>Breya!C3:C200)*(Breya!C3:C200<>"")),1,1))} -> Adagia, Windswept Bastion | AS2: {=IF(COUNTA(_xlfn._xlws.FILTER(OWA!C3:C200,(OWA!B3:B200<>OWA!C3:C200)*(OWA!C3:C200<>"")))=0,"",_xlfn._xlws.SORT(_xlfn._xlws.FILTER(OWA!C3:C200,(OWA!B3:B200<>OWA!C3:C200)*(OWA!C3:C200<>"")),1,1))} -> Dollmaker's Shop // Porcelain Gallery | AT2: {=IF(COUNTA(_xlfn._xlws.FILTER(Alela!C3:C200,(Alela!B3:B200<>Alela!C3:C200)*(Alela!C3:C200<>"")))=0,"",_xlfn._xlws.SORT(_xlfn._xlws.FILTER(Alela!C3:C200,(Alela!B3:B200<>Alela!C3:C200)*(Alela!C3:C200<>"")),1,1))} -> Adagia, Windswept Bastion | AU2: {=IF(COUNTA(_xlfn._xlws.FILTER(Arcades!C3:C200,(Arcades!B3:B200<>Arcades!C3:C200)*(Arcades!C3:C200<>"")))=0,"",_xlfn._xlws.SORT(_xlfn._xlws.FILTER(Arcades!C3:C200,(Arcades!B3:B200<>Arcades!C3:C200)*(Arcades!C3:C200<>"")),1,1))} -> Alchemist's Refuge | AV2: {=IF(COUNTA(_xlfn._xlws.FILTER(Zedruu!C3:C200,(Zedruu!B3:B200<>Zedruu!C3:C200)*(Zedruu!C3:C200<>"")))=0,"",_xlfn._xlws.SORT(_xlfn._xlws.FILTER(Zedruu!C3:C200,(Zedruu!B3:B200<>Zedruu!C3:C200)*(Zedruu!C3:C200<>"")),1,1))} -> Árbitro Silencioso | AW2: {=IF(COUNTA(_xlfn._xlws.FILTER(Exaltado!C3:C200,(Exaltado!B3:B200<>Exaltado!C3:C200)*(Exaltado!C3:C200<>"")))=0,"",_xlfn._xlws.SORT(_xlfn._xlws.FILTER(Exaltado!C3:C200,(Exaltado!B3:B200<>Exaltado!C3:C200)*(Exaltado!C3:C200<>"")),1,1))} -> #VALUE! | AX2: {=IF(COUNTA(_xlfn._xlws.FILTER(Modular!C3:C200,(Modular!B3:B200<>Modular!C3:C200)*(Modular!C3:C200<>"")))=0,"",_xlfn._xlws.SORT(_xlfn._xlws.FILTER(Modular!C3:C200,(Modular!B3:B200<>Modular!C3:C200)*(Modular!C3:C200<>"")),1,1))} -> Adagia, Windswept Bastion | BB2: {=IF(COUNTA(_xlfn.ANCHORARRAY($U$2))+COUNTA(_xlfn.ANCHORARRAY($V$2))=0,"",_xlfn._xlws.SORT(_xlfn.UNIQUE(IF(ROW(INDIRECT("1:"&(COUNTA(_xlfn.ANCHORARRAY($U$2))+COUNTA(_xlfn.ANCHORARRAY($V$2)))))<=COUNTA(_xlfn.ANCHORARRAY($U$2)),INDEX(_xlfn.ANCHORARRAY($U$2),ROW(INDIRECT("1:"&(COUNTA(_xlfn.ANCHORARRAY($U$2))+COUNTA(_xlfn.ANCHORARRAY($V$2)))))),INDEX(_xlfn.ANCHORARRAY($V$2),ROW(INDIRECT("1:"&(COUNTA(_xlfn.ANCHORARRAY($U$2))+COUNTA(_xlfn.ANCHORARRAY($V$2)))))-COUNTA(_xlfn.ANCHORARRAY($U$2))))),1,1))} -> Artifact Mutation | BC2: {=IF(COUNTA(_xlfn.ANCHORARRAY($W$2))+COUNTA(_xlfn.ANCHORARRAY($X$2))=0,"",_xlfn._xlws.SORT(_xlfn.UNIQUE(IF(ROW(INDIRECT("1:"&(COUNTA(_xlfn.ANCHORARRAY($W$2))+COUNTA(_xlfn.ANCHORARRAY($X$2)))))<=COUNTA(_xlfn.ANCHORARRAY($W$2)),INDEX(_xlfn.ANCHORARRAY($W$2),ROW(INDIRECT("1:"&(COUNTA(_xlfn.ANCHORARRAY($W$2))+COUNTA(_xlfn.ANCHORARRAY($X$2)))))),INDEX(_xlfn.ANCHORARRAY($X$2),ROW(INDIRECT("1:"&(COUNTA(_xlfn.ANCHORARRAY($W$2))+COUNTA(_xlfn.ANCHORARRAY($X$2)))))-COUNTA(_xlfn.ANCHORARRAY($W$2))))),1,1))} -> Adarkar Wastes | BD2: {=IF(COUNTA(_xlfn.ANCHORARRAY($Y$2))+COUNTA(_xlfn.ANCHORARRAY($Z$2))=0,"",_xlfn._xlws.SORT(_xlfn.UNIQUE(IF(ROW(INDIRECT("1:"&(COUNTA(_xlfn.ANCHORARRAY($Y$2))+COUNTA(_xlfn.ANCHORARRAY($Z$2)))))<=COUNTA(_xlfn.ANCHORARRAY($Y$2)),INDEX(_xlfn.ANCHORARRAY($Y$2),ROW(INDIRECT("1:"&(COUNTA(_xlfn.ANCHORARRAY($Y$2))+COUNTA(_xlfn.ANCHORARRAY($Z$2)))))),INDEX(_xlfn.ANCHORARRAY($Z$2),ROW(INDIRECT("1:"&(COUNTA(_xlfn.ANCHORARRAY($Y$2))+COUNTA(_xlfn.ANCHORARRAY($Z$2)))))-COUNTA(_xlfn.ANCHORARRAY($Y$2))))),1,1))} -> Access Tunnel | BE2: {=IF(COUNTA(_xlfn.ANCHORARRAY($AA$2))+COUNTA(_xlfn.ANCHORARRAY($AB$2))=0,"",_xlfn._xlws.SORT(_xlfn.UNIQUE(IF(ROW(INDIRECT("1:"&(COUNTA(_xlfn.ANCHORARRAY($AA$2))+COUNTA(_xlfn.ANCHORARRAY($AB$2)))))<=COUNTA(_xlfn.ANCHORARRAY($AA$2)),INDEX(_xlfn.ANCHORARRAY($AA$2),ROW(INDIRECT("1:"&(COUNTA(_xlfn.ANCHORARRAY($AA$2))+COUNTA(_xlfn.ANCHORARRAY($AB$2)))))),INDEX(_xlfn.ANCHORARRAY($AB$2),ROW(INDIRECT("1:"&(COUNTA(_xlfn.ANCHORARRAY($AA$2))+COUNTA(_xlfn.ANCHORARRAY($AB$2)))))-COUNTA(_xlfn.ANCHORARRAY($AA$2))))),1,1))} -> Ancient Greenwarden | BF2: {=IF(COUNTA(_xlfn.ANCHORARRAY($AC$2))+COUNTA(_xlfn.ANCHORARRAY($AD$2))=0,"",_xlfn._xlws.SORT(_xlfn.UNIQUE(IF(ROW(INDIRECT("1:"&(COUNTA(_xlfn.ANCHORARRAY($AC$2))+COUNTA(_xlfn.ANCHORARRAY($AD$2)))))<=COUNTA(_xlfn.ANCHORARRAY($AC$2)),INDEX(_xlfn.ANCHORARRAY($AC$2),ROW(INDIRECT("1:"&(COUNTA(_xlfn.ANCHORARRAY($AC$2))+COUNTA(_xlfn.ANCHORARRAY($AD$2)))))),INDEX(_xlfn.ANCHORARRAY($AD$2),ROW(INDIRECT("1:"&(COUNTA(_xlfn.ANCHORARRAY($AC$2))+COUNTA(_xlfn.ANCHORARRAY($AD$2)))))-COUNTA(_xlfn.ANCHORARRAY($AC$2))))),1,1))} -> Ancient Tomb | BG2: {=IF(COUNTA(_xlfn.ANCHORARRAY($AE$2))+COUNTA(_xlfn.ANCHORARRAY($AF$2))=0,"",_xlfn._xlws.SORT(_xlfn.UNIQUE(IF(ROW(INDIRECT("1:"&(COUNTA(_xlfn.ANCHORARRAY($AE$2))+COUNTA(_xlfn.ANCHORARRAY($AF$2)))))<=COUNTA(_xlfn.ANCHORARRAY($AE$2)),INDEX(_xlfn.ANCHORARRAY($AE$2),ROW(INDIRECT("1:"&(COUNTA(_xlfn.ANCHORARRAY($AE$2))+COUNTA(_xlfn.ANCHORARRAY($AF$2)))))),INDEX(_xlfn.ANCHORARRAY($AF$2),ROW(INDIRECT("1:"&(COUNTA(_xlfn.ANCHORARRAY($AE$2))+COUNTA(_xlfn.ANCHORARRAY($AF$2)))))-COUNTA(_xlfn.ANCHORARRAY($AE$2))))),1,1))} -> A Joia do Enigma | BH2: {=IF(COUNTA(_xlfn.ANCHORARRAY($AG$2))+COUNTA(_xlfn.ANCHORARRAY($AH$2))=0,"",_xlfn._xlws.SORT(_xlfn.UNIQUE(IF(ROW(INDIRECT("1:"&(COUNTA(_xlfn.ANCHORARRAY($AG$2))+COUNTA(_xlfn.ANCHORARRAY($AH$2)))))<=COUNTA(_xlfn.ANCHORARRAY($AG$2)),INDEX(_xlfn.ANCHORARRAY($AG$2),ROW(INDIRECT("1:"&(COUNTA(_xlfn.ANCHORARRAY($AG$2))+COUNTA(_xlfn.ANCHORARRAY($AH$2)))))),INDEX(_xlfn.ANCHORARRAY($AH$2),ROW(INDIRECT("1:"&(COUNTA(_xlfn.ANCHORARRAY($AG$2))+COUNTA(_xlfn.ANCHORARRAY($AH$2)))))-COUNTA(_xlfn.ANCHORARRAY($AG$2))))),1,1))} -> Arcane Lighthouse | BI2: {=IF(COUNTA(_xlfn.ANCHORARRAY($AI$2))+COUNTA(_xlfn.ANCHORARRAY($AJ$2))=0,"",_xlfn._xlws.SORT(_xlfn.UNIQUE(IF(ROW(INDIRECT("1:"&(COUNTA(_xlfn.ANCHORARRAY($AI$2))+COUNTA(_xlfn.ANCHORARRAY($AJ$2)))))<=COUNTA(_xlfn.ANCHORARRAY($AI$2)),INDEX(_xlfn.ANCHORARRAY($AI$2),ROW(INDIRECT("1:"&(COUNTA(_xlfn.ANCHORARRAY($AI$2))+COUNTA(_xlfn.ANCHORARRAY($AJ$2)))))),INDEX(_xlfn.ANCHORARRAY($AJ$2),ROW(INDIRECT("1:"&(COUNTA(_xlfn.ANCHORARRAY($AI$2))+COUNTA(_xlfn.ANCHORARRAY($AJ$2)))))-COUNTA(_xlfn.ANCHORARRAY($AI$2))))),1,1))} -> Cid, Freeflier Pilot | BJ2: {=IF(COUNTA(_xlfn.ANCHORARRAY($AK$2))+COUNTA(_xlfn.ANCHORARRAY($AL$2))=0,"",_xlfn._xlws.SORT(_xlfn.UNIQUE(IF(ROW(INDIRECT("1:"&(COUNTA(_xlfn.ANCHORARRAY($AK$2))+COUNTA(_xlfn.ANCHORARRAY($AL$2)))))<=COUNTA(_xlfn.ANCHORARRAY($AK$2)),INDEX(_xlfn.ANCHORARRAY($AK$2),ROW(INDIRECT("1:"&(COUNTA(_xlfn.ANCHORARRAY($AK$2))+COUNTA(_xlfn.ANCHORARRAY($AL$2)))))),INDEX(_xlfn.ANCHORARRAY($AL$2),ROW(INDIRECT("1:"&(COUNTA(_xlfn.ANCHORARRAY($AK$2))+COUNTA(_xlfn.ANCHORARRAY($AL$2)))))-COUNTA(_xlfn.ANCHORARRAY($AK$2))))),1,1))} -> Alchemist's Refuge | BK2: {=IF(COUNTA(_xlfn.ANCHORARRAY($AM$2))+COUNTA(_xlfn.ANCHORARRAY($AN$2))=0,"",_xlfn._xlws.SORT(_xlfn.UNIQUE(IF(ROW(INDIRECT("1:"&(COUNTA(_xlfn.ANCHORARRAY($AM$2))+COUNTA(_xlfn.ANCHORARRAY($AN$2)))))<=COUNTA(_xlfn.ANCHORARRAY($AM$2)),INDEX(_xlfn.ANCHORARRAY($AM$2),ROW(INDIRECT("1:"&(COUNTA(_xlfn.ANCHORARRAY($AM$2))+COUNTA(_xlfn.ANCHORARRAY($AN$2)))))),INDEX(_xlfn.ANCHORARRAY($AN$2),ROW(INDIRECT("1:"&(COUNTA(_xlfn.ANCHORARRAY($AM$2))+COUNTA(_xlfn.ANCHORARRAY($AN$2)))))-COUNTA(_xlfn.ANCHORARRAY($AM$2))))),1,1))} -> Caverna das Almas | BL2: {=IF(COUNTA(_xlfn.ANCHORARRAY($AO$2))+COUNTA(_xlfn.ANCHORARRAY($AP$2))=0,"",_xlfn._xlws.SORT(_xlfn.UNIQUE(IF(ROW(INDIRECT("1:"&(COUNTA(_xlfn.ANCHORARRAY($AO$2))+COUNTA(_xlfn.ANCHORARRAY($AP$2)))))<=COUNTA(_xlfn.ANCHORARRAY($AO$2)),INDEX(_xlfn.ANCHORARRAY($AO$2),ROW(INDIRECT("1:"&(COUNTA(_xlfn.ANCHORARRAY($AO$2))+COUNTA(_xlfn.ANCHORARRAY($AP$2)))))),INDEX(_xlfn.ANCHORARRAY($AP$2),ROW(INDIRECT("1:"&(COUNTA(_xlfn.ANCHORARRAY($AO$2))+COUNTA(_xlfn.ANCHORARRAY($AP$2)))))-COUNTA(_xlfn.ANCHORARRAY($AO$2))))),1,1))} -> Afundar em Estupor | BM2: {=IF(COUNTA(_xlfn.ANCHORARRAY($AQ$2))+COUNTA(_xlfn.ANCHORARRAY($AR$2))=0,"",_xlfn._xlws.SORT(_xlfn.UNIQUE(IF(ROW(INDIRECT("1:"&(COUNTA(_xlfn.ANCHORARRAY($AQ$2))+COUNTA(_xlfn.ANCHORARRAY($AR$2)))))<=COUNTA(_xlfn.ANCHORARRAY($AQ$2)),INDEX(_xlfn.ANCHORARRAY($AQ$2),ROW(INDIRECT("1:"&(COUNTA(_xlfn.ANCHORARRAY($AQ$2))+COUNTA(_xlfn.ANCHORARRAY($AR$2)))))),INDEX(_xlfn.ANCHORARRAY($AR$2),ROW(INDIRECT("1:"&(COUNTA(_xlfn.ANCHORARRAY($AQ$2))+COUNTA(_xlfn.ANCHORARRAY($AR$2)))))-COUNTA(_xlfn.ANCHORARRAY($AQ$2))))),1,1))} -> Adagia, Windswept Bastion | BN2: {=IF(COUNTA(_xlfn.ANCHORARRAY($AS$2))+COUNTA(_xlfn.ANCHORARRAY($AT$2))=0,"",_xlfn._xlws.SORT(_xlfn.UNIQUE(IF(ROW(INDIRECT("1:"&(COUNTA(_xlfn.ANCHORARRAY($AS$2))+COUNTA(_xlfn.ANCHORARRAY($AT$2)))))<=COUNTA(_xlfn.ANCHORARRAY($AS$2)),INDEX(_xlfn.ANCHORARRAY($AS$2),ROW(INDIRECT("1:"&(COUNTA(_xlfn.ANCHORARRAY($AS$2))+COUNTA(_xlfn.ANCHORARRAY($AT$2)))))),INDEX(_xlfn.ANCHORARRAY($AT$2),ROW(INDIRECT("1:"&(COUNTA(_xlfn.ANCHORARRAY($AS$2))+COUNTA(_xlfn.ANCHORARRAY($AT$2)))))-COUNTA(_xlfn.ANCHORARRAY($AS$2))))),1,1))} -> Adagia, Windswept Bastion | BO2: {=IF(COUNTA(_xlfn.ANCHORARRAY($AU$2))+COUNTA(_xlfn.ANCHORARRAY($AV$2))=0,"",_xlfn._xlws.SORT(_xlfn.UNIQUE(IF(ROW(INDIRECT("1:"&(COUNTA(_xlfn.ANCHORARRAY($AU$2))+COUNTA(_xlfn.ANCHORARRAY($AV$2)))))<=COUNTA(_xlfn.ANCHORARRAY($AU$2)),INDEX(_xlfn.ANCHORARRAY($AU$2),ROW(INDIRECT("1:"&(COUNTA(_xlfn.ANCHORARRAY($AU$2))+COUNTA(_xlfn.ANCHORARRAY($AV$2)))))),INDEX(_xlfn.ANCHORARRAY($AV$2),ROW(INDIRECT("1:"&(COUNTA(_xlfn.ANCHORARRAY($AU$2))+COUNTA(_xlfn.ANCHORARRAY($AV$2)))))-COUNTA(_xlfn.ANCHORARRAY($AU$2))))),1,1))} -> Alchemist's Refuge | BP2: {=IF(COUNTA(_xlfn.ANCHORARRAY($AW$2))+COUNTA(_xlfn.ANCHORARRAY($AX$2))=0,"",_xlfn._xlws.SORT(_xlfn.UNIQUE(IF(ROW(INDIRECT("1:"&(COUNTA(_xlfn.ANCHORARRAY($AW$2))+COUNTA(_xlfn.ANCHORARRAY($AX$2)))))<=COUNTA(_xlfn.ANCHORARRAY($AW$2)),INDEX(_xlfn.ANCHORARRAY($AW$2),ROW(INDIRECT("1:"&(COUNTA(_xlfn.ANCHORARRAY($AW$2))+COUNTA(_xlfn.ANCHORARRAY($AX$2)))))),INDEX(_xlfn.ANCHORARRAY($AX$2),ROW(INDIRECT("1:"&(COUNTA(_xlfn.ANCHORARRAY($AW$2))+COUNTA(_xlfn.ANCHORARRAY($AX$2)))))-COUNTA(_xlfn.ANCHORARRAY($AW$2))))),1,1))} -> Adagia, Windswept Bastion | BQ2: {=IF(COUNTA(_xlfn.ANCHORARRAY($AY$2))+COUNTA(_xlfn.ANCHORARRAY($AZ$2))=0,"",_xlfn._xlws.SORT(_xlfn.UNIQUE(IF(ROW(INDIRECT("1:"&(COUNTA(_xlfn.ANCHORARRAY($AY$2))+COUNTA(_xlfn.ANCHORARRAY($AZ$2)))))<=COUNTA(_xlfn.ANCHORARRAY($AY$2)),INDEX(_xlfn.ANCHORARRAY($AY$2),ROW(INDIRECT("1:"&(COUNTA(_xlfn.ANCHORARRAY($AY$2))+COUNTA(_xlfn.ANCHORARRAY($AZ$2)))))),INDEX(_xlfn.ANCHORARRAY($AZ$2),ROW(INDIRECT("1:"&(COUNTA(_xlfn.ANCHORARRAY($AY$2))+COUNTA(_xlfn.ANCHORARRAY($AZ$2)))))-COUNTA(_xlfn.ANCHORARRAY($AY$2))))),1,1))} -> #REF! | BS2: {=IF(COUNTA(_xlfn.ANCHORARRAY($BB$2))+COUNTA(_xlfn.ANCHORARRAY($BC$2))=0,"",_xlfn._xlws.SORT(_xlfn.UNIQUE(IF(ROW(INDIRECT("1:"&(COUNTA(_xlfn.ANCHORARRAY($BB$2))+COUNTA(_xlfn.ANCHORARRAY($BC$2)))))<=COUNTA(_xlfn.ANCHORARRAY($BB$2)),INDEX(_xlfn.ANCHORARRAY($BB$2),ROW(INDIRECT("1:"&(COUNTA(_xlfn.ANCHORARRAY($BB$2))+COUNTA(_xlfn.ANCHORARRAY($BC$2)))))),INDEX(_xlfn.ANCHORARRAY($BC$2),ROW(INDIRECT("1:"&(COUNTA(_xlfn.ANCHORARRAY($BB$2))+COUNTA(_xlfn.ANCHORARRAY($BC$2)))))-COUNTA(_xlfn.ANCHORARRAY($BB$2))))),1,1))} -> Adarkar Wastes | BT2: {=IF(COUNTA(_xlfn.ANCHORARRAY($BD$2))+COUNTA(_xlfn.ANCHORARRAY($BE$2))=0,"",_xlfn._xlws.SORT(_xlfn.UNIQUE(IF(ROW(INDIRECT("1:"&(COUNTA(_xlfn.ANCHORARRAY($BD$2))+COUNTA(_xlfn.ANCHORARRAY($BE$2)))))<=COUNTA(_xlfn.ANCHORARRAY($BD$2)),INDEX(_xlfn.ANCHORARRAY($BD$2),ROW(INDIRECT("1:"&(COUNTA(_xlfn.ANCHORARRAY($BD$2))+COUNTA(_xlfn.ANCHORARRAY($BE$2)))))),INDEX(_xlfn.ANCHORARRAY($BE$2),ROW(INDIRECT("1:"&(COUNTA(_xlfn.ANCHORARRAY($BD$2))+COUNTA(_xlfn.ANCHORARRAY($BE$2)))))-COUNTA(_xlfn.ANCHORARRAY($BD$2))))),1,1))} -> Access Tunnel | BU2: {=IF(COUNTA(_xlfn.ANCHORARRAY($BF$2))+COUNTA(_xlfn.ANCHORARRAY($BG$2))=0,"",_xlfn._xlws.SORT(_xlfn.UNIQUE(IF(ROW(INDIRECT("1:"&(COUNTA(_xlfn.ANCHORARRAY($BF$2))+COUNTA(_xlfn.ANCHORARRAY($BG$2)))))<=COUNTA(_xlfn.ANCHORARRAY($BF$2)),INDEX(_xlfn.ANCHORARRAY($BF$2),ROW(INDIRECT("1:"&(COUNTA(_xlfn.ANCHORARRAY($BF$2))+COUNTA(_xlfn.ANCHORARRAY($BG$2)))))),INDEX(_xlfn.ANCHORARRAY($BG$2),ROW(INDIRECT("1:"&(COUNTA(_xlfn.ANCHORARRAY($BF$2))+COUNTA(_xlfn.ANCHORARRAY($BG$2)))))-COUNTA(_xlfn.ANCHORARRAY($BF$2))))),1,1))} -> A Joia do Enigma | BV2: {=IF(COUNTA(_xlfn.ANCHORARRAY($BH$2))+COUNTA(_xlfn.ANCHORARRAY($BI$2))=0,"",_xlfn._xlws.SORT(_xlfn.UNIQUE(IF(ROW(INDIRECT("1:"&(COUNTA(_xlfn.ANCHORARRAY($BH$2))+COUNTA(_xlfn.ANCHORARRAY($BI$2)))))<=COUNTA(_xlfn.ANCHORARRAY($BH$2)),INDEX(_xlfn.ANCHORARRAY($BH$2),ROW(INDIRECT("1:"&(COUNTA(_xlfn.ANCHORARRAY($BH$2))+COUNTA(_xlfn.ANCHORARRAY($BI$2)))))),INDEX(_xlfn.ANCHORARRAY($BI$2),ROW(INDIRECT("1:"&(COUNTA(_xlfn.ANCHORARRAY($BH$2))+COUNTA(_xlfn.ANCHORARRAY($BI$2)))))-COUNTA(_xlfn.ANCHORARRAY($BH$2))))),1,1))} -> Arcane Lighthouse | BW2: {=IF(COUNTA(_xlfn.ANCHORARRAY($BJ$2))+COUNTA(_xlfn.ANCHORARRAY($BK$2))=0,"",_xlfn._xlws.SORT(_xlfn.UNIQUE(IF(ROW(INDIRECT("1:"&(COUNTA(_xlfn.ANCHORARRAY($BJ$2))+COUNTA(_xlfn.ANCHORARRAY($BK$2)))))<=COUNTA(_xlfn.ANCHORARRAY($BJ$2)),INDEX(_xlfn.ANCHORARRAY($BJ$2),ROW(INDIRECT("1:"&(COUNTA(_xlfn.ANCHORARRAY($BJ$2))+COUNTA(_xlfn.ANCHORARRAY($BK$2)))))),INDEX(_xlfn.ANCHORARRAY($BK$2),ROW(INDIRECT("1:"&(COUNTA(_xlfn.ANCHORARRAY($BJ$2))+COUNTA(_xlfn.ANCHORARRAY($BK$2)))))-COUNTA(_xlfn.ANCHORARRAY($BJ$2))))),1,1))} -> Alchemist's Refuge | BX2: {=IF(COUNTA(_xlfn.ANCHORARRAY($BL$2))+COUNTA(_xlfn.ANCHORARRAY($BM$2))=0,"",_xlfn._xlws.SORT(_xlfn.UNIQUE(IF(ROW(INDIRECT("1:"&(COUNTA(_xlfn.ANCHORARRAY($BL$2))+COUNTA(_xlfn.ANCHORARRAY($BM$2)))))<=COUNTA(_xlfn.ANCHORARRAY($BL$2)),INDEX(_xlfn.ANCHORARRAY($BL$2),ROW(INDIRECT("1:"&(COUNTA(_xlfn.ANCHORARRAY($BL$2))+COUNTA(_xlfn.ANCHORARRAY($BM$2)))))),INDEX(_xlfn.ANCHORARRAY($BM$2),ROW(INDIRECT("1:"&(COUNTA(_xlfn.ANCHORARRAY($BL$2))+COUNTA(_xlfn.ANCHORARRAY($BM$2)))))-COUNTA(_xlfn.ANCHORARRAY($BL$2))))),1,1))} -> Adagia, Windswept Bastion | BY2: {=IF(COUNTA(_xlfn.ANCHORARRAY($BN$2))+COUNTA(_xlfn.ANCHORARRAY($BO$2))=0,"",_xlfn._xlws.SORT(_xlfn.UNIQUE(IF(ROW(INDIRECT("1:"&(COUNTA(_xlfn.ANCHORARRAY($BN$2))+COUNTA(_xlfn.ANCHORARRAY($BO$2)))))<=COUNTA(_xlfn.ANCHORARRAY($BN$2)),INDEX(_xlfn.ANCHORARRAY($BN$2),ROW(INDIRECT("1:"&(COUNTA(_xlfn.ANCHORARRAY($BN$2))+COUNTA(_xlfn.ANCHORARRAY($BO$2)))))),INDEX(_xlfn.ANCHORARRAY($BO$2),ROW(INDIRECT("1:"&(COUNTA(_xlfn.ANCHORARRAY($BN$2))+COUNTA(_xlfn.ANCHORARRAY($BO$2)))))-COUNTA(_xlfn.ANCHORARRAY($BN$2))))),1,1))} -> Adagia, Windswept Bastion | BZ2: {=IF(COUNTA(_xlfn.ANCHORARRAY($BP$2))+COUNTA(_xlfn.ANCHORARRAY($BQ$2))=0,"",_xlfn._xlws.SORT(_xlfn.UNIQUE(IF(ROW(INDIRECT("1:"&(COUNTA(_xlfn.ANCHORARRAY($BP$2))+COUNTA(_xlfn.ANCHORARRAY($BQ$2)))))<=COUNTA(_xlfn.ANCHORARRAY($BP$2)),INDEX(_xlfn.ANCHORARRAY($BP$2),ROW(INDIRECT("1:"&(COUNTA(_xlfn.ANCHORARRAY($BP$2))+COUNTA(_xlfn.ANCHORARRAY($BQ$2)))))),INDEX(_xlfn.ANCHORARRAY($BQ$2),ROW(INDIRECT("1:"&(COUNTA(_xlfn.ANCHORARRAY($BP$2))+COUNTA(_xlfn.ANCHORARRAY($BQ$2)))))-COUNTA(_xlfn.ANCHORARRAY($BP$2))))),1,1))} -> Adagia, Windswept Bastion | CB2: {=IF(COUNTA(_xlfn.ANCHORARRAY($BS$2))+COUNTA(_xlfn.ANCHORARRAY($BT$2))=0,"",_xlfn._xlws.SORT(_xlfn.UNIQUE(IF(ROW(INDIRECT("1:"&(COUNTA(_xlfn.ANCHORARRAY($BS$2))+COUNTA(_xlfn.ANCHORARRAY($BT$2)))))<=COUNTA(_xlfn.ANCHORARRAY($BS$2)),INDEX(_xlfn.ANCHORARRAY($BS$2),ROW(INDIRECT("1:"&(COUNTA(_xlfn.ANCHORARRAY($BS$2))+COUNTA(_xlfn.ANCHORARRAY($BT$2)))))),INDEX(_xlfn.ANCHORARRAY($BT$2),ROW(INDIRECT("1:"&(COUNTA(_xlfn.ANCHORARRAY($BS$2))+COUNTA(_xlfn.ANCHORARRAY($BT$2)))))-COUNTA(_xlfn.ANCHORARRAY($BS$2))))),1,1))} -> Access Tunnel | CC2: {=IF(COUNTA(_xlfn.ANCHORARRAY($BU$2))+COUNTA(_xlfn.ANCHORARRAY($BV$2))=0,"",_xlfn._xlws.SORT(_xlfn.UNIQUE(IF(ROW(INDIRECT("1:"&(COUNTA(_xlfn.ANCHORARRAY($BU$2))+COUNTA(_xlfn.ANCHORARRAY($BV$2)))))<=COUNTA(_xlfn.ANCHORARRAY($BU$2)),INDEX(_xlfn.ANCHORARRAY($BU$2),ROW(INDIRECT("1:"&(COUNTA(_xlfn.ANCHORARRAY($BU$2))+COUNTA(_xlfn.ANCHORARRAY($BV$2)))))),INDEX(_xlfn.ANCHORARRAY($BV$2),ROW(INDIRECT("1:"&(COUNTA(_xlfn.ANCHORARRAY($BU$2))+COUNTA(_xlfn.ANCHORARRAY($BV$2)))))-COUNTA(_xlfn.ANCHORARRAY($BU$2))))),1,1))} -> A Joia do Enigma | CD2: {=IF(COUNTA(_xlfn.ANCHORARRAY($BW$2))+COUNTA(_xlfn.ANCHORARRAY($BX$2))=0,"",_xlfn._xlws.SORT(_xlfn.UNIQUE(IF(ROW(INDIRECT("1:"&(COUNTA(_xlfn.ANCHORARRAY($BW$2))+COUNTA(_xlfn.ANCHORARRAY($BX$2)))))<=COUNTA(_xlfn.ANCHORARRAY($BW$2)),INDEX(_xlfn.ANCHORARRAY($BW$2),ROW(INDIRECT("1:"&(COUNTA(_xlfn.ANCHORARRAY($BW$2))+COUNTA(_xlfn.ANCHORARRAY($BX$2)))))),INDEX(_xlfn.ANCHORARRAY($BX$2),ROW(INDIRECT("1:"&(COUNTA(_xlfn.ANCHORARRAY($BW$2))+COUNTA(_xlfn.ANCHORARRAY($BX$2)))))-COUNTA(_xlfn.ANCHORARRAY($BW$2))))),1,1))} -> Adagia, Windswept Bastion | CE2: {=IF(COUNTA(_xlfn.ANCHORARRAY($BY$2))+COUNTA(_xlfn.ANCHORARRAY($BZ$2))=0,"",_xlfn._xlws.SORT(_xlfn.UNIQUE(IF(ROW(INDIRECT("1:"&(COUNTA(_xlfn.ANCHORARRAY($BY$2))+COUNTA(_xlfn.ANCHORARRAY($BZ$2)))))<=COUNTA(_xlfn.ANCHORARRAY($BY$2)),INDEX(_xlfn.ANCHORARRAY($BY$2),ROW(INDIRECT("1:"&(COUNTA(_xlfn.ANCHORARRAY($BY$2))+COUNTA(_xlfn.ANCHORARRAY($BZ$2)))))),INDEX(_xlfn.ANCHORARRAY($BZ$2),ROW(INDIRECT("1:"&(COUNTA(_xlfn.ANCHORARRAY($BY$2))+COUNTA(_xlfn.ANCHORARRAY($BZ$2)))))-COUNTA(_xlfn.ANCHORARRAY($BY$2))))),1,1))} -> Adagia, Windswept Bastion | CG2: {=IF(COUNTA(_xlfn.ANCHORARRAY($CB$2))+COUNTA(_xlfn.ANCHORARRAY($CC$2))=0,"",_xlfn._xlws.SORT(_xlfn.UNIQUE(IF(ROW(INDIRECT("1:"&(COUNTA(_xlfn.ANCHORARRAY($CB$2))+COUNTA(_xlfn.ANCHORARRAY($CC$2)))))<=COUNTA(_xlfn.ANCHORARRAY($CB$2)),INDEX(_xlfn.ANCHORARRAY($CB$2),ROW(INDIRECT("1:"&(COUNTA(_xlfn.ANCHORARRAY($CB$2))+COUNTA(_xlfn.ANCHORARRAY($CC$2)))))),INDEX(_xlfn.ANCHORARRAY($CC$2),ROW(INDIRECT("1:"&(COUNTA(_xlfn.ANCHORARRAY($CB$2))+COUNTA(_xlfn.ANCHORARRAY($CC$2)))))-COUNTA(_xlfn.ANCHORARRAY($CB$2))))),1,1))} -> A Joia do Enigma | CH2: {=IF(COUNTA(_xlfn.ANCHORARRAY($CD$2))+COUNTA(_xlfn.ANCHORARRAY($CE$2))=0,"",_xlfn._xlws.SORT(_xlfn.UNIQUE(IF(ROW(INDIRECT("1:"&(COUNTA(_xlfn.ANCHORARRAY($CD$2))+COUNTA(_xlfn.ANCHORARRAY($CE$2)))))<=COUNTA(_xlfn.ANCHORARRAY($CD$2)),INDEX(_xlfn.ANCHORARRAY($CD$2),ROW(INDIRECT("1:"&(COUNTA(_xlfn.ANCHORARRAY($CD$2))+COUNTA(_xlfn.ANCHORARRAY($CE$2)))))),INDEX(_xlfn.ANCHORARRAY($CE$2),ROW(INDIRECT("1:"&(COUNTA(_xlfn.ANCHORARRAY($CD$2))+COUNTA(_xlfn.ANCHORARRAY($CE$2)))))-COUNTA(_xlfn.ANCHORARRAY($CD$2))))),1,1))} -> Adagia, Windswept Bastion | CJ2: {=IF(COUNTA(_xlfn.ANCHORARRAY($CG$2))+COUNTA(_xlfn.ANCHORARRAY($CH$2))=0,"",_xlfn._xlws.SORT(_xlfn.UNIQUE(IF(ROW(INDIRECT("1:"&(COUNTA(_xlfn.ANCHORARRAY($CG$2))+COUNTA(_xlfn.ANCHORARRAY($CH$2)))))<=COUNTA(_xlfn.ANCHORARRAY($CG$2)),INDEX(_xlfn.ANCHORARRAY($CG$2),ROW(INDIRECT("1:"&(COUNTA(_xlfn.ANCHORARRAY($CG$2))+COUNTA(_xlfn.ANCHORARRAY($CH$2)))))),INDEX(_xlfn.ANCHORARRAY($CH$2),ROW(INDIRECT("1:"&(COUNTA(_xlfn.ANCHORARRAY($CG$2))+COUNTA(_xlfn.ANCHORARRAY($CH$2)))))-COUNTA(_xlfn.ANCHORARRAY($CG$2))))),1,1))} -> A Joia do Enigma
A3: =IFERROR(INDEX($S$3:$S$200, MATCH($C3, $I$3:$I$200, 0)), "") -> 2 | B3: =COUNTIF(U:AX,G3) -> 1 | C3: =IFERROR( INDEX($U$1:$AX$1, MATCH(TRUE, CHOOSE({1;2;3;4;5;6;7;8;9;10;11;12;13;14;15;16;17;18;19;20;21;22;23;24;25;26;27;28;29;30;31;32}, COUNTIFS($U$2:$U$200,$G3)>0, COUNTIFS($V$2:$V$200,$G3)>0, COUNTIFS($W$2:$W$200,$G3)>0, COUNTIFS($X$2:$X$200,$G3)>0, COUNTIFS($Y$2:$Y$200,$G3)>0, COUNTIFS($Z$2:$Z$200,$G3)>0, COUNTIFS($AA$2:$AA$200,$G3)>0, COUNTIFS($AB$2:$AB$200,$G3)>0, COUNTIFS($AC$2:$AC$200,$G3)>0, COUNTIFS($AD$2:$AD$200,$G3)>0, COUNTIFS($AE$2:$AE$200,$G3)>0, COUNTIFS($AF$2:$AF$200,$G3)>0, COUNTIFS($AG$2:$AG$200,$G3)>0, COUNTIFS($AH$2:$AH$200,$G3)>0, COUNTIFS($AI$2:$AI$200,$G3)>0, COUNTIFS($AJ$2:$AJ$200,$G3)>0, COUNTIFS($AK$2:$AK$200,$G3)>0, COUNTIFS($AL$2:$AL$200,$G3)>0, COUNTIFS($AM$2:$AM$200,$G3)>0, COUNTIFS($AN$2:$AN$200,$G3)>0, COUNTIFS($AO$2:$AO$200,$G3)>0, COUNTIFS($AP$2:$AP$200,$G3)>0, COUNTIFS($AQ$2:$AQ$200,$G3)>0, COUNTIFS($AR$2:$AR$200,$G3)>0, COUNTIFS($AS$2:$AS$200,$G3)>0, COUNTIFS($AT$2:$AT$200,$G3)>0, COUNTIFS($AU$2:$AU$200,$G3)>0, COUNTIFS($AV$2:$AV$200,$G3)>0, COUNTIFS($AW$2:$AW$200,$G3)>0, COUNTIFS($AX$2:$AX$200,$G3)>0 ), 0) ), "") -> Rani | D3: {=IFERROR( INDEX( _xlfn._xlws.FILTER($U$1:$AX$1, TRANSPOSE( CHOOSE({1;2;3;4;5;6;7;8;9;10;11;12;13;14;15;16;17;18;19;20;21;22;23;24;25;26;27;28;29;30}, COUNTIFS($U$2:$U$200,$G3)>0, COUNTIFS($V$2:$V$200,$G3)>0, COUNTIFS($W$2:$W$200,$G3)>0, COUNTIFS($X$2:$X$200,$G3)>0, COUNTIFS($Y$2:$Y$200,$G3)>0, COUNTIFS($Z$2:$Z$200,$G3)>0, COUNTIFS($AA$2:$AA$200,$G3)>0, COUNTIFS($AB$2:$AB$200,$G3)>0, COUNTIFS($AC$2:$AC$200,$G3)>0, COUNTIFS($AD$2:$AD$200,$G3)>0, COUNTIFS($AE$2:$AE$200,$G3)>0, COUNTIFS($AF$2:$AF$200,$G3)>0, COUNTIFS($AG$2:$AG$200,$G3)>0, COUNTIFS($AH$2:$AH$200,$G3)>0, COUNTIFS($AI$2:$AI$200,$G3)>0, COUNTIFS($AJ$2:$AJ$200,$G3)>0, COUNTIFS($AK$2:$AK$200,$G3)>0, COUNTIFS($AL$2:$AL$200,$G3)>0, COUNTIFS($AM$2:$AM$200,$G3)>0, COUNTIFS($AN$2:$AN$200,$G3)>0, COUNTIFS($AO$2:$AO$200,$G3)>0, COUNTIFS($AP$2:$AP$200,$G3)>0, COUNTIFS($AQ$2:$AQ$200,$G3)>0, COUNTIFS($AR$2:$AR$200,$G3)>0, COUNTIFS($AS$2:$AS$200,$G3)>0, COUNTIFS($AT$2:$AT$200,$G3)>0, COUNTIFS($AU$2:$AU$200,$G3)>0, COUNTIFS($AV$2:$AV$200,$G3)>0, COUNTIFS($AW$2:$AW$200,$G3)>0, COUNTIFS($AX$2:$AX$200,$G3)>0 )), ), 2 ), "")} | E3: {=IFERROR( INDEX( _xlfn._xlws.FILTER($U$1:$AX$1, TRANSPOSE( CHOOSE({1;2;3;4;5;6;7;8;9;10;11;12;13;14;15;16;17;18;19;20;21;22;23;24;25;26;27;28;29;30}, COUNTIFS($U$2:$U$200,$G3)>0, COUNTIFS($V$2:$V$200,$G3)>0, COUNTIFS($W$2:$W$200,$G3)>0, COUNTIFS($X$2:$X$200,$G3)>0, COUNTIFS($Y$2:$Y$200,$G3)>0, COUNTIFS($Z$2:$Z$200,$G3)>0, COUNTIFS($AA$2:$AA$200,$G3)>0, COUNTIFS($AB$2:$AB$200,$G3)>0, COUNTIFS($AC$2:$AC$200,$G3)>0, COUNTIFS($AD$2:$AD$200,$G3)>0, COUNTIFS($AE$2:$AE$200,$G3)>0, COUNTIFS($AF$2:$AF$200,$G3)>0, COUNTIFS($AG$2:$AG$200,$G3)>0, COUNTIFS($AH$2:$AH$200,$G3)>0, COUNTIFS($AI$2:$AI$200,$G3)>0, COUNTIFS($AJ$2:$AJ$200,$G3)>0, COUNTIFS($AK$2:$AK$200,$G3)>0, COUNTIFS($AL$2:$AL$200,$G3)>0, COUNTIFS($AM$2:$AM$200,$G3)>0, COUNTIFS($AN$2:$AN$200,$G3)>0, COUNTIFS($AO$2:$AO$200,$G3)>0, COUNTIFS($AP$2:$AP$200,$G3)>0, COUNTIFS($AQ$2:$AQ$200,$G3)>0, COUNTIFS($AR$2:$AR$200,$G3)>0, COUNTIFS($AS$2:$AS$200,$G3)>0, COUNTIFS($AT$2:$AT$200,$G3)>0, COUNTIFS($AU$2:$AU$200,$G3)>0, COUNTIFS($AV$2:$AV$200,$G3)>0, COUNTIFS($AW$2:$AW$200,$G3)>0, COUNTIFS($AX$2:$AX$200,$G3)>0 )), ), 3 ), "")} | F3: {=IFERROR( INDEX( _xlfn._xlws.FILTER($U$1:$AX$1, TRANSPOSE( CHOOSE({1;2;3;4;5;6;7;8;9;10;11;12;13;14;15;16;17;18;19;20;21;22;23;24;25;26;27;28;29;30}, COUNTIFS($U$2:$U$200,$G3)>0, COUNTIFS($V$2:$V$200,$G3)>0, COUNTIFS($W$2:$W$200,$G3)>0, COUNTIFS($X$2:$X$200,$G3)>0, COUNTIFS($Y$2:$Y$200,$G3)>0, COUNTIFS($Z$2:$Z$200,$G3)>0, COUNTIFS($AA$2:$AA$200,$G3)>0, COUNTIFS($AB$2:$AB$200,$G3)>0, COUNTIFS($AC$2:$AC$200,$G3)>0, COUNTIFS($AD$2:$AD$200,$G3)>0, COUNTIFS($AE$2:$AE$200,$G3)>0, COUNTIFS($AF$2:$AF$200,$G3)>0, COUNTIFS($AG$2:$AG$200,$G3)>0, COUNTIFS($AH$2:$AH$200,$G3)>0, COUNTIFS($AI$2:$AI$200,$G3)>0, COUNTIFS($AJ$2:$AJ$200,$G3)>0, COUNTIFS($AK$2:$AK$200,$G3)>0, COUNTIFS($AL$2:$AL$200,$G3)>0, COUNTIFS($AM$2:$AM$200,$G3)>0, COUNTIFS($AN$2:$AN$200,$G3)>0, COUNTIFS($AO$2:$AO$200,$G3)>0, COUNTIFS($AP$2:$AP$200,$G3)>0, COUNTIFS($AQ$2:$AQ$200,$G3)>0, COUNTIFS($AR$2:$AR$200,$G3)>0, COUNTIFS($AS$2:$AS$200,$G3)>0, COUNTIFS($AT$2:$AT$200,$G3)>0, COUNTIFS($AU$2:$AU$200,$G3)>0, COUNTIFS($AV$2:$AV$200,$G3)>0, COUNTIFS($AW$2:$AW$200,$G3)>0, COUNTIFS($AX$2:$AX$200,$G3)>0 )), ), 4 ), "")} | G3: Access Tunnel | I3: Narset | J3: =Narset!G2 -> 29 | K3: Sim | L3: Sim | M3: Sim | N3: Não | O3: Não | P3: Mill | Q3: Combate | R3: Mill e Tokens | S3: =IF(J3<6,"5",IF(J3<11,"4",IF(J3<16,"3",IF(J3<31,"2","1")))) -> 2 | U3: Bojuka Bog | V3: Aura Mutation | W3: Aligned Heart | X3: Arwen, Weaver of Hope | Y3: Autoridade dos Cônsules | Z3: Bojuka Bog | AA3: Call to the Kindred | AB3: Grave Pact | AC3: Kozilek, the Broken Reality | AD3: Crisol dos Mundos | AE3: Chimil, o Sol Interior | AF3: Arid Mesa | AG3: Drowned Catacomb | AH3: Bojuka Bog | AI3: Cloud, Midgar Mercenary | AJ3: Elspeth, Sun's Champion | AK3: Obelisco de Obsidiana | AL3: Dionus, Elvish Archdruid | AM3: Mistrise Village | AN3: Jetmir's Garden | AO3: Baral, Chief of Compliance | AP3: Jidoor, Aristocratic Capital // Overture | AQ3: Chandra's Ignition | AR3: Daretti, Ingenious Iconoclast | AS3: Illustrious Wanderglyph | AT3: Lagoa Espelhada | AU3: Teyo, Geometric Tactician | AV3: Emergency Eject | AX3: Ancient Den | BB3: Aura Mutation | BC3: Aligned Heart | BD3: Ascensão do Avernus | BE3: Beast Within | BF3: Crisol dos Mundos | BG3: Amphibian Downpour | BH3: Bojuka Bog | BI3: Cloud, Midgar Mercenary | BJ3: Dionus, Elvish Archdruid | BK3: Emrakul, um Novo Mundo | BL3: Baral, Chief of Compliance | BM3: Bugenhagen, Wise Elder | BN3: Dollmaker's Shop // Porcelain Gallery | BO3: Árbitro Silencioso | BP3: Ancient Den | BS3: Aligned Heart | BT3: Ancient Greenwarden | BU3: Amphibian Downpour | BV3: Bojuka Bog | BW3: Caverna das Almas | BX3: Afundar em Estupor | BY3: Alchemist's Refuge | BZ3: Ancient Den | CB3: Adarkar Wastes | CC3: Amphibian Downpour | CD3: Afundar em Estupor | CE3: Alchemist's Refuge | CG3: Access Tunnel | CH3: Afundar em Estupor | CJ3: Access Tunnel
A4: =IFERROR(INDEX($S$3:$S$200, MATCH($C4, $I$3:$I$200, 0)), "") -> 5 | B4: =COUNTIF(U:AX,G4) -> 3 | C4: =IFERROR( INDEX($U$1:$AX$1, MATCH(TRUE, CHOOSE({1;2;3;4;5;6;7;8;9;10;11;12;13;14;15;16;17;18;19;20;21;22;23;24;25;26;27;28;29;30;31;32}, COUNTIFS($U$2:$U$200,$G4)>0, COUNTIFS($V$2:$V$200,$G4)>0, COUNTIFS($W$2:$W$200,$G4)>0, COUNTIFS($X$2:$X$200,$G4)>0, COUNTIFS($Y$2:$Y$200,$G4)>0, COUNTIFS($Z$2:$Z$200,$G4)>0, COUNTIFS($AA$2:$AA$200,$G4)>0, COUNTIFS($AB$2:$AB$200,$G4)>0, COUNTIFS($AC$2:$AC$200,$G4)>0, COUNTIFS($AD$2:$AD$200,$G4)>0, COUNTIFS($AE$2:$AE$200,$G4)>0, COUNTIFS($AF$2:$AF$200,$G4)>0, COUNTIFS($AG$2:$AG$200,$G4)>0, COUNTIFS($AH$2:$AH$200,$G4)>0, COUNTIFS($AI$2:$AI$200,$G4)>0, COUNTIFS($AJ$2:$AJ$200,$G4)>0, COUNTIFS($AK$2:$AK$200,$G4)>0, COUNTIFS($AL$2:$AL$200,$G4)>0, COUNTIFS($AM$2:$AM$200,$G4)>0, COUNTIFS($AN$2:$AN$200,$G4)>0, COUNTIFS($AO$2:$AO$200,$G4)>0, COUNTIFS($AP$2:$AP$200,$G4)>0, COUNTIFS($AQ$2:$AQ$200,$G4)>0, COUNTIFS($AR$2:$AR$200,$G4)>0, COUNTIFS($AS$2:$AS$200,$G4)>0, COUNTIFS($AT$2:$AT$200,$G4)>0, COUNTIFS($AU$2:$AU$200,$G4)>0, COUNTIFS($AV$2:$AV$200,$G4)>0, COUNTIFS($AW$2:$AW$200,$G4)>0, COUNTIFS($AX$2:$AX$200,$G4)>0 ), 0) ), "") -> Breya | D4: {=IFERROR( INDEX( _xlfn._xlws.FILTER($U$1:$AX$1, TRANSPOSE( CHOOSE({1;2;3;4;5;6;7;8;9;10;11;12;13;14;15;16;17;18;19;20;21;22;23;24;25;26;27;28;29;30}, COUNTIFS($U$2:$U$200,$G4)>0, COUNTIFS($V$2:$V$200,$G4)>0, COUNTIFS($W$2:$W$200,$G4)>0, COUNTIFS($X$2:$X$200,$G4)>0, COUNTIFS($Y$2:$Y$200,$G4)>0, COUNTIFS($Z$2:$Z$200,$G4)>0, COUNTIFS($AA$2:$AA$200,$G4)>0, COUNTIFS($AB$2:$AB$200,$G4)>0, COUNTIFS($AC$2:$AC$200,$G4)>0, COUNTIFS($AD$2:$AD$200,$G4)>0, COUNTIFS($AE$2:$AE$200,$G4)>0, COUNTIFS($AF$2:$AF$200,$G4)>0, COUNTIFS($AG$2:$AG$200,$G4)>0, COUNTIFS($AH$2:$AH$200,$G4)>0, COUNTIFS($AI$2:$AI$200,$G4)>0, COUNTIFS($AJ$2:$AJ$200,$G4)>0, COUNTIFS($AK$2:$AK$200,$G4)>0, COUNTIFS($AL$2:$AL$200,$G4)>0, COUNTIFS($AM$2:$AM$200,$G4)>0, COUNTIFS($AN$2:$AN$200,$G4)>0, COUNTIFS($AO$2:$AO$200,$G4)>0, COUNTIFS($AP$2:$AP$200,$G4)>0, COUNTIFS($AQ$2:$AQ$200,$G4)>0, COUNTIFS($AR$2:$AR$200,$G4)>0, COUNTIFS($AS$2:$AS$200,$G4)>0, COUNTIFS($AT$2:$AT$200,$G4)>0, COUNTIFS($AU$2:$AU$200,$G4)>0, COUNTIFS($AV$2:$AV$200,$G4)>0, COUNTIFS($AW$2:$AW$200,$G4)>0, COUNTIFS($AX$2:$AX$200,$G4)>0 )), ), 2 ), "")} -> Alela | E4: {=IFERROR( INDEX( _xlfn._xlws.FILTER($U$1:$AX$1, TRANSPOSE( CHOOSE({1;2;3;4;5;6;7;8;9;10;11;12;13;14;15;16;17;18;19;20;21;22;23;24;25;26;27;28;29;30}, COUNTIFS($U$2:$U$200,$G4)>0, COUNTIFS($V$2:$V$200,$G4)>0, COUNTIFS($W$2:$W$200,$G4)>0, COUNTIFS($X$2:$X$200,$G4)>0, COUNTIFS($Y$2:$Y$200,$G4)>0, COUNTIFS($Z$2:$Z$200,$G4)>0, COUNTIFS($AA$2:$AA$200,$G4)>0, COUNTIFS($AB$2:$AB$200,$G4)>0, COUNTIFS($AC$2:$AC$200,$G4)>0, COUNTIFS($AD$2:$AD$200,$G4)>0, COUNTIFS($AE$2:$AE$200,$G4)>0, COUNTIFS($AF$2:$AF$200,$G4)>0, COUNTIFS($AG$2:$AG$200,$G4)>0, COUNTIFS($AH$2:$AH$200,$G4)>0, COUNTIFS($AI$2:$AI$200,$G4)>0, COUNTIFS($AJ$2:$AJ$200,$G4)>0, COUNTIFS($AK$2:$AK$200,$G4)>0, COUNTIFS($AL$2:$AL$200,$G4)>0, COUNTIFS($AM$2:$AM$200,$G4)>0, COUNTIFS($AN$2:$AN$200,$G4)>0, COUNTIFS($AO$2:$AO$200,$G4)>0, COUNTIFS($AP$2:$AP$200,$G4)>0, COUNTIFS($AQ$2:$AQ$200,$G4)>0, COUNTIFS($AR$2:$AR$200,$G4)>0, COUNTIFS($AS$2:$AS$200,$G4)>0, COUNTIFS($AT$2:$AT$200,$G4)>0, COUNTIFS($AU$2:$AU$200,$G4)>0, COUNTIFS($AV$2:$AV$200,$G4)>0, COUNTIFS($AW$2:$AW$200,$G4)>0, COUNTIFS($AX$2:$AX$200,$G4)>0 )), ), 3 ), "")} -> Modular | F4: {=IFERROR( INDEX( _xlfn._xlws.FILTER($U$1:$AX$1, TRANSPOSE( CHOOSE({1;2;3;4;5;6;7;8;9;10;11;12;13;14;15;16;17;18;19;20;21;22;23;24;25;26;27;28;29;30}, COUNTIFS($U$2:$U$200,$G4)>0, COUNTIFS($V$2:$V$200,$G4)>0, COUNTIFS($W$2:$W$200,$G4)>0, COUNTIFS($X$2:$X$200,$G4)>0, COUNTIFS($Y$2:$Y$200,$G4)>0, COUNTIFS($Z$2:$Z$200,$G4)>0, COUNTIFS($AA$2:$AA$200,$G4)>0, COUNTIFS($AB$2:$AB$200,$G4)>0, COUNTIFS($AC$2:$AC$200,$G4)>0, COUNTIFS($AD$2:$AD$200,$G4)>0, COUNTIFS($AE$2:$AE$200,$G4)>0, COUNTIFS($AF$2:$AF$200,$G4)>0, COUNTIFS($AG$2:$AG$200,$G4)>0, COUNTIFS($AH$2:$AH$200,$G4)>0, COUNTIFS($AI$2:$AI$200,$G4)>0, COUNTIFS($AJ$2:$AJ$200,$G4)>0, COUNTIFS($AK$2:$AK$200,$G4)>0, COUNTIFS($AL$2:$AL$200,$G4)>0, COUNTIFS($AM$2:$AM$200,$G4)>0, COUNTIFS($AN$2:$AN$200,$G4)>0, COUNTIFS($AO$2:$AO$200,$G4)>0, COUNTIFS($AP$2:$AP$200,$G4)>0, COUNTIFS($AQ$2:$AQ$200,$G4)>0, COUNTIFS($AR$2:$AR$200,$G4)>0, COUNTIFS($AS$2:$AS$200,$G4)>0, COUNTIFS($AT$2:$AT$200,$G4)>0, COUNTIFS($AU$2:$AU$200,$G4)>0, COUNTIFS($AV$2:$AV$200,$G4)>0, COUNTIFS($AW$2:$AW$200,$G4)>0, COUNTIFS($AX$2:$AX$200,$G4)>0 )), ), 4 ), "")} | G4: Adagia, Windswept Bastion | I4: Baylen | J4: =Baylen!G2 -> 27 | K4: Sim | L4: Não | M4: Sim | N4: Não | O4: Sim | P4: Voltron | Q4: Combate | R4: Muitos Tokens | S4: =IF(J4<6,"5",IF(J4<11,"4",IF(J4<16,"3",IF(J4<31,"2","1")))) -> 2 | U4: Broadside Bombardiers | V4: Boros Charm | W4: Clifftop Retreat | X4: Cankerbloom | Y4: Bojuka Bog | Z4: Bothersome Quasit | AA4: Deeproot Historian | AB4: Horizon Explorer | AC4: Mistrise Village | AD4: Delighted Halfling | AE4: Extinguisher Battleship | AF4: Batwing Brume | AG4: Faerie Slumber Party | AH4: Burnt Offering | AI4: Espada da Riqueza e do Poder | AJ4: Freyalise, Llanowar's Fury | AK4: Shaku da Honra Desgastada | AL4: Evendo, Waking Haven | AM4: Planetary Annihilation | AN4: Raffine's Tower | AO4: Careful Study | AP4: Scour for Scrap | AQ4: High-Society Hunter | AR4: Reflecting Pool | AS4: Scattered Groves | AT4: Olho de Ojer Taq | AV4: Homeward Path | AX4: Arcbound Fiend | BB4: Back in Town | BC4: Ardbert, Warrior of Darkness | BD4: Autoridade dos Cônsules | BE4: Call to the Kindred | BF4: Delighted Halfling | BG4: Arid Mesa | BH4: Burnt Offering | BI4: Commodore Guff | BJ4: Evendo, Waking Haven | BK4: Jetmir's Garden | BL4: Careful Study | BM4: Chandra's Ignition | BN4: Illustrious Wanderglyph | BO4: Emergency Eject | BP4: Arcbound Fiend | BS4: Ardbert, Warrior of Darkness | BT4: Ascensão do Avernus | BU4: Ancient Tomb | BV4: Burnt Offering | BW4: Dionus, Elvish Archdruid | BX4: Baral, Chief of Compliance | BY4: Árbitro Silencioso | BZ4: Arcbound Fiend | CB4: Aligned Heart | CC4: Ancient Tomb | CD4: Alchemist's Refuge | CE4: Ancient Den | CG4: Adarkar Wastes | CH4: Alchemist's Refuge | CJ4: Adagia, Windswept Bastion
A5: =IFERROR(INDEX($S$3:$S$200, MATCH($C5, $I$3:$I$200, 0)), "") -> 2 | B5: =COUNTIF(U:AX,G5) -> 1 | C5: =IFERROR( INDEX($U$1:$AX$1, MATCH(TRUE, CHOOSE({1;2;3;4;5;6;7;8;9;10;11;12;13;14;15;16;17;18;19;20;21;22;23;24;25;26;27;28;29;30;31;32}, COUNTIFS($U$2:$U$200,$G5)>0, COUNTIFS($V$2:$V$200,$G5)>0, COUNTIFS($W$2:$W$200,$G5)>0, COUNTIFS($X$2:$X$200,$G5)>0, COUNTIFS($Y$2:$Y$200,$G5)>0, COUNTIFS($Z$2:$Z$200,$G5)>0, COUNTIFS($AA$2:$AA$200,$G5)>0, COUNTIFS($AB$2:$AB$200,$G5)>0, COUNTIFS($AC$2:$AC$200,$G5)>0, COUNTIFS($AD$2:$AD$200,$G5)>0, COUNTIFS($AE$2:$AE$200,$G5)>0, COUNTIFS($AF$2:$AF$200,$G5)>0, COUNTIFS($AG$2:$AG$200,$G5)>0, COUNTIFS($AH$2:$AH$200,$G5)>0, COUNTIFS($AI$2:$AI$200,$G5)>0, COUNTIFS($AJ$2:$AJ$200,$G5)>0, COUNTIFS($AK$2:$AK$200,$G5)>0, COUNTIFS($AL$2:$AL$200,$G5)>0, COUNTIFS($AM$2:$AM$200,$G5)>0, COUNTIFS($AN$2:$AN$200,$G5)>0, COUNTIFS($AO$2:$AO$200,$G5)>0, COUNTIFS($AP$2:$AP$200,$G5)>0, COUNTIFS($AQ$2:$AQ$200,$G5)>0, COUNTIFS($AR$2:$AR$200,$G5)>0, COUNTIFS($AS$2:$AS$200,$G5)>0, COUNTIFS($AT$2:$AT$200,$G5)>0, COUNTIFS($AU$2:$AU$200,$G5)>0, COUNTIFS($AV$2:$AV$200,$G5)>0, COUNTIFS($AW$2:$AW$200,$G5)>0, COUNTIFS($AX$2:$AX$200,$G5)>0 ), 0) ), "") -> Narset | D5: {=IFERROR( INDEX( _xlfn._xlws.FILTER($U$1:$AX$1, TRANSPOSE( CHOOSE({1;2;3;4;5;6;7;8;9;10;11;12;13;14;15;16;17;18;19;20;21;22;23;24;25;26;27;28;29;30}, COUNTIFS($U$2:$U$200,$G5)>0, COUNTIFS($V$2:$V$200,$G5)>0, COUNTIFS($W$2:$W$200,$G5)>0, COUNTIFS($X$2:$X$200,$G5)>0, COUNTIFS($Y$2:$Y$200,$G5)>0, COUNTIFS($Z$2:$Z$200,$G5)>0, COUNTIFS($AA$2:$AA$200,$G5)>0, COUNTIFS($AB$2:$AB$200,$G5)>0, COUNTIFS($AC$2:$AC$200,$G5)>0, COUNTIFS($AD$2:$AD$200,$G5)>0, COUNTIFS($AE$2:$AE$200,$G5)>0, COUNTIFS($AF$2:$AF$200,$G5)>0, COUNTIFS($AG$2:$AG$200,$G5)>0, COUNTIFS($AH$2:$AH$200,$G5)>0, COUNTIFS($AI$2:$AI$200,$G5)>0, COUNTIFS($AJ$2:$AJ$200,$G5)>0, COUNTIFS($AK$2:$AK$200,$G5)>0, COUNTIFS($AL$2:$AL$200,$G5)>0, COUNTIFS($AM$2:$AM$200,$G5)>0, COUNTIFS($AN$2:$AN$200,$G5)>0, COUNTIFS($AO$2:$AO$200,$G5)>0, COUNTIFS($AP$2:$AP$200,$G5)>0, COUNTIFS($AQ$2:$AQ$200,$G5)>0, COUNTIFS($AR$2:$AR$200,$G5)>0, COUNTIFS($AS$2:$AS$200,$G5)>0, COUNTIFS($AT$2:$AT$200,$G5)>0, COUNTIFS($AU$2:$AU$200,$G5)>0, COUNTIFS($AV$2:$AV$200,$G5)>0, COUNTIFS($AW$2:$AW$200,$G5)>0, COUNTIFS($AX$2:$AX$200,$G5)>0 )), ), 2 ), "")} | E5: {=IFERROR( INDEX( _xlfn._xlws.FILTER($U$1:$AX$1, TRANSPOSE( CHOOSE({1;2;3;4;5;6;7;8;9;10;11;12;13;14;15;16;17;18;19;20;21;22;23;24;25;26;27;28;29;30}, COUNTIFS($U$2:$U$200,$G5)>0, COUNTIFS($V$2:$V$200,$G5)>0, COUNTIFS($W$2:$W$200,$G5)>0, COUNTIFS($X$2:$X$200,$G5)>0, COUNTIFS($Y$2:$Y$200,$G5)>0, COUNTIFS($Z$2:$Z$200,$G5)>0, COUNTIFS($AA$2:$AA$200,$G5)>0, COUNTIFS($AB$2:$AB$200,$G5)>0, COUNTIFS($AC$2:$AC$200,$G5)>0, COUNTIFS($AD$2:$AD$200,$G5)>0, COUNTIFS($AE$2:$AE$200,$G5)>0, COUNTIFS($AF$2:$AF$200,$G5)>0, COUNTIFS($AG$2:$AG$200,$G5)>0, COUNTIFS($AH$2:$AH$200,$G5)>0, COUNTIFS($AI$2:$AI$200,$G5)>0, COUNTIFS($AJ$2:$AJ$200,$G5)>0, COUNTIFS($AK$2:$AK$200,$G5)>0, COUNTIFS($AL$2:$AL$200,$G5)>0, COUNTIFS($AM$2:$AM$200,$G5)>0, COUNTIFS($AN$2:$AN$200,$G5)>0, COUNTIFS($AO$2:$AO$200,$G5)>0, COUNTIFS($AP$2:$AP$200,$G5)>0, COUNTIFS($AQ$2:$AQ$200,$G5)>0, COUNTIFS($AR$2:$AR$200,$G5)>0, COUNTIFS($AS$2:$AS$200,$G5)>0, COUNTIFS($AT$2:$AT$200,$G5)>0, COUNTIFS($AU$2:$AU$200,$G5)>0, COUNTIFS($AV$2:$AV$200,$G5)>0, COUNTIFS($AW$2:$AW$200,$G5)>0, COUNTIFS($AX$2:$AX$200,$G5)>0 )), ), 3 ), "")} | F5: {=IFERROR( INDEX( _xlfn._xlws.FILTER($U$1:$AX$1, TRANSPOSE( CHOOSE({1;2;3;4;5;6;7;8;9;10;11;12;13;14;15;16;17;18;19;20;21;22;23;24;25;26;27;28;29;30}, COUNTIFS($U$2:$U$200,$G5)>0, COUNTIFS($V$2:$V$200,$G5)>0, COUNTIFS($W$2:$W$200,$G5)>0, COUNTIFS($X$2:$X$200,$G5)>0, COUNTIFS($Y$2:$Y$200,$G5)>0, COUNTIFS($Z$2:$Z$200,$G5)>0, COUNTIFS($AA$2:$AA$200,$G5)>0, COUNTIFS($AB$2:$AB$200,$G5)>0, COUNTIFS($AC$2:$AC$200,$G5)>0, COUNTIFS($AD$2:$AD$200,$G5)>0, COUNTIFS($AE$2:$AE$200,$G5)>0, COUNTIFS($AF$2:$AF$200,$G5)>0, COUNTIFS($AG$2:$AG$200,$G5)>0, COUNTIFS($AH$2:$AH$200,$G5)>0, COUNTIFS($AI$2:$AI$200,$G5)>0, COUNTIFS($AJ$2:$AJ$200,$G5)>0, COUNTIFS($AK$2:$AK$200,$G5)>0, COUNTIFS($AL$2:$AL$200,$G5)>0, COUNTIFS($AM$2:$AM$200,$G5)>0, COUNTIFS($AN$2:$AN$200,$G5)>0, COUNTIFS($AO$2:$AO$200,$G5)>0, COUNTIFS($AP$2:$AP$200,$G5)>0, COUNTIFS($AQ$2:$AQ$200,$G5)>0, COUNTIFS($AR$2:$AR$200,$G5)>0, COUNTIFS($AS$2:$AS$200,$G5)>0, COUNTIFS($AT$2:$AT$200,$G5)>0, COUNTIFS($AU$2:$AU$200,$G5)>0, COUNTIFS($AV$2:$AV$200,$G5)>0, COUNTIFS($AW$2:$AW$200,$G5)>0, COUNTIFS($AX$2:$AX$200,$G5)>0 )), ), 4 ), "")} | G5: Adarkar Wastes | I5: Tayam | J5: =Tayam!G2 -> 31 | K5: Sim | L5: Não | M5: Não | N5: Sim | O5: Sim | P5: Combate | Q5: Combo | R5: Counters, tudo drop 3- | S5: =IF(J5<6,"5",IF(J5<11,"4",IF(J5<16,"3",IF(J5<31,"2","1")))) -> 1 | U5: Emberwilde Captain | V5: Brushland | W5: Full Throttle | X5: Canopy Vista | Y5: Enduring Innocence | Z5: Counterspell | AA5: Harvest Season | AB5: Jadar, Ghoulcaller of Nephalia | AC5: Mox Tantalite | AD5: Entomb | AE5: Gerrard's Hourglass Pendant | AF5: Luxury Suite | AG5: Louisoix's Sacrifice | AH5: Diário de Tarrian | AI5: Espada de Banquete e Fome | AJ5: Karn Liberated | AK5: Uthros, Titanic Godcore | AL5: Nissa, Resurgent Animist | AM5: Ulamog, o Profanador | AN5: Sliver Gravemother | AO5: Collector's Vault | AP5: Season of Weaving | AQ5: Jenova, Ancient Calamity | AS5: Stridehangar Automaton | AT5: Renewed Solidarity | AX5: Arcbound Overseer | BB5: Bojuka Bog | BC5: Arwen, Weaver of Hope | BD5: Bojuka Bog | BE5: Deeproot Historian | BF5: Emrakul, um Novo Mundo | BG5: Batwing Brume | BH5: Creeping Tar Pit | BI5: Elspeth, Sun's Champion | BJ5: Matoya, Archon Elder | BK5: Mistrise Village | BL5: Collector's Vault | BM5: Daretti, Ingenious Iconoclast | BN5: Lagoa Espelhada | BO5: Homeward Path | BP5: Arcbound Overseer | BS5: Artifact Mutation | BT5: Autoridade dos Cônsules | BU5: Arid Mesa | BV5: Cid, Freeflier Pilot | BW5: Emrakul, um Novo Mundo | BX5: Bugenhagen, Wise Elder | BY5: Dollmaker's Shop // Porcelain Gallery | BZ5: Arcbound Overseer | CB5: Ancient Greenwarden | CC5: Arcane Lighthouse | CD5: Baral, Chief of Compliance | CE5: Árbitro Silencioso | CG5: Aligned Heart | CH5: Ancient Den | CJ5: Adarkar Wastes
A6: =IFERROR(INDEX($S$3:$S$200, MATCH($C6, $I$3:$I$200, 0)), "") -> 4 | B6: =COUNTIF(U:AX,G6) -> 1 | C6: =IFERROR( INDEX($U$1:$AX$1, MATCH(TRUE, CHOOSE({1;2;3;4;5;6;7;8;9;10;11;12;13;14;15;16;17;18;19;20;21;22;23;24;25;26;27;28;29;30;31;32}, COUNTIFS($U$2:$U$200,$G6)>0, COUNTIFS($V$2:$V$200,$G6)>0, COUNTIFS($W$2:$W$200,$G6)>0, COUNTIFS($X$2:$X$200,$G6)>0, COUNTIFS($Y$2:$Y$200,$G6)>0, COUNTIFS($Z$2:$Z$200,$G6)>0, COUNTIFS($AA$2:$AA$200,$G6)>0, COUNTIFS($AB$2:$AB$200,$G6)>0, COUNTIFS($AC$2:$AC$200,$G6)>0, COUNTIFS($AD$2:$AD$200,$G6)>0, COUNTIFS($AE$2:$AE$200,$G6)>0, COUNTIFS($AF$2:$AF$200,$G6)>0, COUNTIFS($AG$2:$AG$200,$G6)>0, COUNTIFS($AH$2:$AH$200,$G6)>0, COUNTIFS($AI$2:$AI$200,$G6)>0, COUNTIFS($AJ$2:$AJ$200,$G6)>0, COUNTIFS($AK$2:$AK$200,$G6)>0, COUNTIFS($AL$2:$AL$200,$G6)>0, COUNTIFS($AM$2:$AM$200,$G6)>0, COUNTIFS($AN$2:$AN$200,$G6)>0, COUNTIFS($AO$2:$AO$200,$G6)>0, COUNTIFS($AP$2:$AP$200,$G6)>0, COUNTIFS($AQ$2:$AQ$200,$G6)>0, COUNTIFS($AR$2:$AR$200,$G6)>0, COUNTIFS($AS$2:$AS$200,$G6)>0, COUNTIFS($AT$2:$AT$200,$G6)>0, COUNTIFS($AU$2:$AU$200,$G6)>0, COUNTIFS($AV$2:$AV$200,$G6)>0, COUNTIFS($AW$2:$AW$200,$G6)>0, COUNTIFS($AX$2:$AX$200,$G6)>0 ), 0) ), "") -> Rielle | D6: {=IFERROR( INDEX( _xlfn._xlws.FILTER($U$1:$AX$1, TRANSPOSE( CHOOSE({1;2;3;4;5;6;7;8;9;10;11;12;13;14;15;16;17;18;19;20;21;22;23;24;25;26;27;28;29;30}, COUNTIFS($U$2:$U$200,$G6)>0, COUNTIFS($V$2:$V$200,$G6)>0, COUNTIFS($W$2:$W$200,$G6)>0, COUNTIFS($X$2:$X$200,$G6)>0, COUNTIFS($Y$2:$Y$200,$G6)>0, COUNTIFS($Z$2:$Z$200,$G6)>0, COUNTIFS($AA$2:$AA$200,$G6)>0, COUNTIFS($AB$2:$AB$200,$G6)>0, COUNTIFS($AC$2:$AC$200,$G6)>0, COUNTIFS($AD$2:$AD$200,$G6)>0, COUNTIFS($AE$2:$AE$200,$G6)>0, COUNTIFS($AF$2:$AF$200,$G6)>0, COUNTIFS($AG$2:$AG$200,$G6)>0, COUNTIFS($AH$2:$AH$200,$G6)>0, COUNTIFS($AI$2:$AI$200,$G6)>0, COUNTIFS($AJ$2:$AJ$200,$G6)>0, COUNTIFS($AK$2:$AK$200,$G6)>0, COUNTIFS($AL$2:$AL$200,$G6)>0, COUNTIFS($AM$2:$AM$200,$G6)>0, COUNTIFS($AN$2:$AN$200,$G6)>0, COUNTIFS($AO$2:$AO$200,$G6)>0, COUNTIFS($AP$2:$AP$200,$G6)>0, COUNTIFS($AQ$2:$AQ$200,$G6)>0, COUNTIFS($AR$2:$AR$200,$G6)>0, COUNTIFS($AS$2:$AS$200,$G6)>0, COUNTIFS($AT$2:$AT$200,$G6)>0, COUNTIFS($AU$2:$AU$200,$G6)>0, COUNTIFS($AV$2:$AV$200,$G6)>0, COUNTIFS($AW$2:$AW$200,$G6)>0, COUNTIFS($AX$2:$AX$200,$G6)>0 )), ), 2 ), "")} | E6: {=IFERROR( INDEX( _xlfn._xlws.FILTER($U$1:$AX$1, TRANSPOSE( CHOOSE({1;2;3;4;5;6;7;8;9;10;11;12;13;14;15;16;17;18;19;20;21;22;23;24;25;26;27;28;29;30}, COUNTIFS($U$2:$U$200,$G6)>0, COUNTIFS($V$2:$V$200,$G6)>0, COUNTIFS($W$2:$W$200,$G6)>0, COUNTIFS($X$2:$X$200,$G6)>0, COUNTIFS($Y$2:$Y$200,$G6)>0, COUNTIFS($Z$2:$Z$200,$G6)>0, COUNTIFS($AA$2:$AA$200,$G6)>0, COUNTIFS($AB$2:$AB$200,$G6)>0, COUNTIFS($AC$2:$AC$200,$G6)>0, COUNTIFS($AD$2:$AD$200,$G6)>0, COUNTIFS($AE$2:$AE$200,$G6)>0, COUNTIFS($AF$2:$AF$200,$G6)>0, COUNTIFS($AG$2:$AG$200,$G6)>0, COUNTIFS($AH$2:$AH$200,$G6)>0, COUNTIFS($AI$2:$AI$200,$G6)>0, COUNTIFS($AJ$2:$AJ$200,$G6)>0, COUNTIFS($AK$2:$AK$200,$G6)>0, COUNTIFS($AL$2:$AL$200,$G6)>0, COUNTIFS($AM$2:$AM$200,$G6)>0, COUNTIFS($AN$2:$AN$200,$G6)>0, COUNTIFS($AO$2:$AO$200,$G6)>0, COUNTIFS($AP$2:$AP$200,$G6)>0, COUNTIFS($AQ$2:$AQ$200,$G6)>0, COUNTIFS($AR$2:$AR$200,$G6)>0, COUNTIFS($AS$2:$AS$200,$G6)>0, COUNTIFS($AT$2:$AT$200,$G6)>0, COUNTIFS($AU$2:$AU$200,$G6)>0, COUNTIFS($AV$2:$AV$200,$G6)>0, COUNTIFS($AW$2:$AW$200,$G6)>0, COUNTIFS($AX$2:$AX$200,$G6)>0 )), ), 3 ), "")} | F6: {=IFERROR( INDEX( _xlfn._xlws.FILTER($U$1:$AX$1, TRANSPOSE( CHOOSE({1;2;3;4;5;6;7;8;9;10;11;12;13;14;15;16;17;18;19;20;21;22;23;24;25;26;27;28;29;30}, COUNTIFS($U$2:$U$200,$G6)>0, COUNTIFS($V$2:$V$200,$G6)>0, COUNTIFS($W$2:$W$200,$G6)>0, COUNTIFS($X$2:$X$200,$G6)>0, COUNTIFS($Y$2:$Y$200,$G6)>0, COUNTIFS($Z$2:$Z$200,$G6)>0, COUNTIFS($AA$2:$AA$200,$G6)>0, COUNTIFS($AB$2:$AB$200,$G6)>0, COUNTIFS($AC$2:$AC$200,$G6)>0, COUNTIFS($AD$2:$AD$200,$G6)>0, COUNTIFS($AE$2:$AE$200,$G6)>0, COUNTIFS($AF$2:$AF$200,$G6)>0, COUNTIFS($AG$2:$AG$200,$G6)>0, COUNTIFS($AH$2:$AH$200,$G6)>0, COUNTIFS($AI$2:$AI$200,$G6)>0, COUNTIFS($AJ$2:$AJ$200,$G6)>0, COUNTIFS($AK$2:$AK$200,$G6)>0, COUNTIFS($AL$2:$AL$200,$G6)>0, COUNTIFS($AM$2:$AM$200,$G6)>0, COUNTIFS($AN$2:$AN$200,$G6)>0, COUNTIFS($AO$2:$AO$200,$G6)>0, COUNTIFS($AP$2:$AP$200,$G6)>0, COUNTIFS($AQ$2:$AQ$200,$G6)>0, COUNTIFS($AR$2:$AR$200,$G6)>0, COUNTIFS($AS$2:$AS$200,$G6)>0, COUNTIFS($AT$2:$AT$200,$G6)>0, COUNTIFS($AU$2:$AU$200,$G6)>0, COUNTIFS($AV$2:$AV$200,$G6)>0, COUNTIFS($AW$2:$AW$200,$G6)>0, COUNTIFS($AX$2:$AX$200,$G6)>0 )), ), 4 ), "")} | G6: Afundar em Estupor | I6: Piratas | J6: =Piratas!G2 -> 17 | K6: Não | L6: Sim | M6: Sim | N6: Sim | O6: Não | P6: Combate | Q6: Combo | R6: Tesouros e Roubos | S6: =IF(J6<6,"5",IF(J6<11,"4",IF(J6<16,"3",IF(J6<31,"2","1")))) -> 2 | U6: Fabled Passage | V6: Castle Ardenvale | W6: Genji Glove | X6: Champion of Lambholt | Y6: Exemplar of Light | Z6: Cyber Conversion | AA6: Herald of Secret Streams | AB6: Misty Rainforest | AC6: Rise of the Eldrazi | AD6: Hedge Shredder | AE6: Inventors' Fair | AF6: Mandate of Peace | AG6: Morphic Pool | AH6: Glasspool Mimic | AI6: Espada de Fogo e Gelo | AJ6: Kaya the Inexorable | AL6: Overgrown Tomb | AM6: Valfenda | AN6: Thrumming Hivepool | AO6: Ojer Pakpatiq, Era Profunda | AP6: Sonic Screwdriver | AQ6: Nibelheim Aflame | AS6: Susur Secundi, Void Altar | AT6: Westvale Abbey | AX6: Badgermole | BB6: Boros Charm | BC6: Cankerbloom | BD6: Bothersome Quasit | BE6: Grave Pact | BF6: Entomb | BG6: Chimil, o Sol Interior | BH6: Diário de Tarrian | BI6: Espada da Riqueza e do Poder | BJ6: Nissa, Resurgent Animist | BK6: Planetary Annihilation | BL6: Invasion of Segovia | BM6: High-Society Hunter | BN6: Olho de Ojer Taq | BO6: Teyo, Geometric Tactician | BP6: Badgermole | BS6: Arwen, Weaver of Hope | BT6: Beast Within | BU6: Batwing Brume | BV6: Cloud, Midgar Mercenary | BW6: Evendo, Waking Haven | BX6: Careful Study | BY6: Emergency Eject | BZ6: Badgermole | CB6: Ardbert, Warrior of Darkness | CC6: Arid Mesa | CD6: Bugenhagen, Wise Elder | CE6: Arcbound Fiend | CG6: Amphibian Downpour | CH6: Árbitro Silencioso | CJ6: Afundar em Estupor
A7: =IFERROR(INDEX($S$3:$S$200, MATCH($C7, $I$3:$I$200, 0)), "") -> 4 | B7: =COUNTIF(U:AX,G7) -> 2 | C7: =IFERROR( INDEX($U$1:$AX$1, MATCH(TRUE, CHOOSE({1;2;3;4;5;6;7;8;9;10;11;12;13;14;15;16;17;18;19;20;21;22;23;24;25;26;27;28;29;30;31;32}, COUNTIFS($U$2:$U$200,$G7)>0, COUNTIFS($V$2:$V$200,$G7)>0, COUNTIFS($W$2:$W$200,$G7)>0, COUNTIFS($X$2:$X$200,$G7)>0, COUNTIFS($Y$2:$Y$200,$G7)>0, COUNTIFS($Z$2:$Z$200,$G7)>0, COUNTIFS($AA$2:$AA$200,$G7)>0, COUNTIFS($AB$2:$AB$200,$G7)>0, COUNTIFS($AC$2:$AC$200,$G7)>0, COUNTIFS($AD$2:$AD$200,$G7)>0, COUNTIFS($AE$2:$AE$200,$G7)>0, COUNTIFS($AF$2:$AF$200,$G7)>0, COUNTIFS($AG$2:$AG$200,$G7)>0, COUNTIFS($AH$2:$AH$200,$G7)>0, COUNTIFS($AI$2:$AI$200,$G7)>0, COUNTIFS($AJ$2:$AJ$200,$G7)>0, COUNTIFS($AK$2:$AK$200,$G7)>0, COUNTIFS($AL$2:$AL$200,$G7)>0, COUNTIFS($AM$2:$AM$200,$G7)>0, COUNTIFS($AN$2:$AN$200,$G7)>0, COUNTIFS($AO$2:$AO$200,$G7)>0, COUNTIFS($AP$2:$AP$200,$G7)>0, COUNTIFS($AQ$2:$AQ$200,$G7)>0, COUNTIFS($AR$2:$AR$200,$G7)>0, COUNTIFS($AS$2:$AS$200,$G7)>0, COUNTIFS($AT$2:$AT$200,$G7)>0, COUNTIFS($AU$2:$AU$200,$G7)>0, COUNTIFS($AV$2:$AV$200,$G7)>0, COUNTIFS($AW$2:$AW$200,$G7)>0, COUNTIFS($AX$2:$AX$200,$G7)>0 ), 0) ), "") -> Elfos | D7: {=IFERROR( INDEX( _xlfn._xlws.FILTER($U$1:$AX$1, TRANSPOSE( CHOOSE({1;2;3;4;5;6;7;8;9;10;11;12;13;14;15;16;17;18;19;20;21;22;23;24;25;26;27;28;29;30}, COUNTIFS($U$2:$U$200,$G7)>0, COUNTIFS($V$2:$V$200,$G7)>0, COUNTIFS($W$2:$W$200,$G7)>0, COUNTIFS($X$2:$X$200,$G7)>0, COUNTIFS($Y$2:$Y$200,$G7)>0, COUNTIFS($Z$2:$Z$200,$G7)>0, COUNTIFS($AA$2:$AA$200,$G7)>0, COUNTIFS($AB$2:$AB$200,$G7)>0, COUNTIFS($AC$2:$AC$200,$G7)>0, COUNTIFS($AD$2:$AD$200,$G7)>0, COUNTIFS($AE$2:$AE$200,$G7)>0, COUNTIFS($AF$2:$AF$200,$G7)>0, COUNTIFS($AG$2:$AG$200,$G7)>0, COUNTIFS($AH$2:$AH$200,$G7)>0, COUNTIFS($AI$2:$AI$200,$G7)>0, COUNTIFS($AJ$2:$AJ$200,$G7)>0, COUNTIFS($AK$2:$AK$200,$G7)>0, COUNTIFS($AL$2:$AL$200,$G7)>0, COUNTIFS($AM$2:$AM$200,$G7)>0, COUNTIFS($AN$2:$AN$200,$G7)>0, COUNTIFS($AO$2:$AO$200,$G7)>0, COUNTIFS($AP$2:$AP$200,$G7)>0, COUNTIFS($AQ$2:$AQ$200,$G7)>0, COUNTIFS($AR$2:$AR$200,$G7)>0, COUNTIFS($AS$2:$AS$200,$G7)>0, COUNTIFS($AT$2:$AT$200,$G7)>0, COUNTIFS($AU$2:$AU$200,$G7)>0, COUNTIFS($AV$2:$AV$200,$G7)>0, COUNTIFS($AW$2:$AW$200,$G7)>0, COUNTIFS($AX$2:$AX$200,$G7)>0 )), ), 2 ), "")} -> Arcades | E7: {=IFERROR( INDEX( _xlfn._xlws.FILTER($U$1:$AX$1, TRANSPOSE( CHOOSE({1;2;3;4;5;6;7;8;9;10;11;12;13;14;15;16;17;18;19;20;21;22;23;24;25;26;27;28;29;30}, COUNTIFS($U$2:$U$200,$G7)>0, COUNTIFS($V$2:$V$200,$G7)>0, COUNTIFS($W$2:$W$200,$G7)>0, COUNTIFS($X$2:$X$200,$G7)>0, COUNTIFS($Y$2:$Y$200,$G7)>0, COUNTIFS($Z$2:$Z$200,$G7)>0, COUNTIFS($AA$2:$AA$200,$G7)>0, COUNTIFS($AB$2:$AB$200,$G7)>0, COUNTIFS($AC$2:$AC$200,$G7)>0, COUNTIFS($AD$2:$AD$200,$G7)>0, COUNTIFS($AE$2:$AE$200,$G7)>0, COUNTIFS($AF$2:$AF$200,$G7)>0, COUNTIFS($AG$2:$AG$200,$G7)>0, COUNTIFS($AH$2:$AH$200,$G7)>0, COUNTIFS($AI$2:$AI$200,$G7)>0, COUNTIFS($AJ$2:$AJ$200,$G7)>0, COUNTIFS($AK$2:$AK$200,$G7)>0, COUNTIFS($AL$2:$AL$200,$G7)>0, COUNTIFS($AM$2:$AM$200,$G7)>0, COUNTIFS($AN$2:$AN$200,$G7)>0, COUNTIFS($AO$2:$AO$200,$G7)>0, COUNTIFS($AP$2:$AP$200,$G7)>0, COUNTIFS($AQ$2:$AQ$200,$G7)>0, COUNTIFS($AR$2:$AR$200,$G7)>0, COUNTIFS($AS$2:$AS$200,$G7)>0, COUNTIFS($AT$2:$AT$200,$G7)>0, COUNTIFS($AU$2:$AU$200,$G7)>0, COUNTIFS($AV$2:$AV$200,$G7)>0, COUNTIFS($AW$2:$AW$200,$G7)>0, COUNTIFS($AX$2:$AX$200,$G7)>0 )), ), 3 ), "")} | F7: {=IFERROR( INDEX( _xlfn._xlws.FILTER($U$1:$AX$1, TRANSPOSE( CHOOSE({1;2;3;4;5;6;7;8;9;10;11;12;13;14;15;16;17;18;19;20;21;22;23;24;25;26;27;28;29;30}, COUNTIFS($U$2:$U$200,$G7)>0, COUNTIFS($V$2:$V$200,$G7)>0, COUNTIFS($W$2:$W$200,$G7)>0, COUNTIFS($X$2:$X$200,$G7)>0, COUNTIFS($Y$2:$Y$200,$G7)>0, COUNTIFS($Z$2:$Z$200,$G7)>0, COUNTIFS($AA$2:$AA$200,$G7)>0, COUNTIFS($AB$2:$AB$200,$G7)>0, COUNTIFS($AC$2:$AC$200,$G7)>0, COUNTIFS($AD$2:$AD$200,$G7)>0, COUNTIFS($AE$2:$AE$200,$G7)>0, COUNTIFS($AF$2:$AF$200,$G7)>0, COUNTIFS($AG$2:$AG$200,$G7)>0, COUNTIFS($AH$2:$AH$200,$G7)>0, COUNTIFS($AI$2:$AI$200,$G7)>0, COUNTIFS($AJ$2:$AJ$200,$G7)>0, COUNTIFS($AK$2:$AK$200,$G7)>0, COUNTIFS($AL$2:$AL$200,$G7)>0, COUNTIFS($AM$2:$AM$200,$G7)>0, COUNTIFS($AN$2:$AN$200,$G7)>0, COUNTIFS($AO$2:$AO$200,$G7)>0, COUNTIFS($AP$2:$AP$200,$G7)>0, COUNTIFS($AQ$2:$AQ$200,$G7)>0, COUNTIFS($AR$2:$AR$200,$G7)>0, COUNTIFS($AS$2:$AS$200,$G7)>0, COUNTIFS($AT$2:$AT$200,$G7)>0, COUNTIFS($AU$2:$AU$200,$G7)>0, COUNTIFS($AV$2:$AV$200,$G7)>0, COUNTIFS($AW$2:$AW$200,$G7)>0, COUNTIFS($AX$2:$AX$200,$G7)>0 )), ), 4 ), "")} | G7: Alchemist's Refuge | I7: Carlos | J7: =Carlos!G2 -> 14 | K7: Sim | L7: Não | M7: Não | N7: Sim | O7: Não | P7: Voltron | Q7: Dano Direto | R7: Ganhar Vida e Reanimate | S7: =IF(J7<6,"5",IF(J7<11,"4",IF(J7<16,"3",IF(J7<31,"2","1")))) -> 3 | U7: Glint-Horn Buccaneer | V7: Champions from Beyond | W7: Ghostly Prison | X7: Dever Além da Morte | Y7: Giver of Runes | Z7: Drowned Catacomb | AA7: Kodama's Reach | AB7: Scalding Tarn | AC7: Rotating Fireplace | AD7: Petrified Field | AE7: Mirrex | AF7: Polluted Delta | AG7: Satoru, the Infiltrator | AH7: Mistbind Clique | AI7: Espada de Luz e Sombra | AJ7: Lolth, Rainha Aranha | AL7: Swamp | AN7: Trioma de Indatha | AO7: Serenata das Estriges | AP7: Três Passos à Frente | AQ7: Pain for All | AS7: Warren Soultrader | AX7: Beast Within | BB7: Broadside Bombardiers | BC7: Canopy Vista | BD7: Counterspell | BE7: Harvest Season | BF7: Hedge Shredder | BG7: Extinguisher Battleship | BH7: Drowned Catacomb | BI7: Espada de Banquete e Fome | BJ7: Obelisco de Obsidiana | BK7: Raffine's Tower | BL7: Jidoor, Aristocratic Capital // Overture | BM7: Jenova, Ancient Calamity | BN7: Renewed Solidarity | BP7: Beast Within | BS7: Aura Mutation | BT7: Bojuka Bog | BU7: Chimil, o Sol Interior | BV7: Commodore Guff | BW7: Jetmir's Garden | BX7: Chandra's Ignition | BY7: Homeward Path | BZ7: Beast Within | CB7: Artifact Mutation | CC7: Batwing Brume | CD7: Careful Study | CE7: Arcbound Overseer | CG7: Ancient Greenwarden | CH7: Arcbound Fiend | CJ7: Alchemist's Refuge
A8: =IFERROR(INDEX($S$3:$S$200, MATCH($C8, $I$3:$I$200, 0)), "") -> 2 | B8: =COUNTIF(U:AX,G8) -> 1 | C8: =IFERROR( INDEX($U$1:$AX$1, MATCH(TRUE, CHOOSE({1;2;3;4;5;6;7;8;9;10;11;12;13;14;15;16;17;18;19;20;21;22;23;24;25;26;27;28;29;30;31;32}, COUNTIFS($U$2:$U$200,$G8)>0, COUNTIFS($V$2:$V$200,$G8)>0, COUNTIFS($W$2:$W$200,$G8)>0, COUNTIFS($X$2:$X$200,$G8)>0, COUNTIFS($Y$2:$Y$200,$G8)>0, COUNTIFS($Z$2:$Z$200,$G8)>0, COUNTIFS($AA$2:$AA$200,$G8)>0, COUNTIFS($AB$2:$AB$200,$G8)>0, COUNTIFS($AC$2:$AC$200,$G8)>0, COUNTIFS($AD$2:$AD$200,$G8)>0, COUNTIFS($AE$2:$AE$200,$G8)>0, COUNTIFS($AF$2:$AF$200,$G8)>0, COUNTIFS($AG$2:$AG$200,$G8)>0, COUNTIFS($AH$2:$AH$200,$G8)>0, COUNTIFS($AI$2:$AI$200,$G8)>0, COUNTIFS($AJ$2:$AJ$200,$G8)>0, COUNTIFS($AK$2:$AK$200,$G8)>0, COUNTIFS($AL$2:$AL$200,$G8)>0, COUNTIFS($AM$2:$AM$200,$G8)>0, COUNTIFS($AN$2:$AN$200,$G8)>0, COUNTIFS($AO$2:$AO$200,$G8)>0, COUNTIFS($AP$2:$AP$200,$G8)>0, COUNTIFS($AQ$2:$AQ$200,$G8)>0, COUNTIFS($AR$2:$AR$200,$G8)>0, COUNTIFS($AS$2:$AS$200,$G8)>0, COUNTIFS($AT$2:$AT$200,$G8)>0, COUNTIFS($AU$2:$AU$200,$G8)>0, COUNTIFS($AV$2:$AV$200,$G8)>0, COUNTIFS($AW$2:$AW$200,$G8)>0, COUNTIFS($AX$2:$AX$200,$G8)>0 ), 0) ), "") -> Narset | D8: {=IFERROR( INDEX( _xlfn._xlws.FILTER($U$1:$AX$1, TRANSPOSE( CHOOSE({1;2;3;4;5;6;7;8;9;10;11;12;13;14;15;16;17;18;19;20;21;22;23;24;25;26;27;28;29;30}, COUNTIFS($U$2:$U$200,$G8)>0, COUNTIFS($V$2:$V$200,$G8)>0, COUNTIFS($W$2:$W$200,$G8)>0, COUNTIFS($X$2:$X$200,$G8)>0, COUNTIFS($Y$2:$Y$200,$G8)>0, COUNTIFS($Z$2:$Z$200,$G8)>0, COUNTIFS($AA$2:$AA$200,$G8)>0, COUNTIFS($AB$2:$AB$200,$G8)>0, COUNTIFS($AC$2:$AC$200,$G8)>0, COUNTIFS($AD$2:$AD$200,$G8)>0, COUNTIFS($AE$2:$AE$200,$G8)>0, COUNTIFS($AF$2:$AF$200,$G8)>0, COUNTIFS($AG$2:$AG$200,$G8)>0, COUNTIFS($AH$2:$AH$200,$G8)>0, COUNTIFS($AI$2:$AI$200,$G8)>0, COUNTIFS($AJ$2:$AJ$200,$G8)>0, COUNTIFS($AK$2:$AK$200,$G8)>0, COUNTIFS($AL$2:$AL$200,$G8)>0, COUNTIFS($AM$2:$AM$200,$G8)>0, COUNTIFS($AN$2:$AN$200,$G8)>0, COUNTIFS($AO$2:$AO$200,$G8)>0, COUNTIFS($AP$2:$AP$200,$G8)>0, COUNTIFS($AQ$2:$AQ$200,$G8)>0, COUNTIFS($AR$2:$AR$200,$G8)>0, COUNTIFS($AS$2:$AS$200,$G8)>0, COUNTIFS($AT$2:$AT$200,$G8)>0, COUNTIFS($AU$2:$AU$200,$G8)>0, COUNTIFS($AV$2:$AV$200,$G8)>0, COUNTIFS($AW$2:$AW$200,$G8)>0, COUNTIFS($AX$2:$AX$200,$G8)>0 )), ), 2 ), "")} | E8: {=IFERROR( INDEX( _xlfn._xlws.FILTER($U$1:$AX$1, TRANSPOSE( CHOOSE({1;2;3;4;5;6;7;8;9;10;11;12;13;14;15;16;17;18;19;20;21;22;23;24;25;26;27;28;29;30}, COUNTIFS($U$2:$U$200,$G8)>0, COUNTIFS($V$2:$V$200,$G8)>0, COUNTIFS($W$2:$W$200,$G8)>0, COUNTIFS($X$2:$X$200,$G8)>0, COUNTIFS($Y$2:$Y$200,$G8)>0, COUNTIFS($Z$2:$Z$200,$G8)>0, COUNTIFS($AA$2:$AA$200,$G8)>0, COUNTIFS($AB$2:$AB$200,$G8)>0, COUNTIFS($AC$2:$AC$200,$G8)>0, COUNTIFS($AD$2:$AD$200,$G8)>0, COUNTIFS($AE$2:$AE$200,$G8)>0, COUNTIFS($AF$2:$AF$200,$G8)>0, COUNTIFS($AG$2:$AG$200,$G8)>0, COUNTIFS($AH$2:$AH$200,$G8)>0, COUNTIFS($AI$2:$AI$200,$G8)>0, COUNTIFS($AJ$2:$AJ$200,$G8)>0, COUNTIFS($AK$2:$AK$200,$G8)>0, COUNTIFS($AL$2:$AL$200,$G8)>0, COUNTIFS($AM$2:$AM$200,$G8)>0, COUNTIFS($AN$2:$AN$200,$G8)>0, COUNTIFS($AO$2:$AO$200,$G8)>0, COUNTIFS($AP$2:$AP$200,$G8)>0, COUNTIFS($AQ$2:$AQ$200,$G8)>0, COUNTIFS($AR$2:$AR$200,$G8)>0, COUNTIFS($AS$2:$AS$200,$G8)>0, COUNTIFS($AT$2:$AT$200,$G8)>0, COUNTIFS($AU$2:$AU$200,$G8)>0, COUNTIFS($AV$2:$AV$200,$G8)>0, COUNTIFS($AW$2:$AW$200,$G8)>0, COUNTIFS($AX$2:$AX$200,$G8)>0 )), ), 3 ), "")} | F8: {=IFERROR( INDEX( _xlfn._xlws.FILTER($U$1:$AX$1, TRANSPOSE( CHOOSE({1;2;3;4;5;6;7;8;9;10;11;12;13;14;15;16;17;18;19;20;21;22;23;24;25;26;27;28;29;30}, COUNTIFS($U$2:$U$200,$G8)>0, COUNTIFS($V$2:$V$200,$G8)>0, COUNTIFS($W$2:$W$200,$G8)>0, COUNTIFS($X$2:$X$200,$G8)>0, COUNTIFS($Y$2:$Y$200,$G8)>0, COUNTIFS($Z$2:$Z$200,$G8)>0, COUNTIFS($AA$2:$AA$200,$G8)>0, COUNTIFS($AB$2:$AB$200,$G8)>0, COUNTIFS($AC$2:$AC$200,$G8)>0, COUNTIFS($AD$2:$AD$200,$G8)>0, COUNTIFS($AE$2:$AE$200,$G8)>0, COUNTIFS($AF$2:$AF$200,$G8)>0, COUNTIFS($AG$2:$AG$200,$G8)>0, COUNTIFS($AH$2:$AH$200,$G8)>0, COUNTIFS($AI$2:$AI$200,$G8)>0, COUNTIFS($AJ$2:$AJ$200,$G8)>0, COUNTIFS($AK$2:$AK$200,$G8)>0, COUNTIFS($AL$2:$AL$200,$G8)>0, COUNTIFS($AM$2:$AM$200,$G8)>0, COUNTIFS($AN$2:$AN$200,$G8)>0, COUNTIFS($AO$2:$AO$200,$G8)>0, COUNTIFS($AP$2:$AP$200,$G8)>0, COUNTIFS($AQ$2:$AQ$200,$G8)>0, COUNTIFS($AR$2:$AR$200,$G8)>0, COUNTIFS($AS$2:$AS$200,$G8)>0, COUNTIFS($AT$2:$AT$200,$G8)>0, COUNTIFS($AU$2:$AU$200,$G8)>0, COUNTIFS($AV$2:$AV$200,$G8)>0, COUNTIFS($AW$2:$AW$200,$G8)>0, COUNTIFS($AX$2:$AX$200,$G8)>0 )), ), 4 ), "")} | G8: Aligned Heart | I8: Rani | J8: =Rani!G2 -> 21 | K8: Não | L8: Sim | M8: Sim | N8: Sim | O8: Não | P8: Combate | Q8: Voltron | R8: Atiçar e Investigar | S8: =IF(J8<6,"5",IF(J8<11,"4",IF(J8<16,"3",IF(J8<31,"2","1")))) -> 2 | U8: Hedron Detonator | V8: Exalted Sunborn | W8: Incendiary Command | X8: Devoted Druid | Y8: Guia das Almas | Z8: Dúplice Debochada | AA8: Lord of Atlantis | AB8: Sothera, the Supervoid | AC8: The Tenth Doctor | AD8: Phyrexian Tower | AE8: Portal to Phyrexia | AF8: Spectator Seating | AG8: Sea Gate Restoration | AH8: Molten Echoes | AI8: Espada de Verdade e Justiça | AJ8: Nicol Bolas, God-Pharaoh | AL8: Three Tree City | AN8: Trioma de Raugrin | AO8: Sokenzan, Crisol da Afronta | AP8: Unstoppable Plan | AQ8: Red XIII, Proud Warrior | AX8: Dispatch | BB8: Brushland | BC8: Champion of Lambholt | BD8: Cyber Conversion | BE8: Herald of Secret Streams | BF8: Kozilek, the Broken Reality | BG8: Gerrard's Hourglass Pendant | BH8: Faerie Slumber Party | BI8: Espada de Fogo e Gelo | BJ8: Overgrown Tomb | BK8: Sliver Gravemother | BL8: Ojer Pakpatiq, Era Profunda | BM8: Nibelheim Aflame | BN8: Scattered Groves | BP8: Dispatch | BS8: Back in Town | BT8: Bothersome Quasit | BU8: Crisol dos Mundos | BV8: Creeping Tar Pit | BW8: Matoya, Archon Elder | BX8: Collector's Vault | BY8: Illustrious Wanderglyph | BZ8: Dispatch | CB8: Arwen, Weaver of Hope | CC8: Bojuka Bog | CD8: Caverna das Almas | CE8: Badgermole | CG8: Ancient Tomb | CH8: Arcbound Overseer | CJ8: Aligned Heart
A9: =IFERROR(INDEX($S$3:$S$200, MATCH($C9, $I$3:$I$200, 0)), "") -> 4 | B9: =COUNTIF(U:AX,G9) -> 1 | C9: =IFERROR( INDEX($U$1:$AX$1, MATCH(TRUE, CHOOSE({1;2;3;4;5;6;7;8;9;10;11;12;13;14;15;16;17;18;19;20;21;22;23;24;25;26;27;28;29;30;31;32}, COUNTIFS($U$2:$U$200,$G9)>0, COUNTIFS($V$2:$V$200,$G9)>0, COUNTIFS($W$2:$W$200,$G9)>0, COUNTIFS($X$2:$X$200,$G9)>0, COUNTIFS($Y$2:$Y$200,$G9)>0, COUNTIFS($Z$2:$Z$200,$G9)>0, COUNTIFS($AA$2:$AA$200,$G9)>0, COUNTIFS($AB$2:$AB$200,$G9)>0, COUNTIFS($AC$2:$AC$200,$G9)>0, COUNTIFS($AD$2:$AD$200,$G9)>0, COUNTIFS($AE$2:$AE$200,$G9)>0, COUNTIFS($AF$2:$AF$200,$G9)>0, COUNTIFS($AG$2:$AG$200,$G9)>0, COUNTIFS($AH$2:$AH$200,$G9)>0, COUNTIFS($AI$2:$AI$200,$G9)>0, COUNTIFS($AJ$2:$AJ$200,$G9)>0, COUNTIFS($AK$2:$AK$200,$G9)>0, COUNTIFS($AL$2:$AL$200,$G9)>0, COUNTIFS($AM$2:$AM$200,$G9)>0, COUNTIFS($AN$2:$AN$200,$G9)>0, COUNTIFS($AO$2:$AO$200,$G9)>0, COUNTIFS($AP$2:$AP$200,$G9)>0, COUNTIFS($AQ$2:$AQ$200,$G9)>0, COUNTIFS($AR$2:$AR$200,$G9)>0, COUNTIFS($AS$2:$AS$200,$G9)>0, COUNTIFS($AT$2:$AT$200,$G9)>0, COUNTIFS($AU$2:$AU$200,$G9)>0, COUNTIFS($AV$2:$AV$200,$G9)>0, COUNTIFS($AW$2:$AW$200,$G9)>0, COUNTIFS($AX$2:$AX$200,$G9)>0 ), 0) ), "") -> VialIshai | D9: {=IFERROR( INDEX( _xlfn._xlws.FILTER($U$1:$AX$1, TRANSPOSE( CHOOSE({1;2;3;4;5;6;7;8;9;10;11;12;13;14;15;16;17;18;19;20;21;22;23;24;25;26;27;28;29;30}, COUNTIFS($U$2:$U$200,$G9)>0, COUNTIFS($V$2:$V$200,$G9)>0, COUNTIFS($W$2:$W$200,$G9)>0, COUNTIFS($X$2:$X$200,$G9)>0, COUNTIFS($Y$2:$Y$200,$G9)>0, COUNTIFS($Z$2:$Z$200,$G9)>0, COUNTIFS($AA$2:$AA$200,$G9)>0, COUNTIFS($AB$2:$AB$200,$G9)>0, COUNTIFS($AC$2:$AC$200,$G9)>0, COUNTIFS($AD$2:$AD$200,$G9)>0, COUNTIFS($AE$2:$AE$200,$G9)>0, COUNTIFS($AF$2:$AF$200,$G9)>0, COUNTIFS($AG$2:$AG$200,$G9)>0, COUNTIFS($AH$2:$AH$200,$G9)>0, COUNTIFS($AI$2:$AI$200,$G9)>0, COUNTIFS($AJ$2:$AJ$200,$G9)>0, COUNTIFS($AK$2:$AK$200,$G9)>0, COUNTIFS($AL$2:$AL$200,$G9)>0, COUNTIFS($AM$2:$AM$200,$G9)>0, COUNTIFS($AN$2:$AN$200,$G9)>0, COUNTIFS($AO$2:$AO$200,$G9)>0, COUNTIFS($AP$2:$AP$200,$G9)>0, COUNTIFS($AQ$2:$AQ$200,$G9)>0, COUNTIFS($AR$2:$AR$200,$G9)>0, COUNTIFS($AS$2:$AS$200,$G9)>0, COUNTIFS($AT$2:$AT$200,$G9)>0, COUNTIFS($AU$2:$AU$200,$G9)>0, COUNTIFS($AV$2:$AV$200,$G9)>0, COUNTIFS($AW$2:$AW$200,$G9)>0, COUNTIFS($AX$2:$AX$200,$G9)>0 )), ), 2 ), "")} | E9: {=IFERROR( INDEX( _xlfn._xlws.FILTER($U$1:$AX$1, TRANSPOSE( CHOOSE({1;2;3;4;5;6;7;8;9;10;11;12;13;14;15;16;17;18;19;20;21;22;23;24;25;26;27;28;29;30}, COUNTIFS($U$2:$U$200,$G9)>0, COUNTIFS($V$2:$V$200,$G9)>0, COUNTIFS($W$2:$W$200,$G9)>0, COUNTIFS($X$2:$X$200,$G9)>0, COUNTIFS($Y$2:$Y$200,$G9)>0, COUNTIFS($Z$2:$Z$200,$G9)>0, COUNTIFS($AA$2:$AA$200,$G9)>0, COUNTIFS($AB$2:$AB$200,$G9)>0, COUNTIFS($AC$2:$AC$200,$G9)>0, COUNTIFS($AD$2:$AD$200,$G9)>0, COUNTIFS($AE$2:$AE$200,$G9)>0, COUNTIFS($AF$2:$AF$200,$G9)>0, COUNTIFS($AG$2:$AG$200,$G9)>0, COUNTIFS($AH$2:$AH$200,$G9)>0, COUNTIFS($AI$2:$AI$200,$G9)>0, COUNTIFS($AJ$2:$AJ$200,$G9)>0, COUNTIFS($AK$2:$AK$200,$G9)>0, COUNTIFS($AL$2:$AL$200,$G9)>0, COUNTIFS($AM$2:$AM$200,$G9)>0, COUNTIFS($AN$2:$AN$200,$G9)>0, COUNTIFS($AO$2:$AO$200,$G9)>0, COUNTIFS($AP$2:$AP$200,$G9)>0, COUNTIFS($AQ$2:$AQ$200,$G9)>0, COUNTIFS($AR$2:$AR$200,$G9)>0, COUNTIFS($AS$2:$AS$200,$G9)>0, COUNTIFS($AT$2:$AT$200,$G9)>0, COUNTIFS($AU$2:$AU$200,$G9)>0, COUNTIFS($AV$2:$AV$200,$G9)>0, COUNTIFS($AW$2:$AW$200,$G9)>0, COUNTIFS($AX$2:$AX$200,$G9)>0 )), ), 3 ), "")} | F9: {=IFERROR( INDEX( _xlfn._xlws.FILTER($U$1:$AX$1, TRANSPOSE( CHOOSE({1;2;3;4;5;6;7;8;9;10;11;12;13;14;15;16;17;18;19;20;21;22;23;24;25;26;27;28;29;30}, COUNTIFS($U$2:$U$200,$G9)>0, COUNTIFS($V$2:$V$200,$G9)>0, COUNTIFS($W$2:$W$200,$G9)>0, COUNTIFS($X$2:$X$200,$G9)>0, COUNTIFS($Y$2:$Y$200,$G9)>0, COUNTIFS($Z$2:$Z$200,$G9)>0, COUNTIFS($AA$2:$AA$200,$G9)>0, COUNTIFS($AB$2:$AB$200,$G9)>0, COUNTIFS($AC$2:$AC$200,$G9)>0, COUNTIFS($AD$2:$AD$200,$G9)>0, COUNTIFS($AE$2:$AE$200,$G9)>0, COUNTIFS($AF$2:$AF$200,$G9)>0, COUNTIFS($AG$2:$AG$200,$G9)>0, COUNTIFS($AH$2:$AH$200,$G9)>0, COUNTIFS($AI$2:$AI$200,$G9)>0, COUNTIFS($AJ$2:$AJ$200,$G9)>0, COUNTIFS($AK$2:$AK$200,$G9)>0, COUNTIFS($AL$2:$AL$200,$G9)>0, COUNTIFS($AM$2:$AM$200,$G9)>0, COUNTIFS($AN$2:$AN$200,$G9)>0, COUNTIFS($AO$2:$AO$200,$G9)>0, COUNTIFS($AP$2:$AP$200,$G9)>0, COUNTIFS($AQ$2:$AQ$200,$G9)>0, COUNTIFS($AR$2:$AR$200,$G9)>0, COUNTIFS($AS$2:$AS$200,$G9)>0, COUNTIFS($AT$2:$AT$200,$G9)>0, COUNTIFS($AU$2:$AU$200,$G9)>0, COUNTIFS($AV$2:$AV$200,$G9)>0, COUNTIFS($AW$2:$AW$200,$G9)>0, COUNTIFS($AX$2:$AX$200,$G9)>0 )), ), 4 ), "")} | G9: Amphibian Downpour | I9: Kumena | J9: =Kumena!G2 -> 21 | K9: Não | L9: Sim | M9: Não | N9: Não | O9: Sim | P9: Combate | Q9: Voltron | R9: Tribal de Tritões | S9: =IF(J9<6,"5",IF(J9<11,"4",IF(J9<16,"3",IF(J9<31,"2","1")))) -> 2 | U9: Mines of Moria | V9: Farmer Cotton | W9: Irenicus's Vile Duplication | X9: Forest | Y9: Hierofante de Elenda | Z9: Fellwar Stone | AA9: Lullmage Mentor | AB9: Teferi's Ageless Insight | AC9: Thought Vessel | AD9: Ripples of Undeath | AE9: Rings of Brighthearth | AF9: Vontade Dominadora | AG9: Shizo, Death's Storehouse | AH9: Reliquary Tower | AI9: Firion, Wild Rose Warrior | AJ9: O Dínamo Peregrino | AL9: Watery Grave | AN9: Trioma de Zagoth | AQ9: Saqueador Amaldiçoado | AX9: Duty Beyond Death | BB9: Castle Ardenvale | BC9: Clifftop Retreat | BD9: Drowned Catacomb | BE9: Horizon Explorer | BF9: Mistrise Village | BG9: Inventors' Fair | BH9: Glasspool Mimic | BI9: Espada de Luz e Sombra | BJ9: Shaku da Honra Desgastada | BK9: Thrumming Hivepool | BL9: Scour for Scrap | BM9: Pain for All | BN9: Stridehangar Automaton | BP9: Duty Beyond Death | BS9: Bojuka Bog | BT9: Call to the Kindred | BU9: Delighted Halfling | BV9: Diário de Tarrian | BW9: Mistrise Village | BX9: Daretti, Ingenious Iconoclast | BY9: Lagoa Espelhada | BZ9: Duty Beyond Death | CB9: Ascensão do Avernus | CC9: Burnt Offering | CD9: Chandra's Ignition | CE9: Beast Within | CG9: Arcane Lighthouse | CH9: Badgermole | CJ9: Amphibian Downpour
A10: =IFERROR(INDEX($S$3:$S$200, MATCH($C10, $I$3:$I$200, 0)), "") -> 1 | B10: =COUNTIF(U:AX,G10) -> 1 | C10: =IFERROR( INDEX($U$1:$AX$1, MATCH(TRUE, CHOOSE({1;2;3;4;5;6;7;8;9;10;11;12;13;14;15;16;17;18;19;20;21;22;23;24;25;26;27;28;29;30;31;32}, COUNTIFS($U$2:$U$200,$G10)>0, COUNTIFS($V$2:$V$200,$G10)>0, COUNTIFS($W$2:$W$200,$G10)>0, COUNTIFS($X$2:$X$200,$G10)>0, COUNTIFS($Y$2:$Y$200,$G10)>0, COUNTIFS($Z$2:$Z$200,$G10)>0, COUNTIFS($AA$2:$AA$200,$G10)>0, COUNTIFS($AB$2:$AB$200,$G10)>0, COUNTIFS($AC$2:$AC$200,$G10)>0, COUNTIFS($AD$2:$AD$200,$G10)>0, COUNTIFS($AE$2:$AE$200,$G10)>0, COUNTIFS($AF$2:$AF$200,$G10)>0, COUNTIFS($AG$2:$AG$200,$G10)>0, COUNTIFS($AH$2:$AH$200,$G10)>0, COUNTIFS($AI$2:$AI$200,$G10)>0, COUNTIFS($AJ$2:$AJ$200,$G10)>0, COUNTIFS($AK$2:$AK$200,$G10)>0, COUNTIFS($AL$2:$AL$200,$G10)>0, COUNTIFS($AM$2:$AM$200,$G10)>0, COUNTIFS($AN$2:$AN$200,$G10)>0, COUNTIFS($AO$2:$AO$200,$G10)>0, COUNTIFS($AP$2:$AP$200,$G10)>0, COUNTIFS($AQ$2:$AQ$200,$G10)>0, COUNTIFS($AR$2:$AR$200,$G10)>0, COUNTIFS($AS$2:$AS$200,$G10)>0, COUNTIFS($AT$2:$AT$200,$G10)>0, COUNTIFS($AU$2:$AU$200,$G10)>0, COUNTIFS($AV$2:$AV$200,$G10)>0, COUNTIFS($AW$2:$AW$200,$G10)>0, COUNTIFS($AX$2:$AX$200,$G10)>0 ), 0) ), "") -> Modular | D10: {=IFERROR( INDEX( _xlfn._xlws.FILTER($U$1:$AX$1, TRANSPOSE( CHOOSE({1;2;3;4;5;6;7;8;9;10;11;12;13;14;15;16;17;18;19;20;21;22;23;24;25;26;27;28;29;30}, COUNTIFS($U$2:$U$200,$G10)>0, COUNTIFS($V$2:$V$200,$G10)>0, COUNTIFS($W$2:$W$200,$G10)>0, COUNTIFS($X$2:$X$200,$G10)>0, COUNTIFS($Y$2:$Y$200,$G10)>0, COUNTIFS($Z$2:$Z$200,$G10)>0, COUNTIFS($AA$2:$AA$200,$G10)>0, COUNTIFS($AB$2:$AB$200,$G10)>0, COUNTIFS($AC$2:$AC$200,$G10)>0, COUNTIFS($AD$2:$AD$200,$G10)>0, COUNTIFS($AE$2:$AE$200,$G10)>0, COUNTIFS($AF$2:$AF$200,$G10)>0, COUNTIFS($AG$2:$AG$200,$G10)>0, COUNTIFS($AH$2:$AH$200,$G10)>0, COUNTIFS($AI$2:$AI$200,$G10)>0, COUNTIFS($AJ$2:$AJ$200,$G10)>0, COUNTIFS($AK$2:$AK$200,$G10)>0, COUNTIFS($AL$2:$AL$200,$G10)>0, COUNTIFS($AM$2:$AM$200,$G10)>0, COUNTIFS($AN$2:$AN$200,$G10)>0, COUNTIFS($AO$2:$AO$200,$G10)>0, COUNTIFS($AP$2:$AP$200,$G10)>0, COUNTIFS($AQ$2:$AQ$200,$G10)>0, COUNTIFS($AR$2:$AR$200,$G10)>0, COUNTIFS($AS$2:$AS$200,$G10)>0, COUNTIFS($AT$2:$AT$200,$G10)>0, COUNTIFS($AU$2:$AU$200,$G10)>0, COUNTIFS($AV$2:$AV$200,$G10)>0, COUNTIFS($AW$2:$AW$200,$G10)>0, COUNTIFS($AX$2:$AX$200,$G10)>0 )), ), 2 ), "")} | E10: {=IFERROR( INDEX( _xlfn._xlws.FILTER($U$1:$AX$1, TRANSPOSE( CHOOSE({1;2;3;4;5;6;7;8;9;10;11;12;13;14;15;16;17;18;19;20;21;22;23;24;25;26;27;28;29;30}, COUNTIFS($U$2:$U$200,$G10)>0, COUNTIFS($V$2:$V$200,$G10)>0, COUNTIFS($W$2:$W$200,$G10)>0, COUNTIFS($X$2:$X$200,$G10)>0, COUNTIFS($Y$2:$Y$200,$G10)>0, COUNTIFS($Z$2:$Z$200,$G10)>0, COUNTIFS($AA$2:$AA$200,$G10)>0, COUNTIFS($AB$2:$AB$200,$G10)>0, COUNTIFS($AC$2:$AC$200,$G10)>0, COUNTIFS($AD$2:$AD$200,$G10)>0, COUNTIFS($AE$2:$AE$200,$G10)>0, COUNTIFS($AF$2:$AF$200,$G10)>0, COUNTIFS($AG$2:$AG$200,$G10)>0, COUNTIFS($AH$2:$AH$200,$G10)>0, COUNTIFS($AI$2:$AI$200,$G10)>0, COUNTIFS($AJ$2:$AJ$200,$G10)>0, COUNTIFS($AK$2:$AK$200,$G10)>0, COUNTIFS($AL$2:$AL$200,$G10)>0, COUNTIFS($AM$2:$AM$200,$G10)>0, COUNTIFS($AN$2:$AN$200,$G10)>0, COUNTIFS($AO$2:$AO$200,$G10)>0, COUNTIFS($AP$2:$AP$200,$G10)>0, COUNTIFS($AQ$2:$AQ$200,$G10)>0, COUNTIFS($AR$2:$AR$200,$G10)>0, COUNTIFS($AS$2:$AS$200,$G10)>0, COUNTIFS($AT$2:$AT$200,$G10)>0, COUNTIFS($AU$2:$AU$200,$G10)>0, COUNTIFS($AV$2:$AV$200,$G10)>0, COUNTIFS($AW$2:$AW$200,$G10)>0, COUNTIFS($AX$2:$AX$200,$G10)>0 )), ), 3 ), "")} | F10: {=IFERROR( INDEX( _xlfn._xlws.FILTER($U$1:$AX$1, TRANSPOSE( CHOOSE({1;2;3;4;5;6;7;8;9;10;11;12;13;14;15;16;17;18;19;20;21;22;23;24;25;26;27;28;29;30}, COUNTIFS($U$2:$U$200,$G10)>0, COUNTIFS($V$2:$V$200,$G10)>0, COUNTIFS($W$2:$W$200,$G10)>0, COUNTIFS($X$2:$X$200,$G10)>0, COUNTIFS($Y$2:$Y$200,$G10)>0, COUNTIFS($Z$2:$Z$200,$G10)>0, COUNTIFS($AA$2:$AA$200,$G10)>0, COUNTIFS($AB$2:$AB$200,$G10)>0, COUNTIFS($AC$2:$AC$200,$G10)>0, COUNTIFS($AD$2:$AD$200,$G10)>0, COUNTIFS($AE$2:$AE$200,$G10)>0, COUNTIFS($AF$2:$AF$200,$G10)>0, COUNTIFS($AG$2:$AG$200,$G10)>0, COUNTIFS($AH$2:$AH$200,$G10)>0, COUNTIFS($AI$2:$AI$200,$G10)>0, COUNTIFS($AJ$2:$AJ$200,$G10)>0, COUNTIFS($AK$2:$AK$200,$G10)>0, COUNTIFS($AL$2:$AL$200,$G10)>0, COUNTIFS($AM$2:$AM$200,$G10)>0, COUNTIFS($AN$2:$AN$200,$G10)>0, COUNTIFS($AO$2:$AO$200,$G10)>0, COUNTIFS($AP$2:$AP$200,$G10)>0, COUNTIFS($AQ$2:$AQ$200,$G10)>0, COUNTIFS($AR$2:$AR$200,$G10)>0, COUNTIFS($AS$2:$AS$200,$G10)>0, COUNTIFS($AT$2:$AT$200,$G10)>0, COUNTIFS($AU$2:$AU$200,$G10)>0, COUNTIFS($AV$2:$AV$200,$G10)>0, COUNTIFS($AW$2:$AW$200,$G10)>0, COUNTIFS($AX$2:$AX$200,$G10)>0 )), ), 4 ), "")} | G10: Ancient Den | I10: Zimone | J10: =Zimone!G2 -> 11 | K10: Não | L10: Sim | M10: Não | N10: Sim | O10: Sim | P10: Combate | Q10: Dano Direto | R10: Terrenos e Valor | S10: =IF(J10<6,"5",IF(J10<11,"4",IF(J10<16,"3",IF(J10<31,"2","1")))) -> 3 | U10: Reliquary Tower | V10: Farseek | W10: Jidoor, Aristocratic Capital // Overture | X10: Gavony Township | Y10: Keen Duelist | Z10: Firkraag, Cunning Instigator | AA10: Merrow Commerce | AB10: Thousand-Year Elixir | AC10: Thran Dynamo | AD10: Takenuma, Charco Abandonado | AE10: Sonic Screwdriver | AF10: Watery Grave | AG10: Temporal Manipulation | AH10: Saw in Half | AI10: Jitte Perdida | AJ10: Oko, Thief of Crowns | AL10: Zagoth Triome | AQ10: The Masamune | AX10: Earth Rumble | BB10: Champions from Beyond | BC10: Dever Além da Morte | BD10: Dúplice Debochada | BE10: Jadar, Ghoulcaller of Nephalia | BF10: Mox Tantalite | BG10: Luxury Suite | BH10: Louisoix's Sacrifice | BI10: Espada de Verdade e Justiça | BJ10: Swamp | BK10: Trioma de Indatha | BL10: Season of Weaving | BM10: Red XIII, Proud Warrior | BN10: Susur Secundi, Void Altar | BP10: Earth Rumble | BS10: Boros Charm | BT10: Counterspell | BU10: Emrakul, um Novo Mundo | BV10: Drowned Catacomb | BW10: Nissa, Resurgent Animist | BX10: High-Society Hunter | BY10: Olho de Ojer Taq | BZ10: Earth Rumble | CB10: Aura Mutation | CC10: Chimil, o Sol Interior | CD10: Collector's Vault | CE10: Dispatch | CG10: Ardbert, Warrior of Darkness | CH10: Baral, Chief of Compliance | CJ10: Ancient Den
A11: =IFERROR(INDEX($S$3:$S$200, MATCH($C11, $I$3:$I$200, 0)), "") -> 3 | B11: =COUNTIF(U:AX,G11) -> 1 | C11: =IFERROR( INDEX($U$1:$AX$1, MATCH(TRUE, CHOOSE({1;2;3;4;5;6;7;8;9;10;11;12;13;14;15;16;17;18;19;20;21;22;23;24;25;26;27;28;29;30;31;32}, COUNTIFS($U$2:$U$200,$G11)>0, COUNTIFS($V$2:$V$200,$G11)>0, COUNTIFS($W$2:$W$200,$G11)>0, COUNTIFS($X$2:$X$200,$G11)>0, COUNTIFS($Y$2:$Y$200,$G11)>0, COUNTIFS($Z$2:$Z$200,$G11)>0, COUNTIFS($AA$2:$AA$200,$G11)>0, COUNTIFS($AB$2:$AB$200,$G11)>0, COUNTIFS($AC$2:$AC$200,$G11)>0, COUNTIFS($AD$2:$AD$200,$G11)>0, COUNTIFS($AE$2:$AE$200,$G11)>0, COUNTIFS($AF$2:$AF$200,$G11)>0, COUNTIFS($AG$2:$AG$200,$G11)>0, COUNTIFS($AH$2:$AH$200,$G11)>0, COUNTIFS($AI$2:$AI$200,$G11)>0, COUNTIFS($AJ$2:$AJ$200,$G11)>0, COUNTIFS($AK$2:$AK$200,$G11)>0, COUNTIFS($AL$2:$AL$200,$G11)>0, COUNTIFS($AM$2:$AM$200,$G11)>0, COUNTIFS($AN$2:$AN$200,$G11)>0, COUNTIFS($AO$2:$AO$200,$G11)>0, COUNTIFS($AP$2:$AP$200,$G11)>0, COUNTIFS($AQ$2:$AQ$200,$G11)>0, COUNTIFS($AR$2:$AR$200,$G11)>0, COUNTIFS($AS$2:$AS$200,$G11)>0, COUNTIFS($AT$2:$AT$200,$G11)>0, COUNTIFS($AU$2:$AU$200,$G11)>0, COUNTIFS($AV$2:$AV$200,$G11)>0, COUNTIFS($AW$2:$AW$200,$G11)>0, COUNTIFS($AX$2:$AX$200,$G11)>0 ), 0) ), "") -> Zimone | D11: {=IFERROR( INDEX( _xlfn._xlws.FILTER($U$1:$AX$1, TRANSPOSE( CHOOSE({1;2;3;4;5;6;7;8;9;10;11;12;13;14;15;16;17;18;19;20;21;22;23;24;25;26;27;28;29;30}, COUNTIFS($U$2:$U$200,$G11)>0, COUNTIFS($V$2:$V$200,$G11)>0, COUNTIFS($W$2:$W$200,$G11)>0, COUNTIFS($X$2:$X$200,$G11)>0, COUNTIFS($Y$2:$Y$200,$G11)>0, COUNTIFS($Z$2:$Z$200,$G11)>0, COUNTIFS($AA$2:$AA$200,$G11)>0, COUNTIFS($AB$2:$AB$200,$G11)>0, COUNTIFS($AC$2:$AC$200,$G11)>0, COUNTIFS($AD$2:$AD$200,$G11)>0, COUNTIFS($AE$2:$AE$200,$G11)>0, COUNTIFS($AF$2:$AF$200,$G11)>0, COUNTIFS($AG$2:$AG$200,$G11)>0, COUNTIFS($AH$2:$AH$200,$G11)>0, COUNTIFS($AI$2:$AI$200,$G11)>0, COUNTIFS($AJ$2:$AJ$200,$G11)>0, COUNTIFS($AK$2:$AK$200,$G11)>0, COUNTIFS($AL$2:$AL$200,$G11)>0, COUNTIFS($AM$2:$AM$200,$G11)>0, COUNTIFS($AN$2:$AN$200,$G11)>0, COUNTIFS($AO$2:$AO$200,$G11)>0, COUNTIFS($AP$2:$AP$200,$G11)>0, COUNTIFS($AQ$2:$AQ$200,$G11)>0, COUNTIFS($AR$2:$AR$200,$G11)>0, COUNTIFS($AS$2:$AS$200,$G11)>0, COUNTIFS($AT$2:$AT$200,$G11)>0, COUNTIFS($AU$2:$AU$200,$G11)>0, COUNTIFS($AV$2:$AV$200,$G11)>0, COUNTIFS($AW$2:$AW$200,$G11)>0, COUNTIFS($AX$2:$AX$200,$G11)>0 )), ), 2 ), "")} | E11: {=IFERROR( INDEX( _xlfn._xlws.FILTER($U$1:$AX$1, TRANSPOSE( CHOOSE({1;2;3;4;5;6;7;8;9;10;11;12;13;14;15;16;17;18;19;20;21;22;23;24;25;26;27;28;29;30}, COUNTIFS($U$2:$U$200,$G11)>0, COUNTIFS($V$2:$V$200,$G11)>0, COUNTIFS($W$2:$W$200,$G11)>0, COUNTIFS($X$2:$X$200,$G11)>0, COUNTIFS($Y$2:$Y$200,$G11)>0, COUNTIFS($Z$2:$Z$200,$G11)>0, COUNTIFS($AA$2:$AA$200,$G11)>0, COUNTIFS($AB$2:$AB$200,$G11)>0, COUNTIFS($AC$2:$AC$200,$G11)>0, COUNTIFS($AD$2:$AD$200,$G11)>0, COUNTIFS($AE$2:$AE$200,$G11)>0, COUNTIFS($AF$2:$AF$200,$G11)>0, COUNTIFS($AG$2:$AG$200,$G11)>0, COUNTIFS($AH$2:$AH$200,$G11)>0, COUNTIFS($AI$2:$AI$200,$G11)>0, COUNTIFS($AJ$2:$AJ$200,$G11)>0, COUNTIFS($AK$2:$AK$200,$G11)>0, COUNTIFS($AL$2:$AL$200,$G11)>0, COUNTIFS($AM$2:$AM$200,$G11)>0, COUNTIFS($AN$2:$AN$200,$G11)>0, COUNTIFS($AO$2:$AO$200,$G11)>0, COUNTIFS($AP$2:$AP$200,$G11)>0, COUNTIFS($AQ$2:$AQ$200,$G11)>0, COUNTIFS($AR$2:$AR$200,$G11)>0, COUNTIFS($AS$2:$AS$200,$G11)>0, COUNTIFS($AT$2:$AT$200,$G11)>0, COUNTIFS($AU$2:$AU$200,$G11)>0, COUNTIFS($AV$2:$AV$200,$G11)>0, COUNTIFS($AW$2:$AW$200,$G11)>0, COUNTIFS($AX$2:$AX$200,$G11)>0 )), ), 3 ), "")} | F11: {=IFERROR( INDEX( _xlfn._xlws.FILTER($U$1:$AX$1, TRANSPOSE( CHOOSE({1;2;3;4;5;6;7;8;9;10;11;12;13;14;15;16;17;18;19;20;21;22;23;24;25;26;27;28;29;30}, COUNTIFS($U$2:$U$200,$G11)>0, COUNTIFS($V$2:$V$200,$G11)>0, COUNTIFS($W$2:$W$200,$G11)>0, COUNTIFS($X$2:$X$200,$G11)>0, COUNTIFS($Y$2:$Y$200,$G11)>0, COUNTIFS($Z$2:$Z$200,$G11)>0, COUNTIFS($AA$2:$AA$200,$G11)>0, COUNTIFS($AB$2:$AB$200,$G11)>0, COUNTIFS($AC$2:$AC$200,$G11)>0, COUNTIFS($AD$2:$AD$200,$G11)>0, COUNTIFS($AE$2:$AE$200,$G11)>0, COUNTIFS($AF$2:$AF$200,$G11)>0, COUNTIFS($AG$2:$AG$200,$G11)>0, COUNTIFS($AH$2:$AH$200,$G11)>0, COUNTIFS($AI$2:$AI$200,$G11)>0, COUNTIFS($AJ$2:$AJ$200,$G11)>0, COUNTIFS($AK$2:$AK$200,$G11)>0, COUNTIFS($AL$2:$AL$200,$G11)>0, COUNTIFS($AM$2:$AM$200,$G11)>0, COUNTIFS($AN$2:$AN$200,$G11)>0, COUNTIFS($AO$2:$AO$200,$G11)>0, COUNTIFS($AP$2:$AP$200,$G11)>0, COUNTIFS($AQ$2:$AQ$200,$G11)>0, COUNTIFS($AR$2:$AR$200,$G11)>0, COUNTIFS($AS$2:$AS$200,$G11)>0, COUNTIFS($AT$2:$AT$200,$G11)>0, COUNTIFS($AU$2:$AU$200,$G11)>0, COUNTIFS($AV$2:$AV$200,$G11)>0, COUNTIFS($AW$2:$AW$200,$G11)>0, COUNTIFS($AX$2:$AX$200,$G11)>0 )), ), 4 ), "")} | G11: Ancient Greenwarden | I11: JhoiraB | J11: =JhoiraB!G2 -> 12 | K11: Não | L11: Sim | M11: Sim | N11: Não | O11: Não | P11: Combo | Q11: Combate | R11: Big Mana | S11: =IF(J11<6,"5",IF(J11<11,"4",IF(J11<16,"3",IF(J11<31,"2","1")))) -> 3 | U11: Secluded Courtyard | V11: Gavony Township | W11: Khorvath's Fury | X11: Gyre Sage | Y11: Mother of runes | Z11: Frenzied Gorespawn | AA11: Merrow Harbinger | AB11: Three Visits | AC11: Ulamog, o Profanador | AD11: Titania, Voice of Gaea | AE11: The Mycosynth Gardens | AG11: Temporal Trespass | AH11: Warren Soultrader | AI11: Kellan, the Fae-Blooded // Birthright Boon | AJ11: Ripples of Potential | AX11: Earthbending Student | BB11: Emberwilde Captain | BC11: Devoted Druid | BD11: Enduring Innocence | BE11: Kodama's Reach | BF11: Petrified Field | BG11: Mandate of Peace | BH11: Mistbind Clique | BI11: Firion, Wild Rose Warrior | BJ11: Three Tree City | BK11: Trioma de Raugrin | BL11: Serenata das Estriges | BM11: Reflecting Pool | BN11: Warren Soultrader | BP11: Earthbending Student | BS11: Broadside Bombardiers | BT11: Cyber Conversion | BU11: Entomb | BV11: Elspeth, Sun's Champion | BW11: Obelisco de Obsidiana | BX11: Invasion of Segovia | BY11: Renewed Solidarity | BZ11: Earthbending Student | CB11: Autoridade dos Cônsules | CC11: Cid, Freeflier Pilot | CD11: Daretti, Ingenious Iconoclast | CE11: Dollmaker's Shop // Porcelain Gallery | CG11: Arid Mesa | CH11: Beast Within | CJ11: Ancient Greenwarden
A12: =IFERROR(INDEX($S$3:$S$200, MATCH($C12, $I$3:$I$200, 0)), "") -> 3 | B12: =COUNTIF(U:AX,G12) -> 1 | C12: =IFERROR( INDEX($U$1:$AX$1, MATCH(TRUE, CHOOSE({1;2;3;4;5;6;7;8;9;10;11;12;13;14;15;16;17;18;19;20;21;22;23;24;25;26;27;28;29;30;31;32}, COUNTIFS($U$2:$U$200,$G12)>0, COUNTIFS($V$2:$V$200,$G12)>0, COUNTIFS($W$2:$W$200,$G12)>0, COUNTIFS($X$2:$X$200,$G12)>0, COUNTIFS($Y$2:$Y$200,$G12)>0, COUNTIFS($Z$2:$Z$200,$G12)>0, COUNTIFS($AA$2:$AA$200,$G12)>0, COUNTIFS($AB$2:$AB$200,$G12)>0, COUNTIFS($AC$2:$AC$200,$G12)>0, COUNTIFS($AD$2:$AD$200,$G12)>0, COUNTIFS($AE$2:$AE$200,$G12)>0, COUNTIFS($AF$2:$AF$200,$G12)>0, COUNTIFS($AG$2:$AG$200,$G12)>0, COUNTIFS($AH$2:$AH$200,$G12)>0, COUNTIFS($AI$2:$AI$200,$G12)>0, COUNTIFS($AJ$2:$AJ$200,$G12)>0, COUNTIFS($AK$2:$AK$200,$G12)>0, COUNTIFS($AL$2:$AL$200,$G12)>0, COUNTIFS($AM$2:$AM$200,$G12)>0, COUNTIFS($AN$2:$AN$200,$G12)>0, COUNTIFS($AO$2:$AO$200,$G12)>0, COUNTIFS($AP$2:$AP$200,$G12)>0, COUNTIFS($AQ$2:$AQ$200,$G12)>0, COUNTIFS($AR$2:$AR$200,$G12)>0, COUNTIFS($AS$2:$AS$200,$G12)>0, COUNTIFS($AT$2:$AT$200,$G12)>0, COUNTIFS($AU$2:$AU$200,$G12)>0, COUNTIFS($AV$2:$AV$200,$G12)>0, COUNTIFS($AW$2:$AW$200,$G12)>0, COUNTIFS($AX$2:$AX$200,$G12)>0 ), 0) ), "") -> Gritrog | D12: {=IFERROR( INDEX( _xlfn._xlws.FILTER($U$1:$AX$1, TRANSPOSE( CHOOSE({1;2;3;4;5;6;7;8;9;10;11;12;13;14;15;16;17;18;19;20;21;22;23;24;25;26;27;28;29;30}, COUNTIFS($U$2:$U$200,$G12)>0, COUNTIFS($V$2:$V$200,$G12)>0, COUNTIFS($W$2:$W$200,$G12)>0, COUNTIFS($X$2:$X$200,$G12)>0, COUNTIFS($Y$2:$Y$200,$G12)>0, COUNTIFS($Z$2:$Z$200,$G12)>0, COUNTIFS($AA$2:$AA$200,$G12)>0, COUNTIFS($AB$2:$AB$200,$G12)>0, COUNTIFS($AC$2:$AC$200,$G12)>0, COUNTIFS($AD$2:$AD$200,$G12)>0, COUNTIFS($AE$2:$AE$200,$G12)>0, COUNTIFS($AF$2:$AF$200,$G12)>0, COUNTIFS($AG$2:$AG$200,$G12)>0, COUNTIFS($AH$2:$AH$200,$G12)>0, COUNTIFS($AI$2:$AI$200,$G12)>0, COUNTIFS($AJ$2:$AJ$200,$G12)>0, COUNTIFS($AK$2:$AK$200,$G12)>0, COUNTIFS($AL$2:$AL$200,$G12)>0, COUNTIFS($AM$2:$AM$200,$G12)>0, COUNTIFS($AN$2:$AN$200,$G12)>0, COUNTIFS($AO$2:$AO$200,$G12)>0, COUNTIFS($AP$2:$AP$200,$G12)>0, COUNTIFS($AQ$2:$AQ$200,$G12)>0, COUNTIFS($AR$2:$AR$200,$G12)>0, COUNTIFS($AS$2:$AS$200,$G12)>0, COUNTIFS($AT$2:$AT$200,$G12)>0, COUNTIFS($AU$2:$AU$200,$G12)>0, COUNTIFS($AV$2:$AV$200,$G12)>0, COUNTIFS($AW$2:$AW$200,$G12)>0, COUNTIFS($AX$2:$AX$200,$G12)>0 )), ), 2 ), "")} | E12: {=IFERROR( INDEX( _xlfn._xlws.FILTER($U$1:$AX$1, TRANSPOSE( CHOOSE({1;2;3;4;5;6;7;8;9;10;11;12;13;14;15;16;17;18;19;20;21;22;23;24;25;26;27;28;29;30}, COUNTIFS($U$2:$U$200,$G12)>0, COUNTIFS($V$2:$V$200,$G12)>0, COUNTIFS($W$2:$W$200,$G12)>0, COUNTIFS($X$2:$X$200,$G12)>0, COUNTIFS($Y$2:$Y$200,$G12)>0, COUNTIFS($Z$2:$Z$200,$G12)>0, COUNTIFS($AA$2:$AA$200,$G12)>0, COUNTIFS($AB$2:$AB$200,$G12)>0, COUNTIFS($AC$2:$AC$200,$G12)>0, COUNTIFS($AD$2:$AD$200,$G12)>0, COUNTIFS($AE$2:$AE$200,$G12)>0, COUNTIFS($AF$2:$AF$200,$G12)>0, COUNTIFS($AG$2:$AG$200,$G12)>0, COUNTIFS($AH$2:$AH$200,$G12)>0, COUNTIFS($AI$2:$AI$200,$G12)>0, COUNTIFS($AJ$2:$AJ$200,$G12)>0, COUNTIFS($AK$2:$AK$200,$G12)>0, COUNTIFS($AL$2:$AL$200,$G12)>0, COUNTIFS($AM$2:$AM$200,$G12)>0, COUNTIFS($AN$2:$AN$200,$G12)>0, COUNTIFS($AO$2:$AO$200,$G12)>0, COUNTIFS($AP$2:$AP$200,$G12)>0, COUNTIFS($AQ$2:$AQ$200,$G12)>0, COUNTIFS($AR$2:$AR$200,$G12)>0, COUNTIFS($AS$2:$AS$200,$G12)>0, COUNTIFS($AT$2:$AT$200,$G12)>0, COUNTIFS($AU$2:$AU$200,$G12)>0, COUNTIFS($AV$2:$AV$200,$G12)>0, COUNTIFS($AW$2:$AW$200,$G12)>0, COUNTIFS($AX$2:$AX$200,$G12)>0 )), ), 3 ), "")} | F12: {=IFERROR( INDEX( _xlfn._xlws.FILTER($U$1:$AX$1, TRANSPOSE( CHOOSE({1;2;3;4;5;6;7;8;9;10;11;12;13;14;15;16;17;18;19;20;21;22;23;24;25;26;27;28;29;30}, COUNTIFS($U$2:$U$200,$G12)>0, COUNTIFS($V$2:$V$200,$G12)>0, COUNTIFS($W$2:$W$200,$G12)>0, COUNTIFS($X$2:$X$200,$G12)>0, COUNTIFS($Y$2:$Y$200,$G12)>0, COUNTIFS($Z$2:$Z$200,$G12)>0, COUNTIFS($AA$2:$AA$200,$G12)>0, COUNTIFS($AB$2:$AB$200,$G12)>0, COUNTIFS($AC$2:$AC$200,$G12)>0, COUNTIFS($AD$2:$AD$200,$G12)>0, COUNTIFS($AE$2:$AE$200,$G12)>0, COUNTIFS($AF$2:$AF$200,$G12)>0, COUNTIFS($AG$2:$AG$200,$G12)>0, COUNTIFS($AH$2:$AH$200,$G12)>0, COUNTIFS($AI$2:$AI$200,$G12)>0, COUNTIFS($AJ$2:$AJ$200,$G12)>0, COUNTIFS($AK$2:$AK$200,$G12)>0, COUNTIFS($AL$2:$AL$200,$G12)>0, COUNTIFS($AM$2:$AM$200,$G12)>0, COUNTIFS($AN$2:$AN$200,$G12)>0, COUNTIFS($AO$2:$AO$200,$G12)>0, COUNTIFS($AP$2:$AP$200,$G12)>0, COUNTIFS($AQ$2:$AQ$200,$G12)>0, COUNTIFS($AR$2:$AR$200,$G12)>0, COUNTIFS($AS$2:$AS$200,$G12)>0, COUNTIFS($AT$2:$AT$200,$G12)>0, COUNTIFS($AU$2:$AU$200,$G12)>0, COUNTIFS($AV$2:$AV$200,$G12)>0, COUNTIFS($AW$2:$AW$200,$G12)>0, COUNTIFS($AX$2:$AX$200,$G12)>0 )), ), 4 ), "")} | G12: Ancient Tomb | I12: Gritrog | J12: =Gitrog!G2 -> 11 | K12: Não | L12: Não | M12: Não | N12: Sim | O12: Sim | P12: Combo | Q12: - | R12: Fast Combo | S12: =IF(J12<6,"5",IF(J12<11,"4",IF(J12<16,"3",IF(J12<31,"2","1")))) -> 3 | U12: Shoot the Sheriff | V12: Generous Gift | W12: Lightning Greaves | X12: Hydra's Growth | Y12: Sevinne's Reclamation | Z12: Gallifrey Council Chamber | AA12: Reliquary Tower | AB12: Zagoth Triome | AC12: Ulamog's Dreadsire | AD12: Ulamog, the Infinite Gyre | AE12: Vexing Puzzlebox | AG12: Valfenda | AI12: Lightning Greaves | AJ12: Vronos, Masked Inquisitor | AX12: Elvish Reclaimer | BB12: Exalted Sunborn | BC12: Forest | BD12: Exemplar of Light | BE12: Lord of Atlantis | BF12: Phyrexian Tower | BG12: Mirrex | BH12: Molten Echoes | BI12: Freyalise, Llanowar's Fury | BJ12: Uthros, Titanic Godcore | BK12: Trioma de Zagoth | BL12: Sokenzan, Crisol da Afronta | BM12: Saqueador Amaldiçoado | BN12: Westvale Abbey | BP12: Elvish Reclaimer | BS12: Brushland | BT12: Deeproot Historian | BU12: Extinguisher Battleship | BV12: Espada da Riqueza e do Poder | BW12: Overgrown Tomb | BX12: Jenova, Ancient Calamity | BY12: Scattered Groves | BZ12: Elvish Reclaimer | CB12: Back in Town | CC12: Cloud, Midgar Mercenary | CD12: Dionus, Elvish Archdruid | CE12: Duty Beyond Death | CG12: Artifact Mutation | CH12: Bugenhagen, Wise Elder | CJ12: Ancient Tomb
A13: =IFERROR(INDEX($S$3:$S$200, MATCH($C13, $I$3:$I$200, 0)), "") -> 5 | B13: =COUNTIF(U:AX,G13) -> 1 | C13: =IFERROR( INDEX($U$1:$AX$1, MATCH(TRUE, CHOOSE({1;2;3;4;5;6;7;8;9;10;11;12;13;14;15;16;17;18;19;20;21;22;23;24;25;26;27;28;29;30;31;32}, COUNTIFS($U$2:$U$200,$G13)>0, COUNTIFS($V$2:$V$200,$G13)>0, COUNTIFS($W$2:$W$200,$G13)>0, COUNTIFS($X$2:$X$200,$G13)>0, COUNTIFS($Y$2:$Y$200,$G13)>0, COUNTIFS($Z$2:$Z$200,$G13)>0, COUNTIFS($AA$2:$AA$200,$G13)>0, COUNTIFS($AB$2:$AB$200,$G13)>0, COUNTIFS($AC$2:$AC$200,$G13)>0, COUNTIFS($AD$2:$AD$200,$G13)>0, COUNTIFS($AE$2:$AE$200,$G13)>0, COUNTIFS($AF$2:$AF$200,$G13)>0, COUNTIFS($AG$2:$AG$200,$G13)>0, COUNTIFS($AH$2:$AH$200,$G13)>0, COUNTIFS($AI$2:$AI$200,$G13)>0, COUNTIFS($AJ$2:$AJ$200,$G13)>0, COUNTIFS($AK$2:$AK$200,$G13)>0, COUNTIFS($AL$2:$AL$200,$G13)>0, COUNTIFS($AM$2:$AM$200,$G13)>0, COUNTIFS($AN$2:$AN$200,$G13)>0, COUNTIFS($AO$2:$AO$200,$G13)>0, COUNTIFS($AP$2:$AP$200,$G13)>0, COUNTIFS($AQ$2:$AQ$200,$G13)>0, COUNTIFS($AR$2:$AR$200,$G13)>0, COUNTIFS($AS$2:$AS$200,$G13)>0, COUNTIFS($AT$2:$AT$200,$G13)>0, COUNTIFS($AU$2:$AU$200,$G13)>0, COUNTIFS($AV$2:$AV$200,$G13)>0, COUNTIFS($AW$2:$AW$200,$G13)>0, COUNTIFS($AX$2:$AX$200,$G13)>0 ), 0) ), "") -> Zedruu | D13: {=IFERROR( INDEX( _xlfn._xlws.FILTER($U$1:$AX$1, TRANSPOSE( CHOOSE({1;2;3;4;5;6;7;8;9;10;11;12;13;14;15;16;17;18;19;20;21;22;23;24;25;26;27;28;29;30}, COUNTIFS($U$2:$U$200,$G13)>0, COUNTIFS($V$2:$V$200,$G13)>0, COUNTIFS($W$2:$W$200,$G13)>0, COUNTIFS($X$2:$X$200,$G13)>0, COUNTIFS($Y$2:$Y$200,$G13)>0, COUNTIFS($Z$2:$Z$200,$G13)>0, COUNTIFS($AA$2:$AA$200,$G13)>0, COUNTIFS($AB$2:$AB$200,$G13)>0, COUNTIFS($AC$2:$AC$200,$G13)>0, COUNTIFS($AD$2:$AD$200,$G13)>0, COUNTIFS($AE$2:$AE$200,$G13)>0, COUNTIFS($AF$2:$AF$200,$G13)>0, COUNTIFS($AG$2:$AG$200,$G13)>0, COUNTIFS($AH$2:$AH$200,$G13)>0, COUNTIFS($AI$2:$AI$200,$G13)>0, COUNTIFS($AJ$2:$AJ$200,$G13)>0, COUNTIFS($AK$2:$AK$200,$G13)>0, COUNTIFS($AL$2:$AL$200,$G13)>0, COUNTIFS($AM$2:$AM$200,$G13)>0, COUNTIFS($AN$2:$AN$200,$G13)>0, COUNTIFS($AO$2:$AO$200,$G13)>0, COUNTIFS($AP$2:$AP$200,$G13)>0, COUNTIFS($AQ$2:$AQ$200,$G13)>0, COUNTIFS($AR$2:$AR$200,$G13)>0, COUNTIFS($AS$2:$AS$200,$G13)>0, COUNTIFS($AT$2:$AT$200,$G13)>0, COUNTIFS($AU$2:$AU$200,$G13)>0, COUNTIFS($AV$2:$AV$200,$G13)>0, COUNTIFS($AW$2:$AW$200,$G13)>0, COUNTIFS($AX$2:$AX$200,$G13)>0 )), ), 2 ), "")} | E13: {=IFERROR( INDEX( _xlfn._xlws.FILTER($U$1:$AX$1, TRANSPOSE( CHOOSE({1;2;3;4;5;6;7;8;9;10;11;12;13;14;15;16;17;18;19;20;21;22;23;24;25;26;27;28;29;30}, COUNTIFS($U$2:$U$200,$G13)>0, COUNTIFS($V$2:$V$200,$G13)>0, COUNTIFS($W$2:$W$200,$G13)>0, COUNTIFS($X$2:$X$200,$G13)>0, COUNTIFS($Y$2:$Y$200,$G13)>0, COUNTIFS($Z$2:$Z$200,$G13)>0, COUNTIFS($AA$2:$AA$200,$G13)>0, COUNTIFS($AB$2:$AB$200,$G13)>0, COUNTIFS($AC$2:$AC$200,$G13)>0, COUNTIFS($AD$2:$AD$200,$G13)>0, COUNTIFS($AE$2:$AE$200,$G13)>0, COUNTIFS($AF$2:$AF$200,$G13)>0, COUNTIFS($AG$2:$AG$200,$G13)>0, COUNTIFS($AH$2:$AH$200,$G13)>0, COUNTIFS($AI$2:$AI$200,$G13)>0, COUNTIFS($AJ$2:$AJ$200,$G13)>0, COUNTIFS($AK$2:$AK$200,$G13)>0, COUNTIFS($AL$2:$AL$200,$G13)>0, COUNTIFS($AM$2:$AM$200,$G13)>0, COUNTIFS($AN$2:$AN$200,$G13)>0, COUNTIFS($AO$2:$AO$200,$G13)>0, COUNTIFS($AP$2:$AP$200,$G13)>0, COUNTIFS($AQ$2:$AQ$200,$G13)>0, COUNTIFS($AR$2:$AR$200,$G13)>0, COUNTIFS($AS$2:$AS$200,$G13)>0, COUNTIFS($AT$2:$AT$200,$G13)>0, COUNTIFS($AU$2:$AU$200,$G13)>0, COUNTIFS($AV$2:$AV$200,$G13)>0, COUNTIFS($AW$2:$AW$200,$G13)>0, COUNTIFS($AX$2:$AX$200,$G13)>0 )), ), 3 ), "")} | F13: {=IFERROR( INDEX( _xlfn._xlws.FILTER($U$1:$AX$1, TRANSPOSE( CHOOSE({1;2;3;4;5;6;7;8;9;10;11;12;13;14;15;16;17;18;19;20;21;22;23;24;25;26;27;28;29;30}, COUNTIFS($U$2:$U$200,$G13)>0, COUNTIFS($V$2:$V$200,$G13)>0, COUNTIFS($W$2:$W$200,$G13)>0, COUNTIFS($X$2:$X$200,$G13)>0, COUNTIFS($Y$2:$Y$200,$G13)>0, COUNTIFS($Z$2:$Z$200,$G13)>0, COUNTIFS($AA$2:$AA$200,$G13)>0, COUNTIFS($AB$2:$AB$200,$G13)>0, COUNTIFS($AC$2:$AC$200,$G13)>0, COUNTIFS($AD$2:$AD$200,$G13)>0, COUNTIFS($AE$2:$AE$200,$G13)>0, COUNTIFS($AF$2:$AF$200,$G13)>0, COUNTIFS($AG$2:$AG$200,$G13)>0, COUNTIFS($AH$2:$AH$200,$G13)>0, COUNTIFS($AI$2:$AI$200,$G13)>0, COUNTIFS($AJ$2:$AJ$200,$G13)>0, COUNTIFS($AK$2:$AK$200,$G13)>0, COUNTIFS($AL$2:$AL$200,$G13)>0, COUNTIFS($AM$2:$AM$200,$G13)>0, COUNTIFS($AN$2:$AN$200,$G13)>0, COUNTIFS($AO$2:$AO$200,$G13)>0, COUNTIFS($AP$2:$AP$200,$G13)>0, COUNTIFS($AQ$2:$AQ$200,$G13)>0, COUNTIFS($AR$2:$AR$200,$G13)>0, COUNTIFS($AS$2:$AS$200,$G13)>0, COUNTIFS($AT$2:$AT$200,$G13)>0, COUNTIFS($AU$2:$AU$200,$G13)>0, COUNTIFS($AV$2:$AV$200,$G13)>0, COUNTIFS($AW$2:$AW$200,$G13)>0, COUNTIFS($AX$2:$AX$200,$G13)>0 )), ), 4 ), "")} | G13: Árbitro Silencioso | I13: Muzzio | J13: =Muzzio!G2 -> 11 | K13: Não | L13: Sim | M13: Não | N13: Não | O13: Não | P13: Combo | Q13: - | R13: Engrenagens para Combar | S13: =IF(J13<6,"5",IF(J13<11,"4",IF(J13<16,"3",IF(J13<31,"2","1")))) -> 3 | U13: Storm the Vault | V13: Jacked Rabbit | W13: Maddening Cacophony | X13: Incubation Druid | Y13: Takenuma, Charco Abandonado | Z13: Ghoulish Impetus | AA13: Seahunter | AC13: Valfenda | AG13: Watery Grave | AI13: Stoneforge Mystic | AX13: Esper Sentinel | BB13: Fabled Passage | BC13: Full Throttle | BD13: Fellwar Stone | BE13: Lullmage Mentor | BF13: Ripples of Undeath | BG13: Polluted Delta | BH13: Morphic Pool | BI13: Jitte Perdida | BJ13: Watery Grave | BK13: Ulamog, o Profanador | BL13: Sonic Screwdriver | BM13: The Masamune | BP13: Esper Sentinel | BS13: Cankerbloom | BT13: Drowned Catacomb | BU13: Gerrard's Hourglass Pendant | BV13: Espada de Banquete e Fome | BW13: Planetary Annihilation | BX13: Jidoor, Aristocratic Capital // Overture | BY13: Stridehangar Automaton | BZ13: Esper Sentinel | CB13: Beast Within | CC13: Commodore Guff | CD13: Emrakul, um Novo Mundo | CE13: Earth Rumble | CG13: Arwen, Weaver of Hope | CH13: Careful Study | CJ13: Árbitro Silencioso
A14: =IFERROR(INDEX($S$3:$S$200, MATCH($C14, $I$3:$I$200, 0)), "") -> 4 | B14: =COUNTIF(U:AX,G14) -> 1 | C14: =IFERROR( INDEX($U$1:$AX$1, MATCH(TRUE, CHOOSE({1;2;3;4;5;6;7;8;9;10;11;12;13;14;15;16;17;18;19;20;21;22;23;24;25;26;27;28;29;30;31;32}, COUNTIFS($U$2:$U$200,$G14)>0, COUNTIFS($V$2:$V$200,$G14)>0, COUNTIFS($W$2:$W$200,$G14)>0, COUNTIFS($X$2:$X$200,$G14)>0, COUNTIFS($Y$2:$Y$200,$G14)>0, COUNTIFS($Z$2:$Z$200,$G14)>0, COUNTIFS($AA$2:$AA$200,$G14)>0, COUNTIFS($AB$2:$AB$200,$G14)>0, COUNTIFS($AC$2:$AC$200,$G14)>0, COUNTIFS($AD$2:$AD$200,$G14)>0, COUNTIFS($AE$2:$AE$200,$G14)>0, COUNTIFS($AF$2:$AF$200,$G14)>0, COUNTIFS($AG$2:$AG$200,$G14)>0, COUNTIFS($AH$2:$AH$200,$G14)>0, COUNTIFS($AI$2:$AI$200,$G14)>0, COUNTIFS($AJ$2:$AJ$200,$G14)>0, COUNTIFS($AK$2:$AK$200,$G14)>0, COUNTIFS($AL$2:$AL$200,$G14)>0, COUNTIFS($AM$2:$AM$200,$G14)>0, COUNTIFS($AN$2:$AN$200,$G14)>0, COUNTIFS($AO$2:$AO$200,$G14)>0, COUNTIFS($AP$2:$AP$200,$G14)>0, COUNTIFS($AQ$2:$AQ$200,$G14)>0, COUNTIFS($AR$2:$AR$200,$G14)>0, COUNTIFS($AS$2:$AS$200,$G14)>0, COUNTIFS($AT$2:$AT$200,$G14)>0, COUNTIFS($AU$2:$AU$200,$G14)>0, COUNTIFS($AV$2:$AV$200,$G14)>0, COUNTIFS($AW$2:$AW$200,$G14)>0, COUNTIFS($AX$2:$AX$200,$G14)>0 ), 0) ), "") -> Inalla | D14: {=IFERROR( INDEX( _xlfn._xlws.FILTER($U$1:$AX$1, TRANSPOSE( CHOOSE({1;2;3;4;5;6;7;8;9;10;11;12;13;14;15;16;17;18;19;20;21;22;23;24;25;26;27;28;29;30}, COUNTIFS($U$2:$U$200,$G14)>0, COUNTIFS($V$2:$V$200,$G14)>0, COUNTIFS($W$2:$W$200,$G14)>0, COUNTIFS($X$2:$X$200,$G14)>0, COUNTIFS($Y$2:$Y$200,$G14)>0, COUNTIFS($Z$2:$Z$200,$G14)>0, COUNTIFS($AA$2:$AA$200,$G14)>0, COUNTIFS($AB$2:$AB$200,$G14)>0, COUNTIFS($AC$2:$AC$200,$G14)>0, COUNTIFS($AD$2:$AD$200,$G14)>0, COUNTIFS($AE$2:$AE$200,$G14)>0, COUNTIFS($AF$2:$AF$200,$G14)>0, COUNTIFS($AG$2:$AG$200,$G14)>0, COUNTIFS($AH$2:$AH$200,$G14)>0, COUNTIFS($AI$2:$AI$200,$G14)>0, COUNTIFS($AJ$2:$AJ$200,$G14)>0, COUNTIFS($AK$2:$AK$200,$G14)>0, COUNTIFS($AL$2:$AL$200,$G14)>0, COUNTIFS($AM$2:$AM$200,$G14)>0, COUNTIFS($AN$2:$AN$200,$G14)>0, COUNTIFS($AO$2:$AO$200,$G14)>0, COUNTIFS($AP$2:$AP$200,$G14)>0, COUNTIFS($AQ$2:$AQ$200,$G14)>0, COUNTIFS($AR$2:$AR$200,$G14)>0, COUNTIFS($AS$2:$AS$200,$G14)>0, COUNTIFS($AT$2:$AT$200,$G14)>0, COUNTIFS($AU$2:$AU$200,$G14)>0, COUNTIFS($AV$2:$AV$200,$G14)>0, COUNTIFS($AW$2:$AW$200,$G14)>0, COUNTIFS($AX$2:$AX$200,$G14)>0 )), ), 2 ), "")} | E14: {=IFERROR( INDEX( _xlfn._xlws.FILTER($U$1:$AX$1, TRANSPOSE( CHOOSE({1;2;3;4;5;6;7;8;9;10;11;12;13;14;15;16;17;18;19;20;21;22;23;24;25;26;27;28;29;30}, COUNTIFS($U$2:$U$200,$G14)>0, COUNTIFS($V$2:$V$200,$G14)>0, COUNTIFS($W$2:$W$200,$G14)>0, COUNTIFS($X$2:$X$200,$G14)>0, COUNTIFS($Y$2:$Y$200,$G14)>0, COUNTIFS($Z$2:$Z$200,$G14)>0, COUNTIFS($AA$2:$AA$200,$G14)>0, COUNTIFS($AB$2:$AB$200,$G14)>0, COUNTIFS($AC$2:$AC$200,$G14)>0, COUNTIFS($AD$2:$AD$200,$G14)>0, COUNTIFS($AE$2:$AE$200,$G14)>0, COUNTIFS($AF$2:$AF$200,$G14)>0, COUNTIFS($AG$2:$AG$200,$G14)>0, COUNTIFS($AH$2:$AH$200,$G14)>0, COUNTIFS($AI$2:$AI$200,$G14)>0, COUNTIFS($AJ$2:$AJ$200,$G14)>0, COUNTIFS($AK$2:$AK$200,$G14)>0, COUNTIFS($AL$2:$AL$200,$G14)>0, COUNTIFS($AM$2:$AM$200,$G14)>0, COUNTIFS($AN$2:$AN$200,$G14)>0, COUNTIFS($AO$2:$AO$200,$G14)>0, COUNTIFS($AP$2:$AP$200,$G14)>0, COUNTIFS($AQ$2:$AQ$200,$G14)>0, COUNTIFS($AR$2:$AR$200,$G14)>0, COUNTIFS($AS$2:$AS$200,$G14)>0, COUNTIFS($AT$2:$AT$200,$G14)>0, COUNTIFS($AU$2:$AU$200,$G14)>0, COUNTIFS($AV$2:$AV$200,$G14)>0, COUNTIFS($AW$2:$AW$200,$G14)>0, COUNTIFS($AX$2:$AX$200,$G14)>0 )), ), 3 ), "")} | F14: {=IFERROR( INDEX( _xlfn._xlws.FILTER($U$1:$AX$1, TRANSPOSE( CHOOSE({1;2;3;4;5;6;7;8;9;10;11;12;13;14;15;16;17;18;19;20;21;22;23;24;25;26;27;28;29;30}, COUNTIFS($U$2:$U$200,$G14)>0, COUNTIFS($V$2:$V$200,$G14)>0, COUNTIFS($W$2:$W$200,$G14)>0, COUNTIFS($X$2:$X$200,$G14)>0, COUNTIFS($Y$2:$Y$200,$G14)>0, COUNTIFS($Z$2:$Z$200,$G14)>0, COUNTIFS($AA$2:$AA$200,$G14)>0, COUNTIFS($AB$2:$AB$200,$G14)>0, COUNTIFS($AC$2:$AC$200,$G14)>0, COUNTIFS($AD$2:$AD$200,$G14)>0, COUNTIFS($AE$2:$AE$200,$G14)>0, COUNTIFS($AF$2:$AF$200,$G14)>0, COUNTIFS($AG$2:$AG$200,$G14)>0, COUNTIFS($AH$2:$AH$200,$G14)>0, COUNTIFS($AI$2:$AI$200,$G14)>0, COUNTIFS($AJ$2:$AJ$200,$G14)>0, COUNTIFS($AK$2:$AK$200,$G14)>0, COUNTIFS($AL$2:$AL$200,$G14)>0, COUNTIFS($AM$2:$AM$200,$G14)>0, COUNTIFS($AN$2:$AN$200,$G14)>0, COUNTIFS($AO$2:$AO$200,$G14)>0, COUNTIFS($AP$2:$AP$200,$G14)>0, COUNTIFS($AQ$2:$AQ$200,$G14)>0, COUNTIFS($AR$2:$AR$200,$G14)>0, COUNTIFS($AS$2:$AS$200,$G14)>0, COUNTIFS($AT$2:$AT$200,$G14)>0, COUNTIFS($AU$2:$AU$200,$G14)>0, COUNTIFS($AV$2:$AV$200,$G14)>0, COUNTIFS($AW$2:$AW$200,$G14)>0, COUNTIFS($AX$2:$AX$200,$G14)>0 )), ), 4 ), "")} | G14: Arcane Lighthouse | I14: VialIshai | J14: =VialIshai!G2 -> 9 | K14: Sim | L14: Sim | M14: Sim | N14: Sim | O14: Não | P14: Ping | Q14: Voltron | R14: Controlar e Punir | S14: =IF(J14<6,"5",IF(J14<11,"4",IF(J14<16,"3",IF(J14<31,"2","1")))) -> 4 | U14: Temple of Malice | V14: Jetmir, Nexus of Revels | W14: Memory Erosion | X14: Kutzil, Malamet Exemplar | Y14: Unholy Annex // Ritual Chamber | Z14: Havengul Laboratory | AA14: Simic Charm | AX14: Evendo Brushrazer | BB14: Farmer Cotton | BC14: Gavony Township | BD14: Firkraag, Cunning Instigator | BE14: Merrow Commerce | BF14: Rise of the Eldrazi | BG14: Portal to Phyrexia | BH14: Reliquary Tower | BI14: Karn Liberated | BJ14: Zagoth Triome | BK14: Valfenda | BL14: Três Passos à Frente | BP14: Evendo Brushrazer | BS14: Canopy Vista | BT14: Dúplice Debochada | BU14: Hedge Shredder | BV14: Espada de Fogo e Gelo | BW14: Raffine's Tower | BX14: Nibelheim Aflame | BY14: Susur Secundi, Void Altar | BZ14: Evendo Brushrazer | CB14: Bojuka Bog | CC14: Creeping Tar Pit | CD14: Evendo, Waking Haven | CE14: Earthbending Student | CG14: Ascensão do Avernus | CH14: Caverna das Almas | CJ14: Arcane Lighthouse
A15: =IFERROR(INDEX($S$3:$S$200, MATCH($C15, $I$3:$I$200, 0)), "") -> 1 | B15: =COUNTIF(U:AX,G15) -> 1 | C15: =IFERROR( INDEX($U$1:$AX$1, MATCH(TRUE, CHOOSE({1;2;3;4;5;6;7;8;9;10;11;12;13;14;15;16;17;18;19;20;21;22;23;24;25;26;27;28;29;30;31;32}, COUNTIFS($U$2:$U$200,$G15)>0, COUNTIFS($V$2:$V$200,$G15)>0, COUNTIFS($W$2:$W$200,$G15)>0, COUNTIFS($X$2:$X$200,$G15)>0, COUNTIFS($Y$2:$Y$200,$G15)>0, COUNTIFS($Z$2:$Z$200,$G15)>0, COUNTIFS($AA$2:$AA$200,$G15)>0, COUNTIFS($AB$2:$AB$200,$G15)>0, COUNTIFS($AC$2:$AC$200,$G15)>0, COUNTIFS($AD$2:$AD$200,$G15)>0, COUNTIFS($AE$2:$AE$200,$G15)>0, COUNTIFS($AF$2:$AF$200,$G15)>0, COUNTIFS($AG$2:$AG$200,$G15)>0, COUNTIFS($AH$2:$AH$200,$G15)>0, COUNTIFS($AI$2:$AI$200,$G15)>0, COUNTIFS($AJ$2:$AJ$200,$G15)>0, COUNTIFS($AK$2:$AK$200,$G15)>0, COUNTIFS($AL$2:$AL$200,$G15)>0, COUNTIFS($AM$2:$AM$200,$G15)>0, COUNTIFS($AN$2:$AN$200,$G15)>0, COUNTIFS($AO$2:$AO$200,$G15)>0, COUNTIFS($AP$2:$AP$200,$G15)>0, COUNTIFS($AQ$2:$AQ$200,$G15)>0, COUNTIFS($AR$2:$AR$200,$G15)>0, COUNTIFS($AS$2:$AS$200,$G15)>0, COUNTIFS($AT$2:$AT$200,$G15)>0, COUNTIFS($AU$2:$AU$200,$G15)>0, COUNTIFS($AV$2:$AV$200,$G15)>0, COUNTIFS($AW$2:$AW$200,$G15)>0, COUNTIFS($AX$2:$AX$200,$G15)>0 ), 0) ), "") -> Modular | D15: {=IFERROR( INDEX( _xlfn._xlws.FILTER($U$1:$AX$1, TRANSPOSE( CHOOSE({1;2;3;4;5;6;7;8;9;10;11;12;13;14;15;16;17;18;19;20;21;22;23;24;25;26;27;28;29;30}, COUNTIFS($U$2:$U$200,$G15)>0, COUNTIFS($V$2:$V$200,$G15)>0, COUNTIFS($W$2:$W$200,$G15)>0, COUNTIFS($X$2:$X$200,$G15)>0, COUNTIFS($Y$2:$Y$200,$G15)>0, COUNTIFS($Z$2:$Z$200,$G15)>0, COUNTIFS($AA$2:$AA$200,$G15)>0, COUNTIFS($AB$2:$AB$200,$G15)>0, COUNTIFS($AC$2:$AC$200,$G15)>0, COUNTIFS($AD$2:$AD$200,$G15)>0, COUNTIFS($AE$2:$AE$200,$G15)>0, COUNTIFS($AF$2:$AF$200,$G15)>0, COUNTIFS($AG$2:$AG$200,$G15)>0, COUNTIFS($AH$2:$AH$200,$G15)>0, COUNTIFS($AI$2:$AI$200,$G15)>0, COUNTIFS($AJ$2:$AJ$200,$G15)>0, COUNTIFS($AK$2:$AK$200,$G15)>0, COUNTIFS($AL$2:$AL$200,$G15)>0, COUNTIFS($AM$2:$AM$200,$G15)>0, COUNTIFS($AN$2:$AN$200,$G15)>0, COUNTIFS($AO$2:$AO$200,$G15)>0, COUNTIFS($AP$2:$AP$200,$G15)>0, COUNTIFS($AQ$2:$AQ$200,$G15)>0, COUNTIFS($AR$2:$AR$200,$G15)>0, COUNTIFS($AS$2:$AS$200,$G15)>0, COUNTIFS($AT$2:$AT$200,$G15)>0, COUNTIFS($AU$2:$AU$200,$G15)>0, COUNTIFS($AV$2:$AV$200,$G15)>0, COUNTIFS($AW$2:$AW$200,$G15)>0, COUNTIFS($AX$2:$AX$200,$G15)>0 )), ), 2 ), "")} | E15: {=IFERROR( INDEX( _xlfn._xlws.FILTER($U$1:$AX$1, TRANSPOSE( CHOOSE({1;2;3;4;5;6;7;8;9;10;11;12;13;14;15;16;17;18;19;20;21;22;23;24;25;26;27;28;29;30}, COUNTIFS($U$2:$U$200,$G15)>0, COUNTIFS($V$2:$V$200,$G15)>0, COUNTIFS($W$2:$W$200,$G15)>0, COUNTIFS($X$2:$X$200,$G15)>0, COUNTIFS($Y$2:$Y$200,$G15)>0, COUNTIFS($Z$2:$Z$200,$G15)>0, COUNTIFS($AA$2:$AA$200,$G15)>0, COUNTIFS($AB$2:$AB$200,$G15)>0, COUNTIFS($AC$2:$AC$200,$G15)>0, COUNTIFS($AD$2:$AD$200,$G15)>0, COUNTIFS($AE$2:$AE$200,$G15)>0, COUNTIFS($AF$2:$AF$200,$G15)>0, COUNTIFS($AG$2:$AG$200,$G15)>0, COUNTIFS($AH$2:$AH$200,$G15)>0, COUNTIFS($AI$2:$AI$200,$G15)>0, COUNTIFS($AJ$2:$AJ$200,$G15)>0, COUNTIFS($AK$2:$AK$200,$G15)>0, COUNTIFS($AL$2:$AL$200,$G15)>0, COUNTIFS($AM$2:$AM$200,$G15)>0, COUNTIFS($AN$2:$AN$200,$G15)>0, COUNTIFS($AO$2:$AO$200,$G15)>0, COUNTIFS($AP$2:$AP$200,$G15)>0, COUNTIFS($AQ$2:$AQ$200,$G15)>0, COUNTIFS($AR$2:$AR$200,$G15)>0, COUNTIFS($AS$2:$AS$200,$G15)>0, COUNTIFS($AT$2:$AT$200,$G15)>0, COUNTIFS($AU$2:$AU$200,$G15)>0, COUNTIFS($AV$2:$AV$200,$G15)>0, COUNTIFS($AW$2:$AW$200,$G15)>0, COUNTIFS($AX$2:$AX$200,$G15)>0 )), ), 3 ), "")} | F15: {=IFERROR( INDEX( _xlfn._xlws.FILTER($U$1:$AX$1, TRANSPOSE( CHOOSE({1;2;3;4;5;6;7;8;9;10;11;12;13;14;15;16;17;18;19;20;21;22;23;24;25;26;27;28;29;30}, COUNTIFS($U$2:$U$200,$G15)>0, COUNTIFS($V$2:$V$200,$G15)>0, COUNTIFS($W$2:$W$200,$G15)>0, COUNTIFS($X$2:$X$200,$G15)>0, COUNTIFS($Y$2:$Y$200,$G15)>0, COUNTIFS($Z$2:$Z$200,$G15)>0, COUNTIFS($AA$2:$AA$200,$G15)>0, COUNTIFS($AB$2:$AB$200,$G15)>0, COUNTIFS($AC$2:$AC$200,$G15)>0, COUNTIFS($AD$2:$AD$200,$G15)>0, COUNTIFS($AE$2:$AE$200,$G15)>0, COUNTIFS($AF$2:$AF$200,$G15)>0, COUNTIFS($AG$2:$AG$200,$G15)>0, COUNTIFS($AH$2:$AH$200,$G15)>0, COUNTIFS($AI$2:$AI$200,$G15)>0, COUNTIFS($AJ$2:$AJ$200,$G15)>0, COUNTIFS($AK$2:$AK$200,$G15)>0, COUNTIFS($AL$2:$AL$200,$G15)>0, COUNTIFS($AM$2:$AM$200,$G15)>0, COUNTIFS($AN$2:$AN$200,$G15)>0, COUNTIFS($AO$2:$AO$200,$G15)>0, COUNTIFS($AP$2:$AP$200,$G15)>0, COUNTIFS($AQ$2:$AQ$200,$G15)>0, COUNTIFS($AR$2:$AR$200,$G15)>0, COUNTIFS($AS$2:$AS$200,$G15)>0, COUNTIFS($AT$2:$AT$200,$G15)>0, COUNTIFS($AU$2:$AU$200,$G15)>0, COUNTIFS($AV$2:$AV$200,$G15)>0, COUNTIFS($AW$2:$AW$200,$G15)>0, COUNTIFS($AX$2:$AX$200,$G15)>0 )), ), 4 ), "")} | G15: Arcbound Fiend | I15: Yuriko | J15: =Yuriko!G2 -> 12 | K15: Não | L15: Sim | M15: Não | N15: Sim | O15: Não | P15: Ping | Q15: - | R15: Turnos Extras | S15: =IF(J15<6,"5",IF(J15<11,"4",IF(J15<16,"3",IF(J15<31,"2","1")))) -> 3 | U15: The Indomitable | V15: Karplusan Forest | W15: Monastery Siege | X15: Lae'zel, Vlaakith's Champion | Y15: Vault of the Archangel | Z15: Life of the Party | AA15: Singer of Swift Rivers | AX15: Filigree Vector | BB15: Farseek | BC15: Genji Glove | BD15: Frenzied Gorespawn | BE15: Merrow Harbinger | BF15: Rotating Fireplace | BG15: Rings of Brighthearth | BH15: Satoru, the Infiltrator | BI15: Kaya the Inexorable | BL15: Unstoppable Plan | BP15: Filigree Vector | BS15: Castle Ardenvale | BT15: Enduring Innocence | BU15: Inventors' Fair | BV15: Espada de Luz e Sombra | BW15: Shaku da Honra Desgastada | BX15: Ojer Pakpatiq, Era Profunda | BY15: Teyo, Geometric Tactician | BZ15: Filigree Vector | CB15: Boros Charm | CC15: Crisol dos Mundos | CD15: High-Society Hunter | CE15: Elvish Reclaimer | CG15: Aura Mutation | CH15: Chandra's Ignition | CJ15: Arcbound Fiend
A16: =IFERROR(INDEX($S$3:$S$200, MATCH($C16, $I$3:$I$200, 0)), "") -> 1 | B16: =COUNTIF(U:AX,G16) -> 1 | C16: =IFERROR( INDEX($U$1:$AX$1, MATCH(TRUE, CHOOSE({1;2;3;4;5;6;7;8;9;10;11;12;13;14;15;16;17;18;19;20;21;22;23;24;25;26;27;28;29;30;31;32}, COUNTIFS($U$2:$U$200,$G16)>0, COUNTIFS($V$2:$V$200,$G16)>0, COUNTIFS($W$2:$W$200,$G16)>0, COUNTIFS($X$2:$X$200,$G16)>0, COUNTIFS($Y$2:$Y$200,$G16)>0, COUNTIFS($Z$2:$Z$200,$G16)>0, COUNTIFS($AA$2:$AA$200,$G16)>0, COUNTIFS($AB$2:$AB$200,$G16)>0, COUNTIFS($AC$2:$AC$200,$G16)>0, COUNTIFS($AD$2:$AD$200,$G16)>0, COUNTIFS($AE$2:$AE$200,$G16)>0, COUNTIFS($AF$2:$AF$200,$G16)>0, COUNTIFS($AG$2:$AG$200,$G16)>0, COUNTIFS($AH$2:$AH$200,$G16)>0, COUNTIFS($AI$2:$AI$200,$G16)>0, COUNTIFS($AJ$2:$AJ$200,$G16)>0, COUNTIFS($AK$2:$AK$200,$G16)>0, COUNTIFS($AL$2:$AL$200,$G16)>0, COUNTIFS($AM$2:$AM$200,$G16)>0, COUNTIFS($AN$2:$AN$200,$G16)>0, COUNTIFS($AO$2:$AO$200,$G16)>0, COUNTIFS($AP$2:$AP$200,$G16)>0, COUNTIFS($AQ$2:$AQ$200,$G16)>0, COUNTIFS($AR$2:$AR$200,$G16)>0, COUNTIFS($AS$2:$AS$200,$G16)>0, COUNTIFS($AT$2:$AT$200,$G16)>0, COUNTIFS($AU$2:$AU$200,$G16)>0, COUNTIFS($AV$2:$AV$200,$G16)>0, COUNTIFS($AW$2:$AW$200,$G16)>0, COUNTIFS($AX$2:$AX$200,$G16)>0 ), 0) ), "") -> Modular | D16: {=IFERROR( INDEX( _xlfn._xlws.FILTER($U$1:$AX$1, TRANSPOSE( CHOOSE({1;2;3;4;5;6;7;8;9;10;11;12;13;14;15;16;17;18;19;20;21;22;23;24;25;26;27;28;29;30}, COUNTIFS($U$2:$U$200,$G16)>0, COUNTIFS($V$2:$V$200,$G16)>0, COUNTIFS($W$2:$W$200,$G16)>0, COUNTIFS($X$2:$X$200,$G16)>0, COUNTIFS($Y$2:$Y$200,$G16)>0, COUNTIFS($Z$2:$Z$200,$G16)>0, COUNTIFS($AA$2:$AA$200,$G16)>0, COUNTIFS($AB$2:$AB$200,$G16)>0, COUNTIFS($AC$2:$AC$200,$G16)>0, COUNTIFS($AD$2:$AD$200,$G16)>0, COUNTIFS($AE$2:$AE$200,$G16)>0, COUNTIFS($AF$2:$AF$200,$G16)>0, COUNTIFS($AG$2:$AG$200,$G16)>0, COUNTIFS($AH$2:$AH$200,$G16)>0, COUNTIFS($AI$2:$AI$200,$G16)>0, COUNTIFS($AJ$2:$AJ$200,$G16)>0, COUNTIFS($AK$2:$AK$200,$G16)>0, COUNTIFS($AL$2:$AL$200,$G16)>0, COUNTIFS($AM$2:$AM$200,$G16)>0, COUNTIFS($AN$2:$AN$200,$G16)>0, COUNTIFS($AO$2:$AO$200,$G16)>0, COUNTIFS($AP$2:$AP$200,$G16)>0, COUNTIFS($AQ$2:$AQ$200,$G16)>0, COUNTIFS($AR$2:$AR$200,$G16)>0, COUNTIFS($AS$2:$AS$200,$G16)>0, COUNTIFS($AT$2:$AT$200,$G16)>0, COUNTIFS($AU$2:$AU$200,$G16)>0, COUNTIFS($AV$2:$AV$200,$G16)>0, COUNTIFS($AW$2:$AW$200,$G16)>0, COUNTIFS($AX$2:$AX$200,$G16)>0 )), ), 2 ), "")} | E16: {=IFERROR( INDEX( _xlfn._xlws.FILTER($U$1:$AX$1, TRANSPOSE( CHOOSE({1;2;3;4;5;6;7;8;9;10;11;12;13;14;15;16;17;18;19;20;21;22;23;24;25;26;27;28;29;30}, COUNTIFS($U$2:$U$200,$G16)>0, COUNTIFS($V$2:$V$200,$G16)>0, COUNTIFS($W$2:$W$200,$G16)>0, COUNTIFS($X$2:$X$200,$G16)>0, COUNTIFS($Y$2:$Y$200,$G16)>0, COUNTIFS($Z$2:$Z$200,$G16)>0, COUNTIFS($AA$2:$AA$200,$G16)>0, COUNTIFS($AB$2:$AB$200,$G16)>0, COUNTIFS($AC$2:$AC$200,$G16)>0, COUNTIFS($AD$2:$AD$200,$G16)>0, COUNTIFS($AE$2:$AE$200,$G16)>0, COUNTIFS($AF$2:$AF$200,$G16)>0, COUNTIFS($AG$2:$AG$200,$G16)>0, COUNTIFS($AH$2:$AH$200,$G16)>0, COUNTIFS($AI$2:$AI$200,$G16)>0, COUNTIFS($AJ$2:$AJ$200,$G16)>0, COUNTIFS($AK$2:$AK$200,$G16)>0, COUNTIFS($AL$2:$AL$200,$G16)>0, COUNTIFS($AM$2:$AM$200,$G16)>0, COUNTIFS($AN$2:$AN$200,$G16)>0, COUNTIFS($AO$2:$AO$200,$G16)>0, COUNTIFS($AP$2:$AP$200,$G16)>0, COUNTIFS($AQ$2:$AQ$200,$G16)>0, COUNTIFS($AR$2:$AR$200,$G16)>0, COUNTIFS($AS$2:$AS$200,$G16)>0, COUNTIFS($AT$2:$AT$200,$G16)>0, COUNTIFS($AU$2:$AU$200,$G16)>0, COUNTIFS($AV$2:$AV$200,$G16)>0, COUNTIFS($AW$2:$AW$200,$G16)>0, COUNTIFS($AX$2:$AX$200,$G16)>0 )), ), 3 ), "")} | F16: {=IFERROR( INDEX( _xlfn._xlws.FILTER($U$1:$AX$1, TRANSPOSE( CHOOSE({1;2;3;4;5;6;7;8;9;10;11;12;13;14;15;16;17;18;19;20;21;22;23;24;25;26;27;28;29;30}, COUNTIFS($U$2:$U$200,$G16)>0, COUNTIFS($V$2:$V$200,$G16)>0, COUNTIFS($W$2:$W$200,$G16)>0, COUNTIFS($X$2:$X$200,$G16)>0, COUNTIFS($Y$2:$Y$200,$G16)>0, COUNTIFS($Z$2:$Z$200,$G16)>0, COUNTIFS($AA$2:$AA$200,$G16)>0, COUNTIFS($AB$2:$AB$200,$G16)>0, COUNTIFS($AC$2:$AC$200,$G16)>0, COUNTIFS($AD$2:$AD$200,$G16)>0, COUNTIFS($AE$2:$AE$200,$G16)>0, COUNTIFS($AF$2:$AF$200,$G16)>0, COUNTIFS($AG$2:$AG$200,$G16)>0, COUNTIFS($AH$2:$AH$200,$G16)>0, COUNTIFS($AI$2:$AI$200,$G16)>0, COUNTIFS($AJ$2:$AJ$200,$G16)>0, COUNTIFS($AK$2:$AK$200,$G16)>0, COUNTIFS($AL$2:$AL$200,$G16)>0, COUNTIFS($AM$2:$AM$200,$G16)>0, COUNTIFS($AN$2:$AN$200,$G16)>0, COUNTIFS($AO$2:$AO$200,$G16)>0, COUNTIFS($AP$2:$AP$200,$G16)>0, COUNTIFS($AQ$2:$AQ$200,$G16)>0, COUNTIFS($AR$2:$AR$200,$G16)>0, COUNTIFS($AS$2:$AS$200,$G16)>0, COUNTIFS($AT$2:$AT$200,$G16)>0, COUNTIFS($AU$2:$AU$200,$G16)>0, COUNTIFS($AV$2:$AV$200,$G16)>0, COUNTIFS($AW$2:$AW$200,$G16)>0, COUNTIFS($AX$2:$AX$200,$G16)>0 )), ), 4 ), "")} | G16: Arcbound Overseer | I16: Inalla | J16: =Inalla!G2 -> 10 | K16: Não | L16: Sim | M16: Sim | N16: Sim | O16: Não | P16: Combo | Q16: Dano Direto | R16: Magos e Combos | S16: =IF(J16<6,"5",IF(J16<11,"4",IF(J16<16,"3",IF(J16<31,"2","1")))) -> 4 | U16: Time Sieve | V16: Lightning Greaves | W16: Psychic Corrosion | X16: Llanowar Wastes | Z16: Reliquary Tower | AA16: Sol Ring | AX16: Gavony Township | BB16: Gavony Township | BC16: Ghostly Prison | BD16: Gallifrey Council Chamber | BE16: Misty Rainforest | BF16: Takenuma, Charco Abandonado | BG16: Sonic Screwdriver | BH16: Saw in Half | BI16: Kellan, the Fae-Blooded // Birthright Boon | BP16: Gavony Township | BS16: Champion of Lambholt | BT16: Exemplar of Light | BU16: Kozilek, the Broken Reality | BV16: Espada de Verdade e Justiça | BW16: Sliver Gravemother | BX16: Pain for All | BY16: Warren Soultrader | BZ16: Gavony Township | CB16: Bothersome Quasit | CC16: Delighted Halfling | CD16: Invasion of Segovia | CE16: Emergency Eject | CG16: Autoridade dos Cônsules | CH16: Collector's Vault | CJ16: Arcbound Overseer
A17: =IFERROR(INDEX($S$3:$S$200, MATCH($C17, $I$3:$I$200, 0)), "") -> 1 | B17: =COUNTIF(U:AX,G17) -> 1 | C17: =IFERROR( INDEX($U$1:$AX$1, MATCH(TRUE, CHOOSE({1;2;3;4;5;6;7;8;9;10;11;12;13;14;15;16;17;18;19;20;21;22;23;24;25;26;27;28;29;30;31;32}, COUNTIFS($U$2:$U$200,$G17)>0, COUNTIFS($V$2:$V$200,$G17)>0, COUNTIFS($W$2:$W$200,$G17)>0, COUNTIFS($X$2:$X$200,$G17)>0, COUNTIFS($Y$2:$Y$200,$G17)>0, COUNTIFS($Z$2:$Z$200,$G17)>0, COUNTIFS($AA$2:$AA$200,$G17)>0, COUNTIFS($AB$2:$AB$200,$G17)>0, COUNTIFS($AC$2:$AC$200,$G17)>0, COUNTIFS($AD$2:$AD$200,$G17)>0, COUNTIFS($AE$2:$AE$200,$G17)>0, COUNTIFS($AF$2:$AF$200,$G17)>0, COUNTIFS($AG$2:$AG$200,$G17)>0, COUNTIFS($AH$2:$AH$200,$G17)>0, COUNTIFS($AI$2:$AI$200,$G17)>0, COUNTIFS($AJ$2:$AJ$200,$G17)>0, COUNTIFS($AK$2:$AK$200,$G17)>0, COUNTIFS($AL$2:$AL$200,$G17)>0, COUNTIFS($AM$2:$AM$200,$G17)>0, COUNTIFS($AN$2:$AN$200,$G17)>0, COUNTIFS($AO$2:$AO$200,$G17)>0, COUNTIFS($AP$2:$AP$200,$G17)>0, COUNTIFS($AQ$2:$AQ$200,$G17)>0, COUNTIFS($AR$2:$AR$200,$G17)>0, COUNTIFS($AS$2:$AS$200,$G17)>0, COUNTIFS($AT$2:$AT$200,$G17)>0, COUNTIFS($AU$2:$AU$200,$G17)>0, COUNTIFS($AV$2:$AV$200,$G17)>0, COUNTIFS($AW$2:$AW$200,$G17)>0, COUNTIFS($AX$2:$AX$200,$G17)>0 ), 0) ), "") -> Tayam | D17: {=IFERROR( INDEX( _xlfn._xlws.FILTER($U$1:$AX$1, TRANSPOSE( CHOOSE({1;2;3;4;5;6;7;8;9;10;11;12;13;14;15;16;17;18;19;20;21;22;23;24;25;26;27;28;29;30}, COUNTIFS($U$2:$U$200,$G17)>0, COUNTIFS($V$2:$V$200,$G17)>0, COUNTIFS($W$2:$W$200,$G17)>0, COUNTIFS($X$2:$X$200,$G17)>0, COUNTIFS($Y$2:$Y$200,$G17)>0, COUNTIFS($Z$2:$Z$200,$G17)>0, COUNTIFS($AA$2:$AA$200,$G17)>0, COUNTIFS($AB$2:$AB$200,$G17)>0, COUNTIFS($AC$2:$AC$200,$G17)>0, COUNTIFS($AD$2:$AD$200,$G17)>0, COUNTIFS($AE$2:$AE$200,$G17)>0, COUNTIFS($AF$2:$AF$200,$G17)>0, COUNTIFS($AG$2:$AG$200,$G17)>0, COUNTIFS($AH$2:$AH$200,$G17)>0, COUNTIFS($AI$2:$AI$200,$G17)>0, COUNTIFS($AJ$2:$AJ$200,$G17)>0, COUNTIFS($AK$2:$AK$200,$G17)>0, COUNTIFS($AL$2:$AL$200,$G17)>0, COUNTIFS($AM$2:$AM$200,$G17)>0, COUNTIFS($AN$2:$AN$200,$G17)>0, COUNTIFS($AO$2:$AO$200,$G17)>0, COUNTIFS($AP$2:$AP$200,$G17)>0, COUNTIFS($AQ$2:$AQ$200,$G17)>0, COUNTIFS($AR$2:$AR$200,$G17)>0, COUNTIFS($AS$2:$AS$200,$G17)>0, COUNTIFS($AT$2:$AT$200,$G17)>0, COUNTIFS($AU$2:$AU$200,$G17)>0, COUNTIFS($AV$2:$AV$200,$G17)>0, COUNTIFS($AW$2:$AW$200,$G17)>0, COUNTIFS($AX$2:$AX$200,$G17)>0 )), ), 2 ), "")} | E17: {=IFERROR( INDEX( _xlfn._xlws.FILTER($U$1:$AX$1, TRANSPOSE( CHOOSE({1;2;3;4;5;6;7;8;9;10;11;12;13;14;15;16;17;18;19;20;21;22;23;24;25;26;27;28;29;30}, COUNTIFS($U$2:$U$200,$G17)>0, COUNTIFS($V$2:$V$200,$G17)>0, COUNTIFS($W$2:$W$200,$G17)>0, COUNTIFS($X$2:$X$200,$G17)>0, COUNTIFS($Y$2:$Y$200,$G17)>0, COUNTIFS($Z$2:$Z$200,$G17)>0, COUNTIFS($AA$2:$AA$200,$G17)>0, COUNTIFS($AB$2:$AB$200,$G17)>0, COUNTIFS($AC$2:$AC$200,$G17)>0, COUNTIFS($AD$2:$AD$200,$G17)>0, COUNTIFS($AE$2:$AE$200,$G17)>0, COUNTIFS($AF$2:$AF$200,$G17)>0, COUNTIFS($AG$2:$AG$200,$G17)>0, COUNTIFS($AH$2:$AH$200,$G17)>0, COUNTIFS($AI$2:$AI$200,$G17)>0, COUNTIFS($AJ$2:$AJ$200,$G17)>0, COUNTIFS($AK$2:$AK$200,$G17)>0, COUNTIFS($AL$2:$AL$200,$G17)>0, COUNTIFS($AM$2:$AM$200,$G17)>0, COUNTIFS($AN$2:$AN$200,$G17)>0, COUNTIFS($AO$2:$AO$200,$G17)>0, COUNTIFS($AP$2:$AP$200,$G17)>0, COUNTIFS($AQ$2:$AQ$200,$G17)>0, COUNTIFS($AR$2:$AR$200,$G17)>0, COUNTIFS($AS$2:$AS$200,$G17)>0, COUNTIFS($AT$2:$AT$200,$G17)>0, COUNTIFS($AU$2:$AU$200,$G17)>0, COUNTIFS($AV$2:$AV$200,$G17)>0, COUNTIFS($AW$2:$AW$200,$G17)>0, COUNTIFS($AX$2:$AX$200,$G17)>0 )), ), 3 ), "")} | F17: {=IFERROR( INDEX( _xlfn._xlws.FILTER($U$1:$AX$1, TRANSPOSE( CHOOSE({1;2;3;4;5;6;7;8;9;10;11;12;13;14;15;16;17;18;19;20;21;22;23;24;25;26;27;28;29;30}, COUNTIFS($U$2:$U$200,$G17)>0, COUNTIFS($V$2:$V$200,$G17)>0, COUNTIFS($W$2:$W$200,$G17)>0, COUNTIFS($X$2:$X$200,$G17)>0, COUNTIFS($Y$2:$Y$200,$G17)>0, COUNTIFS($Z$2:$Z$200,$G17)>0, COUNTIFS($AA$2:$AA$200,$G17)>0, COUNTIFS($AB$2:$AB$200,$G17)>0, COUNTIFS($AC$2:$AC$200,$G17)>0, COUNTIFS($AD$2:$AD$200,$G17)>0, COUNTIFS($AE$2:$AE$200,$G17)>0, COUNTIFS($AF$2:$AF$200,$G17)>0, COUNTIFS($AG$2:$AG$200,$G17)>0, COUNTIFS($AH$2:$AH$200,$G17)>0, COUNTIFS($AI$2:$AI$200,$G17)>0, COUNTIFS($AJ$2:$AJ$200,$G17)>0, COUNTIFS($AK$2:$AK$200,$G17)>0, COUNTIFS($AL$2:$AL$200,$G17)>0, COUNTIFS($AM$2:$AM$200,$G17)>0, COUNTIFS($AN$2:$AN$200,$G17)>0, COUNTIFS($AO$2:$AO$200,$G17)>0, COUNTIFS($AP$2:$AP$200,$G17)>0, COUNTIFS($AQ$2:$AQ$200,$G17)>0, COUNTIFS($AR$2:$AR$200,$G17)>0, COUNTIFS($AS$2:$AS$200,$G17)>0, COUNTIFS($AT$2:$AT$200,$G17)>0, COUNTIFS($AU$2:$AU$200,$G17)>0, COUNTIFS($AV$2:$AV$200,$G17)>0, COUNTIFS($AW$2:$AW$200,$G17)>0, COUNTIFS($AX$2:$AX$200,$G17)>0 )), ), 4 ), "")} | G17: Ardbert, Warrior of Darkness | I17: Akiri | J17: =Akiri!G2 -> 12 | K17: Sim | L17: Não | M17: Sim | N17: Não | O17: Não | P17: Combate | Q17: Voltron | R17: Equipamentos | S17: =IF(J17<6,"5",IF(J17<11,"4",IF(J17<16,"3",IF(J17<31,"2","1")))) -> 3 | U17: Timestream Navigator | V17: Marcha dos Canonizados | W17: Reforge the Soul | X17: Maester Seymour | Z17: Rogue's Passage | AA17: Stonybrook Banneret | AX17: Great Furnace | BB17: Generous Gift | BC17: Gyre Sage | BD17: Ghoulish Impetus | BE17: Reliquary Tower | BF17: The Tenth Doctor | BG17: Spectator Seating | BH17: Sea Gate Restoration | BI17: Lightning Greaves | BP17: Great Furnace | BS17: Champions from Beyond | BT17: Fellwar Stone | BU17: Luxury Suite | BV17: Faerie Slumber Party | BW17: Swamp | BX17: Red XIII, Proud Warrior | BY17: Westvale Abbey | BZ17: Great Furnace | CB17: Broadside Bombardiers | CC17: Diário de Tarrian | CD17: Jenova, Ancient Calamity | CE17: Esper Sentinel | CG17: Back in Town | CH17: Daretti, Ingenious Iconoclast | CJ17: Ardbert, Warrior of Darkness
A18: =IFERROR(INDEX($S$3:$S$200, MATCH($C18, $I$3:$I$200, 0)), "") -> 4 | B18: =COUNTIF(U:AX,G18) -> 1 | C18: =IFERROR( INDEX($U$1:$AX$1, MATCH(TRUE, CHOOSE({1;2;3;4;5;6;7;8;9;10;11;12;13;14;15;16;17;18;19;20;21;22;23;24;25;26;27;28;29;30;31;32}, COUNTIFS($U$2:$U$200,$G18)>0, COUNTIFS($V$2:$V$200,$G18)>0, COUNTIFS($W$2:$W$200,$G18)>0, COUNTIFS($X$2:$X$200,$G18)>0, COUNTIFS($Y$2:$Y$200,$G18)>0, COUNTIFS($Z$2:$Z$200,$G18)>0, COUNTIFS($AA$2:$AA$200,$G18)>0, COUNTIFS($AB$2:$AB$200,$G18)>0, COUNTIFS($AC$2:$AC$200,$G18)>0, COUNTIFS($AD$2:$AD$200,$G18)>0, COUNTIFS($AE$2:$AE$200,$G18)>0, COUNTIFS($AF$2:$AF$200,$G18)>0, COUNTIFS($AG$2:$AG$200,$G18)>0, COUNTIFS($AH$2:$AH$200,$G18)>0, COUNTIFS($AI$2:$AI$200,$G18)>0, COUNTIFS($AJ$2:$AJ$200,$G18)>0, COUNTIFS($AK$2:$AK$200,$G18)>0, COUNTIFS($AL$2:$AL$200,$G18)>0, COUNTIFS($AM$2:$AM$200,$G18)>0, COUNTIFS($AN$2:$AN$200,$G18)>0, COUNTIFS($AO$2:$AO$200,$G18)>0, COUNTIFS($AP$2:$AP$200,$G18)>0, COUNTIFS($AQ$2:$AQ$200,$G18)>0, COUNTIFS($AR$2:$AR$200,$G18)>0, COUNTIFS($AS$2:$AS$200,$G18)>0, COUNTIFS($AT$2:$AT$200,$G18)>0, COUNTIFS($AU$2:$AU$200,$G18)>0, COUNTIFS($AV$2:$AV$200,$G18)>0, COUNTIFS($AW$2:$AW$200,$G18)>0, COUNTIFS($AX$2:$AX$200,$G18)>0 ), 0) ), "") -> VialIshai | D18: {=IFERROR( INDEX( _xlfn._xlws.FILTER($U$1:$AX$1, TRANSPOSE( CHOOSE({1;2;3;4;5;6;7;8;9;10;11;12;13;14;15;16;17;18;19;20;21;22;23;24;25;26;27;28;29;30}, COUNTIFS($U$2:$U$200,$G18)>0, COUNTIFS($V$2:$V$200,$G18)>0, COUNTIFS($W$2:$W$200,$G18)>0, COUNTIFS($X$2:$X$200,$G18)>0, COUNTIFS($Y$2:$Y$200,$G18)>0, COUNTIFS($Z$2:$Z$200,$G18)>0, COUNTIFS($AA$2:$AA$200,$G18)>0, COUNTIFS($AB$2:$AB$200,$G18)>0, COUNTIFS($AC$2:$AC$200,$G18)>0, COUNTIFS($AD$2:$AD$200,$G18)>0, COUNTIFS($AE$2:$AE$200,$G18)>0, COUNTIFS($AF$2:$AF$200,$G18)>0, COUNTIFS($AG$2:$AG$200,$G18)>0, COUNTIFS($AH$2:$AH$200,$G18)>0, COUNTIFS($AI$2:$AI$200,$G18)>0, COUNTIFS($AJ$2:$AJ$200,$G18)>0, COUNTIFS($AK$2:$AK$200,$G18)>0, COUNTIFS($AL$2:$AL$200,$G18)>0, COUNTIFS($AM$2:$AM$200,$G18)>0, COUNTIFS($AN$2:$AN$200,$G18)>0, COUNTIFS($AO$2:$AO$200,$G18)>0, COUNTIFS($AP$2:$AP$200,$G18)>0, COUNTIFS($AQ$2:$AQ$200,$G18)>0, COUNTIFS($AR$2:$AR$200,$G18)>0, COUNTIFS($AS$2:$AS$200,$G18)>0, COUNTIFS($AT$2:$AT$200,$G18)>0, COUNTIFS($AU$2:$AU$200,$G18)>0, COUNTIFS($AV$2:$AV$200,$G18)>0, COUNTIFS($AW$2:$AW$200,$G18)>0, COUNTIFS($AX$2:$AX$200,$G18)>0 )), ), 2 ), "")} | E18: {=IFERROR( INDEX( _xlfn._xlws.FILTER($U$1:$AX$1, TRANSPOSE( CHOOSE({1;2;3;4;5;6;7;8;9;10;11;12;13;14;15;16;17;18;19;20;21;22;23;24;25;26;27;28;29;30}, COUNTIFS($U$2:$U$200,$G18)>0, COUNTIFS($V$2:$V$200,$G18)>0, COUNTIFS($W$2:$W$200,$G18)>0, COUNTIFS($X$2:$X$200,$G18)>0, COUNTIFS($Y$2:$Y$200,$G18)>0, COUNTIFS($Z$2:$Z$200,$G18)>0, COUNTIFS($AA$2:$AA$200,$G18)>0, COUNTIFS($AB$2:$AB$200,$G18)>0, COUNTIFS($AC$2:$AC$200,$G18)>0, COUNTIFS($AD$2:$AD$200,$G18)>0, COUNTIFS($AE$2:$AE$200,$G18)>0, COUNTIFS($AF$2:$AF$200,$G18)>0, COUNTIFS($AG$2:$AG$200,$G18)>0, COUNTIFS($AH$2:$AH$200,$G18)>0, COUNTIFS($AI$2:$AI$200,$G18)>0, COUNTIFS($AJ$2:$AJ$200,$G18)>0, COUNTIFS($AK$2:$AK$200,$G18)>0, COUNTIFS($AL$2:$AL$200,$G18)>0, COUNTIFS($AM$2:$AM$200,$G18)>0, COUNTIFS($AN$2:$AN$200,$G18)>0, COUNTIFS($AO$2:$AO$200,$G18)>0, COUNTIFS($AP$2:$AP$200,$G18)>0, COUNTIFS($AQ$2:$AQ$200,$G18)>0, COUNTIFS($AR$2:$AR$200,$G18)>0, COUNTIFS($AS$2:$AS$200,$G18)>0, COUNTIFS($AT$2:$AT$200,$G18)>0, COUNTIFS($AU$2:$AU$200,$G18)>0, COUNTIFS($AV$2:$AV$200,$G18)>0, COUNTIFS($AW$2:$AW$200,$G18)>0, COUNTIFS($AX$2:$AX$200,$G18)>0 )), ), 3 ), "")} | F18: {=IFERROR( INDEX( _xlfn._xlws.FILTER($U$1:$AX$1, TRANSPOSE( CHOOSE({1;2;3;4;5;6;7;8;9;10;11;12;13;14;15;16;17;18;19;20;21;22;23;24;25;26;27;28;29;30}, COUNTIFS($U$2:$U$200,$G18)>0, COUNTIFS($V$2:$V$200,$G18)>0, COUNTIFS($W$2:$W$200,$G18)>0, COUNTIFS($X$2:$X$200,$G18)>0, COUNTIFS($Y$2:$Y$200,$G18)>0, COUNTIFS($Z$2:$Z$200,$G18)>0, COUNTIFS($AA$2:$AA$200,$G18)>0, COUNTIFS($AB$2:$AB$200,$G18)>0, COUNTIFS($AC$2:$AC$200,$G18)>0, COUNTIFS($AD$2:$AD$200,$G18)>0, COUNTIFS($AE$2:$AE$200,$G18)>0, COUNTIFS($AF$2:$AF$200,$G18)>0, COUNTIFS($AG$2:$AG$200,$G18)>0, COUNTIFS($AH$2:$AH$200,$G18)>0, COUNTIFS($AI$2:$AI$200,$G18)>0, COUNTIFS($AJ$2:$AJ$200,$G18)>0, COUNTIFS($AK$2:$AK$200,$G18)>0, COUNTIFS($AL$2:$AL$200,$G18)>0, COUNTIFS($AM$2:$AM$200,$G18)>0, COUNTIFS($AN$2:$AN$200,$G18)>0, COUNTIFS($AO$2:$AO$200,$G18)>0, COUNTIFS($AP$2:$AP$200,$G18)>0, COUNTIFS($AQ$2:$AQ$200,$G18)>0, COUNTIFS($AR$2:$AR$200,$G18)>0, COUNTIFS($AS$2:$AS$200,$G18)>0, COUNTIFS($AT$2:$AT$200,$G18)>0, COUNTIFS($AU$2:$AU$200,$G18)>0, COUNTIFS($AV$2:$AV$200,$G18)>0, COUNTIFS($AW$2:$AW$200,$G18)>0, COUNTIFS($AX$2:$AX$200,$G18)>0 )), ), 4 ), "")} | G18: Arid Mesa | I18: Sisay | J18: =Sisay!G2 -> 11 | K18: Sim | L18: Sim | M18: Sim | N18: Sim | O18: Sim | P18: Combate | Q18: Dano Direto | R18: Super-Amigos | S18: =IF(J18<6,"5",IF(J18<11,"4",IF(J18<16,"3",IF(J18<31,"2","1")))) -> 3 | U18: Treasure Vault | V18: Prosperous Partnership | W18: Relentless Assault | X18: Managorger Hydra | Z18: Sol Ring | AA18: Summon: Leviathan | AX18: Haru, Hidden Talent | BB18: Glint-Horn Buccaneer | BC18: Hydra's Growth | BD18: Giver of Runes | BE18: Scalding Tarn | BF18: Thought Vessel | BG18: The Mycosynth Gardens | BH18: Shizo, Death's Storehouse | BI18: Lolth, Rainha Aranha | BP18: Haru, Hidden Talent | BS18: Clifftop Retreat | BT18: Firkraag, Cunning Instigator | BU18: Mandate of Peace | BV18: Firion, Wild Rose Warrior | BW18: Three Tree City | BX18: Reflecting Pool | BZ18: Haru, Hidden Talent | CB18: Brushland | CC18: Drowned Catacomb | CD18: Jetmir's Garden | CE18: Evendo Brushrazer | CG18: Batwing Brume | CH18: Dionus, Elvish Archdruid | CJ18: Arid Mesa
A19: =IFERROR(INDEX($S$3:$S$200, MATCH($C19, $I$3:$I$200, 0)), "") -> 2 | B19: =COUNTIF(U:AX,G19) -> 1 | C19: =IFERROR( INDEX($U$1:$AX$1, MATCH(TRUE, CHOOSE({1;2;3;4;5;6;7;8;9;10;11;12;13;14;15;16;17;18;19;20;21;22;23;24;25;26;27;28;29;30;31;32}, COUNTIFS($U$2:$U$200,$G19)>0, COUNTIFS($V$2:$V$200,$G19)>0, COUNTIFS($W$2:$W$200,$G19)>0, COUNTIFS($X$2:$X$200,$G19)>0, COUNTIFS($Y$2:$Y$200,$G19)>0, COUNTIFS($Z$2:$Z$200,$G19)>0, COUNTIFS($AA$2:$AA$200,$G19)>0, COUNTIFS($AB$2:$AB$200,$G19)>0, COUNTIFS($AC$2:$AC$200,$G19)>0, COUNTIFS($AD$2:$AD$200,$G19)>0, COUNTIFS($AE$2:$AE$200,$G19)>0, COUNTIFS($AF$2:$AF$200,$G19)>0, COUNTIFS($AG$2:$AG$200,$G19)>0, COUNTIFS($AH$2:$AH$200,$G19)>0, COUNTIFS($AI$2:$AI$200,$G19)>0, COUNTIFS($AJ$2:$AJ$200,$G19)>0, COUNTIFS($AK$2:$AK$200,$G19)>0, COUNTIFS($AL$2:$AL$200,$G19)>0, COUNTIFS($AM$2:$AM$200,$G19)>0, COUNTIFS($AN$2:$AN$200,$G19)>0, COUNTIFS($AO$2:$AO$200,$G19)>0, COUNTIFS($AP$2:$AP$200,$G19)>0, COUNTIFS($AQ$2:$AQ$200,$G19)>0, COUNTIFS($AR$2:$AR$200,$G19)>0, COUNTIFS($AS$2:$AS$200,$G19)>0, COUNTIFS($AT$2:$AT$200,$G19)>0, COUNTIFS($AU$2:$AU$200,$G19)>0, COUNTIFS($AV$2:$AV$200,$G19)>0, COUNTIFS($AW$2:$AW$200,$G19)>0, COUNTIFS($AX$2:$AX$200,$G19)>0 ), 0) ), "") -> Baylen | D19: {=IFERROR( INDEX( _xlfn._xlws.FILTER($U$1:$AX$1, TRANSPOSE( CHOOSE({1;2;3;4;5;6;7;8;9;10;11;12;13;14;15;16;17;18;19;20;21;22;23;24;25;26;27;28;29;30}, COUNTIFS($U$2:$U$200,$G19)>0, COUNTIFS($V$2:$V$200,$G19)>0, COUNTIFS($W$2:$W$200,$G19)>0, COUNTIFS($X$2:$X$200,$G19)>0, COUNTIFS($Y$2:$Y$200,$G19)>0, COUNTIFS($Z$2:$Z$200,$G19)>0, COUNTIFS($AA$2:$AA$200,$G19)>0, COUNTIFS($AB$2:$AB$200,$G19)>0, COUNTIFS($AC$2:$AC$200,$G19)>0, COUNTIFS($AD$2:$AD$200,$G19)>0, COUNTIFS($AE$2:$AE$200,$G19)>0, COUNTIFS($AF$2:$AF$200,$G19)>0, COUNTIFS($AG$2:$AG$200,$G19)>0, COUNTIFS($AH$2:$AH$200,$G19)>0, COUNTIFS($AI$2:$AI$200,$G19)>0, COUNTIFS($AJ$2:$AJ$200,$G19)>0, COUNTIFS($AK$2:$AK$200,$G19)>0, COUNTIFS($AL$2:$AL$200,$G19)>0, COUNTIFS($AM$2:$AM$200,$G19)>0, COUNTIFS($AN$2:$AN$200,$G19)>0, COUNTIFS($AO$2:$AO$200,$G19)>0, COUNTIFS($AP$2:$AP$200,$G19)>0, COUNTIFS($AQ$2:$AQ$200,$G19)>0, COUNTIFS($AR$2:$AR$200,$G19)>0, COUNTIFS($AS$2:$AS$200,$G19)>0, COUNTIFS($AT$2:$AT$200,$G19)>0, COUNTIFS($AU$2:$AU$200,$G19)>0, COUNTIFS($AV$2:$AV$200,$G19)>0, COUNTIFS($AW$2:$AW$200,$G19)>0, COUNTIFS($AX$2:$AX$200,$G19)>0 )), ), 2 ), "")} | E19: {=IFERROR( INDEX( _xlfn._xlws.FILTER($U$1:$AX$1, TRANSPOSE( CHOOSE({1;2;3;4;5;6;7;8;9;10;11;12;13;14;15;16;17;18;19;20;21;22;23;24;25;26;27;28;29;30}, COUNTIFS($U$2:$U$200,$G19)>0, COUNTIFS($V$2:$V$200,$G19)>0, COUNTIFS($W$2:$W$200,$G19)>0, COUNTIFS($X$2:$X$200,$G19)>0, COUNTIFS($Y$2:$Y$200,$G19)>0, COUNTIFS($Z$2:$Z$200,$G19)>0, COUNTIFS($AA$2:$AA$200,$G19)>0, COUNTIFS($AB$2:$AB$200,$G19)>0, COUNTIFS($AC$2:$AC$200,$G19)>0, COUNTIFS($AD$2:$AD$200,$G19)>0, COUNTIFS($AE$2:$AE$200,$G19)>0, COUNTIFS($AF$2:$AF$200,$G19)>0, COUNTIFS($AG$2:$AG$200,$G19)>0, COUNTIFS($AH$2:$AH$200,$G19)>0, COUNTIFS($AI$2:$AI$200,$G19)>0, COUNTIFS($AJ$2:$AJ$200,$G19)>0, COUNTIFS($AK$2:$AK$200,$G19)>0, COUNTIFS($AL$2:$AL$200,$G19)>0, COUNTIFS($AM$2:$AM$200,$G19)>0, COUNTIFS($AN$2:$AN$200,$G19)>0, COUNTIFS($AO$2:$AO$200,$G19)>0, COUNTIFS($AP$2:$AP$200,$G19)>0, COUNTIFS($AQ$2:$AQ$200,$G19)>0, COUNTIFS($AR$2:$AR$200,$G19)>0, COUNTIFS($AS$2:$AS$200,$G19)>0, COUNTIFS($AT$2:$AT$200,$G19)>0, COUNTIFS($AU$2:$AU$200,$G19)>0, COUNTIFS($AV$2:$AV$200,$G19)>0, COUNTIFS($AW$2:$AW$200,$G19)>0, COUNTIFS($AX$2:$AX$200,$G19)>0 )), ), 3 ), "")} | F19: {=IFERROR( INDEX( _xlfn._xlws.FILTER($U$1:$AX$1, TRANSPOSE( CHOOSE({1;2;3;4;5;6;7;8;9;10;11;12;13;14;15;16;17;18;19;20;21;22;23;24;25;26;27;28;29;30}, COUNTIFS($U$2:$U$200,$G19)>0, COUNTIFS($V$2:$V$200,$G19)>0, COUNTIFS($W$2:$W$200,$G19)>0, COUNTIFS($X$2:$X$200,$G19)>0, COUNTIFS($Y$2:$Y$200,$G19)>0, COUNTIFS($Z$2:$Z$200,$G19)>0, COUNTIFS($AA$2:$AA$200,$G19)>0, COUNTIFS($AB$2:$AB$200,$G19)>0, COUNTIFS($AC$2:$AC$200,$G19)>0, COUNTIFS($AD$2:$AD$200,$G19)>0, COUNTIFS($AE$2:$AE$200,$G19)>0, COUNTIFS($AF$2:$AF$200,$G19)>0, COUNTIFS($AG$2:$AG$200,$G19)>0, COUNTIFS($AH$2:$AH$200,$G19)>0, COUNTIFS($AI$2:$AI$200,$G19)>0, COUNTIFS($AJ$2:$AJ$200,$G19)>0, COUNTIFS($AK$2:$AK$200,$G19)>0, COUNTIFS($AL$2:$AL$200,$G19)>0, COUNTIFS($AM$2:$AM$200,$G19)>0, COUNTIFS($AN$2:$AN$200,$G19)>0, COUNTIFS($AO$2:$AO$200,$G19)>0, COUNTIFS($AP$2:$AP$200,$G19)>0, COUNTIFS($AQ$2:$AQ$200,$G19)>0, COUNTIFS($AR$2:$AR$200,$G19)>0, COUNTIFS($AS$2:$AS$200,$G19)>0, COUNTIFS($AT$2:$AT$200,$G19)>0, COUNTIFS($AU$2:$AU$200,$G19)>0, COUNTIFS($AV$2:$AV$200,$G19)>0, COUNTIFS($AW$2:$AW$200,$G19)>0, COUNTIFS($AX$2:$AX$200,$G19)>0 )), ), 4 ), "")} | G19: Artifact Mutation | I19: Thrakiri | J19: =Thrakiri!G2 -> 4 | K19: Sim | L19: Sim | M19: Sim | N19: Não | O19: Sim | P19: Combo | Q19: Voltron | R19: Engrenagens para Combar | S19: =IF(J19<6,"5",IF(J19<11,"4",IF(J19<16,"3",IF(J19<31,"2","1")))) -> 5 | V19: Purphoros, God of the Forge | W19: Sea of Clouds | X19: Ozolith, the Shattered Spire | Z19: Sulfur Falls | AA19: Surgespanner | AX19: Haywire Mite | BB19: Hedron Detonator | BC19: Incendiary Command | BD19: Guia das Almas | BE19: Seahunter | BF19: Thran Dynamo | BG19: Vexing Puzzlebox | BH19: Temporal Manipulation | BI19: Nicol Bolas, God-Pharaoh | BP19: Haywire Mite | BS19: Dever Além da Morte | BT19: Frenzied Gorespawn | BU19: Mirrex | BV19: Freyalise, Llanowar's Fury | BW19: Thrumming Hivepool | BX19: Saqueador Amaldiçoado | BZ19: Haywire Mite | CB19: Call to the Kindred | CC19: Elspeth, Sun's Champion | CD19: Jidoor, Aristocratic Capital // Overture | CE19: Filigree Vector | CG19: Beast Within | CH19: Dispatch | CJ19: Artifact Mutation
A20: =IFERROR(INDEX($S$3:$S$200, MATCH($C20, $I$3:$I$200, 0)), "") -> 1 | B20: =COUNTIF(U:AX,G20) -> 1 | C20: =IFERROR( INDEX($U$1:$AX$1, MATCH(TRUE, CHOOSE({1;2;3;4;5;6;7;8;9;10;11;12;13;14;15;16;17;18;19;20;21;22;23;24;25;26;27;28;29;30;31;32}, COUNTIFS($U$2:$U$200,$G20)>0, COUNTIFS($V$2:$V$200,$G20)>0, COUNTIFS($W$2:$W$200,$G20)>0, COUNTIFS($X$2:$X$200,$G20)>0, COUNTIFS($Y$2:$Y$200,$G20)>0, COUNTIFS($Z$2:$Z$200,$G20)>0, COUNTIFS($AA$2:$AA$200,$G20)>0, COUNTIFS($AB$2:$AB$200,$G20)>0, COUNTIFS($AC$2:$AC$200,$G20)>0, COUNTIFS($AD$2:$AD$200,$G20)>0, COUNTIFS($AE$2:$AE$200,$G20)>0, COUNTIFS($AF$2:$AF$200,$G20)>0, COUNTIFS($AG$2:$AG$200,$G20)>0, COUNTIFS($AH$2:$AH$200,$G20)>0, COUNTIFS($AI$2:$AI$200,$G20)>0, COUNTIFS($AJ$2:$AJ$200,$G20)>0, COUNTIFS($AK$2:$AK$200,$G20)>0, COUNTIFS($AL$2:$AL$200,$G20)>0, COUNTIFS($AM$2:$AM$200,$G20)>0, COUNTIFS($AN$2:$AN$200,$G20)>0, COUNTIFS($AO$2:$AO$200,$G20)>0, COUNTIFS($AP$2:$AP$200,$G20)>0, COUNTIFS($AQ$2:$AQ$200,$G20)>0, COUNTIFS($AR$2:$AR$200,$G20)>0, COUNTIFS($AS$2:$AS$200,$G20)>0, COUNTIFS($AT$2:$AT$200,$G20)>0, COUNTIFS($AU$2:$AU$200,$G20)>0, COUNTIFS($AV$2:$AV$200,$G20)>0, COUNTIFS($AW$2:$AW$200,$G20)>0, COUNTIFS($AX$2:$AX$200,$G20)>0 ), 0) ), "") -> Tayam | D20: {=IFERROR( INDEX( _xlfn._xlws.FILTER($U$1:$AX$1, TRANSPOSE( CHOOSE({1;2;3;4;5;6;7;8;9;10;11;12;13;14;15;16;17;18;19;20;21;22;23;24;25;26;27;28;29;30}, COUNTIFS($U$2:$U$200,$G20)>0, COUNTIFS($V$2:$V$200,$G20)>0, COUNTIFS($W$2:$W$200,$G20)>0, COUNTIFS($X$2:$X$200,$G20)>0, COUNTIFS($Y$2:$Y$200,$G20)>0, COUNTIFS($Z$2:$Z$200,$G20)>0, COUNTIFS($AA$2:$AA$200,$G20)>0, COUNTIFS($AB$2:$AB$200,$G20)>0, COUNTIFS($AC$2:$AC$200,$G20)>0, COUNTIFS($AD$2:$AD$200,$G20)>0, COUNTIFS($AE$2:$AE$200,$G20)>0, COUNTIFS($AF$2:$AF$200,$G20)>0, COUNTIFS($AG$2:$AG$200,$G20)>0, COUNTIFS($AH$2:$AH$200,$G20)>0, COUNTIFS($AI$2:$AI$200,$G20)>0, COUNTIFS($AJ$2:$AJ$200,$G20)>0, COUNTIFS($AK$2:$AK$200,$G20)>0, COUNTIFS($AL$2:$AL$200,$G20)>0, COUNTIFS($AM$2:$AM$200,$G20)>0, COUNTIFS($AN$2:$AN$200,$G20)>0, COUNTIFS($AO$2:$AO$200,$G20)>0, COUNTIFS($AP$2:$AP$200,$G20)>0, COUNTIFS($AQ$2:$AQ$200,$G20)>0, COUNTIFS($AR$2:$AR$200,$G20)>0, COUNTIFS($AS$2:$AS$200,$G20)>0, COUNTIFS($AT$2:$AT$200,$G20)>0, COUNTIFS($AU$2:$AU$200,$G20)>0, COUNTIFS($AV$2:$AV$200,$G20)>0, COUNTIFS($AW$2:$AW$200,$G20)>0, COUNTIFS($AX$2:$AX$200,$G20)>0 )), ), 2 ), "")} | E20: {=IFERROR( INDEX( _xlfn._xlws.FILTER($U$1:$AX$1, TRANSPOSE( CHOOSE({1;2;3;4;5;6;7;8;9;10;11;12;13;14;15;16;17;18;19;20;21;22;23;24;25;26;27;28;29;30}, COUNTIFS($U$2:$U$200,$G20)>0, COUNTIFS($V$2:$V$200,$G20)>0, COUNTIFS($W$2:$W$200,$G20)>0, COUNTIFS($X$2:$X$200,$G20)>0, COUNTIFS($Y$2:$Y$200,$G20)>0, COUNTIFS($Z$2:$Z$200,$G20)>0, COUNTIFS($AA$2:$AA$200,$G20)>0, COUNTIFS($AB$2:$AB$200,$G20)>0, COUNTIFS($AC$2:$AC$200,$G20)>0, COUNTIFS($AD$2:$AD$200,$G20)>0, COUNTIFS($AE$2:$AE$200,$G20)>0, COUNTIFS($AF$2:$AF$200,$G20)>0, COUNTIFS($AG$2:$AG$200,$G20)>0, COUNTIFS($AH$2:$AH$200,$G20)>0, COUNTIFS($AI$2:$AI$200,$G20)>0, COUNTIFS($AJ$2:$AJ$200,$G20)>0, COUNTIFS($AK$2:$AK$200,$G20)>0, COUNTIFS($AL$2:$AL$200,$G20)>0, COUNTIFS($AM$2:$AM$200,$G20)>0, COUNTIFS($AN$2:$AN$200,$G20)>0, COUNTIFS($AO$2:$AO$200,$G20)>0, COUNTIFS($AP$2:$AP$200,$G20)>0, COUNTIFS($AQ$2:$AQ$200,$G20)>0, COUNTIFS($AR$2:$AR$200,$G20)>0, COUNTIFS($AS$2:$AS$200,$G20)>0, COUNTIFS($AT$2:$AT$200,$G20)>0, COUNTIFS($AU$2:$AU$200,$G20)>0, COUNTIFS($AV$2:$AV$200,$G20)>0, COUNTIFS($AW$2:$AW$200,$G20)>0, COUNTIFS($AX$2:$AX$200,$G20)>0 )), ), 3 ), "")} | F20: {=IFERROR( INDEX( _xlfn._xlws.FILTER($U$1:$AX$1, TRANSPOSE( CHOOSE({1;2;3;4;5;6;7;8;9;10;11;12;13;14;15;16;17;18;19;20;21;22;23;24;25;26;27;28;29;30}, COUNTIFS($U$2:$U$200,$G20)>0, COUNTIFS($V$2:$V$200,$G20)>0, COUNTIFS($W$2:$W$200,$G20)>0, COUNTIFS($X$2:$X$200,$G20)>0, COUNTIFS($Y$2:$Y$200,$G20)>0, COUNTIFS($Z$2:$Z$200,$G20)>0, COUNTIFS($AA$2:$AA$200,$G20)>0, COUNTIFS($AB$2:$AB$200,$G20)>0, COUNTIFS($AC$2:$AC$200,$G20)>0, COUNTIFS($AD$2:$AD$200,$G20)>0, COUNTIFS($AE$2:$AE$200,$G20)>0, COUNTIFS($AF$2:$AF$200,$G20)>0, COUNTIFS($AG$2:$AG$200,$G20)>0, COUNTIFS($AH$2:$AH$200,$G20)>0, COUNTIFS($AI$2:$AI$200,$G20)>0, COUNTIFS($AJ$2:$AJ$200,$G20)>0, COUNTIFS($AK$2:$AK$200,$G20)>0, COUNTIFS($AL$2:$AL$200,$G20)>0, COUNTIFS($AM$2:$AM$200,$G20)>0, COUNTIFS($AN$2:$AN$200,$G20)>0, COUNTIFS($AO$2:$AO$200,$G20)>0, COUNTIFS($AP$2:$AP$200,$G20)>0, COUNTIFS($AQ$2:$AQ$200,$G20)>0, COUNTIFS($AR$2:$AR$200,$G20)>0, COUNTIFS($AS$2:$AS$200,$G20)>0, COUNTIFS($AT$2:$AT$200,$G20)>0, COUNTIFS($AU$2:$AU$200,$G20)>0, COUNTIFS($AV$2:$AV$200,$G20)>0, COUNTIFS($AW$2:$AW$200,$G20)>0, COUNTIFS($AX$2:$AX$200,$G20)>0 )), ), 4 ), "")} | G20: Arwen, Weaver of Hope | I20: Elfos | J20: =Elfos!G2 -> 9 | K20: Não | L20: Sim | M20: Não | N20: Sim | O20: Sim | P20: Combo | Q20: Combate | R20: Muita Mana | S20: =IF(J20<6,"5",IF(J20<11,"4",IF(J20<16,"3",IF(J20<31,"2","1")))) -> 4 | V20: Rogue's Passage | W20: Slash the Ranks | X20: Patrolling Peacemaker | Z20: Thought Vessel | AA20: Throne of the God-Pharaoh | AX20: High Market | BB20: Jacked Rabbit | BC20: Incubation Druid | BD20: Havengul Laboratory | BE20: Simic Charm | BF20: Titania, Voice of Gaea | BG20: Vontade Dominadora | BH20: Temporal Trespass | BI20: O Dínamo Peregrino | BP20: High Market | BS20: Devoted Druid | BT20: Gallifrey Council Chamber | BU20: Mistrise Village | BV20: Glasspool Mimic | BW20: Trioma de Indatha | BX20: Scour for Scrap | BZ20: High Market | CB20: Cankerbloom | CC20: Emrakul, um Novo Mundo | CD20: Matoya, Archon Elder | CE20: Gavony Township | CG20: Bojuka Bog | CH20: Dollmaker's Shop // Porcelain Gallery | CJ20: Arwen, Weaver of Hope
A21: =IFERROR(INDEX($S$3:$S$200, MATCH($C21, $I$3:$I$200, 0)), "") -> 3 | B21: =COUNTIF(U:AX,G21) -> 1 | C21: =IFERROR( INDEX($U$1:$AX$1, MATCH(TRUE, CHOOSE({1;2;3;4;5;6;7;8;9;10;11;12;13;14;15;16;17;18;19;20;21;22;23;24;25;26;27;28;29;30;31;32}, COUNTIFS($U$2:$U$200,$G21)>0, COUNTIFS($V$2:$V$200,$G21)>0, COUNTIFS($W$2:$W$200,$G21)>0, COUNTIFS($X$2:$X$200,$G21)>0, COUNTIFS($Y$2:$Y$200,$G21)>0, COUNTIFS($Z$2:$Z$200,$G21)>0, COUNTIFS($AA$2:$AA$200,$G21)>0, COUNTIFS($AB$2:$AB$200,$G21)>0, COUNTIFS($AC$2:$AC$200,$G21)>0, COUNTIFS($AD$2:$AD$200,$G21)>0, COUNTIFS($AE$2:$AE$200,$G21)>0, COUNTIFS($AF$2:$AF$200,$G21)>0, COUNTIFS($AG$2:$AG$200,$G21)>0, COUNTIFS($AH$2:$AH$200,$G21)>0, COUNTIFS($AI$2:$AI$200,$G21)>0, COUNTIFS($AJ$2:$AJ$200,$G21)>0, COUNTIFS($AK$2:$AK$200,$G21)>0, COUNTIFS($AL$2:$AL$200,$G21)>0, COUNTIFS($AM$2:$AM$200,$G21)>0, COUNTIFS($AN$2:$AN$200,$G21)>0, COUNTIFS($AO$2:$AO$200,$G21)>0, COUNTIFS($AP$2:$AP$200,$G21)>0, COUNTIFS($AQ$2:$AQ$200,$G21)>0, COUNTIFS($AR$2:$AR$200,$G21)>0, COUNTIFS($AS$2:$AS$200,$G21)>0, COUNTIFS($AT$2:$AT$200,$G21)>0, COUNTIFS($AU$2:$AU$200,$G21)>0, COUNTIFS($AV$2:$AV$200,$G21)>0, COUNTIFS($AW$2:$AW$200,$G21)>0, COUNTIFS($AX$2:$AX$200,$G21)>0 ), 0) ), "") -> Carlos | D21: {=IFERROR( INDEX( _xlfn._xlws.FILTER($U$1:$AX$1, TRANSPOSE( CHOOSE({1;2;3;4;5;6;7;8;9;10;11;12;13;14;15;16;17;18;19;20;21;22;23;24;25;26;27;28;29;30}, COUNTIFS($U$2:$U$200,$G21)>0, COUNTIFS($V$2:$V$200,$G21)>0, COUNTIFS($W$2:$W$200,$G21)>0, COUNTIFS($X$2:$X$200,$G21)>0, COUNTIFS($Y$2:$Y$200,$G21)>0, COUNTIFS($Z$2:$Z$200,$G21)>0, COUNTIFS($AA$2:$AA$200,$G21)>0, COUNTIFS($AB$2:$AB$200,$G21)>0, COUNTIFS($AC$2:$AC$200,$G21)>0, COUNTIFS($AD$2:$AD$200,$G21)>0, COUNTIFS($AE$2:$AE$200,$G21)>0, COUNTIFS($AF$2:$AF$200,$G21)>0, COUNTIFS($AG$2:$AG$200,$G21)>0, COUNTIFS($AH$2:$AH$200,$G21)>0, COUNTIFS($AI$2:$AI$200,$G21)>0, COUNTIFS($AJ$2:$AJ$200,$G21)>0, COUNTIFS($AK$2:$AK$200,$G21)>0, COUNTIFS($AL$2:$AL$200,$G21)>0, COUNTIFS($AM$2:$AM$200,$G21)>0, COUNTIFS($AN$2:$AN$200,$G21)>0, COUNTIFS($AO$2:$AO$200,$G21)>0, COUNTIFS($AP$2:$AP$200,$G21)>0, COUNTIFS($AQ$2:$AQ$200,$G21)>0, COUNTIFS($AR$2:$AR$200,$G21)>0, COUNTIFS($AS$2:$AS$200,$G21)>0, COUNTIFS($AT$2:$AT$200,$G21)>0, COUNTIFS($AU$2:$AU$200,$G21)>0, COUNTIFS($AV$2:$AV$200,$G21)>0, COUNTIFS($AW$2:$AW$200,$G21)>0, COUNTIFS($AX$2:$AX$200,$G21)>0 )), ), 2 ), "")} | E21: {=IFERROR( INDEX( _xlfn._xlws.FILTER($U$1:$AX$1, TRANSPOSE( CHOOSE({1;2;3;4;5;6;7;8;9;10;11;12;13;14;15;16;17;18;19;20;21;22;23;24;25;26;27;28;29;30}, COUNTIFS($U$2:$U$200,$G21)>0, COUNTIFS($V$2:$V$200,$G21)>0, COUNTIFS($W$2:$W$200,$G21)>0, COUNTIFS($X$2:$X$200,$G21)>0, COUNTIFS($Y$2:$Y$200,$G21)>0, COUNTIFS($Z$2:$Z$200,$G21)>0, COUNTIFS($AA$2:$AA$200,$G21)>0, COUNTIFS($AB$2:$AB$200,$G21)>0, COUNTIFS($AC$2:$AC$200,$G21)>0, COUNTIFS($AD$2:$AD$200,$G21)>0, COUNTIFS($AE$2:$AE$200,$G21)>0, COUNTIFS($AF$2:$AF$200,$G21)>0, COUNTIFS($AG$2:$AG$200,$G21)>0, COUNTIFS($AH$2:$AH$200,$G21)>0, COUNTIFS($AI$2:$AI$200,$G21)>0, COUNTIFS($AJ$2:$AJ$200,$G21)>0, COUNTIFS($AK$2:$AK$200,$G21)>0, COUNTIFS($AL$2:$AL$200,$G21)>0, COUNTIFS($AM$2:$AM$200,$G21)>0, COUNTIFS($AN$2:$AN$200,$G21)>0, COUNTIFS($AO$2:$AO$200,$G21)>0, COUNTIFS($AP$2:$AP$200,$G21)>0, COUNTIFS($AQ$2:$AQ$200,$G21)>0, COUNTIFS($AR$2:$AR$200,$G21)>0, COUNTIFS($AS$2:$AS$200,$G21)>0, COUNTIFS($AT$2:$AT$200,$G21)>0, COUNTIFS($AU$2:$AU$200,$G21)>0, COUNTIFS($AV$2:$AV$200,$G21)>0, COUNTIFS($AW$2:$AW$200,$G21)>0, COUNTIFS($AX$2:$AX$200,$G21)>0 )), ), 3 ), "")} | F21: {=IFERROR( INDEX( _xlfn._xlws.FILTER($U$1:$AX$1, TRANSPOSE( CHOOSE({1;2;3;4;5;6;7;8;9;10;11;12;13;14;15;16;17;18;19;20;21;22;23;24;25;26;27;28;29;30}, COUNTIFS($U$2:$U$200,$G21)>0, COUNTIFS($V$2:$V$200,$G21)>0, COUNTIFS($W$2:$W$200,$G21)>0, COUNTIFS($X$2:$X$200,$G21)>0, COUNTIFS($Y$2:$Y$200,$G21)>0, COUNTIFS($Z$2:$Z$200,$G21)>0, COUNTIFS($AA$2:$AA$200,$G21)>0, COUNTIFS($AB$2:$AB$200,$G21)>0, COUNTIFS($AC$2:$AC$200,$G21)>0, COUNTIFS($AD$2:$AD$200,$G21)>0, COUNTIFS($AE$2:$AE$200,$G21)>0, COUNTIFS($AF$2:$AF$200,$G21)>0, COUNTIFS($AG$2:$AG$200,$G21)>0, COUNTIFS($AH$2:$AH$200,$G21)>0, COUNTIFS($AI$2:$AI$200,$G21)>0, COUNTIFS($AJ$2:$AJ$200,$G21)>0, COUNTIFS($AK$2:$AK$200,$G21)>0, COUNTIFS($AL$2:$AL$200,$G21)>0, COUNTIFS($AM$2:$AM$200,$G21)>0, COUNTIFS($AN$2:$AN$200,$G21)>0, COUNTIFS($AO$2:$AO$200,$G21)>0, COUNTIFS($AP$2:$AP$200,$G21)>0, COUNTIFS($AQ$2:$AQ$200,$G21)>0, COUNTIFS($AR$2:$AR$200,$G21)>0, COUNTIFS($AS$2:$AS$200,$G21)>0, COUNTIFS($AT$2:$AT$200,$G21)>0, COUNTIFS($AU$2:$AU$200,$G21)>0, COUNTIFS($AV$2:$AV$200,$G21)>0, COUNTIFS($AW$2:$AW$200,$G21)>0, COUNTIFS($AX$2:$AX$200,$G21)>0 )), ), 4 ), "")} | G21: Ascensão do Avernus | I21: Jhoira | J21: =Jhoira!G2 -> 5 | K21: Não | L21: Sim | M21: Sim | N21: Não | O21: Não | P21: Combo | Q21: Combate | R21: Destruição em Massa | S21: =IF(J21<6,"5",IF(J21<11,"4",IF(J21<16,"3",IF(J21<31,"2","1")))) -> 5 | V21: Second Harvest | W21: Slayers' Stronghold | X21: Protection Magic | Z21: Trenzalore Clocktower | AA21: Tishana, Voice of Thunder | AX21: Inkmoth Nexus | BB21: Jetmir, Nexus of Revels | BC21: Irenicus's Vile Duplication | BD21: Hierofante de Elenda | BE21: Singer of Swift Rivers | BF21: Ulamog, o Profanador | BG21: Watery Grave | BH21: Valfenda | BI21: Oko, Thief of Crowns | BP21: Inkmoth Nexus | BS21: Emberwilde Captain | BT21: Ghoulish Impetus | BU21: Mox Tantalite | BV21: Jitte Perdida | BW21: Trioma de Raugrin | BX21: Season of Weaving | BZ21: Inkmoth Nexus | CB21: Canopy Vista | CC21: Entomb | CD21: Mistrise Village | CE21: Great Furnace | CG21: Boros Charm | CH21: Duty Beyond Death | CJ21: Ascensão do Avernus
A22: =IFERROR(INDEX($S$3:$S$200, MATCH($C22, $I$3:$I$200, 0)), "") -> 2 | B22: =COUNTIF(U:AX,G22) -> 1 | C22: =IFERROR( INDEX($U$1:$AX$1, MATCH(TRUE, CHOOSE({1;2;3;4;5;6;7;8;9;10;11;12;13;14;15;16;17;18;19;20;21;22;23;24;25;26;27;28;29;30;31;32}, COUNTIFS($U$2:$U$200,$G22)>0, COUNTIFS($V$2:$V$200,$G22)>0, COUNTIFS($W$2:$W$200,$G22)>0, COUNTIFS($X$2:$X$200,$G22)>0, COUNTIFS($Y$2:$Y$200,$G22)>0, COUNTIFS($Z$2:$Z$200,$G22)>0, COUNTIFS($AA$2:$AA$200,$G22)>0, COUNTIFS($AB$2:$AB$200,$G22)>0, COUNTIFS($AC$2:$AC$200,$G22)>0, COUNTIFS($AD$2:$AD$200,$G22)>0, COUNTIFS($AE$2:$AE$200,$G22)>0, COUNTIFS($AF$2:$AF$200,$G22)>0, COUNTIFS($AG$2:$AG$200,$G22)>0, COUNTIFS($AH$2:$AH$200,$G22)>0, COUNTIFS($AI$2:$AI$200,$G22)>0, COUNTIFS($AJ$2:$AJ$200,$G22)>0, COUNTIFS($AK$2:$AK$200,$G22)>0, COUNTIFS($AL$2:$AL$200,$G22)>0, COUNTIFS($AM$2:$AM$200,$G22)>0, COUNTIFS($AN$2:$AN$200,$G22)>0, COUNTIFS($AO$2:$AO$200,$G22)>0, COUNTIFS($AP$2:$AP$200,$G22)>0, COUNTIFS($AQ$2:$AQ$200,$G22)>0, COUNTIFS($AR$2:$AR$200,$G22)>0, COUNTIFS($AS$2:$AS$200,$G22)>0, COUNTIFS($AT$2:$AT$200,$G22)>0, COUNTIFS($AU$2:$AU$200,$G22)>0, COUNTIFS($AV$2:$AV$200,$G22)>0, COUNTIFS($AW$2:$AW$200,$G22)>0, COUNTIFS($AX$2:$AX$200,$G22)>0 ), 0) ), "") -> Baylen | D22: {=IFERROR( INDEX( _xlfn._xlws.FILTER($U$1:$AX$1, TRANSPOSE( CHOOSE({1;2;3;4;5;6;7;8;9;10;11;12;13;14;15;16;17;18;19;20;21;22;23;24;25;26;27;28;29;30}, COUNTIFS($U$2:$U$200,$G22)>0, COUNTIFS($V$2:$V$200,$G22)>0, COUNTIFS($W$2:$W$200,$G22)>0, COUNTIFS($X$2:$X$200,$G22)>0, COUNTIFS($Y$2:$Y$200,$G22)>0, COUNTIFS($Z$2:$Z$200,$G22)>0, COUNTIFS($AA$2:$AA$200,$G22)>0, COUNTIFS($AB$2:$AB$200,$G22)>0, COUNTIFS($AC$2:$AC$200,$G22)>0, COUNTIFS($AD$2:$AD$200,$G22)>0, COUNTIFS($AE$2:$AE$200,$G22)>0, COUNTIFS($AF$2:$AF$200,$G22)>0, COUNTIFS($AG$2:$AG$200,$G22)>0, COUNTIFS($AH$2:$AH$200,$G22)>0, COUNTIFS($AI$2:$AI$200,$G22)>0, COUNTIFS($AJ$2:$AJ$200,$G22)>0, COUNTIFS($AK$2:$AK$200,$G22)>0, COUNTIFS($AL$2:$AL$200,$G22)>0, COUNTIFS($AM$2:$AM$200,$G22)>0, COUNTIFS($AN$2:$AN$200,$G22)>0, COUNTIFS($AO$2:$AO$200,$G22)>0, COUNTIFS($AP$2:$AP$200,$G22)>0, COUNTIFS($AQ$2:$AQ$200,$G22)>0, COUNTIFS($AR$2:$AR$200,$G22)>0, COUNTIFS($AS$2:$AS$200,$G22)>0, COUNTIFS($AT$2:$AT$200,$G22)>0, COUNTIFS($AU$2:$AU$200,$G22)>0, COUNTIFS($AV$2:$AV$200,$G22)>0, COUNTIFS($AW$2:$AW$200,$G22)>0, COUNTIFS($AX$2:$AX$200,$G22)>0 )), ), 2 ), "")} | E22: {=IFERROR( INDEX( _xlfn._xlws.FILTER($U$1:$AX$1, TRANSPOSE( CHOOSE({1;2;3;4;5;6;7;8;9;10;11;12;13;14;15;16;17;18;19;20;21;22;23;24;25;26;27;28;29;30}, COUNTIFS($U$2:$U$200,$G22)>0, COUNTIFS($V$2:$V$200,$G22)>0, COUNTIFS($W$2:$W$200,$G22)>0, COUNTIFS($X$2:$X$200,$G22)>0, COUNTIFS($Y$2:$Y$200,$G22)>0, COUNTIFS($Z$2:$Z$200,$G22)>0, COUNTIFS($AA$2:$AA$200,$G22)>0, COUNTIFS($AB$2:$AB$200,$G22)>0, COUNTIFS($AC$2:$AC$200,$G22)>0, COUNTIFS($AD$2:$AD$200,$G22)>0, COUNTIFS($AE$2:$AE$200,$G22)>0, COUNTIFS($AF$2:$AF$200,$G22)>0, COUNTIFS($AG$2:$AG$200,$G22)>0, COUNTIFS($AH$2:$AH$200,$G22)>0, COUNTIFS($AI$2:$AI$200,$G22)>0, COUNTIFS($AJ$2:$AJ$200,$G22)>0, COUNTIFS($AK$2:$AK$200,$G22)>0, COUNTIFS($AL$2:$AL$200,$G22)>0, COUNTIFS($AM$2:$AM$200,$G22)>0, COUNTIFS($AN$2:$AN$200,$G22)>0, COUNTIFS($AO$2:$AO$200,$G22)>0, COUNTIFS($AP$2:$AP$200,$G22)>0, COUNTIFS($AQ$2:$AQ$200,$G22)>0, COUNTIFS($AR$2:$AR$200,$G22)>0, COUNTIFS($AS$2:$AS$200,$G22)>0, COUNTIFS($AT$2:$AT$200,$G22)>0, COUNTIFS($AU$2:$AU$200,$G22)>0, COUNTIFS($AV$2:$AV$200,$G22)>0, COUNTIFS($AW$2:$AW$200,$G22)>0, COUNTIFS($AX$2:$AX$200,$G22)>0 )), ), 3 ), "")} | F22: {=IFERROR( INDEX( _xlfn._xlws.FILTER($U$1:$AX$1, TRANSPOSE( CHOOSE({1;2;3;4;5;6;7;8;9;10;11;12;13;14;15;16;17;18;19;20;21;22;23;24;25;26;27;28;29;30}, COUNTIFS($U$2:$U$200,$G22)>0, COUNTIFS($V$2:$V$200,$G22)>0, COUNTIFS($W$2:$W$200,$G22)>0, COUNTIFS($X$2:$X$200,$G22)>0, COUNTIFS($Y$2:$Y$200,$G22)>0, COUNTIFS($Z$2:$Z$200,$G22)>0, COUNTIFS($AA$2:$AA$200,$G22)>0, COUNTIFS($AB$2:$AB$200,$G22)>0, COUNTIFS($AC$2:$AC$200,$G22)>0, COUNTIFS($AD$2:$AD$200,$G22)>0, COUNTIFS($AE$2:$AE$200,$G22)>0, COUNTIFS($AF$2:$AF$200,$G22)>0, COUNTIFS($AG$2:$AG$200,$G22)>0, COUNTIFS($AH$2:$AH$200,$G22)>0, COUNTIFS($AI$2:$AI$200,$G22)>0, COUNTIFS($AJ$2:$AJ$200,$G22)>0, COUNTIFS($AK$2:$AK$200,$G22)>0, COUNTIFS($AL$2:$AL$200,$G22)>0, COUNTIFS($AM$2:$AM$200,$G22)>0, COUNTIFS($AN$2:$AN$200,$G22)>0, COUNTIFS($AO$2:$AO$200,$G22)>0, COUNTIFS($AP$2:$AP$200,$G22)>0, COUNTIFS($AQ$2:$AQ$200,$G22)>0, COUNTIFS($AR$2:$AR$200,$G22)>0, COUNTIFS($AS$2:$AS$200,$G22)>0, COUNTIFS($AT$2:$AT$200,$G22)>0, COUNTIFS($AU$2:$AU$200,$G22)>0, COUNTIFS($AV$2:$AV$200,$G22)>0, COUNTIFS($AW$2:$AW$200,$G22)>0, COUNTIFS($AX$2:$AX$200,$G22)>0 )), ), 4 ), "")} | G22: Aura Mutation | I22: Fractius | J22: =Fractius!G2 -> 8 | K22: Sim | L22: Sim | M22: Sim | N22: Sim | O22: Sim | P22: Combate | Q22: Voltron | R22: Tribal de Fractius | S22: =IF(J22<6,"5",IF(J22<11,"4",IF(J22<16,"3",IF(J22<31,"2","1")))) -> 4 | V22: Seedborn Muse | W22: Smuggler's Share | X22: Resourceful Defense | Z22: Xantcha, Agente Adormecida | AA22: Vanquisher's Banner | AX22: Karn's Bastion | BB22: Karplusan Forest | BC22: Jidoor, Aristocratic Capital // Overture | BD22: Keen Duelist | BE22: Sol Ring | BF22: Ulamog, the Infinite Gyre | BH22: Warren Soultrader | BI22: Ripples of Potential | BP22: Karn's Bastion | BS22: Exalted Sunborn | BT22: Giver of Runes | BU22: Petrified Field | BV22: Karn Liberated | BW22: Trioma de Zagoth | BX22: Serenata das Estriges | BZ22: Karn's Bastion | CB22: Castle Ardenvale | CC22: Espada da Riqueza e do Poder | CD22: Nibelheim Aflame | CE22: Haru, Hidden Talent | CG22: Bothersome Quasit | CH22: Earth Rumble | CJ22: Aura Mutation
A23: =IFERROR(INDEX($S$3:$S$200, MATCH($C23, $I$3:$I$200, 0)), "") -> 3 | B23: =COUNTIF(U:AX,G23) -> 1 | C23: =IFERROR( INDEX($U$1:$AX$1, MATCH(TRUE, CHOOSE({1;2;3;4;5;6;7;8;9;10;11;12;13;14;15;16;17;18;19;20;21;22;23;24;25;26;27;28;29;30;31;32}, COUNTIFS($U$2:$U$200,$G23)>0, COUNTIFS($V$2:$V$200,$G23)>0, COUNTIFS($W$2:$W$200,$G23)>0, COUNTIFS($X$2:$X$200,$G23)>0, COUNTIFS($Y$2:$Y$200,$G23)>0, COUNTIFS($Z$2:$Z$200,$G23)>0, COUNTIFS($AA$2:$AA$200,$G23)>0, COUNTIFS($AB$2:$AB$200,$G23)>0, COUNTIFS($AC$2:$AC$200,$G23)>0, COUNTIFS($AD$2:$AD$200,$G23)>0, COUNTIFS($AE$2:$AE$200,$G23)>0, COUNTIFS($AF$2:$AF$200,$G23)>0, COUNTIFS($AG$2:$AG$200,$G23)>0, COUNTIFS($AH$2:$AH$200,$G23)>0, COUNTIFS($AI$2:$AI$200,$G23)>0, COUNTIFS($AJ$2:$AJ$200,$G23)>0, COUNTIFS($AK$2:$AK$200,$G23)>0, COUNTIFS($AL$2:$AL$200,$G23)>0, COUNTIFS($AM$2:$AM$200,$G23)>0, COUNTIFS($AN$2:$AN$200,$G23)>0, COUNTIFS($AO$2:$AO$200,$G23)>0, COUNTIFS($AP$2:$AP$200,$G23)>0, COUNTIFS($AQ$2:$AQ$200,$G23)>0, COUNTIFS($AR$2:$AR$200,$G23)>0, COUNTIFS($AS$2:$AS$200,$G23)>0, COUNTIFS($AT$2:$AT$200,$G23)>0, COUNTIFS($AU$2:$AU$200,$G23)>0, COUNTIFS($AV$2:$AV$200,$G23)>0, COUNTIFS($AW$2:$AW$200,$G23)>0, COUNTIFS($AX$2:$AX$200,$G23)>0 ), 0) ), "") -> Carlos | D23: {=IFERROR( INDEX( _xlfn._xlws.FILTER($U$1:$AX$1, TRANSPOSE( CHOOSE({1;2;3;4;5;6;7;8;9;10;11;12;13;14;15;16;17;18;19;20;21;22;23;24;25;26;27;28;29;30}, COUNTIFS($U$2:$U$200,$G23)>0, COUNTIFS($V$2:$V$200,$G23)>0, COUNTIFS($W$2:$W$200,$G23)>0, COUNTIFS($X$2:$X$200,$G23)>0, COUNTIFS($Y$2:$Y$200,$G23)>0, COUNTIFS($Z$2:$Z$200,$G23)>0, COUNTIFS($AA$2:$AA$200,$G23)>0, COUNTIFS($AB$2:$AB$200,$G23)>0, COUNTIFS($AC$2:$AC$200,$G23)>0, COUNTIFS($AD$2:$AD$200,$G23)>0, COUNTIFS($AE$2:$AE$200,$G23)>0, COUNTIFS($AF$2:$AF$200,$G23)>0, COUNTIFS($AG$2:$AG$200,$G23)>0, COUNTIFS($AH$2:$AH$200,$G23)>0, COUNTIFS($AI$2:$AI$200,$G23)>0, COUNTIFS($AJ$2:$AJ$200,$G23)>0, COUNTIFS($AK$2:$AK$200,$G23)>0, COUNTIFS($AL$2:$AL$200,$G23)>0, COUNTIFS($AM$2:$AM$200,$G23)>0, COUNTIFS($AN$2:$AN$200,$G23)>0, COUNTIFS($AO$2:$AO$200,$G23)>0, COUNTIFS($AP$2:$AP$200,$G23)>0, COUNTIFS($AQ$2:$AQ$200,$G23)>0, COUNTIFS($AR$2:$AR$200,$G23)>0, COUNTIFS($AS$2:$AS$200,$G23)>0, COUNTIFS($AT$2:$AT$200,$G23)>0, COUNTIFS($AU$2:$AU$200,$G23)>0, COUNTIFS($AV$2:$AV$200,$G23)>0, COUNTIFS($AW$2:$AW$200,$G23)>0, COUNTIFS($AX$2:$AX$200,$G23)>0 )), ), 2 ), "")} | E23: {=IFERROR( INDEX( _xlfn._xlws.FILTER($U$1:$AX$1, TRANSPOSE( CHOOSE({1;2;3;4;5;6;7;8;9;10;11;12;13;14;15;16;17;18;19;20;21;22;23;24;25;26;27;28;29;30}, COUNTIFS($U$2:$U$200,$G23)>0, COUNTIFS($V$2:$V$200,$G23)>0, COUNTIFS($W$2:$W$200,$G23)>0, COUNTIFS($X$2:$X$200,$G23)>0, COUNTIFS($Y$2:$Y$200,$G23)>0, COUNTIFS($Z$2:$Z$200,$G23)>0, COUNTIFS($AA$2:$AA$200,$G23)>0, COUNTIFS($AB$2:$AB$200,$G23)>0, COUNTIFS($AC$2:$AC$200,$G23)>0, COUNTIFS($AD$2:$AD$200,$G23)>0, COUNTIFS($AE$2:$AE$200,$G23)>0, COUNTIFS($AF$2:$AF$200,$G23)>0, COUNTIFS($AG$2:$AG$200,$G23)>0, COUNTIFS($AH$2:$AH$200,$G23)>0, COUNTIFS($AI$2:$AI$200,$G23)>0, COUNTIFS($AJ$2:$AJ$200,$G23)>0, COUNTIFS($AK$2:$AK$200,$G23)>0, COUNTIFS($AL$2:$AL$200,$G23)>0, COUNTIFS($AM$2:$AM$200,$G23)>0, COUNTIFS($AN$2:$AN$200,$G23)>0, COUNTIFS($AO$2:$AO$200,$G23)>0, COUNTIFS($AP$2:$AP$200,$G23)>0, COUNTIFS($AQ$2:$AQ$200,$G23)>0, COUNTIFS($AR$2:$AR$200,$G23)>0, COUNTIFS($AS$2:$AS$200,$G23)>0, COUNTIFS($AT$2:$AT$200,$G23)>0, COUNTIFS($AU$2:$AU$200,$G23)>0, COUNTIFS($AV$2:$AV$200,$G23)>0, COUNTIFS($AW$2:$AW$200,$G23)>0, COUNTIFS($AX$2:$AX$200,$G23)>0 )), ), 3 ), "")} | F23: {=IFERROR( INDEX( _xlfn._xlws.FILTER($U$1:$AX$1, TRANSPOSE( CHOOSE({1;2;3;4;5;6;7;8;9;10;11;12;13;14;15;16;17;18;19;20;21;22;23;24;25;26;27;28;29;30}, COUNTIFS($U$2:$U$200,$G23)>0, COUNTIFS($V$2:$V$200,$G23)>0, COUNTIFS($W$2:$W$200,$G23)>0, COUNTIFS($X$2:$X$200,$G23)>0, COUNTIFS($Y$2:$Y$200,$G23)>0, COUNTIFS($Z$2:$Z$200,$G23)>0, COUNTIFS($AA$2:$AA$200,$G23)>0, COUNTIFS($AB$2:$AB$200,$G23)>0, COUNTIFS($AC$2:$AC$200,$G23)>0, COUNTIFS($AD$2:$AD$200,$G23)>0, COUNTIFS($AE$2:$AE$200,$G23)>0, COUNTIFS($AF$2:$AF$200,$G23)>0, COUNTIFS($AG$2:$AG$200,$G23)>0, COUNTIFS($AH$2:$AH$200,$G23)>0, COUNTIFS($AI$2:$AI$200,$G23)>0, COUNTIFS($AJ$2:$AJ$200,$G23)>0, COUNTIFS($AK$2:$AK$200,$G23)>0, COUNTIFS($AL$2:$AL$200,$G23)>0, COUNTIFS($AM$2:$AM$200,$G23)>0, COUNTIFS($AN$2:$AN$200,$G23)>0, COUNTIFS($AO$2:$AO$200,$G23)>0, COUNTIFS($AP$2:$AP$200,$G23)>0, COUNTIFS($AQ$2:$AQ$200,$G23)>0, COUNTIFS($AR$2:$AR$200,$G23)>0, COUNTIFS($AS$2:$AS$200,$G23)>0, COUNTIFS($AT$2:$AT$200,$G23)>0, COUNTIFS($AU$2:$AU$200,$G23)>0, COUNTIFS($AV$2:$AV$200,$G23)>0, COUNTIFS($AW$2:$AW$200,$G23)>0, COUNTIFS($AX$2:$AX$200,$G23)>0 )), ), 4 ), "")} | G23: Autoridade dos Cônsules | I23: Rielle | J23: =Rielle!G2 -> 7 | K23: Não | L23: Sim | M23: Sim | N23: Não | O23: Não | P23: Voltron | Q23: Dano Direto | R23: Controle Voltron | S23: =IF(J23<6,"5",IF(J23<11,"4",IF(J23<16,"3",IF(J23<31,"2","1")))) -> 4 | V23: Sunscorched Divide | W23: Sokenzan, Crucible of Defiance | X23: Reyhan, Last of the Abzan | AX23: Kodama of the West Tree | BB23: Lightning Greaves | BC23: Khorvath's Fury | BD23: Life of the Party | BE23: Sothera, the Supervoid | BF23: Ulamog's Dreadsire | BH23: Watery Grave | BI23: Stoneforge Mystic | BP23: Kodama of the West Tree | BS23: Fabled Passage | BT23: Grave Pact | BU23: Phyrexian Tower | BV23: Kaya the Inexorable | BW23: Ulamog, o Profanador | BX23: Sokenzan, Crisol da Afronta | BZ23: Kodama of the West Tree | CB23: Champion of Lambholt | CC23: Espada de Banquete e Fome | CD23: Nissa, Resurgent Animist | CE23: Haywire Mite | CG23: Broadside Bombardiers | CH23: Earthbending Student | CJ23: Autoridade dos Cônsules
A24: =IFERROR(INDEX($S$3:$S$200, MATCH($C24, $I$3:$I$200, 0)), "") -> 2 | B24: =COUNTIF(U:AX,G24) -> 1 | C24: =IFERROR( INDEX($U$1:$AX$1, MATCH(TRUE, CHOOSE({1;2;3;4;5;6;7;8;9;10;11;12;13;14;15;16;17;18;19;20;21;22;23;24;25;26;27;28;29;30;31;32}, COUNTIFS($U$2:$U$200,$G24)>0, COUNTIFS($V$2:$V$200,$G24)>0, COUNTIFS($W$2:$W$200,$G24)>0, COUNTIFS($X$2:$X$200,$G24)>0, COUNTIFS($Y$2:$Y$200,$G24)>0, COUNTIFS($Z$2:$Z$200,$G24)>0, COUNTIFS($AA$2:$AA$200,$G24)>0, COUNTIFS($AB$2:$AB$200,$G24)>0, COUNTIFS($AC$2:$AC$200,$G24)>0, COUNTIFS($AD$2:$AD$200,$G24)>0, COUNTIFS($AE$2:$AE$200,$G24)>0, COUNTIFS($AF$2:$AF$200,$G24)>0, COUNTIFS($AG$2:$AG$200,$G24)>0, COUNTIFS($AH$2:$AH$200,$G24)>0, COUNTIFS($AI$2:$AI$200,$G24)>0, COUNTIFS($AJ$2:$AJ$200,$G24)>0, COUNTIFS($AK$2:$AK$200,$G24)>0, COUNTIFS($AL$2:$AL$200,$G24)>0, COUNTIFS($AM$2:$AM$200,$G24)>0, COUNTIFS($AN$2:$AN$200,$G24)>0, COUNTIFS($AO$2:$AO$200,$G24)>0, COUNTIFS($AP$2:$AP$200,$G24)>0, COUNTIFS($AQ$2:$AQ$200,$G24)>0, COUNTIFS($AR$2:$AR$200,$G24)>0, COUNTIFS($AS$2:$AS$200,$G24)>0, COUNTIFS($AT$2:$AT$200,$G24)>0, COUNTIFS($AU$2:$AU$200,$G24)>0, COUNTIFS($AV$2:$AV$200,$G24)>0, COUNTIFS($AW$2:$AW$200,$G24)>0, COUNTIFS($AX$2:$AX$200,$G24)>0 ), 0) ), "") -> Piratas | D24: {=IFERROR( INDEX( _xlfn._xlws.FILTER($U$1:$AX$1, TRANSPOSE( CHOOSE({1;2;3;4;5;6;7;8;9;10;11;12;13;14;15;16;17;18;19;20;21;22;23;24;25;26;27;28;29;30}, COUNTIFS($U$2:$U$200,$G24)>0, COUNTIFS($V$2:$V$200,$G24)>0, COUNTIFS($W$2:$W$200,$G24)>0, COUNTIFS($X$2:$X$200,$G24)>0, COUNTIFS($Y$2:$Y$200,$G24)>0, COUNTIFS($Z$2:$Z$200,$G24)>0, COUNTIFS($AA$2:$AA$200,$G24)>0, COUNTIFS($AB$2:$AB$200,$G24)>0, COUNTIFS($AC$2:$AC$200,$G24)>0, COUNTIFS($AD$2:$AD$200,$G24)>0, COUNTIFS($AE$2:$AE$200,$G24)>0, COUNTIFS($AF$2:$AF$200,$G24)>0, COUNTIFS($AG$2:$AG$200,$G24)>0, COUNTIFS($AH$2:$AH$200,$G24)>0, COUNTIFS($AI$2:$AI$200,$G24)>0, COUNTIFS($AJ$2:$AJ$200,$G24)>0, COUNTIFS($AK$2:$AK$200,$G24)>0, COUNTIFS($AL$2:$AL$200,$G24)>0, COUNTIFS($AM$2:$AM$200,$G24)>0, COUNTIFS($AN$2:$AN$200,$G24)>0, COUNTIFS($AO$2:$AO$200,$G24)>0, COUNTIFS($AP$2:$AP$200,$G24)>0, COUNTIFS($AQ$2:$AQ$200,$G24)>0, COUNTIFS($AR$2:$AR$200,$G24)>0, COUNTIFS($AS$2:$AS$200,$G24)>0, COUNTIFS($AT$2:$AT$200,$G24)>0, COUNTIFS($AU$2:$AU$200,$G24)>0, COUNTIFS($AV$2:$AV$200,$G24)>0, COUNTIFS($AW$2:$AW$200,$G24)>0, COUNTIFS($AX$2:$AX$200,$G24)>0 )), ), 2 ), "")} | E24: {=IFERROR( INDEX( _xlfn._xlws.FILTER($U$1:$AX$1, TRANSPOSE( CHOOSE({1;2;3;4;5;6;7;8;9;10;11;12;13;14;15;16;17;18;19;20;21;22;23;24;25;26;27;28;29;30}, COUNTIFS($U$2:$U$200,$G24)>0, COUNTIFS($V$2:$V$200,$G24)>0, COUNTIFS($W$2:$W$200,$G24)>0, COUNTIFS($X$2:$X$200,$G24)>0, COUNTIFS($Y$2:$Y$200,$G24)>0, COUNTIFS($Z$2:$Z$200,$G24)>0, COUNTIFS($AA$2:$AA$200,$G24)>0, COUNTIFS($AB$2:$AB$200,$G24)>0, COUNTIFS($AC$2:$AC$200,$G24)>0, COUNTIFS($AD$2:$AD$200,$G24)>0, COUNTIFS($AE$2:$AE$200,$G24)>0, COUNTIFS($AF$2:$AF$200,$G24)>0, COUNTIFS($AG$2:$AG$200,$G24)>0, COUNTIFS($AH$2:$AH$200,$G24)>0, COUNTIFS($AI$2:$AI$200,$G24)>0, COUNTIFS($AJ$2:$AJ$200,$G24)>0, COUNTIFS($AK$2:$AK$200,$G24)>0, COUNTIFS($AL$2:$AL$200,$G24)>0, COUNTIFS($AM$2:$AM$200,$G24)>0, COUNTIFS($AN$2:$AN$200,$G24)>0, COUNTIFS($AO$2:$AO$200,$G24)>0, COUNTIFS($AP$2:$AP$200,$G24)>0, COUNTIFS($AQ$2:$AQ$200,$G24)>0, COUNTIFS($AR$2:$AR$200,$G24)>0, COUNTIFS($AS$2:$AS$200,$G24)>0, COUNTIFS($AT$2:$AT$200,$G24)>0, COUNTIFS($AU$2:$AU$200,$G24)>0, COUNTIFS($AV$2:$AV$200,$G24)>0, COUNTIFS($AW$2:$AW$200,$G24)>0, COUNTIFS($AX$2:$AX$200,$G24)>0 )), ), 3 ), "")} | F24: {=IFERROR( INDEX( _xlfn._xlws.FILTER($U$1:$AX$1, TRANSPOSE( CHOOSE({1;2;3;4;5;6;7;8;9;10;11;12;13;14;15;16;17;18;19;20;21;22;23;24;25;26;27;28;29;30}, COUNTIFS($U$2:$U$200,$G24)>0, COUNTIFS($V$2:$V$200,$G24)>0, COUNTIFS($W$2:$W$200,$G24)>0, COUNTIFS($X$2:$X$200,$G24)>0, COUNTIFS($Y$2:$Y$200,$G24)>0, COUNTIFS($Z$2:$Z$200,$G24)>0, COUNTIFS($AA$2:$AA$200,$G24)>0, COUNTIFS($AB$2:$AB$200,$G24)>0, COUNTIFS($AC$2:$AC$200,$G24)>0, COUNTIFS($AD$2:$AD$200,$G24)>0, COUNTIFS($AE$2:$AE$200,$G24)>0, COUNTIFS($AF$2:$AF$200,$G24)>0, COUNTIFS($AG$2:$AG$200,$G24)>0, COUNTIFS($AH$2:$AH$200,$G24)>0, COUNTIFS($AI$2:$AI$200,$G24)>0, COUNTIFS($AJ$2:$AJ$200,$G24)>0, COUNTIFS($AK$2:$AK$200,$G24)>0, COUNTIFS($AL$2:$AL$200,$G24)>0, COUNTIFS($AM$2:$AM$200,$G24)>0, COUNTIFS($AN$2:$AN$200,$G24)>0, COUNTIFS($AO$2:$AO$200,$G24)>0, COUNTIFS($AP$2:$AP$200,$G24)>0, COUNTIFS($AQ$2:$AQ$200,$G24)>0, COUNTIFS($AR$2:$AR$200,$G24)>0, COUNTIFS($AS$2:$AS$200,$G24)>0, COUNTIFS($AT$2:$AT$200,$G24)>0, COUNTIFS($AU$2:$AU$200,$G24)>0, COUNTIFS($AV$2:$AV$200,$G24)>0, COUNTIFS($AW$2:$AW$200,$G24)>0, COUNTIFS($AX$2:$AX$200,$G24)>0 )), ), 4 ), "")} | G24: Back in Town | I24: Oona | J24: =Oona!G2 -> 7 | K24: Não | L24: Sim | M24: Não | N24: Sim | O24: Não | P24: Mill | Q24: Combate | R24: Mill e Tokens | S24: =IF(J24<6,"5",IF(J24<11,"4",IF(J24<16,"3",IF(J24<31,"2","1")))) -> 4 | V24: Teferi's Protection | W24: Sol Ring | X24: Shelinda, Yevon Acolyte | AX24: Lithoform Engine | BB24: Marcha dos Canonizados | BC24: Kutzil, Malamet Exemplar | BD24: Mother of runes | BE24: Stonybrook Banneret | BF24: Valfenda | BI24: Vronos, Masked Inquisitor | BP24: Lithoform Engine | BS24: Farmer Cotton | BT24: Guia das Almas | BU24: Polluted Delta | BV24: Kellan, the Fae-Blooded // Birthright Boon | BW24: Uthros, Titanic Godcore | BX24: Sonic Screwdriver | BZ24: Lithoform Engine | CB24: Champions from Beyond | CC24: Espada de Fogo e Gelo | CD24: Obelisco de Obsidiana | CE24: High Market | CG24: Brushland | CH24: Elvish Reclaimer | CJ24: Back in Town
A25: =IFERROR(INDEX($S$3:$S$200, MATCH($C25, $I$3:$I$200, 0)), "") -> 1 | B25: =COUNTIF(U:AX,G25) -> 1 | C25: =IFERROR( INDEX($U$1:$AX$1, MATCH(TRUE, CHOOSE({1;2;3;4;5;6;7;8;9;10;11;12;13;14;15;16;17;18;19;20;21;22;23;24;25;26;27;28;29;30;31;32}, COUNTIFS($U$2:$U$200,$G25)>0, COUNTIFS($V$2:$V$200,$G25)>0, COUNTIFS($W$2:$W$200,$G25)>0, COUNTIFS($X$2:$X$200,$G25)>0, COUNTIFS($Y$2:$Y$200,$G25)>0, COUNTIFS($Z$2:$Z$200,$G25)>0, COUNTIFS($AA$2:$AA$200,$G25)>0, COUNTIFS($AB$2:$AB$200,$G25)>0, COUNTIFS($AC$2:$AC$200,$G25)>0, COUNTIFS($AD$2:$AD$200,$G25)>0, COUNTIFS($AE$2:$AE$200,$G25)>0, COUNTIFS($AF$2:$AF$200,$G25)>0, COUNTIFS($AG$2:$AG$200,$G25)>0, COUNTIFS($AH$2:$AH$200,$G25)>0, COUNTIFS($AI$2:$AI$200,$G25)>0, COUNTIFS($AJ$2:$AJ$200,$G25)>0, COUNTIFS($AK$2:$AK$200,$G25)>0, COUNTIFS($AL$2:$AL$200,$G25)>0, COUNTIFS($AM$2:$AM$200,$G25)>0, COUNTIFS($AN$2:$AN$200,$G25)>0, COUNTIFS($AO$2:$AO$200,$G25)>0, COUNTIFS($AP$2:$AP$200,$G25)>0, COUNTIFS($AQ$2:$AQ$200,$G25)>0, COUNTIFS($AR$2:$AR$200,$G25)>0, COUNTIFS($AS$2:$AS$200,$G25)>0, COUNTIFS($AT$2:$AT$200,$G25)>0, COUNTIFS($AU$2:$AU$200,$G25)>0, COUNTIFS($AV$2:$AV$200,$G25)>0, COUNTIFS($AW$2:$AW$200,$G25)>0, COUNTIFS($AX$2:$AX$200,$G25)>0 ), 0) ), "") -> Modular | D25: {=IFERROR( INDEX( _xlfn._xlws.FILTER($U$1:$AX$1, TRANSPOSE( CHOOSE({1;2;3;4;5;6;7;8;9;10;11;12;13;14;15;16;17;18;19;20;21;22;23;24;25;26;27;28;29;30}, COUNTIFS($U$2:$U$200,$G25)>0, COUNTIFS($V$2:$V$200,$G25)>0, COUNTIFS($W$2:$W$200,$G25)>0, COUNTIFS($X$2:$X$200,$G25)>0, COUNTIFS($Y$2:$Y$200,$G25)>0, COUNTIFS($Z$2:$Z$200,$G25)>0, COUNTIFS($AA$2:$AA$200,$G25)>0, COUNTIFS($AB$2:$AB$200,$G25)>0, COUNTIFS($AC$2:$AC$200,$G25)>0, COUNTIFS($AD$2:$AD$200,$G25)>0, COUNTIFS($AE$2:$AE$200,$G25)>0, COUNTIFS($AF$2:$AF$200,$G25)>0, COUNTIFS($AG$2:$AG$200,$G25)>0, COUNTIFS($AH$2:$AH$200,$G25)>0, COUNTIFS($AI$2:$AI$200,$G25)>0, COUNTIFS($AJ$2:$AJ$200,$G25)>0, COUNTIFS($AK$2:$AK$200,$G25)>0, COUNTIFS($AL$2:$AL$200,$G25)>0, COUNTIFS($AM$2:$AM$200,$G25)>0, COUNTIFS($AN$2:$AN$200,$G25)>0, COUNTIFS($AO$2:$AO$200,$G25)>0, COUNTIFS($AP$2:$AP$200,$G25)>0, COUNTIFS($AQ$2:$AQ$200,$G25)>0, COUNTIFS($AR$2:$AR$200,$G25)>0, COUNTIFS($AS$2:$AS$200,$G25)>0, COUNTIFS($AT$2:$AT$200,$G25)>0, COUNTIFS($AU$2:$AU$200,$G25)>0, COUNTIFS($AV$2:$AV$200,$G25)>0, COUNTIFS($AW$2:$AW$200,$G25)>0, COUNTIFS($AX$2:$AX$200,$G25)>0 )), ), 2 ), "")} | E25: {=IFERROR( INDEX( _xlfn._xlws.FILTER($U$1:$AX$1, TRANSPOSE( CHOOSE({1;2;3;4;5;6;7;8;9;10;11;12;13;14;15;16;17;18;19;20;21;22;23;24;25;26;27;28;29;30}, COUNTIFS($U$2:$U$200,$G25)>0, COUNTIFS($V$2:$V$200,$G25)>0, COUNTIFS($W$2:$W$200,$G25)>0, COUNTIFS($X$2:$X$200,$G25)>0, COUNTIFS($Y$2:$Y$200,$G25)>0, COUNTIFS($Z$2:$Z$200,$G25)>0, COUNTIFS($AA$2:$AA$200,$G25)>0, COUNTIFS($AB$2:$AB$200,$G25)>0, COUNTIFS($AC$2:$AC$200,$G25)>0, COUNTIFS($AD$2:$AD$200,$G25)>0, COUNTIFS($AE$2:$AE$200,$G25)>0, COUNTIFS($AF$2:$AF$200,$G25)>0, COUNTIFS($AG$2:$AG$200,$G25)>0, COUNTIFS($AH$2:$AH$200,$G25)>0, COUNTIFS($AI$2:$AI$200,$G25)>0, COUNTIFS($AJ$2:$AJ$200,$G25)>0, COUNTIFS($AK$2:$AK$200,$G25)>0, COUNTIFS($AL$2:$AL$200,$G25)>0, COUNTIFS($AM$2:$AM$200,$G25)>0, COUNTIFS($AN$2:$AN$200,$G25)>0, COUNTIFS($AO$2:$AO$200,$G25)>0, COUNTIFS($AP$2:$AP$200,$G25)>0, COUNTIFS($AQ$2:$AQ$200,$G25)>0, COUNTIFS($AR$2:$AR$200,$G25)>0, COUNTIFS($AS$2:$AS$200,$G25)>0, COUNTIFS($AT$2:$AT$200,$G25)>0, COUNTIFS($AU$2:$AU$200,$G25)>0, COUNTIFS($AV$2:$AV$200,$G25)>0, COUNTIFS($AW$2:$AW$200,$G25)>0, COUNTIFS($AX$2:$AX$200,$G25)>0 )), ), 3 ), "")} | F25: {=IFERROR( INDEX( _xlfn._xlws.FILTER($U$1:$AX$1, TRANSPOSE( CHOOSE({1;2;3;4;5;6;7;8;9;10;11;12;13;14;15;16;17;18;19;20;21;22;23;24;25;26;27;28;29;30}, COUNTIFS($U$2:$U$200,$G25)>0, COUNTIFS($V$2:$V$200,$G25)>0, COUNTIFS($W$2:$W$200,$G25)>0, COUNTIFS($X$2:$X$200,$G25)>0, COUNTIFS($Y$2:$Y$200,$G25)>0, COUNTIFS($Z$2:$Z$200,$G25)>0, COUNTIFS($AA$2:$AA$200,$G25)>0, COUNTIFS($AB$2:$AB$200,$G25)>0, COUNTIFS($AC$2:$AC$200,$G25)>0, COUNTIFS($AD$2:$AD$200,$G25)>0, COUNTIFS($AE$2:$AE$200,$G25)>0, COUNTIFS($AF$2:$AF$200,$G25)>0, COUNTIFS($AG$2:$AG$200,$G25)>0, COUNTIFS($AH$2:$AH$200,$G25)>0, COUNTIFS($AI$2:$AI$200,$G25)>0, COUNTIFS($AJ$2:$AJ$200,$G25)>0, COUNTIFS($AK$2:$AK$200,$G25)>0, COUNTIFS($AL$2:$AL$200,$G25)>0, COUNTIFS($AM$2:$AM$200,$G25)>0, COUNTIFS($AN$2:$AN$200,$G25)>0, COUNTIFS($AO$2:$AO$200,$G25)>0, COUNTIFS($AP$2:$AP$200,$G25)>0, COUNTIFS($AQ$2:$AQ$200,$G25)>0, COUNTIFS($AR$2:$AR$200,$G25)>0, COUNTIFS($AS$2:$AS$200,$G25)>0, COUNTIFS($AT$2:$AT$200,$G25)>0, COUNTIFS($AU$2:$AU$200,$G25)>0, COUNTIFS($AV$2:$AV$200,$G25)>0, COUNTIFS($AW$2:$AW$200,$G25)>0, COUNTIFS($AX$2:$AX$200,$G25)>0 )), ), 4 ), "")} | G25: Badgermole | I25: Kresh | J25: =Kresh!G2 -> 9 | K25: Não | L25: Não | M25: Sim | N25: Sim | O25: Sim | P25: Voltron | Q25: Dano Direto | R25: Controle Voltron | S25: =IF(J25<6,"5",IF(J25<11,"4",IF(J25<16,"3",IF(J25<31,"2","1")))) -> 4 | V25: The Shire | W25: Spectator Seating | X25: Song of Freyalise | AX25: Lotus Field | BB25: Mines of Moria | BC25: Lae'zel, Vlaakith's Champion | BD25: Reliquary Tower | BE25: Summon: Leviathan | BP25: Lotus Field | BS25: Farseek | BT25: Harvest Season | BU25: Portal to Phyrexia | BV25: Lightning Greaves | BW25: Valfenda | BX25: The Masamune | BZ25: Lotus Field | CB25: Clifftop Retreat | CC25: Espada de Luz e Sombra | CD25: Ojer Pakpatiq, Era Profunda | CE25: Homeward Path | CG25: Burnt Offering | CH25: Emergency Eject | CJ25: Badgermole
A26: =IFERROR(INDEX($S$3:$S$200, MATCH($C26, $I$3:$I$200, 0)), "") -> 4 | B26: =COUNTIF(U:AX,G26) -> 1 | C26: =IFERROR( INDEX($U$1:$AX$1, MATCH(TRUE, CHOOSE({1;2;3;4;5;6;7;8;9;10;11;12;13;14;15;16;17;18;19;20;21;22;23;24;25;26;27;28;29;30;31;32}, COUNTIFS($U$2:$U$200,$G26)>0, COUNTIFS($V$2:$V$200,$G26)>0, COUNTIFS($W$2:$W$200,$G26)>0, COUNTIFS($X$2:$X$200,$G26)>0, COUNTIFS($Y$2:$Y$200,$G26)>0, COUNTIFS($Z$2:$Z$200,$G26)>0, COUNTIFS($AA$2:$AA$200,$G26)>0, COUNTIFS($AB$2:$AB$200,$G26)>0, COUNTIFS($AC$2:$AC$200,$G26)>0, COUNTIFS($AD$2:$AD$200,$G26)>0, COUNTIFS($AE$2:$AE$200,$G26)>0, COUNTIFS($AF$2:$AF$200,$G26)>0, COUNTIFS($AG$2:$AG$200,$G26)>0, COUNTIFS($AH$2:$AH$200,$G26)>0, COUNTIFS($AI$2:$AI$200,$G26)>0, COUNTIFS($AJ$2:$AJ$200,$G26)>0, COUNTIFS($AK$2:$AK$200,$G26)>0, COUNTIFS($AL$2:$AL$200,$G26)>0, COUNTIFS($AM$2:$AM$200,$G26)>0, COUNTIFS($AN$2:$AN$200,$G26)>0, COUNTIFS($AO$2:$AO$200,$G26)>0, COUNTIFS($AP$2:$AP$200,$G26)>0, COUNTIFS($AQ$2:$AQ$200,$G26)>0, COUNTIFS($AR$2:$AR$200,$G26)>0, COUNTIFS($AS$2:$AS$200,$G26)>0, COUNTIFS($AT$2:$AT$200,$G26)>0, COUNTIFS($AU$2:$AU$200,$G26)>0, COUNTIFS($AV$2:$AV$200,$G26)>0, COUNTIFS($AW$2:$AW$200,$G26)>0, COUNTIFS($AX$2:$AX$200,$G26)>0 ), 0) ), "") -> Rielle | D26: {=IFERROR( INDEX( _xlfn._xlws.FILTER($U$1:$AX$1, TRANSPOSE( CHOOSE({1;2;3;4;5;6;7;8;9;10;11;12;13;14;15;16;17;18;19;20;21;22;23;24;25;26;27;28;29;30}, COUNTIFS($U$2:$U$200,$G26)>0, COUNTIFS($V$2:$V$200,$G26)>0, COUNTIFS($W$2:$W$200,$G26)>0, COUNTIFS($X$2:$X$200,$G26)>0, COUNTIFS($Y$2:$Y$200,$G26)>0, COUNTIFS($Z$2:$Z$200,$G26)>0, COUNTIFS($AA$2:$AA$200,$G26)>0, COUNTIFS($AB$2:$AB$200,$G26)>0, COUNTIFS($AC$2:$AC$200,$G26)>0, COUNTIFS($AD$2:$AD$200,$G26)>0, COUNTIFS($AE$2:$AE$200,$G26)>0, COUNTIFS($AF$2:$AF$200,$G26)>0, COUNTIFS($AG$2:$AG$200,$G26)>0, COUNTIFS($AH$2:$AH$200,$G26)>0, COUNTIFS($AI$2:$AI$200,$G26)>0, COUNTIFS($AJ$2:$AJ$200,$G26)>0, COUNTIFS($AK$2:$AK$200,$G26)>0, COUNTIFS($AL$2:$AL$200,$G26)>0, COUNTIFS($AM$2:$AM$200,$G26)>0, COUNTIFS($AN$2:$AN$200,$G26)>0, COUNTIFS($AO$2:$AO$200,$G26)>0, COUNTIFS($AP$2:$AP$200,$G26)>0, COUNTIFS($AQ$2:$AQ$200,$G26)>0, COUNTIFS($AR$2:$AR$200,$G26)>0, COUNTIFS($AS$2:$AS$200,$G26)>0, COUNTIFS($AT$2:$AT$200,$G26)>0, COUNTIFS($AU$2:$AU$200,$G26)>0, COUNTIFS($AV$2:$AV$200,$G26)>0, COUNTIFS($AW$2:$AW$200,$G26)>0, COUNTIFS($AX$2:$AX$200,$G26)>0 )), ), 2 ), "")} | E26: {=IFERROR( INDEX( _xlfn._xlws.FILTER($U$1:$AX$1, TRANSPOSE( CHOOSE({1;2;3;4;5;6;7;8;9;10;11;12;13;14;15;16;17;18;19;20;21;22;23;24;25;26;27;28;29;30}, COUNTIFS($U$2:$U$200,$G26)>0, COUNTIFS($V$2:$V$200,$G26)>0, COUNTIFS($W$2:$W$200,$G26)>0, COUNTIFS($X$2:$X$200,$G26)>0, COUNTIFS($Y$2:$Y$200,$G26)>0, COUNTIFS($Z$2:$Z$200,$G26)>0, COUNTIFS($AA$2:$AA$200,$G26)>0, COUNTIFS($AB$2:$AB$200,$G26)>0, COUNTIFS($AC$2:$AC$200,$G26)>0, COUNTIFS($AD$2:$AD$200,$G26)>0, COUNTIFS($AE$2:$AE$200,$G26)>0, COUNTIFS($AF$2:$AF$200,$G26)>0, COUNTIFS($AG$2:$AG$200,$G26)>0, COUNTIFS($AH$2:$AH$200,$G26)>0, COUNTIFS($AI$2:$AI$200,$G26)>0, COUNTIFS($AJ$2:$AJ$200,$G26)>0, COUNTIFS($AK$2:$AK$200,$G26)>0, COUNTIFS($AL$2:$AL$200,$G26)>0, COUNTIFS($AM$2:$AM$200,$G26)>0, COUNTIFS($AN$2:$AN$200,$G26)>0, COUNTIFS($AO$2:$AO$200,$G26)>0, COUNTIFS($AP$2:$AP$200,$G26)>0, COUNTIFS($AQ$2:$AQ$200,$G26)>0, COUNTIFS($AR$2:$AR$200,$G26)>0, COUNTIFS($AS$2:$AS$200,$G26)>0, COUNTIFS($AT$2:$AT$200,$G26)>0, COUNTIFS($AU$2:$AU$200,$G26)>0, COUNTIFS($AV$2:$AV$200,$G26)>0, COUNTIFS($AW$2:$AW$200,$G26)>0, COUNTIFS($AX$2:$AX$200,$G26)>0 )), ), 3 ), "")} | F26: {=IFERROR( INDEX( _xlfn._xlws.FILTER($U$1:$AX$1, TRANSPOSE( CHOOSE({1;2;3;4;5;6;7;8;9;10;11;12;13;14;15;16;17;18;19;20;21;22;23;24;25;26;27;28;29;30}, COUNTIFS($U$2:$U$200,$G26)>0, COUNTIFS($V$2:$V$200,$G26)>0, COUNTIFS($W$2:$W$200,$G26)>0, COUNTIFS($X$2:$X$200,$G26)>0, COUNTIFS($Y$2:$Y$200,$G26)>0, COUNTIFS($Z$2:$Z$200,$G26)>0, COUNTIFS($AA$2:$AA$200,$G26)>0, COUNTIFS($AB$2:$AB$200,$G26)>0, COUNTIFS($AC$2:$AC$200,$G26)>0, COUNTIFS($AD$2:$AD$200,$G26)>0, COUNTIFS($AE$2:$AE$200,$G26)>0, COUNTIFS($AF$2:$AF$200,$G26)>0, COUNTIFS($AG$2:$AG$200,$G26)>0, COUNTIFS($AH$2:$AH$200,$G26)>0, COUNTIFS($AI$2:$AI$200,$G26)>0, COUNTIFS($AJ$2:$AJ$200,$G26)>0, COUNTIFS($AK$2:$AK$200,$G26)>0, COUNTIFS($AL$2:$AL$200,$G26)>0, COUNTIFS($AM$2:$AM$200,$G26)>0, COUNTIFS($AN$2:$AN$200,$G26)>0, COUNTIFS($AO$2:$AO$200,$G26)>0, COUNTIFS($AP$2:$AP$200,$G26)>0, COUNTIFS($AQ$2:$AQ$200,$G26)>0, COUNTIFS($AR$2:$AR$200,$G26)>0, COUNTIFS($AS$2:$AS$200,$G26)>0, COUNTIFS($AT$2:$AT$200,$G26)>0, COUNTIFS($AU$2:$AU$200,$G26)>0, COUNTIFS($AV$2:$AV$200,$G26)>0, COUNTIFS($AW$2:$AW$200,$G26)>0, COUNTIFS($AX$2:$AX$200,$G26)>0 )), ), 4 ), "")} | G26: Baral, Chief of Compliance | I26: Breya | J26: =Breya!G2 -> 3 | K26: Sim | L26: Sim | M26: Sim | N26: Sim | O26: Não | P26: Combate | Q26: Dano Direto | R26: Thopteros e Blink | S26: =IF(J26<6,"5",IF(J26<11,"4",IF(J26<16,"3",IF(J26<31,"2","1")))) -> 5 | V26: Time of Need | W26: The Water Crystal | X26: Sphere Grid | AX26: Monumental Henge | BB26: Prosperous Partnership | BC26: Lightning Greaves | BD26: Rogue's Passage | BE26: Surgespanner | BP26: Monumental Henge | BS26: Forest | BT26: Havengul Laboratory | BU26: Rings of Brighthearth | BV26: Lolth, Rainha Aranha | BW26: Watery Grave | BX26: Três Passos à Frente | BZ26: Monumental Henge | CB26: Counterspell | CC26: Espada de Verdade e Justiça | CD26: Overgrown Tomb | CE26: Illustrious Wanderglyph | CG26: Call to the Kindred | CH26: Emrakul, um Novo Mundo | CJ26: Baral, Chief of Compliance
A27: =IFERROR(INDEX($S$3:$S$200, MATCH($C27, $I$3:$I$200, 0)), "") -> 4 | B27: =COUNTIF(U:AX,G27) -> 1 | C27: =IFERROR( INDEX($U$1:$AX$1, MATCH(TRUE, CHOOSE({1;2;3;4;5;6;7;8;9;10;11;12;13;14;15;16;17;18;19;20;21;22;23;24;25;26;27;28;29;30;31;32}, COUNTIFS($U$2:$U$200,$G27)>0, COUNTIFS($V$2:$V$200,$G27)>0, COUNTIFS($W$2:$W$200,$G27)>0, COUNTIFS($X$2:$X$200,$G27)>0, COUNTIFS($Y$2:$Y$200,$G27)>0, COUNTIFS($Z$2:$Z$200,$G27)>0, COUNTIFS($AA$2:$AA$200,$G27)>0, COUNTIFS($AB$2:$AB$200,$G27)>0, COUNTIFS($AC$2:$AC$200,$G27)>0, COUNTIFS($AD$2:$AD$200,$G27)>0, COUNTIFS($AE$2:$AE$200,$G27)>0, COUNTIFS($AF$2:$AF$200,$G27)>0, COUNTIFS($AG$2:$AG$200,$G27)>0, COUNTIFS($AH$2:$AH$200,$G27)>0, COUNTIFS($AI$2:$AI$200,$G27)>0, COUNTIFS($AJ$2:$AJ$200,$G27)>0, COUNTIFS($AK$2:$AK$200,$G27)>0, COUNTIFS($AL$2:$AL$200,$G27)>0, COUNTIFS($AM$2:$AM$200,$G27)>0, COUNTIFS($AN$2:$AN$200,$G27)>0, COUNTIFS($AO$2:$AO$200,$G27)>0, COUNTIFS($AP$2:$AP$200,$G27)>0, COUNTIFS($AQ$2:$AQ$200,$G27)>0, COUNTIFS($AR$2:$AR$200,$G27)>0, COUNTIFS($AS$2:$AS$200,$G27)>0, COUNTIFS($AT$2:$AT$200,$G27)>0, COUNTIFS($AU$2:$AU$200,$G27)>0, COUNTIFS($AV$2:$AV$200,$G27)>0, COUNTIFS($AW$2:$AW$200,$G27)>0, COUNTIFS($AX$2:$AX$200,$G27)>0 ), 0) ), "") -> VialIshai | D27: {=IFERROR( INDEX( _xlfn._xlws.FILTER($U$1:$AX$1, TRANSPOSE( CHOOSE({1;2;3;4;5;6;7;8;9;10;11;12;13;14;15;16;17;18;19;20;21;22;23;24;25;26;27;28;29;30}, COUNTIFS($U$2:$U$200,$G27)>0, COUNTIFS($V$2:$V$200,$G27)>0, COUNTIFS($W$2:$W$200,$G27)>0, COUNTIFS($X$2:$X$200,$G27)>0, COUNTIFS($Y$2:$Y$200,$G27)>0, COUNTIFS($Z$2:$Z$200,$G27)>0, COUNTIFS($AA$2:$AA$200,$G27)>0, COUNTIFS($AB$2:$AB$200,$G27)>0, COUNTIFS($AC$2:$AC$200,$G27)>0, COUNTIFS($AD$2:$AD$200,$G27)>0, COUNTIFS($AE$2:$AE$200,$G27)>0, COUNTIFS($AF$2:$AF$200,$G27)>0, COUNTIFS($AG$2:$AG$200,$G27)>0, COUNTIFS($AH$2:$AH$200,$G27)>0, COUNTIFS($AI$2:$AI$200,$G27)>0, COUNTIFS($AJ$2:$AJ$200,$G27)>0, COUNTIFS($AK$2:$AK$200,$G27)>0, COUNTIFS($AL$2:$AL$200,$G27)>0, COUNTIFS($AM$2:$AM$200,$G27)>0, COUNTIFS($AN$2:$AN$200,$G27)>0, COUNTIFS($AO$2:$AO$200,$G27)>0, COUNTIFS($AP$2:$AP$200,$G27)>0, COUNTIFS($AQ$2:$AQ$200,$G27)>0, COUNTIFS($AR$2:$AR$200,$G27)>0, COUNTIFS($AS$2:$AS$200,$G27)>0, COUNTIFS($AT$2:$AT$200,$G27)>0, COUNTIFS($AU$2:$AU$200,$G27)>0, COUNTIFS($AV$2:$AV$200,$G27)>0, COUNTIFS($AW$2:$AW$200,$G27)>0, COUNTIFS($AX$2:$AX$200,$G27)>0 )), ), 2 ), "")} | E27: {=IFERROR( INDEX( _xlfn._xlws.FILTER($U$1:$AX$1, TRANSPOSE( CHOOSE({1;2;3;4;5;6;7;8;9;10;11;12;13;14;15;16;17;18;19;20;21;22;23;24;25;26;27;28;29;30}, COUNTIFS($U$2:$U$200,$G27)>0, COUNTIFS($V$2:$V$200,$G27)>0, COUNTIFS($W$2:$W$200,$G27)>0, COUNTIFS($X$2:$X$200,$G27)>0, COUNTIFS($Y$2:$Y$200,$G27)>0, COUNTIFS($Z$2:$Z$200,$G27)>0, COUNTIFS($AA$2:$AA$200,$G27)>0, COUNTIFS($AB$2:$AB$200,$G27)>0, COUNTIFS($AC$2:$AC$200,$G27)>0, COUNTIFS($AD$2:$AD$200,$G27)>0, COUNTIFS($AE$2:$AE$200,$G27)>0, COUNTIFS($AF$2:$AF$200,$G27)>0, COUNTIFS($AG$2:$AG$200,$G27)>0, COUNTIFS($AH$2:$AH$200,$G27)>0, COUNTIFS($AI$2:$AI$200,$G27)>0, COUNTIFS($AJ$2:$AJ$200,$G27)>0, COUNTIFS($AK$2:$AK$200,$G27)>0, COUNTIFS($AL$2:$AL$200,$G27)>0, COUNTIFS($AM$2:$AM$200,$G27)>0, COUNTIFS($AN$2:$AN$200,$G27)>0, COUNTIFS($AO$2:$AO$200,$G27)>0, COUNTIFS($AP$2:$AP$200,$G27)>0, COUNTIFS($AQ$2:$AQ$200,$G27)>0, COUNTIFS($AR$2:$AR$200,$G27)>0, COUNTIFS($AS$2:$AS$200,$G27)>0, COUNTIFS($AT$2:$AT$200,$G27)>0, COUNTIFS($AU$2:$AU$200,$G27)>0, COUNTIFS($AV$2:$AV$200,$G27)>0, COUNTIFS($AW$2:$AW$200,$G27)>0, COUNTIFS($AX$2:$AX$200,$G27)>0 )), ), 3 ), "")} | F27: {=IFERROR( INDEX( _xlfn._xlws.FILTER($U$1:$AX$1, TRANSPOSE( CHOOSE({1;2;3;4;5;6;7;8;9;10;11;12;13;14;15;16;17;18;19;20;21;22;23;24;25;26;27;28;29;30}, COUNTIFS($U$2:$U$200,$G27)>0, COUNTIFS($V$2:$V$200,$G27)>0, COUNTIFS($W$2:$W$200,$G27)>0, COUNTIFS($X$2:$X$200,$G27)>0, COUNTIFS($Y$2:$Y$200,$G27)>0, COUNTIFS($Z$2:$Z$200,$G27)>0, COUNTIFS($AA$2:$AA$200,$G27)>0, COUNTIFS($AB$2:$AB$200,$G27)>0, COUNTIFS($AC$2:$AC$200,$G27)>0, COUNTIFS($AD$2:$AD$200,$G27)>0, COUNTIFS($AE$2:$AE$200,$G27)>0, COUNTIFS($AF$2:$AF$200,$G27)>0, COUNTIFS($AG$2:$AG$200,$G27)>0, COUNTIFS($AH$2:$AH$200,$G27)>0, COUNTIFS($AI$2:$AI$200,$G27)>0, COUNTIFS($AJ$2:$AJ$200,$G27)>0, COUNTIFS($AK$2:$AK$200,$G27)>0, COUNTIFS($AL$2:$AL$200,$G27)>0, COUNTIFS($AM$2:$AM$200,$G27)>0, COUNTIFS($AN$2:$AN$200,$G27)>0, COUNTIFS($AO$2:$AO$200,$G27)>0, COUNTIFS($AP$2:$AP$200,$G27)>0, COUNTIFS($AQ$2:$AQ$200,$G27)>0, COUNTIFS($AR$2:$AR$200,$G27)>0, COUNTIFS($AS$2:$AS$200,$G27)>0, COUNTIFS($AT$2:$AT$200,$G27)>0, COUNTIFS($AU$2:$AU$200,$G27)>0, COUNTIFS($AV$2:$AV$200,$G27)>0, COUNTIFS($AW$2:$AW$200,$G27)>0, COUNTIFS($AX$2:$AX$200,$G27)>0 )), ), 4 ), "")} | G27: Batwing Brume | I27: OWA | J27: =OWA!G2 -> 6 | K27: Sim | L27: Não | M27: Não | N27: Sim | O27: Sim | P27: Combate | Q27: Dano Direto | R27: Tokens e Reanimate | S27: =IF(J27<6,"5",IF(J27<11,"4",IF(J27<16,"3",IF(J27<31,"2","1")))) -> 4 | V27: Virtue of Loyalty // Ardenvale Fealty | W27: Training Center | X27: Summon: Fenrir | AX27: Mystic Forge | BB27: Purphoros, God of the Forge | BC27: Llanowar Wastes | BD27: Sevinne's Reclamation | BE27: Teferi's Ageless Insight | BP27: Mystic Forge | BS27: Full Throttle | BT27: Herald of Secret Streams | BU27: Ripples of Undeath | BV27: Louisoix's Sacrifice | BW27: Zagoth Triome | BX27: Unstoppable Plan | BZ27: Mystic Forge | CB27: Cyber Conversion | CC27: Extinguisher Battleship | CD27: Pain for All | CE27: Inkmoth Nexus | CG27: Cankerbloom | CH27: Esper Sentinel | CJ27: Batwing Brume
A28: =IFERROR(INDEX($S$3:$S$200, MATCH($C28, $I$3:$I$200, 0)), "") -> 2 | B28: =COUNTIF(U:AX,G28) -> 2 | C28: =IFERROR( INDEX($U$1:$AX$1, MATCH(TRUE, CHOOSE({1;2;3;4;5;6;7;8;9;10;11;12;13;14;15;16;17;18;19;20;21;22;23;24;25;26;27;28;29;30;31;32}, COUNTIFS($U$2:$U$200,$G28)>0, COUNTIFS($V$2:$V$200,$G28)>0, COUNTIFS($W$2:$W$200,$G28)>0, COUNTIFS($X$2:$X$200,$G28)>0, COUNTIFS($Y$2:$Y$200,$G28)>0, COUNTIFS($Z$2:$Z$200,$G28)>0, COUNTIFS($AA$2:$AA$200,$G28)>0, COUNTIFS($AB$2:$AB$200,$G28)>0, COUNTIFS($AC$2:$AC$200,$G28)>0, COUNTIFS($AD$2:$AD$200,$G28)>0, COUNTIFS($AE$2:$AE$200,$G28)>0, COUNTIFS($AF$2:$AF$200,$G28)>0, COUNTIFS($AG$2:$AG$200,$G28)>0, COUNTIFS($AH$2:$AH$200,$G28)>0, COUNTIFS($AI$2:$AI$200,$G28)>0, COUNTIFS($AJ$2:$AJ$200,$G28)>0, COUNTIFS($AK$2:$AK$200,$G28)>0, COUNTIFS($AL$2:$AL$200,$G28)>0, COUNTIFS($AM$2:$AM$200,$G28)>0, COUNTIFS($AN$2:$AN$200,$G28)>0, COUNTIFS($AO$2:$AO$200,$G28)>0, COUNTIFS($AP$2:$AP$200,$G28)>0, COUNTIFS($AQ$2:$AQ$200,$G28)>0, COUNTIFS($AR$2:$AR$200,$G28)>0, COUNTIFS($AS$2:$AS$200,$G28)>0, COUNTIFS($AT$2:$AT$200,$G28)>0, COUNTIFS($AU$2:$AU$200,$G28)>0, COUNTIFS($AV$2:$AV$200,$G28)>0, COUNTIFS($AW$2:$AW$200,$G28)>0, COUNTIFS($AX$2:$AX$200,$G28)>0 ), 0) ), "") -> Kumena | D28: {=IFERROR( INDEX( _xlfn._xlws.FILTER($U$1:$AX$1, TRANSPOSE( CHOOSE({1;2;3;4;5;6;7;8;9;10;11;12;13;14;15;16;17;18;19;20;21;22;23;24;25;26;27;28;29;30}, COUNTIFS($U$2:$U$200,$G28)>0, COUNTIFS($V$2:$V$200,$G28)>0, COUNTIFS($W$2:$W$200,$G28)>0, COUNTIFS($X$2:$X$200,$G28)>0, COUNTIFS($Y$2:$Y$200,$G28)>0, COUNTIFS($Z$2:$Z$200,$G28)>0, COUNTIFS($AA$2:$AA$200,$G28)>0, COUNTIFS($AB$2:$AB$200,$G28)>0, COUNTIFS($AC$2:$AC$200,$G28)>0, COUNTIFS($AD$2:$AD$200,$G28)>0, COUNTIFS($AE$2:$AE$200,$G28)>0, COUNTIFS($AF$2:$AF$200,$G28)>0, COUNTIFS($AG$2:$AG$200,$G28)>0, COUNTIFS($AH$2:$AH$200,$G28)>0, COUNTIFS($AI$2:$AI$200,$G28)>0, COUNTIFS($AJ$2:$AJ$200,$G28)>0, COUNTIFS($AK$2:$AK$200,$G28)>0, COUNTIFS($AL$2:$AL$200,$G28)>0, COUNTIFS($AM$2:$AM$200,$G28)>0, COUNTIFS($AN$2:$AN$200,$G28)>0, COUNTIFS($AO$2:$AO$200,$G28)>0, COUNTIFS($AP$2:$AP$200,$G28)>0, COUNTIFS($AQ$2:$AQ$200,$G28)>0, COUNTIFS($AR$2:$AR$200,$G28)>0, COUNTIFS($AS$2:$AS$200,$G28)>0, COUNTIFS($AT$2:$AT$200,$G28)>0, COUNTIFS($AU$2:$AU$200,$G28)>0, COUNTIFS($AV$2:$AV$200,$G28)>0, COUNTIFS($AW$2:$AW$200,$G28)>0, COUNTIFS($AX$2:$AX$200,$G28)>0 )), ), 2 ), "")} -> Modular | E28: {=IFERROR( INDEX( _xlfn._xlws.FILTER($U$1:$AX$1, TRANSPOSE( CHOOSE({1;2;3;4;5;6;7;8;9;10;11;12;13;14;15;16;17;18;19;20;21;22;23;24;25;26;27;28;29;30}, COUNTIFS($U$2:$U$200,$G28)>0, COUNTIFS($V$2:$V$200,$G28)>0, COUNTIFS($W$2:$W$200,$G28)>0, COUNTIFS($X$2:$X$200,$G28)>0, COUNTIFS($Y$2:$Y$200,$G28)>0, COUNTIFS($Z$2:$Z$200,$G28)>0, COUNTIFS($AA$2:$AA$200,$G28)>0, COUNTIFS($AB$2:$AB$200,$G28)>0, COUNTIFS($AC$2:$AC$200,$G28)>0, COUNTIFS($AD$2:$AD$200,$G28)>0, COUNTIFS($AE$2:$AE$200,$G28)>0, COUNTIFS($AF$2:$AF$200,$G28)>0, COUNTIFS($AG$2:$AG$200,$G28)>0, COUNTIFS($AH$2:$AH$200,$G28)>0, COUNTIFS($AI$2:$AI$200,$G28)>0, COUNTIFS($AJ$2:$AJ$200,$G28)>0, COUNTIFS($AK$2:$AK$200,$G28)>0, COUNTIFS($AL$2:$AL$200,$G28)>0, COUNTIFS($AM$2:$AM$200,$G28)>0, COUNTIFS($AN$2:$AN$200,$G28)>0, COUNTIFS($AO$2:$AO$200,$G28)>0, COUNTIFS($AP$2:$AP$200,$G28)>0, COUNTIFS($AQ$2:$AQ$200,$G28)>0, COUNTIFS($AR$2:$AR$200,$G28)>0, COUNTIFS($AS$2:$AS$200,$G28)>0, COUNTIFS($AT$2:$AT$200,$G28)>0, COUNTIFS($AU$2:$AU$200,$G28)>0, COUNTIFS($AV$2:$AV$200,$G28)>0, COUNTIFS($AW$2:$AW$200,$G28)>0, COUNTIFS($AX$2:$AX$200,$G28)>0 )), ), 3 ), "")} | F28: {=IFERROR( INDEX( _xlfn._xlws.FILTER($U$1:$AX$1, TRANSPOSE( CHOOSE({1;2;3;4;5;6;7;8;9;10;11;12;13;14;15;16;17;18;19;20;21;22;23;24;25;26;27;28;29;30}, COUNTIFS($U$2:$U$200,$G28)>0, COUNTIFS($V$2:$V$200,$G28)>0, COUNTIFS($W$2:$W$200,$G28)>0, COUNTIFS($X$2:$X$200,$G28)>0, COUNTIFS($Y$2:$Y$200,$G28)>0, COUNTIFS($Z$2:$Z$200,$G28)>0, COUNTIFS($AA$2:$AA$200,$G28)>0, COUNTIFS($AB$2:$AB$200,$G28)>0, COUNTIFS($AC$2:$AC$200,$G28)>0, COUNTIFS($AD$2:$AD$200,$G28)>0, COUNTIFS($AE$2:$AE$200,$G28)>0, COUNTIFS($AF$2:$AF$200,$G28)>0, COUNTIFS($AG$2:$AG$200,$G28)>0, COUNTIFS($AH$2:$AH$200,$G28)>0, COUNTIFS($AI$2:$AI$200,$G28)>0, COUNTIFS($AJ$2:$AJ$200,$G28)>0, COUNTIFS($AK$2:$AK$200,$G28)>0, COUNTIFS($AL$2:$AL$200,$G28)>0, COUNTIFS($AM$2:$AM$200,$G28)>0, COUNTIFS($AN$2:$AN$200,$G28)>0, COUNTIFS($AO$2:$AO$200,$G28)>0, COUNTIFS($AP$2:$AP$200,$G28)>0, COUNTIFS($AQ$2:$AQ$200,$G28)>0, COUNTIFS($AR$2:$AR$200,$G28)>0, COUNTIFS($AS$2:$AS$200,$G28)>0, COUNTIFS($AT$2:$AT$200,$G28)>0, COUNTIFS($AU$2:$AU$200,$G28)>0, COUNTIFS($AV$2:$AV$200,$G28)>0, COUNTIFS($AW$2:$AW$200,$G28)>0, COUNTIFS($AX$2:$AX$200,$G28)>0 )), ), 4 ), "")} | G28: Beast Within | I28: Alela | J28: =Alela!G2 -> 5 | K28: Sim | L28: Sim | M28: Não | N28: Sim | O28: Não | P28: Combate | Q28: Voltron | R28: Stax e Tokens | S28: =IF(J28<6,"5",IF(J28<11,"4",IF(J28<16,"3",IF(J28<31,"2","1")))) -> 5 | V28: Warleader's Call | W28: Windcrag Siege | X28: Summon: Ixion | AX28: Rustvale Bridge | BB28: Reliquary Tower | BC28: Maddening Cacophony | BD28: Sol Ring | BE28: Thousand-Year Elixir | BP28: Rustvale Bridge | BS28: Gavony Township | BT28: Hierofante de Elenda | BU28: Rise of the Eldrazi | BV28: Mistbind Clique | BZ28: Rustvale Bridge | CB28: Deeproot Historian | CC28: Faerie Slumber Party | CD28: Planetary Annihilation | CE28: Karn's Bastion | CG28: Canopy Vista | CH28: Evendo Brushrazer | CJ28: Beast Within
A29: =IFERROR(INDEX($S$3:$S$200, MATCH($C29, $I$3:$I$200, 0)), "") -> 2 | B29: =COUNTIF(U:AX,G29) -> 4 | C29: =IFERROR( INDEX($U$1:$AX$1, MATCH(TRUE, CHOOSE({1;2;3;4;5;6;7;8;9;10;11;12;13;14;15;16;17;18;19;20;21;22;23;24;25;26;27;28;29;30;31;32}, COUNTIFS($U$2:$U$200,$G29)>0, COUNTIFS($V$2:$V$200,$G29)>0, COUNTIFS($W$2:$W$200,$G29)>0, COUNTIFS($X$2:$X$200,$G29)>0, COUNTIFS($Y$2:$Y$200,$G29)>0, COUNTIFS($Z$2:$Z$200,$G29)>0, COUNTIFS($AA$2:$AA$200,$G29)>0, COUNTIFS($AB$2:$AB$200,$G29)>0, COUNTIFS($AC$2:$AC$200,$G29)>0, COUNTIFS($AD$2:$AD$200,$G29)>0, COUNTIFS($AE$2:$AE$200,$G29)>0, COUNTIFS($AF$2:$AF$200,$G29)>0, COUNTIFS($AG$2:$AG$200,$G29)>0, COUNTIFS($AH$2:$AH$200,$G29)>0, COUNTIFS($AI$2:$AI$200,$G29)>0, COUNTIFS($AJ$2:$AJ$200,$G29)>0, COUNTIFS($AK$2:$AK$200,$G29)>0, COUNTIFS($AL$2:$AL$200,$G29)>0, COUNTIFS($AM$2:$AM$200,$G29)>0, COUNTIFS($AN$2:$AN$200,$G29)>0, COUNTIFS($AO$2:$AO$200,$G29)>0, COUNTIFS($AP$2:$AP$200,$G29)>0, COUNTIFS($AQ$2:$AQ$200,$G29)>0, COUNTIFS($AR$2:$AR$200,$G29)>0, COUNTIFS($AS$2:$AS$200,$G29)>0, COUNTIFS($AT$2:$AT$200,$G29)>0, COUNTIFS($AU$2:$AU$200,$G29)>0, COUNTIFS($AV$2:$AV$200,$G29)>0, COUNTIFS($AW$2:$AW$200,$G29)>0, COUNTIFS($AX$2:$AX$200,$G29)>0 ), 0) ), "") -> Piratas | D29: {=IFERROR( INDEX( _xlfn._xlws.FILTER($U$1:$AX$1, TRANSPOSE( CHOOSE({1;2;3;4;5;6;7;8;9;10;11;12;13;14;15;16;17;18;19;20;21;22;23;24;25;26;27;28;29;30}, COUNTIFS($U$2:$U$200,$G29)>0, COUNTIFS($V$2:$V$200,$G29)>0, COUNTIFS($W$2:$W$200,$G29)>0, COUNTIFS($X$2:$X$200,$G29)>0, COUNTIFS($Y$2:$Y$200,$G29)>0, COUNTIFS($Z$2:$Z$200,$G29)>0, COUNTIFS($AA$2:$AA$200,$G29)>0, COUNTIFS($AB$2:$AB$200,$G29)>0, COUNTIFS($AC$2:$AC$200,$G29)>0, COUNTIFS($AD$2:$AD$200,$G29)>0, COUNTIFS($AE$2:$AE$200,$G29)>0, COUNTIFS($AF$2:$AF$200,$G29)>0, COUNTIFS($AG$2:$AG$200,$G29)>0, COUNTIFS($AH$2:$AH$200,$G29)>0, COUNTIFS($AI$2:$AI$200,$G29)>0, COUNTIFS($AJ$2:$AJ$200,$G29)>0, COUNTIFS($AK$2:$AK$200,$G29)>0, COUNTIFS($AL$2:$AL$200,$G29)>0, COUNTIFS($AM$2:$AM$200,$G29)>0, COUNTIFS($AN$2:$AN$200,$G29)>0, COUNTIFS($AO$2:$AO$200,$G29)>0, COUNTIFS($AP$2:$AP$200,$G29)>0, COUNTIFS($AQ$2:$AQ$200,$G29)>0, COUNTIFS($AR$2:$AR$200,$G29)>0, COUNTIFS($AS$2:$AS$200,$G29)>0, COUNTIFS($AT$2:$AT$200,$G29)>0, COUNTIFS($AU$2:$AU$200,$G29)>0, COUNTIFS($AV$2:$AV$200,$G29)>0, COUNTIFS($AW$2:$AW$200,$G29)>0, COUNTIFS($AX$2:$AX$200,$G29)>0 )), ), 2 ), "")} -> Carlos | E29: {=IFERROR( INDEX( _xlfn._xlws.FILTER($U$1:$AX$1, TRANSPOSE( CHOOSE({1;2;3;4;5;6;7;8;9;10;11;12;13;14;15;16;17;18;19;20;21;22;23;24;25;26;27;28;29;30}, COUNTIFS($U$2:$U$200,$G29)>0, COUNTIFS($V$2:$V$200,$G29)>0, COUNTIFS($W$2:$W$200,$G29)>0, COUNTIFS($X$2:$X$200,$G29)>0, COUNTIFS($Y$2:$Y$200,$G29)>0, COUNTIFS($Z$2:$Z$200,$G29)>0, COUNTIFS($AA$2:$AA$200,$G29)>0, COUNTIFS($AB$2:$AB$200,$G29)>0, COUNTIFS($AC$2:$AC$200,$G29)>0, COUNTIFS($AD$2:$AD$200,$G29)>0, COUNTIFS($AE$2:$AE$200,$G29)>0, COUNTIFS($AF$2:$AF$200,$G29)>0, COUNTIFS($AG$2:$AG$200,$G29)>0, COUNTIFS($AH$2:$AH$200,$G29)>0, COUNTIFS($AI$2:$AI$200,$G29)>0, COUNTIFS($AJ$2:$AJ$200,$G29)>0, COUNTIFS($AK$2:$AK$200,$G29)>0, COUNTIFS($AL$2:$AL$200,$G29)>0, COUNTIFS($AM$2:$AM$200,$G29)>0, COUNTIFS($AN$2:$AN$200,$G29)>0, COUNTIFS($AO$2:$AO$200,$G29)>0, COUNTIFS($AP$2:$AP$200,$G29)>0, COUNTIFS($AQ$2:$AQ$200,$G29)>0, COUNTIFS($AR$2:$AR$200,$G29)>0, COUNTIFS($AS$2:$AS$200,$G29)>0, COUNTIFS($AT$2:$AT$200,$G29)>0, COUNTIFS($AU$2:$AU$200,$G29)>0, COUNTIFS($AV$2:$AV$200,$G29)>0, COUNTIFS($AW$2:$AW$200,$G29)>0, COUNTIFS($AX$2:$AX$200,$G29)>0 )), ), 3 ), "")} -> Rani | F29: {=IFERROR( INDEX( _xlfn._xlws.FILTER($U$1:$AX$1, TRANSPOSE( CHOOSE({1;2;3;4;5;6;7;8;9;10;11;12;13;14;15;16;17;18;19;20;21;22;23;24;25;26;27;28;29;30}, COUNTIFS($U$2:$U$200,$G29)>0, COUNTIFS($V$2:$V$200,$G29)>0, COUNTIFS($W$2:$W$200,$G29)>0, COUNTIFS($X$2:$X$200,$G29)>0, COUNTIFS($Y$2:$Y$200,$G29)>0, COUNTIFS($Z$2:$Z$200,$G29)>0, COUNTIFS($AA$2:$AA$200,$G29)>0, COUNTIFS($AB$2:$AB$200,$G29)>0, COUNTIFS($AC$2:$AC$200,$G29)>0, COUNTIFS($AD$2:$AD$200,$G29)>0, COUNTIFS($AE$2:$AE$200,$G29)>0, COUNTIFS($AF$2:$AF$200,$G29)>0, COUNTIFS($AG$2:$AG$200,$G29)>0, COUNTIFS($AH$2:$AH$200,$G29)>0, COUNTIFS($AI$2:$AI$200,$G29)>0, COUNTIFS($AJ$2:$AJ$200,$G29)>0, COUNTIFS($AK$2:$AK$200,$G29)>0, COUNTIFS($AL$2:$AL$200,$G29)>0, COUNTIFS($AM$2:$AM$200,$G29)>0, COUNTIFS($AN$2:$AN$200,$G29)>0, COUNTIFS($AO$2:$AO$200,$G29)>0, COUNTIFS($AP$2:$AP$200,$G29)>0, COUNTIFS($AQ$2:$AQ$200,$G29)>0, COUNTIFS($AR$2:$AR$200,$G29)>0, COUNTIFS($AS$2:$AS$200,$G29)>0, COUNTIFS($AT$2:$AT$200,$G29)>0, COUNTIFS($AU$2:$AU$200,$G29)>0, COUNTIFS($AV$2:$AV$200,$G29)>0, COUNTIFS($AW$2:$AW$200,$G29)>0, COUNTIFS($AX$2:$AX$200,$G29)>0 )), ), 4 ), "")} -> Inalla | G29: Bojuka Bog | I29: Arcades | J29: =Arcades!G2 -> 2 | K29: Sim | L29: Sim | M29: Não | N29: Não | O29: Sim | P29: Combate | Q29: Voltron | R29: Bater sem Apanhar | S29: =IF(J29<6,"5",IF(J29<11,"4",IF(J29<16,"3",IF(J29<31,"2","1")))) -> 5 | W29: World at War | X29: Tayam, Luminous Enigma | AX29: Sacred Ground | BB29: Rogue's Passage | BC29: Maester Seymour | BD29: Sulfur Falls | BE29: Three Visits | BP29: Sacred Ground | BS29: Generous Gift | BT29: Horizon Explorer | BU29: Rotating Fireplace | BV29: Molten Echoes | BZ29: Sacred Ground | CB29: Dever Além da Morte | CC29: Firion, Wild Rose Warrior | CD29: Raffine's Tower | CE29: Kodama of the West Tree | CG29: Castle Ardenvale | CH29: Evendo, Waking Haven | CJ29: Bojuka Bog
