Workbook

Sheet COMPRAS
A1: Total: | B1: =C2+C8+C13+C18+C23+C28+C32+C34+C38+C50 -> 0 | E1: Deck | F1: =A2 -> Marcelo | G1: =B3 -> Overrun | H1: =B4 -> Base | I1: =B5 -> 0 | J1: =B6 -> Liga | L1: =A8 -> Interessantes | M1: =B9 -> Valor | N1: =B10 -> Liga | O1: =B11 -> Loja 1 | Q1: =A13 -> Player 3 | R1: =B14 -> Rayearth | S1: =B15 -> Mineral | T1: =B16 -> CardTutor | V1: =A18 -> Player 4 | W1: =B19 -> Rayearth | X1: =B20 -> Mineral | Y1: =B21 -> CardTutor | AA1: =A23 -> Player 5 | AB1: =B24 -> Rayearth | AC1: =B25 -> Mineral | AD1: =B26 -> CardTutor | AF1: =A28 -> Player 6 | AG1: =B29 -> Rayearth | AH1: =B30 -> Mineral | AI1: =B31 -> CardTutor
A2: Marcelo | B2: Total Lojas: | C2: =SUM(C3:C6) -> 0
A3: =COUNTA(F2:F216) -> 0 | B3: Overrun | C3: =SUM(G:G) -> 0
B4: Base | C4: =SUM(H:H) -> 0
C5: =SUM(I:I) -> 0
B6: Liga | C6: =SUM(J:J) -> 0
A8: Interessantes | B8: Total Lojas: | C8: =SUM(C9:C11) -> 0
A9: =COUNTA(L2:L173) -> 0 | B9: Valor | C9: =SUM(M:M) -> 0
B10: Liga | C10: =SUM(N:N) -> 0
B11: Loja 1 | C11: =SUM(O:O) -> 0
A13: Player 3 | B13: Total Lojas: | C13: =SUM(C14:C16) -> 0
A14: =COUNTA(Q2:Q173) -> 0 | B14: Rayearth | C14: =SUM(R:R) -> 0
B15: Mineral | C15: =SUM(S:S) -> 0
B16: CardTutor | C16: =SUM(T:T) -> 0
A18: Player 4 | B18: Total Lojas: | C18: =SUM(C19:C21) -> 0
A19: =COUNTA(V2:V173) -> 0 | B19: Rayearth | C19: =SUM(W1:W9973) -> 0
B20: Mineral | C20: =SUM(X1:X9978) -> 0
B21: CardTutor | C21: =SUM(Y:Y) -> 0
A23: Player 5 | B23: Total Lojas: | C23: =SUM(C24:C26) -> 0
A24: =COUNTA(V7:V178) -> 0 | B24: Rayearth | C24: =SUM(AB:AB) -> 0
B25: Mineral | C25: =SUM(AC:AC) -> 0
B26: CardTutor | C26: =SUM(AD:AD) -> 0
A28: Player 6 | B28: Total Lojas: | C28: =SUM(C29:C31) -> 0
A29: =COUNTA(V11:V183) -> 0 | B29: Rayearth | C29: =SUM(AG:AG) -> 0
B30: Mineral | C30: =SUM(AH:AH) -> 0
B31: CardTutor | C31: =SUM(AI:AI) -> 0

Sheet STATS
A1: Dia | B1: Player 1 | C1: Deck 1 | D1: Player 2 | E1: Deck 2 | F1: Player 3 | G1: Deck 3 | H1: Player 4 | I1: Deck 4 | J1: Vitória | M1: Deck | N1: Partidas | O1: Winrate | Q1: Player | R1: Partidas | S1: Winrate
A2: 45587 | B2: Marcelo | C2: Elfos | D2: Vivian | E2: Zimone | F2: Renato | G2: Raffine | H2: Dexter | I2: Kaalia | J2: Marcelo | K2: Elfos | M2: Akiri | N2: =COUNTIF(C:C,M2)+COUNTIF(E:E,M2)+COUNTIF(G:G,M2)+COUNTIF(I:I,M2) -> 2 | O2: =IF(N2>=10,(COUNTIF(K:K,M2)/N2),"Insuficiente") -> Insuficiente | Q2: Marcelo | R2: =COUNTIF(B:B,Q2)+COUNTIF(D:D,Q2)+COUNTIF(F:F,Q2)+COUNTIF(H:H,Q2) -> 11 | S2: =IF(R2>=10, (COUNTIF(J:J,Q2)/R2), "Insuficiente") -> 0.36363636
A3: 45594 | B3: Marcelo | C3: Breya | D3: Vivian | E3: Zimone | F3: Renato | G3: Raffine | H3: Dexter | I3: Tovolar | J3: Vivian | K3: Zimone | M3: Arcades | N3: =COUNTIF(C:C,M3)+COUNTIF(E:E,M3)+COUNTIF(G:G,M3)+COUNTIF(I:I,M3) -> 1 | O3: =IF(N3>=10,(COUNTIF(K:K,M3)/N3),"Insuficiente") -> Insuficiente | Q3: Vivian | R3: =COUNTIF(B:B,Q3)+COUNTIF(D:D,Q3)+COUNTIF(F:F,Q3)+COUNTIF(H:H,Q3) -> 11 | S3: =IF(R3>=10, (COUNTIF(J:J,Q3)/R3), "Insuficiente") -> 0.27272727
A4: 45594 | B4: Marcelo | C4: Trakiri | D4: Vivian | E4: Zimone | F4: Renato | G4: Raffine | H4: Hamster | I4: Muzzio | J4: Marcelo | K4: Trakiri | M4: Baylen | N4: =COUNTIF(C:C,M4)+COUNTIF(E:E,M4)+COUNTIF(G:G,M4)+COUNTIF(I:I,M4) -> 1 | O4: =IF(N4>=10,(COUNTIF(K:K,M4)/N4),"Insuficiente") -> Insuficiente | Q4: Renato | R4: =COUNTIF(B:B,Q4)+COUNTIF(D:D,Q4)+COUNTIF(F:F,Q4)+COUNTIF(H:H,Q4) -> 6 | S4: =IF(R4>=10, (COUNTIF(J:J,Q4)/R4), "Insuficiente") -> Insuficiente
A5: 45594 | B5: Marcelo | C5: Akiri | D5: Vivian | E5: Zimone | F5: Renato | G5: Baylen | H5: Hamster | I5: Kumena | J5: Marcelo | K5: Akiri | M5: Breya | N5: =COUNTIF(C:C,M5)+COUNTIF(E:E,M5)+COUNTIF(G:G,M5)+COUNTIF(I:I,M5) -> 1 | O5: =IF(N5>=10,(COUNTIF(K:K,M5)/N5),"Insuficiente") -> Insuficiente | Q5: Dexter | R5: =COUNTIF(B:B,Q5)+COUNTIF(D:D,Q5)+COUNTIF(F:F,Q5)+COUNTIF(H:H,Q5) -> 5 | S5: =IF(R5>=10, (COUNTIF(J:J,Q5)/R5), "Insuficiente") -> Insuficiente
A6: 45597 | B6: Marcelo | C6: Inalla | D6: Vivian | E6: Zimone | F6: Renato | G6: Raffine | H6: João | I6: Winota | J6: João | K6: Winota | M6: Elfos | N6: =COUNTIF(C:C,M6)+COUNTIF(E:E,M6)+COUNTIF(G:G,M6)+COUNTIF(I:I,M6) -> 1 | O6: =IF(N6>=10,(COUNTIF(K:K,M6)/N6),"Insuficiente") -> Insuficiente | Q6: Hamster | R6: =COUNTIF(B:B,Q6)+COUNTIF(D:D,Q6)+COUNTIF(F:F,Q6)+COUNTIF(H:H,Q6) -> 2 | S6: =IF(R6>=10, (COUNTIF(J:J,Q6)/R6), "Insuficiente") -> Insuficiente
A7: 45597 | B7: Marcelo | C7: Yuriko | D7: Vivian | E7: Zimone | F7: Renato | G7: Raffine | H7: João | I7: Winota | J7: Vivian | K7: Zimone | M7: FF Counters | N7: =COUNTIF(C:C,M7)+COUNTIF(E:E,M7)+COUNTIF(G:G,M7)+COUNTIF(I:I,M7) -> 2 | O7: =IF(N7>=10,(COUNTIF(K:K,M7)/N7),"Insuficiente") -> Insuficiente | Q7: Talita | R7: =COUNTIF(B:B,Q7)+COUNTIF(D:D,Q7)+COUNTIF(F:F,Q7)+COUNTIF(H:H,Q7) -> 3 | S7: =IF(R7>=10, (COUNTIF(J:J,Q7)/R7), "Insuficiente") -> Insuficiente
A8: 45599 | B8: Marcelo | C8: Narset | D8: Vivian | E8: Arcades | F8: Dexter | G8: Who Villains | H8: Talita | I8: Who Time | J8: Vivian | K8: Arcades | M8: Hashaton | N8: =COUNTIF(C:C,M8)+COUNTIF(E:E,M8)+COUNTIF(G:G,M8)+COUNTIF(I:I,M8) -> 1 | O8: =IF(N8>=10,(COUNTIF(K:K,M8)/N8),"Insuficiente") -> Insuficiente | Q8: João | R8: =COUNTIF(B:B,Q8)+COUNTIF(D:D,Q8)+COUNTIF(F:F,Q8)+COUNTIF(H:H,Q8) -> 4 | S8: =IF(R8>=10, (COUNTIF(J:J,Q8)/R8), "Insuficiente") -> Insuficiente
A9: 45599 | B9: Marcelo | C9: Thantis | D9: Vivian | E9: Akiri | F9: Dexter | G9: Who Villains | H9: Talita | I9: Ladinos | J9: Talita | K9: Ladinos | M9: Inalla | N9: =COUNTIF(C:C,M9)+COUNTIF(E:E,M9)+COUNTIF(G:G,M9)+COUNTIF(I:I,M9) -> 1 | O9: =IF(N9>=10,(COUNTIF(K:K,M9)/N9),"Insuficiente") -> Insuficiente | Q9: Philips | R9: =COUNTIF(B:B,Q9)+COUNTIF(D:D,Q9)+COUNTIF(F:F,Q9)+COUNTIF(H:H,Q9) -> 2 | S9: =IF(R9>=10, (COUNTIF(J:J,Q9)/R9), "Insuficiente") -> Insuficiente
A10: 45835 | B10: Marcelo | C10: Zedruu | D10: Vivian | E10: Jhoira | F10: Dexter | G10: Who Villains | H10: Talita | I10: Who Time | J10: Dexter | K10: Who Villains | M10: Jhoira | N10: =COUNTIF(C:C,M10)+COUNTIF(E:E,M10)+COUNTIF(G:G,M10)+COUNTIF(I:I,M10) -> 1 | O10: =IF(N10>=10,(COUNTIF(K:K,M10)/N10),"Insuficiente") -> Insuficiente
A11: 45864 | B11: Marcelo | C11: Muzzio | D11: Vivian | E11: Zimone | F11: Philips | G11: Hashaton | H11: João | I11: FF Counters | J11: Marcelo | K11: Muzzio | M11: Kaalia | N11: =COUNTIF(C:C,M11)+COUNTIF(E:E,M11)+COUNTIF(G:G,M11)+COUNTIF(I:I,M11) -> 2 | O11: =IF(N11>=10,(COUNTIF(K:K,M11)/N11),"Insuficiente") -> Insuficiente
A12: 45864 | B12: Marcelo | C12: Sisay | D12: Vivian | E12: Zimone | F12: Philips | G12: Kaalia | H12: João | I12: FF Counters | J12: Philips | K12: Kaalia | M12: Kumena | N12: =COUNTIF(C:C,M12)+COUNTIF(E:E,M12)+COUNTIF(G:G,M12)+COUNTIF(I:I,M12) -> 1 | O12: =IF(N12>=10,(COUNTIF(K:K,M12)/N12),"Insuficiente") -> Insuficiente
M13: Ladinos | N13: =COUNTIF(C:C,M13)+COUNTIF(E:E,M13)+COUNTIF(G:G,M13)+COUNTIF(I:I,M13) -> 1 | O13: =IF(N13>=10,(COUNTIF(K:K,M13)/N13),"Insuficiente") -> Insuficiente
M14: Muzzio | N14: =COUNTIF(C:C,M14)+COUNTIF(E:E,M14)+COUNTIF(G:G,M14)+COUNTIF(I:I,M14) -> 2 | O14: =IF(N14>=10,(COUNTIF(K:K,M14)/N14),"Insuficiente") -> Insuficiente
M15: Narset | N15: =COUNTIF(C:C,M15)+COUNTIF(E:E,M15)+COUNTIF(G:G,M15)+COUNTIF(I:I,M15) -> 1 | O15: =IF(N15>=10,(COUNTIF(K:K,M15)/N15),"Insuficiente") -> Insuficiente
M16: Raffine | N16: =COUNTIF(C:C,M16)+COUNTIF(E:E,M16)+COUNTIF(G:G,M16)+COUNTIF(I:I,M16) -> 5 | O16: =IF(N16>=10,(COUNTIF(K:K,M16)/N16),"Insuficiente") -> Insuficiente
M17: Sisay | N17: =COUNTIF(C:C,M17)+COUNTIF(E:E,M17)+COUNTIF(G:G,M17)+COUNTIF(I:I,M17) -> 1 | O17: =IF(N17>=10,(COUNTIF(K:K,M17)/N17),"Insuficiente") -> Insuficiente
M18: Thantis | N18: =COUNTIF(C:C,M18)+COUNTIF(E:E,M18)+COUNTIF(G:G,M18)+COUNTIF(I:I,M18) -> 1 | O18: =IF(N18>=10,(COUNTIF(K:K,M18)/N18),"Insuficiente") -> Insuficiente
M19: Tovolar | N19: =COUNTIF(C:C,M19)+COUNTIF(E:E,M19)+COUNTIF(G:G,M19)+COUNTIF(I:I,M19) -> 1 | O19: =IF(N19>=10,(COUNTIF(K:K,M19)/N19),"Insuficiente") -> Insuficiente
M20: Trakiri | N20: =COUNTIF(C:C,M20)+COUNTIF(E:E,M20)+COUNTIF(G:G,M20)+COUNTIF(I:I,M20) -> 1 | O20: =IF(N20>=10,(COUNTIF(K:K,M20)/N20),"Insuficiente") -> Insuficiente
M21: Who Time | N21: =COUNTIF(C:C,M21)+COUNTIF(E:E,M21)+COUNTIF(G:G,M21)+COUNTIF(I:I,M21) -> 2 | O21: =IF(N21>=10,(COUNTIF(K:K,M21)/N21),"Insuficiente") -> Insuficiente
M22: Who Villains | N22: =COUNTIF(C:C,M22)+COUNTIF(E:E,M22)+COUNTIF(G:G,M22)+COUNTIF(I:I,M22) -> 3 | O22: =IF(N22>=10,(COUNTIF(K:K,M22)/N22),"Insuficiente") -> Insuficiente
M23: Winota | N23: =COUNTIF(C:C,M23)+COUNTIF(E:E,M23)+COUNTIF(G:G,M23)+COUNTIF(I:I,M23) -> 2 | O23: =IF(N23>=10,(COUNTIF(K:K,M23)/N23),"Insuficiente") -> Insuficiente
M24: Yuriko | N24: =COUNTIF(C:C,M24)+COUNTIF(E:E,M24)+COUNTIF(G:G,M24)+COUNTIF(I:I,M24) -> 1 | O24: =IF(N24>=10,(COUNTIF(K:K,M24)/N24),"Insuficiente") -> Insuficiente
... M26: Zimone | N26: =COUNTIF(C:C,M26)+COUNTIF(E:E,M26)+COUNTIF(G:G,M26)+COUNTIF(I:I,M26) -> 8 | O26: =IF(N26>=10,(COUNTIF(K:K,M26)/N26),"Insuficiente") -> Insuficiente

Sheet WATCH
A1: Carta | B1: Identidade | G1: Tipo | H1: Categoria | I1: Classe | J1: Formato | K1: Deck
A5: Weathered Runestone | B5: Não | C5: Não | D5: Não | E5: Não | F5: Não | G5: Artefato | H5: Stax | I5: Cemitério
A6: Shivan Harvest | B6: Não | C6: Não | D6: Sim | E6: Não | F6: Não | G6: Encantamento | H6: Remoção | I6: Terreno
A7: Scouting Trek | B7: Não | C7: Não | D7: Não | E7: Não | F7: Sim | G7: Feitiço | H7: Combo | I7: Tutor
A8: Overabundance | B8: Não | C8: Não | D8: Sim | E8: Não | F8: Não | G8: Encantamento | H8: Ramp | I8: Punição
A9: Spreading Plague | B9: Não | C9: Não | D9: Não | E9: Sim | F9: Não | G9: Encantamento | H9: Stax | I9: Criaturas
A10: Explosão da Alma | B10: Não | C10: Não | D10: Sim | E10: Não | F10: Não | G10: Instantânea | H10: Wincon | I10: Dano
A11: Obsidian Fireheat | B11: Não | C11: Não | D11: Sim | E11: Não | F11: Não | G11: Criatura | H11: Wincon | I11: Punição
A12: Interdict | B12: Não | C12: Sim | D12: Não | E12: Não | F12: Não | G12: Instantânea | H12: Anule | I12: Habilidade
A13: Mogg Infestation | B13: Não | C13: Não | D13: Sim | E13: Não | F13: Não | G13: Feitiço | H13: Remoção | I13: Criaturas
A14: Life // Death | B14: Não | C14: Não | D14: Não | E14: Não | F14: Sim | G14: Feitiço | H14: Combo | I14: Terreno
A15: Debt of Loyalt | B15: Sim | C15: Não | D15: Não | E15: Não | F15: Não | G15: Instantânea | H15: Remoção | I15: Roubo
A16: Yavimaya Hollow | B16: Não | C16: Não | D16: Não | E16: Não | F16: Sim | G16: Terreno | H16: Proteção | I16: Criaturas
... A26: Preferência de Cineréia | B26: Não | C26: Não | D26: Sim | E26: Não | F26: Não | G26: Encantamento | H26: Stax | I26: Criaturas
A27: Temporada da Multiplicação
A28: Final de Devastação
A29: The Great Henge
A30: Intervenção Heróica
A31: Presa-Gélida de Ohran
A32: Altar de Ashnod
A33: Ornato de Esmeralda
A34: Ornato de Azeviche
A35: Ornato de Rubi
A36: Ornato de Safira
A37: Ornato de Pérola
A38: Espada da Animista
... A74: Arachnogenesis

Sheet RESUMO
A1: Prioridade | B1: Faltam | C1: Deck 1 | D1: Deck 2 | E1: Deck 3 | F1: Deck 4 | G1: Carta | J1: Alterações | K1: Cores | P1: =COUNTA(I3:I5000) & " Decks" -> 30 Decks | U1: Piratas | V1: Baylen | W1: Narset | X1: Tayam | Y1: Carlos | Z1: Rani | AA1: Kumena | AB1: Zimone | AC1: JhoiraB | AD1: Gritrog | AE1: Muzzio | AF1: VialIshai | AG1: Yuriko | AH1: Inalla | AI1: Akiri | AJ1: Sisay | AK1: Thrakiri | AL1: Elfos | AM1: Jhoira | AN1: Fractius | AO1: Rielle | AP1: Oona | AQ1: Kresh | AR1: Breya | AS1: OWA | AT1: Alela | AU1: Arcades | AV1: Zedruu | AW1: Exaltado | AX1: Modular
A2: =IFERROR(INDEX($S$3:$S$200, MATCH($C2, $I$3:$I$200, 0)), "") -> 3 | B2: =COUNTIF(U:AX,G2) -> 1 | C2: =IFERROR( INDEX($U$1:$AX$1, MATCH(TRUE, CHOOSE({1;2;3;4;5;6;7;8;9;10;11;12;13;14;15;16;17;18;19;20;21;22;23;24;25;26;27;28;29;30;31;32}, COUNTIFS($U$2:$U$200,$G2)>0, COUNTIFS($V$2:$V$200,$G2)>0, COUNTIFS($W$2:$W$200,$G2)>0, COUNTIFS($X$2:$X$200,$G2)>0, COUNTIFS($Y$2:$Y$200,$G2)>0, COUNTIFS($Z$2:$Z$200,$G2)>0, COUNTIFS($AA$2:$AA$200,$G2)>0, COUNTIFS($AB$2:$AB$200,$G2)>0, COUNTIFS($AC$2:$AC$200,$G2)>0, COUNTIFS($AD$2:$AD$200,$G2)>0, COUNTIFS($AE$2:$AE$200,$G2)>0, COUNTIFS($AF$2:$AF$200,$G2)>0, COUNTIFS($AG$2:$AG$200,$G2)>0, COUNTIFS($AH$2:$AH$200,$G2)>0, COUNTIFS($AI$2:$AI$200,$G2)>0, COUNTIFS($AJ$2:$AJ$200,$G2)>0, COUNTIFS($AK$2:$AK$200,$G2)>0, COUNTIFS($AL$2:$AL$200,$G2)>0, COUNTIFS($AM$2:$AM$200,$G2)>0, COUNTIFS($AN$2:$AN$200,$G2)>0, COUNTIFS($AO$2:$AO$200,$G2)>0, COUNTIFS($AP$2:$AP$200,$G2)>0, COUNTIFS($AQ$2:$AQ$200,$G2)>0, COUNTIFS($AR$2:$AR$200,$G2)>0, COUNTIFS($AS$2:$AS$200,$G2)>0, COUNTIFS($AT$2:$AT$200,$G2)>0, COUNTIFS($AU$2:$AU$200,$G2)>0, COUNTIFS($AV$2:$AV$200,$G2)>0, COUNTIFS($AW$2:$AW$200,$G2)>0, COUNTIFS($AX$2:$AX$200,$G2)>0 ), 0) ), "") -> Muzzio | D2: {=IFERROR( INDEX( _xlfn._xlws.FILTER($U$1:$AX$1, TRANSPOSE( CHOOSE({1;2;3;4;5;6;7;8;9;10;11;12;13;14;15;16;17;18;19;20;21;22;23;24;25;26;27;28;29;30}, COUNTIFS($U$2:$U$200,$G2)>0, COUNTIFS($V$2:$V$200,$G2)>0, COUNTIFS($W$2:$W$200,$G2)>0, COUNTIFS($X$2:$X$200,$G2)>0, COUNTIFS($Y$2:$Y$200,$G2)>0, COUNTIFS($Z$2:$Z$200,$G2)>0, COUNTIFS($AA$2:$AA$200,$G2)>0, COUNTIFS($AB$2:$AB$200,$G2)>0, COUNTIFS($AC$2:$AC$200,$G2)>0, COUNTIFS($AD$2:$AD$200,$G2)>0, COUNTIFS($AE$2:$AE$200,$G2)>0, COUNTIFS($AF$2:$AF$200,$G2)>0, COUNTIFS($AG$2:$AG$200,$G2)>0, COUNTIFS($AH$2:$AH$200,$G2)>0, COUNTIFS($AI$2:$AI$200,$G2)>0, COUNTIFS($AJ$2:$AJ$200,$G2)>0, COUNTIFS($AK$2:$AK$200,$G2)>0, COUNTIFS($AL$2:$AL$200,$G2)>0, COUNTIFS($AM$2:$AM$200,$G2)>0, COUNTIFS($AN$2:$AN$200,$G2)>0, COUNTIFS($AO$2:$AO$200,$G2)>0, COUNTIFS($AP$2:$AP$200,$G2)>0, COUNTIFS($AQ$2:$AQ$200,$G2)>0, COUNTIFS($AR$2:$AR$200,$G2)>0, COUNTIFS($AS$2:$AS$200,$G2)>0, COUNTIFS($AT$2:$AT$200,$G2)>0, COUNTIFS($AU$2:$AU$200,$G2)>0, COUNTIFS($AV$2:$AV$200,$G2)>0, COUNTIFS($AW$2:$AW$200,$G2)>0, COUNTIFS($AX$2:$AX$200,$G2)>0 )), ), 2 ), "")} | E2: {=IFERROR( INDEX( _xlfn._xlws.FILTER($U$1:$AX$1, TRANSPOSE( CHOOSE({1;2;3;4;5;6;7;8;9;10;11;12;13;14;15;16;17;18;19;20;21;22;23;24;25;26;27;28;29;30}, COUNTIFS($U$2:$U$200,$G2)>0, COUNTIFS($V$2:$V$200,$G2)>0, COUNTIFS($W$2:$W$200,$G2)>0, COUNTIFS($X$2:$X$200,$G2)>0, COUNTIFS($Y$2:$Y$200,$G2)>0, COUNTIFS($Z$2:$Z$200,$G2)>0, COUNTIFS($AA$2:$AA$200,$G2)>0, COUNTIFS($AB$2:$AB$200,$G2)>0, COUNTIFS($AC$2:$AC$200,$G2)>0, COUNTIFS($AD$2:$AD$200,$G2)>0, COUNTIFS($AE$2:$AE$200,$G2)>0, COUNTIFS($AF$2:$AF$200,$G2)>0, COUNTIFS($AG$2:$AG$200,$G2)>0, COUNTIFS($AH$2:$AH$200,$G2)>0, COUNTIFS($AI$2:$AI$200,$G2)>0, COUNTIFS($AJ$2:$AJ$200,$G2)>0, COUNTIFS($AK$2:$AK$200,$G2)>0, COUNTIFS($AL$2:$AL$200,$G2)>0, COUNTIFS($AM$2:$AM$200,$G2)>0, COUNTIFS($AN$2:$AN$200,$G2)>0, COUNTIFS($AO$2:$AO$200,$G2)>0, COUNTIFS($AP$2:$AP$200,$G2)>0, COUNTIFS($AQ$2:$AQ$200,$G2)>0, COUNTIFS($AR$2:$AR$200,$G2)>0, COUNTIFS($AS$2:$AS$200,$G2)>0, COUNTIFS($AT$2:$AT$200,$G2)>0, COUNTIFS($AU$2:$AU$200,$G2)>0, COUNTIFS($AV$2:$AV$200,$G2)>0, COUNTIFS($AW$2:$AW$200,$G2)>0, COUNTIFS($AX$2:$AX$200,$G2)>0 )), ), 3 ), "")} | F2: {=IFERROR( INDEX( _xlfn._xlws.FILTER($U$1:$AX$1, TRANSPOSE( CHOOSE({1;2;3;4;5;6;7;8;9;10;11;12;13;14;15;16;17;18;19;20;21;22;23;24;25;26;27;28;29;30}, COUNTIFS($U$2:$U$200,$G2)>0, COUNTIFS($V$2:$V$200,$G2)>0, COUNTIFS($W$2:$W$200,$G2)>0, COUNTIFS($X$2:$X$200,$G2)>0, COUNTIFS($Y$2:$Y$200,$G2)>0, COUNTIFS($Z$2:$Z$200,$G2)>0, COUNTIFS($AA$2:$AA$200,$G2)>0, COUNTIFS($AB$2:$AB$200,$G2)>0, COUNTIFS($AC$2:$AC$200,$G2)>0, COUNTIFS($AD$2:$AD$200,$G2)>0, COUNTIFS($AE$2:$AE$200,$G2)>0, COUNTIFS($AF$2:$AF$200,$G2)>0, COUNTIFS($AG$2:$AG$200,$G2)>0, COUNTIFS($AH$2:$AH$200,$G2)>0, COUNTIFS($AI$2:$AI$200,$G2)>0, COUNTIFS($AJ$2:$AJ$200,$G2)>0, COUNTIFS($AK$2:$AK$200,$G2)>0, COUNTIFS($AL$2:$AL$200,$G2)>0, COUNTIFS($AM$2:$AM$200,$G2)>0, COUNTIFS($AN$2:$AN$200,$G2)>0, COUNTIFS($AO$2:$AO$200,$G2)>0, COUNTIFS($AP$2:$AP$200,$G2)>0, COUNTIFS($AQ$2:$AQ$200,$G2)>0, COUNTIFS($AR$2:$AR$200,$G2)>0, COUNTIFS($AS$2:$AS$200,$G2)>0, COUNTIFS($AT$2:$AT$200,$G2)>0, COUNTIFS($AU$2:$AU$200,$G2)>0, COUNTIFS($AV$2:$AV$200,$G2)>0, COUNTIFS($AW$2:$AW$200,$G2)>0, COUNTIFS($AX$2:$AX$200,$G2)>0 )), ), 4 ), "")} | G2: {=IF(COUNTA(_xlfn.ANCHORARRAY($BT$2))+COUNTA(_xlfn.ANCHORARRAY($BO$2))=0,"",_xlfn._xlws.SORT(_xlfn.UNIQUE(IF(ROW(INDIRECT("1:"&(COUNTA(_xlfn.ANCHORARRAY($BT$2))+COUNTA(_xlfn.ANCHORARRAY($BO$2)))))<=COUNTA(_xlfn.ANCHORARRAY($BT$2)),INDEX(_xlfn.ANCHORARRAY($BT$2),ROW(INDIRECT("1:"&(COUNTA(_xlfn.ANCHORARRAY($BT$2))+COUNTA(_xlfn.ANCHORARRAY($BO$2)))))),INDEX(_xlfn.ANCHORARRAY($BO$2),ROW(INDIRECT("1:"&(COUNTA(_xlfn.ANCHORARRAY($BT$2))+COUNTA(_xlfn.ANCHORARRAY($BO$2)))))-COUNTA(_xlfn.ANCHORARRAY($BT$2))))),1,1))} -> A Joia do Enigma | I2: Total | J2: =SUM(J3:J30) -> 357 | K2: =COUNTIF(K3:K5000,"Sim") -> 16 | L2: =COUNTIF(L3:L5000,"Sim") -> 22 | M2: =COUNTIF(M3:M5000,"Sim") -> 17 | N2: =COUNTIF(N3:N5000,"Sim") -> 17 | O2: =COUNTIF(O3:O5000,"Sim") -> 14 | P2: Wincon | Q2: Sub Plan | R2: Descrição | S2: Prioridade | U2: {=IF(COUNTA(_xlfn._xlws.FILTER(Piratas!C3:C200,(Piratas!B3:B200<>Piratas!C3:C200)*(Piratas!C3:C200<>"")))=0,"",_xlfn._xlws.SORT(_xlfn._xlws.FILTER(Piratas!C3:C200,(Piratas!B3:B200<>Piratas!C3:C200)*(Piratas!C3:C200<>"")),1,1))} -> Back in Town | V2: {=IF(COUNTA(_xlfn._xlws.FILTER(Baylen!C3:C200,(Baylen!B3:B200<>Baylen!C3:C200)*(Baylen!C3:C200<>"")))=0,"",_xlfn._xlws.SORT(_xlfn._xlws.FILTER(Baylen!C3:C200,(Baylen!B3:B200<>Baylen!C3:C200)*(Baylen!C3:C200<>"")),1,1))} -> Artifact Mutation | W2: {=IF(COUNTA(_xlfn._xlws.FILTER(Narset!C3:C200,(Narset!B3:B200<>Narset!C3:C200)*(Narset!C3:C200<>"")))=0,"",_xlfn._xlws.SORT(_xlfn._xlws.FILTER(Narset!C3:C200,(Narset!B3:B200<>Narset!C3:C200)*(Narset!C3:C200<>"")),1,1))} -> Adarkar Wastes | X2: {=IF(COUNTA(_xlfn._xlws.FILTER(Tayam!C3:C200,(Tayam!B3:B200<>Tayam!C3:C200)*(Tayam!C3:C200<>"")))=0,"",_xlfn._xlws.SORT(_xlfn._xlws.FILTER(Tayam!C3:C200,(Tayam!B3:B200<>Tayam!C3:C200)*(Tayam!C3:C200<>"")),1,1))} -> Ardbert, Warrior of Darkness | Y2: {=IF(COUNTA(_xlfn._xlws.FILTER(Carlos!C3:C200,(Carlos!B3:B200<>Carlos!C3:C200)*(Carlos!C3:C200<>"")))=0,"",_xlfn._xlws.SORT(_xlfn._xlws.FILTER(Carlos!C3:C200,(Carlos!B3:B200<>Carlos!C3:C200)*(Carlos!C3:C200<>"")),1,1))} -> Ascensão do Avernus | Z2: {=IF(COUNTA(_xlfn._xlws.FILTER(Rani!C3:C200,(Rani!B3:B200<>Rani!C3:C200)*(Rani!C3:C200<>"")))=0,"",_xlfn._xlws.SORT(_xlfn._xlws.FILTER(Rani!C3:C200,(Rani!B3:B200<>Rani!C3:C200)*(Rani!C3:C200<>"")),1,1))} -> Access Tunnel | AA2: {=IF(COUNTA(_xlfn._xlws.FILTER(Kumena!C3:C200,(Kumena!B3:B200<>Kumena!C3:C200)*(Kumena!C3:C200<>"")))=0,"",_xlfn._xlws.SORT(_xlfn._xlws.FILTER(Kumena!C3:C200,(Kumena!B3:B200<>Kumena!C3:C200)*(Kumena!C3:C200<>"")),1,1))} -> Beast Within | AB2: {=IF(COUNTA(_xlfn._xlws.FILTER(Zimone!C3:C200,(Zimone!B3:B200<>Zimone!C3:C200)*(Zimone!C3:C200<>"")))=0,"",_xlfn._xlws.SORT(_xlfn._xlws.FILTER(Zimone!C3:C200,(Zimone!B3:B200<>Zimone!C3:C200)*(Zimone!C3:C200<>"")),1,1))} -> Ancient Greenwarden | AC2: {=IF(COUNTA(_xlfn._xlws.FILTER(JhoiraB!C3:C200,(JhoiraB!B3:B200<>JhoiraB!C3:C200)*(JhoiraB!C3:C200<>"")))=0,"",_xlfn._xlws.SORT(_xlfn._xlws.FILTER(JhoiraB!C3:C200,(JhoiraB!B3:B200<>JhoiraB!C3:C200)*(JhoiraB!C3:C200<>"")),1,1))} -> Emrakul, um Novo Mundo | AD2: {=IF(COUNTA(_xlfn._xlws.FILTER(Gitrog!C3:C200,(Gitrog!B3:B200<>Gitrog!C3:C200)*(Gitrog!C3:C200<>"")))=0,"",_xlfn._xlws.SORT(_xlfn._xlws.FILTER(Gitrog!C3:C200,(Gitrog!B3:B200<>Gitrog!C3:C200)*(Gitrog!C3:C200<>"")),1,1))} -> Ancient Tomb | AE2: {=IF(COUNTA(_xlfn._xlws.FILTER(Muzzio!C3:C200,(Muzzio!B3:B200<>Muzzio!C3:C200)*(Muzzio!C3:C200<>"")))=0,"",_xlfn._xlws.SORT(_xlfn._xlws.FILTER(Muzzio!C3:C200,(Muzzio!B3:B200<>Muzzio!C3:C200)*(Muzzio!C3:C200<>"")),1,1))} -> A Joia do Enigma | AF2: {=IF(COUNTA(_xlfn._xlws.FILTER(VialIshai!C3:C200,(VialIshai!B3:B200<>VialIshai!C3:C200)*(VialIshai!C3:C200<>"")))=0,"",_xlfn._xlws.SORT(_xlfn._xlws.FILTER(VialIshai!C3:C200,(VialIshai!B3:B200<>VialIshai!C3:C200)*(VialIshai!C3:C200<>"")),1,1))} -> Amphibian Downpour | AG2: {=IF(COUNTA(_xlfn._xlws.FILTER(Yuriko!C3:C200,(Yuriko!B3:B200<>Yuriko!C3:C200)*(Yuriko!C3:C200<>"")))=0,"",_xlfn._xlws.SORT(_xlfn._xlws.FILTER(Yuriko!C3:C200,(Yuriko!B3:B200<>Yuriko!C3:C200)*(Yuriko!C3:C200<>"")),1,1))} -> Creeping Tar Pit | AH2: {=IF(COUNTA(_xlfn._xlws.FILTER(Inalla!C3:C200,(Inalla!B3:B200<>Inalla!C3:C200)*(Inalla!C3:C200<>"")))=0,"",_xlfn._xlws.SORT(_xlfn._xlws.FILTER(Inalla!C3:C200,(Inalla!B3:B200<>Inalla!C3:C200)*(Inalla!C3:C200<>"")),1,1))} -> Arcane Lighthouse | AI2: {=IF(COUNTA(_xlfn._xlws.FILTER(Akiri!C3:C200,(Akiri!B3:B200<>Akiri!C3:C200)*(Akiri!C3:C200<>"")))=0,"",_xlfn._xlws.SORT(_xlfn._xlws.FILTER(Akiri!C3:C200,(Akiri!B3:B200<>Akiri!C3:C200)*(Akiri!C3:C200<>"")),1,1))} -> Cid, Freeflier Pilot | AJ2: {=IF(COUNTA(_xlfn._xlws.FILTER(Sisay!C3:C200,(Sisay!B3:B200<>Sisay!C3:C200)*(Sisay!C3:C200<>"")))=0,"",_xlfn._xlws.SORT(_xlfn._xlws.FILTER(Sisay!C3:C200,(Sisay!B3:B200<>Sisay!C3:C200)*(Sisay!C3:C200<>"")),1,1))} -> Commodore Guff | AK2: {=IF(COUNTA(_xlfn._xlws.FILTER(Thrakiri!C3:C200,(Thrakiri!B3:B200<>Thrakiri!C3:C200)*(Thrakiri!C3:C200<>"")))=0,"",_xlfn._xlws.SORT(_xlfn._xlws.FILTER(Thrakiri!C3:C200,(Thrakiri!B3:B200<>Thrakiri!C3:C200)*(Thrakiri!C3:C200<>"")),1,1))} -> Matoya, Archon Elder | AL2: {=IF(COUNTA(_xlfn._xlws.FILTER(Elfos!C3:C200,(Elfos!B3:B200<>Elfos!C3:C200)*(Elfos!C3:C200<>"")))=0,"",_xlfn._xlws.SORT(_xlfn._xlws.FILTER(Elfos!C3:C200,(Elfos!B3:B200<>Elfos!C3:C200)*(Elfos!C3:C200<>"")),1,1))} -> Alchemist's Refuge | AM2: {=IF(COUNTA(_xlfn._xlws.FILTER(Jhoira!C3:C200,(Jhoira!B3:B200<>Jhoira!C3:C200)*(Jhoira!C3:C200<>"")))=0,"",_xlfn._xlws.SORT(_xlfn._xlws.FILTER(Jhoira!C3:C200,(Jhoira!B3:B200<>Jhoira!C3:C200)*(Jhoira!C3:C200<>"")),1,1))} -> Emrakul, um Novo Mundo | AN2: {=IF(COUNTA(_xlfn._xlws.FILTER(Fractius!C3:C200,(Fractius!B3:B200<>Fractius!C3:C200)*(Fractius!C3:C200<>"")))=0,"",_xlfn._xlws.SORT(_xlfn._xlws.FILTER(Fractius!C3:C200,(Fractius!B3:B200<>Fractius!C3:C200)*(Fractius!C3:C200<>"")),1,1))} -> Caverna das Almas | AO2: {=IF(COUNTA(_xlfn._xlws.FILTER(Rielle!C3:C200,(Rielle!B3:B200<>Rielle!C3:C200)*(Rielle!C3:C200<>"")))=0,"",_xlfn._xlws.SORT(_xlfn._xlws.FILTER(Rielle!C3:C200,(Rielle!B3:B200<>Rielle!C3:C200)*(Rielle!C3:C200<>"")),1,1))} -> Afundar em Estupor | AP2: {=IF(COUNTA(_xlfn._xlws.FILTER(Oona!C3:C200,(Oona!B3:B200<>Oona!C3:C200)*(Oona!C3:C200<>"")))=0,"",_xlfn._xlws.SORT(_xlfn._xlws.FILTER(Oona!C3:C200,(Oona!B3:B200<>Oona!C3:C200)*(Oona!C3:C200<>"")),1,1))} -> Invasion of Segovia | AQ2: {=IF(COUNTA(_xlfn._xlws.FILTER(Kresh!C3:C200,(Kresh!B3:B200<>Kresh!C3:C200)*(Kresh!C3:C200<>"")))=0,"",_xlfn._xlws.SORT(_xlfn._xlws.FILTER(Kresh!C3:C200,(Kresh!B3:B200<>Kresh!C3:C200)*(Kresh!C3:C200<>"")),1,1))} -> Bugenhagen, Wise Elder | AR2: {=IF(COUNTA(_xlfn._xlws.FILTER(Breya!C3:C200,(Breya!B3:B200<>Breya!C3:C200)*(Breya!C3:C200<>"")))=0,"",_xlfn._xlws.SORT(_xlfn._xlws.FILTER(Breya!C3:C200,(Breya!B3:B200<>Breya!C3:C200)*(Breya!C3:C200<>"")),1,1))} -> Adagia, Windswept Bastion | AS2: {=IF(COUNTA(_xlfn._xlws.FILTER(OWA!C3:C200,(OWA!B3:B200<>OWA!C3:C200)*(OWA!C3:C200<>"")))=0,"",_xlfn._xlws.SORT(_xlfn._xlws.FILTER(OWA!C3:C200,(OWA!B3:B200<>OWA!C3:C200)*(OWA!C3:C200<>"")),1,1))} -> Dollmaker's Shop // Porcelain Gallery | AT2: {=IF(COUNTA(_xlfn._xlws.FILTER(Alela!C3:C200,(Alela!B3:B200<>Alela!C3:C200)*(Alela!C3:C200<>"")))=0,"",_xlfn._xlws.SORT(_xlfn._xlws.FILTER(Alela!C3:C200,(Alela!B3:B200<>Alela!C3:C200)*(Alela!C3:C200<>"")),1,1))} -> Adagia, Windswept Bastion | AU2: {=IF(COUNTA(_xlfn._xlws.FILTER(Arcades!C3:C200,(Arcades!B3:B200<>Arcades!C3:C200)*(Arcades!C3:C200<>"")))=0,"",_xlfn._xlws.SORT(_xlfn._xlws.FILTER(Arcades!C3:C200,(Arcades!B3:B200<>Arcades!C3:C200)*(Arcades!C3:C200<>"")),1,1))} -> Alchemist's Refuge | AV2: {=IF(COUNTA(_xlfn._xlws.FILTER(Zedruu!C3:C200,(Zedruu!B3:B200<>Zedruu!C3:C200)*(Zedruu!C3:C200<>"")))=0,"",_xlfn._xlws.SORT(_xlfn._xlws.FILTER(Zedruu!C3:C200,(Zedruu!B3:B200<>Zedruu!C3:C200)*(Zedruu!C3:C200<>"")),1,1))} -> Árbitro Silencioso | AW2: {=IF(COUNTA(_xlfn._xlws.FILTER(Exaltado!C3:C200,(Exaltado!B3:B200<>Exaltado!C3:C200)*(Exaltado!C3:C200<>"")))=0,"",_xlfn._xlws.SORT(_xlfn._xlws.FILTER(Exaltado!C3:C200,(Exaltado!B3:B200<>Exaltado!C3:C200)*(Exaltado!C3:C200<>"")),1,1))} -> #VALUE! | AX2: {=IF(COUNTA(_xlfn._xlws.FILTER(Modular!C3:C200,(Modular!B3:B200<>Modular!C3:C200)*(Modular!C3:C200<>"")))=0,"",_xlfn._xlws.SORT(_xlfn._xlws.FILTER(Modular!C3:C200,(Modular!B3:B200<>Modular!C3:C200)*(Modular!C3:C200<>"")),1,1))} -> Adagia, Windswept Bastion | AZ2: {=IF(COUNTA(_xlfn._xlws.FILTER(Thrakiri!C3:C103,(Thrakiri!B3:B103<>Thrakiri!C3:C103)*(Thrakiri!C3:C103<>"")))+COUNTA(_xlfn._xlws.FILTER(Gitrog!C3:C102,(Gitrog!B3:B102<>Gitrog!C3:C102)*(Gitrog!C3:C102<>"")))+COUNTA(_xlfn._xlws.FILTER(Elfos!C3:C103,(Elfos!B3:B103<>Elfos!C3:C103)*(Elfos!C3:C103<>"")))=0,"",_xlfn._xlws.SORT(_xlfn.UNIQUE(IF(ROW(INDIRECT("1:"&(COUNTA(_xlfn._xlws.FILTER(Thrakiri!C3:C103,(Thrakiri!B3:B103<>Thrakiri!C3:C103)*(Thrakiri!C3:C103<>"")))+COUNTA(_xlfn._xlws.FILTER(Gitrog!C3:C102,(Gitrog!B3:B102<>Gitrog!C3:C102)*(Gitrog!C3:C102<>"")))+COUNTA(_xlfn._xlws.FILTER(Elfos!C3:C103,(Elfos!B3:B103<>Elfos!C3:C103)*(Elfos!C3:C103<>""))))))<=COUNTA(_xlfn._xlws.FILTER(Thrakiri!C3:C103,(Thrakiri!B3:B103<>Thrakiri!C3:C103)*(Thrakiri!C3:C103<>""))),INDEX(_xlfn._xlws.FILTER(Thrakiri!C3:C103,(Thrakiri!B3:B103<>Thrakiri!C3:C103)*(Thrakiri!C3:C103<>"")),ROW(INDIRECT("1:"&(COUNTA(_xlfn._xlws.FILTER(Thrakiri!C3:C103,(Thrakiri!B3:B103<>Thrakiri!C3:C103)*(Thrakiri!C3:C103<>"")))+COUNTA(_xlfn._xlws.FILTER(Gitrog!C3:C102,(Gitrog!B3:B102<>Gitrog!C3:C102)*(Gitrog!C3:C102<>"")))+COUNTA(_xlfn._xlws.FILTER(Elfos!C3:C103,(Elfos!B3:B103<>Elfos!C3:C103)*(Elfos!C3:C103<>""))))))),IF(ROW(INDIRECT("1:"&(COUNTA(_xlfn._xlws.FILTER(Thrakiri!C3:C103,(Thrakiri!B3:B103<>Thrakiri!C3:C103)*(Thrakiri!C3:C103<>"")))+COUNTA(_xlfn._xlws.FILTER(Gitrog!C3:C102,(Gitrog!B3:B102<>Gitrog!C3:C102)*(Gitrog!C3:C102<>"")))+COUNTA(_xlfn._xlws.FILTER(Elfos!C3:C103,(Elfos!B3:B103<>Elfos!C3:C103)*(Elfos!C3:C103<>""))))))<=COUNTA(_xlfn._xlws.FILTER(Thrakiri!C3:C103,(Thrakiri!B3:B103<>Thrakiri!C3:C103)*(Thrakiri!C3:C103<>"")))+COUNTA(_xlfn._xlws.FILTER(Gitrog!C3:C102,(Gitrog!B3:B102<>Gitrog!C3:C102)*(Gitrog!C3:C102<>""))),INDEX(_xlfn._xlws.FILTER(Gitrog!C3:C102,(Gitrog!B3:B102<>Gitrog!C3:C102)*(Gitrog!C3:C102<>"")),ROW(INDIRECT("1:"&(COUNTA(_xlfn._xlws.FILTER(Thrakiri!C3:C103,(Thrakiri!B3:B103<>Thrakiri!C3:C103)*(Thrakiri!C3:C103<>"")))+COUNTA(_xlfn._xlws.FILTER(Gitrog!C3:C102,(Gitrog!B3:B102<>Gitrog!C3:C102)*(Gitrog!C3:C102<>"")))+COUNTA(_xlfn._xlws.FILTER(Elfos!C3:C103,(Elfos!B3:B103<>Elfos!C3:C103)*(Elfos!C3:C103<>""))))))-COUNTA(_xlfn._xlws.FILTER(Thrakiri!C3:C103,(Thrakiri!B3:B103<>Thrakiri!C3:C103)*(Thrakiri!C3:C103<>"")))),INDEX(_xlfn._xlws.FILTER(Elfos!C3:C103,(Elfos!B3:B103<>Elfos!C3:C103)*(Elfos!C3:C103<>"")),ROW(INDIRECT("1:"&(COUNTA(_xlfn._xlws.FILTER(Thrakiri!C3:C103,(Thrakiri!B3:B103<>Thrakiri!C3:C103)*(Thrakiri!C3:C103<>"")))+COUNTA(_xlfn._xlws.FILTER(Gitrog!C3:C102,(Gitrog!B3:B102<>Gitrog!C3:C102)*(Gitrog!C3:C102<>"")))+COUNTA(_xlfn._xlws.FILTER(Elfos!C3:C103,(Elfos!B3:B103<>Elfos!C3:C103)*(Elfos!C3:C103<>""))))))-COUNTA(_xlfn._xlws.FILTER(Thrakiri!C3:C103,(Thrakiri!B3:B103<>Thrakiri!C3:C103)*(Thrakiri!C3:C103<>"")))-COUNTA(_xlfn._xlws.FILTER(Gitrog!C3:C102,(Gitrog!B3:B102<>Gitrog!C3:C102)*(Gitrog!C3:C102<>"")))))),1,-1)))} -> Alchemist's Refuge | BA2: {=IF(COUNTA(_xlfn._xlws.FILTER(Jhoira!C3:C101,(Jhoira!B3:B101<>Jhoira!C3:C101)*(Jhoira!C3:C101<>"")))+COUNTA(_xlfn._xlws.FILTER(Fractius!C3:C102,(Fractius!B3:B102<>Fractius!C3:C102)*(Fractius!C3:C102<>"")))+COUNTA(_xlfn._xlws.FILTER(Muzzio!C3:C102,(Muzzio!B3:B102<>Muzzio!C3:C102)*(Muzzio!C3:C102<>"")))=0,"",_xlfn._xlws.SORT(_xlfn.UNIQUE(IF(ROW(INDIRECT("1:"&(COUNTA(_xlfn._xlws.FILTER(Jhoira!C3:C101,(Jhoira!B3:B101<>Jhoira!C3:C101)*(Jhoira!C3:C101<>"")))+COUNTA(_xlfn._xlws.FILTER(Fractius!C3:C102,(Fractius!B3:B102<>Fractius!C3:C102)*(Fractius!C3:C102<>"")))+COUNTA(_xlfn._xlws.FILTER(Muzzio!C3:C102,(Muzzio!B3:B102<>Muzzio!C3:C102)*(Muzzio!C3:C102<>""))))))<=COUNTA(_xlfn._xlws.FILTER(Jhoira!C3:C101,(Jhoira!B3:B101<>Jhoira!C3:C101)*(Jhoira!C3:C101<>""))),INDEX(_xlfn._xlws.FILTER(Jhoira!C3:C101,(Jhoira!B3:B101<>Jhoira!C3:C101)*(Jhoira!C3:C101<>"")),ROW(INDIRECT("1:"&(COUNTA(_xlfn._xlws.FILTER(Jhoira!C3:C101,(Jhoira!B3:B101<>Jhoira!C3:C101)*(Jhoira!C3:C101<>"")))+COUNTA(_xlfn._xlws.FILTER(Fractius!C3:C102,(Fractius!B3:B102<>Fractius!C3:C102)*(Fractius!C3:C102<>"")))+COUNTA(_xlfn._xlws.FILTER(Muzzio!C3:C102,(Muzzio!B3:B102<>Muzzio!C3:C102)*(Muzzio!C3:C102<>""))))))),IF(ROW(INDIRECT("1:"&(COUNTA(_xlfn._xlws.FILTER(Jhoira!C3:C101,(Jhoira!B3:B101<>Jhoira!C3:C101)*(Jhoira!C3:C101<>"")))+COUNTA(_xlfn._xlws.FILTER(Fractius!C3:C102,(Fractius!B3:B102<>Fractius!C3:C102)*(Fractius!C3:C102<>"")))+COUNTA(_xlfn._xlws.FILTER(Muzzio!C3:C102,(Muzzio!B3:B102<>Muzzio!C3:C102)*(Muzzio!C3:C102<>""))))))<=COUNTA(_xlfn._xlws.FILTER(Jhoira!C3:C101,(Jhoira!B3:B101<>Jhoira!C3:C101)*(Jhoira!C3:C101<>"")))+COUNTA(_xlfn._xlws.FILTER(Fractius!C3:C102,(Fractius!B3:B102<>Fractius!C3:C102)*(Fractius!C3:C102<>""))),INDEX(_xlfn._xlws.FILTER(Fractius!C3:C102,(Fractius!B3:B102<>Fractius!C3:C102)*(Fractius!C3:C102<>"")),ROW(INDIRECT("1:"&(COUNTA(_xlfn._xlws.FILTER(Jhoira!C3:C101,(Jhoira!B3:B101<>Jhoira!C3:C101)*(Jhoira!C3:C101<>"")))+COUNTA(_xlfn._xlws.FILTER(Fractius!C3:C102,(Fractius!B3:B102<>Fractius!C3:C102)*(Fractius!C3:C102<>"")))+COUNTA(_xlfn._xlws.FILTER(Muzzio!C3:C102,(Muzzio!B3:B102<>Muzzio!C3:C102)*(Muzzio!C3:C102<>""))))))-COUNTA(_xlfn._xlws.FILTER(Jhoira!C3:C101,(Jhoira!B3:B101<>Jhoira!C3:C101)*(Jhoira!C3:C101<>"")))),INDEX(_xlfn._xlws.FILTER(Muzzio!C3:C102,(Muzzio!B3:B102<>Muzzio!C3:C102)*(Muzzio!C3:C102<>"")),ROW(INDIRECT("1:"&(COUNTA(_xlfn._xlws.FILTER(Jhoira!C3:C101,(Jhoira!B3:B101<>Jhoira!C3:C101)*(Jhoira!C3:C101<>"")))+COUNTA(_xlfn._xlws.FILTER(Fractius!C3:C102,(Fractius!B3:B102<>Fractius!C3:C102)*(Fractius!C3:C102<>"")))+COUNTA(_xlfn._xlws.FILTER(Muzzio!C3:C102,(Muzzio!B3:B102<>Muzzio!C3:C102)*(Muzzio!C3:C102<>""))))))-COUNTA(_xlfn._xlws.FILTER(Jhoira!C3:C101,(Jhoira!B3:B101<>Jhoira!C3:C101)*(Jhoira!C3:C101<>"")))-COUNTA(_xlfn._xlws.FILTER(Fractius!C3:C102,(Fractius!B3:B102<>Fractius!C3:C102)*(Fractius!C3:C102<>"")))))),1,-1)))} -> A Joia do Enigma | BB2: {=IF(COUNTA(_xlfn._xlws.FILTER(Rielle!C3:C102,(Rielle!B3:B102<>Rielle!C3:C102)*(Rielle!C3:C102<>"")))+COUNTA(_xlfn._xlws.FILTER(Alela!C3:C102,(Alela!B3:B102<>Alela!C3:C102)*(Alela!C3:C102<>"")))+COUNTA(_xlfn._xlws.FILTER(Arcades!C3:C102,(Arcades!B3:B102<>Arcades!C3:C102)*(Arcades!C3:C102<>"")))=0,"",_xlfn._xlws.SORT(_xlfn.UNIQUE(IF(ROW(INDIRECT("1:"&(COUNTA(_xlfn._xlws.FILTER(Rielle!C3:C102,(Rielle!B3:B102<>Rielle!C3:C102)*(Rielle!C3:C102<>"")))+COUNTA(_xlfn._xlws.FILTER(Alela!C3:C102,(Alela!B3:B102<>Alela!C3:C102)*(Alela!C3:C102<>"")))+COUNTA(_xlfn._xlws.FILTER(Arcades!C3:C102,(Arcades!B3:B102<>Arcades!C3:C102)*(Arcades!C3:C102<>""))))))<=COUNTA(_xlfn._xlws.FILTER(Rielle!C3:C102,(Rielle!B3:B102<>Rielle!C3:C102)*(Rielle!C3:C102<>""))),INDEX(_xlfn._xlws.FILTER(Rielle!C3:C102,(Rielle!B3:B102<>Rielle!C3:C102)*(Rielle!C3:C102<>"")),ROW(INDIRECT("1:"&(COUNTA(_xlfn._xlws.FILTER(Rielle!C3:C102,(Rielle!B3:B102<>Rielle!C3:C102)*(Rielle!C3:C102<>"")))+COUNTA(_xlfn._xlws.FILTER(Alela!C3:C102,(Alela!B3:B102<>Alela!C3:C102)*(Alela!C3:C102<>"")))+COUNTA(_xlfn._xlws.FILTER(Arcades!C3:C102,(Arcades!B3:B102<>Arcades!C3:C102)*(Arcades!C3:C102<>""))))))),IF(ROW(INDIRECT("1:"&(COUNTA(_xlfn._xlws.FILTER(Rielle!C3:C102,(Rielle!B3:B102<>Rielle!C3:C102)*(Rielle!C3:C102<>"")))+COUNTA(_xlfn._xlws.FILTER(Alela!C3:C102,(Alela!B3:B102<>Alela!C3:C102)*(Alela!C3:C102<>"")))+COUNTA(_xlfn._xlws.FILTER(Arcades!C3:C102,(Arcades!B3:B102<>Arcades!C3:C102)*(Arcades!C3:C102<>""))))))<=COUNTA(_xlfn._xlws.FILTER(Rielle!C3:C102,(Rielle!B3:B102<>Rielle!C3:C102)*(Rielle!C3:C102<>"")))+COUNTA(_xlfn._xlws.FILTER(Alela!C3:C102,(Alela!B3:B102<>Alela!C3:C102)*(Alela!C3:C102<>""))),INDEX(_xlfn._xlws.FILTER(Alela!C3:C102,(Alela!B3:B102<>Alela!C3:C102)*(Alela!C3:C102<>"")),ROW(INDIRECT("1:"&(COUNTA(_xlfn._xlws.FILTER(Rielle!C3:C102,(Rielle!B3:B102<>Rielle!C3:C102)*(Rielle!C3:C102<>"")))+COUNTA(_xlfn._xlws.FILTER(Alela!C3:C102,(Alela!B3:B102<>Alela!C3:C102)*(Alela!C3:C102<>"")))+COUNTA(_xlfn._xlws.FILTER(Arcades!C3:C102,(Arcades!B3:B102<>Arcades!C3:C102)*(Arcades!C3:C102<>""))))))-COUNTA(_xlfn._xlws.FILTER(Rielle!C3:C102,(Rielle!B3:B102<>Rielle!C3:C102)*(Rielle!C3:C102<>"")))),INDEX(_xlfn._xlws.FILTER(Arcades!C3:C102,(Arcades!B3:B102<>Arcades!C3:C102)*(Arcades!C3:C102<>"")),ROW(INDIRECT("1:"&(COUNTA(_xlfn._xlws.FILTER(Rielle!C3:C102,(Rielle!B3:B102<>Rielle!C3:C102)*(Rielle!C3:C102<>"")))+COUNTA(_xlfn._xlws.FILTER(Alela!C3:C102,(Alela!B3:B102<>Alela!C3:C102)*(Alela!C3:C102<>"")))+COUNTA(_xlfn._xlws.FILTER(Arcades!C3:C102,(Arcades!B3:B102<>Arcades!C3:C102)*(Arcades!C3:C102<>""))))))-COUNTA(_xlfn._xlws.FILTER(Rielle!C3:C102,(Rielle!B3:B102<>Rielle!C3:C102)*(Rielle!C3:C102<>"")))-COUNTA(_xlfn._xlws.FILTER(Alela!C3:C102,(Alela!B3:B102<>Alela!C3:C102)*(Alela!C3:C102<>"")))))),1,-1)))} -> Adagia, Windswept Bastion | BC2: {=IF(COUNTA(_xlfn._xlws.FILTER(VialIshai!C3:C103,(VialIshai!B3:B103<>VialIshai!C3:C103)*(VialIshai!C3:C103<>"")))+COUNTA(_xlfn._xlws.FILTER(Yuriko!C3:C102,(Yuriko!B3:B102<>Yuriko!C3:C102)*(Yuriko!C3:C102<>"")))+COUNTA(_xlfn._xlws.FILTER(Zedruu!C3:C102,(Zedruu!B3:B102<>Zedruu!C3:C102)*(Zedruu!C3:C102<>"")))=0,"",_xlfn._xlws.SORT(_xlfn.UNIQUE(IF(ROW(INDIRECT("1:"&(COUNTA(_xlfn._xlws.FILTER(VialIshai!C3:C103,(VialIshai!B3:B103<>VialIshai!C3:C103)*(VialIshai!C3:C103<>"")))+COUNTA(_xlfn._xlws.FILTER(Yuriko!C3:C102,(Yuriko!B3:B102<>Yuriko!C3:C102)*(Yuriko!C3:C102<>"")))+COUNTA(_xlfn._xlws.FILTER(Zedruu!C3:C102,(Zedruu!B3:B102<>Zedruu!C3:C102)*(Zedruu!C3:C102<>""))))))<=COUNTA(_xlfn._xlws.FILTER(VialIshai!C3:C103,(VialIshai!B3:B103<>VialIshai!C3:C103)*(VialIshai!C3:C103<>""))),INDEX(_xlfn._xlws.FILTER(VialIshai!C3:C103,(VialIshai!B3:B103<>VialIshai!C3:C103)*(VialIshai!C3:C103<>"")),ROW(INDIRECT("1:"&(COUNTA(_xlfn._xlws.FILTER(VialIshai!C3:C103,(VialIshai!B3:B103<>VialIshai!C3:C103)*(VialIshai!C3:C103<>"")))+COUNTA(_xlfn._xlws.FILTER(Yuriko!C3:C102,(Yuriko!B3:B102<>Yuriko!C3:C102)*(Yuriko!C3:C102<>"")))+COUNTA(_xlfn._xlws.FILTER(Zedruu!C3:C102,(Zedruu!B3:B102<>Zedruu!C3:C102)*(Zedruu!C3:C102<>""))))))),IF(ROW(INDIRECT("1:"&(COUNTA(_xlfn._xlws.FILTER(VialIshai!C3:C103,(VialIshai!B3:B103<>VialIshai!C3:C103)*(VialIshai!C3:C103<>"")))+COUNTA(_xlfn._xlws.FILTER(Yuriko!C3:C102,(Yuriko!B3:B102<>Yuriko!C3:C102)*(Yuriko!C3:C102<>"")))+COUNTA(_xlfn._xlws.FILTER(Zedruu!C3:C102,(Zedruu!B3:B102<>Zedruu!C3:C102)*(Zedruu!C3:C102<>""))))))<=COUNTA(_xlfn._xlws.FILTER(VialIshai!C3:C103,(VialIshai!B3:B103<>VialIshai!C3:C103)*(VialIshai!C3:C103<>"")))+COUNTA(_xlfn._xlws.FILTER(Yuriko!C3:C102,(Yuriko!B3:B102<>Yuriko!C3:C102)*(Yuriko!C3:C102<>""))),INDEX(_xlfn._xlws.FILTER(Yuriko!C3:C102,(Yuriko!B3:B102<>Yuriko!C3:C102)*(Yuriko!C3:C102<>"")),ROW(INDIRECT("1:"&(COUNTA(_xlfn._xlws.FILTER(VialIshai!C3:C103,(VialIshai!B3:B103<>VialIshai!C3:C103)*(VialIshai!C3:C103<>"")))+COUNTA(_xlfn._xlws.FILTER(Yuriko!C3:C102,(Yuriko!B3:B102<>Yuriko!C3:C102)*(Yuriko!C3:C102<>"")))+COUNTA(_xlfn._xlws.FILTER(Zedruu!C3:C102,(Zedruu!B3:B102<>Zedruu!C3:C102)*(Zedruu!C3:C102<>""))))))-COUNTA(_xlfn._xlws.FILTER(VialIshai!C3:C103,(VialIshai!B3:B103<>VialIshai!C3:C103)*(VialIshai!C3:C103<>"")))),INDEX(_xlfn._xlws.FILTER(Zedruu!C3:C102,(Zedruu!B3:B102<>Zedruu!C3:C102)*(Zedruu!C3:C102<>"")),ROW(INDIRECT("1:"&(COUNTA(_xlfn._xlws.FILTER(VialIshai!C3:C103,(VialIshai!B3:B103<>VialIshai!C3:C103)*(VialIshai!C3:C103<>"")))+COUNTA(_xlfn._xlws.FILTER(Yuriko!C3:C102,(Yuriko!B3:B102<>Yuriko!C3:C102)*(Yuriko!C3:C102<>"")))+COUNTA(_xlfn._xlws.FILTER(Zedruu!C3:C102,(Zedruu!B3:B102<>Zedruu!C3:C102)*(Zedruu!C3:C102<>""))))))-COUNTA(_xlfn._xlws.FILTER(VialIshai!C3:C103,(VialIshai!B3:B103<>VialIshai!C3:C103)*(VialIshai!C3:C103<>"")))-COUNTA(_xlfn._xlws.FILTER(Yuriko!C3:C102,(Yuriko!B3:B102<>Yuriko!C3:C102)*(Yuriko!C3:C102<>"")))))),1,-1)))} -> Amphibian Downpour | BD2: {=IF(COUNTA(_xlfn._xlws.FILTER(Inalla!C3:C102,(Inalla!B3:B102<>Inalla!C3:C102)*(Inalla!C3:C102<>"")))+COUNTA(_xlfn._xlws.FILTER(Carlos!C3:C102,(Carlos!B3:B102<>Carlos!C3:C102)*(Carlos!C3:C102<>"")))+COUNTA(_xlfn._xlws.FILTER(Oona!C3:C102,(Oona!B3:B102<>Oona!C3:C102)*(Oona!C3:C102<>"")))=0,"",_xlfn._xlws.SORT(_xlfn.UNIQUE(IF(ROW(INDIRECT("1:"&(COUNTA(_xlfn._xlws.FILTER(Inalla!C3:C102,(Inalla!B3:B102<>Inalla!C3:C102)*(Inalla!C3:C102<>"")))+COUNTA(_xlfn._xlws.FILTER(Carlos!C3:C102,(Carlos!B3:B102<>Carlos!C3:C102)*(Carlos!C3:C102<>"")))+COUNTA(_xlfn._xlws.FILTER(Oona!C3:C102,(Oona!B3:B102<>Oona!C3:C102)*(Oona!C3:C102<>""))))))<=COUNTA(_xlfn._xlws.FILTER(Inalla!C3:C102,(Inalla!B3:B102<>Inalla!C3:C102)*(Inalla!C3:C102<>""))),INDEX(_xlfn._xlws.FILTER(Inalla!C3:C102,(Inalla!B3:B102<>Inalla!C3:C102)*(Inalla!C3:C102<>"")),ROW(INDIRECT("1:"&(COUNTA(_xlfn._xlws.FILTER(Inalla!C3:C102,(Inalla!B3:B102<>Inalla!C3:C102)*(Inalla!C3:C102<>"")))+COUNTA(_xlfn._xlws.FILTER(Carlos!C3:C102,(Carlos!B3:B102<>Carlos!C3:C102)*(Carlos!C3:C102<>"")))+COUNTA(_xlfn._xlws.FILTER(Oona!C3:C102,(Oona!B3:B102<>Oona!C3:C102)*(Oona!C3:C102<>""))))))),IF(ROW(INDIRECT("1:"&(COUNTA(_xlfn._xlws.FILTER(Inalla!C3:C102,(Inalla!B3:B102<>Inalla!C3:C102)*(Inalla!C3:C102<>"")))+COUNTA(_xlfn._xlws.FILTER(Carlos!C3:C102,(Carlos!B3:B102<>Carlos!C3:C102)*(Carlos!C3:C102<>"")))+COUNTA(_xlfn._xlws.FILTER(Oona!C3:C102,(Oona!B3:B102<>Oona!C3:C102)*(Oona!C3:C102<>""))))))<=COUNTA(_xlfn._xlws.FILTER(Inalla!C3:C102,(Inalla!B3:B102<>Inalla!C3:C102)*(Inalla!C3:C102<>"")))+COUNTA(_xlfn._xlws.FILTER(Carlos!C3:C102,(Carlos!B3:B102<>Carlos!C3:C102)*(Carlos!C3:C102<>""))),INDEX(_xlfn._xlws.FILTER(Carlos!C3:C102,(Carlos!B3:B102<>Carlos!C3:C102)*(Carlos!C3:C102<>"")),ROW(INDIRECT("1:"&(COUNTA(_xlfn._xlws.FILTER(Inalla!C3:C102,(Inalla!B3:B102<>Inalla!C3:C102)*(Inalla!C3:C102<>"")))+COUNTA(_xlfn._xlws.FILTER(Carlos!C3:C102,(Carlos!B3:B102<>Carlos!C3:C102)*(Carlos!C3:C102<>"")))+COUNTA(_xlfn._xlws.FILTER(Oona!C3:C102,(Oona!B3:B102<>Oona!C3:C102)*(Oona!C3:C102<>""))))))-COUNTA(_xlfn._xlws.FILTER(Inalla!C3:C102,(Inalla!B3:B102<>Inalla!C3:C102)*(Inalla!C3:C102<>"")))),INDEX(_xlfn._xlws.FILTER(Oona!C3:C102,(Oona!B3:B102<>Oona!C3:C102)*(Oona!C3:C102<>"")),ROW(INDIRECT("1:"&(COUNTA(_xlfn._xlws.FILTER(Inalla!C3:C102,(Inalla!B3:B102<>Inalla!C3:C102)*(Inalla!C3:C102<>"")))+COUNTA(_xlfn._xlws.FILTER(Carlos!C3:C102,(Carlos!B3:B102<>Carlos!C3:C102)*(Carlos!C3:C102<>"")))+COUNTA(_xlfn._xlws.FILTER(Oona!C3:C102,(Oona!B3:B102<>Oona!C3:C102)*(Oona!C3:C102<>""))))))-COUNTA(_xlfn._xlws.FILTER(Inalla!C3:C102,(Inalla!B3:B102<>Inalla!C3:C102)*(Inalla!C3:C102<>"")))-COUNTA(_xlfn._xlws.FILTER(Carlos!C3:C102,(Carlos!B3:B102<>Carlos!C3:C102)*(Carlos!C3:C102<>"")))))),1,-1)))} -> Arcane Lighthouse | BE2: {=IF(COUNTA(_xlfn._xlws.FILTER(Kresh!C3:C102,(Kresh!B3:B102<>Kresh!C3:C102)*(Kresh!C3:C102<>"")))+COUNTA(_xlfn._xlws.FILTER(Akiri!C3:C102,(Akiri!B3:B102<>Akiri!C3:C102)*(Akiri!C3:C102<>"")))+COUNTA(_xlfn._xlws.FILTER(Breya!C3:C102,(Breya!B3:B102<>Breya!C3:C102)*(Breya!C3:C102<>"")))=0,"",_xlfn._xlws.SORT(_xlfn.UNIQUE(IF(ROW(INDIRECT("1:"&(COUNTA(_xlfn._xlws.FILTER(Kresh!C3:C102,(Kresh!B3:B102<>Kresh!C3:C102)*(Kresh!C3:C102<>"")))+COUNTA(_xlfn._xlws.FILTER(Akiri!C3:C102,(Akiri!B3:B102<>Akiri!C3:C102)*(Akiri!C3:C102<>"")))+COUNTA(_xlfn._xlws.FILTER(Breya!C3:C102,(Breya!B3:B102<>Breya!C3:C102)*(Breya!C3:C102<>""))))))<=COUNTA(_xlfn._xlws.FILTER(Kresh!C3:C102,(Kresh!B3:B102<>Kresh!C3:C102)*(Kresh!C3:C102<>""))),INDEX(_xlfn._xlws.FILTER(Kresh!C3:C102,(Kresh!B3:B102<>Kresh!C3:C102)*(Kresh!C3:C102<>"")),ROW(INDIRECT("1:"&(COUNTA(_xlfn._xlws.FILTER(Kresh!C3:C102,(Kresh!B3:B102<>Kresh!C3:C102)*(Kresh!C3:C102<>"")))+COUNTA(_xlfn._xlws.FILTER(Akiri!C3:C102,(Akiri!B3:B102<>Akiri!C3:C102)*(Akiri!C3:C102<>"")))+COUNTA(_xlfn._xlws.FILTER(Breya!C3:C102,(Breya!B3:B102<>Breya!C3:C102)*(Breya!C3:C102<>""))))))),IF(ROW(INDIRECT("1:"&(COUNTA(_xlfn._xlws.FILTER(Kresh!C3:C102,(Kresh!B3:B102<>Kresh!C3:C102)*(Kresh!C3:C102<>"")))+COUNTA(_xlfn._xlws.FILTER(Akiri!C3:C102,(Akiri!B3:B102<>Akiri!C3:C102)*(Akiri!C3:C102<>"")))+COUNTA(_xlfn._xlws.FILTER(Breya!C3:C102,(Breya!B3:B102<>Breya!C3:C102)*(Breya!C3:C102<>""))))))<=COUNTA(_xlfn._xlws.FILTER(Kresh!C3:C102,(Kresh!B3:B102<>Kresh!C3:C102)*(Kresh!C3:C102<>"")))+COUNTA(_xlfn._xlws.FILTER(Akiri!C3:C102,(Akiri!B3:B102<>Akiri!C3:C102)*(Akiri!C3:C102<>""))),INDEX(_xlfn._xlws.FILTER(Akiri!C3:C102,(Akiri!B3:B102<>Akiri!C3:C102)*(Akiri!C3:C102<>"")),ROW(INDIRECT("1:"&(COUNTA(_xlfn._xlws.FILTER(Kresh!C3:C102,(Kresh!B3:B102<>Kresh!C3:C102)*(Kresh!C3:C102<>"")))+COUNTA(_xlfn._xlws.FILTER(Akiri!C3:C102,(Akiri!B3:B102<>Akiri!C3:C102)*(Akiri!C3:C102<>"")))+COUNTA(_xlfn._xlws.FILTER(Breya!C3:C102,(Breya!B3:B102<>Breya!C3:C102)*(Breya!C3:C102<>""))))))-COUNTA(_xlfn._xlws.FILTER(Kresh!C3:C102,(Kresh!B3:B102<>Kresh!C3:C102)*(Kresh!C3:C102<>"")))),INDEX(_xlfn._xlws.FILTER(Breya!C3:C102,(Breya!B3:B102<>Breya!C3:C102)*(Breya!C3:C102<>"")),ROW(INDIRECT("1:"&(COUNTA(_xlfn._xlws.FILTER(Kresh!C3:C102,(Kresh!B3:B102<>Kresh!C3:C102)*(Kresh!C3:C102<>"")))+COUNTA(_xlfn._xlws.FILTER(Akiri!C3:C102,(Akiri!B3:B102<>Akiri!C3:C102)*(Akiri!C3:C102<>"")))+COUNTA(_xlfn._xlws.FILTER(Breya!C3:C102,(Breya!B3:B102<>Breya!C3:C102)*(Breya!C3:C102<>""))))))-COUNTA(_xlfn._xlws.FILTER(Kresh!C3:C102,(Kresh!B3:B102<>Kresh!C3:C102)*(Kresh!C3:C102<>"")))-COUNTA(_xlfn._xlws.FILTER(Akiri!C3:C102,(Akiri!B3:B102<>Akiri!C3:C102)*(Akiri!C3:C102<>"")))))),1,-1)))} -> Adagia, Windswept Bastion | BF2: {=IF(COUNTA(_xlfn._xlws.FILTER(Rani!C3:C102,(Rani!B3:B102<>Rani!C3:C102)*(Rani!C3:C102<>"")))+COUNTA(_xlfn._xlws.FILTER(Sisay!C3:C102,(Sisay!B3:B102<>Sisay!C3:C102)*(Sisay!C3:C102<>"")))+COUNTA(_xlfn._xlws.FILTER(OWA!C3:C103,(OWA!B3:B103<>OWA!C3:C103)*(OWA!C3:C103<>"")))=0,"",_xlfn._xlws.SORT(_xlfn.UNIQUE(IF(ROW(INDIRECT("1:"&(COUNTA(_xlfn._xlws.FILTER(Rani!C3:C102,(Rani!B3:B102<>Rani!C3:C102)*(Rani!C3:C102<>"")))+COUNTA(_xlfn._xlws.FILTER(Sisay!C3:C102,(Sisay!B3:B102<>Sisay!C3:C102)*(Sisay!C3:C102<>"")))+COUNTA(_xlfn._xlws.FILTER(OWA!C3:C103,(OWA!B3:B103<>OWA!C3:C103)*(OWA!C3:C103<>""))))))<=COUNTA(_xlfn._xlws.FILTER(Rani!C3:C102,(Rani!B3:B102<>Rani!C3:C102)*(Rani!C3:C102<>""))),INDEX(_xlfn._xlws.FILTER(Rani!C3:C102,(Rani!B3:B102<>Rani!C3:C102)*(Rani!C3:C102<>"")),ROW(INDIRECT("1:"&(COUNTA(_xlfn._xlws.FILTER(Rani!C3:C102,(Rani!B3:B102<>Rani!C3:C102)*(Rani!C3:C102<>"")))+COUNTA(_xlfn._xlws.FILTER(Sisay!C3:C102,(Sisay!B3:B102<>Sisay!C3:C102)*(Sisay!C3:C102<>"")))+COUNTA(_xlfn._xlws.FILTER(OWA!C3:C103,(OWA!B3:B103<>OWA!C3:C103)*(OWA!C3:C103<>""))))))),IF(ROW(INDIRECT("1:"&(COUNTA(_xlfn._xlws.FILTER(Rani!C3:C102,(Rani!B3:B102<>Rani!C3:C102)*(Rani!C3:C102<>"")))+COUNTA(_xlfn._xlws.FILTER(Sisay!C3:C102,(Sisay!B3:B102<>Sisay!C3:C102)*(Sisay!C3:C102<>"")))+COUNTA(_xlfn._xlws.FILTER(OWA!C3:C103,(OWA!B3:B103<>OWA!C3:C103)*(OWA!C3:C103<>""))))))<=COUNTA(_xlfn._xlws.FILTER(Rani!C3:C102,(Rani!B3:B102<>Rani!C3:C102)*(Rani!C3:C102<>"")))+COUNTA(_xlfn._xlws.FILTER(Sisay!C3:C102,(Sisay!B3:B102<>Sisay!C3:C102)*(Sisay!C3:C102<>""))),INDEX(_xlfn._xlws.FILTER(Sisay!C3:C102,(Sisay!B3:B102<>Sisay!C3:C102)*(Sisay!C3:C102<>"")),ROW(INDIRECT("1:"&(COUNTA(_xlfn._xlws.FILTER(Rani!C3:C102,(Rani!B3:B102<>Rani!C3:C102)*(Rani!C3:C102<>"")))+COUNTA(_xlfn._xlws.FILTER(Sisay!C3:C102,(Sisay!B3:B102<>Sisay!C3:C102)*(Sisay!C3:C102<>"")))+COUNTA(_xlfn._xlws.FILTER(OWA!C3:C103,(OWA!B3:B103<>OWA!C3:C103)*(OWA!C3:C103<>""))))))-COUNTA(_xlfn._xlws.FILTER(Rani!C3:C102,(Rani!B3:B102<>Rani!C3:C102)*(Rani!C3:C102<>"")))),INDEX(_xlfn._xlws.FILTER(OWA!C3:C103,(OWA!B3:B103<>OWA!C3:C103)*(OWA!C3:C103<>"")),ROW(INDIRECT("1:"&(COUNTA(_xlfn._xlws.FILTER(Rani!C3:C102,(Rani!B3:B102<>Rani!C3:C102)*(Rani!C3:C102<>"")))+COUNTA(_xlfn._xlws.FILTER(Sisay!C3:C102,(Sisay!B3:B102<>Sisay!C3:C102)*(Sisay!C3:C102<>"")))+COUNTA(_xlfn._xlws.FILTER(OWA!C3:C103,(OWA!B3:B103<>OWA!C3:C103)*(OWA!C3:C103<>""))))))-COUNTA(_xlfn._xlws.FILTER(Rani!C3:C102,(Rani!B3:B102<>Rani!C3:C102)*(Rani!C3:C102<>"")))-COUNTA(_xlfn._xlws.FILTER(Sisay!C3:C102,(Sisay!B3:B102<>Sisay!C3:C102)*(Sisay!C3:C102<>"")))))),1,-1)))} -> Access Tunnel | BG2: {=IF(COUNTA(_xlfn._xlws.FILTER(Narset!C3:C102,(Narset!B3:B102<>Narset!C3:C102)*(Narset!C3:C102<>"")))+COUNTA(_xlfn._xlws.FILTER(Kumena!C3:C102,(Kumena!B3:B102<>Kumena!C3:C102)*(Kumena!C3:C102<>"")))+COUNTA(_xlfn._xlws.FILTER(Zimone!C3:C102,(Zimone!B3:B102<>Zimone!C3:C102)*(Zimone!C3:C102<>"")))=0,"",_xlfn._xlws.SORT(_xlfn.UNIQUE(IF(ROW(INDIRECT("1:"&(COUNTA(_xlfn._xlws.FILTER(Narset!C3:C102,(Narset!B3:B102<>Narset!C3:C102)*(Narset!C3:C102<>"")))+COUNTA(_xlfn._xlws.FILTER(Kumena!C3:C102,(Kumena!B3:B102<>Kumena!C3:C102)*(Kumena!C3:C102<>"")))+COUNTA(_xlfn._xlws.FILTER(Zimone!C3:C102,(Zimone!B3:B102<>Zimone!C3:C102)*(Zimone!C3:C102<>""))))))<=COUNTA(_xlfn._xlws.FILTER(Narset!C3:C102,(Narset!B3:B102<>Narset!C3:C102)*(Narset!C3:C102<>""))),INDEX(_xlfn._xlws.FILTER(Narset!C3:C102,(Narset!B3:B102<>Narset!C3:C102)*(Narset!C3:C102<>"")),ROW(INDIRECT("1:"&(COUNTA(_xlfn._xlws.FILTER(Narset!C3:C102,(Narset!B3:B102<>Narset!C3:C102)*(Narset!C3:C102<>"")))+COUNTA(_xlfn._xlws.FILTER(Kumena!C3:C102,(Kumena!B3:B102<>Kumena!C3:C102)*(Kumena!C3:C102<>"")))+COUNTA(_xlfn._xlws.FILTER(Zimone!C3:C102,(Zimone!B3:B102<>Zimone!C3:C102)*(Zimone!C3:C102<>""))))))),IF(ROW(INDIRECT("1:"&(COUNTA(_xlfn._xlws.FILTER(Narset!C3:C102,(Narset!B3:B102<>Narset!C3:C102)*(Narset!C3:C102<>"")))+COUNTA(_xlfn._xlws.FILTER(Kumena!C3:C102,(Kumena!B3:B102<>Kumena!C3:C102)*(Kumena!C3:C102<>"")))+COUNTA(_xlfn._xlws.FILTER(Zimone!C3:C102,(Zimone!B3:B102<>Zimone!C3:C102)*(Zimone!C3:C102<>""))))))<=COUNTA(_xlfn._xlws.FILTER(Narset!C3:C102,(Narset!B3:B102<>Narset!C3:C102)*(Narset!C3:C102<>"")))+COUNTA(_xlfn._xlws.FILTER(Kumena!C3:C102,(Kumena!B3:B102<>Kumena!C3:C102)*(Kumena!C3:C102<>""))),INDEX(_xlfn._xlws.FILTER(Kumena!C3:C102,(Kumena!B3:B102<>Kumena!C3:C102)*(Kumena!C3:C102<>"")),ROW(INDIRECT("1:"&(COUNTA(_xlfn._xlws.FILTER(Narset!C3:C102,(Narset!B3:B102<>Narset!C3:C102)*(Narset!C3:C102<>"")))+COUNTA(_xlfn._xlws.FILTER(Kumena!C3:C102,(Kumena!B3:B102<>Kumena!C3:C102)*(Kumena!C3:C102<>"")))+COUNTA(_xlfn._xlws.FILTER(Zimone!C3:C102,(Zimone!B3:B102<>Zimone!C3:C102)*(Zimone!C3:C102<>""))))))-COUNTA(_xlfn._xlws.FILTER(Narset!C3:C102,(Narset!B3:B102<>Narset!C3:C102)*(Narset!C3:C102<>"")))),INDEX(_xlfn._xlws.FILTER(Zimone!C3:C102,(Zimone!B3:B102<>Zimone!C3:C102)*(Zimone!C3:C102<>"")),ROW(INDIRECT("1:"&(COUNTA(_xlfn._xlws.FILTER(Narset!C3:C102,(Narset!B3:B102<>Narset!C3:C102)*(Narset!C3:C102<>"")))+COUNTA(_xlfn._xlws.FILTER(Kumena!C3:C102,(Kumena!B3:B102<>Kumena!C3:C102)*(Kumena!C3:C102<>"")))+COUNTA(_xlfn._xlws.FILTER(Zimone!C3:C102,(Zimone!B3:B102<>Zimone!C3:C102)*(Zimone!C3:C102<>""))))))-COUNTA(_xlfn._xlws.FILTER(Narset!C3:C102,(Narset!B3:B102<>Narset!C3:C102)*(Narset!C3:C102<>"")))-COUNTA(_xlfn._xlws.FILTER(Kumena!C3:C102,(Kumena!B3:B102<>Kumena!C3:C102)*(Kumena!C3:C102<>"")))))),1,-1)))} -> Adarkar Wastes | BH2: {=IF(COUNTA(_xlfn._xlws.FILTER(Baylen!C3:C102,(Baylen!B3:B102<>Baylen!C3:C102)*(Baylen!C3:C102<>"")))+COUNTA(_xlfn._xlws.FILTER(Tayam!C3:C101,(Tayam!B3:B101<>Tayam!C3:C101)*(Tayam!C3:C101<>"")))+COUNTA(_xlfn._xlws.FILTER(JhoiraB!C3:C101,(JhoiraB!B3:B101<>JhoiraB!C3:C101)*(JhoiraB!C3:C101<>"")))=0,"",_xlfn._xlws.SORT(_xlfn.UNIQUE(IF(ROW(INDIRECT("1:"&(COUNTA(_xlfn._xlws.FILTER(Baylen!C3:C102,(Baylen!B3:B102<>Baylen!C3:C102)*(Baylen!C3:C102<>"")))+COUNTA(_xlfn._xlws.FILTER(Tayam!C3:C101,(Tayam!B3:B101<>Tayam!C3:C101)*(Tayam!C3:C101<>"")))+COUNTA(_xlfn._xlws.FILTER(JhoiraB!C3:C101,(JhoiraB!B3:B101<>JhoiraB!C3:C101)*(JhoiraB!C3:C101<>""))))))<=COUNTA(_xlfn._xlws.FILTER(Baylen!C3:C102,(Baylen!B3:B102<>Baylen!C3:C102)*(Baylen!C3:C102<>""))),INDEX(_xlfn._xlws.FILTER(Baylen!C3:C102,(Baylen!B3:B102<>Baylen!C3:C102)*(Baylen!C3:C102<>"")),ROW(INDIRECT("1:"&(COUNTA(_xlfn._xlws.FILTER(Baylen!C3:C102,(Baylen!B3:B102<>Baylen!C3:C102)*(Baylen!C3:C102<>"")))+COUNTA(_xlfn._xlws.FILTER(Tayam!C3:C101,(Tayam!B3:B101<>Tayam!C3:C101)*(Tayam!C3:C101<>"")))+COUNTA(_xlfn._xlws.FILTER(JhoiraB!C3:C101,(JhoiraB!B3:B101<>JhoiraB!C3:C101)*(JhoiraB!C3:C101<>""))))))),IF(ROW(INDIRECT("1:"&(COUNTA(_xlfn._xlws.FILTER(Baylen!C3:C102,(Baylen!B3:B102<>Baylen!C3:C102)*(Baylen!C3:C102<>"")))+COUNTA(_xlfn._xlws.FILTER(Tayam!C3:C101,(Tayam!B3:B101<>Tayam!C3:C101)*(Tayam!C3:C101<>"")))+COUNTA(_xlfn._xlws.FILTER(JhoiraB!C3:C101,(JhoiraB!B3:B101<>JhoiraB!C3:C101)*(JhoiraB!C3:C101<>""))))))<=COUNTA(_xlfn._xlws.FILTER(Baylen!C3:C102,(Baylen!B3:B102<>Baylen!C3:C102)*(Baylen!C3:C102<>"")))+COUNTA(_xlfn._xlws.FILTER(Tayam!C3:C101,(Tayam!B3:B101<>Tayam!C3:C101)*(Tayam!C3:C101<>""))),INDEX(_xlfn._xlws.FILTER(Tayam!C3:C101,(Tayam!B3:B101<>Tayam!C3:C101)*(Tayam!C3:C101<>"")),ROW(INDIRECT("1:"&(COUNTA(_xlfn._xlws.FILTER(Baylen!C3:C102,(Baylen!B3:B102<>Baylen!C3:C102)*(Baylen!C3:C102<>"")))+COUNTA(_xlfn._xlws.FILTER(Tayam!C3:C101,(Tayam!B3:B101<>Tayam!C3:C101)*(Tayam!C3:C101<>"")))+COUNTA(_xlfn._xlws.FILTER(JhoiraB!C3:C101,(JhoiraB!B3:B101<>JhoiraB!C3:C101)*(JhoiraB!C3:C101<>""))))))-COUNTA(_xlfn._xlws.FILTER(Baylen!C3:C102,(Baylen!B3:B102<>Baylen!C3:C102)*(Baylen!C3:C102<>"")))),INDEX(_xlfn._xlws.FILTER(JhoiraB!C3:C101,(JhoiraB!B3:B101<>JhoiraB!C3:C101)*(JhoiraB!C3:C101<>"")),ROW(INDIRECT("1:"&(COUNTA(_xlfn._xlws.FILTER(Baylen!C3:C102,(Baylen!B3:B102<>Baylen!C3:C102)*(Baylen!C3:C102<>"")))+COUNTA(_xlfn._xlws.FILTER(Tayam!C3:C101,(Tayam!B3:B101<>Tayam!C3:C101)*(Tayam!C3:C101<>"")))+COUNTA(_xlfn._xlws.FILTER(JhoiraB!C3:C101,(JhoiraB!B3:B101<>JhoiraB!C3:C101)*(JhoiraB!C3:C101<>""))))))-COUNTA(_xlfn._xlws.FILTER(Baylen!C3:C102,(Baylen!B3:B102<>Baylen!C3:C102)*(Baylen!C3:C102<>"")))-COUNTA(_xlfn._xlws.FILTER(Tayam!C3:C101,(Tayam!B3:B101<>Tayam!C3:C101)*(Tayam!C3:C101<>"")))))),1,-1)))} -> Ardbert, Warrior of Darkness | BI2: {=IF(COUNTA(_xlfn._xlws.FILTER(Piratas!C3:C102,(Piratas!B3:B102<>Piratas!C3:C102)*(Piratas!C3:C102<>"")))+COUNTA(_xlfn._xlws.FILTER(#REF!,(#REF!<>#REF!)*(#REF!<>"")))+COUNTA(_xlfn._xlws.FILTER(Modular!C3:C101,(Modular!B3:B101<>Modular!C3:C101)*(Modular!C3:C101<>"")))=0,"",_xlfn._xlws.SORT(_xlfn.UNIQUE(IF(ROW(INDIRECT("1:"&(COUNTA(_xlfn._xlws.FILTER(Piratas!C3:C102,(Piratas!B3:B102<>Piratas!C3:C102)*(Piratas!C3:C102<>"")))+COUNTA(_xlfn._xlws.FILTER(#REF!,(#REF!<>#REF!)*(#REF!<>"")))+COUNTA(_xlfn._xlws.FILTER(Modular!C3:C101,(Modular!B3:B101<>Modular!C3:C101)*(Modular!C3:C101<>""))))))<=COUNTA(_xlfn._xlws.FILTER(Piratas!C3:C102,(Piratas!B3:B102<>Piratas!C3:C102)*(Piratas!C3:C102<>""))),INDEX(_xlfn._xlws.FILTER(Piratas!C3:C102,(Piratas!B3:B102<>Piratas!C3:C102)*(Piratas!C3:C102<>"")),ROW(INDIRECT("1:"&(COUNTA(_xlfn._xlws.FILTER(Piratas!C3:C102,(Piratas!B3:B102<>Piratas!C3:C102)*(Piratas!C3:C102<>"")))+COUNTA(_xlfn._xlws.FILTER(#REF!,(#REF!<>#REF!)*(#REF!<>"")))+COUNTA(_xlfn._xlws.FILTER(Modular!C3:C101,(Modular!B3:B101<>Modular!C3:C101)*(Modular!C3:C101<>""))))))),IF(ROW(INDIRECT("1:"&(COUNTA(_xlfn._xlws.FILTER(Piratas!C3:C102,(Piratas!B3:B102<>Piratas!C3:C102)*(Piratas!C3:C102<>"")))+COUNTA(_xlfn._xlws.FILTER(#REF!,(#REF!<>#REF!)*(#REF!<>"")))+COUNTA(_xlfn._xlws.FILTER(Modular!C3:C101,(Modular!B3:B101<>Modular!C3:C101)*(Modular!C3:C101<>""))))))<=COUNTA(_xlfn._xlws.FILTER(Piratas!C3:C102,(Piratas!B3:B102<>Piratas!C3:C102)*(Piratas!C3:C102<>"")))+COUNTA(_xlfn._xlws.FILTER(#REF!,(#REF!<>#REF!)*(#REF!<>""))),INDEX(_xlfn._xlws.FILTER(#REF!,(#REF!<>#REF!)*(#REF!<>"")),ROW(INDIRECT("1:"&(COUNTA(_xlfn._xlws.FILTER(Piratas!C3:C102,(Piratas!B3:B102<>Piratas!C3:C102)*(Piratas!C3:C102<>"")))+COUNTA(_xlfn._xlws.FILTER(#REF!,(#REF!<>#REF!)*(#REF!<>"")))+COUNTA(_xlfn._xlws.FILTER(Modular!C3:C101,(Modular!B3:B101<>Modular!C3:C101)*(Modular!C3:C101<>""))))))-COUNTA(_xlfn._xlws.FILTER(Piratas!C3:C102,(Piratas!B3:B102<>Piratas!C3:C102)*(Piratas!C3:C102<>"")))),INDEX(_xlfn._xlws.FILTER(Modular!C3:C101,(Modular!B3:B101<>Modular!C3:C101)*(Modular!C3:C101<>"")),ROW(INDIRECT("1:"&(COUNTA(_xlfn._xlws.FILTER(Piratas!C3:C102,(Piratas!B3:B102<>Piratas!C3:C102)*(Piratas!C3:C102<>"")))+COUNTA(_xlfn._xlws.FILTER(#REF!,(#REF!<>#REF!)*(#REF!<>"")))+COUNTA(_xlfn._xlws.FILTER(Modular!C3:C101,(Modular!B3:B101<>Modular!C3:C101)*(Modular!C3:C101<>""))))))-COUNTA(_xlfn._xlws.FILTER(Piratas!C3:C102,(Piratas!B3:B102<>Piratas!C3:C102)*(Piratas!C3:C102<>"")))-COUNTA(_xlfn._xlws.FILTER(#REF!,(#REF!<>#REF!)*(#REF!<>"")))))),1,-1)))} -> Adagia, Windswept Bastion | BK2: {=IF(COUNTA(_xlfn.ANCHORARRAY($AZ$2))+COUNTA(_xlfn.ANCHORARRAY($BA$2))=0,"",_xlfn._xlws.SORT(_xlfn.UNIQUE(IF(ROW(INDIRECT("1:"&(COUNTA(_xlfn.ANCHORARRAY($AZ$2))+COUNTA(_xlfn.ANCHORARRAY($BA$2)))))<=COUNTA(_xlfn.ANCHORARRAY($AZ$2)),INDEX(_xlfn.ANCHORARRAY($AZ$2),ROW(INDIRECT("1:"&(COUNTA(_xlfn.ANCHORARRAY($AZ$2))+COUNTA(_xlfn.ANCHORARRAY($BA$2)))))),INDEX(_xlfn.ANCHORARRAY($BA$2),ROW(INDIRECT("1:"&(COUNTA(_xlfn.ANCHORARRAY($AZ$2))+COUNTA(_xlfn.ANCHORARRAY($BA$2)))))-COUNTA(_xlfn.ANCHORARRAY($AZ$2))))),1,1))} -> A Joia do Enigma | BL2: {=IF(COUNTA(_xlfn.ANCHORARRAY($BB$2))+COUNTA(_xlfn.ANCHORARRAY($BC$2))=0,"",_xlfn._xlws.SORT(_xlfn.UNIQUE(IF(ROW(INDIRECT("1:"&(COUNTA(_xlfn.ANCHORARRAY($BB$2))+COUNTA(_xlfn.ANCHORARRAY($BC$2)))))<=COUNTA(_xlfn.ANCHORARRAY($BB$2)),INDEX(_xlfn.ANCHORARRAY($BB$2),ROW(INDIRECT("1:"&(COUNTA(_xlfn.ANCHORARRAY($BB$2))+COUNTA(_xlfn.ANCHORARRAY($BC$2)))))),INDEX(_xlfn.ANCHORARRAY($BC$2),ROW(INDIRECT("1:"&(COUNTA(_xlfn.ANCHORARRAY($BB$2))+COUNTA(_xlfn.ANCHORARRAY($BC$2)))))-COUNTA(_xlfn.ANCHORARRAY($BB$2))))),1,1))} -> Adagia, Windswept Bastion | BM2: {=IF(COUNTA(_xlfn.ANCHORARRAY($BD$2))+COUNTA(_xlfn.ANCHORARRAY($BE$2))=0,"",_xlfn._xlws.SORT(_xlfn.UNIQUE(IF(ROW(INDIRECT("1:"&(COUNTA(_xlfn.ANCHORARRAY($BD$2))+COUNTA(_xlfn.ANCHORARRAY($BE$2)))))<=COUNTA(_xlfn.ANCHORARRAY($BD$2)),INDEX(_xlfn.ANCHORARRAY($BD$2),ROW(INDIRECT("1:"&(COUNTA(_xlfn.ANCHORARRAY($BD$2))+COUNTA(_xlfn.ANCHORARRAY($BE$2)))))),INDEX(_xlfn.ANCHORARRAY($BE$2),ROW(INDIRECT("1:"&(COUNTA(_xlfn.ANCHORARRAY($BD$2))+COUNTA(_xlfn.ANCHORARRAY($BE$2)))))-COUNTA(_xlfn.ANCHORARRAY($BD$2))))),1,1))} -> Adagia, Windswept Bastion | BN2: {=IF(COUNTA(_xlfn.ANCHORARRAY($BF$2))+COUNTA(_xlfn.ANCHORARRAY($BG$2))=0,"",_xlfn._xlws.SORT(_xlfn.UNIQUE(IF(ROW(INDIRECT("1:"&(COUNTA(_xlfn.ANCHORARRAY($BF$2))+COUNTA(_xlfn.ANCHORARRAY($BG$2)))))<=COUNTA(_xlfn.ANCHORARRAY($BF$2)),INDEX(_xlfn.ANCHORARRAY($BF$2),ROW(INDIRECT("1:"&(COUNTA(_xlfn.ANCHORARRAY($BF$2))+COUNTA(_xlfn.ANCHORARRAY($BG$2)))))),INDEX(_xlfn.ANCHORARRAY($BG$2),ROW(INDIRECT("1:"&(COUNTA(_xlfn.ANCHORARRAY($BF$2))+COUNTA(_xlfn.ANCHORARRAY($BG$2)))))-COUNTA(_xlfn.ANCHORARRAY($BF$2))))),1,1))} -> Access Tunnel | BO2: {=IF(COUNTA(_xlfn.ANCHORARRAY($BH$2))+COUNTA(_xlfn.ANCHORARRAY($BI$2))=0,"",_xlfn._xlws.SORT(_xlfn.UNIQUE(IF(ROW(INDIRECT("1:"&(COUNTA(_xlfn.ANCHORARRAY($BH$2))+COUNTA(_xlfn.ANCHORARRAY($BI$2)))))<=COUNTA(_xlfn.ANCHORARRAY($BH$2)),INDEX(_xlfn.ANCHORARRAY($BH$2),ROW(INDIRECT("1:"&(COUNTA(_xlfn.ANCHORARRAY($BH$2))+COUNTA(_xlfn.ANCHORARRAY($BI$2)))))),INDEX(_xlfn.ANCHORARRAY($BI$2),ROW(INDIRECT("1:"&(COUNTA(_xlfn.ANCHORARRAY($BH$2))+COUNTA(_xlfn.ANCHORARRAY($BI$2)))))-COUNTA(_xlfn.ANCHORARRAY($BH$2))))),1,1))} -> Adagia, Windswept Bastion | BQ2: {=IF(COUNTA(_xlfn.ANCHORARRAY($BK$2))+COUNTA(_xlfn.ANCHORARRAY($BL$2))=0,"",_xlfn._xlws.SORT(_xlfn.UNIQUE(IF(ROW(INDIRECT("1:"&(COUNTA(_xlfn.ANCHORARRAY($BK$2))+COUNTA(_xlfn.ANCHORARRAY($BL$2)))))<=COUNTA(_xlfn.ANCHORARRAY($BK$2)),INDEX(_xlfn.ANCHORARRAY($BK$2),ROW(INDIRECT("1:"&(COUNTA(_xlfn.ANCHORARRAY($BK$2))+COUNTA(_xlfn.ANCHORARRAY($BL$2)))))),INDEX(_xlfn.ANCHORARRAY($BL$2),ROW(INDIRECT("1:"&(COUNTA(_xlfn.ANCHORARRAY($BK$2))+COUNTA(_xlfn.ANCHORARRAY($BL$2)))))-COUNTA(_xlfn.ANCHORARRAY($BK$2))))),1,1))} -> A Joia do Enigma | BR2: {=IF(COUNTA(_xlfn.ANCHORARRAY($BM$2))+COUNTA(_xlfn.ANCHORARRAY($BN$2))=0,"",_xlfn._xlws.SORT(_xlfn.UNIQUE(IF(ROW(INDIRECT("1:"&(COUNTA(_xlfn.ANCHORARRAY($BM$2))+COUNTA(_xlfn.ANCHORARRAY($BN$2)))))<=COUNTA(_xlfn.ANCHORARRAY($BM$2)),INDEX(_xlfn.ANCHORARRAY($BM$2),ROW(INDIRECT("1:"&(COUNTA(_xlfn.ANCHORARRAY($BM$2))+COUNTA(_xlfn.ANCHORARRAY($BN$2)))))),INDEX(_xlfn.ANCHORARRAY($BN$2),ROW(INDIRECT("1:"&(COUNTA(_xlfn.ANCHORARRAY($BM$2))+COUNTA(_xlfn.ANCHORARRAY($BN$2)))))-COUNTA(_xlfn.ANCHORARRAY($BM$2))))),1,1))} -> Access Tunnel | BT2: {=IF(COUNTA(_xlfn.ANCHORARRAY($BQ$2))+COUNTA(_xlfn.ANCHORARRAY($BR$2))=0,"",_xlfn._xlws.SORT(_xlfn.UNIQUE(IF(ROW(INDIRECT("1:"&(COUNTA(_xlfn.ANCHORARRAY($BQ$2))+COUNTA(_xlfn.ANCHORARRAY($BR$2)))))<=COUNTA(_xlfn.ANCHORARRAY($BQ$2)),INDEX(_xlfn.ANCHORARRAY($BQ$2),ROW(INDIRECT("1:"&(COUNTA(_xlfn.ANCHORARRAY($BQ$2))+COUNTA(_xlfn.ANCHORARRAY($BR$2)))))),INDEX(_xlfn.ANCHORARRAY($BR$2),ROW(INDIRECT("1:"&(COUNTA(_xlfn.ANCHORARRAY($BQ$2))+COUNTA(_xlfn.ANCHORARRAY($BR$2)))))-COUNTA(_xlfn.ANCHORARRAY($BQ$2))))),1,1))} -> A Joia do Enigma
A3: =IFERROR(INDEX($S$3:$S$200, MATCH($C3, $I$3:$I$200, 0)), "") -> 3 | B3: =COUNTIF(U:AX,G3) -> 1 | C3: =IFERROR( INDEX($U$1:$AX$1, MATCH(TRUE, CHOOSE({1;2;3;4;5;6;7;8;9;10;11;12;13;14;15;16;17;18;19;20;21;22;23;24;25;26;27;28;29;30;31;32}, COUNTIFS($U$2:$U$200,$G3)>0, COUNTIFS($V$2:$V$200,$G3)>0, COUNTIFS($W$2:$W$200,$G3)>0, COUNTIFS($X$2:$X$200,$G3)>0, COUNTIFS($Y$2:$Y$200,$G3)>0, COUNTIFS($Z$2:$Z$200,$G3)>0, COUNTIFS($AA$2:$AA$200,$G3)>0, COUNTIFS($AB$2:$AB$200,$G3)>0, COUNTIFS($AC$2:$AC$200,$G3)>0, COUNTIFS($AD$2:$AD$200,$G3)>0, COUNTIFS($AE$2:$AE$200,$G3)>0, COUNTIFS($AF$2:$AF$200,$G3)>0, COUNTIFS($AG$2:$AG$200,$G3)>0, COUNTIFS($AH$2:$AH$200,$G3)>0, COUNTIFS($AI$2:$AI$200,$G3)>0, COUNTIFS($AJ$2:$AJ$200,$G3)>0, COUNTIFS($AK$2:$AK$200,$G3)>0, COUNTIFS($AL$2:$AL$200,$G3)>0, COUNTIFS($AM$2:$AM$200,$G3)>0, COUNTIFS($AN$2:$AN$200,$G3)>0, COUNTIFS($AO$2:$AO$200,$G3)>0, COUNTIFS($AP$2:$AP$200,$G3)>0, COUNTIFS($AQ$2:$AQ$200,$G3)>0, COUNTIFS($AR$2:$AR$200,$G3)>0, COUNTIFS($AS$2:$AS$200,$G3)>0, COUNTIFS($AT$2:$AT$200,$G3)>0, COUNTIFS($AU$2:$AU$200,$G3)>0, COUNTIFS($AV$2:$AV$200,$G3)>0, COUNTIFS($AW$2:$AW$200,$G3)>0, COUNTIFS($AX$2:$AX$200,$G3)>0 ), 0) ), "") -> Muzzio | D3: {=IFERROR( INDEX( _xlfn._xlws.FILTER($U$1:$AX$1, TRANSPOSE( CHOOSE({1;2;3;4;5;6;7;8;9;10;11;12;13;14;15;16;17;18;19;20;21;22;23;24;25;26;27;28;29;30}, COUNTIFS($U$2:$U$200,$G3)>0, COUNTIFS($V$2:$V$200,$G3)>0, COUNTIFS($W$2:$W$200,$G3)>0, COUNTIFS($X$2:$X$200,$G3)>0, COUNTIFS($Y$2:$Y$200,$G3)>0, COUNTIFS($Z$2:$Z$200,$G3)>0, COUNTIFS($AA$2:$AA$200,$G3)>0, COUNTIFS($AB$2:$AB$200,$G3)>0, COUNTIFS($AC$2:$AC$200,$G3)>0, COUNTIFS($AD$2:$AD$200,$G3)>0, COUNTIFS($AE$2:$AE$200,$G3)>0, COUNTIFS($AF$2:$AF$200,$G3)>0, COUNTIFS($AG$2:$AG$200,$G3)>0, COUNTIFS($AH$2:$AH$200,$G3)>0, COUNTIFS($AI$2:$AI$200,$G3)>0, COUNTIFS($AJ$2:$AJ$200,$G3)>0, COUNTIFS($AK$2:$AK$200,$G3)>0, COUNTIFS($AL$2:$AL$200,$G3)>0, COUNTIFS($AM$2:$AM$200,$G3)>0, COUNTIFS($AN$2:$AN$200,$G3)>0, COUNTIFS($AO$2:$AO$200,$G3)>0, COUNTIFS($AP$2:$AP$200,$G3)>0, COUNTIFS($AQ$2:$AQ$200,$G3)>0, COUNTIFS($AR$2:$AR$200,$G3)>0, COUNTIFS($AS$2:$AS$200,$G3)>0, COUNTIFS($AT$2:$AT$200,$G3)>0, COUNTIFS($AU$2:$AU$200,$G3)>0, COUNTIFS($AV$2:$AV$200,$G3)>0, COUNTIFS($AW$2:$AW$200,$G3)>0, COUNTIFS($AX$2:$AX$200,$G3)>0 )), ), 2 ), "")} | E3: {=IFERROR( INDEX( _xlfn._xlws.FILTER($U$1:$AX$1, TRANSPOSE( CHOOSE({1;2;3;4;5;6;7;8;9;10;11;12;13;14;15;16;17;18;19;20;21;22;23;24;25;26;27;28;29;30}, COUNTIFS($U$2:$U$200,$G3)>0, COUNTIFS($V$2:$V$200,$G3)>0, COUNTIFS($W$2:$W$200,$G3)>0, COUNTIFS($X$2:$X$200,$G3)>0, COUNTIFS($Y$2:$Y$200,$G3)>0, COUNTIFS($Z$2:$Z$200,$G3)>0, COUNTIFS($AA$2:$AA$200,$G3)>0, COUNTIFS($AB$2:$AB$200,$G3)>0, COUNTIFS($AC$2:$AC$200,$G3)>0, COUNTIFS($AD$2:$AD$200,$G3)>0, COUNTIFS($AE$2:$AE$200,$G3)>0, COUNTIFS($AF$2:$AF$200,$G3)>0, COUNTIFS($AG$2:$AG$200,$G3)>0, COUNTIFS($AH$2:$AH$200,$G3)>0, COUNTIFS($AI$2:$AI$200,$G3)>0, COUNTIFS($AJ$2:$AJ$200,$G3)>0, COUNTIFS($AK$2:$AK$200,$G3)>0, COUNTIFS($AL$2:$AL$200,$G3)>0, COUNTIFS($AM$2:$AM$200,$G3)>0, COUNTIFS($AN$2:$AN$200,$G3)>0, COUNTIFS($AO$2:$AO$200,$G3)>0, COUNTIFS($AP$2:$AP$200,$G3)>0, COUNTIFS($AQ$2:$AQ$200,$G3)>0, COUNTIFS($AR$2:$AR$200,$G3)>0, COUNTIFS($AS$2:$AS$200,$G3)>0, COUNTIFS($AT$2:$AT$200,$G3)>0, COUNTIFS($AU$2:$AU$200,$G3)>0, COUNTIFS($AV$2:$AV$200,$G3)>0, COUNTIFS($AW$2:$AW$200,$G3)>0, COUNTIFS($AX$2:$AX$200,$G3)>0 )), ), 3 ), "")} | F3: {=IFERROR( INDEX( _xlfn._xlws.FILTER($U$1:$AX$1, TRANSPOSE( CHOOSE({1;2;3;4;5;6;7;8;9;10;11;12;13;14;15;16;17;18;19;20;21;22;23;24;25;26;27;28;29;30}, COUNTIFS($U$2:$U$200,$G3)>0, COUNTIFS($V$2:$V$200,$G3)>0, COUNTIFS($W$2:$W$200,$G3)>0, COUNTIFS($X$2:$X$200,$G3)>0, COUNTIFS($Y$2:$Y$200,$G3)>0, COUNTIFS($Z$2:$Z$200,$G3)>0, COUNTIFS($AA$2:$AA$200,$G3)>0, COUNTIFS($AB$2:$AB$200,$G3)>0, COUNTIFS($AC$2:$AC$200,$G3)>0, COUNTIFS($AD$2:$AD$200,$G3)>0, COUNTIFS($AE$2:$AE$200,$G3)>0, COUNTIFS($AF$2:$AF$200,$G3)>0, COUNTIFS($AG$2:$AG$200,$G3)>0, COUNTIFS($AH$2:$AH$200,$G3)>0, COUNTIFS($AI$2:$AI$200,$G3)>0, COUNTIFS($AJ$2:$AJ$200,$G3)>0, COUNTIFS($AK$2:$AK$200,$G3)>0, COUNTIFS($AL$2:$AL$200,$G3)>0, COUNTIFS($AM$2:$AM$200,$G3)>0, COUNTIFS($AN$2:$AN$200,$G3)>0, COUNTIFS($AO$2:$AO$200,$G3)>0, COUNTIFS($AP$2:$AP$200,$G3)>0, COUNTIFS($AQ$2:$AQ$200,$G3)>0, COUNTIFS($AR$2:$AR$200,$G3)>0, COUNTIFS($AS$2:$AS$200,$G3)>0, COUNTIFS($AT$2:$AT$200,$G3)>0, COUNTIFS($AU$2:$AU$200,$G3)>0, COUNTIFS($AV$2:$AV$200,$G3)>0, COUNTIFS($AW$2:$AW$200,$G3)>0, COUNTIFS($AX$2:$AX$200,$G3)>0 )), ), 4 ), "")} | G3: Academy Ruins | I3: Narset | J3: =Narset!G2 -> 30 | K3: Sim | L3: Sim | M3: Sim | N3: Não | O3: Não | P3: Mill | Q3: Combate | R3: Mill e Tokens | S3: =IF(J3<6,"5",IF(J3<11,"4",IF(J3<16,"3",IF(J3<31,"2","1")))) -> 2 | U3: Bident of Thassa | V3: Aura Mutation | W3: Aligned Heart | X3: Arwen, Weaver of Hope | Y3: Autoridade dos Cônsules | Z3: Bojuka Bog | AA3: Call to the Kindred | AB3: Bloodstained Mire | AC3: Kozilek, the Broken Reality | AD3: Broodheart Engine | AE3: Academy Ruins | AF3: Arid Mesa | AG3: Drowned Catacomb | AH3: Bojuka Bog | AI3: Cloud, Midgar Mercenary | AJ3: Elspeth, Sun's Champion | AK3: Obelisco de Obsidiana | AL3: Dionus, Elvish Archdruid | AM3: Mistrise Village | AN3: Jetmir's Garden | AO3: Baral, Chief of Compliance | AP3: Jidoor, Aristocratic Capital // Overture | AQ3: Chandra's Ignition | AR3: Daretti, Ingenious Iconoclast | AS3: Illustrious Wanderglyph | AT3: Lagoa Espelhada | AU3: Teyo, Geometric Tactician | AV3: Emergency Eject | AX3: Ancient Den | AZ3: Ancient Tomb | BA3: Academy Ruins | BB3: Afundar em Estupor | BC3: Árbitro Silencioso | BD3: Ascensão do Avernus | BE3: Bugenhagen, Wise Elder | BF3: Bojuka Bog | BG3: Aligned Heart | BH3: Artifact Mutation | BI3: Ancient Den | BK3: Academy Ruins | BL3: Afundar em Estupor | BM3: Arcane Lighthouse | BN3: Adarkar Wastes | BO3: Ancient Den | BQ3: Academy Ruins | BR3: Adagia, Windswept Bastion | BT3: Academy Ruins
A4: =IFERROR(INDEX($S$3:$S$200, MATCH($C4, $I$3:$I$200, 0)), "") -> 2 | B4: =COUNTIF(U:AX,G4) -> 1 | C4: =IFERROR( INDEX($U$1:$AX$1, MATCH(TRUE, CHOOSE({1;2;3;4;5;6;7;8;9;10;11;12;13;14;15;16;17;18;19;20;21;22;23;24;25;26;27;28;29;30;31;32}, COUNTIFS($U$2:$U$200,$G4)>0, COUNTIFS($V$2:$V$200,$G4)>0, COUNTIFS($W$2:$W$200,$G4)>0, COUNTIFS($X$2:$X$200,$G4)>0, COUNTIFS($Y$2:$Y$200,$G4)>0, COUNTIFS($Z$2:$Z$200,$G4)>0, COUNTIFS($AA$2:$AA$200,$G4)>0, COUNTIFS($AB$2:$AB$200,$G4)>0, COUNTIFS($AC$2:$AC$200,$G4)>0, COUNTIFS($AD$2:$AD$200,$G4)>0, COUNTIFS($AE$2:$AE$200,$G4)>0, COUNTIFS($AF$2:$AF$200,$G4)>0, COUNTIFS($AG$2:$AG$200,$G4)>0, COUNTIFS($AH$2:$AH$200,$G4)>0, COUNTIFS($AI$2:$AI$200,$G4)>0, COUNTIFS($AJ$2:$AJ$200,$G4)>0, COUNTIFS($AK$2:$AK$200,$G4)>0, COUNTIFS($AL$2:$AL$200,$G4)>0, COUNTIFS($AM$2:$AM$200,$G4)>0, COUNTIFS($AN$2:$AN$200,$G4)>0, COUNTIFS($AO$2:$AO$200,$G4)>0, COUNTIFS($AP$2:$AP$200,$G4)>0, COUNTIFS($AQ$2:$AQ$200,$G4)>0, COUNTIFS($AR$2:$AR$200,$G4)>0, COUNTIFS($AS$2:$AS$200,$G4)>0, COUNTIFS($AT$2:$AT$200,$G4)>0, COUNTIFS($AU$2:$AU$200,$G4)>0, COUNTIFS($AV$2:$AV$200,$G4)>0, COUNTIFS($AW$2:$AW$200,$G4)>0, COUNTIFS($AX$2:$AX$200,$G4)>0 ), 0) ), "") -> Rani | D4: {=IFERROR( INDEX( _xlfn._xlws.FILTER($U$1:$AX$1, TRANSPOSE( CHOOSE({1;2;3;4;5;6;7;8;9;10;11;12;13;14;15;16;17;18;19;20;21;22;23;24;25;26;27;28;29;30}, COUNTIFS($U$2:$U$200,$G4)>0, COUNTIFS($V$2:$V$200,$G4)>0, COUNTIFS($W$2:$W$200,$G4)>0, COUNTIFS($X$2:$X$200,$G4)>0, COUNTIFS($Y$2:$Y$200,$G4)>0, COUNTIFS($Z$2:$Z$200,$G4)>0, COUNTIFS($AA$2:$AA$200,$G4)>0, COUNTIFS($AB$2:$AB$200,$G4)>0, COUNTIFS($AC$2:$AC$200,$G4)>0, COUNTIFS($AD$2:$AD$200,$G4)>0, COUNTIFS($AE$2:$AE$200,$G4)>0, COUNTIFS($AF$2:$AF$200,$G4)>0, COUNTIFS($AG$2:$AG$200,$G4)>0, COUNTIFS($AH$2:$AH$200,$G4)>0, COUNTIFS($AI$2:$AI$200,$G4)>0, COUNTIFS($AJ$2:$AJ$200,$G4)>0, COUNTIFS($AK$2:$AK$200,$G4)>0, COUNTIFS($AL$2:$AL$200,$G4)>0, COUNTIFS($AM$2:$AM$200,$G4)>0, COUNTIFS($AN$2:$AN$200,$G4)>0, COUNTIFS($AO$2:$AO$200,$G4)>0, COUNTIFS($AP$2:$AP$200,$G4)>0, COUNTIFS($AQ$2:$AQ$200,$G4)>0, COUNTIFS($AR$2:$AR$200,$G4)>0, COUNTIFS($AS$2:$AS$200,$G4)>0, COUNTIFS($AT$2:$AT$200,$G4)>0, COUNTIFS($AU$2:$AU$200,$G4)>0, COUNTIFS($AV$2:$AV$200,$G4)>0, COUNTIFS($AW$2:$AW$200,$G4)>0, COUNTIFS($AX$2:$AX$200,$G4)>0 )), ), 2 ), "")} | E4: {=IFERROR( INDEX( _xlfn._xlws.FILTER($U$1:$AX$1, TRANSPOSE( CHOOSE({1;2;3;4;5;6;7;8;9;10;11;12;13;14;15;16;17;18;19;20;21;22;23;24;25;26;27;28;29;30}, COUNTIFS($U$2:$U$200,$G4)>0, COUNTIFS($V$2:$V$200,$G4)>0, COUNTIFS($W$2:$W$200,$G4)>0, COUNTIFS($X$2:$X$200,$G4)>0, COUNTIFS($Y$2:$Y$200,$G4)>0, COUNTIFS($Z$2:$Z$200,$G4)>0, COUNTIFS($AA$2:$AA$200,$G4)>0, COUNTIFS($AB$2:$AB$200,$G4)>0, COUNTIFS($AC$2:$AC$200,$G4)>0, COUNTIFS($AD$2:$AD$200,$G4)>0, COUNTIFS($AE$2:$AE$200,$G4)>0, COUNTIFS($AF$2:$AF$200,$G4)>0, COUNTIFS($AG$2:$AG$200,$G4)>0, COUNTIFS($AH$2:$AH$200,$G4)>0, COUNTIFS($AI$2:$AI$200,$G4)>0, COUNTIFS($AJ$2:$AJ$200,$G4)>0, COUNTIFS($AK$2:$AK$200,$G4)>0, COUNTIFS($AL$2:$AL$200,$G4)>0, COUNTIFS($AM$2:$AM$200,$G4)>0, COUNTIFS($AN$2:$AN$200,$G4)>0, COUNTIFS($AO$2:$AO$200,$G4)>0, COUNTIFS($AP$2:$AP$200,$G4)>0, COUNTIFS($AQ$2:$AQ$200,$G4)>0, COUNTIFS($AR$2:$AR$200,$G4)>0, COUNTIFS($AS$2:$AS$200,$G4)>0, COUNTIFS($AT$2:$AT$200,$G4)>0, COUNTIFS($AU$2:$AU$200,$G4)>0, COUNTIFS($AV$2:$AV$200,$G4)>0, COUNTIFS($AW$2:$AW$200,$G4)>0, COUNTIFS($AX$2:$AX$200,$G4)>0 )), ), 3 ), "")} | F4: {=IFERROR( INDEX( _xlfn._xlws.FILTER($U$1:$AX$1, TRANSPOSE( CHOOSE({1;2;3;4;5;6;7;8;9;10;11;12;13;14;15;16;17;18;19;20;21;22;23;24;25;26;27;28;29;30}, COUNTIFS($U$2:$U$200,$G4)>0, COUNTIFS($V$2:$V$200,$G4)>0, COUNTIFS($W$2:$W$200,$G4)>0, COUNTIFS($X$2:$X$200,$G4)>0, COUNTIFS($Y$2:$Y$200,$G4)>0, COUNTIFS($Z$2:$Z$200,$G4)>0, COUNTIFS($AA$2:$AA$200,$G4)>0, COUNTIFS($AB$2:$AB$200,$G4)>0, COUNTIFS($AC$2:$AC$200,$G4)>0, COUNTIFS($AD$2:$AD$200,$G4)>0, COUNTIFS($AE$2:$AE$200,$G4)>0, COUNTIFS($AF$2:$AF$200,$G4)>0, COUNTIFS($AG$2:$AG$200,$G4)>0, COUNTIFS($AH$2:$AH$200,$G4)>0, COUNTIFS($AI$2:$AI$200,$G4)>0, COUNTIFS($AJ$2:$AJ$200,$G4)>0, COUNTIFS($AK$2:$AK$200,$G4)>0, COUNTIFS($AL$2:$AL$200,$G4)>0, COUNTIFS($AM$2:$AM$200,$G4)>0, COUNTIFS($AN$2:$AN$200,$G4)>0, COUNTIFS($AO$2:$AO$200,$G4)>0, COUNTIFS($AP$2:$AP$200,$G4)>0, COUNTIFS($AQ$2:$AQ$200,$G4)>0, COUNTIFS($AR$2:$AR$200,$G4)>0, COUNTIFS($AS$2:$AS$200,$G4)>0, COUNTIFS($AT$2:$AT$200,$G4)>0, COUNTIFS($AU$2:$AU$200,$G4)>0, COUNTIFS($AV$2:$AV$200,$G4)>0, COUNTIFS($AW$2:$AW$200,$G4)>0, COUNTIFS($AX$2:$AX$200,$G4)>0 )), ), 4 ), "")} | G4: Access Tunnel | I4: Baylen | J4: =Baylen!G2 -> 31 | K4: Sim | L4: Não | M4: Sim | N4: Não | O4: Sim | P4: Voltron | Q4: Combate | R4: Muitos Tokens | S4: =IF(J4<6,"5",IF(J4<11,"4",IF(J4<16,"3",IF(J4<31,"2","1")))) -> 1 | U4: Bojuka Bog | V4: Boros Charm | W4: Clifftop Retreat | X4: Branching Evolution | Y4: Bojuka Bog | Z4: Counterspell | AA4: Deeproot Historian | AB4: Fabled Passage | AC4: Mistrise Village | AD4: Crisol dos Mundos | AE4: Chimil, o Sol Interior | AF4: Batwing Brume | AG4: Faerie Slumber Party | AH4: Burnt Offering | AI4: Espada da Riqueza e do Poder | AJ4: Freyalise, Llanowar's Fury | AK4: Shaku da Honra Desgastada | AL4: Evendo, Waking Haven | AM4: Planetary Annihilation | AN4: Raffine's Tower | AO4: Careful Study | AP4: Scour for Scrap | AQ4: High-Society Hunter | AR4: Reflecting Pool | AS4: Scattered Groves | AT4: Olho de Ojer Taq | AV4: Homeward Path | AX4: Annie Joins Up | AZ4: Broodheart Engine | BA4: Caverna das Almas | BB4: Alchemist's Refuge | BC4: Arid Mesa | BD4: Autoridade dos Cônsules | BE4: Chandra's Ignition | BF4: Commodore Guff | BG4: Ancient Greenwarden | BH4: Arwen, Weaver of Hope | BI4: Annie Joins Up | BK4: Alchemist's Refuge | BL4: Alchemist's Refuge | BM4: Ascensão do Avernus | BN4: Aligned Heart | BO4: Annie Joins Up | BQ4: Adagia, Windswept Bastion | BR4: Adarkar Wastes | BT4: Access Tunnel
A5: =IFERROR(INDEX($S$3:$S$200, MATCH($C5, $I$3:$I$200, 0)), "") -> 5 | B5: =COUNTIF(U:AX,G5) -> 3 | C5: =IFERROR( INDEX($U$1:$AX$1, MATCH(TRUE, CHOOSE({1;2;3;4;5;6;7;8;9;10;11;12;13;14;15;16;17;18;19;20;21;22;23;24;25;26;27;28;29;30;31;32}, COUNTIFS($U$2:$U$200,$G5)>0, COUNTIFS($V$2:$V$200,$G5)>0, COUNTIFS($W$2:$W$200,$G5)>0, COUNTIFS($X$2:$X$200,$G5)>0, COUNTIFS($Y$2:$Y$200,$G5)>0, COUNTIFS($Z$2:$Z$200,$G5)>0, COUNTIFS($AA$2:$AA$200,$G5)>0, COUNTIFS($AB$2:$AB$200,$G5)>0, COUNTIFS($AC$2:$AC$200,$G5)>0, COUNTIFS($AD$2:$AD$200,$G5)>0, COUNTIFS($AE$2:$AE$200,$G5)>0, COUNTIFS($AF$2:$AF$200,$G5)>0, COUNTIFS($AG$2:$AG$200,$G5)>0, COUNTIFS($AH$2:$AH$200,$G5)>0, COUNTIFS($AI$2:$AI$200,$G5)>0, COUNTIFS($AJ$2:$AJ$200,$G5)>0, COUNTIFS($AK$2:$AK$200,$G5)>0, COUNTIFS($AL$2:$AL$200,$G5)>0, COUNTIFS($AM$2:$AM$200,$G5)>0, COUNTIFS($AN$2:$AN$200,$G5)>0, COUNTIFS($AO$2:$AO$200,$G5)>0, COUNTIFS($AP$2:$AP$200,$G5)>0, COUNTIFS($AQ$2:$AQ$200,$G5)>0, COUNTIFS($AR$2:$AR$200,$G5)>0, COUNTIFS($AS$2:$AS$200,$G5)>0, COUNTIFS($AT$2:$AT$200,$G5)>0, COUNTIFS($AU$2:$AU$200,$G5)>0, COUNTIFS($AV$2:$AV$200,$G5)>0, COUNTIFS($AW$2:$AW$200,$G5)>0, COUNTIFS($AX$2:$AX$200,$G5)>0 ), 0) ), "") -> Breya | D5: {=IFERROR( INDEX( _xlfn._xlws.FILTER($U$1:$AX$1, TRANSPOSE( CHOOSE({1;2;3;4;5;6;7;8;9;10;11;12;13;14;15;16;17;18;19;20;21;22;23;24;25;26;27;28;29;30}, COUNTIFS($U$2:$U$200,$G5)>0, COUNTIFS($V$2:$V$200,$G5)>0, COUNTIFS($W$2:$W$200,$G5)>0, COUNTIFS($X$2:$X$200,$G5)>0, COUNTIFS($Y$2:$Y$200,$G5)>0, COUNTIFS($Z$2:$Z$200,$G5)>0, COUNTIFS($AA$2:$AA$200,$G5)>0, COUNTIFS($AB$2:$AB$200,$G5)>0, COUNTIFS($AC$2:$AC$200,$G5)>0, COUNTIFS($AD$2:$AD$200,$G5)>0, COUNTIFS($AE$2:$AE$200,$G5)>0, COUNTIFS($AF$2:$AF$200,$G5)>0, COUNTIFS($AG$2:$AG$200,$G5)>0, COUNTIFS($AH$2:$AH$200,$G5)>0, COUNTIFS($AI$2:$AI$200,$G5)>0, COUNTIFS($AJ$2:$AJ$200,$G5)>0, COUNTIFS($AK$2:$AK$200,$G5)>0, COUNTIFS($AL$2:$AL$200,$G5)>0, COUNTIFS($AM$2:$AM$200,$G5)>0, COUNTIFS($AN$2:$AN$200,$G5)>0, COUNTIFS($AO$2:$AO$200,$G5)>0, COUNTIFS($AP$2:$AP$200,$G5)>0, COUNTIFS($AQ$2:$AQ$200,$G5)>0, COUNTIFS($AR$2:$AR$200,$G5)>0, COUNTIFS($AS$2:$AS$200,$G5)>0, COUNTIFS($AT$2:$AT$200,$G5)>0, COUNTIFS($AU$2:$AU$200,$G5)>0, COUNTIFS($AV$2:$AV$200,$G5)>0, COUNTIFS($AW$2:$AW$200,$G5)>0, COUNTIFS($AX$2:$AX$200,$G5)>0 )), ), 2 ), "")} -> Alela | E5: {=IFERROR( INDEX( _xlfn._xlws.FILTER($U$1:$AX$1, TRANSPOSE( CHOOSE({1;2;3;4;5;6;7;8;9;10;11;12;13;14;15;16;17;18;19;20;21;22;23;24;25;26;27;28;29;30}, COUNTIFS($U$2:$U$200,$G5)>0, COUNTIFS($V$2:$V$200,$G5)>0, COUNTIFS($W$2:$W$200,$G5)>0, COUNTIFS($X$2:$X$200,$G5)>0, COUNTIFS($Y$2:$Y$200,$G5)>0, COUNTIFS($Z$2:$Z$200,$G5)>0, COUNTIFS($AA$2:$AA$200,$G5)>0, COUNTIFS($AB$2:$AB$200,$G5)>0, COUNTIFS($AC$2:$AC$200,$G5)>0, COUNTIFS($AD$2:$AD$200,$G5)>0, COUNTIFS($AE$2:$AE$200,$G5)>0, COUNTIFS($AF$2:$AF$200,$G5)>0, COUNTIFS($AG$2:$AG$200,$G5)>0, COUNTIFS($AH$2:$AH$200,$G5)>0, COUNTIFS($AI$2:$AI$200,$G5)>0, COUNTIFS($AJ$2:$AJ$200,$G5)>0, COUNTIFS($AK$2:$AK$200,$G5)>0, COUNTIFS($AL$2:$AL$200,$G5)>0, COUNTIFS($AM$2:$AM$200,$G5)>0, COUNTIFS($AN$2:$AN$200,$G5)>0, COUNTIFS($AO$2:$AO$200,$G5)>0, COUNTIFS($AP$2:$AP$200,$G5)>0, COUNTIFS($AQ$2:$AQ$200,$G5)>0, COUNTIFS($AR$2:$AR$200,$G5)>0, COUNTIFS($AS$2:$AS$200,$G5)>0, COUNTIFS($AT$2:$AT$200,$G5)>0, COUNTIFS($AU$2:$AU$200,$G5)>0, COUNTIFS($AV$2:$AV$200,$G5)>0, COUNTIFS($AW$2:$AW$200,$G5)>0, COUNTIFS($AX$2:$AX$200,$G5)>0 )), ), 3 ), "")} -> Modular | F5: {=IFERROR( INDEX( _xlfn._xlws.FILTER($U$1:$AX$1, TRANSPOSE( CHOOSE({1;2;3;4;5;6;7;8;9;10;11;12;13;14;15;16;17;18;19;20;21;22;23;24;25;26;27;28;29;30}, COUNTIFS($U$2:$U$200,$G5)>0, COUNTIFS($V$2:$V$200,$G5)>0, COUNTIFS($W$2:$W$200,$G5)>0, COUNTIFS($X$2:$X$200,$G5)>0, COUNTIFS($Y$2:$Y$200,$G5)>0, COUNTIFS($Z$2:$Z$200,$G5)>0, COUNTIFS($AA$2:$AA$200,$G5)>0, COUNTIFS($AB$2:$AB$200,$G5)>0, COUNTIFS($AC$2:$AC$200,$G5)>0, COUNTIFS($AD$2:$AD$200,$G5)>0, COUNTIFS($AE$2:$AE$200,$G5)>0, COUNTIFS($AF$2:$AF$200,$G5)>0, COUNTIFS($AG$2:$AG$200,$G5)>0, COUNTIFS($AH$2:$AH$200,$G5)>0, COUNTIFS($AI$2:$AI$200,$G5)>0, COUNTIFS($AJ$2:$AJ$200,$G5)>0, COUNTIFS($AK$2:$AK$200,$G5)>0, COUNTIFS($AL$2:$AL$200,$G5)>0, COUNTIFS($AM$2:$AM$200,$G5)>0, COUNTIFS($AN$2:$AN$200,$G5)>0, COUNTIFS($AO$2:$AO$200,$G5)>0, COUNTIFS($AP$2:$AP$200,$G5)>0, COUNTIFS($AQ$2:$AQ$200,$G5)>0, COUNTIFS($AR$2:$AR$200,$G5)>0, COUNTIFS($AS$2:$AS$200,$G5)>0, COUNTIFS($AT$2:$AT$200,$G5)>0, COUNTIFS($AU$2:$AU$200,$G5)>0, COUNTIFS($AV$2:$AV$200,$G5)>0, COUNTIFS($AW$2:$AW$200,$G5)>0, COUNTIFS($AX$2:$AX$200,$G5)>0 )), ), 4 ), "")} | G5: Adagia, Windswept Bastion | I5: Tayam | J5: =Tayam!G2 -> 41 | K5: Sim | L5: Não | M5: Não | N5: Sim | O5: Sim | P5: Combate | Q5: Combo | R5: Counters, tudo drop 3- | S5: =IF(J5<6,"5",IF(J5<11,"4",IF(J5<16,"3",IF(J5<31,"2","1")))) -> 1 | U5: Broadside Bombardiers | V5: Brushland | W5: Full Throttle | X5: Bulwark Ox | Y5: Enduring Innocence | Z5: Cyber Conversion | AA5: Harvest Season | AB5: Grave Pact | AC5: Mox Tantalite | AD5: Delighted Halfling | AE5: Extinguisher Battleship | AF5: Chronomantic Escape | AG5: Louisoix's Sacrifice | AH5: Diário de Tarrian | AI5: Espada de Banquete e Fome | AJ5: Karn Liberated | AK5: Uthros, Titanic Godcore | AL5: Nissa, Resurgent Animist | AM5: Ulamog, o Profanador | AN5: Sliver Gravemother | AO5: Collector's Vault | AP5: Season of Weaving | AQ5: Jenova, Ancient Calamity | AS5: Stridehangar Automaton | AT5: Renewed Solidarity | AX5: Arcane Signet | AZ5: Crisol dos Mundos | BA5: Chimil, o Sol Interior | BB5: Baral, Chief of Compliance | BC5: Batwing Brume | BD5: Bojuka Bog | BE5: Cid, Freeflier Pilot | BF5: Counterspell | BG5: Beast Within | BH5: Aura Mutation | BI5: Arcane Signet | BK5: Ancient Tomb | BL5: Amphibian Downpour | BM5: Autoridade dos Cônsules | BN5: Ancient Greenwarden | BO5: Arcane Signet | BQ5: Afundar em Estupor | BR5: Aligned Heart | BT5: Adagia, Windswept Bastion
A6: =IFERROR(INDEX($S$3:$S$200, MATCH($C6, $I$3:$I$200, 0)), "") -> 2 | B6: =COUNTIF(U:AX,G6) -> 1 | C6: =IFERROR( INDEX($U$1:$AX$1, MATCH(TRUE, CHOOSE({1;2;3;4;5;6;7;8;9;10;11;12;13;14;15;16;17;18;19;20;21;22;23;24;25;26;27;28;29;30;31;32}, COUNTIFS($U$2:$U$200,$G6)>0, COUNTIFS($V$2:$V$200,$G6)>0, COUNTIFS($W$2:$W$200,$G6)>0, COUNTIFS($X$2:$X$200,$G6)>0, COUNTIFS($Y$2:$Y$200,$G6)>0, COUNTIFS($Z$2:$Z$200,$G6)>0, COUNTIFS($AA$2:$AA$200,$G6)>0, COUNTIFS($AB$2:$AB$200,$G6)>0, COUNTIFS($AC$2:$AC$200,$G6)>0, COUNTIFS($AD$2:$AD$200,$G6)>0, COUNTIFS($AE$2:$AE$200,$G6)>0, COUNTIFS($AF$2:$AF$200,$G6)>0, COUNTIFS($AG$2:$AG$200,$G6)>0, COUNTIFS($AH$2:$AH$200,$G6)>0, COUNTIFS($AI$2:$AI$200,$G6)>0, COUNTIFS($AJ$2:$AJ$200,$G6)>0, COUNTIFS($AK$2:$AK$200,$G6)>0, COUNTIFS($AL$2:$AL$200,$G6)>0, COUNTIFS($AM$2:$AM$200,$G6)>0, COUNTIFS($AN$2:$AN$200,$G6)>0, COUNTIFS($AO$2:$AO$200,$G6)>0, COUNTIFS($AP$2:$AP$200,$G6)>0, COUNTIFS($AQ$2:$AQ$200,$G6)>0, COUNTIFS($AR$2:$AR$200,$G6)>0, COUNTIFS($AS$2:$AS$200,$G6)>0, COUNTIFS($AT$2:$AT$200,$G6)>0, COUNTIFS($AU$2:$AU$200,$G6)>0, COUNTIFS($AV$2:$AV$200,$G6)>0, COUNTIFS($AW$2:$AW$200,$G6)>0, COUNTIFS($AX$2:$AX$200,$G6)>0 ), 0) ), "") -> Narset | D6: {=IFERROR( INDEX( _xlfn._xlws.FILTER($U$1:$AX$1, TRANSPOSE( CHOOSE({1;2;3;4;5;6;7;8;9;10;11;12;13;14;15;16;17;18;19;20;21;22;23;24;25;26;27;28;29;30}, COUNTIFS($U$2:$U$200,$G6)>0, COUNTIFS($V$2:$V$200,$G6)>0, COUNTIFS($W$2:$W$200,$G6)>0, COUNTIFS($X$2:$X$200,$G6)>0, COUNTIFS($Y$2:$Y$200,$G6)>0, COUNTIFS($Z$2:$Z$200,$G6)>0, COUNTIFS($AA$2:$AA$200,$G6)>0, COUNTIFS($AB$2:$AB$200,$G6)>0, COUNTIFS($AC$2:$AC$200,$G6)>0, COUNTIFS($AD$2:$AD$200,$G6)>0, COUNTIFS($AE$2:$AE$200,$G6)>0, COUNTIFS($AF$2:$AF$200,$G6)>0, COUNTIFS($AG$2:$AG$200,$G6)>0, COUNTIFS($AH$2:$AH$200,$G6)>0, COUNTIFS($AI$2:$AI$200,$G6)>0, COUNTIFS($AJ$2:$AJ$200,$G6)>0, COUNTIFS($AK$2:$AK$200,$G6)>0, COUNTIFS($AL$2:$AL$200,$G6)>0, COUNTIFS($AM$2:$AM$200,$G6)>0, COUNTIFS($AN$2:$AN$200,$G6)>0, COUNTIFS($AO$2:$AO$200,$G6)>0, COUNTIFS($AP$2:$AP$200,$G6)>0, COUNTIFS($AQ$2:$AQ$200,$G6)>0, COUNTIFS($AR$2:$AR$200,$G6)>0, COUNTIFS($AS$2:$AS$200,$G6)>0, COUNTIFS($AT$2:$AT$200,$G6)>0, COUNTIFS($AU$2:$AU$200,$G6)>0, COUNTIFS($AV$2:$AV$200,$G6)>0, COUNTIFS($AW$2:$AW$200,$G6)>0, COUNTIFS($AX$2:$AX$200,$G6)>0 )), ), 2 ), "")} | E6: {=IFERROR( INDEX( _xlfn._xlws.FILTER($U$1:$AX$1, TRANSPOSE( CHOOSE({1;2;3;4;5;6;7;8;9;10;11;12;13;14;15;16;17;18;19;20;21;22;23;24;25;26;27;28;29;30}, COUNTIFS($U$2:$U$200,$G6)>0, COUNTIFS($V$2:$V$200,$G6)>0, COUNTIFS($W$2:$W$200,$G6)>0, COUNTIFS($X$2:$X$200,$G6)>0, COUNTIFS($Y$2:$Y$200,$G6)>0, COUNTIFS($Z$2:$Z$200,$G6)>0, COUNTIFS($AA$2:$AA$200,$G6)>0, COUNTIFS($AB$2:$AB$200,$G6)>0, COUNTIFS($AC$2:$AC$200,$G6)>0, COUNTIFS($AD$2:$AD$200,$G6)>0, COUNTIFS($AE$2:$AE$200,$G6)>0, COUNTIFS($AF$2:$AF$200,$G6)>0, COUNTIFS($AG$2:$AG$200,$G6)>0, COUNTIFS($AH$2:$AH$200,$G6)>0, COUNTIFS($AI$2:$AI$200,$G6)>0, COUNTIFS($AJ$2:$AJ$200,$G6)>0, COUNTIFS($AK$2:$AK$200,$G6)>0, COUNTIFS($AL$2:$AL$200,$G6)>0, COUNTIFS($AM$2:$AM$200,$G6)>0, COUNTIFS($AN$2:$AN$200,$G6)>0, COUNTIFS($AO$2:$AO$200,$G6)>0, COUNTIFS($AP$2:$AP$200,$G6)>0, COUNTIFS($AQ$2:$AQ$200,$G6)>0, COUNTIFS($AR$2:$AR$200,$G6)>0, COUNTIFS($AS$2:$AS$200,$G6)>0, COUNTIFS($AT$2:$AT$200,$G6)>0, COUNTIFS($AU$2:$AU$200,$G6)>0, COUNTIFS($AV$2:$AV$200,$G6)>0, COUNTIFS($AW$2:$AW$200,$G6)>0, COUNTIFS($AX$2:$AX$200,$G6)>0 )), ), 3 ), "")} | F6: {=IFERROR( INDEX( _xlfn._xlws.FILTER($U$1:$AX$1, TRANSPOSE( CHOOSE({1;2;3;4;5;6;7;8;9;10;11;12;13;14;15;16;17;18;19;20;21;22;23;24;25;26;27;28;29;30}, COUNTIFS($U$2:$U$200,$G6)>0, COUNTIFS($V$2:$V$200,$G6)>0, COUNTIFS($W$2:$W$200,$G6)>0, COUNTIFS($X$2:$X$200,$G6)>0, COUNTIFS($Y$2:$Y$200,$G6)>0, COUNTIFS($Z$2:$Z$200,$G6)>0, COUNTIFS($AA$2:$AA$200,$G6)>0, COUNTIFS($AB$2:$AB$200,$G6)>0, COUNTIFS($AC$2:$AC$200,$G6)>0, COUNTIFS($AD$2:$AD$200,$G6)>0, COUNTIFS($AE$2:$AE$200,$G6)>0, COUNTIFS($AF$2:$AF$200,$G6)>0, COUNTIFS($AG$2:$AG$200,$G6)>0, COUNTIFS($AH$2:$AH$200,$G6)>0, COUNTIFS($AI$2:$AI$200,$G6)>0, COUNTIFS($AJ$2:$AJ$200,$G6)>0, COUNTIFS($AK$2:$AK$200,$G6)>0, COUNTIFS($AL$2:$AL$200,$G6)>0, COUNTIFS($AM$2:$AM$200,$G6)>0, COUNTIFS($AN$2:$AN$200,$G6)>0, COUNTIFS($AO$2:$AO$200,$G6)>0, COUNTIFS($AP$2:$AP$200,$G6)>0, COUNTIFS($AQ$2:$AQ$200,$G6)>0, COUNTIFS($AR$2:$AR$200,$G6)>0, COUNTIFS($AS$2:$AS$200,$G6)>0, COUNTIFS($AT$2:$AT$200,$G6)>0, COUNTIFS($AU$2:$AU$200,$G6)>0, COUNTIFS($AV$2:$AV$200,$G6)>0, COUNTIFS($AW$2:$AW$200,$G6)>0, COUNTIFS($AX$2:$AX$200,$G6)>0 )), ), 4 ), "")} | G6: Adarkar Wastes | I6: Piratas | J6: =Piratas!G2 -> 28 | K6: Não | L6: Sim | M6: Sim | N6: Sim | O6: Não | P6: Combate | Q6: Combo | R6: Tesouros e Roubos | S6: =IF(J6<6,"5",IF(J6<11,"4",IF(J6<16,"3",IF(J6<31,"2","1")))) -> 2 | U6: Coastline Marauders | V6: Canopy Vista | W6: Genji Glove | X6: Cankerbloom | Y6: Exemplar of Light | Z6: Drowned Catacomb | AA6: Herald of Secret Streams | AB6: Horizon Explorer | AC6: Rise of the Eldrazi | AD6: Entomb | AE6: Gerrard's Hourglass Pendant | AF6: Luxury Suite | AG6: Morphic Pool | AH6: Dour Port-Mage | AI6: Espada de Fogo e Gelo | AJ6: Kaya the Inexorable | AL6: Three Tree City | AM6: Valfenda | AN6: Thrumming Hivepool | AO6: Ojer Pakpatiq, Era Profunda | AP6: Sonic Screwdriver | AQ6: Nibelheim Aflame | AS6: Susur Secundi, Void Altar | AT6: Westvale Abbey | AX6: Arcbound Crusher | AZ6: Delighted Halfling | BA6: Emrakul, um Novo Mundo | BB6: Careful Study | BC6: Chronomantic Escape | BD6: Bojuka Bog | BE6: Cloud, Midgar Mercenary | BF6: Cyber Conversion | BG6: Bloodstained Mire | BH6: Boros Charm | BI6: Arcbound Crusher | BK6: Broodheart Engine | BL6: Árbitro Silencioso | BM6: Bojuka Bog | BN6: Beast Within | BO6: Arcbound Crusher | BQ6: Alchemist's Refuge | BR6: Ancient Greenwarden | BT6: Adarkar Wastes
A7: =IFERROR(INDEX($S$3:$S$200, MATCH($C7, $I$3:$I$200, 0)), "") -> 4 | B7: =COUNTIF(U:AX,G7) -> 1 | C7: =IFERROR( INDEX($U$1:$AX$1, MATCH(TRUE, CHOOSE({1;2;3;4;5;6;7;8;9;10;11;12;13;14;15;16;17;18;19;20;21;22;23;24;25;26;27;28;29;30;31;32}, COUNTIFS($U$2:$U$200,$G7)>0, COUNTIFS($V$2:$V$200,$G7)>0, COUNTIFS($W$2:$W$200,$G7)>0, COUNTIFS($X$2:$X$200,$G7)>0, COUNTIFS($Y$2:$Y$200,$G7)>0, COUNTIFS($Z$2:$Z$200,$G7)>0, COUNTIFS($AA$2:$AA$200,$G7)>0, COUNTIFS($AB$2:$AB$200,$G7)>0, COUNTIFS($AC$2:$AC$200,$G7)>0, COUNTIFS($AD$2:$AD$200,$G7)>0, COUNTIFS($AE$2:$AE$200,$G7)>0, COUNTIFS($AF$2:$AF$200,$G7)>0, COUNTIFS($AG$2:$AG$200,$G7)>0, COUNTIFS($AH$2:$AH$200,$G7)>0, COUNTIFS($AI$2:$AI$200,$G7)>0, COUNTIFS($AJ$2:$AJ$200,$G7)>0, COUNTIFS($AK$2:$AK$200,$G7)>0, COUNTIFS($AL$2:$AL$200,$G7)>0, COUNTIFS($AM$2:$AM$200,$G7)>0, COUNTIFS($AN$2:$AN$200,$G7)>0, COUNTIFS($AO$2:$AO$200,$G7)>0, COUNTIFS($AP$2:$AP$200,$G7)>0, COUNTIFS($AQ$2:$AQ$200,$G7)>0, COUNTIFS($AR$2:$AR$200,$G7)>0, COUNTIFS($AS$2:$AS$200,$G7)>0, COUNTIFS($AT$2:$AT$200,$G7)>0, COUNTIFS($AU$2:$AU$200,$G7)>0, COUNTIFS($AV$2:$AV$200,$G7)>0, COUNTIFS($AW$2:$AW$200,$G7)>0, COUNTIFS($AX$2:$AX$200,$G7)>0 ), 0) ), "") -> Rielle | D7: {=IFERROR( INDEX( _xlfn._xlws.FILTER($U$1:$AX$1, TRANSPOSE( CHOOSE({1;2;3;4;5;6;7;8;9;10;11;12;13;14;15;16;17;18;19;20;21;22;23;24;25;26;27;28;29;30}, COUNTIFS($U$2:$U$200,$G7)>0, COUNTIFS($V$2:$V$200,$G7)>0, COUNTIFS($W$2:$W$200,$G7)>0, COUNTIFS($X$2:$X$200,$G7)>0, COUNTIFS($Y$2:$Y$200,$G7)>0, COUNTIFS($Z$2:$Z$200,$G7)>0, COUNTIFS($AA$2:$AA$200,$G7)>0, COUNTIFS($AB$2:$AB$200,$G7)>0, COUNTIFS($AC$2:$AC$200,$G7)>0, COUNTIFS($AD$2:$AD$200,$G7)>0, COUNTIFS($AE$2:$AE$200,$G7)>0, COUNTIFS($AF$2:$AF$200,$G7)>0, COUNTIFS($AG$2:$AG$200,$G7)>0, COUNTIFS($AH$2:$AH$200,$G7)>0, COUNTIFS($AI$2:$AI$200,$G7)>0, COUNTIFS($AJ$2:$AJ$200,$G7)>0, COUNTIFS($AK$2:$AK$200,$G7)>0, COUNTIFS($AL$2:$AL$200,$G7)>0, COUNTIFS($AM$2:$AM$200,$G7)>0, COUNTIFS($AN$2:$AN$200,$G7)>0, COUNTIFS($AO$2:$AO$200,$G7)>0, COUNTIFS($AP$2:$AP$200,$G7)>0, COUNTIFS($AQ$2:$AQ$200,$G7)>0, COUNTIFS($AR$2:$AR$200,$G7)>0, COUNTIFS($AS$2:$AS$200,$G7)>0, COUNTIFS($AT$2:$AT$200,$G7)>0, COUNTIFS($AU$2:$AU$200,$G7)>0, COUNTIFS($AV$2:$AV$200,$G7)>0, COUNTIFS($AW$2:$AW$200,$G7)>0, COUNTIFS($AX$2:$AX$200,$G7)>0 )), ), 2 ), "")} | E7: {=IFERROR( INDEX( _xlfn._xlws.FILTER($U$1:$AX$1, TRANSPOSE( CHOOSE({1;2;3;4;5;6;7;8;9;10;11;12;13;14;15;16;17;18;19;20;21;22;23;24;25;26;27;28;29;30}, COUNTIFS($U$2:$U$200,$G7)>0, COUNTIFS($V$2:$V$200,$G7)>0, COUNTIFS($W$2:$W$200,$G7)>0, COUNTIFS($X$2:$X$200,$G7)>0, COUNTIFS($Y$2:$Y$200,$G7)>0, COUNTIFS($Z$2:$Z$200,$G7)>0, COUNTIFS($AA$2:$AA$200,$G7)>0, COUNTIFS($AB$2:$AB$200,$G7)>0, COUNTIFS($AC$2:$AC$200,$G7)>0, COUNTIFS($AD$2:$AD$200,$G7)>0, COUNTIFS($AE$2:$AE$200,$G7)>0, COUNTIFS($AF$2:$AF$200,$G7)>0, COUNTIFS($AG$2:$AG$200,$G7)>0, COUNTIFS($AH$2:$AH$200,$G7)>0, COUNTIFS($AI$2:$AI$200,$G7)>0, COUNTIFS($AJ$2:$AJ$200,$G7)>0, COUNTIFS($AK$2:$AK$200,$G7)>0, COUNTIFS($AL$2:$AL$200,$G7)>0, COUNTIFS($AM$2:$AM$200,$G7)>0, COUNTIFS($AN$2:$AN$200,$G7)>0, COUNTIFS($AO$2:$AO$200,$G7)>0, COUNTIFS($AP$2:$AP$200,$G7)>0, COUNTIFS($AQ$2:$AQ$200,$G7)>0, COUNTIFS($AR$2:$AR$200,$G7)>0, COUNTIFS($AS$2:$AS$200,$G7)>0, COUNTIFS($AT$2:$AT$200,$G7)>0, COUNTIFS($AU$2:$AU$200,$G7)>0, COUNTIFS($AV$2:$AV$200,$G7)>0, COUNTIFS($AW$2:$AW$200,$G7)>0, COUNTIFS($AX$2:$AX$200,$G7)>0 )), ), 3 ), "")} | F7: {=IFERROR( INDEX( _xlfn._xlws.FILTER($U$1:$AX$1, TRANSPOSE( CHOOSE({1;2;3;4;5;6;7;8;9;10;11;12;13;14;15;16;17;18;19;20;21;22;23;24;25;26;27;28;29;30}, COUNTIFS($U$2:$U$200,$G7)>0, COUNTIFS($V$2:$V$200,$G7)>0, COUNTIFS($W$2:$W$200,$G7)>0, COUNTIFS($X$2:$X$200,$G7)>0, COUNTIFS($Y$2:$Y$200,$G7)>0, COUNTIFS($Z$2:$Z$200,$G7)>0, COUNTIFS($AA$2:$AA$200,$G7)>0, COUNTIFS($AB$2:$AB$200,$G7)>0, COUNTIFS($AC$2:$AC$200,$G7)>0, COUNTIFS($AD$2:$AD$200,$G7)>0, COUNTIFS($AE$2:$AE$200,$G7)>0, COUNTIFS($AF$2:$AF$200,$G7)>0, COUNTIFS($AG$2:$AG$200,$G7)>0, COUNTIFS($AH$2:$AH$200,$G7)>0, COUNTIFS($AI$2:$AI$200,$G7)>0, COUNTIFS($AJ$2:$AJ$200,$G7)>0, COUNTIFS($AK$2:$AK$200,$G7)>0, COUNTIFS($AL$2:$AL$200,$G7)>0, COUNTIFS($AM$2:$AM$200,$G7)>0, COUNTIFS($AN$2:$AN$200,$G7)>0, COUNTIFS($AO$2:$AO$200,$G7)>0, COUNTIFS($AP$2:$AP$200,$G7)>0, COUNTIFS($AQ$2:$AQ$200,$G7)>0, COUNTIFS($AR$2:$AR$200,$G7)>0, COUNTIFS($AS$2:$AS$200,$G7)>0, COUNTIFS($AT$2:$AT$200,$G7)>0, COUNTIFS($AU$2:$AU$200,$G7)>0, COUNTIFS($AV$2:$AV$200,$G7)>0, COUNTIFS($AW$2:$AW$200,$G7)>0, COUNTIFS($AX$2:$AX$200,$G7)>0 )), ), 4 ), "")} | G7: Afundar em Estupor | I7: Carlos | J7: =Carlos!G2 -> 15 | K7: Sim | L7: Não | M7: Não | N7: Sim | O7: Não | P7: Voltron | Q7: Dano Direto | R7: Ganhar Vida e Reanimate | S7: =IF(J7<6,"5",IF(J7<11,"4",IF(J7<16,"3",IF(J7<31,"2","1")))) -> 3 | U7: Deadeye Tracker | V7: Castle Ardenvale | W7: Ghostly Prison | X7: Canopy Vista | Y7: Giver of Runes | Z7: Dúplice Debochada | AA7: Kodama's Reach | AB7: Jadar, Ghoulcaller of Nephalia | AC7: Rotating Fireplace | AD7: Hedge Shredder | AE7: Inventors' Fair | AF7: Mandate of Peace | AG7: Satoru, the Infiltrator | AH7: Glasspool Mimic | AI7: Espada de Luz e Sombra | AJ7: Lolth, Rainha Aranha | AL7: Zagoth Triome | AN7: Trioma de Indatha | AO7: Serenata das Estriges | AP7: Três Passos à Frente | AQ7: Pain for All | AS7: Warren Soultrader | AX7: Arcbound Fiend | AZ7: Dionus, Elvish Archdruid | BA7: Extinguisher Battleship | BB7: Collector's Vault | BC7: Creeping Tar Pit | BD7: Burnt Offering | BE7: Daretti, Ingenious Iconoclast | BF7: Dollmaker's Shop // Porcelain Gallery | BG7: Call to the Kindred | BH7: Branching Evolution | BI7: Arcbound Fiend | BK7: Caverna das Almas | BL7: Arid Mesa | BM7: Bugenhagen, Wise Elder | BN7: Bloodstained Mire | BO7: Arcbound Fiend | BQ7: Amphibian Downpour | BR7: Arcane Lighthouse | BT7: Afundar em Estupor
A8: =IFERROR(INDEX($S$3:$S$200, MATCH($C8, $I$3:$I$200, 0)), "") -> 4 | B8: =COUNTIF(U:AX,G8) -> 2 | C8: =IFERROR( INDEX($U$1:$AX$1, MATCH(TRUE, CHOOSE({1;2;3;4;5;6;7;8;9;10;11;12;13;14;15;16;17;18;19;20;21;22;23;24;25;26;27;28;29;30;31;32}, COUNTIFS($U$2:$U$200,$G8)>0, COUNTIFS($V$2:$V$200,$G8)>0, COUNTIFS($W$2:$W$200,$G8)>0, COUNTIFS($X$2:$X$200,$G8)>0, COUNTIFS($Y$2:$Y$200,$G8)>0, COUNTIFS($Z$2:$Z$200,$G8)>0, COUNTIFS($AA$2:$AA$200,$G8)>0, COUNTIFS($AB$2:$AB$200,$G8)>0, COUNTIFS($AC$2:$AC$200,$G8)>0, COUNTIFS($AD$2:$AD$200,$G8)>0, COUNTIFS($AE$2:$AE$200,$G8)>0, COUNTIFS($AF$2:$AF$200,$G8)>0, COUNTIFS($AG$2:$AG$200,$G8)>0, COUNTIFS($AH$2:$AH$200,$G8)>0, COUNTIFS($AI$2:$AI$200,$G8)>0, COUNTIFS($AJ$2:$AJ$200,$G8)>0, COUNTIFS($AK$2:$AK$200,$G8)>0, COUNTIFS($AL$2:$AL$200,$G8)>0, COUNTIFS($AM$2:$AM$200,$G8)>0, COUNTIFS($AN$2:$AN$200,$G8)>0, COUNTIFS($AO$2:$AO$200,$G8)>0, COUNTIFS($AP$2:$AP$200,$G8)>0, COUNTIFS($AQ$2:$AQ$200,$G8)>0, COUNTIFS($AR$2:$AR$200,$G8)>0, COUNTIFS($AS$2:$AS$200,$G8)>0, COUNTIFS($AT$2:$AT$200,$G8)>0, COUNTIFS($AU$2:$AU$200,$G8)>0, COUNTIFS($AV$2:$AV$200,$G8)>0, COUNTIFS($AW$2:$AW$200,$G8)>0, COUNTIFS($AX$2:$AX$200,$G8)>0 ), 0) ), "") -> Elfos | D8: {=IFERROR( INDEX( _xlfn._xlws.FILTER($U$1:$AX$1, TRANSPOSE( CHOOSE({1;2;3;4;5;6;7;8;9;10;11;12;13;14;15;16;17;18;19;20;21;22;23;24;25;26;27;28;29;30}, COUNTIFS($U$2:$U$200,$G8)>0, COUNTIFS($V$2:$V$200,$G8)>0, COUNTIFS($W$2:$W$200,$G8)>0, COUNTIFS($X$2:$X$200,$G8)>0, COUNTIFS($Y$2:$Y$200,$G8)>0, COUNTIFS($Z$2:$Z$200,$G8)>0, COUNTIFS($AA$2:$AA$200,$G8)>0, COUNTIFS($AB$2:$AB$200,$G8)>0, COUNTIFS($AC$2:$AC$200,$G8)>0, COUNTIFS($AD$2:$AD$200,$G8)>0, COUNTIFS($AE$2:$AE$200,$G8)>0, COUNTIFS($AF$2:$AF$200,$G8)>0, COUNTIFS($AG$2:$AG$200,$G8)>0, COUNTIFS($AH$2:$AH$200,$G8)>0, COUNTIFS($AI$2:$AI$200,$G8)>0, COUNTIFS($AJ$2:$AJ$200,$G8)>0, COUNTIFS($AK$2:$AK$200,$G8)>0, COUNTIFS($AL$2:$AL$200,$G8)>0, COUNTIFS($AM$2:$AM$200,$G8)>0, COUNTIFS($AN$2:$AN$200,$G8)>0, COUNTIFS($AO$2:$AO$200,$G8)>0, COUNTIFS($AP$2:$AP$200,$G8)>0, COUNTIFS($AQ$2:$AQ$200,$G8)>0, COUNTIFS($AR$2:$AR$200,$G8)>0, COUNTIFS($AS$2:$AS$200,$G8)>0, COUNTIFS($AT$2:$AT$200,$G8)>0, COUNTIFS($AU$2:$AU$200,$G8)>0, COUNTIFS($AV$2:$AV$200,$G8)>0, COUNTIFS($AW$2:$AW$200,$G8)>0, COUNTIFS($AX$2:$AX$200,$G8)>0 )), ), 2 ), "")} -> Arcades | E8: {=IFERROR( INDEX( _xlfn._xlws.FILTER($U$1:$AX$1, TRANSPOSE( CHOOSE({1;2;3;4;5;6;7;8;9;10;11;12;13;14;15;16;17;18;19;20;21;22;23;24;25;26;27;28;29;30}, COUNTIFS($U$2:$U$200,$G8)>0, COUNTIFS($V$2:$V$200,$G8)>0, COUNTIFS($W$2:$W$200,$G8)>0, COUNTIFS($X$2:$X$200,$G8)>0, COUNTIFS($Y$2:$Y$200,$G8)>0, COUNTIFS($Z$2:$Z$200,$G8)>0, COUNTIFS($AA$2:$AA$200,$G8)>0, COUNTIFS($AB$2:$AB$200,$G8)>0, COUNTIFS($AC$2:$AC$200,$G8)>0, COUNTIFS($AD$2:$AD$200,$G8)>0, COUNTIFS($AE$2:$AE$200,$G8)>0, COUNTIFS($AF$2:$AF$200,$G8)>0, COUNTIFS($AG$2:$AG$200,$G8)>0, COUNTIFS($AH$2:$AH$200,$G8)>0, COUNTIFS($AI$2:$AI$200,$G8)>0, COUNTIFS($AJ$2:$AJ$200,$G8)>0, COUNTIFS($AK$2:$AK$200,$G8)>0, COUNTIFS($AL$2:$AL$200,$G8)>0, COUNTIFS($AM$2:$AM$200,$G8)>0, COUNTIFS($AN$2:$AN$200,$G8)>0, COUNTIFS($AO$2:$AO$200,$G8)>0, COUNTIFS($AP$2:$AP$200,$G8)>0, COUNTIFS($AQ$2:$AQ$200,$G8)>0, COUNTIFS($AR$2:$AR$200,$G8)>0, COUNTIFS($AS$2:$AS$200,$G8)>0, COUNTIFS($AT$2:$AT$200,$G8)>0, COUNTIFS($AU$2:$AU$200,$G8)>0, COUNTIFS($AV$2:$AV$200,$G8)>0, COUNTIFS($AW$2:$AW$200,$G8)>0, COUNTIFS($AX$2:$AX$200,$G8)>0 )), ), 3 ), "")} | F8: {=IFERROR( INDEX( _xlfn._xlws.FILTER($U$1:$AX$1, TRANSPOSE( CHOOSE({1;2;3;4;5;6;7;8;9;10;11;12;13;14;15;16;17;18;19;20;21;22;23;24;25;26;27;28;29;30}, COUNTIFS($U$2:$U$200,$G8)>0, COUNTIFS($V$2:$V$200,$G8)>0, COUNTIFS($W$2:$W$200,$G8)>0, COUNTIFS($X$2:$X$200,$G8)>0, COUNTIFS($Y$2:$Y$200,$G8)>0, COUNTIFS($Z$2:$Z$200,$G8)>0, COUNTIFS($AA$2:$AA$200,$G8)>0, COUNTIFS($AB$2:$AB$200,$G8)>0, COUNTIFS($AC$2:$AC$200,$G8)>0, COUNTIFS($AD$2:$AD$200,$G8)>0, COUNTIFS($AE$2:$AE$200,$G8)>0, COUNTIFS($AF$2:$AF$200,$G8)>0, COUNTIFS($AG$2:$AG$200,$G8)>0, COUNTIFS($AH$2:$AH$200,$G8)>0, COUNTIFS($AI$2:$AI$200,$G8)>0, COUNTIFS($AJ$2:$AJ$200,$G8)>0, COUNTIFS($AK$2:$AK$200,$G8)>0, COUNTIFS($AL$2:$AL$200,$G8)>0, COUNTIFS($AM$2:$AM$200,$G8)>0, COUNTIFS($AN$2:$AN$200,$G8)>0, COUNTIFS($AO$2:$AO$200,$G8)>0, COUNTIFS($AP$2:$AP$200,$G8)>0, COUNTIFS($AQ$2:$AQ$200,$G8)>0, COUNTIFS($AR$2:$AR$200,$G8)>0, COUNTIFS($AS$2:$AS$200,$G8)>0, COUNTIFS($AT$2:$AT$200,$G8)>0, COUNTIFS($AU$2:$AU$200,$G8)>0, COUNTIFS($AV$2:$AV$200,$G8)>0, COUNTIFS($AW$2:$AW$200,$G8)>0, COUNTIFS($AX$2:$AX$200,$G8)>0 )), ), 4 ), "")} | G8: Alchemist's Refuge | I8: Rani | J8: =Rani!G2 -> 19 | K8: Não | L8: Sim | M8: Sim | N8: Sim | O8: Não | P8: Combate | Q8: Voltron | R8: Atiçar e Investigar | S8: =IF(J8<6,"5",IF(J8<11,"4",IF(J8<16,"3",IF(J8<31,"2","1")))) -> 2 | U8: Emberwilde Captain | V8: Champions from Beyond | W8: Incendiary Command | X8: Champion of Lambholt | Y8: Guia das Almas | Z8: Equilíbrio de Poderes | AA8: Lord of Atlantis | AB8: Misty Rainforest | AC8: The Tenth Doctor | AD8: Petrified Field | AE8: Mirrex | AF8: Polluted Delta | AG8: Sea Gate Restoration | AH8: Merchant of Secrets | AI8: Espada de Verdade e Justiça | AJ8: Nicol Bolas, God-Pharaoh | AN8: Trioma de Raugrin | AO8: Sokenzan, Crisol da Afronta | AP8: Unstoppable Plan | AQ8: Red XIII, Proud Warrior | AX8: Arcbound Javelineer | AZ8: Entomb | BA8: Gerrard's Hourglass Pendant | BB8: Lagoa Espelhada | BC8: Drowned Catacomb | BD8: Diário de Tarrian | BE8: Espada da Riqueza e do Poder | BF8: Drowned Catacomb | BG8: Clifftop Retreat | BH8: Brushland | BI8: Arcbound Javelineer | BK8: Chimil, o Sol Interior | BL8: Baral, Chief of Compliance | BM8: Burnt Offering | BN8: Bojuka Bog | BO8: Arcbound Javelineer | BQ8: Ancient Tomb | BR8: Ascensão do Avernus | BT8: Alchemist's Refuge
A9: =IFERROR(INDEX($S$3:$S$200, MATCH($C9, $I$3:$I$200, 0)), "") -> 2 | B9: =COUNTIF(U:AX,G9) -> 1 | C9: =IFERROR( INDEX($U$1:$AX$1, MATCH(TRUE, CHOOSE({1;2;3;4;5;6;7;8;9;10;11;12;13;14;15;16;17;18;19;20;21;22;23;24;25;26;27;28;29;30;31;32}, COUNTIFS($U$2:$U$200,$G9)>0, COUNTIFS($V$2:$V$200,$G9)>0, COUNTIFS($W$2:$W$200,$G9)>0, COUNTIFS($X$2:$X$200,$G9)>0, COUNTIFS($Y$2:$Y$200,$G9)>0, COUNTIFS($Z$2:$Z$200,$G9)>0, COUNTIFS($AA$2:$AA$200,$G9)>0, COUNTIFS($AB$2:$AB$200,$G9)>0, COUNTIFS($AC$2:$AC$200,$G9)>0, COUNTIFS($AD$2:$AD$200,$G9)>0, COUNTIFS($AE$2:$AE$200,$G9)>0, COUNTIFS($AF$2:$AF$200,$G9)>0, COUNTIFS($AG$2:$AG$200,$G9)>0, COUNTIFS($AH$2:$AH$200,$G9)>0, COUNTIFS($AI$2:$AI$200,$G9)>0, COUNTIFS($AJ$2:$AJ$200,$G9)>0, COUNTIFS($AK$2:$AK$200,$G9)>0, COUNTIFS($AL$2:$AL$200,$G9)>0, COUNTIFS($AM$2:$AM$200,$G9)>0, COUNTIFS($AN$2:$AN$200,$G9)>0, COUNTIFS($AO$2:$AO$200,$G9)>0, COUNTIFS($AP$2:$AP$200,$G9)>0, COUNTIFS($AQ$2:$AQ$200,$G9)>0, COUNTIFS($AR$2:$AR$200,$G9)>0, COUNTIFS($AS$2:$AS$200,$G9)>0, COUNTIFS($AT$2:$AT$200,$G9)>0, COUNTIFS($AU$2:$AU$200,$G9)>0, COUNTIFS($AV$2:$AV$200,$G9)>0, COUNTIFS($AW$2:$AW$200,$G9)>0, COUNTIFS($AX$2:$AX$200,$G9)>0 ), 0) ), "") -> Narset | D9: {=IFERROR( INDEX( _xlfn._xlws.FILTER($U$1:$AX$1, TRANSPOSE( CHOOSE({1;2;3;4;5;6;7;8;9;10;11;12;13;14;15;16;17;18;19;20;21;22;23;24;25;26;27;28;29;30}, COUNTIFS($U$2:$U$200,$G9)>0, COUNTIFS($V$2:$V$200,$G9)>0, COUNTIFS($W$2:$W$200,$G9)>0, COUNTIFS($X$2:$X$200,$G9)>0, COUNTIFS($Y$2:$Y$200,$G9)>0, COUNTIFS($Z$2:$Z$200,$G9)>0, COUNTIFS($AA$2:$AA$200,$G9)>0, COUNTIFS($AB$2:$AB$200,$G9)>0, COUNTIFS($AC$2:$AC$200,$G9)>0, COUNTIFS($AD$2:$AD$200,$G9)>0, COUNTIFS($AE$2:$AE$200,$G9)>0, COUNTIFS($AF$2:$AF$200,$G9)>0, COUNTIFS($AG$2:$AG$200,$G9)>0, COUNTIFS($AH$2:$AH$200,$G9)>0, COUNTIFS($AI$2:$AI$200,$G9)>0, COUNTIFS($AJ$2:$AJ$200,$G9)>0, COUNTIFS($AK$2:$AK$200,$G9)>0, COUNTIFS($AL$2:$AL$200,$G9)>0, COUNTIFS($AM$2:$AM$200,$G9)>0, COUNTIFS($AN$2:$AN$200,$G9)>0, COUNTIFS($AO$2:$AO$200,$G9)>0, COUNTIFS($AP$2:$AP$200,$G9)>0, COUNTIFS($AQ$2:$AQ$200,$G9)>0, COUNTIFS($AR$2:$AR$200,$G9)>0, COUNTIFS($AS$2:$AS$200,$G9)>0, COUNTIFS($AT$2:$AT$200,$G9)>0, COUNTIFS($AU$2:$AU$200,$G9)>0, COUNTIFS($AV$2:$AV$200,$G9)>0, COUNTIFS($AW$2:$AW$200,$G9)>0, COUNTIFS($AX$2:$AX$200,$G9)>0 )), ), 2 ), "")} | E9: {=IFERROR( INDEX( _xlfn._xlws.FILTER($U$1:$AX$1, TRANSPOSE( CHOOSE({1;2;3;4;5;6;7;8;9;10;11;12;13;14;15;16;17;18;19;20;21;22;23;24;25;26;27;28;29;30}, COUNTIFS($U$2:$U$200,$G9)>0, COUNTIFS($V$2:$V$200,$G9)>0, COUNTIFS($W$2:$W$200,$G9)>0, COUNTIFS($X$2:$X$200,$G9)>0, COUNTIFS($Y$2:$Y$200,$G9)>0, COUNTIFS($Z$2:$Z$200,$G9)>0, COUNTIFS($AA$2:$AA$200,$G9)>0, COUNTIFS($AB$2:$AB$200,$G9)>0, COUNTIFS($AC$2:$AC$200,$G9)>0, COUNTIFS($AD$2:$AD$200,$G9)>0, COUNTIFS($AE$2:$AE$200,$G9)>0, COUNTIFS($AF$2:$AF$200,$G9)>0, COUNTIFS($AG$2:$AG$200,$G9)>0, COUNTIFS($AH$2:$AH$200,$G9)>0, COUNTIFS($AI$2:$AI$200,$G9)>0, COUNTIFS($AJ$2:$AJ$200,$G9)>0, COUNTIFS($AK$2:$AK$200,$G9)>0, COUNTIFS($AL$2:$AL$200,$G9)>0, COUNTIFS($AM$2:$AM$200,$G9)>0, COUNTIFS($AN$2:$AN$200,$G9)>0, COUNTIFS($AO$2:$AO$200,$G9)>0, COUNTIFS($AP$2:$AP$200,$G9)>0, COUNTIFS($AQ$2:$AQ$200,$G9)>0, COUNTIFS($AR$2:$AR$200,$G9)>0, COUNTIFS($AS$2:$AS$200,$G9)>0, COUNTIFS($AT$2:$AT$200,$G9)>0, COUNTIFS($AU$2:$AU$200,$G9)>0, COUNTIFS($AV$2:$AV$200,$G9)>0, COUNTIFS($AW$2:$AW$200,$G9)>0, COUNTIFS($AX$2:$AX$200,$G9)>0 )), ), 3 ), "")} | F9: {=IFERROR( INDEX( _xlfn._xlws.FILTER($U$1:$AX$1, TRANSPOSE( CHOOSE({1;2;3;4;5;6;7;8;9;10;11;12;13;14;15;16;17;18;19;20;21;22;23;24;25;26;27;28;29;30}, COUNTIFS($U$2:$U$200,$G9)>0, COUNTIFS($V$2:$V$200,$G9)>0, COUNTIFS($W$2:$W$200,$G9)>0, COUNTIFS($X$2:$X$200,$G9)>0, COUNTIFS($Y$2:$Y$200,$G9)>0, COUNTIFS($Z$2:$Z$200,$G9)>0, COUNTIFS($AA$2:$AA$200,$G9)>0, COUNTIFS($AB$2:$AB$200,$G9)>0, COUNTIFS($AC$2:$AC$200,$G9)>0, COUNTIFS($AD$2:$AD$200,$G9)>0, COUNTIFS($AE$2:$AE$200,$G9)>0, COUNTIFS($AF$2:$AF$200,$G9)>0, COUNTIFS($AG$2:$AG$200,$G9)>0, COUNTIFS($AH$2:$AH$200,$G9)>0, COUNTIFS($AI$2:$AI$200,$G9)>0, COUNTIFS($AJ$2:$AJ$200,$G9)>0, COUNTIFS($AK$2:$AK$200,$G9)>0, COUNTIFS($AL$2:$AL$200,$G9)>0, COUNTIFS($AM$2:$AM$200,$G9)>0, COUNTIFS($AN$2:$AN$200,$G9)>0, COUNTIFS($AO$2:$AO$200,$G9)>0, COUNTIFS($AP$2:$AP$200,$G9)>0, COUNTIFS($AQ$2:$AQ$200,$G9)>0, COUNTIFS($AR$2:$AR$200,$G9)>0, COUNTIFS($AS$2:$AS$200,$G9)>0, COUNTIFS($AT$2:$AT$200,$G9)>0, COUNTIFS($AU$2:$AU$200,$G9)>0, COUNTIFS($AV$2:$AV$200,$G9)>0, COUNTIFS($AW$2:$AW$200,$G9)>0, COUNTIFS($AX$2:$AX$200,$G9)>0 )), ), 4 ), "")} | G9: Aligned Heart | I9: Kumena | J9: =Kumena!G2 -> 21 | K9: Não | L9: Sim | M9: Não | N9: Não | O9: Sim | P9: Combate | Q9: Voltron | R9: Tribal de Tritões | S9: =IF(J9<6,"5",IF(J9<11,"4",IF(J9<16,"3",IF(J9<31,"2","1")))) -> 2 | U9: Fabled Passage | V9: Cinder Glade | W9: Irenicus's Vile Duplication | X9: Conclave Mentor | Y9: Hierofante de Elenda | Z9: Fellwar Stone | AA9: Lullmage Mentor | AB9: Scalding Tarn | AC9: Thought Vessel | AD9: Phyrexian Tower | AE9: Portal to Phyrexia | AF9: Prismatic Strands | AG9: Shizo, Death's Storehouse | AH9: Mistbind Clique | AI9: Firion, Wild Rose Warrior | AJ9: O Dínamo Peregrino | AN9: Trioma de Zagoth | AQ9: Saqueador Amaldiçoado | AX9: Arcbound Mouser | AZ9: Evendo, Waking Haven | BA9: Inventors' Fair | BB9: Ojer Pakpatiq, Era Profunda | BC9: Emergency Eject | BD9: Dour Port-Mage | BE9: Espada de Banquete e Fome | BF9: Dúplice Debochada | BG9: Deeproot Historian | BH9: Bulwark Ox | BI9: Arcbound Mouser | BK9: Crisol dos Mundos | BL9: Batwing Brume | BM9: Chandra's Ignition | BN9: Call to the Kindred | BO9: Arcbound Mouser | BQ9: Árbitro Silencioso | BR9: Autoridade dos Cônsules | BT9: Aligned Heart
A10: =IFERROR(INDEX($S$3:$S$200, MATCH($C10, $I$3:$I$200, 0)), "") -> 3 | B10: =COUNTIF(U:AX,G10) -> 1 | C10: =IFERROR( INDEX($U$1:$AX$1, MATCH(TRUE, CHOOSE({1;2;3;4;5;6;7;8;9;10;11;12;13;14;15;16;17;18;19;20;21;22;23;24;25;26;27;28;29;30;31;32}, COUNTIFS($U$2:$U$200,$G10)>0, COUNTIFS($V$2:$V$200,$G10)>0, COUNTIFS($W$2:$W$200,$G10)>0, COUNTIFS($X$2:$X$200,$G10)>0, COUNTIFS($Y$2:$Y$200,$G10)>0, COUNTIFS($Z$2:$Z$200,$G10)>0, COUNTIFS($AA$2:$AA$200,$G10)>0, COUNTIFS($AB$2:$AB$200,$G10)>0, COUNTIFS($AC$2:$AC$200,$G10)>0, COUNTIFS($AD$2:$AD$200,$G10)>0, COUNTIFS($AE$2:$AE$200,$G10)>0, COUNTIFS($AF$2:$AF$200,$G10)>0, COUNTIFS($AG$2:$AG$200,$G10)>0, COUNTIFS($AH$2:$AH$200,$G10)>0, COUNTIFS($AI$2:$AI$200,$G10)>0, COUNTIFS($AJ$2:$AJ$200,$G10)>0, COUNTIFS($AK$2:$AK$200,$G10)>0, COUNTIFS($AL$2:$AL$200,$G10)>0, COUNTIFS($AM$2:$AM$200,$G10)>0, COUNTIFS($AN$2:$AN$200,$G10)>0, COUNTIFS($AO$2:$AO$200,$G10)>0, COUNTIFS($AP$2:$AP$200,$G10)>0, COUNTIFS($AQ$2:$AQ$200,$G10)>0, COUNTIFS($AR$2:$AR$200,$G10)>0, COUNTIFS($AS$2:$AS$200,$G10)>0, COUNTIFS($AT$2:$AT$200,$G10)>0, COUNTIFS($AU$2:$AU$200,$G10)>0, COUNTIFS($AV$2:$AV$200,$G10)>0, COUNTIFS($AW$2:$AW$200,$G10)>0, COUNTIFS($AX$2:$AX$200,$G10)>0 ), 0) ), "") -> VialIshai | D10: {=IFERROR( INDEX( _xlfn._xlws.FILTER($U$1:$AX$1, TRANSPOSE( CHOOSE({1;2;3;4;5;6;7;8;9;10;11;12;13;14;15;16;17;18;19;20;21;22;23;24;25;26;27;28;29;30}, COUNTIFS($U$2:$U$200,$G10)>0, COUNTIFS($V$2:$V$200,$G10)>0, COUNTIFS($W$2:$W$200,$G10)>0, COUNTIFS($X$2:$X$200,$G10)>0, COUNTIFS($Y$2:$Y$200,$G10)>0, COUNTIFS($Z$2:$Z$200,$G10)>0, COUNTIFS($AA$2:$AA$200,$G10)>0, COUNTIFS($AB$2:$AB$200,$G10)>0, COUNTIFS($AC$2:$AC$200,$G10)>0, COUNTIFS($AD$2:$AD$200,$G10)>0, COUNTIFS($AE$2:$AE$200,$G10)>0, COUNTIFS($AF$2:$AF$200,$G10)>0, COUNTIFS($AG$2:$AG$200,$G10)>0, COUNTIFS($AH$2:$AH$200,$G10)>0, COUNTIFS($AI$2:$AI$200,$G10)>0, COUNTIFS($AJ$2:$AJ$200,$G10)>0, COUNTIFS($AK$2:$AK$200,$G10)>0, COUNTIFS($AL$2:$AL$200,$G10)>0, COUNTIFS($AM$2:$AM$200,$G10)>0, COUNTIFS($AN$2:$AN$200,$G10)>0, COUNTIFS($AO$2:$AO$200,$G10)>0, COUNTIFS($AP$2:$AP$200,$G10)>0, COUNTIFS($AQ$2:$AQ$200,$G10)>0, COUNTIFS($AR$2:$AR$200,$G10)>0, COUNTIFS($AS$2:$AS$200,$G10)>0, COUNTIFS($AT$2:$AT$200,$G10)>0, COUNTIFS($AU$2:$AU$200,$G10)>0, COUNTIFS($AV$2:$AV$200,$G10)>0, COUNTIFS($AW$2:$AW$200,$G10)>0, COUNTIFS($AX$2:$AX$200,$G10)>0 )), ), 2 ), "")} | E10: {=IFERROR( INDEX( _xlfn._xlws.FILTER($U$1:$AX$1, TRANSPOSE( CHOOSE({1;2;3;4;5;6;7;8;9;10;11;12;13;14;15;16;17;18;19;20;21;22;23;24;25;26;27;28;29;30}, COUNTIFS($U$2:$U$200,$G10)>0, COUNTIFS($V$2:$V$200,$G10)>0, COUNTIFS($W$2:$W$200,$G10)>0, COUNTIFS($X$2:$X$200,$G10)>0, COUNTIFS($Y$2:$Y$200,$G10)>0, COUNTIFS($Z$2:$Z$200,$G10)>0, COUNTIFS($AA$2:$AA$200,$G10)>0, COUNTIFS($AB$2:$AB$200,$G10)>0, COUNTIFS($AC$2:$AC$200,$G10)>0, COUNTIFS($AD$2:$AD$200,$G10)>0, COUNTIFS($AE$2:$AE$200,$G10)>0, COUNTIFS($AF$2:$AF$200,$G10)>0, COUNTIFS($AG$2:$AG$200,$G10)>0, COUNTIFS($AH$2:$AH$200,$G10)>0, COUNTIFS($AI$2:$AI$200,$G10)>0, COUNTIFS($AJ$2:$AJ$200,$G10)>0, COUNTIFS($AK$2:$AK$200,$G10)>0, COUNTIFS($AL$2:$AL$200,$G10)>0, COUNTIFS($AM$2:$AM$200,$G10)>0, COUNTIFS($AN$2:$AN$200,$G10)>0, COUNTIFS($AO$2:$AO$200,$G10)>0, COUNTIFS($AP$2:$AP$200,$G10)>0, COUNTIFS($AQ$2:$AQ$200,$G10)>0, COUNTIFS($AR$2:$AR$200,$G10)>0, COUNTIFS($AS$2:$AS$200,$G10)>0, COUNTIFS($AT$2:$AT$200,$G10)>0, COUNTIFS($AU$2:$AU$200,$G10)>0, COUNTIFS($AV$2:$AV$200,$G10)>0, COUNTIFS($AW$2:$AW$200,$G10)>0, COUNTIFS($AX$2:$AX$200,$G10)>0 )), ), 3 ), "")} | F10: {=IFERROR( INDEX( _xlfn._xlws.FILTER($U$1:$AX$1, TRANSPOSE( CHOOSE({1;2;3;4;5;6;7;8;9;10;11;12;13;14;15;16;17;18;19;20;21;22;23;24;25;26;27;28;29;30}, COUNTIFS($U$2:$U$200,$G10)>0, COUNTIFS($V$2:$V$200,$G10)>0, COUNTIFS($W$2:$W$200,$G10)>0, COUNTIFS($X$2:$X$200,$G10)>0, COUNTIFS($Y$2:$Y$200,$G10)>0, COUNTIFS($Z$2:$Z$200,$G10)>0, COUNTIFS($AA$2:$AA$200,$G10)>0, COUNTIFS($AB$2:$AB$200,$G10)>0, COUNTIFS($AC$2:$AC$200,$G10)>0, COUNTIFS($AD$2:$AD$200,$G10)>0, COUNTIFS($AE$2:$AE$200,$G10)>0, COUNTIFS($AF$2:$AF$200,$G10)>0, COUNTIFS($AG$2:$AG$200,$G10)>0, COUNTIFS($AH$2:$AH$200,$G10)>0, COUNTIFS($AI$2:$AI$200,$G10)>0, COUNTIFS($AJ$2:$AJ$200,$G10)>0, COUNTIFS($AK$2:$AK$200,$G10)>0, COUNTIFS($AL$2:$AL$200,$G10)>0, COUNTIFS($AM$2:$AM$200,$G10)>0, COUNTIFS($AN$2:$AN$200,$G10)>0, COUNTIFS($AO$2:$AO$200,$G10)>0, COUNTIFS($AP$2:$AP$200,$G10)>0, COUNTIFS($AQ$2:$AQ$200,$G10)>0, COUNTIFS($AR$2:$AR$200,$G10)>0, COUNTIFS($AS$2:$AS$200,$G10)>0, COUNTIFS($AT$2:$AT$200,$G10)>0, COUNTIFS($AU$2:$AU$200,$G10)>0, COUNTIFS($AV$2:$AV$200,$G10)>0, COUNTIFS($AW$2:$AW$200,$G10)>0, COUNTIFS($AX$2:$AX$200,$G10)>0 )), ), 4 ), "")} | G10: Amphibian Downpour | I10: Zimone | J10: =Zimone!G2 -> 13 | K10: Não | L10: Sim | M10: Não | N10: Sim | O10: Sim | P10: Combate | Q10: Dano Direto | R10: Terrenos e Valor | S10: =IF(J10<6,"5",IF(J10<11,"4",IF(J10<16,"3",IF(J10<31,"2","1")))) -> 3 | U10: Forerunner of the Coalition | V10: Exalted Sunborn | W10: Jidoor, Aristocratic Capital // Overture | X10: Deceptive Landscape | Y10: Keen Duelist | Z10: Frenzied Gorespawn | AA10: Merrow Commerce | AB10: Sothera, the Supervoid | AC10: Thran Dynamo | AD10: Ripples of Undeath | AE10: Rings of Brighthearth | AF10: Spectator Seating | AG10: Temporal Manipulation | AH10: Molten Echoes | AI10: Jitte Perdida | AJ10: Oko, Thief of Crowns | AQ10: The Masamune | AX10: Arcbound Overseer | AZ10: Hedge Shredder | BA10: Jetmir's Garden | BB10: Olho de Ojer Taq | BC10: Faerie Slumber Party | BD10: Enduring Innocence | BE10: Espada de Fogo e Gelo | BF10: Elspeth, Sun's Champion | BG10: Fabled Passage | BH10: Cankerbloom | BI10: Arcbound Overseer | BK10: Delighted Halfling | BL10: Careful Study | BM10: Cid, Freeflier Pilot | BN10: Clifftop Retreat | BO10: Arcbound Overseer | BQ10: Arid Mesa | BR10: Beast Within | BT10: Amphibian Downpour
A11: =IFERROR(INDEX($S$3:$S$200, MATCH($C11, $I$3:$I$200, 0)), "") -> 1 | B11: =COUNTIF(U:AX,G11) -> 1 | C11: =IFERROR( INDEX($U$1:$AX$1, MATCH(TRUE, CHOOSE({1;2;3;4;5;6;7;8;9;10;11;12;13;14;15;16;17;18;19;20;21;22;23;24;25;26;27;28;29;30;31;32}, COUNTIFS($U$2:$U$200,$G11)>0, COUNTIFS($V$2:$V$200,$G11)>0, COUNTIFS($W$2:$W$200,$G11)>0, COUNTIFS($X$2:$X$200,$G11)>0, COUNTIFS($Y$2:$Y$200,$G11)>0, COUNTIFS($Z$2:$Z$200,$G11)>0, COUNTIFS($AA$2:$AA$200,$G11)>0, COUNTIFS($AB$2:$AB$200,$G11)>0, COUNTIFS($AC$2:$AC$200,$G11)>0, COUNTIFS($AD$2:$AD$200,$G11)>0, COUNTIFS($AE$2:$AE$200,$G11)>0, COUNTIFS($AF$2:$AF$200,$G11)>0, COUNTIFS($AG$2:$AG$200,$G11)>0, COUNTIFS($AH$2:$AH$200,$G11)>0, COUNTIFS($AI$2:$AI$200,$G11)>0, COUNTIFS($AJ$2:$AJ$200,$G11)>0, COUNTIFS($AK$2:$AK$200,$G11)>0, COUNTIFS($AL$2:$AL$200,$G11)>0, COUNTIFS($AM$2:$AM$200,$G11)>0, COUNTIFS($AN$2:$AN$200,$G11)>0, COUNTIFS($AO$2:$AO$200,$G11)>0, COUNTIFS($AP$2:$AP$200,$G11)>0, COUNTIFS($AQ$2:$AQ$200,$G11)>0, COUNTIFS($AR$2:$AR$200,$G11)>0, COUNTIFS($AS$2:$AS$200,$G11)>0, COUNTIFS($AT$2:$AT$200,$G11)>0, COUNTIFS($AU$2:$AU$200,$G11)>0, COUNTIFS($AV$2:$AV$200,$G11)>0, COUNTIFS($AW$2:$AW$200,$G11)>0, COUNTIFS($AX$2:$AX$200,$G11)>0 ), 0) ), "") -> Modular | D11: {=IFERROR( INDEX( _xlfn._xlws.FILTER($U$1:$AX$1, TRANSPOSE( CHOOSE({1;2;3;4;5;6;7;8;9;10;11;12;13;14;15;16;17;18;19;20;21;22;23;24;25;26;27;28;29;30}, COUNTIFS($U$2:$U$200,$G11)>0, COUNTIFS($V$2:$V$200,$G11)>0, COUNTIFS($W$2:$W$200,$G11)>0, COUNTIFS($X$2:$X$200,$G11)>0, COUNTIFS($Y$2:$Y$200,$G11)>0, COUNTIFS($Z$2:$Z$200,$G11)>0, COUNTIFS($AA$2:$AA$200,$G11)>0, COUNTIFS($AB$2:$AB$200,$G11)>0, COUNTIFS($AC$2:$AC$200,$G11)>0, COUNTIFS($AD$2:$AD$200,$G11)>0, COUNTIFS($AE$2:$AE$200,$G11)>0, COUNTIFS($AF$2:$AF$200,$G11)>0, COUNTIFS($AG$2:$AG$200,$G11)>0, COUNTIFS($AH$2:$AH$200,$G11)>0, COUNTIFS($AI$2:$AI$200,$G11)>0, COUNTIFS($AJ$2:$AJ$200,$G11)>0, COUNTIFS($AK$2:$AK$200,$G11)>0, COUNTIFS($AL$2:$AL$200,$G11)>0, COUNTIFS($AM$2:$AM$200,$G11)>0, COUNTIFS($AN$2:$AN$200,$G11)>0, COUNTIFS($AO$2:$AO$200,$G11)>0, COUNTIFS($AP$2:$AP$200,$G11)>0, COUNTIFS($AQ$2:$AQ$200,$G11)>0, COUNTIFS($AR$2:$AR$200,$G11)>0, COUNTIFS($AS$2:$AS$200,$G11)>0, COUNTIFS($AT$2:$AT$200,$G11)>0, COUNTIFS($AU$2:$AU$200,$G11)>0, COUNTIFS($AV$2:$AV$200,$G11)>0, COUNTIFS($AW$2:$AW$200,$G11)>0, COUNTIFS($AX$2:$AX$200,$G11)>0 )), ), 2 ), "")} | E11: {=IFERROR( INDEX( _xlfn._xlws.FILTER($U$1:$AX$1, TRANSPOSE( CHOOSE({1;2;3;4;5;6;7;8;9;10;11;12;13;14;15;16;17;18;19;20;21;22;23;24;25;26;27;28;29;30}, COUNTIFS($U$2:$U$200,$G11)>0, COUNTIFS($V$2:$V$200,$G11)>0, COUNTIFS($W$2:$W$200,$G11)>0, COUNTIFS($X$2:$X$200,$G11)>0, COUNTIFS($Y$2:$Y$200,$G11)>0, COUNTIFS($Z$2:$Z$200,$G11)>0, COUNTIFS($AA$2:$AA$200,$G11)>0, COUNTIFS($AB$2:$AB$200,$G11)>0, COUNTIFS($AC$2:$AC$200,$G11)>0, COUNTIFS($AD$2:$AD$200,$G11)>0, COUNTIFS($AE$2:$AE$200,$G11)>0, COUNTIFS($AF$2:$AF$200,$G11)>0, COUNTIFS($AG$2:$AG$200,$G11)>0, COUNTIFS($AH$2:$AH$200,$G11)>0, COUNTIFS($AI$2:$AI$200,$G11)>0, COUNTIFS($AJ$2:$AJ$200,$G11)>0, COUNTIFS($AK$2:$AK$200,$G11)>0, COUNTIFS($AL$2:$AL$200,$G11)>0, COUNTIFS($AM$2:$AM$200,$G11)>0, COUNTIFS($AN$2:$AN$200,$G11)>0, COUNTIFS($AO$2:$AO$200,$G11)>0, COUNTIFS($AP$2:$AP$200,$G11)>0, COUNTIFS($AQ$2:$AQ$200,$G11)>0, COUNTIFS($AR$2:$AR$200,$G11)>0, COUNTIFS($AS$2:$AS$200,$G11)>0, COUNTIFS($AT$2:$AT$200,$G11)>0, COUNTIFS($AU$2:$AU$200,$G11)>0, COUNTIFS($AV$2:$AV$200,$G11)>0, COUNTIFS($AW$2:$AW$200,$G11)>0, COUNTIFS($AX$2:$AX$200,$G11)>0 )), ), 3 ), "")} | F11: {=IFERROR( INDEX( _xlfn._xlws.FILTER($U$1:$AX$1, TRANSPOSE( CHOOSE({1;2;3;4;5;6;7;8;9;10;11;12;13;14;15;16;17;18;19;20;21;22;23;24;25;26;27;28;29;30}, COUNTIFS($U$2:$U$200,$G11)>0, COUNTIFS($V$2:$V$200,$G11)>0, COUNTIFS($W$2:$W$200,$G11)>0, COUNTIFS($X$2:$X$200,$G11)>0, COUNTIFS($Y$2:$Y$200,$G11)>0, COUNTIFS($Z$2:$Z$200,$G11)>0, COUNTIFS($AA$2:$AA$200,$G11)>0, COUNTIFS($AB$2:$AB$200,$G11)>0, COUNTIFS($AC$2:$AC$200,$G11)>0, COUNTIFS($AD$2:$AD$200,$G11)>0, COUNTIFS($AE$2:$AE$200,$G11)>0, COUNTIFS($AF$2:$AF$200,$G11)>0, COUNTIFS($AG$2:$AG$200,$G11)>0, COUNTIFS($AH$2:$AH$200,$G11)>0, COUNTIFS($AI$2:$AI$200,$G11)>0, COUNTIFS($AJ$2:$AJ$200,$G11)>0, COUNTIFS($AK$2:$AK$200,$G11)>0, COUNTIFS($AL$2:$AL$200,$G11)>0, COUNTIFS($AM$2:$AM$200,$G11)>0, COUNTIFS($AN$2:$AN$200,$G11)>0, COUNTIFS($AO$2:$AO$200,$G11)>0, COUNTIFS($AP$2:$AP$200,$G11)>0, COUNTIFS($AQ$2:$AQ$200,$G11)>0, COUNTIFS($AR$2:$AR$200,$G11)>0, COUNTIFS($AS$2:$AS$200,$G11)>0, COUNTIFS($AT$2:$AT$200,$G11)>0, COUNTIFS($AU$2:$AU$200,$G11)>0, COUNTIFS($AV$2:$AV$200,$G11)>0, COUNTIFS($AW$2:$AW$200,$G11)>0, COUNTIFS($AX$2:$AX$200,$G11)>0 )), ), 4 ), "")} | G11: Ancient Den | I11: JhoiraB | J11: =JhoiraB!G2 -> 12 | K11: Não | L11: Sim | M11: Sim | N11: Não | O11: Não | P11: Combo | Q11: Combate | R11: Big Mana | S11: =IF(J11<6,"5",IF(J11<11,"4",IF(J11<16,"3",IF(J11<31,"2","1")))) -> 3 | U11: Glint-Horn Buccaneer | V11: Farmer Cotton | W11: Khorvath's Fury | X11: Dever Além da Morte | Y11: Mother of runes | Z11: Gallifrey Council Chamber | AA11: Merrow Harbinger | AB11: Teferi's Ageless Insight | AC11: Ulamog, o Profanador | AD11: Takenuma, Charco Abandonado | AE11: Sonic Screwdriver | AF11: Vontade Dominadora | AG11: Temporal Trespass | AH11: Reliquary Tower | AI11: Kellan, the Fae-Blooded // Birthright Boon | AJ11: Ripples of Potential | AX11: Arcbound Ravager | AZ11: Matoya, Archon Elder | BA11: Mirrex | BB11: Renewed Solidarity | BC11: Homeward Path | BD11: Exemplar of Light | BE11: Espada de Luz e Sombra | BF11: Equilíbrio de Poderes | BG11: Full Throttle | BH11: Canopy Vista | BI11: Arcbound Ravager | BK11: Dionus, Elvish Archdruid | BL11: Chronomantic Escape | BM11: Cloud, Midgar Mercenary | BN11: Commodore Guff | BO11: Arcbound Ravager | BQ11: Baral, Chief of Compliance | BR11: Bloodstained Mire | BT11: Ancient Greenwarden
A12: =IFERROR(INDEX($S$3:$S$200, MATCH($C12, $I$3:$I$200, 0)), "") -> 3 | B12: =COUNTIF(U:AX,G12) -> 1 | C12: =IFERROR( INDEX($U$1:$AX$1, MATCH(TRUE, CHOOSE({1;2;3;4;5;6;7;8;9;10;11;12;13;14;15;16;17;18;19;20;21;22;23;24;25;26;27;28;29;30;31;32}, COUNTIFS($U$2:$U$200,$G12)>0, COUNTIFS($V$2:$V$200,$G12)>0, COUNTIFS($W$2:$W$200,$G12)>0, COUNTIFS($X$2:$X$200,$G12)>0, COUNTIFS($Y$2:$Y$200,$G12)>0, COUNTIFS($Z$2:$Z$200,$G12)>0, COUNTIFS($AA$2:$AA$200,$G12)>0, COUNTIFS($AB$2:$AB$200,$G12)>0, COUNTIFS($AC$2:$AC$200,$G12)>0, COUNTIFS($AD$2:$AD$200,$G12)>0, COUNTIFS($AE$2:$AE$200,$G12)>0, COUNTIFS($AF$2:$AF$200,$G12)>0, COUNTIFS($AG$2:$AG$200,$G12)>0, COUNTIFS($AH$2:$AH$200,$G12)>0, COUNTIFS($AI$2:$AI$200,$G12)>0, COUNTIFS($AJ$2:$AJ$200,$G12)>0, COUNTIFS($AK$2:$AK$200,$G12)>0, COUNTIFS($AL$2:$AL$200,$G12)>0, COUNTIFS($AM$2:$AM$200,$G12)>0, COUNTIFS($AN$2:$AN$200,$G12)>0, COUNTIFS($AO$2:$AO$200,$G12)>0, COUNTIFS($AP$2:$AP$200,$G12)>0, COUNTIFS($AQ$2:$AQ$200,$G12)>0, COUNTIFS($AR$2:$AR$200,$G12)>0, COUNTIFS($AS$2:$AS$200,$G12)>0, COUNTIFS($AT$2:$AT$200,$G12)>0, COUNTIFS($AU$2:$AU$200,$G12)>0, COUNTIFS($AV$2:$AV$200,$G12)>0, COUNTIFS($AW$2:$AW$200,$G12)>0, COUNTIFS($AX$2:$AX$200,$G12)>0 ), 0) ), "") -> Zimone | D12: {=IFERROR( INDEX( _xlfn._xlws.FILTER($U$1:$AX$1, TRANSPOSE( CHOOSE({1;2;3;4;5;6;7;8;9;10;11;12;13;14;15;16;17;18;19;20;21;22;23;24;25;26;27;28;29;30}, COUNTIFS($U$2:$U$200,$G12)>0, COUNTIFS($V$2:$V$200,$G12)>0, COUNTIFS($W$2:$W$200,$G12)>0, COUNTIFS($X$2:$X$200,$G12)>0, COUNTIFS($Y$2:$Y$200,$G12)>0, COUNTIFS($Z$2:$Z$200,$G12)>0, COUNTIFS($AA$2:$AA$200,$G12)>0, COUNTIFS($AB$2:$AB$200,$G12)>0, COUNTIFS($AC$2:$AC$200,$G12)>0, COUNTIFS($AD$2:$AD$200,$G12)>0, COUNTIFS($AE$2:$AE$200,$G12)>0, COUNTIFS($AF$2:$AF$200,$G12)>0, COUNTIFS($AG$2:$AG$200,$G12)>0, COUNTIFS($AH$2:$AH$200,$G12)>0, COUNTIFS($AI$2:$AI$200,$G12)>0, COUNTIFS($AJ$2:$AJ$200,$G12)>0, COUNTIFS($AK$2:$AK$200,$G12)>0, COUNTIFS($AL$2:$AL$200,$G12)>0, COUNTIFS($AM$2:$AM$200,$G12)>0, COUNTIFS($AN$2:$AN$200,$G12)>0, COUNTIFS($AO$2:$AO$200,$G12)>0, COUNTIFS($AP$2:$AP$200,$G12)>0, COUNTIFS($AQ$2:$AQ$200,$G12)>0, COUNTIFS($AR$2:$AR$200,$G12)>0, COUNTIFS($AS$2:$AS$200,$G12)>0, COUNTIFS($AT$2:$AT$200,$G12)>0, COUNTIFS($AU$2:$AU$200,$G12)>0, COUNTIFS($AV$2:$AV$200,$G12)>0, COUNTIFS($AW$2:$AW$200,$G12)>0, COUNTIFS($AX$2:$AX$200,$G12)>0 )), ), 2 ), "")} | E12: {=IFERROR( INDEX( _xlfn._xlws.FILTER($U$1:$AX$1, TRANSPOSE( CHOOSE({1;2;3;4;5;6;7;8;9;10;11;12;13;14;15;16;17;18;19;20;21;22;23;24;25;26;27;28;29;30}, COUNTIFS($U$2:$U$200,$G12)>0, COUNTIFS($V$2:$V$200,$G12)>0, COUNTIFS($W$2:$W$200,$G12)>0, COUNTIFS($X$2:$X$200,$G12)>0, COUNTIFS($Y$2:$Y$200,$G12)>0, COUNTIFS($Z$2:$Z$200,$G12)>0, COUNTIFS($AA$2:$AA$200,$G12)>0, COUNTIFS($AB$2:$AB$200,$G12)>0, COUNTIFS($AC$2:$AC$200,$G12)>0, COUNTIFS($AD$2:$AD$200,$G12)>0, COUNTIFS($AE$2:$AE$200,$G12)>0, COUNTIFS($AF$2:$AF$200,$G12)>0, COUNTIFS($AG$2:$AG$200,$G12)>0, COUNTIFS($AH$2:$AH$200,$G12)>0, COUNTIFS($AI$2:$AI$200,$G12)>0, COUNTIFS($AJ$2:$AJ$200,$G12)>0, COUNTIFS($AK$2:$AK$200,$G12)>0, COUNTIFS($AL$2:$AL$200,$G12)>0, COUNTIFS($AM$2:$AM$200,$G12)>0, COUNTIFS($AN$2:$AN$200,$G12)>0, COUNTIFS($AO$2:$AO$200,$G12)>0, COUNTIFS($AP$2:$AP$200,$G12)>0, COUNTIFS($AQ$2:$AQ$200,$G12)>0, COUNTIFS($AR$2:$AR$200,$G12)>0, COUNTIFS($AS$2:$AS$200,$G12)>0, COUNTIFS($AT$2:$AT$200,$G12)>0, COUNTIFS($AU$2:$AU$200,$G12)>0, COUNTIFS($AV$2:$AV$200,$G12)>0, COUNTIFS($AW$2:$AW$200,$G12)>0, COUNTIFS($AX$2:$AX$200,$G12)>0 )), ), 3 ), "")} | F12: {=IFERROR( INDEX( _xlfn._xlws.FILTER($U$1:$AX$1, TRANSPOSE( CHOOSE({1;2;3;4;5;6;7;8;9;10;11;12;13;14;15;16;17;18;19;20;21;22;23;24;25;26;27;28;29;30}, COUNTIFS($U$2:$U$200,$G12)>0, COUNTIFS($V$2:$V$200,$G12)>0, COUNTIFS($W$2:$W$200,$G12)>0, COUNTIFS($X$2:$X$200,$G12)>0, COUNTIFS($Y$2:$Y$200,$G12)>0, COUNTIFS($Z$2:$Z$200,$G12)>0, COUNTIFS($AA$2:$AA$200,$G12)>0, COUNTIFS($AB$2:$AB$200,$G12)>0, COUNTIFS($AC$2:$AC$200,$G12)>0, COUNTIFS($AD$2:$AD$200,$G12)>0, COUNTIFS($AE$2:$AE$200,$G12)>0, COUNTIFS($AF$2:$AF$200,$G12)>0, COUNTIFS($AG$2:$AG$200,$G12)>0, COUNTIFS($AH$2:$AH$200,$G12)>0, COUNTIFS($AI$2:$AI$200,$G12)>0, COUNTIFS($AJ$2:$AJ$200,$G12)>0, COUNTIFS($AK$2:$AK$200,$G12)>0, COUNTIFS($AL$2:$AL$200,$G12)>0, COUNTIFS($AM$2:$AM$200,$G12)>0, COUNTIFS($AN$2:$AN$200,$G12)>0, COUNTIFS($AO$2:$AO$200,$G12)>0, COUNTIFS($AP$2:$AP$200,$G12)>0, COUNTIFS($AQ$2:$AQ$200,$G12)>0, COUNTIFS($AR$2:$AR$200,$G12)>0, COUNTIFS($AS$2:$AS$200,$G12)>0, COUNTIFS($AT$2:$AT$200,$G12)>0, COUNTIFS($AU$2:$AU$200,$G12)>0, COUNTIFS($AV$2:$AV$200,$G12)>0, COUNTIFS($AW$2:$AW$200,$G12)>0, COUNTIFS($AX$2:$AX$200,$G12)>0 )), ), 4 ), "")} | G12: Ancient Greenwarden | I12: Gritrog | J12: =Gitrog!G2 -> 12 | K12: Não | L12: Não | M12: Não | N12: Sim | O12: Sim | P12: Combo | Q12: - | R12: Fast Combo | S12: =IF(J12<6,"5",IF(J12<11,"4",IF(J12<16,"3",IF(J12<31,"2","1")))) -> 3 | U12: Go for the Throat | V12: Farseek | W12: Lightning Greaves | X12: Devoted Druid | Y12: Sorin da Casa Markov | Z12: Havengul Laboratory | AA12: Reliquary Tower | AB12: Thousand-Year Elixir | AC12: Ulamog's Dreadsire | AD12: Titania, Voice of Gaea | AE12: The Mycosynth Gardens | AF12: Watery Grave | AG12: Valfenda | AH12: Saw in Half | AI12: Lightning Greaves | AJ12: Vronos, Masked Inquisitor | AX12: Arcbound Reclaimer | AZ12: Nissa, Resurgent Animist | BA12: Mistrise Village | BB12: Serenata das Estriges | BC12: Louisoix's Sacrifice | BD12: Giver of Runes | BE12: Espada de Verdade e Justiça | BF12: Fellwar Stone | BG12: Genji Glove | BH12: Canopy Vista | BI12: Arcbound Reclaimer | BK12: Emrakul, um Novo Mundo | BL12: Collector's Vault | BM12: Daretti, Ingenious Iconoclast | BN12: Counterspell | BO12: Arcbound Reclaimer | BQ12: Batwing Brume | BR12: Bojuka Bog | BT12: Ancient Tomb
A13: =IFERROR(INDEX($S$3:$S$200, MATCH($C13, $I$3:$I$200, 0)), "") -> 3 | B13: =COUNTIF(U:AX,G13) -> 1 | C13: =IFERROR( INDEX($U$1:$AX$1, MATCH(TRUE, CHOOSE({1;2;3;4;5;6;7;8;9;10;11;12;13;14;15;16;17;18;19;20;21;22;23;24;25;26;27;28;29;30;31;32}, COUNTIFS($U$2:$U$200,$G13)>0, COUNTIFS($V$2:$V$200,$G13)>0, COUNTIFS($W$2:$W$200,$G13)>0, COUNTIFS($X$2:$X$200,$G13)>0, COUNTIFS($Y$2:$Y$200,$G13)>0, COUNTIFS($Z$2:$Z$200,$G13)>0, COUNTIFS($AA$2:$AA$200,$G13)>0, COUNTIFS($AB$2:$AB$200,$G13)>0, COUNTIFS($AC$2:$AC$200,$G13)>0, COUNTIFS($AD$2:$AD$200,$G13)>0, COUNTIFS($AE$2:$AE$200,$G13)>0, COUNTIFS($AF$2:$AF$200,$G13)>0, COUNTIFS($AG$2:$AG$200,$G13)>0, COUNTIFS($AH$2:$AH$200,$G13)>0, COUNTIFS($AI$2:$AI$200,$G13)>0, COUNTIFS($AJ$2:$AJ$200,$G13)>0, COUNTIFS($AK$2:$AK$200,$G13)>0, COUNTIFS($AL$2:$AL$200,$G13)>0, COUNTIFS($AM$2:$AM$200,$G13)>0, COUNTIFS($AN$2:$AN$200,$G13)>0, COUNTIFS($AO$2:$AO$200,$G13)>0, COUNTIFS($AP$2:$AP$200,$G13)>0, COUNTIFS($AQ$2:$AQ$200,$G13)>0, COUNTIFS($AR$2:$AR$200,$G13)>0, COUNTIFS($AS$2:$AS$200,$G13)>0, COUNTIFS($AT$2:$AT$200,$G13)>0, COUNTIFS($AU$2:$AU$200,$G13)>0, COUNTIFS($AV$2:$AV$200,$G13)>0, COUNTIFS($AW$2:$AW$200,$G13)>0, COUNTIFS($AX$2:$AX$200,$G13)>0 ), 0) ), "") -> Gritrog | D13: {=IFERROR( INDEX( _xlfn._xlws.FILTER($U$1:$AX$1, TRANSPOSE( CHOOSE({1;2;3;4;5;6;7;8;9;10;11;12;13;14;15;16;17;18;19;20;21;22;23;24;25;26;27;28;29;30}, COUNTIFS($U$2:$U$200,$G13)>0, COUNTIFS($V$2:$V$200,$G13)>0, COUNTIFS($W$2:$W$200,$G13)>0, COUNTIFS($X$2:$X$200,$G13)>0, COUNTIFS($Y$2:$Y$200,$G13)>0, COUNTIFS($Z$2:$Z$200,$G13)>0, COUNTIFS($AA$2:$AA$200,$G13)>0, COUNTIFS($AB$2:$AB$200,$G13)>0, COUNTIFS($AC$2:$AC$200,$G13)>0, COUNTIFS($AD$2:$AD$200,$G13)>0, COUNTIFS($AE$2:$AE$200,$G13)>0, COUNTIFS($AF$2:$AF$200,$G13)>0, COUNTIFS($AG$2:$AG$200,$G13)>0, COUNTIFS($AH$2:$AH$200,$G13)>0, COUNTIFS($AI$2:$AI$200,$G13)>0, COUNTIFS($AJ$2:$AJ$200,$G13)>0, COUNTIFS($AK$2:$AK$200,$G13)>0, COUNTIFS($AL$2:$AL$200,$G13)>0, COUNTIFS($AM$2:$AM$200,$G13)>0, COUNTIFS($AN$2:$AN$200,$G13)>0, COUNTIFS($AO$2:$AO$200,$G13)>0, COUNTIFS($AP$2:$AP$200,$G13)>0, COUNTIFS($AQ$2:$AQ$200,$G13)>0, COUNTIFS($AR$2:$AR$200,$G13)>0, COUNTIFS($AS$2:$AS$200,$G13)>0, COUNTIFS($AT$2:$AT$200,$G13)>0, COUNTIFS($AU$2:$AU$200,$G13)>0, COUNTIFS($AV$2:$AV$200,$G13)>0, COUNTIFS($AW$2:$AW$200,$G13)>0, COUNTIFS($AX$2:$AX$200,$G13)>0 )), ), 2 ), "")} | E13: {=IFERROR( INDEX( _xlfn._xlws.FILTER($U$1:$AX$1, TRANSPOSE( CHOOSE({1;2;3;4;5;6;7;8;9;10;11;12;13;14;15;16;17;18;19;20;21;22;23;24;25;26;27;28;29;30}, COUNTIFS($U$2:$U$200,$G13)>0, COUNTIFS($V$2:$V$200,$G13)>0, COUNTIFS($W$2:$W$200,$G13)>0, COUNTIFS($X$2:$X$200,$G13)>0, COUNTIFS($Y$2:$Y$200,$G13)>0, COUNTIFS($Z$2:$Z$200,$G13)>0, COUNTIFS($AA$2:$AA$200,$G13)>0, COUNTIFS($AB$2:$AB$200,$G13)>0, COUNTIFS($AC$2:$AC$200,$G13)>0, COUNTIFS($AD$2:$AD$200,$G13)>0, COUNTIFS($AE$2:$AE$200,$G13)>0, COUNTIFS($AF$2:$AF$200,$G13)>0, COUNTIFS($AG$2:$AG$200,$G13)>0, COUNTIFS($AH$2:$AH$200,$G13)>0, COUNTIFS($AI$2:$AI$200,$G13)>0, COUNTIFS($AJ$2:$AJ$200,$G13)>0, COUNTIFS($AK$2:$AK$200,$G13)>0, COUNTIFS($AL$2:$AL$200,$G13)>0, COUNTIFS($AM$2:$AM$200,$G13)>0, COUNTIFS($AN$2:$AN$200,$G13)>0, COUNTIFS($AO$2:$AO$200,$G13)>0, COUNTIFS($AP$2:$AP$200,$G13)>0, COUNTIFS($AQ$2:$AQ$200,$G13)>0, COUNTIFS($AR$2:$AR$200,$G13)>0, COUNTIFS($AS$2:$AS$200,$G13)>0, COUNTIFS($AT$2:$AT$200,$G13)>0, COUNTIFS($AU$2:$AU$200,$G13)>0, COUNTIFS($AV$2:$AV$200,$G13)>0, COUNTIFS($AW$2:$AW$200,$G13)>0, COUNTIFS($AX$2:$AX$200,$G13)>0 )), ), 3 ), "")} | F13: {=IFERROR( INDEX( _xlfn._xlws.FILTER($U$1:$AX$1, TRANSPOSE( CHOOSE({1;2;3;4;5;6;7;8;9;10;11;12;13;14;15;16;17;18;19;20;21;22;23;24;25;26;27;28;29;30}, COUNTIFS($U$2:$U$200,$G13)>0, COUNTIFS($V$2:$V$200,$G13)>0, COUNTIFS($W$2:$W$200,$G13)>0, COUNTIFS($X$2:$X$200,$G13)>0, COUNTIFS($Y$2:$Y$200,$G13)>0, COUNTIFS($Z$2:$Z$200,$G13)>0, COUNTIFS($AA$2:$AA$200,$G13)>0, COUNTIFS($AB$2:$AB$200,$G13)>0, COUNTIFS($AC$2:$AC$200,$G13)>0, COUNTIFS($AD$2:$AD$200,$G13)>0, COUNTIFS($AE$2:$AE$200,$G13)>0, COUNTIFS($AF$2:$AF$200,$G13)>0, COUNTIFS($AG$2:$AG$200,$G13)>0, COUNTIFS($AH$2:$AH$200,$G13)>0, COUNTIFS($AI$2:$AI$200,$G13)>0, COUNTIFS($AJ$2:$AJ$200,$G13)>0, COUNTIFS($AK$2:$AK$200,$G13)>0, COUNTIFS($AL$2:$AL$200,$G13)>0, COUNTIFS($AM$2:$AM$200,$G13)>0, COUNTIFS($AN$2:$AN$200,$G13)>0, COUNTIFS($AO$2:$AO$200,$G13)>0, COUNTIFS($AP$2:$AP$200,$G13)>0, COUNTIFS($AQ$2:$AQ$200,$G13)>0, COUNTIFS($AR$2:$AR$200,$G13)>0, COUNTIFS($AS$2:$AS$200,$G13)>0, COUNTIFS($AT$2:$AT$200,$G13)>0, COUNTIFS($AU$2:$AU$200,$G13)>0, COUNTIFS($AV$2:$AV$200,$G13)>0, COUNTIFS($AW$2:$AW$200,$G13)>0, COUNTIFS($AX$2:$AX$200,$G13)>0 )), ), 4 ), "")} | G13: Ancient Tomb | I13: Muzzio | J13: =Muzzio!G2 -> 12 | K13: Não | L13: Sim | M13: Não | N13: Não | O13: Não | P13: Combo | Q13: - | R13: Engrenagens para Combar | S13: =IF(J13<6,"5",IF(J13<11,"4",IF(J13<16,"3",IF(J13<31,"2","1")))) -> 3 | U13: Hedron Detonator | V13: Gavony Township | W13: Maddening Cacophony | X13: Exotic Orchard | Y13: Takenuma, Charco Abandonado | Z13: Life of the Party | AA13: Seahunter | AB13: Three Visits | AC13: Valfenda | AD13: Ulamog, the Infinite Gyre | AE13: Vexing Puzzlebox | AG13: Watery Grave | AH13: Warren Soultrader | AI13: Stoneforge Mystic | AX13: Arcbound Shikari | AZ13: Obelisco de Obsidiana | BA13: Planetary Annihilation | BB13: Sokenzan, Crisol da Afronta | BC13: Luxury Suite | BD13: Glasspool Mimic | BE13: Firion, Wild Rose Warrior | BF13: Frenzied Gorespawn | BG13: Ghostly Prison | BH13: Castle Ardenvale | BI13: Arcbound Shikari | BK13: Entomb | BL13: Creeping Tar Pit | BM13: Diário de Tarrian | BN13: Cyber Conversion | BO13: Arcbound Shikari | BQ13: Broodheart Engine | BR13: Bugenhagen, Wise Elder | BT13: Árbitro Silencioso
A14: =IFERROR(INDEX($S$3:$S$200, MATCH($C14, $I$3:$I$200, 0)), "") -> 1 | B14: =COUNTIF(U:AX,G14) -> 1 | C14: =IFERROR( INDEX($U$1:$AX$1, MATCH(TRUE, CHOOSE({1;2;3;4;5;6;7;8;9;10;11;12;13;14;15;16;17;18;19;20;21;22;23;24;25;26;27;28;29;30;31;32}, COUNTIFS($U$2:$U$200,$G14)>0, COUNTIFS($V$2:$V$200,$G14)>0, COUNTIFS($W$2:$W$200,$G14)>0, COUNTIFS($X$2:$X$200,$G14)>0, COUNTIFS($Y$2:$Y$200,$G14)>0, COUNTIFS($Z$2:$Z$200,$G14)>0, COUNTIFS($AA$2:$AA$200,$G14)>0, COUNTIFS($AB$2:$AB$200,$G14)>0, COUNTIFS($AC$2:$AC$200,$G14)>0, COUNTIFS($AD$2:$AD$200,$G14)>0, COUNTIFS($AE$2:$AE$200,$G14)>0, COUNTIFS($AF$2:$AF$200,$G14)>0, COUNTIFS($AG$2:$AG$200,$G14)>0, COUNTIFS($AH$2:$AH$200,$G14)>0, COUNTIFS($AI$2:$AI$200,$G14)>0, COUNTIFS($AJ$2:$AJ$200,$G14)>0, COUNTIFS($AK$2:$AK$200,$G14)>0, COUNTIFS($AL$2:$AL$200,$G14)>0, COUNTIFS($AM$2:$AM$200,$G14)>0, COUNTIFS($AN$2:$AN$200,$G14)>0, COUNTIFS($AO$2:$AO$200,$G14)>0, COUNTIFS($AP$2:$AP$200,$G14)>0, COUNTIFS($AQ$2:$AQ$200,$G14)>0, COUNTIFS($AR$2:$AR$200,$G14)>0, COUNTIFS($AS$2:$AS$200,$G14)>0, COUNTIFS($AT$2:$AT$200,$G14)>0, COUNTIFS($AU$2:$AU$200,$G14)>0, COUNTIFS($AV$2:$AV$200,$G14)>0, COUNTIFS($AW$2:$AW$200,$G14)>0, COUNTIFS($AX$2:$AX$200,$G14)>0 ), 0) ), "") -> Modular | D14: {=IFERROR( INDEX( _xlfn._xlws.FILTER($U$1:$AX$1, TRANSPOSE( CHOOSE({1;2;3;4;5;6;7;8;9;10;11;12;13;14;15;16;17;18;19;20;21;22;23;24;25;26;27;28;29;30}, COUNTIFS($U$2:$U$200,$G14)>0, COUNTIFS($V$2:$V$200,$G14)>0, COUNTIFS($W$2:$W$200,$G14)>0, COUNTIFS($X$2:$X$200,$G14)>0, COUNTIFS($Y$2:$Y$200,$G14)>0, COUNTIFS($Z$2:$Z$200,$G14)>0, COUNTIFS($AA$2:$AA$200,$G14)>0, COUNTIFS($AB$2:$AB$200,$G14)>0, COUNTIFS($AC$2:$AC$200,$G14)>0, COUNTIFS($AD$2:$AD$200,$G14)>0, COUNTIFS($AE$2:$AE$200,$G14)>0, COUNTIFS($AF$2:$AF$200,$G14)>0, COUNTIFS($AG$2:$AG$200,$G14)>0, COUNTIFS($AH$2:$AH$200,$G14)>0, COUNTIFS($AI$2:$AI$200,$G14)>0, COUNTIFS($AJ$2:$AJ$200,$G14)>0, COUNTIFS($AK$2:$AK$200,$G14)>0, COUNTIFS($AL$2:$AL$200,$G14)>0, COUNTIFS($AM$2:$AM$200,$G14)>0, COUNTIFS($AN$2:$AN$200,$G14)>0, COUNTIFS($AO$2:$AO$200,$G14)>0, COUNTIFS($AP$2:$AP$200,$G14)>0, COUNTIFS($AQ$2:$AQ$200,$G14)>0, COUNTIFS($AR$2:$AR$200,$G14)>0, COUNTIFS($AS$2:$AS$200,$G14)>0, COUNTIFS($AT$2:$AT$200,$G14)>0, COUNTIFS($AU$2:$AU$200,$G14)>0, COUNTIFS($AV$2:$AV$200,$G14)>0, COUNTIFS($AW$2:$AW$200,$G14)>0, COUNTIFS($AX$2:$AX$200,$G14)>0 )), ), 2 ), "")} | E14: {=IFERROR( INDEX( _xlfn._xlws.FILTER($U$1:$AX$1, TRANSPOSE( CHOOSE({1;2;3;4;5;6;7;8;9;10;11;12;13;14;15;16;17;18;19;20;21;22;23;24;25;26;27;28;29;30}, COUNTIFS($U$2:$U$200,$G14)>0, COUNTIFS($V$2:$V$200,$G14)>0, COUNTIFS($W$2:$W$200,$G14)>0, COUNTIFS($X$2:$X$200,$G14)>0, COUNTIFS($Y$2:$Y$200,$G14)>0, COUNTIFS($Z$2:$Z$200,$G14)>0, COUNTIFS($AA$2:$AA$200,$G14)>0, COUNTIFS($AB$2:$AB$200,$G14)>0, COUNTIFS($AC$2:$AC$200,$G14)>0, COUNTIFS($AD$2:$AD$200,$G14)>0, COUNTIFS($AE$2:$AE$200,$G14)>0, COUNTIFS($AF$2:$AF$200,$G14)>0, COUNTIFS($AG$2:$AG$200,$G14)>0, COUNTIFS($AH$2:$AH$200,$G14)>0, COUNTIFS($AI$2:$AI$200,$G14)>0, COUNTIFS($AJ$2:$AJ$200,$G14)>0, COUNTIFS($AK$2:$AK$200,$G14)>0, COUNTIFS($AL$2:$AL$200,$G14)>0, COUNTIFS($AM$2:$AM$200,$G14)>0, COUNTIFS($AN$2:$AN$200,$G14)>0, COUNTIFS($AO$2:$AO$200,$G14)>0, COUNTIFS($AP$2:$AP$200,$G14)>0, COUNTIFS($AQ$2:$AQ$200,$G14)>0, COUNTIFS($AR$2:$AR$200,$G14)>0, COUNTIFS($AS$2:$AS$200,$G14)>0, COUNTIFS($AT$2:$AT$200,$G14)>0, COUNTIFS($AU$2:$AU$200,$G14)>0, COUNTIFS($AV$2:$AV$200,$G14)>0, COUNTIFS($AW$2:$AW$200,$G14)>0, COUNTIFS($AX$2:$AX$200,$G14)>0 )), ), 3 ), "")} | F14: {=IFERROR( INDEX( _xlfn._xlws.FILTER($U$1:$AX$1, TRANSPOSE( CHOOSE({1;2;3;4;5;6;7;8;9;10;11;12;13;14;15;16;17;18;19;20;21;22;23;24;25;26;27;28;29;30}, COUNTIFS($U$2:$U$200,$G14)>0, COUNTIFS($V$2:$V$200,$G14)>0, COUNTIFS($W$2:$W$200,$G14)>0, COUNTIFS($X$2:$X$200,$G14)>0, COUNTIFS($Y$2:$Y$200,$G14)>0, COUNTIFS($Z$2:$Z$200,$G14)>0, COUNTIFS($AA$2:$AA$200,$G14)>0, COUNTIFS($AB$2:$AB$200,$G14)>0, COUNTIFS($AC$2:$AC$200,$G14)>0, COUNTIFS($AD$2:$AD$200,$G14)>0, COUNTIFS($AE$2:$AE$200,$G14)>0, COUNTIFS($AF$2:$AF$200,$G14)>0, COUNTIFS($AG$2:$AG$200,$G14)>0, COUNTIFS($AH$2:$AH$200,$G14)>0, COUNTIFS($AI$2:$AI$200,$G14)>0, COUNTIFS($AJ$2:$AJ$200,$G14)>0, COUNTIFS($AK$2:$AK$200,$G14)>0, COUNTIFS($AL$2:$AL$200,$G14)>0, COUNTIFS($AM$2:$AM$200,$G14)>0, COUNTIFS($AN$2:$AN$200,$G14)>0, COUNTIFS($AO$2:$AO$200,$G14)>0, COUNTIFS($AP$2:$AP$200,$G14)>0, COUNTIFS($AQ$2:$AQ$200,$G14)>0, COUNTIFS($AR$2:$AR$200,$G14)>0, COUNTIFS($AS$2:$AS$200,$G14)>0, COUNTIFS($AT$2:$AT$200,$G14)>0, COUNTIFS($AU$2:$AU$200,$G14)>0, COUNTIFS($AV$2:$AV$200,$G14)>0, COUNTIFS($AW$2:$AW$200,$G14)>0, COUNTIFS($AX$2:$AX$200,$G14)>0 )), ), 4 ), "")} | G14: Annie Joins Up | I14: VialIshai | J14: =VialIshai!G2 -> 11 | K14: Sim | L14: Sim | M14: Sim | N14: Sim | O14: Não | P14: Ping | Q14: Voltron | R14: Controlar e Punir | S14: =IF(J14<6,"5",IF(J14<11,"4",IF(J14<16,"3",IF(J14<31,"2","1")))) -> 3 | U14: Malcolm, Alluring Scoundrel | V14: Generous Gift | W14: Memory Erosion | X14: Gavony Township | Y14: Terramorphic Expanse | Z14: Reliquary Tower | AA14: Simic Charm | AB14: Zagoth Triome | AX14: Arcbound Slith | AZ14: Petrified Field | BA14: Portal to Phyrexia | BB14: Teyo, Geometric Tactician | BC14: Mandate of Peace | BD14: Guia das Almas | BE14: High-Society Hunter | BF14: Freyalise, Llanowar's Fury | BG14: Grave Pact | BH14: Champion of Lambholt | BI14: Arcbound Slith | BK14: Evendo, Waking Haven | BL14: Drowned Catacomb | BM14: Dour Port-Mage | BN14: Deeproot Historian | BO14: Arcbound Slith | BQ14: Careful Study | BR14: Burnt Offering | BT14: Arcane Lighthouse
A15: =IFERROR(INDEX($S$3:$S$200, MATCH($C15, $I$3:$I$200, 0)), "") -> 5 | B15: =COUNTIF(U:AX,G15) -> 1 | C15: =IFERROR( INDEX($U$1:$AX$1, MATCH(TRUE, CHOOSE({1;2;3;4;5;6;7;8;9;10;11;12;13;14;15;16;17;18;19;20;21;22;23;24;25;26;27;28;29;30;31;32}, COUNTIFS($U$2:$U$200,$G15)>0, COUNTIFS($V$2:$V$200,$G15)>0, COUNTIFS($W$2:$W$200,$G15)>0, COUNTIFS($X$2:$X$200,$G15)>0, COUNTIFS($Y$2:$Y$200,$G15)>0, COUNTIFS($Z$2:$Z$200,$G15)>0, COUNTIFS($AA$2:$AA$200,$G15)>0, COUNTIFS($AB$2:$AB$200,$G15)>0, COUNTIFS($AC$2:$AC$200,$G15)>0, COUNTIFS($AD$2:$AD$200,$G15)>0, COUNTIFS($AE$2:$AE$200,$G15)>0, COUNTIFS($AF$2:$AF$200,$G15)>0, COUNTIFS($AG$2:$AG$200,$G15)>0, COUNTIFS($AH$2:$AH$200,$G15)>0, COUNTIFS($AI$2:$AI$200,$G15)>0, COUNTIFS($AJ$2:$AJ$200,$G15)>0, COUNTIFS($AK$2:$AK$200,$G15)>0, COUNTIFS($AL$2:$AL$200,$G15)>0, COUNTIFS($AM$2:$AM$200,$G15)>0, COUNTIFS($AN$2:$AN$200,$G15)>0, COUNTIFS($AO$2:$AO$200,$G15)>0, COUNTIFS($AP$2:$AP$200,$G15)>0, COUNTIFS($AQ$2:$AQ$200,$G15)>0, COUNTIFS($AR$2:$AR$200,$G15)>0, COUNTIFS($AS$2:$AS$200,$G15)>0, COUNTIFS($AT$2:$AT$200,$G15)>0, COUNTIFS($AU$2:$AU$200,$G15)>0, COUNTIFS($AV$2:$AV$200,$G15)>0, COUNTIFS($AW$2:$AW$200,$G15)>0, COUNTIFS($AX$2:$AX$200,$G15)>0 ), 0) ), "") -> Zedruu | D15: {=IFERROR( INDEX( _xlfn._xlws.FILTER($U$1:$AX$1, TRANSPOSE( CHOOSE({1;2;3;4;5;6;7;8;9;10;11;12;13;14;15;16;17;18;19;20;21;22;23;24;25;26;27;28;29;30}, COUNTIFS($U$2:$U$200,$G15)>0, COUNTIFS($V$2:$V$200,$G15)>0, COUNTIFS($W$2:$W$200,$G15)>0, COUNTIFS($X$2:$X$200,$G15)>0, COUNTIFS($Y$2:$Y$200,$G15)>0, COUNTIFS($Z$2:$Z$200,$G15)>0, COUNTIFS($AA$2:$AA$200,$G15)>0, COUNTIFS($AB$2:$AB$200,$G15)>0, COUNTIFS($AC$2:$AC$200,$G15)>0, COUNTIFS($AD$2:$AD$200,$G15)>0, COUNTIFS($AE$2:$AE$200,$G15)>0, COUNTIFS($AF$2:$AF$200,$G15)>0, COUNTIFS($AG$2:$AG$200,$G15)>0, COUNTIFS($AH$2:$AH$200,$G15)>0, COUNTIFS($AI$2:$AI$200,$G15)>0, COUNTIFS($AJ$2:$AJ$200,$G15)>0, COUNTIFS($AK$2:$AK$200,$G15)>0, COUNTIFS($AL$2:$AL$200,$G15)>0, COUNTIFS($AM$2:$AM$200,$G15)>0, COUNTIFS($AN$2:$AN$200,$G15)>0, COUNTIFS($AO$2:$AO$200,$G15)>0, COUNTIFS($AP$2:$AP$200,$G15)>0, COUNTIFS($AQ$2:$AQ$200,$G15)>0, COUNTIFS($AR$2:$AR$200,$G15)>0, COUNTIFS($AS$2:$AS$200,$G15)>0, COUNTIFS($AT$2:$AT$200,$G15)>0, COUNTIFS($AU$2:$AU$200,$G15)>0, COUNTIFS($AV$2:$AV$200,$G15)>0, COUNTIFS($AW$2:$AW$200,$G15)>0, COUNTIFS($AX$2:$AX$200,$G15)>0 )), ), 2 ), "")} | E15: {=IFERROR( INDEX( _xlfn._xlws.FILTER($U$1:$AX$1, TRANSPOSE( CHOOSE({1;2;3;4;5;6;7;8;9;10;11;12;13;14;15;16;17;18;19;20;21;22;23;24;25;26;27;28;29;30}, COUNTIFS($U$2:$U$200,$G15)>0, COUNTIFS($V$2:$V$200,$G15)>0, COUNTIFS($W$2:$W$200,$G15)>0, COUNTIFS($X$2:$X$200,$G15)>0, COUNTIFS($Y$2:$Y$200,$G15)>0, COUNTIFS($Z$2:$Z$200,$G15)>0, COUNTIFS($AA$2:$AA$200,$G15)>0, COUNTIFS($AB$2:$AB$200,$G15)>0, COUNTIFS($AC$2:$AC$200,$G15)>0, COUNTIFS($AD$2:$AD$200,$G15)>0, COUNTIFS($AE$2:$AE$200,$G15)>0, COUNTIFS($AF$2:$AF$200,$G15)>0, COUNTIFS($AG$2:$AG$200,$G15)>0, COUNTIFS($AH$2:$AH$200,$G15)>0, COUNTIFS($AI$2:$AI$200,$G15)>0, COUNTIFS($AJ$2:$AJ$200,$G15)>0, COUNTIFS($AK$2:$AK$200,$G15)>0, COUNTIFS($AL$2:$AL$200,$G15)>0, COUNTIFS($AM$2:$AM$200,$G15)>0, COUNTIFS($AN$2:$AN$200,$G15)>0, COUNTIFS($AO$2:$AO$200,$G15)>0, COUNTIFS($AP$2:$AP$200,$G15)>0, COUNTIFS($AQ$2:$AQ$200,$G15)>0, COUNTIFS($AR$2:$AR$200,$G15)>0, COUNTIFS($AS$2:$AS$200,$G15)>0, COUNTIFS($AT$2:$AT$200,$G15)>0, COUNTIFS($AU$2:$AU$200,$G15)>0, COUNTIFS($AV$2:$AV$200,$G15)>0, COUNTIFS($AW$2:$AW$200,$G15)>0, COUNTIFS($AX$2:$AX$200,$G15)>0 )), ), 3 ), "")} | F15: {=IFERROR( INDEX( _xlfn._xlws.FILTER($U$1:$AX$1, TRANSPOSE( CHOOSE({1;2;3;4;5;6;7;8;9;10;11;12;13;14;15;16;17;18;19;20;21;22;23;24;25;26;27;28;29;30}, COUNTIFS($U$2:$U$200,$G15)>0, COUNTIFS($V$2:$V$200,$G15)>0, COUNTIFS($W$2:$W$200,$G15)>0, COUNTIFS($X$2:$X$200,$G15)>0, COUNTIFS($Y$2:$Y$200,$G15)>0, COUNTIFS($Z$2:$Z$200,$G15)>0, COUNTIFS($AA$2:$AA$200,$G15)>0, COUNTIFS($AB$2:$AB$200,$G15)>0, COUNTIFS($AC$2:$AC$200,$G15)>0, COUNTIFS($AD$2:$AD$200,$G15)>0, COUNTIFS($AE$2:$AE$200,$G15)>0, COUNTIFS($AF$2:$AF$200,$G15)>0, COUNTIFS($AG$2:$AG$200,$G15)>0, COUNTIFS($AH$2:$AH$200,$G15)>0, COUNTIFS($AI$2:$AI$200,$G15)>0, COUNTIFS($AJ$2:$AJ$200,$G15)>0, COUNTIFS($AK$2:$AK$200,$G15)>0, COUNTIFS($AL$2:$AL$200,$G15)>0, COUNTIFS($AM$2:$AM$200,$G15)>0, COUNTIFS($AN$2:$AN$200,$G15)>0, COUNTIFS($AO$2:$AO$200,$G15)>0, COUNTIFS($AP$2:$AP$200,$G15)>0, COUNTIFS($AQ$2:$AQ$200,$G15)>0, COUNTIFS($AR$2:$AR$200,$G15)>0, COUNTIFS($AS$2:$AS$200,$G15)>0, COUNTIFS($AT$2:$AT$200,$G15)>0, COUNTIFS($AU$2:$AU$200,$G15)>0, COUNTIFS($AV$2:$AV$200,$G15)>0, COUNTIFS($AW$2:$AW$200,$G15)>0, COUNTIFS($AX$2:$AX$200,$G15)>0 )), ), 4 ), "")} | G15: Árbitro Silencioso | I15: Yuriko | J15: =Yuriko!G2 -> 12 | K15: Não | L15: Sim | M15: Não | N15: Sim | O15: Não | P15: Ping | Q15: - | R15: Turnos Extras | S15: =IF(J15<6,"5",IF(J15<11,"4",IF(J15<16,"3",IF(J15<31,"2","1")))) -> 3 | U15: Mines of Moria | V15: Jacked Rabbit | W15: Monastery Siege | X15: Gyre Sage | Y15: Unholy Annex // Ritual Chamber | Z15: Rogue's Passage | AA15: Singer of Swift Rivers | AX15: Arcbound Stinger | AZ15: Phyrexian Tower | BA15: Raffine's Tower | BB15: Westvale Abbey | BC15: Morphic Pool | BD15: Hierofante de Elenda | BE15: Jenova, Ancient Calamity | BF15: Gallifrey Council Chamber | BG15: Harvest Season | BH15: Champions from Beyond | BI15: Arcbound Stinger | BK15: Extinguisher Battleship | BL15: Emergency Eject | BM15: Enduring Innocence | BN15: Dollmaker's Shop // Porcelain Gallery | BO15: Arcbound Stinger | BQ15: Caverna das Almas | BR15: Call to the Kindred | BT15: Arid Mesa
A16: =IFERROR(INDEX($S$3:$S$200, MATCH($C16, $I$3:$I$200, 0)), "") -> 3 | B16: =COUNTIF(U:AX,G16) -> 1 | C16: =IFERROR( INDEX($U$1:$AX$1, MATCH(TRUE, CHOOSE({1;2;3;4;5;6;7;8;9;10;11;12;13;14;15;16;17;18;19;20;21;22;23;24;25;26;27;28;29;30;31;32}, COUNTIFS($U$2:$U$200,$G16)>0, COUNTIFS($V$2:$V$200,$G16)>0, COUNTIFS($W$2:$W$200,$G16)>0, COUNTIFS($X$2:$X$200,$G16)>0, COUNTIFS($Y$2:$Y$200,$G16)>0, COUNTIFS($Z$2:$Z$200,$G16)>0, COUNTIFS($AA$2:$AA$200,$G16)>0, COUNTIFS($AB$2:$AB$200,$G16)>0, COUNTIFS($AC$2:$AC$200,$G16)>0, COUNTIFS($AD$2:$AD$200,$G16)>0, COUNTIFS($AE$2:$AE$200,$G16)>0, COUNTIFS($AF$2:$AF$200,$G16)>0, COUNTIFS($AG$2:$AG$200,$G16)>0, COUNTIFS($AH$2:$AH$200,$G16)>0, COUNTIFS($AI$2:$AI$200,$G16)>0, COUNTIFS($AJ$2:$AJ$200,$G16)>0, COUNTIFS($AK$2:$AK$200,$G16)>0, COUNTIFS($AL$2:$AL$200,$G16)>0, COUNTIFS($AM$2:$AM$200,$G16)>0, COUNTIFS($AN$2:$AN$200,$G16)>0, COUNTIFS($AO$2:$AO$200,$G16)>0, COUNTIFS($AP$2:$AP$200,$G16)>0, COUNTIFS($AQ$2:$AQ$200,$G16)>0, COUNTIFS($AR$2:$AR$200,$G16)>0, COUNTIFS($AS$2:$AS$200,$G16)>0, COUNTIFS($AT$2:$AT$200,$G16)>0, COUNTIFS($AU$2:$AU$200,$G16)>0, COUNTIFS($AV$2:$AV$200,$G16)>0, COUNTIFS($AW$2:$AW$200,$G16)>0, COUNTIFS($AX$2:$AX$200,$G16)>0 ), 0) ), "") -> Inalla | D16: {=IFERROR( INDEX( _xlfn._xlws.FILTER($U$1:$AX$1, TRANSPOSE( CHOOSE({1;2;3;4;5;6;7;8;9;10;11;12;13;14;15;16;17;18;19;20;21;22;23;24;25;26;27;28;29;30}, COUNTIFS($U$2:$U$200,$G16)>0, COUNTIFS($V$2:$V$200,$G16)>0, COUNTIFS($W$2:$W$200,$G16)>0, COUNTIFS($X$2:$X$200,$G16)>0, COUNTIFS($Y$2:$Y$200,$G16)>0, COUNTIFS($Z$2:$Z$200,$G16)>0, COUNTIFS($AA$2:$AA$200,$G16)>0, COUNTIFS($AB$2:$AB$200,$G16)>0, COUNTIFS($AC$2:$AC$200,$G16)>0, COUNTIFS($AD$2:$AD$200,$G16)>0, COUNTIFS($AE$2:$AE$200,$G16)>0, COUNTIFS($AF$2:$AF$200,$G16)>0, COUNTIFS($AG$2:$AG$200,$G16)>0, COUNTIFS($AH$2:$AH$200,$G16)>0, COUNTIFS($AI$2:$AI$200,$G16)>0, COUNTIFS($AJ$2:$AJ$200,$G16)>0, COUNTIFS($AK$2:$AK$200,$G16)>0, COUNTIFS($AL$2:$AL$200,$G16)>0, COUNTIFS($AM$2:$AM$200,$G16)>0, COUNTIFS($AN$2:$AN$200,$G16)>0, COUNTIFS($AO$2:$AO$200,$G16)>0, COUNTIFS($AP$2:$AP$200,$G16)>0, COUNTIFS($AQ$2:$AQ$200,$G16)>0, COUNTIFS($AR$2:$AR$200,$G16)>0, COUNTIFS($AS$2:$AS$200,$G16)>0, COUNTIFS($AT$2:$AT$200,$G16)>0, COUNTIFS($AU$2:$AU$200,$G16)>0, COUNTIFS($AV$2:$AV$200,$G16)>0, COUNTIFS($AW$2:$AW$200,$G16)>0, COUNTIFS($AX$2:$AX$200,$G16)>0 )), ), 2 ), "")} | E16: {=IFERROR( INDEX( _xlfn._xlws.FILTER($U$1:$AX$1, TRANSPOSE( CHOOSE({1;2;3;4;5;6;7;8;9;10;11;12;13;14;15;16;17;18;19;20;21;22;23;24;25;26;27;28;29;30}, COUNTIFS($U$2:$U$200,$G16)>0, COUNTIFS($V$2:$V$200,$G16)>0, COUNTIFS($W$2:$W$200,$G16)>0, COUNTIFS($X$2:$X$200,$G16)>0, COUNTIFS($Y$2:$Y$200,$G16)>0, COUNTIFS($Z$2:$Z$200,$G16)>0, COUNTIFS($AA$2:$AA$200,$G16)>0, COUNTIFS($AB$2:$AB$200,$G16)>0, COUNTIFS($AC$2:$AC$200,$G16)>0, COUNTIFS($AD$2:$AD$200,$G16)>0, COUNTIFS($AE$2:$AE$200,$G16)>0, COUNTIFS($AF$2:$AF$200,$G16)>0, COUNTIFS($AG$2:$AG$200,$G16)>0, COUNTIFS($AH$2:$AH$200,$G16)>0, COUNTIFS($AI$2:$AI$200,$G16)>0, COUNTIFS($AJ$2:$AJ$200,$G16)>0, COUNTIFS($AK$2:$AK$200,$G16)>0, COUNTIFS($AL$2:$AL$200,$G16)>0, COUNTIFS($AM$2:$AM$200,$G16)>0, COUNTIFS($AN$2:$AN$200,$G16)>0, COUNTIFS($AO$2:$AO$200,$G16)>0, COUNTIFS($AP$2:$AP$200,$G16)>0, COUNTIFS($AQ$2:$AQ$200,$G16)>0, COUNTIFS($AR$2:$AR$200,$G16)>0, COUNTIFS($AS$2:$AS$200,$G16)>0, COUNTIFS($AT$2:$AT$200,$G16)>0, COUNTIFS($AU$2:$AU$200,$G16)>0, COUNTIFS($AV$2:$AV$200,$G16)>0, COUNTIFS($AW$2:$AW$200,$G16)>0, COUNTIFS($AX$2:$AX$200,$G16)>0 )), ), 3 ), "")} | F16: {=IFERROR( INDEX( _xlfn._xlws.FILTER($U$1:$AX$1, TRANSPOSE( CHOOSE({1;2;3;4;5;6;7;8;9;10;11;12;13;14;15;16;17;18;19;20;21;22;23;24;25;26;27;28;29;30}, COUNTIFS($U$2:$U$200,$G16)>0, COUNTIFS($V$2:$V$200,$G16)>0, COUNTIFS($W$2:$W$200,$G16)>0, COUNTIFS($X$2:$X$200,$G16)>0, COUNTIFS($Y$2:$Y$200,$G16)>0, COUNTIFS($Z$2:$Z$200,$G16)>0, COUNTIFS($AA$2:$AA$200,$G16)>0, COUNTIFS($AB$2:$AB$200,$G16)>0, COUNTIFS($AC$2:$AC$200,$G16)>0, COUNTIFS($AD$2:$AD$200,$G16)>0, COUNTIFS($AE$2:$AE$200,$G16)>0, COUNTIFS($AF$2:$AF$200,$G16)>0, COUNTIFS($AG$2:$AG$200,$G16)>0, COUNTIFS($AH$2:$AH$200,$G16)>0, COUNTIFS($AI$2:$AI$200,$G16)>0, COUNTIFS($AJ$2:$AJ$200,$G16)>0, COUNTIFS($AK$2:$AK$200,$G16)>0, COUNTIFS($AL$2:$AL$200,$G16)>0, COUNTIFS($AM$2:$AM$200,$G16)>0, COUNTIFS($AN$2:$AN$200,$G16)>0, COUNTIFS($AO$2:$AO$200,$G16)>0, COUNTIFS($AP$2:$AP$200,$G16)>0, COUNTIFS($AQ$2:$AQ$200,$G16)>0, COUNTIFS($AR$2:$AR$200,$G16)>0, COUNTIFS($AS$2:$AS$200,$G16)>0, COUNTIFS($AT$2:$AT$200,$G16)>0, COUNTIFS($AU$2:$AU$200,$G16)>0, COUNTIFS($AV$2:$AV$200,$G16)>0, COUNTIFS($AW$2:$AW$200,$G16)>0, COUNTIFS($AX$2:$AX$200,$G16)>0 )), ), 4 ), "")} | G16: Arcane Lighthouse | I16: Inalla | J16: =Inalla!G2 -> 12 | K16: Não | L16: Sim | M16: Sim | N16: Sim | O16: Não | P16: Combo | Q16: Dano Direto | R16: Magos e Combos | S16: =IF(J16<6,"5",IF(J16<11,"4",IF(J16<16,"3",IF(J16<31,"2","1")))) -> 3 | U16: Reckless Fireweaver | V16: Jetmir, Nexus of Revels | W16: Psychic Corrosion | X16: Hydraw's Growth | Y16: Vault of the Archangel | Z16: Sol Ring | AA16: Sol Ring | AX16: Arcbound Tracker | AZ16: Ripples of Undeath | BA16: Rings of Brighthearth | BC16: Polluted Delta | BD16: Invasion of Segovia | BE16: Jitte Perdida | BF16: Havengul Laboratory | BG16: Herald of Secret Streams | BH16: Cinder Glade | BI16: Arcbound Tracker | BK16: Gerrard's Hourglass Pendant | BL16: Faerie Slumber Party | BM16: Espada da Riqueza e do Poder | BN16: Drowned Catacomb | BO16: Arcbound Tracker | BQ16: Chimil, o Sol Interior | BR16: Chandra's Ignition | BT16: Ascensão do Avernus
A17: =IFERROR(INDEX($S$3:$S$200, MATCH($C17, $I$3:$I$200, 0)), "") -> 1 | B17: =COUNTIF(U:AX,G17) -> 1 | C17: =IFERROR( INDEX($U$1:$AX$1, MATCH(TRUE, CHOOSE({1;2;3;4;5;6;7;8;9;10;11;12;13;14;15;16;17;18;19;20;21;22;23;24;25;26;27;28;29;30;31;32}, COUNTIFS($U$2:$U$200,$G17)>0, COUNTIFS($V$2:$V$200,$G17)>0, COUNTIFS($W$2:$W$200,$G17)>0, COUNTIFS($X$2:$X$200,$G17)>0, COUNTIFS($Y$2:$Y$200,$G17)>0, COUNTIFS($Z$2:$Z$200,$G17)>0, COUNTIFS($AA$2:$AA$200,$G17)>0, COUNTIFS($AB$2:$AB$200,$G17)>0, COUNTIFS($AC$2:$AC$200,$G17)>0, COUNTIFS($AD$2:$AD$200,$G17)>0, COUNTIFS($AE$2:$AE$200,$G17)>0, COUNTIFS($AF$2:$AF$200,$G17)>0, COUNTIFS($AG$2:$AG$200,$G17)>0, COUNTIFS($AH$2:$AH$200,$G17)>0, COUNTIFS($AI$2:$AI$200,$G17)>0, COUNTIFS($AJ$2:$AJ$200,$G17)>0, COUNTIFS($AK$2:$AK$200,$G17)>0, COUNTIFS($AL$2:$AL$200,$G17)>0, COUNTIFS($AM$2:$AM$200,$G17)>0, COUNTIFS($AN$2:$AN$200,$G17)>0, COUNTIFS($AO$2:$AO$200,$G17)>0, COUNTIFS($AP$2:$AP$200,$G17)>0, COUNTIFS($AQ$2:$AQ$200,$G17)>0, COUNTIFS($AR$2:$AR$200,$G17)>0, COUNTIFS($AS$2:$AS$200,$G17)>0, COUNTIFS($AT$2:$AT$200,$G17)>0, COUNTIFS($AU$2:$AU$200,$G17)>0, COUNTIFS($AV$2:$AV$200,$G17)>0, COUNTIFS($AW$2:$AW$200,$G17)>0, COUNTIFS($AX$2:$AX$200,$G17)>0 ), 0) ), "") -> Modular | D17: {=IFERROR( INDEX( _xlfn._xlws.FILTER($U$1:$AX$1, TRANSPOSE( CHOOSE({1;2;3;4;5;6;7;8;9;10;11;12;13;14;15;16;17;18;19;20;21;22;23;24;25;26;27;28;29;30}, COUNTIFS($U$2:$U$200,$G17)>0, COUNTIFS($V$2:$V$200,$G17)>0, COUNTIFS($W$2:$W$200,$G17)>0, COUNTIFS($X$2:$X$200,$G17)>0, COUNTIFS($Y$2:$Y$200,$G17)>0, COUNTIFS($Z$2:$Z$200,$G17)>0, COUNTIFS($AA$2:$AA$200,$G17)>0, COUNTIFS($AB$2:$AB$200,$G17)>0, COUNTIFS($AC$2:$AC$200,$G17)>0, COUNTIFS($AD$2:$AD$200,$G17)>0, COUNTIFS($AE$2:$AE$200,$G17)>0, COUNTIFS($AF$2:$AF$200,$G17)>0, COUNTIFS($AG$2:$AG$200,$G17)>0, COUNTIFS($AH$2:$AH$200,$G17)>0, COUNTIFS($AI$2:$AI$200,$G17)>0, COUNTIFS($AJ$2:$AJ$200,$G17)>0, COUNTIFS($AK$2:$AK$200,$G17)>0, COUNTIFS($AL$2:$AL$200,$G17)>0, COUNTIFS($AM$2:$AM$200,$G17)>0, COUNTIFS($AN$2:$AN$200,$G17)>0, COUNTIFS($AO$2:$AO$200,$G17)>0, COUNTIFS($AP$2:$AP$200,$G17)>0, COUNTIFS($AQ$2:$AQ$200,$G17)>0, COUNTIFS($AR$2:$AR$200,$G17)>0, COUNTIFS($AS$2:$AS$200,$G17)>0, COUNTIFS($AT$2:$AT$200,$G17)>0, COUNTIFS($AU$2:$AU$200,$G17)>0, COUNTIFS($AV$2:$AV$200,$G17)>0, COUNTIFS($AW$2:$AW$200,$G17)>0, COUNTIFS($AX$2:$AX$200,$G17)>0 )), ), 2 ), "")} | E17: {=IFERROR( INDEX( _xlfn._xlws.FILTER($U$1:$AX$1, TRANSPOSE( CHOOSE({1;2;3;4;5;6;7;8;9;10;11;12;13;14;15;16;17;18;19;20;21;22;23;24;25;26;27;28;29;30}, COUNTIFS($U$2:$U$200,$G17)>0, COUNTIFS($V$2:$V$200,$G17)>0, COUNTIFS($W$2:$W$200,$G17)>0, COUNTIFS($X$2:$X$200,$G17)>0, COUNTIFS($Y$2:$Y$200,$G17)>0, COUNTIFS($Z$2:$Z$200,$G17)>0, COUNTIFS($AA$2:$AA$200,$G17)>0, COUNTIFS($AB$2:$AB$200,$G17)>0, COUNTIFS($AC$2:$AC$200,$G17)>0, COUNTIFS($AD$2:$AD$200,$G17)>0, COUNTIFS($AE$2:$AE$200,$G17)>0, COUNTIFS($AF$2:$AF$200,$G17)>0, COUNTIFS($AG$2:$AG$200,$G17)>0, COUNTIFS($AH$2:$AH$200,$G17)>0, COUNTIFS($AI$2:$AI$200,$G17)>0, COUNTIFS($AJ$2:$AJ$200,$G17)>0, COUNTIFS($AK$2:$AK$200,$G17)>0, COUNTIFS($AL$2:$AL$200,$G17)>0, COUNTIFS($AM$2:$AM$200,$G17)>0, COUNTIFS($AN$2:$AN$200,$G17)>0, COUNTIFS($AO$2:$AO$200,$G17)>0, COUNTIFS($AP$2:$AP$200,$G17)>0, COUNTIFS($AQ$2:$AQ$200,$G17)>0, COUNTIFS($AR$2:$AR$200,$G17)>0, COUNTIFS($AS$2:$AS$200,$G17)>0, COUNTIFS($AT$2:$AT$200,$G17)>0, COUNTIFS($AU$2:$AU$200,$G17)>0, COUNTIFS($AV$2:$AV$200,$G17)>0, COUNTIFS($AW$2:$AW$200,$G17)>0, COUNTIFS($AX$2:$AX$200,$G17)>0 )), ), 3 ), "")} | F17: {=IFERROR( INDEX( _xlfn._xlws.FILTER($U$1:$AX$1, TRANSPOSE( CHOOSE({1;2;3;4;5;6;7;8;9;10;11;12;13;14;15;16;17;18;19;20;21;22;23;24;25;26;27;28;29;30}, COUNTIFS($U$2:$U$200,$G17)>0, COUNTIFS($V$2:$V$200,$G17)>0, COUNTIFS($W$2:$W$200,$G17)>0, COUNTIFS($X$2:$X$200,$G17)>0, COUNTIFS($Y$2:$Y$200,$G17)>0, COUNTIFS($Z$2:$Z$200,$G17)>0, COUNTIFS($AA$2:$AA$200,$G17)>0, COUNTIFS($AB$2:$AB$200,$G17)>0, COUNTIFS($AC$2:$AC$200,$G17)>0, COUNTIFS($AD$2:$AD$200,$G17)>0, COUNTIFS($AE$2:$AE$200,$G17)>0, COUNTIFS($AF$2:$AF$200,$G17)>0, COUNTIFS($AG$2:$AG$200,$G17)>0, COUNTIFS($AH$2:$AH$200,$G17)>0, COUNTIFS($AI$2:$AI$200,$G17)>0, COUNTIFS($AJ$2:$AJ$200,$G17)>0, COUNTIFS($AK$2:$AK$200,$G17)>0, COUNTIFS($AL$2:$AL$200,$G17)>0, COUNTIFS($AM$2:$AM$200,$G17)>0, COUNTIFS($AN$2:$AN$200,$G17)>0, COUNTIFS($AO$2:$AO$200,$G17)>0, COUNTIFS($AP$2:$AP$200,$G17)>0, COUNTIFS($AQ$2:$AQ$200,$G17)>0, COUNTIFS($AR$2:$AR$200,$G17)>0, COUNTIFS($AS$2:$AS$200,$G17)>0, COUNTIFS($AT$2:$AT$200,$G17)>0, COUNTIFS($AU$2:$AU$200,$G17)>0, COUNTIFS($AV$2:$AV$200,$G17)>0, COUNTIFS($AW$2:$AW$200,$G17)>0, COUNTIFS($AX$2:$AX$200,$G17)>0 )), ), 4 ), "")} | G17: Arcane Signet | I17: Akiri | J17: =Akiri!G2 -> 12 | K17: Sim | L17: Não | M17: Sim | N17: Não | O17: Não | P17: Combate | Q17: Voltron | R17: Equipamentos | S17: =IF(J17<6,"5",IF(J17<11,"4",IF(J17<16,"3",IF(J17<31,"2","1")))) -> 3 | U17: Reliquary Tower | V17: Karplusan Forest | W17: Reforge the Soul | X17: Incubation Druid | Z17: Sulfur Falls | AA17: Stonybrook Banneret | AX17: Arcbound Whelp | AZ17: Shaku da Honra Desgastada | BA17: Sliver Gravemother | BC17: Prismatic Strands | BD17: Jidoor, Aristocratic Capital // Overture | BE17: Kellan, the Fae-Blooded // Birthright Boon | BF17: Illustrious Wanderglyph | BG17: Horizon Explorer | BH17: Conclave Mentor | BI17: Arcbound Whelp | BK17: Hedge Shredder | BL17: Homeward Path | BM17: Espada de Banquete e Fome | BN17: Dúplice Debochada | BO17: Arcbound Whelp | BQ17: Chronomantic Escape | BR17: Cid, Freeflier Pilot | BT17: Autoridade dos Cônsules
A18: =IFERROR(INDEX($S$3:$S$200, MATCH($C18, $I$3:$I$200, 0)), "") -> 1 | B18: =COUNTIF(U:AX,G18) -> 1 | C18: =IFERROR( INDEX($U$1:$AX$1, MATCH(TRUE, CHOOSE({1;2;3;4;5;6;7;8;9;10;11;12;13;14;15;16;17;18;19;20;21;22;23;24;25;26;27;28;29;30;31;32}, COUNTIFS($U$2:$U$200,$G18)>0, COUNTIFS($V$2:$V$200,$G18)>0, COUNTIFS($W$2:$W$200,$G18)>0, COUNTIFS($X$2:$X$200,$G18)>0, COUNTIFS($Y$2:$Y$200,$G18)>0, COUNTIFS($Z$2:$Z$200,$G18)>0, COUNTIFS($AA$2:$AA$200,$G18)>0, COUNTIFS($AB$2:$AB$200,$G18)>0, COUNTIFS($AC$2:$AC$200,$G18)>0, COUNTIFS($AD$2:$AD$200,$G18)>0, COUNTIFS($AE$2:$AE$200,$G18)>0, COUNTIFS($AF$2:$AF$200,$G18)>0, COUNTIFS($AG$2:$AG$200,$G18)>0, COUNTIFS($AH$2:$AH$200,$G18)>0, COUNTIFS($AI$2:$AI$200,$G18)>0, COUNTIFS($AJ$2:$AJ$200,$G18)>0, COUNTIFS($AK$2:$AK$200,$G18)>0, COUNTIFS($AL$2:$AL$200,$G18)>0, COUNTIFS($AM$2:$AM$200,$G18)>0, COUNTIFS($AN$2:$AN$200,$G18)>0, COUNTIFS($AO$2:$AO$200,$G18)>0, COUNTIFS($AP$2:$AP$200,$G18)>0, COUNTIFS($AQ$2:$AQ$200,$G18)>0, COUNTIFS($AR$2:$AR$200,$G18)>0, COUNTIFS($AS$2:$AS$200,$G18)>0, COUNTIFS($AT$2:$AT$200,$G18)>0, COUNTIFS($AU$2:$AU$200,$G18)>0, COUNTIFS($AV$2:$AV$200,$G18)>0, COUNTIFS($AW$2:$AW$200,$G18)>0, COUNTIFS($AX$2:$AX$200,$G18)>0 ), 0) ), "") -> Modular | D18: {=IFERROR( INDEX( _xlfn._xlws.FILTER($U$1:$AX$1, TRANSPOSE( CHOOSE({1;2;3;4;5;6;7;8;9;10;11;12;13;14;15;16;17;18;19;20;21;22;23;24;25;26;27;28;29;30}, COUNTIFS($U$2:$U$200,$G18)>0, COUNTIFS($V$2:$V$200,$G18)>0, COUNTIFS($W$2:$W$200,$G18)>0, COUNTIFS($X$2:$X$200,$G18)>0, COUNTIFS($Y$2:$Y$200,$G18)>0, COUNTIFS($Z$2:$Z$200,$G18)>0, COUNTIFS($AA$2:$AA$200,$G18)>0, COUNTIFS($AB$2:$AB$200,$G18)>0, COUNTIFS($AC$2:$AC$200,$G18)>0, COUNTIFS($AD$2:$AD$200,$G18)>0, COUNTIFS($AE$2:$AE$200,$G18)>0, COUNTIFS($AF$2:$AF$200,$G18)>0, COUNTIFS($AG$2:$AG$200,$G18)>0, COUNTIFS($AH$2:$AH$200,$G18)>0, COUNTIFS($AI$2:$AI$200,$G18)>0, COUNTIFS($AJ$2:$AJ$200,$G18)>0, COUNTIFS($AK$2:$AK$200,$G18)>0, COUNTIFS($AL$2:$AL$200,$G18)>0, COUNTIFS($AM$2:$AM$200,$G18)>0, COUNTIFS($AN$2:$AN$200,$G18)>0, COUNTIFS($AO$2:$AO$200,$G18)>0, COUNTIFS($AP$2:$AP$200,$G18)>0, COUNTIFS($AQ$2:$AQ$200,$G18)>0, COUNTIFS($AR$2:$AR$200,$G18)>0, COUNTIFS($AS$2:$AS$200,$G18)>0, COUNTIFS($AT$2:$AT$200,$G18)>0, COUNTIFS($AU$2:$AU$200,$G18)>0, COUNTIFS($AV$2:$AV$200,$G18)>0, COUNTIFS($AW$2:$AW$200,$G18)>0, COUNTIFS($AX$2:$AX$200,$G18)>0 )), ), 2 ), "")} | E18: {=IFERROR( INDEX( _xlfn._xlws.FILTER($U$1:$AX$1, TRANSPOSE( CHOOSE({1;2;3;4;5;6;7;8;9;10;11;12;13;14;15;16;17;18;19;20;21;22;23;24;25;26;27;28;29;30}, COUNTIFS($U$2:$U$200,$G18)>0, COUNTIFS($V$2:$V$200,$G18)>0, COUNTIFS($W$2:$W$200,$G18)>0, COUNTIFS($X$2:$X$200,$G18)>0, COUNTIFS($Y$2:$Y$200,$G18)>0, COUNTIFS($Z$2:$Z$200,$G18)>0, COUNTIFS($AA$2:$AA$200,$G18)>0, COUNTIFS($AB$2:$AB$200,$G18)>0, COUNTIFS($AC$2:$AC$200,$G18)>0, COUNTIFS($AD$2:$AD$200,$G18)>0, COUNTIFS($AE$2:$AE$200,$G18)>0, COUNTIFS($AF$2:$AF$200,$G18)>0, COUNTIFS($AG$2:$AG$200,$G18)>0, COUNTIFS($AH$2:$AH$200,$G18)>0, COUNTIFS($AI$2:$AI$200,$G18)>0, COUNTIFS($AJ$2:$AJ$200,$G18)>0, COUNTIFS($AK$2:$AK$200,$G18)>0, COUNTIFS($AL$2:$AL$200,$G18)>0, COUNTIFS($AM$2:$AM$200,$G18)>0, COUNTIFS($AN$2:$AN$200,$G18)>0, COUNTIFS($AO$2:$AO$200,$G18)>0, COUNTIFS($AP$2:$AP$200,$G18)>0, COUNTIFS($AQ$2:$AQ$200,$G18)>0, COUNTIFS($AR$2:$AR$200,$G18)>0, COUNTIFS($AS$2:$AS$200,$G18)>0, COUNTIFS($AT$2:$AT$200,$G18)>0, COUNTIFS($AU$2:$AU$200,$G18)>0, COUNTIFS($AV$2:$AV$200,$G18)>0, COUNTIFS($AW$2:$AW$200,$G18)>0, COUNTIFS($AX$2:$AX$200,$G18)>0 )), ), 3 ), "")} | F18: {=IFERROR( INDEX( _xlfn._xlws.FILTER($U$1:$AX$1, TRANSPOSE( CHOOSE({1;2;3;4;5;6;7;8;9;10;11;12;13;14;15;16;17;18;19;20;21;22;23;24;25;26;27;28;29;30}, COUNTIFS($U$2:$U$200,$G18)>0, COUNTIFS($V$2:$V$200,$G18)>0, COUNTIFS($W$2:$W$200,$G18)>0, COUNTIFS($X$2:$X$200,$G18)>0, COUNTIFS($Y$2:$Y$200,$G18)>0, COUNTIFS($Z$2:$Z$200,$G18)>0, COUNTIFS($AA$2:$AA$200,$G18)>0, COUNTIFS($AB$2:$AB$200,$G18)>0, COUNTIFS($AC$2:$AC$200,$G18)>0, COUNTIFS($AD$2:$AD$200,$G18)>0, COUNTIFS($AE$2:$AE$200,$G18)>0, COUNTIFS($AF$2:$AF$200,$G18)>0, COUNTIFS($AG$2:$AG$200,$G18)>0, COUNTIFS($AH$2:$AH$200,$G18)>0, COUNTIFS($AI$2:$AI$200,$G18)>0, COUNTIFS($AJ$2:$AJ$200,$G18)>0, COUNTIFS($AK$2:$AK$200,$G18)>0, COUNTIFS($AL$2:$AL$200,$G18)>0, COUNTIFS($AM$2:$AM$200,$G18)>0, COUNTIFS($AN$2:$AN$200,$G18)>0, COUNTIFS($AO$2:$AO$200,$G18)>0, COUNTIFS($AP$2:$AP$200,$G18)>0, COUNTIFS($AQ$2:$AQ$200,$G18)>0, COUNTIFS($AR$2:$AR$200,$G18)>0, COUNTIFS($AS$2:$AS$200,$G18)>0, COUNTIFS($AT$2:$AT$200,$G18)>0, COUNTIFS($AU$2:$AU$200,$G18)>0, COUNTIFS($AV$2:$AV$200,$G18)>0, COUNTIFS($AW$2:$AW$200,$G18)>0, COUNTIFS($AX$2:$AX$200,$G18)>0 )), ), 4 ), "")} | G18: Arcbound Crusher | I18: Sisay | J18: =Sisay!G2 -> 11 | K18: Sim | L18: Sim | M18: Sim | N18: Sim | O18: Sim | P18: Combate | Q18: Dano Direto | R18: Super-Amigos | S18: =IF(J18<6,"5",IF(J18<11,"4",IF(J18<16,"3",IF(J18<31,"2","1")))) -> 3 | U18: Secluded Courtyard | V18: Lightning Greaves | W18: Relentless Assault | X18: Kutzil, Malamet Exemplar | Z18: Thought Vessel | AA18: Summon: Leviathan | AX18: Badgermole | AZ18: Takenuma, Charco Abandonado | BA18: Sonic Screwdriver | BC18: Satoru, the Infiltrator | BD18: Keen Duelist | BE18: Lightning Greaves | BF18: Karn Liberated | BG18: Incendiary Command | BH18: Deceptive Landscape | BI18: Back in Town | BK18: Inventors' Fair | BL18: Lagoa Espelhada | BM18: Espada de Fogo e Gelo | BN18: Elspeth, Sun's Champion | BO18: Ardbert, Warrior of Darkness | BQ18: Collector's Vault | BR18: Clifftop Retreat | BT18: Baral, Chief of Compliance
A19: =IFERROR(INDEX($S$3:$S$200, MATCH($C19, $I$3:$I$200, 0)), "") -> 1 | B19: =COUNTIF(U:AX,G19) -> 1 | C19: =IFERROR( INDEX($U$1:$AX$1, MATCH(TRUE, CHOOSE({1;2;3;4;5;6;7;8;9;10;11;12;13;14;15;16;17;18;19;20;21;22;23;24;25;26;27;28;29;30;31;32}, COUNTIFS($U$2:$U$200,$G19)>0, COUNTIFS($V$2:$V$200,$G19)>0, COUNTIFS($W$2:$W$200,$G19)>0, COUNTIFS($X$2:$X$200,$G19)>0, COUNTIFS($Y$2:$Y$200,$G19)>0, COUNTIFS($Z$2:$Z$200,$G19)>0, COUNTIFS($AA$2:$AA$200,$G19)>0, COUNTIFS($AB$2:$AB$200,$G19)>0, COUNTIFS($AC$2:$AC$200,$G19)>0, COUNTIFS($AD$2:$AD$200,$G19)>0, COUNTIFS($AE$2:$AE$200,$G19)>0, COUNTIFS($AF$2:$AF$200,$G19)>0, COUNTIFS($AG$2:$AG$200,$G19)>0, COUNTIFS($AH$2:$AH$200,$G19)>0, COUNTIFS($AI$2:$AI$200,$G19)>0, COUNTIFS($AJ$2:$AJ$200,$G19)>0, COUNTIFS($AK$2:$AK$200,$G19)>0, COUNTIFS($AL$2:$AL$200,$G19)>0, COUNTIFS($AM$2:$AM$200,$G19)>0, COUNTIFS($AN$2:$AN$200,$G19)>0, COUNTIFS($AO$2:$AO$200,$G19)>0, COUNTIFS($AP$2:$AP$200,$G19)>0, COUNTIFS($AQ$2:$AQ$200,$G19)>0, COUNTIFS($AR$2:$AR$200,$G19)>0, COUNTIFS($AS$2:$AS$200,$G19)>0, COUNTIFS($AT$2:$AT$200,$G19)>0, COUNTIFS($AU$2:$AU$200,$G19)>0, COUNTIFS($AV$2:$AV$200,$G19)>0, COUNTIFS($AW$2:$AW$200,$G19)>0, COUNTIFS($AX$2:$AX$200,$G19)>0 ), 0) ), "") -> Modular | D19: {=IFERROR( INDEX( _xlfn._xlws.FILTER($U$1:$AX$1, TRANSPOSE( CHOOSE({1;2;3;4;5;6;7;8;9;10;11;12;13;14;15;16;17;18;19;20;21;22;23;24;25;26;27;28;29;30}, COUNTIFS($U$2:$U$200,$G19)>0, COUNTIFS($V$2:$V$200,$G19)>0, COUNTIFS($W$2:$W$200,$G19)>0, COUNTIFS($X$2:$X$200,$G19)>0, COUNTIFS($Y$2:$Y$200,$G19)>0, COUNTIFS($Z$2:$Z$200,$G19)>0, COUNTIFS($AA$2:$AA$200,$G19)>0, COUNTIFS($AB$2:$AB$200,$G19)>0, COUNTIFS($AC$2:$AC$200,$G19)>0, COUNTIFS($AD$2:$AD$200,$G19)>0, COUNTIFS($AE$2:$AE$200,$G19)>0, COUNTIFS($AF$2:$AF$200,$G19)>0, COUNTIFS($AG$2:$AG$200,$G19)>0, COUNTIFS($AH$2:$AH$200,$G19)>0, COUNTIFS($AI$2:$AI$200,$G19)>0, COUNTIFS($AJ$2:$AJ$200,$G19)>0, COUNTIFS($AK$2:$AK$200,$G19)>0, COUNTIFS($AL$2:$AL$200,$G19)>0, COUNTIFS($AM$2:$AM$200,$G19)>0, COUNTIFS($AN$2:$AN$200,$G19)>0, COUNTIFS($AO$2:$AO$200,$G19)>0, COUNTIFS($AP$2:$AP$200,$G19)>0, COUNTIFS($AQ$2:$AQ$200,$G19)>0, COUNTIFS($AR$2:$AR$200,$G19)>0, COUNTIFS($AS$2:$AS$200,$G19)>0, COUNTIFS($AT$2:$AT$200,$G19)>0, COUNTIFS($AU$2:$AU$200,$G19)>0, COUNTIFS($AV$2:$AV$200,$G19)>0, COUNTIFS($AW$2:$AW$200,$G19)>0, COUNTIFS($AX$2:$AX$200,$G19)>0 )), ), 2 ), "")} | E19: {=IFERROR( INDEX( _xlfn._xlws.FILTER($U$1:$AX$1, TRANSPOSE( CHOOSE({1;2;3;4;5;6;7;8;9;10;11;12;13;14;15;16;17;18;19;20;21;22;23;24;25;26;27;28;29;30}, COUNTIFS($U$2:$U$200,$G19)>0, COUNTIFS($V$2:$V$200,$G19)>0, COUNTIFS($W$2:$W$200,$G19)>0, COUNTIFS($X$2:$X$200,$G19)>0, COUNTIFS($Y$2:$Y$200,$G19)>0, COUNTIFS($Z$2:$Z$200,$G19)>0, COUNTIFS($AA$2:$AA$200,$G19)>0, COUNTIFS($AB$2:$AB$200,$G19)>0, COUNTIFS($AC$2:$AC$200,$G19)>0, COUNTIFS($AD$2:$AD$200,$G19)>0, COUNTIFS($AE$2:$AE$200,$G19)>0, COUNTIFS($AF$2:$AF$200,$G19)>0, COUNTIFS($AG$2:$AG$200,$G19)>0, COUNTIFS($AH$2:$AH$200,$G19)>0, COUNTIFS($AI$2:$AI$200,$G19)>0, COUNTIFS($AJ$2:$AJ$200,$G19)>0, COUNTIFS($AK$2:$AK$200,$G19)>0, COUNTIFS($AL$2:$AL$200,$G19)>0, COUNTIFS($AM$2:$AM$200,$G19)>0, COUNTIFS($AN$2:$AN$200,$G19)>0, COUNTIFS($AO$2:$AO$200,$G19)>0, COUNTIFS($AP$2:$AP$200,$G19)>0, COUNTIFS($AQ$2:$AQ$200,$G19)>0, COUNTIFS($AR$2:$AR$200,$G19)>0, COUNTIFS($AS$2:$AS$200,$G19)>0, COUNTIFS($AT$2:$AT$200,$G19)>0, COUNTIFS($AU$2:$AU$200,$G19)>0, COUNTIFS($AV$2:$AV$200,$G19)>0, COUNTIFS($AW$2:$AW$200,$G19)>0, COUNTIFS($AX$2:$AX$200,$G19)>0 )), ), 3 ), "")} | F19: {=IFERROR( INDEX( _xlfn._xlws.FILTER($U$1:$AX$1, TRANSPOSE( CHOOSE({1;2;3;4;5;6;7;8;9;10;11;12;13;14;15;16;17;18;19;20;21;22;23;24;25;26;27;28;29;30}, COUNTIFS($U$2:$U$200,$G19)>0, COUNTIFS($V$2:$V$200,$G19)>0, COUNTIFS($W$2:$W$200,$G19)>0, COUNTIFS($X$2:$X$200,$G19)>0, COUNTIFS($Y$2:$Y$200,$G19)>0, COUNTIFS($Z$2:$Z$200,$G19)>0, COUNTIFS($AA$2:$AA$200,$G19)>0, COUNTIFS($AB$2:$AB$200,$G19)>0, COUNTIFS($AC$2:$AC$200,$G19)>0, COUNTIFS($AD$2:$AD$200,$G19)>0, COUNTIFS($AE$2:$AE$200,$G19)>0, COUNTIFS($AF$2:$AF$200,$G19)>0, COUNTIFS($AG$2:$AG$200,$G19)>0, COUNTIFS($AH$2:$AH$200,$G19)>0, COUNTIFS($AI$2:$AI$200,$G19)>0, COUNTIFS($AJ$2:$AJ$200,$G19)>0, COUNTIFS($AK$2:$AK$200,$G19)>0, COUNTIFS($AL$2:$AL$200,$G19)>0, COUNTIFS($AM$2:$AM$200,$G19)>0, COUNTIFS($AN$2:$AN$200,$G19)>0, COUNTIFS($AO$2:$AO$200,$G19)>0, COUNTIFS($AP$2:$AP$200,$G19)>0, COUNTIFS($AQ$2:$AQ$200,$G19)>0, COUNTIFS($AR$2:$AR$200,$G19)>0, COUNTIFS($AS$2:$AS$200,$G19)>0, COUNTIFS($AT$2:$AT$200,$G19)>0, COUNTIFS($AU$2:$AU$200,$G19)>0, COUNTIFS($AV$2:$AV$200,$G19)>0, COUNTIFS($AW$2:$AW$200,$G19)>0, COUNTIFS($AX$2:$AX$200,$G19)>0 )), ), 4 ), "")} | G19: Arcbound Fiend | I19: Thrakiri | J19: =Thrakiri!G2 -> 4 | K19: Sim | L19: Sim | M19: Sim | N19: Não | O19: Sim | P19: Combo | Q19: Voltron | R19: Engrenagens para Combar | S19: =IF(J19<6,"5",IF(J19<11,"4",IF(J19<16,"3",IF(J19<31,"2","1")))) -> 5 | U19: Seething Landscape | V19: Marcha dos Canonizados | W19: Sea of Clouds | X19: Lae'zel, Vlaakith's Champion | Z19: Trenzalore Clocktower | AA19: Surgespanner | AX19: Beast Within | AZ19: Three Tree City | BA19: The Mycosynth Gardens | BC19: Sea Gate Restoration | BD19: Merchant of Secrets | BE19: Nibelheim Aflame | BF19: Kaya the Inexorable | BG19: Irenicus's Vile Duplication | BH19: Dever Além da Morte | BI19: Badgermole | BK19: Jetmir's Garden | BL19: Louisoix's Sacrifice | BM19: Espada de Luz e Sombra | BN19: Equilíbrio de Poderes | BO19: Artifact Mutation | BQ19: Creeping Tar Pit | BR19: Cloud, Midgar Mercenary | BT19: Batwing Brume
A20: =IFERROR(INDEX($S$3:$S$200, MATCH($C20, $I$3:$I$200, 0)), "") -> 1 | B20: =COUNTIF(U:AX,G20) -> 1 | C20: =IFERROR( INDEX($U$1:$AX$1, MATCH(TRUE, CHOOSE({1;2;3;4;5;6;7;8;9;10;11;12;13;14;15;16;17;18;19;20;21;22;23;24;25;26;27;28;29;30;31;32}, COUNTIFS($U$2:$U$200,$G20)>0, COUNTIFS($V$2:$V$200,$G20)>0, COUNTIFS($W$2:$W$200,$G20)>0, COUNTIFS($X$2:$X$200,$G20)>0, COUNTIFS($Y$2:$Y$200,$G20)>0, COUNTIFS($Z$2:$Z$200,$G20)>0, COUNTIFS($AA$2:$AA$200,$G20)>0, COUNTIFS($AB$2:$AB$200,$G20)>0, COUNTIFS($AC$2:$AC$200,$G20)>0, COUNTIFS($AD$2:$AD$200,$G20)>0, COUNTIFS($AE$2:$AE$200,$G20)>0, COUNTIFS($AF$2:$AF$200,$G20)>0, COUNTIFS($AG$2:$AG$200,$G20)>0, COUNTIFS($AH$2:$AH$200,$G20)>0, COUNTIFS($AI$2:$AI$200,$G20)>0, COUNTIFS($AJ$2:$AJ$200,$G20)>0, COUNTIFS($AK$2:$AK$200,$G20)>0, COUNTIFS($AL$2:$AL$200,$G20)>0, COUNTIFS($AM$2:$AM$200,$G20)>0, COUNTIFS($AN$2:$AN$200,$G20)>0, COUNTIFS($AO$2:$AO$200,$G20)>0, COUNTIFS($AP$2:$AP$200,$G20)>0, COUNTIFS($AQ$2:$AQ$200,$G20)>0, COUNTIFS($AR$2:$AR$200,$G20)>0, COUNTIFS($AS$2:$AS$200,$G20)>0, COUNTIFS($AT$2:$AT$200,$G20)>0, COUNTIFS($AU$2:$AU$200,$G20)>0, COUNTIFS($AV$2:$AV$200,$G20)>0, COUNTIFS($AW$2:$AW$200,$G20)>0, COUNTIFS($AX$2:$AX$200,$G20)>0 ), 0) ), "") -> Modular | D20: {=IFERROR( INDEX( _xlfn._xlws.FILTER($U$1:$AX$1, TRANSPOSE( CHOOSE({1;2;3;4;5;6;7;8;9;10;11;12;13;14;15;16;17;18;19;20;21;22;23;24;25;26;27;28;29;30}, COUNTIFS($U$2:$U$200,$G20)>0, COUNTIFS($V$2:$V$200,$G20)>0, COUNTIFS($W$2:$W$200,$G20)>0, COUNTIFS($X$2:$X$200,$G20)>0, COUNTIFS($Y$2:$Y$200,$G20)>0, COUNTIFS($Z$2:$Z$200,$G20)>0, COUNTIFS($AA$2:$AA$200,$G20)>0, COUNTIFS($AB$2:$AB$200,$G20)>0, COUNTIFS($AC$2:$AC$200,$G20)>0, COUNTIFS($AD$2:$AD$200,$G20)>0, COUNTIFS($AE$2:$AE$200,$G20)>0, COUNTIFS($AF$2:$AF$200,$G20)>0, COUNTIFS($AG$2:$AG$200,$G20)>0, COUNTIFS($AH$2:$AH$200,$G20)>0, COUNTIFS($AI$2:$AI$200,$G20)>0, COUNTIFS($AJ$2:$AJ$200,$G20)>0, COUNTIFS($AK$2:$AK$200,$G20)>0, COUNTIFS($AL$2:$AL$200,$G20)>0, COUNTIFS($AM$2:$AM$200,$G20)>0, COUNTIFS($AN$2:$AN$200,$G20)>0, COUNTIFS($AO$2:$AO$200,$G20)>0, COUNTIFS($AP$2:$AP$200,$G20)>0, COUNTIFS($AQ$2:$AQ$200,$G20)>0, COUNTIFS($AR$2:$AR$200,$G20)>0, COUNTIFS($AS$2:$AS$200,$G20)>0, COUNTIFS($AT$2:$AT$200,$G20)>0, COUNTIFS($AU$2:$AU$200,$G20)>0, COUNTIFS($AV$2:$AV$200,$G20)>0, COUNTIFS($AW$2:$AW$200,$G20)>0, COUNTIFS($AX$2:$AX$200,$G20)>0 )), ), 2 ), "")} | E20: {=IFERROR( INDEX( _xlfn._xlws.FILTER($U$1:$AX$1, TRANSPOSE( CHOOSE({1;2;3;4;5;6;7;8;9;10;11;12;13;14;15;16;17;18;19;20;21;22;23;24;25;26;27;28;29;30}, COUNTIFS($U$2:$U$200,$G20)>0, COUNTIFS($V$2:$V$200,$G20)>0, COUNTIFS($W$2:$W$200,$G20)>0, COUNTIFS($X$2:$X$200,$G20)>0, COUNTIFS($Y$2:$Y$200,$G20)>0, COUNTIFS($Z$2:$Z$200,$G20)>0, COUNTIFS($AA$2:$AA$200,$G20)>0, COUNTIFS($AB$2:$AB$200,$G20)>0, COUNTIFS($AC$2:$AC$200,$G20)>0, COUNTIFS($AD$2:$AD$200,$G20)>0, COUNTIFS($AE$2:$AE$200,$G20)>0, COUNTIFS($AF$2:$AF$200,$G20)>0, COUNTIFS($AG$2:$AG$200,$G20)>0, COUNTIFS($AH$2:$AH$200,$G20)>0, COUNTIFS($AI$2:$AI$200,$G20)>0, COUNTIFS($AJ$2:$AJ$200,$G20)>0, COUNTIFS($AK$2:$AK$200,$G20)>0, COUNTIFS($AL$2:$AL$200,$G20)>0, COUNTIFS($AM$2:$AM$200,$G20)>0, COUNTIFS($AN$2:$AN$200,$G20)>0, COUNTIFS($AO$2:$AO$200,$G20)>0, COUNTIFS($AP$2:$AP$200,$G20)>0, COUNTIFS($AQ$2:$AQ$200,$G20)>0, COUNTIFS($AR$2:$AR$200,$G20)>0, COUNTIFS($AS$2:$AS$200,$G20)>0, COUNTIFS($AT$2:$AT$200,$G20)>0, COUNTIFS($AU$2:$AU$200,$G20)>0, COUNTIFS($AV$2:$AV$200,$G20)>0, COUNTIFS($AW$2:$AW$200,$G20)>0, COUNTIFS($AX$2:$AX$200,$G20)>0 )), ), 3 ), "")} | F20: {=IFERROR( INDEX( _xlfn._xlws.FILTER($U$1:$AX$1, TRANSPOSE( CHOOSE({1;2;3;4;5;6;7;8;9;10;11;12;13;14;15;16;17;18;19;20;21;22;23;24;25;26;27;28;29;30}, COUNTIFS($U$2:$U$200,$G20)>0, COUNTIFS($V$2:$V$200,$G20)>0, COUNTIFS($W$2:$W$200,$G20)>0, COUNTIFS($X$2:$X$200,$G20)>0, COUNTIFS($Y$2:$Y$200,$G20)>0, COUNTIFS($Z$2:$Z$200,$G20)>0, COUNTIFS($AA$2:$AA$200,$G20)>0, COUNTIFS($AB$2:$AB$200,$G20)>0, COUNTIFS($AC$2:$AC$200,$G20)>0, COUNTIFS($AD$2:$AD$200,$G20)>0, COUNTIFS($AE$2:$AE$200,$G20)>0, COUNTIFS($AF$2:$AF$200,$G20)>0, COUNTIFS($AG$2:$AG$200,$G20)>0, COUNTIFS($AH$2:$AH$200,$G20)>0, COUNTIFS($AI$2:$AI$200,$G20)>0, COUNTIFS($AJ$2:$AJ$200,$G20)>0, COUNTIFS($AK$2:$AK$200,$G20)>0, COUNTIFS($AL$2:$AL$200,$G20)>0, COUNTIFS($AM$2:$AM$200,$G20)>0, COUNTIFS($AN$2:$AN$200,$G20)>0, COUNTIFS($AO$2:$AO$200,$G20)>0, COUNTIFS($AP$2:$AP$200,$G20)>0, COUNTIFS($AQ$2:$AQ$200,$G20)>0, COUNTIFS($AR$2:$AR$200,$G20)>0, COUNTIFS($AS$2:$AS$200,$G20)>0, COUNTIFS($AT$2:$AT$200,$G20)>0, COUNTIFS($AU$2:$AU$200,$G20)>0, COUNTIFS($AV$2:$AV$200,$G20)>0, COUNTIFS($AW$2:$AW$200,$G20)>0, COUNTIFS($AX$2:$AX$200,$G20)>0 )), ), 4 ), "")} | G20: Arcbound Javelineer | I20: Elfos | J20: =Elfos!G2 -> 6 | K20: Não | L20: Sim | M20: Não | N20: Sim | O20: Sim | P20: Combo | Q20: Combate | R20: Muita Mana | S20: =IF(J20<6,"5",IF(J20<11,"4",IF(J20<16,"3",IF(J20<31,"2","1")))) -> 4 | U20: Shoot the Sheriff | V20: Mossfire Valley | W20: Slash the Ranks | X20: Maester Seymour | Z20: Xantcha, Agente Adormecida | AA20: Throne of the God-Pharaoh | AX20: Boros Signet | AZ20: Titania, Voice of Gaea | BA20: Thrumming Hivepool | BC20: Shizo, Death's Storehouse | BD20: Mistbind Clique | BE20: Pain for All | BF20: Life of the Party | BG20: Jadar, Ghoulcaller of Nephalia | BH20: Devoted Druid | BI20: Beast Within | BK20: Matoya, Archon Elder | BL20: Luxury Suite | BM20: Espada de Verdade e Justiça | BN20: Fabled Passage | BO20: Arwen, Weaver of Hope | BQ20: Crisol dos Mundos | BR20: Commodore Guff | BT20: Beast Within
A21: =IFERROR(INDEX($S$3:$S$200, MATCH($C21, $I$3:$I$200, 0)), "") -> 1 | B21: =COUNTIF(U:AX,G21) -> 1 | C21: =IFERROR( INDEX($U$1:$AX$1, MATCH(TRUE, CHOOSE({1;2;3;4;5;6;7;8;9;10;11;12;13;14;15;16;17;18;19;20;21;22;23;24;25;26;27;28;29;30;31;32}, COUNTIFS($U$2:$U$200,$G21)>0, COUNTIFS($V$2:$V$200,$G21)>0, COUNTIFS($W$2:$W$200,$G21)>0, COUNTIFS($X$2:$X$200,$G21)>0, COUNTIFS($Y$2:$Y$200,$G21)>0, COUNTIFS($Z$2:$Z$200,$G21)>0, COUNTIFS($AA$2:$AA$200,$G21)>0, COUNTIFS($AB$2:$AB$200,$G21)>0, COUNTIFS($AC$2:$AC$200,$G21)>0, COUNTIFS($AD$2:$AD$200,$G21)>0, COUNTIFS($AE$2:$AE$200,$G21)>0, COUNTIFS($AF$2:$AF$200,$G21)>0, COUNTIFS($AG$2:$AG$200,$G21)>0, COUNTIFS($AH$2:$AH$200,$G21)>0, COUNTIFS($AI$2:$AI$200,$G21)>0, COUNTIFS($AJ$2:$AJ$200,$G21)>0, COUNTIFS($AK$2:$AK$200,$G21)>0, COUNTIFS($AL$2:$AL$200,$G21)>0, COUNTIFS($AM$2:$AM$200,$G21)>0, COUNTIFS($AN$2:$AN$200,$G21)>0, COUNTIFS($AO$2:$AO$200,$G21)>0, COUNTIFS($AP$2:$AP$200,$G21)>0, COUNTIFS($AQ$2:$AQ$200,$G21)>0, COUNTIFS($AR$2:$AR$200,$G21)>0, COUNTIFS($AS$2:$AS$200,$G21)>0, COUNTIFS($AT$2:$AT$200,$G21)>0, COUNTIFS($AU$2:$AU$200,$G21)>0, COUNTIFS($AV$2:$AV$200,$G21)>0, COUNTIFS($AW$2:$AW$200,$G21)>0, COUNTIFS($AX$2:$AX$200,$G21)>0 ), 0) ), "") -> Modular | D21: {=IFERROR( INDEX( _xlfn._xlws.FILTER($U$1:$AX$1, TRANSPOSE( CHOOSE({1;2;3;4;5;6;7;8;9;10;11;12;13;14;15;16;17;18;19;20;21;22;23;24;25;26;27;28;29;30}, COUNTIFS($U$2:$U$200,$G21)>0, COUNTIFS($V$2:$V$200,$G21)>0, COUNTIFS($W$2:$W$200,$G21)>0, COUNTIFS($X$2:$X$200,$G21)>0, COUNTIFS($Y$2:$Y$200,$G21)>0, COUNTIFS($Z$2:$Z$200,$G21)>0, COUNTIFS($AA$2:$AA$200,$G21)>0, COUNTIFS($AB$2:$AB$200,$G21)>0, COUNTIFS($AC$2:$AC$200,$G21)>0, COUNTIFS($AD$2:$AD$200,$G21)>0, COUNTIFS($AE$2:$AE$200,$G21)>0, COUNTIFS($AF$2:$AF$200,$G21)>0, COUNTIFS($AG$2:$AG$200,$G21)>0, COUNTIFS($AH$2:$AH$200,$G21)>0, COUNTIFS($AI$2:$AI$200,$G21)>0, COUNTIFS($AJ$2:$AJ$200,$G21)>0, COUNTIFS($AK$2:$AK$200,$G21)>0, COUNTIFS($AL$2:$AL$200,$G21)>0, COUNTIFS($AM$2:$AM$200,$G21)>0, COUNTIFS($AN$2:$AN$200,$G21)>0, COUNTIFS($AO$2:$AO$200,$G21)>0, COUNTIFS($AP$2:$AP$200,$G21)>0, COUNTIFS($AQ$2:$AQ$200,$G21)>0, COUNTIFS($AR$2:$AR$200,$G21)>0, COUNTIFS($AS$2:$AS$200,$G21)>0, COUNTIFS($AT$2:$AT$200,$G21)>0, COUNTIFS($AU$2:$AU$200,$G21)>0, COUNTIFS($AV$2:$AV$200,$G21)>0, COUNTIFS($AW$2:$AW$200,$G21)>0, COUNTIFS($AX$2:$AX$200,$G21)>0 )), ), 2 ), "")} | E21: {=IFERROR( INDEX( _xlfn._xlws.FILTER($U$1:$AX$1, TRANSPOSE( CHOOSE({1;2;3;4;5;6;7;8;9;10;11;12;13;14;15;16;17;18;19;20;21;22;23;24;25;26;27;28;29;30}, COUNTIFS($U$2:$U$200,$G21)>0, COUNTIFS($V$2:$V$200,$G21)>0, COUNTIFS($W$2:$W$200,$G21)>0, COUNTIFS($X$2:$X$200,$G21)>0, COUNTIFS($Y$2:$Y$200,$G21)>0, COUNTIFS($Z$2:$Z$200,$G21)>0, COUNTIFS($AA$2:$AA$200,$G21)>0, COUNTIFS($AB$2:$AB$200,$G21)>0, COUNTIFS($AC$2:$AC$200,$G21)>0, COUNTIFS($AD$2:$AD$200,$G21)>0, COUNTIFS($AE$2:$AE$200,$G21)>0, COUNTIFS($AF$2:$AF$200,$G21)>0, COUNTIFS($AG$2:$AG$200,$G21)>0, COUNTIFS($AH$2:$AH$200,$G21)>0, COUNTIFS($AI$2:$AI$200,$G21)>0, COUNTIFS($AJ$2:$AJ$200,$G21)>0, COUNTIFS($AK$2:$AK$200,$G21)>0, COUNTIFS($AL$2:$AL$200,$G21)>0, COUNTIFS($AM$2:$AM$200,$G21)>0, COUNTIFS($AN$2:$AN$200,$G21)>0, COUNTIFS($AO$2:$AO$200,$G21)>0, COUNTIFS($AP$2:$AP$200,$G21)>0, COUNTIFS($AQ$2:$AQ$200,$G21)>0, COUNTIFS($AR$2:$AR$200,$G21)>0, COUNTIFS($AS$2:$AS$200,$G21)>0, COUNTIFS($AT$2:$AT$200,$G21)>0, COUNTIFS($AU$2:$AU$200,$G21)>0, COUNTIFS($AV$2:$AV$200,$G21)>0, COUNTIFS($AW$2:$AW$200,$G21)>0, COUNTIFS($AX$2:$AX$200,$G21)>0 )), ), 3 ), "")} | F21: {=IFERROR( INDEX( _xlfn._xlws.FILTER($U$1:$AX$1, TRANSPOSE( CHOOSE({1;2;3;4;5;6;7;8;9;10;11;12;13;14;15;16;17;18;19;20;21;22;23;24;25;26;27;28;29;30}, COUNTIFS($U$2:$U$200,$G21)>0, COUNTIFS($V$2:$V$200,$G21)>0, COUNTIFS($W$2:$W$200,$G21)>0, COUNTIFS($X$2:$X$200,$G21)>0, COUNTIFS($Y$2:$Y$200,$G21)>0, COUNTIFS($Z$2:$Z$200,$G21)>0, COUNTIFS($AA$2:$AA$200,$G21)>0, COUNTIFS($AB$2:$AB$200,$G21)>0, COUNTIFS($AC$2:$AC$200,$G21)>0, COUNTIFS($AD$2:$AD$200,$G21)>0, COUNTIFS($AE$2:$AE$200,$G21)>0, COUNTIFS($AF$2:$AF$200,$G21)>0, COUNTIFS($AG$2:$AG$200,$G21)>0, COUNTIFS($AH$2:$AH$200,$G21)>0, COUNTIFS($AI$2:$AI$200,$G21)>0, COUNTIFS($AJ$2:$AJ$200,$G21)>0, COUNTIFS($AK$2:$AK$200,$G21)>0, COUNTIFS($AL$2:$AL$200,$G21)>0, COUNTIFS($AM$2:$AM$200,$G21)>0, COUNTIFS($AN$2:$AN$200,$G21)>0, COUNTIFS($AO$2:$AO$200,$G21)>0, COUNTIFS($AP$2:$AP$200,$G21)>0, COUNTIFS($AQ$2:$AQ$200,$G21)>0, COUNTIFS($AR$2:$AR$200,$G21)>0, COUNTIFS($AS$2:$AS$200,$G21)>0, COUNTIFS($AT$2:$AT$200,$G21)>0, COUNTIFS($AU$2:$AU$200,$G21)>0, COUNTIFS($AV$2:$AV$200,$G21)>0, COUNTIFS($AW$2:$AW$200,$G21)>0, COUNTIFS($AX$2:$AX$200,$G21)>0 )), ), 4 ), "")} | G21: Arcbound Mouser | I21: Jhoira | J21: =Jhoira!G2 -> 5 | K21: Não | L21: Sim | M21: Sim | N21: Não | O21: Não | P21: Combo | Q21: Combate | R21: Destruição em Massa | S21: =IF(J21<6,"5",IF(J21<11,"4",IF(J21<16,"3",IF(J21<31,"2","1")))) -> 5 | U21: Siren Stormtamer | V21: Nature's Lore | W21: Slayers' Stronghold | X21: Managorger Hydra | AA21: Tishana, Voice of Thunder | AX21: Buried Ruin | AZ21: Ulamog, the Infinite Gyre | BA21: Trioma de Indatha | BC21: Spectator Seating | BD21: Molten Echoes | BE21: Red XIII, Proud Warrior | BF21: Lolth, Rainha Aranha | BG21: Jidoor, Aristocratic Capital // Overture | BH21: Emrakul, um Novo Mundo | BI21: Bident of Thassa | BK21: Mirrex | BL21: Mandate of Peace | BM21: Exemplar of Light | BN21: Fellwar Stone | BO21: Aura Mutation | BQ21: Delighted Halfling | BR21: Counterspell | BT21: Bloodstained Mire
A22: =IFERROR(INDEX($S$3:$S$200, MATCH($C22, $I$3:$I$200, 0)), "") -> 1 | B22: =COUNTIF(U:AX,G22) -> 1 | C22: =IFERROR( INDEX($U$1:$AX$1, MATCH(TRUE, CHOOSE({1;2;3;4;5;6;7;8;9;10;11;12;13;14;15;16;17;18;19;20;21;22;23;24;25;26;27;28;29;30;31;32}, COUNTIFS($U$2:$U$200,$G22)>0, COUNTIFS($V$2:$V$200,$G22)>0, COUNTIFS($W$2:$W$200,$G22)>0, COUNTIFS($X$2:$X$200,$G22)>0, COUNTIFS($Y$2:$Y$200,$G22)>0, COUNTIFS($Z$2:$Z$200,$G22)>0, COUNTIFS($AA$2:$AA$200,$G22)>0, COUNTIFS($AB$2:$AB$200,$G22)>0, COUNTIFS($AC$2:$AC$200,$G22)>0, COUNTIFS($AD$2:$AD$200,$G22)>0, COUNTIFS($AE$2:$AE$200,$G22)>0, COUNTIFS($AF$2:$AF$200,$G22)>0, COUNTIFS($AG$2:$AG$200,$G22)>0, COUNTIFS($AH$2:$AH$200,$G22)>0, COUNTIFS($AI$2:$AI$200,$G22)>0, COUNTIFS($AJ$2:$AJ$200,$G22)>0, COUNTIFS($AK$2:$AK$200,$G22)>0, COUNTIFS($AL$2:$AL$200,$G22)>0, COUNTIFS($AM$2:$AM$200,$G22)>0, COUNTIFS($AN$2:$AN$200,$G22)>0, COUNTIFS($AO$2:$AO$200,$G22)>0, COUNTIFS($AP$2:$AP$200,$G22)>0, COUNTIFS($AQ$2:$AQ$200,$G22)>0, COUNTIFS($AR$2:$AR$200,$G22)>0, COUNTIFS($AS$2:$AS$200,$G22)>0, COUNTIFS($AT$2:$AT$200,$G22)>0, COUNTIFS($AU$2:$AU$200,$G22)>0, COUNTIFS($AV$2:$AV$200,$G22)>0, COUNTIFS($AW$2:$AW$200,$G22)>0, COUNTIFS($AX$2:$AX$200,$G22)>0 ), 0) ), "") -> Modular | D22: {=IFERROR( INDEX( _xlfn._xlws.FILTER($U$1:$AX$1, TRANSPOSE( CHOOSE({1;2;3;4;5;6;7;8;9;10;11;12;13;14;15;16;17;18;19;20;21;22;23;24;25;26;27;28;29;30}, COUNTIFS($U$2:$U$200,$G22)>0, COUNTIFS($V$2:$V$200,$G22)>0, COUNTIFS($W$2:$W$200,$G22)>0, COUNTIFS($X$2:$X$200,$G22)>0, COUNTIFS($Y$2:$Y$200,$G22)>0, COUNTIFS($Z$2:$Z$200,$G22)>0, COUNTIFS($AA$2:$AA$200,$G22)>0, COUNTIFS($AB$2:$AB$200,$G22)>0, COUNTIFS($AC$2:$AC$200,$G22)>0, COUNTIFS($AD$2:$AD$200,$G22)>0, COUNTIFS($AE$2:$AE$200,$G22)>0, COUNTIFS($AF$2:$AF$200,$G22)>0, COUNTIFS($AG$2:$AG$200,$G22)>0, COUNTIFS($AH$2:$AH$200,$G22)>0, COUNTIFS($AI$2:$AI$200,$G22)>0, COUNTIFS($AJ$2:$AJ$200,$G22)>0, COUNTIFS($AK$2:$AK$200,$G22)>0, COUNTIFS($AL$2:$AL$200,$G22)>0, COUNTIFS($AM$2:$AM$200,$G22)>0, COUNTIFS($AN$2:$AN$200,$G22)>0, COUNTIFS($AO$2:$AO$200,$G22)>0, COUNTIFS($AP$2:$AP$200,$G22)>0, COUNTIFS($AQ$2:$AQ$200,$G22)>0, COUNTIFS($AR$2:$AR$200,$G22)>0, COUNTIFS($AS$2:$AS$200,$G22)>0, COUNTIFS($AT$2:$AT$200,$G22)>0, COUNTIFS($AU$2:$AU$200,$G22)>0, COUNTIFS($AV$2:$AV$200,$G22)>0, COUNTIFS($AW$2:$AW$200,$G22)>0, COUNTIFS($AX$2:$AX$200,$G22)>0 )), ), 2 ), "")} | E22: {=IFERROR( INDEX( _xlfn._xlws.FILTER($U$1:$AX$1, TRANSPOSE( CHOOSE({1;2;3;4;5;6;7;8;9;10;11;12;13;14;15;16;17;18;19;20;21;22;23;24;25;26;27;28;29;30}, COUNTIFS($U$2:$U$200,$G22)>0, COUNTIFS($V$2:$V$200,$G22)>0, COUNTIFS($W$2:$W$200,$G22)>0, COUNTIFS($X$2:$X$200,$G22)>0, COUNTIFS($Y$2:$Y$200,$G22)>0, COUNTIFS($Z$2:$Z$200,$G22)>0, COUNTIFS($AA$2:$AA$200,$G22)>0, COUNTIFS($AB$2:$AB$200,$G22)>0, COUNTIFS($AC$2:$AC$200,$G22)>0, COUNTIFS($AD$2:$AD$200,$G22)>0, COUNTIFS($AE$2:$AE$200,$G22)>0, COUNTIFS($AF$2:$AF$200,$G22)>0, COUNTIFS($AG$2:$AG$200,$G22)>0, COUNTIFS($AH$2:$AH$200,$G22)>0, COUNTIFS($AI$2:$AI$200,$G22)>0, COUNTIFS($AJ$2:$AJ$200,$G22)>0, COUNTIFS($AK$2:$AK$200,$G22)>0, COUNTIFS($AL$2:$AL$200,$G22)>0, COUNTIFS($AM$2:$AM$200,$G22)>0, COUNTIFS($AN$2:$AN$200,$G22)>0, COUNTIFS($AO$2:$AO$200,$G22)>0, COUNTIFS($AP$2:$AP$200,$G22)>0, COUNTIFS($AQ$2:$AQ$200,$G22)>0, COUNTIFS($AR$2:$AR$200,$G22)>0, COUNTIFS($AS$2:$AS$200,$G22)>0, COUNTIFS($AT$2:$AT$200,$G22)>0, COUNTIFS($AU$2:$AU$200,$G22)>0, COUNTIFS($AV$2:$AV$200,$G22)>0, COUNTIFS($AW$2:$AW$200,$G22)>0, COUNTIFS($AX$2:$AX$200,$G22)>0 )), ), 3 ), "")} | F22: {=IFERROR( INDEX( _xlfn._xlws.FILTER($U$1:$AX$1, TRANSPOSE( CHOOSE({1;2;3;4;5;6;7;8;9;10;11;12;13;14;15;16;17;18;19;20;21;22;23;24;25;26;27;28;29;30}, COUNTIFS($U$2:$U$200,$G22)>0, COUNTIFS($V$2:$V$200,$G22)>0, COUNTIFS($W$2:$W$200,$G22)>0, COUNTIFS($X$2:$X$200,$G22)>0, COUNTIFS($Y$2:$Y$200,$G22)>0, COUNTIFS($Z$2:$Z$200,$G22)>0, COUNTIFS($AA$2:$AA$200,$G22)>0, COUNTIFS($AB$2:$AB$200,$G22)>0, COUNTIFS($AC$2:$AC$200,$G22)>0, COUNTIFS($AD$2:$AD$200,$G22)>0, COUNTIFS($AE$2:$AE$200,$G22)>0, COUNTIFS($AF$2:$AF$200,$G22)>0, COUNTIFS($AG$2:$AG$200,$G22)>0, COUNTIFS($AH$2:$AH$200,$G22)>0, COUNTIFS($AI$2:$AI$200,$G22)>0, COUNTIFS($AJ$2:$AJ$200,$G22)>0, COUNTIFS($AK$2:$AK$200,$G22)>0, COUNTIFS($AL$2:$AL$200,$G22)>0, COUNTIFS($AM$2:$AM$200,$G22)>0, COUNTIFS($AN$2:$AN$200,$G22)>0, COUNTIFS($AO$2:$AO$200,$G22)>0, COUNTIFS($AP$2:$AP$200,$G22)>0, COUNTIFS($AQ$2:$AQ$200,$G22)>0, COUNTIFS($AR$2:$AR$200,$G22)>0, COUNTIFS($AS$2:$AS$200,$G22)>0, COUNTIFS($AT$2:$AT$200,$G22)>0, COUNTIFS($AU$2:$AU$200,$G22)>0, COUNTIFS($AV$2:$AV$200,$G22)>0, COUNTIFS($AW$2:$AW$200,$G22)>0, COUNTIFS($AX$2:$AX$200,$G22)>0 )), ), 4 ), "")} | G22: Arcbound Overseer | I22: Fractius | J22: =Fractius!G2 -> 8 | K22: Sim | L22: Sim | M22: Sim | N22: Sim | O22: Sim | P22: Combate | Q22: Voltron | R22: Tribal de Fractius | S22: =IF(J22<6,"5",IF(J22<11,"4",IF(J22<16,"3",IF(J22<31,"2","1")))) -> 4 | U22: Spyglass Siren | V22: Prosperous Partnership | W22: Smuggler's Share | X22: Ozolith, the Shattered Spire | AA22: Vanquisher's Banner | AX22: Darksteel Citadel | AZ22: Uthros, Titanic Godcore | BA22: Trioma de Raugrin | BC22: Temporal Manipulation | BD22: Mother of runes | BE22: Reflecting Pool | BF22: Nicol Bolas, God-Pharaoh | BG22: Khorvath's Fury | BH22: Exalted Sunborn | BI22: Bojuka Bog | BK22: Mistrise Village | BL22: Morphic Pool | BM22: Firion, Wild Rose Warrior | BN22: Frenzied Gorespawn | BO22: Back in Town | BQ22: Dionus, Elvish Archdruid | BR22: Cyber Conversion | BT22: Bojuka Bog
A23: =IFERROR(INDEX($S$3:$S$200, MATCH($C23, $I$3:$I$200, 0)), "") -> 1 | B23: =COUNTIF(U:AX,G23) -> 1 | C23: =IFERROR( INDEX($U$1:$AX$1, MATCH(TRUE, CHOOSE({1;2;3;4;5;6;7;8;9;10;11;12;13;14;15;16;17;18;19;20;21;22;23;24;25;26;27;28;29;30;31;32}, COUNTIFS($U$2:$U$200,$G23)>0, COUNTIFS($V$2:$V$200,$G23)>0, COUNTIFS($W$2:$W$200,$G23)>0, COUNTIFS($X$2:$X$200,$G23)>0, COUNTIFS($Y$2:$Y$200,$G23)>0, COUNTIFS($Z$2:$Z$200,$G23)>0, COUNTIFS($AA$2:$AA$200,$G23)>0, COUNTIFS($AB$2:$AB$200,$G23)>0, COUNTIFS($AC$2:$AC$200,$G23)>0, COUNTIFS($AD$2:$AD$200,$G23)>0, COUNTIFS($AE$2:$AE$200,$G23)>0, COUNTIFS($AF$2:$AF$200,$G23)>0, COUNTIFS($AG$2:$AG$200,$G23)>0, COUNTIFS($AH$2:$AH$200,$G23)>0, COUNTIFS($AI$2:$AI$200,$G23)>0, COUNTIFS($AJ$2:$AJ$200,$G23)>0, COUNTIFS($AK$2:$AK$200,$G23)>0, COUNTIFS($AL$2:$AL$200,$G23)>0, COUNTIFS($AM$2:$AM$200,$G23)>0, COUNTIFS($AN$2:$AN$200,$G23)>0, COUNTIFS($AO$2:$AO$200,$G23)>0, COUNTIFS($AP$2:$AP$200,$G23)>0, COUNTIFS($AQ$2:$AQ$200,$G23)>0, COUNTIFS($AR$2:$AR$200,$G23)>0, COUNTIFS($AS$2:$AS$200,$G23)>0, COUNTIFS($AT$2:$AT$200,$G23)>0, COUNTIFS($AU$2:$AU$200,$G23)>0, COUNTIFS($AV$2:$AV$200,$G23)>0, COUNTIFS($AW$2:$AW$200,$G23)>0, COUNTIFS($AX$2:$AX$200,$G23)>0 ), 0) ), "") -> Modular | D23: {=IFERROR( INDEX( _xlfn._xlws.FILTER($U$1:$AX$1, TRANSPOSE( CHOOSE({1;2;3;4;5;6;7;8;9;10;11;12;13;14;15;16;17;18;19;20;21;22;23;24;25;26;27;28;29;30}, COUNTIFS($U$2:$U$200,$G23)>0, COUNTIFS($V$2:$V$200,$G23)>0, COUNTIFS($W$2:$W$200,$G23)>0, COUNTIFS($X$2:$X$200,$G23)>0, COUNTIFS($Y$2:$Y$200,$G23)>0, COUNTIFS($Z$2:$Z$200,$G23)>0, COUNTIFS($AA$2:$AA$200,$G23)>0, COUNTIFS($AB$2:$AB$200,$G23)>0, COUNTIFS($AC$2:$AC$200,$G23)>0, COUNTIFS($AD$2:$AD$200,$G23)>0, COUNTIFS($AE$2:$AE$200,$G23)>0, COUNTIFS($AF$2:$AF$200,$G23)>0, COUNTIFS($AG$2:$AG$200,$G23)>0, COUNTIFS($AH$2:$AH$200,$G23)>0, COUNTIFS($AI$2:$AI$200,$G23)>0, COUNTIFS($AJ$2:$AJ$200,$G23)>0, COUNTIFS($AK$2:$AK$200,$G23)>0, COUNTIFS($AL$2:$AL$200,$G23)>0, COUNTIFS($AM$2:$AM$200,$G23)>0, COUNTIFS($AN$2:$AN$200,$G23)>0, COUNTIFS($AO$2:$AO$200,$G23)>0, COUNTIFS($AP$2:$AP$200,$G23)>0, COUNTIFS($AQ$2:$AQ$200,$G23)>0, COUNTIFS($AR$2:$AR$200,$G23)>0, COUNTIFS($AS$2:$AS$200,$G23)>0, COUNTIFS($AT$2:$AT$200,$G23)>0, COUNTIFS($AU$2:$AU$200,$G23)>0, COUNTIFS($AV$2:$AV$200,$G23)>0, COUNTIFS($AW$2:$AW$200,$G23)>0, COUNTIFS($AX$2:$AX$200,$G23)>0 )), ), 2 ), "")} | E23: {=IFERROR( INDEX( _xlfn._xlws.FILTER($U$1:$AX$1, TRANSPOSE( CHOOSE({1;2;3;4;5;6;7;8;9;10;11;12;13;14;15;16;17;18;19;20;21;22;23;24;25;26;27;28;29;30}, COUNTIFS($U$2:$U$200,$G23)>0, COUNTIFS($V$2:$V$200,$G23)>0, COUNTIFS($W$2:$W$200,$G23)>0, COUNTIFS($X$2:$X$200,$G23)>0, COUNTIFS($Y$2:$Y$200,$G23)>0, COUNTIFS($Z$2:$Z$200,$G23)>0, COUNTIFS($AA$2:$AA$200,$G23)>0, COUNTIFS($AB$2:$AB$200,$G23)>0, COUNTIFS($AC$2:$AC$200,$G23)>0, COUNTIFS($AD$2:$AD$200,$G23)>0, COUNTIFS($AE$2:$AE$200,$G23)>0, COUNTIFS($AF$2:$AF$200,$G23)>0, COUNTIFS($AG$2:$AG$200,$G23)>0, COUNTIFS($AH$2:$AH$200,$G23)>0, COUNTIFS($AI$2:$AI$200,$G23)>0, COUNTIFS($AJ$2:$AJ$200,$G23)>0, COUNTIFS($AK$2:$AK$200,$G23)>0, COUNTIFS($AL$2:$AL$200,$G23)>0, COUNTIFS($AM$2:$AM$200,$G23)>0, COUNTIFS($AN$2:$AN$200,$G23)>0, COUNTIFS($AO$2:$AO$200,$G23)>0, COUNTIFS($AP$2:$AP$200,$G23)>0, COUNTIFS($AQ$2:$AQ$200,$G23)>0, COUNTIFS($AR$2:$AR$200,$G23)>0, COUNTIFS($AS$2:$AS$200,$G23)>0, COUNTIFS($AT$2:$AT$200,$G23)>0, COUNTIFS($AU$2:$AU$200,$G23)>0, COUNTIFS($AV$2:$AV$200,$G23)>0, COUNTIFS($AW$2:$AW$200,$G23)>0, COUNTIFS($AX$2:$AX$200,$G23)>0 )), ), 3 ), "")} | F23: {=IFERROR( INDEX( _xlfn._xlws.FILTER($U$1:$AX$1, TRANSPOSE( CHOOSE({1;2;3;4;5;6;7;8;9;10;11;12;13;14;15;16;17;18;19;20;21;22;23;24;25;26;27;28;29;30}, COUNTIFS($U$2:$U$200,$G23)>0, COUNTIFS($V$2:$V$200,$G23)>0, COUNTIFS($W$2:$W$200,$G23)>0, COUNTIFS($X$2:$X$200,$G23)>0, COUNTIFS($Y$2:$Y$200,$G23)>0, COUNTIFS($Z$2:$Z$200,$G23)>0, COUNTIFS($AA$2:$AA$200,$G23)>0, COUNTIFS($AB$2:$AB$200,$G23)>0, COUNTIFS($AC$2:$AC$200,$G23)>0, COUNTIFS($AD$2:$AD$200,$G23)>0, COUNTIFS($AE$2:$AE$200,$G23)>0, COUNTIFS($AF$2:$AF$200,$G23)>0, COUNTIFS($AG$2:$AG$200,$G23)>0, COUNTIFS($AH$2:$AH$200,$G23)>0, COUNTIFS($AI$2:$AI$200,$G23)>0, COUNTIFS($AJ$2:$AJ$200,$G23)>0, COUNTIFS($AK$2:$AK$200,$G23)>0, COUNTIFS($AL$2:$AL$200,$G23)>0, COUNTIFS($AM$2:$AM$200,$G23)>0, COUNTIFS($AN$2:$AN$200,$G23)>0, COUNTIFS($AO$2:$AO$200,$G23)>0, COUNTIFS($AP$2:$AP$200,$G23)>0, COUNTIFS($AQ$2:$AQ$200,$G23)>0, COUNTIFS($AR$2:$AR$200,$G23)>0, COUNTIFS($AS$2:$AS$200,$G23)>0, COUNTIFS($AT$2:$AT$200,$G23)>0, COUNTIFS($AU$2:$AU$200,$G23)>0, COUNTIFS($AV$2:$AV$200,$G23)>0, COUNTIFS($AW$2:$AW$200,$G23)>0, COUNTIFS($AX$2:$AX$200,$G23)>0 )), ), 4 ), "")} | G23: Arcbound Ravager | I23: Rielle | J23: =Rielle!G2 -> 7 | K23: Não | L23: Sim | M23: Sim | N23: Não | O23: Não | P23: Voltron | Q23: Dano Direto | R23: Controle Voltron | S23: =IF(J23<6,"5",IF(J23<11,"4",IF(J23<16,"3",IF(J23<31,"2","1")))) -> 4 | U23: Storm the Vault | V23: Purphoros, God of the Forge | W23: Sokenzan, Crucible of Defiance | X23: Patrolling Peacemaker | AX23: Dispatch | AZ23: Zagoth Triome | BA23: Trioma de Zagoth | BC23: Temporal Trespass | BD23: Reliquary Tower | BE23: Saqueador Amaldiçoado | BF23: O Dínamo Peregrino | BG23: Kodama's Reach | BH23: Exotic Orchard | BI23: Boros Signet | BK23: Nissa, Resurgent Animist | BL23: Ojer Pakpatiq, Era Profunda | BM23: Giver of Runes | BN23: Freyalise, Llanowar's Fury | BO23: Badgermole | BQ23: Drowned Catacomb | BR23: Daretti, Ingenious Iconoclast | BT23: Broodheart Engine
A24: =IFERROR(INDEX($S$3:$S$200, MATCH($C24, $I$3:$I$200, 0)), "") -> 1 | B24: =COUNTIF(U:AX,G24) -> 1 | C24: =IFERROR( INDEX($U$1:$AX$1, MATCH(TRUE, CHOOSE({1;2;3;4;5;6;7;8;9;10;11;12;13;14;15;16;17;18;19;20;21;22;23;24;25;26;27;28;29;30;31;32}, COUNTIFS($U$2:$U$200,$G24)>0, COUNTIFS($V$2:$V$200,$G24)>0, COUNTIFS($W$2:$W$200,$G24)>0, COUNTIFS($X$2:$X$200,$G24)>0, COUNTIFS($Y$2:$Y$200,$G24)>0, COUNTIFS($Z$2:$Z$200,$G24)>0, COUNTIFS($AA$2:$AA$200,$G24)>0, COUNTIFS($AB$2:$AB$200,$G24)>0, COUNTIFS($AC$2:$AC$200,$G24)>0, COUNTIFS($AD$2:$AD$200,$G24)>0, COUNTIFS($AE$2:$AE$200,$G24)>0, COUNTIFS($AF$2:$AF$200,$G24)>0, COUNTIFS($AG$2:$AG$200,$G24)>0, COUNTIFS($AH$2:$AH$200,$G24)>0, COUNTIFS($AI$2:$AI$200,$G24)>0, COUNTIFS($AJ$2:$AJ$200,$G24)>0, COUNTIFS($AK$2:$AK$200,$G24)>0, COUNTIFS($AL$2:$AL$200,$G24)>0, COUNTIFS($AM$2:$AM$200,$G24)>0, COUNTIFS($AN$2:$AN$200,$G24)>0, COUNTIFS($AO$2:$AO$200,$G24)>0, COUNTIFS($AP$2:$AP$200,$G24)>0, COUNTIFS($AQ$2:$AQ$200,$G24)>0, COUNTIFS($AR$2:$AR$200,$G24)>0, COUNTIFS($AS$2:$AS$200,$G24)>0, COUNTIFS($AT$2:$AT$200,$G24)>0, COUNTIFS($AU$2:$AU$200,$G24)>0, COUNTIFS($AV$2:$AV$200,$G24)>0, COUNTIFS($AW$2:$AW$200,$G24)>0, COUNTIFS($AX$2:$AX$200,$G24)>0 ), 0) ), "") -> Modular | D24: {=IFERROR( INDEX( _xlfn._xlws.FILTER($U$1:$AX$1, TRANSPOSE( CHOOSE({1;2;3;4;5;6;7;8;9;10;11;12;13;14;15;16;17;18;19;20;21;22;23;24;25;26;27;28;29;30}, COUNTIFS($U$2:$U$200,$G24)>0, COUNTIFS($V$2:$V$200,$G24)>0, COUNTIFS($W$2:$W$200,$G24)>0, COUNTIFS($X$2:$X$200,$G24)>0, COUNTIFS($Y$2:$Y$200,$G24)>0, COUNTIFS($Z$2:$Z$200,$G24)>0, COUNTIFS($AA$2:$AA$200,$G24)>0, COUNTIFS($AB$2:$AB$200,$G24)>0, COUNTIFS($AC$2:$AC$200,$G24)>0, COUNTIFS($AD$2:$AD$200,$G24)>0, COUNTIFS($AE$2:$AE$200,$G24)>0, COUNTIFS($AF$2:$AF$200,$G24)>0, COUNTIFS($AG$2:$AG$200,$G24)>0, COUNTIFS($AH$2:$AH$200,$G24)>0, COUNTIFS($AI$2:$AI$200,$G24)>0, COUNTIFS($AJ$2:$AJ$200,$G24)>0, COUNTIFS($AK$2:$AK$200,$G24)>0, COUNTIFS($AL$2:$AL$200,$G24)>0, COUNTIFS($AM$2:$AM$200,$G24)>0, COUNTIFS($AN$2:$AN$200,$G24)>0, COUNTIFS($AO$2:$AO$200,$G24)>0, COUNTIFS($AP$2:$AP$200,$G24)>0, COUNTIFS($AQ$2:$AQ$200,$G24)>0, COUNTIFS($AR$2:$AR$200,$G24)>0, COUNTIFS($AS$2:$AS$200,$G24)>0, COUNTIFS($AT$2:$AT$200,$G24)>0, COUNTIFS($AU$2:$AU$200,$G24)>0, COUNTIFS($AV$2:$AV$200,$G24)>0, COUNTIFS($AW$2:$AW$200,$G24)>0, COUNTIFS($AX$2:$AX$200,$G24)>0 )), ), 2 ), "")} | E24: {=IFERROR( INDEX( _xlfn._xlws.FILTER($U$1:$AX$1, TRANSPOSE( CHOOSE({1;2;3;4;5;6;7;8;9;10;11;12;13;14;15;16;17;18;19;20;21;22;23;24;25;26;27;28;29;30}, COUNTIFS($U$2:$U$200,$G24)>0, COUNTIFS($V$2:$V$200,$G24)>0, COUNTIFS($W$2:$W$200,$G24)>0, COUNTIFS($X$2:$X$200,$G24)>0, COUNTIFS($Y$2:$Y$200,$G24)>0, COUNTIFS($Z$2:$Z$200,$G24)>0, COUNTIFS($AA$2:$AA$200,$G24)>0, COUNTIFS($AB$2:$AB$200,$G24)>0, COUNTIFS($AC$2:$AC$200,$G24)>0, COUNTIFS($AD$2:$AD$200,$G24)>0, COUNTIFS($AE$2:$AE$200,$G24)>0, COUNTIFS($AF$2:$AF$200,$G24)>0, COUNTIFS($AG$2:$AG$200,$G24)>0, COUNTIFS($AH$2:$AH$200,$G24)>0, COUNTIFS($AI$2:$AI$200,$G24)>0, COUNTIFS($AJ$2:$AJ$200,$G24)>0, COUNTIFS($AK$2:$AK$200,$G24)>0, COUNTIFS($AL$2:$AL$200,$G24)>0, COUNTIFS($AM$2:$AM$200,$G24)>0, COUNTIFS($AN$2:$AN$200,$G24)>0, COUNTIFS($AO$2:$AO$200,$G24)>0, COUNTIFS($AP$2:$AP$200,$G24)>0, COUNTIFS($AQ$2:$AQ$200,$G24)>0, COUNTIFS($AR$2:$AR$200,$G24)>0, COUNTIFS($AS$2:$AS$200,$G24)>0, COUNTIFS($AT$2:$AT$200,$G24)>0, COUNTIFS($AU$2:$AU$200,$G24)>0, COUNTIFS($AV$2:$AV$200,$G24)>0, COUNTIFS($AW$2:$AW$200,$G24)>0, COUNTIFS($AX$2:$AX$200,$G24)>0 )), ), 3 ), "")} | F24: {=IFERROR( INDEX( _xlfn._xlws.FILTER($U$1:$AX$1, TRANSPOSE( CHOOSE({1;2;3;4;5;6;7;8;9;10;11;12;13;14;15;16;17;18;19;20;21;22;23;24;25;26;27;28;29;30}, COUNTIFS($U$2:$U$200,$G24)>0, COUNTIFS($V$2:$V$200,$G24)>0, COUNTIFS($W$2:$W$200,$G24)>0, COUNTIFS($X$2:$X$200,$G24)>0, COUNTIFS($Y$2:$Y$200,$G24)>0, COUNTIFS($Z$2:$Z$200,$G24)>0, COUNTIFS($AA$2:$AA$200,$G24)>0, COUNTIFS($AB$2:$AB$200,$G24)>0, COUNTIFS($AC$2:$AC$200,$G24)>0, COUNTIFS($AD$2:$AD$200,$G24)>0, COUNTIFS($AE$2:$AE$200,$G24)>0, COUNTIFS($AF$2:$AF$200,$G24)>0, COUNTIFS($AG$2:$AG$200,$G24)>0, COUNTIFS($AH$2:$AH$200,$G24)>0, COUNTIFS($AI$2:$AI$200,$G24)>0, COUNTIFS($AJ$2:$AJ$200,$G24)>0, COUNTIFS($AK$2:$AK$200,$G24)>0, COUNTIFS($AL$2:$AL$200,$G24)>0, COUNTIFS($AM$2:$AM$200,$G24)>0, COUNTIFS($AN$2:$AN$200,$G24)>0, COUNTIFS($AO$2:$AO$200,$G24)>0, COUNTIFS($AP$2:$AP$200,$G24)>0, COUNTIFS($AQ$2:$AQ$200,$G24)>0, COUNTIFS($AR$2:$AR$200,$G24)>0, COUNTIFS($AS$2:$AS$200,$G24)>0, COUNTIFS($AT$2:$AT$200,$G24)>0, COUNTIFS($AU$2:$AU$200,$G24)>0, COUNTIFS($AV$2:$AV$200,$G24)>0, COUNTIFS($AW$2:$AW$200,$G24)>0, COUNTIFS($AX$2:$AX$200,$G24)>0 )), ), 4 ), "")} | G24: Arcbound Reclaimer | I24: Oona | J24: =Oona!G2 -> 7 | K24: Não | L24: Sim | M24: Não | N24: Sim | O24: Não | P24: Mill | Q24: Combate | R24: Mill e Tokens | S24: =IF(J24<6,"5",IF(J24<11,"4",IF(J24<16,"3",IF(J24<31,"2","1")))) -> 4 | U24: Temple of Malice | V24: Rogue's Passage | W24: Sol Ring | X24: Protection Magic | AX24: Duty Beyond Death | BA24: Ulamog, o Profanador | BC24: Valfenda | BD24: Saw in Half | BE24: Stoneforge Mystic | BF24: Oko, Thief of Crowns | BG24: Lightning Greaves | BH24: Farmer Cotton | BI24: Broadside Bombardiers | BK24: Obelisco de Obsidiana | BL24: Olho de Ojer Taq | BM24: Glasspool Mimic | BN24: Full Throttle | BO24: Beast Within | BQ24: Emergency Eject | BR24: Deeproot Historian | BT24: Bugenhagen, Wise Elder
A25: =IFERROR(INDEX($S$3:$S$200, MATCH($C25, $I$3:$I$200, 0)), "") -> 1 | B25: =COUNTIF(U:AX,G25) -> 1 | C25: =IFERROR( INDEX($U$1:$AX$1, MATCH(TRUE, CHOOSE({1;2;3;4;5;6;7;8;9;10;11;12;13;14;15;16;17;18;19;20;21;22;23;24;25;26;27;28;29;30;31;32}, COUNTIFS($U$2:$U$200,$G25)>0, COUNTIFS($V$2:$V$200,$G25)>0, COUNTIFS($W$2:$W$200,$G25)>0, COUNTIFS($X$2:$X$200,$G25)>0, COUNTIFS($Y$2:$Y$200,$G25)>0, COUNTIFS($Z$2:$Z$200,$G25)>0, COUNTIFS($AA$2:$AA$200,$G25)>0, COUNTIFS($AB$2:$AB$200,$G25)>0, COUNTIFS($AC$2:$AC$200,$G25)>0, COUNTIFS($AD$2:$AD$200,$G25)>0, COUNTIFS($AE$2:$AE$200,$G25)>0, COUNTIFS($AF$2:$AF$200,$G25)>0, COUNTIFS($AG$2:$AG$200,$G25)>0, COUNTIFS($AH$2:$AH$200,$G25)>0, COUNTIFS($AI$2:$AI$200,$G25)>0, COUNTIFS($AJ$2:$AJ$200,$G25)>0, COUNTIFS($AK$2:$AK$200,$G25)>0, COUNTIFS($AL$2:$AL$200,$G25)>0, COUNTIFS($AM$2:$AM$200,$G25)>0, COUNTIFS($AN$2:$AN$200,$G25)>0, COUNTIFS($AO$2:$AO$200,$G25)>0, COUNTIFS($AP$2:$AP$200,$G25)>0, COUNTIFS($AQ$2:$AQ$200,$G25)>0, COUNTIFS($AR$2:$AR$200,$G25)>0, COUNTIFS($AS$2:$AS$200,$G25)>0, COUNTIFS($AT$2:$AT$200,$G25)>0, COUNTIFS($AU$2:$AU$200,$G25)>0, COUNTIFS($AV$2:$AV$200,$G25)>0, COUNTIFS($AW$2:$AW$200,$G25)>0, COUNTIFS($AX$2:$AX$200,$G25)>0 ), 0) ), "") -> Modular | D25: {=IFERROR( INDEX( _xlfn._xlws.FILTER($U$1:$AX$1, TRANSPOSE( CHOOSE({1;2;3;4;5;6;7;8;9;10;11;12;13;14;15;16;17;18;19;20;21;22;23;24;25;26;27;28;29;30}, COUNTIFS($U$2:$U$200,$G25)>0, COUNTIFS($V$2:$V$200,$G25)>0, COUNTIFS($W$2:$W$200,$G25)>0, COUNTIFS($X$2:$X$200,$G25)>0, COUNTIFS($Y$2:$Y$200,$G25)>0, COUNTIFS($Z$2:$Z$200,$G25)>0, COUNTIFS($AA$2:$AA$200,$G25)>0, COUNTIFS($AB$2:$AB$200,$G25)>0, COUNTIFS($AC$2:$AC$200,$G25)>0, COUNTIFS($AD$2:$AD$200,$G25)>0, COUNTIFS($AE$2:$AE$200,$G25)>0, COUNTIFS($AF$2:$AF$200,$G25)>0, COUNTIFS($AG$2:$AG$200,$G25)>0, COUNTIFS($AH$2:$AH$200,$G25)>0, COUNTIFS($AI$2:$AI$200,$G25)>0, COUNTIFS($AJ$2:$AJ$200,$G25)>0, COUNTIFS($AK$2:$AK$200,$G25)>0, COUNTIFS($AL$2:$AL$200,$G25)>0, COUNTIFS($AM$2:$AM$200,$G25)>0, COUNTIFS($AN$2:$AN$200,$G25)>0, COUNTIFS($AO$2:$AO$200,$G25)>0, COUNTIFS($AP$2:$AP$200,$G25)>0, COUNTIFS($AQ$2:$AQ$200,$G25)>0, COUNTIFS($AR$2:$AR$200,$G25)>0, COUNTIFS($AS$2:$AS$200,$G25)>0, COUNTIFS($AT$2:$AT$200,$G25)>0, COUNTIFS($AU$2:$AU$200,$G25)>0, COUNTIFS($AV$2:$AV$200,$G25)>0, COUNTIFS($AW$2:$AW$200,$G25)>0, COUNTIFS($AX$2:$AX$200,$G25)>0 )), ), 2 ), "")} | E25: {=IFERROR( INDEX( _xlfn._xlws.FILTER($U$1:$AX$1, TRANSPOSE( CHOOSE({1;2;3;4;5;6;7;8;9;10;11;12;13;14;15;16;17;18;19;20;21;22;23;24;25;26;27;28;29;30}, COUNTIFS($U$2:$U$200,$G25)>0, COUNTIFS($V$2:$V$200,$G25)>0, COUNTIFS($W$2:$W$200,$G25)>0, COUNTIFS($X$2:$X$200,$G25)>0, COUNTIFS($Y$2:$Y$200,$G25)>0, COUNTIFS($Z$2:$Z$200,$G25)>0, COUNTIFS($AA$2:$AA$200,$G25)>0, COUNTIFS($AB$2:$AB$200,$G25)>0, COUNTIFS($AC$2:$AC$200,$G25)>0, COUNTIFS($AD$2:$AD$200,$G25)>0, COUNTIFS($AE$2:$AE$200,$G25)>0, COUNTIFS($AF$2:$AF$200,$G25)>0, COUNTIFS($AG$2:$AG$200,$G25)>0, COUNTIFS($AH$2:$AH$200,$G25)>0, COUNTIFS($AI$2:$AI$200,$G25)>0, COUNTIFS($AJ$2:$AJ$200,$G25)>0, COUNTIFS($AK$2:$AK$200,$G25)>0, COUNTIFS($AL$2:$AL$200,$G25)>0, COUNTIFS($AM$2:$AM$200,$G25)>0, COUNTIFS($AN$2:$AN$200,$G25)>0, COUNTIFS($AO$2:$AO$200,$G25)>0, COUNTIFS($AP$2:$AP$200,$G25)>0, COUNTIFS($AQ$2:$AQ$200,$G25)>0, COUNTIFS($AR$2:$AR$200,$G25)>0, COUNTIFS($AS$2:$AS$200,$G25)>0, COUNTIFS($AT$2:$AT$200,$G25)>0, COUNTIFS($AU$2:$AU$200,$G25)>0, COUNTIFS($AV$2:$AV$200,$G25)>0, COUNTIFS($AW$2:$AW$200,$G25)>0, COUNTIFS($AX$2:$AX$200,$G25)>0 )), ), 3 ), "")} | F25: {=IFERROR( INDEX( _xlfn._xlws.FILTER($U$1:$AX$1, TRANSPOSE( CHOOSE({1;2;3;4;5;6;7;8;9;10;11;12;13;14;15;16;17;18;19;20;21;22;23;24;25;26;27;28;29;30}, COUNTIFS($U$2:$U$200,$G25)>0, COUNTIFS($V$2:$V$200,$G25)>0, COUNTIFS($W$2:$W$200,$G25)>0, COUNTIFS($X$2:$X$200,$G25)>0, COUNTIFS($Y$2:$Y$200,$G25)>0, COUNTIFS($Z$2:$Z$200,$G25)>0, COUNTIFS($AA$2:$AA$200,$G25)>0, COUNTIFS($AB$2:$AB$200,$G25)>0, COUNTIFS($AC$2:$AC$200,$G25)>0, COUNTIFS($AD$2:$AD$200,$G25)>0, COUNTIFS($AE$2:$AE$200,$G25)>0, COUNTIFS($AF$2:$AF$200,$G25)>0, COUNTIFS($AG$2:$AG$200,$G25)>0, COUNTIFS($AH$2:$AH$200,$G25)>0, COUNTIFS($AI$2:$AI$200,$G25)>0, COUNTIFS($AJ$2:$AJ$200,$G25)>0, COUNTIFS($AK$2:$AK$200,$G25)>0, COUNTIFS($AL$2:$AL$200,$G25)>0, COUNTIFS($AM$2:$AM$200,$G25)>0, COUNTIFS($AN$2:$AN$200,$G25)>0, COUNTIFS($AO$2:$AO$200,$G25)>0, COUNTIFS($AP$2:$AP$200,$G25)>0, COUNTIFS($AQ$2:$AQ$200,$G25)>0, COUNTIFS($AR$2:$AR$200,$G25)>0, COUNTIFS($AS$2:$AS$200,$G25)>0, COUNTIFS($AT$2:$AT$200,$G25)>0, COUNTIFS($AU$2:$AU$200,$G25)>0, COUNTIFS($AV$2:$AV$200,$G25)>0, COUNTIFS($AW$2:$AW$200,$G25)>0, COUNTIFS($AX$2:$AX$200,$G25)>0 )), ), 4 ), "")} | G25: Arcbound Shikari | I25: Kresh | J25: =Kresh!G2 -> 9 | K25: Não | L25: Não | M25: Sim | N25: Sim | O25: Sim | P25: Voltron | Q25: Dano Direto | R25: Controle Voltron | S25: =IF(J25<6,"5",IF(J25<11,"4",IF(J25<16,"3",IF(J25<31,"2","1")))) -> 4 | U25: The Indomitable | V25: Second Harvest | W25: Spark Double | X25: Resourceful Defense | AX25: Earth Rumble | BA25: Valfenda | BC25: Vontade Dominadora | BD25: Scour for Scrap | BE25: The Masamune | BF25: Reliquary Tower | BG25: Lord of Atlantis | BH25: Farseek | BI25: Buried Ruin | BK25: Petrified Field | BL25: Polluted Delta | BM25: Guia das Almas | BN25: Gallifrey Council Chamber | BO25: Bident of Thassa | BQ25: Emrakul, um Novo Mundo | BR25: Diário de Tarrian | BT25: Burnt Offering
A26: =IFERROR(INDEX($S$3:$S$200, MATCH($C26, $I$3:$I$200, 0)), "") -> 1 | B26: =COUNTIF(U:AX,G26) -> 1 | C26: =IFERROR( INDEX($U$1:$AX$1, MATCH(TRUE, CHOOSE({1;2;3;4;5;6;7;8;9;10;11;12;13;14;15;16;17;18;19;20;21;22;23;24;25;26;27;28;29;30;31;32}, COUNTIFS($U$2:$U$200,$G26)>0, COUNTIFS($V$2:$V$200,$G26)>0, COUNTIFS($W$2:$W$200,$G26)>0, COUNTIFS($X$2:$X$200,$G26)>0, COUNTIFS($Y$2:$Y$200,$G26)>0, COUNTIFS($Z$2:$Z$200,$G26)>0, COUNTIFS($AA$2:$AA$200,$G26)>0, COUNTIFS($AB$2:$AB$200,$G26)>0, COUNTIFS($AC$2:$AC$200,$G26)>0, COUNTIFS($AD$2:$AD$200,$G26)>0, COUNTIFS($AE$2:$AE$200,$G26)>0, COUNTIFS($AF$2:$AF$200,$G26)>0, COUNTIFS($AG$2:$AG$200,$G26)>0, COUNTIFS($AH$2:$AH$200,$G26)>0, COUNTIFS($AI$2:$AI$200,$G26)>0, COUNTIFS($AJ$2:$AJ$200,$G26)>0, COUNTIFS($AK$2:$AK$200,$G26)>0, COUNTIFS($AL$2:$AL$200,$G26)>0, COUNTIFS($AM$2:$AM$200,$G26)>0, COUNTIFS($AN$2:$AN$200,$G26)>0, COUNTIFS($AO$2:$AO$200,$G26)>0, COUNTIFS($AP$2:$AP$200,$G26)>0, COUNTIFS($AQ$2:$AQ$200,$G26)>0, COUNTIFS($AR$2:$AR$200,$G26)>0, COUNTIFS($AS$2:$AS$200,$G26)>0, COUNTIFS($AT$2:$AT$200,$G26)>0, COUNTIFS($AU$2:$AU$200,$G26)>0, COUNTIFS($AV$2:$AV$200,$G26)>0, COUNTIFS($AW$2:$AW$200,$G26)>0, COUNTIFS($AX$2:$AX$200,$G26)>0 ), 0) ), "") -> Modular | D26: {=IFERROR( INDEX( _xlfn._xlws.FILTER($U$1:$AX$1, TRANSPOSE( CHOOSE({1;2;3;4;5;6;7;8;9;10;11;12;13;14;15;16;17;18;19;20;21;22;23;24;25;26;27;28;29;30}, COUNTIFS($U$2:$U$200,$G26)>0, COUNTIFS($V$2:$V$200,$G26)>0, COUNTIFS($W$2:$W$200,$G26)>0, COUNTIFS($X$2:$X$200,$G26)>0, COUNTIFS($Y$2:$Y$200,$G26)>0, COUNTIFS($Z$2:$Z$200,$G26)>0, COUNTIFS($AA$2:$AA$200,$G26)>0, COUNTIFS($AB$2:$AB$200,$G26)>0, COUNTIFS($AC$2:$AC$200,$G26)>0, COUNTIFS($AD$2:$AD$200,$G26)>0, COUNTIFS($AE$2:$AE$200,$G26)>0, COUNTIFS($AF$2:$AF$200,$G26)>0, COUNTIFS($AG$2:$AG$200,$G26)>0, COUNTIFS($AH$2:$AH$200,$G26)>0, COUNTIFS($AI$2:$AI$200,$G26)>0, COUNTIFS($AJ$2:$AJ$200,$G26)>0, COUNTIFS($AK$2:$AK$200,$G26)>0, COUNTIFS($AL$2:$AL$200,$G26)>0, COUNTIFS($AM$2:$AM$200,$G26)>0, COUNTIFS($AN$2:$AN$200,$G26)>0, COUNTIFS($AO$2:$AO$200,$G26)>0, COUNTIFS($AP$2:$AP$200,$G26)>0, COUNTIFS($AQ$2:$AQ$200,$G26)>0, COUNTIFS($AR$2:$AR$200,$G26)>0, COUNTIFS($AS$2:$AS$200,$G26)>0, COUNTIFS($AT$2:$AT$200,$G26)>0, COUNTIFS($AU$2:$AU$200,$G26)>0, COUNTIFS($AV$2:$AV$200,$G26)>0, COUNTIFS($AW$2:$AW$200,$G26)>0, COUNTIFS($AX$2:$AX$200,$G26)>0 )), ), 2 ), "")} | E26: {=IFERROR( INDEX( _xlfn._xlws.FILTER($U$1:$AX$1, TRANSPOSE( CHOOSE({1;2;3;4;5;6;7;8;9;10;11;12;13;14;15;16;17;18;19;20;21;22;23;24;25;26;27;28;29;30}, COUNTIFS($U$2:$U$200,$G26)>0, COUNTIFS($V$2:$V$200,$G26)>0, COUNTIFS($W$2:$W$200,$G26)>0, COUNTIFS($X$2:$X$200,$G26)>0, COUNTIFS($Y$2:$Y$200,$G26)>0, COUNTIFS($Z$2:$Z$200,$G26)>0, COUNTIFS($AA$2:$AA$200,$G26)>0, COUNTIFS($AB$2:$AB$200,$G26)>0, COUNTIFS($AC$2:$AC$200,$G26)>0, COUNTIFS($AD$2:$AD$200,$G26)>0, COUNTIFS($AE$2:$AE$200,$G26)>0, COUNTIFS($AF$2:$AF$200,$G26)>0, COUNTIFS($AG$2:$AG$200,$G26)>0, COUNTIFS($AH$2:$AH$200,$G26)>0, COUNTIFS($AI$2:$AI$200,$G26)>0, COUNTIFS($AJ$2:$AJ$200,$G26)>0, COUNTIFS($AK$2:$AK$200,$G26)>0, COUNTIFS($AL$2:$AL$200,$G26)>0, COUNTIFS($AM$2:$AM$200,$G26)>0, COUNTIFS($AN$2:$AN$200,$G26)>0, COUNTIFS($AO$2:$AO$200,$G26)>0, COUNTIFS($AP$2:$AP$200,$G26)>0, COUNTIFS($AQ$2:$AQ$200,$G26)>0, COUNTIFS($AR$2:$AR$200,$G26)>0, COUNTIFS($AS$2:$AS$200,$G26)>0, COUNTIFS($AT$2:$AT$200,$G26)>0, COUNTIFS($AU$2:$AU$200,$G26)>0, COUNTIFS($AV$2:$AV$200,$G26)>0, COUNTIFS($AW$2:$AW$200,$G26)>0, COUNTIFS($AX$2:$AX$200,$G26)>0 )), ), 3 ), "")} | F26: {=IFERROR( INDEX( _xlfn._xlws.FILTER($U$1:$AX$1, TRANSPOSE( CHOOSE({1;2;3;4;5;6;7;8;9;10;11;12;13;14;15;16;17;18;19;20;21;22;23;24;25;26;27;28;29;30}, COUNTIFS($U$2:$U$200,$G26)>0, COUNTIFS($V$2:$V$200,$G26)>0, COUNTIFS($W$2:$W$200,$G26)>0, COUNTIFS($X$2:$X$200,$G26)>0, COUNTIFS($Y$2:$Y$200,$G26)>0, COUNTIFS($Z$2:$Z$200,$G26)>0, COUNTIFS($AA$2:$AA$200,$G26)>0, COUNTIFS($AB$2:$AB$200,$G26)>0, COUNTIFS($AC$2:$AC$200,$G26)>0, COUNTIFS($AD$2:$AD$200,$G26)>0, COUNTIFS($AE$2:$AE$200,$G26)>0, COUNTIFS($AF$2:$AF$200,$G26)>0, COUNTIFS($AG$2:$AG$200,$G26)>0, COUNTIFS($AH$2:$AH$200,$G26)>0, COUNTIFS($AI$2:$AI$200,$G26)>0, COUNTIFS($AJ$2:$AJ$200,$G26)>0, COUNTIFS($AK$2:$AK$200,$G26)>0, COUNTIFS($AL$2:$AL$200,$G26)>0, COUNTIFS($AM$2:$AM$200,$G26)>0, COUNTIFS($AN$2:$AN$200,$G26)>0, COUNTIFS($AO$2:$AO$200,$G26)>0, COUNTIFS($AP$2:$AP$200,$G26)>0, COUNTIFS($AQ$2:$AQ$200,$G26)>0, COUNTIFS($AR$2:$AR$200,$G26)>0, COUNTIFS($AS$2:$AS$200,$G26)>0, COUNTIFS($AT$2:$AT$200,$G26)>0, COUNTIFS($AU$2:$AU$200,$G26)>0, COUNTIFS($AV$2:$AV$200,$G26)>0, COUNTIFS($AW$2:$AW$200,$G26)>0, COUNTIFS($AX$2:$AX$200,$G26)>0 )), ), 4 ), "")} | G26: Arcbound Slith | I26: Breya | J26: =Breya!G2 -> 3 | K26: Sim | L26: Sim | M26: Sim | N26: Sim | O26: Não | P26: Combate | Q26: Dano Direto | R26: Thopteros e Blink | S26: =IF(J26<6,"5",IF(J26<11,"4",IF(J26<16,"3",IF(J26<31,"2","1")))) -> 5 | U26: Time Sieve | V26: Seedborn Muse | W26: Spectator Seating | X26: Retribution of the Ancients | AX26: Earthbending Student | BA26: Vexing Puzzlebox | BC26: Watery Grave | BD26: Season of Weaving | BF26: Ripples of Potential | BG26: Lullmage Mentor | BH26: Gavony Township | BI26: Coastline Marauders | BK26: Phyrexian Tower | BL26: Prismatic Strands | BM26: Hierofante de Elenda | BN26: Genji Glove | BO26: Bojuka Bog | BQ26: Entomb | BR26: Dollmaker's Shop // Porcelain Gallery | BT26: Call to the Kindred
A27: =IFERROR(INDEX($S$3:$S$200, MATCH($C27, $I$3:$I$200, 0)), "") -> 1 | B27: =COUNTIF(U:AX,G27) -> 1 | C27: =IFERROR( INDEX($U$1:$AX$1, MATCH(TRUE, CHOOSE({1;2;3;4;5;6;7;8;9;10;11;12;13;14;15;16;17;18;19;20;21;22;23;24;25;26;27;28;29;30;31;32}, COUNTIFS($U$2:$U$200,$G27)>0, COUNTIFS($V$2:$V$200,$G27)>0, COUNTIFS($W$2:$W$200,$G27)>0, COUNTIFS($X$2:$X$200,$G27)>0, COUNTIFS($Y$2:$Y$200,$G27)>0, COUNTIFS($Z$2:$Z$200,$G27)>0, COUNTIFS($AA$2:$AA$200,$G27)>0, COUNTIFS($AB$2:$AB$200,$G27)>0, COUNTIFS($AC$2:$AC$200,$G27)>0, COUNTIFS($AD$2:$AD$200,$G27)>0, COUNTIFS($AE$2:$AE$200,$G27)>0, COUNTIFS($AF$2:$AF$200,$G27)>0, COUNTIFS($AG$2:$AG$200,$G27)>0, COUNTIFS($AH$2:$AH$200,$G27)>0, COUNTIFS($AI$2:$AI$200,$G27)>0, COUNTIFS($AJ$2:$AJ$200,$G27)>0, COUNTIFS($AK$2:$AK$200,$G27)>0, COUNTIFS($AL$2:$AL$200,$G27)>0, COUNTIFS($AM$2:$AM$200,$G27)>0, COUNTIFS($AN$2:$AN$200,$G27)>0, COUNTIFS($AO$2:$AO$200,$G27)>0, COUNTIFS($AP$2:$AP$200,$G27)>0, COUNTIFS($AQ$2:$AQ$200,$G27)>0, COUNTIFS($AR$2:$AR$200,$G27)>0, COUNTIFS($AS$2:$AS$200,$G27)>0, COUNTIFS($AT$2:$AT$200,$G27)>0, COUNTIFS($AU$2:$AU$200,$G27)>0, COUNTIFS($AV$2:$AV$200,$G27)>0, COUNTIFS($AW$2:$AW$200,$G27)>0, COUNTIFS($AX$2:$AX$200,$G27)>0 ), 0) ), "") -> Modular | D27: {=IFERROR( INDEX( _xlfn._xlws.FILTER($U$1:$AX$1, TRANSPOSE( CHOOSE({1;2;3;4;5;6;7;8;9;10;11;12;13;14;15;16;17;18;19;20;21;22;23;24;25;26;27;28;29;30}, COUNTIFS($U$2:$U$200,$G27)>0, COUNTIFS($V$2:$V$200,$G27)>0, COUNTIFS($W$2:$W$200,$G27)>0, COUNTIFS($X$2:$X$200,$G27)>0, COUNTIFS($Y$2:$Y$200,$G27)>0, COUNTIFS($Z$2:$Z$200,$G27)>0, COUNTIFS($AA$2:$AA$200,$G27)>0, COUNTIFS($AB$2:$AB$200,$G27)>0, COUNTIFS($AC$2:$AC$200,$G27)>0, COUNTIFS($AD$2:$AD$200,$G27)>0, COUNTIFS($AE$2:$AE$200,$G27)>0, COUNTIFS($AF$2:$AF$200,$G27)>0, COUNTIFS($AG$2:$AG$200,$G27)>0, COUNTIFS($AH$2:$AH$200,$G27)>0, COUNTIFS($AI$2:$AI$200,$G27)>0, COUNTIFS($AJ$2:$AJ$200,$G27)>0, COUNTIFS($AK$2:$AK$200,$G27)>0, COUNTIFS($AL$2:$AL$200,$G27)>0, COUNTIFS($AM$2:$AM$200,$G27)>0, COUNTIFS($AN$2:$AN$200,$G27)>0, COUNTIFS($AO$2:$AO$200,$G27)>0, COUNTIFS($AP$2:$AP$200,$G27)>0, COUNTIFS($AQ$2:$AQ$200,$G27)>0, COUNTIFS($AR$2:$AR$200,$G27)>0, COUNTIFS($AS$2:$AS$200,$G27)>0, COUNTIFS($AT$2:$AT$200,$G27)>0, COUNTIFS($AU$2:$AU$200,$G27)>0, COUNTIFS($AV$2:$AV$200,$G27)>0, COUNTIFS($AW$2:$AW$200,$G27)>0, COUNTIFS($AX$2:$AX$200,$G27)>0 )), ), 2 ), "")} | E27: {=IFERROR( INDEX( _xlfn._xlws.FILTER($U$1:$AX$1, TRANSPOSE( CHOOSE({1;2;3;4;5;6;7;8;9;10;11;12;13;14;15;16;17;18;19;20;21;22;23;24;25;26;27;28;29;30}, COUNTIFS($U$2:$U$200,$G27)>0, COUNTIFS($V$2:$V$200,$G27)>0, COUNTIFS($W$2:$W$200,$G27)>0, COUNTIFS($X$2:$X$200,$G27)>0, COUNTIFS($Y$2:$Y$200,$G27)>0, COUNTIFS($Z$2:$Z$200,$G27)>0, COUNTIFS($AA$2:$AA$200,$G27)>0, COUNTIFS($AB$2:$AB$200,$G27)>0, COUNTIFS($AC$2:$AC$200,$G27)>0, COUNTIFS($AD$2:$AD$200,$G27)>0, COUNTIFS($AE$2:$AE$200,$G27)>0, COUNTIFS($AF$2:$AF$200,$G27)>0, COUNTIFS($AG$2:$AG$200,$G27)>0, COUNTIFS($AH$2:$AH$200,$G27)>0, COUNTIFS($AI$2:$AI$200,$G27)>0, COUNTIFS($AJ$2:$AJ$200,$G27)>0, COUNTIFS($AK$2:$AK$200,$G27)>0, COUNTIFS($AL$2:$AL$200,$G27)>0, COUNTIFS($AM$2:$AM$200,$G27)>0, COUNTIFS($AN$2:$AN$200,$G27)>0, COUNTIFS($AO$2:$AO$200,$G27)>0, COUNTIFS($AP$2:$AP$200,$G27)>0, COUNTIFS($AQ$2:$AQ$200,$G27)>0, COUNTIFS($AR$2:$AR$200,$G27)>0, COUNTIFS($AS$2:$AS$200,$G27)>0, COUNTIFS($AT$2:$AT$200,$G27)>0, COUNTIFS($AU$2:$AU$200,$G27)>0, COUNTIFS($AV$2:$AV$200,$G27)>0, COUNTIFS($AW$2:$AW$200,$G27)>0, COUNTIFS($AX$2:$AX$200,$G27)>0 )), ), 3 ), "")} | F27: {=IFERROR( INDEX( _xlfn._xlws.FILTER($U$1:$AX$1, TRANSPOSE( CHOOSE({1;2;3;4;5;6;7;8;9;10;11;12;13;14;15;16;17;18;19;20;21;22;23;24;25;26;27;28;29;30}, COUNTIFS($U$2:$U$200,$G27)>0, COUNTIFS($V$2:$V$200,$G27)>0, COUNTIFS($W$2:$W$200,$G27)>0, COUNTIFS($X$2:$X$200,$G27)>0, COUNTIFS($Y$2:$Y$200,$G27)>0, COUNTIFS($Z$2:$Z$200,$G27)>0, COUNTIFS($AA$2:$AA$200,$G27)>0, COUNTIFS($AB$2:$AB$200,$G27)>0, COUNTIFS($AC$2:$AC$200,$G27)>0, COUNTIFS($AD$2:$AD$200,$G27)>0, COUNTIFS($AE$2:$AE$200,$G27)>0, COUNTIFS($AF$2:$AF$200,$G27)>0, COUNTIFS($AG$2:$AG$200,$G27)>0, COUNTIFS($AH$2:$AH$200,$G27)>0, COUNTIFS($AI$2:$AI$200,$G27)>0, COUNTIFS($AJ$2:$AJ$200,$G27)>0, COUNTIFS($AK$2:$AK$200,$G27)>0, COUNTIFS($AL$2:$AL$200,$G27)>0, COUNTIFS($AM$2:$AM$200,$G27)>0, COUNTIFS($AN$2:$AN$200,$G27)>0, COUNTIFS($AO$2:$AO$200,$G27)>0, COUNTIFS($AP$2:$AP$200,$G27)>0, COUNTIFS($AQ$2:$AQ$200,$G27)>0, COUNTIFS($AR$2:$AR$200,$G27)>0, COUNTIFS($AS$2:$AS$200,$G27)>0, COUNTIFS($AT$2:$AT$200,$G27)>0, COUNTIFS($AU$2:$AU$200,$G27)>0, COUNTIFS($AV$2:$AV$200,$G27)>0, COUNTIFS($AW$2:$AW$200,$G27)>0, COUNTIFS($AX$2:$AX$200,$G27)>0 )), ), 4 ), "")} | G27: Arcbound Stinger | I27: OWA | J27: =OWA!G2 -> 6 | K27: Sim | L27: Não | M27: Não | N27: Sim | O27: Sim | P27: Combate | Q27: Dano Direto | R27: Tokens e Reanimate | S27: =IF(J27<6,"5",IF(J27<11,"4",IF(J27<16,"3",IF(J27<31,"2","1")))) -> 4 | U27: Timestream Navigator | V27: Sunscorched Divide | W27: The Water Crystal | X27: Reyhan, Last of the Abzan | AX27: Elvish Reclaimer | BC27: Watery Grave | BD27: Sonic Screwdriver | BF27: Rogue's Passage | BG27: Maddening Cacophony | BH27: Gavony Township | BI27: Darksteel Citadel | BK27: Planetary Annihilation | BL27: Renewed Solidarity | BM27: High-Society Hunter | BN27: Ghostly Prison | BO27: Boros Charm | BQ27: Evendo, Waking Haven | BR27: Dour Port-Mage | BT27: Careful Study
