Workbook

Sheet COMPRAS
A1: Total: | B1: =C2+C8+C13+C18+C23+C28+C32+C34+C38+C50 -> 0 | E1: Deck | F1: =A2 -> Marcelo | G1: =B3 -> Mega | H1: =B4 -> Overrun | I1: =B5 -> Mundo TCG | J1: =B6 -> Liga | L1: =A8 -> Interessantes | M1: =B9 -> Valor | N1: =B10 -> Liga | O1: =B11 -> Loja 1 | Q1: =A13 -> Player 3 | R1: =B14 -> Rayearth | S1: =B15 -> Mineral | T1: =B16 -> CardTutor | V1: =A18 -> Player 4 | W1: =B19 -> Rayearth | X1: =B20 -> Mineral | Y1: =B21 -> CardTutor | AA1: =A23 -> Player 5 | AB1: =B24 -> Rayearth | AC1: =B25 -> Mineral | AD1: =B26 -> CardTutor | AF1: =A28 -> Player 6 | AG1: =B29 -> Rayearth | AH1: =B30 -> Mineral | AI1: =B31 -> CardTutor
A2: Marcelo | B2: Total Lojas: | C2: =SUM(C3:C6) -> 0 | E2: Rani | F2: Shield Roxo
A3: =COUNTA(F2:F217) -> 2 | B3: Mega | C3: =SUM(G:G) -> 0 | E3: Bichão | F3: Shield Vermelho Crimson?
B4: Overrun | C4: =SUM(H:H) -> 0
B5: Mundo TCG | C5: =SUM(I:I) -> 0
B6: Liga | C6: =SUM(J:J) -> 0
A8: Interessantes | B8: Total Lojas: | C8: =SUM(C9:C11) -> 0
A9: =COUNTA(L2:L173) -> 0 | B9: Valor | C9: =SUM(M:M) -> 0
B10: Liga | C10: =SUM(N:N) -> 0
B11: Loja 1 | C11: =SUM(O:O) -> 0
A13: Player 3 | B13: Total Lojas: | C13: =SUM(C14:C16) -> 0
A14: =COUNTA(Q2:Q173) -> 0 | B14: Rayearth | C14: =SUM(R:R) -> 0
B15: Mineral | C15: =SUM(S:S) -> 0
B16: CardTutor | C16: =SUM(T:T) -> 0
A18: Player 4 | B18: Total Lojas: | C18: =SUM(C19:C21) -> 0
A19: =COUNTA(V2:V173) -> 0 | B19: Rayearth | C19: =SUM(W1:W9973) -> 0
B20: Mineral | C20: =SUM(X1:X9978) -> 0
B21: CardTutor | C21: =SUM(Y:Y) -> 0
A23: Player 5 | B23: Total Lojas: | C23: =SUM(C24:C26) -> 0
A24: =COUNTA(V7:V178) -> 0 | B24: Rayearth | C24: =SUM(AB:AB) -> 0
B25: Mineral | C25: =SUM(AC:AC) -> 0
B26: CardTutor | C26: =SUM(AD:AD) -> 0
A28: Player 6 | B28: Total Lojas: | C28: =SUM(C29:C31) -> 0
A29: =COUNTA(V11:V183) -> 0 | B29: Rayearth | C29: =SUM(AG:AG) -> 0
B30: Mineral | C30: =SUM(AH:AH) -> 0
B31: CardTutor | C31: =SUM(AI:AI) -> 0

Sheet STATS
A1: Dia | B1: Player 1 | C1: Deck 1 | D1: Player 2 | E1: Deck 2 | F1: Player 3 | G1: Deck 3 | H1: Player 4 | I1: Deck 4 | J1: Vitória | M1: Deck | N1: Partidas | O1: Winrate | Q1: Player | R1: Partidas | S1: Winrate
A2: 45587 | B2: Marcelo | C2: Elfos | D2: Vivian | E2: Zimone | F2: Renato | G2: Raffine | H2: Dexter | I2: Kaalia | J2: Marcelo | K2: Elfos | M2: Akiri | N2: =COUNTIF(C:C,M2)+COUNTIF(E:E,M2)+COUNTIF(G:G,M2)+COUNTIF(I:I,M2) -> 2 | O2: =IF(N2>=10,(COUNTIF(K:K,M2)/N2),"Insuficiente") -> Insuficiente | Q2: Marcelo | R2: =COUNTIF(B:B,Q2)+COUNTIF(D:D,Q2)+COUNTIF(F:F,Q2)+COUNTIF(H:H,Q2) -> 11 | S2: =IF(R2>=10, (COUNTIF(J:J,Q2)/R2), "Insuficiente") -> 0.36363636
A3: 45594 | B3: Marcelo | C3: Breya | D3: Vivian | E3: Zimone | F3: Renato | G3: Raffine | H3: Dexter | I3: Tovolar | J3: Vivian | K3: Zimone | M3: Arcades | N3: =COUNTIF(C:C,M3)+COUNTIF(E:E,M3)+COUNTIF(G:G,M3)+COUNTIF(I:I,M3) -> 1 | O3: =IF(N3>=10,(COUNTIF(K:K,M3)/N3),"Insuficiente") -> Insuficiente | Q3: Vivian | R3: =COUNTIF(B:B,Q3)+COUNTIF(D:D,Q3)+COUNTIF(F:F,Q3)+COUNTIF(H:H,Q3) -> 11 | S3: =IF(R3>=10, (COUNTIF(J:J,Q3)/R3), "Insuficiente") -> 0.27272727
A4: 45594 | B4: Marcelo | C4: Trakiri | D4: Vivian | E4: Zimone | F4: Renato | G4: Raffine | H4: Hamster | I4: Muzzio | J4: Marcelo | K4: Trakiri | M4: Baylen | N4: =COUNTIF(C:C,M4)+COUNTIF(E:E,M4)+COUNTIF(G:G,M4)+COUNTIF(I:I,M4) -> 1 | O4: =IF(N4>=10,(COUNTIF(K:K,M4)/N4),"Insuficiente") -> Insuficiente | Q4: Renato | R4: =COUNTIF(B:B,Q4)+COUNTIF(D:D,Q4)+COUNTIF(F:F,Q4)+COUNTIF(H:H,Q4) -> 6 | S4: =IF(R4>=10, (COUNTIF(J:J,Q4)/R4), "Insuficiente") -> Insuficiente
A5: 45594 | B5: Marcelo | C5: Akiri | D5: Vivian | E5: Zimone | F5: Renato | G5: Baylen | H5: Hamster | I5: Kumena | J5: Marcelo | K5: Akiri | M5: Breya | N5: =COUNTIF(C:C,M5)+COUNTIF(E:E,M5)+COUNTIF(G:G,M5)+COUNTIF(I:I,M5) -> 1 | O5: =IF(N5>=10,(COUNTIF(K:K,M5)/N5),"Insuficiente") -> Insuficiente | Q5: Dexter | R5: =COUNTIF(B:B,Q5)+COUNTIF(D:D,Q5)+COUNTIF(F:F,Q5)+COUNTIF(H:H,Q5) -> 5 | S5: =IF(R5>=10, (COUNTIF(J:J,Q5)/R5), "Insuficiente") -> Insuficiente
A6: 45597 | B6: Marcelo | C6: Inalla | D6: Vivian | E6: Zimone | F6: Renato | G6: Raffine | H6: João | I6: Winota | J6: João | K6: Winota | M6: Elfos | N6: =COUNTIF(C:C,M6)+COUNTIF(E:E,M6)+COUNTIF(G:G,M6)+COUNTIF(I:I,M6) -> 1 | O6: =IF(N6>=10,(COUNTIF(K:K,M6)/N6),"Insuficiente") -> Insuficiente | Q6: Hamster | R6: =COUNTIF(B:B,Q6)+COUNTIF(D:D,Q6)+COUNTIF(F:F,Q6)+COUNTIF(H:H,Q6) -> 2 | S6: =IF(R6>=10, (COUNTIF(J:J,Q6)/R6), "Insuficiente") -> Insuficiente
A7: 45597 | B7: Marcelo | C7: Yuriko | D7: Vivian | E7: Zimone | F7: Renato | G7: Raffine | H7: João | I7: Winota | J7: Vivian | K7: Zimone | M7: FF Counters | N7: =COUNTIF(C:C,M7)+COUNTIF(E:E,M7)+COUNTIF(G:G,M7)+COUNTIF(I:I,M7) -> 2 | O7: =IF(N7>=10,(COUNTIF(K:K,M7)/N7),"Insuficiente") -> Insuficiente | Q7: Talita | R7: =COUNTIF(B:B,Q7)+COUNTIF(D:D,Q7)+COUNTIF(F:F,Q7)+COUNTIF(H:H,Q7) -> 3 | S7: =IF(R7>=10, (COUNTIF(J:J,Q7)/R7), "Insuficiente") -> Insuficiente
A8: 45599 | B8: Marcelo | C8: Narset | D8: Vivian | E8: Arcades | F8: Dexter | G8: Who Villains | H8: Talita | I8: Who Time | J8: Vivian | K8: Arcades | M8: Hashaton | N8: =COUNTIF(C:C,M8)+COUNTIF(E:E,M8)+COUNTIF(G:G,M8)+COUNTIF(I:I,M8) -> 1 | O8: =IF(N8>=10,(COUNTIF(K:K,M8)/N8),"Insuficiente") -> Insuficiente | Q8: João | R8: =COUNTIF(B:B,Q8)+COUNTIF(D:D,Q8)+COUNTIF(F:F,Q8)+COUNTIF(H:H,Q8) -> 4 | S8: =IF(R8>=10, (COUNTIF(J:J,Q8)/R8), "Insuficiente") -> Insuficiente
A9: 45599 | B9: Marcelo | C9: Thantis | D9: Vivian | E9: Akiri | F9: Dexter | G9: Who Villains | H9: Talita | I9: Ladinos | J9: Talita | K9: Ladinos | M9: Inalla | N9: =COUNTIF(C:C,M9)+COUNTIF(E:E,M9)+COUNTIF(G:G,M9)+COUNTIF(I:I,M9) -> 1 | O9: =IF(N9>=10,(COUNTIF(K:K,M9)/N9),"Insuficiente") -> Insuficiente | Q9: Philips | R9: =COUNTIF(B:B,Q9)+COUNTIF(D:D,Q9)+COUNTIF(F:F,Q9)+COUNTIF(H:H,Q9) -> 2 | S9: =IF(R9>=10, (COUNTIF(J:J,Q9)/R9), "Insuficiente") -> Insuficiente
A10: 45835 | B10: Marcelo | C10: Zedruu | D10: Vivian | E10: Jhoira | F10: Dexter | G10: Who Villains | H10: Talita | I10: Who Time | J10: Dexter | K10: Who Villains | M10: Jhoira | N10: =COUNTIF(C:C,M10)+COUNTIF(E:E,M10)+COUNTIF(G:G,M10)+COUNTIF(I:I,M10) -> 1 | O10: =IF(N10>=10,(COUNTIF(K:K,M10)/N10),"Insuficiente") -> Insuficiente
A11: 45864 | B11: Marcelo | C11: Muzzio | D11: Vivian | E11: Zimone | F11: Philips | G11: Hashaton | H11: João | I11: FF Counters | J11: Marcelo | K11: Muzzio | M11: Kaalia | N11: =COUNTIF(C:C,M11)+COUNTIF(E:E,M11)+COUNTIF(G:G,M11)+COUNTIF(I:I,M11) -> 2 | O11: =IF(N11>=10,(COUNTIF(K:K,M11)/N11),"Insuficiente") -> Insuficiente
A12: 45864 | B12: Marcelo | C12: Sisay | D12: Vivian | E12: Zimone | F12: Philips | G12: Kaalia | H12: João | I12: FF Counters | J12: Philips | K12: Kaalia | M12: Kumena | N12: =COUNTIF(C:C,M12)+COUNTIF(E:E,M12)+COUNTIF(G:G,M12)+COUNTIF(I:I,M12) -> 1 | O12: =IF(N12>=10,(COUNTIF(K:K,M12)/N12),"Insuficiente") -> Insuficiente
M13: Ladinos | N13: =COUNTIF(C:C,M13)+COUNTIF(E:E,M13)+COUNTIF(G:G,M13)+COUNTIF(I:I,M13) -> 1 | O13: =IF(N13>=10,(COUNTIF(K:K,M13)/N13),"Insuficiente") -> Insuficiente
M14: Muzzio | N14: =COUNTIF(C:C,M14)+COUNTIF(E:E,M14)+COUNTIF(G:G,M14)+COUNTIF(I:I,M14) -> 2 | O14: =IF(N14>=10,(COUNTIF(K:K,M14)/N14),"Insuficiente") -> Insuficiente
M15: Narset | N15: =COUNTIF(C:C,M15)+COUNTIF(E:E,M15)+COUNTIF(G:G,M15)+COUNTIF(I:I,M15) -> 1 | O15: =IF(N15>=10,(COUNTIF(K:K,M15)/N15),"Insuficiente") -> Insuficiente
M16: Raffine | N16: =COUNTIF(C:C,M16)+COUNTIF(E:E,M16)+COUNTIF(G:G,M16)+COUNTIF(I:I,M16) -> 5 | O16: =IF(N16>=10,(COUNTIF(K:K,M16)/N16),"Insuficiente") -> Insuficiente
M17: Sisay | N17: =COUNTIF(C:C,M17)+COUNTIF(E:E,M17)+COUNTIF(G:G,M17)+COUNTIF(I:I,M17) -> 1 | O17: =IF(N17>=10,(COUNTIF(K:K,M17)/N17),"Insuficiente") -> Insuficiente
M18: Thantis | N18: =COUNTIF(C:C,M18)+COUNTIF(E:E,M18)+COUNTIF(G:G,M18)+COUNTIF(I:I,M18) -> 1 | O18: =IF(N18>=10,(COUNTIF(K:K,M18)/N18),"Insuficiente") -> Insuficiente
M19: Tovolar | N19: =COUNTIF(C:C,M19)+COUNTIF(E:E,M19)+COUNTIF(G:G,M19)+COUNTIF(I:I,M19) -> 1 | O19: =IF(N19>=10,(COUNTIF(K:K,M19)/N19),"Insuficiente") -> Insuficiente
M20: Trakiri | N20: =COUNTIF(C:C,M20)+COUNTIF(E:E,M20)+COUNTIF(G:G,M20)+COUNTIF(I:I,M20) -> 1 | O20: =IF(N20>=10,(COUNTIF(K:K,M20)/N20),"Insuficiente") -> Insuficiente
M21: Who Time | N21: =COUNTIF(C:C,M21)+COUNTIF(E:E,M21)+COUNTIF(G:G,M21)+COUNTIF(I:I,M21) -> 2 | O21: =IF(N21>=10,(COUNTIF(K:K,M21)/N21),"Insuficiente") -> Insuficiente
M22: Who Villains | N22: =COUNTIF(C:C,M22)+COUNTIF(E:E,M22)+COUNTIF(G:G,M22)+COUNTIF(I:I,M22) -> 3 | O22: =IF(N22>=10,(COUNTIF(K:K,M22)/N22),"Insuficiente") -> Insuficiente
M23: Winota | N23: =COUNTIF(C:C,M23)+COUNTIF(E:E,M23)+COUNTIF(G:G,M23)+COUNTIF(I:I,M23) -> 2 | O23: =IF(N23>=10,(COUNTIF(K:K,M23)/N23),"Insuficiente") -> Insuficiente
M24: Yuriko | N24: =COUNTIF(C:C,M24)+COUNTIF(E:E,M24)+COUNTIF(G:G,M24)+COUNTIF(I:I,M24) -> 1 | O24: =IF(N24>=10,(COUNTIF(K:K,M24)/N24),"Insuficiente") -> Insuficiente
... M26: Zimone | N26: =COUNTIF(C:C,M26)+COUNTIF(E:E,M26)+COUNTIF(G:G,M26)+COUNTIF(I:I,M26) -> 8 | O26: =IF(N26>=10,(COUNTIF(K:K,M26)/N26),"Insuficiente") -> Insuficiente

Sheet RESUMO
A1: Thrakiri | E1: Gitrog | I1: Elfos | M1: Jhoira | Q1: Fractius | U1: Muzzio
A3: Total | B3: {=_xlfn._xlws.SORT(C3:C101,1,-1,0)} -> Uthros, Titanic Godcore | C3: =IF(Thrakiri!D3="Não",Thrakiri!C3, " ") | E3: Total | F3: {=_xlfn._xlws.SORT(G3:G101,1,-1,0)} -> Ulamog, the Infinite Gyre | G3: =IF(Gitrog!D3="Não",Gitrog!C3, " ") | I3: Total | J3: {=_xlfn._xlws.SORT(K3:K101,1,-1,0)} -> Zagoth Triome | K3: =IF(Elfos!D3="Não",Elfos!C3, " ") | M3: Total | N3: {=_xlfn._xlws.SORT(O3:O101,1,-1,0)} -> Valfenda | O3: =IF(Jhoira!D3="Não",Jhoira!C4, " ") | Q3: Total | R3: {=_xlfn._xlws.SORT(S3:S101,1,-1,0)} -> Trioma de Zagoth | S3: =IF(Fractius!D3="Não",Fractius!C3, " ") | U3: Total | V3: {=_xlfn._xlws.SORT(W3:W101,1,-1,0)} -> The Mycosynth Gardens | W3: =IF(Muzzio!D3="Não",Muzzio!C3, " ")
A4: =Thrakiri!G3 -> 6 | B4: The Mycosynth Gardens | C4: =IF(Thrakiri!D3="Não",Thrakiri!C4, " ") | E4: =Gitrog!G3 -> 12 | F4: Titania, Voice of Gaea | G4: =IF(Gitrog!D3="Não",Gitrog!C4, " ") | I4: =Elfos!G3 -> 6 | J4: Three Tree City | K4: =IF(Elfos!D3="Não",Elfos!C4, " ") | M4: =Jhoira!G4 -> 6 | N4: Ulamog, o Profanador | O4: =IF(Jhoira!D5="Não",Jhoira!C5, " ") | Q4: =Fractius!G3 -> 9 | R4: Trioma de Raugrin | S4: =IF(Fractius!D3="Não",Fractius!C4, " ") | U4: =Muzzio!G3 -> 14 | V4: Sonic Screwdriver | W4: =IF(Muzzio!D3="Não",Muzzio!C4, " ")
B5: The Eternity Elevator | C5: =IF(Thrakiri!D5="Não",Thrakiri!C5, " ") | F5: Takenuma, Charco Abandonado | G5: =IF(Gitrog!D5="Não",Gitrog!C5, " ") | J5: Nissa, Resurgent Animist | K5: =IF(Elfos!D5="Não",Elfos!C5, " ") | N5: Planetary Annihilation | O5: =IF(Jhoira!D6="Não",Jhoira!C6, " ") | R5: Thrumming Hivepool | S5: =IF(Fractius!D5="Não",Fractius!C5, " ") -> Trioma de Zagoth | V5: Rings of Brighthearth | W5: =IF(Muzzio!D5="Não",Muzzio!C5, " ")
B6: Shaku da Honra Desgastada | C6: =IF(Thrakiri!D6="Não",Thrakiri!C6, " ") | F6: Phyrexian Tower | G6: =IF(Gitrog!D6="Não",Gitrog!C6, " ") | J6: Evendo, Waking Haven | K6: =IF(Elfos!D6="Não",Elfos!C6, " ") -> Alchemist's Refuge | N6: Mistrise Village | O6: =IF(Jhoira!D7="Não",Jhoira!C7, " ") | R6: Sliver Gravemother | S6: =IF(Fractius!D6="Não",Fractius!C6, " ") -> Trioma de Raugrin | V6: Portal to Phyrexia | W6: =IF(Muzzio!D6="Não",Muzzio!C6, " ")
B7: Obelisco de Obsidiana | C7: =IF(Thrakiri!D7="Não",Thrakiri!C7, " ") | F7: Petrified Field | G7: =IF(Gitrog!D7="Não",Gitrog!C7, " ") | J7: Dionus, Elvish Archdruid | K7: =IF(Elfos!D7="Não",Elfos!C7, " ") | N7: Emrakul, um Novo Mundo | O7: =IF(Jhoira!D8="Não",Jhoira!C8, " ") | R7: Rakdos Signet | S7: =IF(Fractius!D7="Não",Fractius!C7, " ") | V7: Pingente de Ampulheta de Gerrard | W7: =IF(Muzzio!D7="Não",Muzzio!C7, " ")
B8: Matoya, Archon Elder | C8: =IF(Thrakiri!D8="Não",Thrakiri!C8, " ") | F8: Ondulações de Morte-Vida | G8: =IF(Gitrog!D8="Não",Gitrog!C8, " ") | J8: Alchemist's Refuge | K8: =IF(Elfos!D8="Não",Elfos!C8, " ") | N8: Cyber Conversion | O8: =IF(Jhoira!D9="Não",Jhoira!C9, " ") -> Valfenda | R8: Raffine's Tower | S8: =IF(Fractius!D8="Não",Fractius!C8, " ") -> Raffine's Tower | V8: Mirrex | W8: =IF(Muzzio!D8="Não",Muzzio!C8, " ")
C9: =IF(Thrakiri!D9="Não",Thrakiri!C9, " ") | F9: Hedge Shredder | G9: =IF(Gitrog!D9="Não",Gitrog!C9, " ") | K9: =IF(Elfos!D9="Não",Elfos!C9, " ") | O9: =IF(Jhoira!D10="Não",Jhoira!C10, " ") -> Mistrise Village | R9: Jetmir's Garden | S9: =IF(Fractius!D9="Não",Fractius!C9, " ") | V9: Gogo, Master of Mimicry | W9: =IF(Muzzio!D9="Não",Muzzio!C9, " ")
C10: =IF(Thrakiri!D10="Não",Thrakiri!C10, " ") | F10: Entomb | G10: =IF(Gitrog!D10="Não",Gitrog!C10, " ") | K10: =IF(Elfos!D10="Não",Elfos!C10, " ") | O10: =IF(Jhoira!D11="Não",Jhoira!C11, " ") | R10: Caverna das Almas | S10: =IF(Fractius!D10="Não",Fractius!C10, " ") | V10: Extinguisher Battleship | W10: =IF(Muzzio!D10="Não",Muzzio!C10, " ")
C11: =IF(Thrakiri!D11="Não",Thrakiri!C11, " ") | F11: Delighted Halfling | G11: =IF(Gitrog!D11="Não",Gitrog!C11, " ") | K11: =IF(Elfos!D11="Não",Elfos!C11, " ") | O11: =IF(Jhoira!D12="Não",Jhoira!C12, " ") | S11: =IF(Fractius!D11="Não",Fractius!C11, " ") -> Jetmir's Garden | V11: Dauntless Scrapbot | W11: =IF(Muzzio!D11="Não",Muzzio!C11, " ")
C12: =IF(Thrakiri!D12="Não",Thrakiri!C12, " ") | F12: Crisol dos Mundos | G12: =IF(Gitrog!D12="Não",Gitrog!C12, " ") | K12: =IF(Elfos!D12="Não",Elfos!C12, " ") | O12: =IF(Jhoira!D13="Não",Jhoira!C13, " ") | S12: =IF(Fractius!D12="Não",Fractius!C12, " ") | V12: Chimil, o Sol Interior | W12: =IF(Muzzio!D12="Não",Muzzio!C12, " ")
C13: =IF(Thrakiri!D13="Não",Thrakiri!C13, " ") | F13: Broodheart Engine | G13: =IF(Gitrog!D13="Não",Gitrog!C13, " ") -> Phyrexian Tower | K13: =IF(Elfos!D13="Não",Elfos!C13, " ") -> Zagoth Triome | O13: =IF(Jhoira!D14="Não",Jhoira!C14, " ") | S13: =IF(Fractius!D13="Não",Fractius!C13, " ") -> Caverna das Almas | V13: Caixa Enigmática Desconcertante | W13: =IF(Muzzio!D13="Não",Muzzio!C13, " ") -> Academy Ruins
C14: =IF(Thrakiri!D14="Não",Thrakiri!C14, " ") | F14: Ancient Tomb | G14: =IF(Gitrog!D14="Não",Gitrog!C14, " ") | K14: =IF(Elfos!D14="Não",Elfos!C14, " ") | O14: =IF(Jhoira!D15="Não",Jhoira!C15, " ") | S14: =IF(Fractius!D14="Não",Fractius!C14, " ") | V14: Academy Ruins | W14: =IF(Muzzio!D14="Não",Muzzio!C14, " ")
C15: =IF(Thrakiri!D15="Não",Thrakiri!C15, " ") | G15: =IF(Gitrog!D15="Não",Gitrog!C15, " ") | K15: =IF(Elfos!D15="Não",Elfos!C15, " ") | O15: =IF(Jhoira!D16="Não",Jhoira!C16, " ") | S15: =IF(Fractius!D15="Não",Fractius!C15, " ") | V15: A Joia do Enigma | W15: =IF(Muzzio!D15="Não",Muzzio!C15, " ") -> Mirrex
C16: =IF(Thrakiri!D16="Não",Thrakiri!C16, " ") | G16: =IF(Gitrog!D16="Não",Gitrog!C16, " ") | K16: =IF(Elfos!D16="Não",Elfos!C16, " ") | O16: =IF(Jhoira!D17="Não",Jhoira!C17, " ") | S16: =IF(Fractius!D16="Não",Fractius!C16, " ") | W16: =IF(Muzzio!D16="Não",Muzzio!C16, " ") -> The Mycosynth Gardens
C17: =IF(Thrakiri!D20="Não",Thrakiri!C20, " ") | G17: =IF(Gitrog!D17="Não",Gitrog!C17, " ") -> Petrified Field | K17: =IF(Elfos!D17="Não",Elfos!C17, " ") | O17: =IF(Jhoira!D18="Não",Jhoira!C18, " ") | S17: =IF(Fractius!D17="Não",Fractius!C17, " ") | W17: =IF(Muzzio!D17="Não",Muzzio!C17, " ")
C18: =IF(Thrakiri!D21="Não",Thrakiri!C21, " ") | G18: =IF(Gitrog!D18="Não",Gitrog!C18, " ") -> Ancient Tomb | K18: =IF(Elfos!D18="Não",Elfos!C18, " ") | O18: =IF(Jhoira!D19="Não",Jhoira!C19, " ") | S18: =IF(Fractius!D18="Não",Fractius!C18, " ") | W18: =IF(Muzzio!D18="Não",Muzzio!C18, " ")
C19: =IF(Thrakiri!D22="Não",Thrakiri!C22, " ") | G19: =IF(Gitrog!D19="Não",Gitrog!C19, " ") | K19: =IF(Elfos!D19="Não",Elfos!C19, " ") | O19: =IF(Jhoira!D20="Não",Jhoira!C20, " ") | S19: =IF(Fractius!D19="Não",Fractius!C19, " ") | W19: =IF(Muzzio!D19="Não",Muzzio!C19, " ")
C20: =IF(Thrakiri!D23="Não",Thrakiri!C23, " ") | G20: =IF(Gitrog!D20="Não",Gitrog!C20, " ") | K20: =IF(Elfos!D20="Não",Elfos!C20, " ") -> Three Tree City | O20: =IF(Jhoira!D21="Não",Jhoira!C21, " ") | S20: =IF(Fractius!D20="Não",Fractius!C20, " ") | W20: =IF(Muzzio!D20="Não",Muzzio!C20, " ")
C21: =IF(Thrakiri!D24="Não",Thrakiri!C24, " ") | G21: =IF(Gitrog!D21="Não",Gitrog!C21, " ") | K21: =IF(Elfos!D21="Não",Elfos!C21, " ") -> Evendo, Waking Haven | O21: =IF(Jhoira!D22="Não",Jhoira!C22, " ") | S21: =IF(Fractius!D21="Não",Fractius!C21, " ") | W21: =IF(Muzzio!D21="Não",Muzzio!C21, " ")
C22: =IF(Thrakiri!D25="Não",Thrakiri!C25, " ") | G22: =IF(Gitrog!D22="Não",Gitrog!C22, " ") | K22: =IF(Elfos!D22="Não",Elfos!C22, " ") | O22: =IF(Jhoira!D23="Não",Jhoira!C23, " ") | S22: =IF(Fractius!D22="Não",Fractius!C22, " ") | W22: =IF(Muzzio!D22="Não",Muzzio!C22, " ")
C23: =IF(Thrakiri!D26="Não",Thrakiri!C26, " ") | G23: =IF(Gitrog!D23="Não",Gitrog!C23, " ") | K23: =IF(Elfos!D23="Não",Elfos!C23, " ") | O23: =IF(Jhoira!D24="Não",Jhoira!C24, " ") | S23: =IF(Fractius!D23="Não",Fractius!C23, " ") | W23: =IF(Muzzio!D23="Não",Muzzio!C23, " ")
C24: =IF(Thrakiri!D27="Não",Thrakiri!C27, " ") | G24: =IF(Gitrog!D83="Não",Gitrog!C83, " ") | K24: =IF(Elfos!D24="Não",Elfos!C24, " ") | O24: =IF(Jhoira!D25="Não",Jhoira!C25, " ") | S24: =IF(Fractius!D24="Não",Fractius!C24, " ") | W24: =IF(Muzzio!D24="Não",Muzzio!C24, " ")
C25: =IF(Thrakiri!D28="Não",Thrakiri!C28, " ") | G25: =IF(Gitrog!D24="Não",Gitrog!C24, " ") -> Takenuma, Charco Abandonado | K25: =IF(Elfos!D25="Não",Elfos!C25, " ") | O25: =IF(Jhoira!D26="Não",Jhoira!C26, " ") | S25: =IF(Fractius!D25="Não",Fractius!C25, " ") | W25: =IF(Muzzio!D25="Não",Muzzio!C25, " ")
C26: =IF(Thrakiri!D29="Não",Thrakiri!C29, " ") | G26: =IF(Gitrog!D25="Não",Gitrog!C25, " ") | K26: =IF(Elfos!D26="Não",Elfos!C26, " ") | O26: =IF(Jhoira!D27="Não",Jhoira!C27, " ") | S26: =IF(Fractius!D26="Não",Fractius!C26, " ") | W26: =IF(Muzzio!D26="Não",Muzzio!C26, " ")
C27: =IF(Thrakiri!D30="Não",Thrakiri!C30, " ") | G27: =IF(Gitrog!D26="Não",Gitrog!C26, " ") | K27: =IF(Elfos!D27="Não",Elfos!C27, " ") | O27: =IF(Jhoira!D28="Não",Jhoira!C28, " ") | S27: =IF(Fractius!D27="Não",Fractius!C27, " ") | W27: =IF(Muzzio!D27="Não",Muzzio!C27, " ")
C28: =IF(Thrakiri!D31="Não",Thrakiri!C31, " ") | G28: =IF(Gitrog!D27="Não",Gitrog!C27, " ") | K28: =IF(Elfos!D28="Não",Elfos!C28, " ") | O28: =IF(Jhoira!D29="Não",Jhoira!C29, " ") | S28: =IF(Fractius!D28="Não",Fractius!C28, " ") | W28: =IF(Muzzio!D28="Não",Muzzio!C28, " ")
C29: =IF(Thrakiri!D32="Não",Thrakiri!C32, " ") | G29: =IF(Gitrog!D28="Não",Gitrog!C28, " ") | K29: =IF(Elfos!D29="Não",Elfos!C29, " ") | O29: =IF(Jhoira!D30="Não",Jhoira!C30, " ") | S29: =IF(Fractius!D87="Não",Fractius!C87, " ") | W29: =IF(Muzzio!D29="Não",Muzzio!C29, " ")
C30: =IF(Thrakiri!D18="Não",Thrakiri!C18, " ") | G30: =IF(Gitrog!D29="Não",Gitrog!C29, " ") | K30: =IF(Elfos!D30="Não",Elfos!C30, " ") | O30: =IF(Jhoira!D31="Não",Jhoira!C31, " ") | S30: =IF(Fractius!D29="Não",Fractius!C29, " ") | W30: =IF(Muzzio!D30="Não",Muzzio!C30, " ")
C31: =IF(Thrakiri!D33="Não",Thrakiri!C33, " ") | G31: =IF(Gitrog!D30="Não",Gitrog!C30, " ") | K31: =IF(Elfos!D31="Não",Elfos!C31, " ") | O31: =IF(Jhoira!D32="Não",Jhoira!C32, " ") | S31: =IF(Fractius!D30="Não",Fractius!C30, " ") | W31: =IF(Muzzio!D31="Não",Muzzio!C31, " ")
C32: =IF(Thrakiri!D34="Não",Thrakiri!C34, " ") | G32: =IF(Gitrog!D31="Não",Gitrog!C31, " ") | K32: =IF(Elfos!D32="Não",Elfos!C32, " ") | O32: =IF(Jhoira!D33="Não",Jhoira!C33, " ") | S32: =IF(Fractius!D31="Não",Fractius!C31, " ") | W32: =IF(Muzzio!D33="Não",Muzzio!C33, " ")
C33: =IF(Thrakiri!D35="Não",Thrakiri!C35, " ") | G33: =IF(Gitrog!D32="Não",Gitrog!C32, " ") | K33: =IF(Elfos!D33="Não",Elfos!C33, " ") | O33: =IF(Jhoira!D34="Não",Jhoira!C34, " ") | S33: =IF(Fractius!D32="Não",Fractius!C32, " ") | W33: =IF(Muzzio!D39="Não",Muzzio!C39, " ")
C34: =IF(Thrakiri!D36="Não",Thrakiri!C36, " ") | G34: =IF(Gitrog!D33="Não",Gitrog!C33, " ") | K34: =IF(Elfos!D34="Não",Elfos!C34, " ") | O34: =IF(Jhoira!D35="Não",Jhoira!C35, " ") | S34: =IF(Fractius!D33="Não",Fractius!C33, " ") | W34: =IF(Muzzio!D50="Não",Muzzio!C50, " ")
C35: =IF(Thrakiri!D37="Não",Thrakiri!C37, " ") | G35: =IF(Gitrog!D34="Não",Gitrog!C34, " ") | K35: =IF(Elfos!D35="Não",Elfos!C35, " ") | O35: =IF(Jhoira!D36="Não",Jhoira!C36, " ") | S35: =IF(Fractius!D34="Não",Fractius!C34, " ") | W35: =IF(Muzzio!D49="Não",Muzzio!C49, " ") -> Caixa Enigmática Desconcertante
C36: =IF(Thrakiri!D38="Não",Thrakiri!C38, " ") | G36: =IF(Gitrog!D35="Não",Gitrog!C35, " ") | K36: =IF(Elfos!D36="Não",Elfos!C36, " ") | O36: =IF(Jhoira!D38="Não",Jhoira!C38, " ") | S36: =IF(Fractius!D35="Não",Fractius!C35, " ") | W36: =IF(Muzzio!D45="Não",Muzzio!C45, " ")
C37: =IF(Thrakiri!D39="Não",Thrakiri!C39, " ") | G37: =IF(Gitrog!D36="Não",Gitrog!C36, " ") | K37: =IF(Elfos!D37="Não",Elfos!C37, " ") | O37: =IF(Jhoira!D39="Não",Jhoira!C39, " ") | S37: =IF(Fractius!D36="Não",Fractius!C36, " ") | W37: =IF(Muzzio!D48="Não",Muzzio!C48, " ")
C38: =IF(Thrakiri!D40="Não",Thrakiri!C40, " ") | G38: =IF(Gitrog!D37="Não",Gitrog!C37, " ") | K38: =IF(Elfos!D38="Não",Elfos!C38, " ") | O38: =IF(Jhoira!D40="Não",Jhoira!C40, " ") | S38: =IF(Fractius!D37="Não",Fractius!C37, " ") | W38: =IF(Muzzio!D46="Não",Muzzio!C46, " ")
C39: =IF(Thrakiri!D41="Não",Thrakiri!C41, " ") | G39: =IF(Gitrog!D38="Não",Gitrog!C38, " ") | K39: =IF(Elfos!D39="Não",Elfos!C39, " ") | O39: =IF(Jhoira!D41="Não",Jhoira!C41, " ") | S39: =IF(Fractius!D38="Não",Fractius!C38, " ") | W39: =IF(Muzzio!D52="Não",Muzzio!C52, " ")
C40: =IF(Thrakiri!D42="Não",Thrakiri!C42, " ") | G40: =IF(Gitrog!D39="Não",Gitrog!C39, " ") | K40: =IF(Elfos!D40="Não",Elfos!C40, " ") | O40: =IF(Jhoira!D43="Não",Jhoira!C43, " ") | S40: =IF(Fractius!D39="Não",Fractius!C39, " ") | W40: =IF(Muzzio!D38="Não",Muzzio!C38, " ")
C41: =IF(Thrakiri!D43="Não",Thrakiri!C43, " ") | G41: =IF(Gitrog!D40="Não",Gitrog!C40, " ") | K41: =IF(Elfos!D41="Não",Elfos!C41, " ") | O41: =IF(Jhoira!D42="Não",Jhoira!C42, " ") -> Ulamog, o Profanador | S41: =IF(Fractius!D40="Não",Fractius!C40, " ") | W41: =IF(Muzzio!D34="Não",Muzzio!C34, " ")
C42: =IF(Thrakiri!D44="Não",Thrakiri!C44, " ") | G42: =IF(Gitrog!D41="Não",Gitrog!C41, " ") | K42: =IF(Elfos!D42="Não",Elfos!C42, " ") | O42: =IF(Jhoira!D44="Não",Jhoira!C44, " ") | S42: =IF(Fractius!D42="Não",Fractius!C42, " ") | W42: =IF(Muzzio!D40="Não",Muzzio!C40, " ")
C43: =IF(Thrakiri!D45="Não",Thrakiri!C45, " ") -> Obelisco de Obsidiana | G43: =IF(Gitrog!D42="Não",Gitrog!C42, " ") | K43: =IF(Elfos!D43="Não",Elfos!C43, " ") | O43: =IF(Jhoira!D45="Não",Jhoira!C45, " ") | S43: =IF(Fractius!D43="Não",Fractius!C43, " ") | W43: =IF(Muzzio!D41="Não",Muzzio!C41, " ") -> Sonic Screwdriver
C44: =IF(Thrakiri!D46="Não",Thrakiri!C46, " ") | G44: =IF(Gitrog!D43="Não",Gitrog!C43, " ") | K44: =IF(Elfos!D44="Não",Elfos!C44, " ") | O44: =IF(Jhoira!D46="Não",Jhoira!C46, " ") | S44: =IF(Fractius!D44="Não",Fractius!C44, " ") | W44: =IF(Muzzio!D42="Não",Muzzio!C42, " ")
C45: =IF(Thrakiri!D47="Não",Thrakiri!C47, " ") | G45: =IF(Gitrog!D44="Não",Gitrog!C44, " ") | K45: =IF(Elfos!D45="Não",Elfos!C45, " ") | O45: =IF(Jhoira!D47="Não",Jhoira!C47, " ") | S45: =IF(Fractius!D45="Não",Fractius!C45, " ") | W45: =IF(Muzzio!D35="Não",Muzzio!C35, " ")
C46: =IF(Thrakiri!D48="Não",Thrakiri!C48, " ") | G46: =IF(Gitrog!D45="Não",Gitrog!C45, " ") | K46: =IF(Elfos!D46="Não",Elfos!C46, " ") | O46: =IF(Jhoira!D37="Não",Jhoira!C37, " ") -> Emrakul, um Novo Mundo | S46: =IF(Fractius!D46="Não",Fractius!C46, " ") | W46: =IF(Muzzio!D47="Não",Muzzio!C47, " ")
C47: =IF(Thrakiri!D49="Não",Thrakiri!C49, " ") | G47: =IF(Gitrog!D46="Não",Gitrog!C46, " ") | K47: =IF(Elfos!D47="Não",Elfos!C47, " ") | O47: =IF(Jhoira!D48="Não",Jhoira!C48, " ") | S47: =IF(Fractius!D47="Não",Fractius!C47, " ") | W47: =IF(Muzzio!D51="Não",Muzzio!C51, " ")
C48: =IF(Thrakiri!D17="Não",Thrakiri!C17, " ") -> Uthros, Titanic Godcore | G48: =IF(Gitrog!D47="Não",Gitrog!C47, " ") | K48: =IF(Elfos!D48="Não",Elfos!C48, " ") | O48: =IF(Jhoira!D73="Não",Jhoira!C73, " ") | S48: =IF(Fractius!D48="Não",Fractius!C48, " ") | W48: =IF(Muzzio!D44="Não",Muzzio!C44, " ")
C49: =IF(Thrakiri!D50="Não",Thrakiri!C50, " ") | G49: =IF(Gitrog!D48="Não",Gitrog!C48, " ") | K49: =IF(Elfos!D49="Não",Elfos!C49, " ") | O49: =IF(Jhoira!D56="Não",Jhoira!C56, " ") | S49: =IF(Fractius!D49="Não",Fractius!C49, " ") | W49: =IF(Muzzio!D43="Não",Muzzio!C43, " ")
C50: =IF(Thrakiri!D51="Não",Thrakiri!C51, " ") | G50: =IF(Gitrog!D49="Não",Gitrog!C49, " ") | K50: =IF(Elfos!D50="Não",Elfos!C50, " ") | O50: =IF(Jhoira!D98="Não",Jhoira!C98, " ") | S50: =IF(Fractius!D50="Não",Fractius!C50, " ") | W50: =IF(Muzzio!D37="Não",Muzzio!C37, " ")
C51: =IF(Thrakiri!D52="Não",Thrakiri!C52, " ") -> Shaku da Honra Desgastada | G51: =IF(Gitrog!D50="Não",Gitrog!C50, " ") | K51: =IF(Elfos!D51="Não",Elfos!C51, " ") | O51: =IF(Jhoira!D49="Não",Jhoira!C49, " ") | S51: =IF(Fractius!D51="Não",Fractius!C51, " ") | W51: =IF(Muzzio!D36="Não",Muzzio!C36, " ")
C52: =IF(Thrakiri!D53="Não",Thrakiri!C53, " ") | G52: =IF(Gitrog!D51="Não",Gitrog!C51, " ") | K52: =IF(Elfos!D52="Não",Elfos!C52, " ") | O52: =IF(Jhoira!D50="Não",Jhoira!C50, " ") | S52: =IF(Fractius!D52="Não",Fractius!C52, " ") | W52: =IF(Muzzio!D79="Não",Muzzio!C79, " ")
C53: =IF(Thrakiri!D54="Não",Thrakiri!C54, " ") | G53: =IF(Gitrog!D52="Não",Gitrog!C52, " ") | K53: =IF(Elfos!D53="Não",Elfos!C53, " ") | O53: =IF(Jhoira!D51="Não",Jhoira!C51, " ") | S53: =IF(Fractius!D53="Não",Fractius!C53, " ") | W53: =IF(Muzzio!D53="Não",Muzzio!C53, " ")
C54: =IF(Thrakiri!D56="Não",Thrakiri!C56, " ") -> The Eternity Elevator | G54: =IF(Gitrog!D53="Não",Gitrog!C53, " ") | K54: =IF(Elfos!D54="Não",Elfos!C54, " ") | O54: =IF(Jhoira!D52="Não",Jhoira!C52, " ") | S54: =IF(Fractius!D54="Não",Fractius!C54, " ") | W54: =IF(Muzzio!D55="Não",Muzzio!C55, " ")
C55: =IF(Thrakiri!D69="Não",Thrakiri!C69, " ") | G55: =IF(Gitrog!D54="Não",Gitrog!C54, " ") | K55: =IF(Elfos!D55="Não",Elfos!C55, " ") | O55: =IF(Jhoira!D53="Não",Jhoira!C53, " ") | S55: =IF(Fractius!D55="Não",Fractius!C55, " ") | W55: =IF(Muzzio!D84="Não",Muzzio!C84, " ")
C56: =IF(Thrakiri!D75="Não",Thrakiri!C75, " ") | G56: =IF(Gitrog!D55="Não",Gitrog!C55, " ") | K56: =IF(Elfos!D56="Não",Elfos!C56, " ") | O56: =IF(Jhoira!D55="Não",Jhoira!C55, " ") | S56: =IF(Fractius!D56="Não",Fractius!C56, " ") | W56: =IF(Muzzio!D56="Não",Muzzio!C56, " ")
C57: =IF(Thrakiri!D19="Não",Thrakiri!C19, " ") -> The Mycosynth Gardens | G57: =IF(Gitrog!D56="Não",Gitrog!C56, " ") -> Delighted Halfling | K57: =IF(Elfos!D57="Não",Elfos!C57, " ") | O57: =IF(Jhoira!D57="Não",Jhoira!C57, " ") | S57: =IF(Fractius!D57="Não",Fractius!C57, " ") | W57: =IF(Muzzio!D57="Não",Muzzio!C57, " ")
C58: =IF(Thrakiri!D57="Não",Thrakiri!C57, " ") | G58: =IF(Gitrog!D57="Não",Gitrog!C57, " ") | K58: =IF(Elfos!D58="Não",Elfos!C58, " ") | O58: =IF(Jhoira!D58="Não",Jhoira!C58, " ") | S58: =IF(Fractius!D58="Não",Fractius!C58, " ") | W58: =IF(Muzzio!D58="Não",Muzzio!C58, " ")
C59: =IF(Thrakiri!D58="Não",Thrakiri!C58, " ") | G59: =IF(Gitrog!D58="Não",Gitrog!C58, " ") | K59: =IF(Elfos!D60="Não",Elfos!C60, " ") | O59: =IF(Jhoira!D59="Não",Jhoira!C59, " ") | S59: =IF(Fractius!D59="Não",Fractius!C59, " ") | W59: =IF(Muzzio!D60="Não",Muzzio!C60, " ")
C60: =IF(Thrakiri!D59="Não",Thrakiri!C59, " ") | G60: =IF(Gitrog!D59="Não",Gitrog!C59, " ") | K60: =IF(Elfos!D61="Não",Elfos!C61, " ") | O60: =IF(Jhoira!D60="Não",Jhoira!C60, " ") | S60: =IF(Fractius!D60="Não",Fractius!C60, " ") | W60: =IF(Muzzio!D77="Não",Muzzio!C77, " ") -> A Joia do Enigma
C61: =IF(Thrakiri!D60="Não",Thrakiri!C60, " ") | G61: =IF(Gitrog!D60="Não",Gitrog!C60, " ") | K61: =IF(Elfos!D62="Não",Elfos!C62, " ") | O61: =IF(Jhoira!D61="Não",Jhoira!C61, " ") | S61: =IF(Fractius!D61="Não",Fractius!C61, " ") | W61: =IF(Muzzio!D59="Não",Muzzio!C59, " ")
C62: =IF(Thrakiri!D61="Não",Thrakiri!C61, " ") | G62: =IF(Gitrog!D61="Não",Gitrog!C61, " ") | K62: =IF(Elfos!D63="Não",Elfos!C63, " ") | O62: =IF(Jhoira!D62="Não",Jhoira!C62, " ") | S62: =IF(Fractius!D62="Não",Fractius!C62, " ") | W62: =IF(Muzzio!D61="Não",Muzzio!C61, " ")
C63: =IF(Thrakiri!D62="Não",Thrakiri!C62, " ") | G63: =IF(Gitrog!D62="Não",Gitrog!C62, " ") | K63: =IF(Elfos!D64="Não",Elfos!C64, " ") | O63: =IF(Jhoira!D63="Não",Jhoira!C63, " ") -> Planetary Annihilation | S63: =IF(Fractius!D63="Não",Fractius!C63, " ") | W63: =IF(Muzzio!D62="Não",Muzzio!C62, " ")
C64: =IF(Thrakiri!D63="Não",Thrakiri!C63, " ") | G64: =IF(Gitrog!D63="Não",Gitrog!C63, " ") | K64: =IF(Elfos!D65="Não",Elfos!C65, " ") | O64: =IF(Jhoira!D64="Não",Jhoira!C64, " ") | S64: =IF(Fractius!D64="Não",Fractius!C64, " ") | W64: =IF(Muzzio!D63="Não",Muzzio!C63, " ")
C65: =IF(Thrakiri!D64="Não",Thrakiri!C64, " ") | G65: =IF(Gitrog!D64="Não",Gitrog!C64, " ") | K65: =IF(Elfos!D66="Não",Elfos!C66, " ") | O65: =IF(Jhoira!D65="Não",Jhoira!C65, " ") | S65: =IF(Fractius!D65="Não",Fractius!C65, " ") | W65: =IF(Muzzio!D64="Não",Muzzio!C64, " ")
C66: =IF(Thrakiri!D65="Não",Thrakiri!C65, " ") | G66: =IF(Gitrog!D65="Não",Gitrog!C65, " ") | K66: =IF(Elfos!D67="Não",Elfos!C67, " ") | O66: =IF(Jhoira!D92="Não",Jhoira!C92, " ") | S66: =IF(Fractius!D66="Não",Fractius!C66, " ") | W66: =IF(Muzzio!D76="Não",Muzzio!C76, " ")
C67: =IF(Thrakiri!D66="Não",Thrakiri!C66, " ") | G67: =IF(Gitrog!D76="Não",Gitrog!C76, " ") | K67: =IF(Elfos!D68="Não",Elfos!C68, " ") | O67: =IF(Jhoira!D66="Não",Jhoira!C66, " ") | S67: =IF(Fractius!D67="Não",Fractius!C67, " ") | W67: =IF(Muzzio!D65="Não",Muzzio!C65, " ")
C68: =IF(Thrakiri!D67="Não",Thrakiri!C67, " ") | G68: =IF(Gitrog!D66="Não",Gitrog!C66, " ") | K68: =IF(Elfos!D69="Não",Elfos!C69, " ") | O68: =IF(Jhoira!D67="Não",Jhoira!C67, " ") | S68: =IF(Fractius!D68="Não",Fractius!C68, " ") | W68: =IF(Muzzio!D66="Não",Muzzio!C66, " ") -> Extinguisher Battleship
C69: =IF(Thrakiri!D68="Não",Thrakiri!C68, " ") | G69: =IF(Gitrog!D67="Não",Gitrog!C67, " ") | K69: =IF(Elfos!D70="Não",Elfos!C70, " ") | O69: =IF(Jhoira!D68="Não",Jhoira!C68, " ") | S69: =IF(Fractius!D69="Não",Fractius!C69, " ") | W69: =IF(Muzzio!D32="Não",Muzzio!C32, " ")
C70: =IF(Thrakiri!D70="Não",Thrakiri!C70, " ") | G70: =IF(Gitrog!D68="Não",Gitrog!C68, " ") | K70: =IF(Elfos!D71="Não",Elfos!C71, " ") | O70: =IF(Jhoira!D69="Não",Jhoira!C69, " ") | S70: =IF(Fractius!D71="Não",Fractius!C71, " ") | W70: =IF(Muzzio!D67="Não",Muzzio!C67, " ") -> Portal to Phyrexia
C71: =IF(Thrakiri!D71="Não",Thrakiri!C71, " ") | G71: =IF(Gitrog!D69="Não",Gitrog!C69, " ") | K71: =IF(Elfos!D72="Não",Elfos!C72, " ") | O71: =IF(Jhoira!D70="Não",Jhoira!C70, " ") | S71: =IF(Fractius!D73="Não",Fractius!C73, " ") | W71: =IF(Muzzio!D69="Não",Muzzio!C69, " ")
C72: =IF(Thrakiri!D72="Não",Thrakiri!C72, " ") | G72: =IF(Gitrog!D70="Não",Gitrog!C70, " ") | K72: =IF(Elfos!D73="Não",Elfos!C73, " ") | O72: =IF(Jhoira!D54="Não",Jhoira!C54, " ") | S72: =IF(Fractius!D74="Não",Fractius!C74, " ") | W72: =IF(Muzzio!D70="Não",Muzzio!C70, " ")
C73: =IF(Thrakiri!D73="Não",Thrakiri!C73, " ") | G73: =IF(Gitrog!D71="Não",Gitrog!C71, " ") -> Ulamog, the Infinite Gyre | K73: =IF(Elfos!D74="Não",Elfos!C74, " ") | O73: =IF(Jhoira!D71="Não",Jhoira!C71, " ") | S73: =IF(Fractius!D75="Não",Fractius!C75, " ") | W73: =IF(Muzzio!D71="Não",Muzzio!C71, " ")
C74: =IF(Thrakiri!D74="Não",Thrakiri!C74, " ") | G74: =IF(Gitrog!D72="Não",Gitrog!C72, " ") | K74: =IF(Elfos!D75="Não",Elfos!C75, " ") | O74: =IF(Jhoira!D72="Não",Jhoira!C72, " ") | S74: =IF(Fractius!D76="Não",Fractius!C76, " ") | W74: =IF(Muzzio!D72="Não",Muzzio!C72, " ")
C75: =IF(Thrakiri!D76="Não",Thrakiri!C76, " ") | G75: =IF(Gitrog!D73="Não",Gitrog!C73, " ") | K75: =IF(Elfos!D76="Não",Elfos!C76, " ") | O75: =IF(Jhoira!D74="Não",Jhoira!C74, " ") | S75: =IF(Fractius!D77="Não",Fractius!C77, " ") | W75: =IF(Muzzio!D73="Não",Muzzio!C73, " ")
C76: =IF(Thrakiri!D77="Não",Thrakiri!C77, " ") | G76: =IF(Gitrog!D74="Não",Gitrog!C74, " ") | K76: =IF(Elfos!D77="Não",Elfos!C77, " ") | O76: =IF(Jhoira!D75="Não",Jhoira!C75, " ") | S76: =IF(Fractius!D78="Não",Fractius!C78, " ") | W76: =IF(Muzzio!D74="Não",Muzzio!C74, " ")
C77: =IF(Thrakiri!D78="Não",Thrakiri!C78, " ") | G77: =IF(Gitrog!D75="Não",Gitrog!C75, " ") | K77: =IF(Elfos!D78="Não",Elfos!C78, " ") | O77: =IF(Jhoira!D76="Não",Jhoira!C76, " ") | S77: =IF(Fractius!D79="Não",Fractius!C79, " ") | W77: =IF(Muzzio!D75="Não",Muzzio!C75, " ")
C78: =IF(Thrakiri!D79="Não",Thrakiri!C79, " ") -> Matoya, Archon Elder | G78: =IF(Gitrog!D77="Não",Gitrog!C77, " ") -> Hedge Shredder | K78: =IF(Elfos!D79="Não",Elfos!C79, " ") -> Nissa, Resurgent Animist | O78: =IF(Jhoira!D77="Não",Jhoira!C77, " ") | S78: =IF(Fractius!D41="Não",Fractius!C41, " ") -> Sliver Gravemother | W78: =IF(Muzzio!D78="Não",Muzzio!C78, " ")
C79: =IF(Thrakiri!D80="Não",Thrakiri!C80, " ") | G79: =IF(Gitrog!D78="Não",Gitrog!C78, " ") | K79: =IF(Elfos!D80="Não",Elfos!C80, " ") | O79: =IF(Jhoira!D78="Não",Jhoira!C78, " ") | S79: =IF(Fractius!D82="Não",Fractius!C82, " ") | W79: =IF(Muzzio!D80="Não",Muzzio!C80, " ")
C80: =IF(Thrakiri!D81="Não",Thrakiri!C81, " ") | G80: =IF(Gitrog!D79="Não",Gitrog!C79, " ") -> Broodheart Engine | K80: =IF(Elfos!D81="Não",Elfos!C81, " ") | O80: =IF(Jhoira!D79="Não",Jhoira!C79, " ") | S80: =IF(Fractius!D84="Não",Fractius!C84, " ") | W80: =IF(Muzzio!D81="Não",Muzzio!C81, " ")
C81: =IF(Thrakiri!D82="Não",Thrakiri!C82, " ") | G81: =IF(Gitrog!D80="Não",Gitrog!C80, " ") | K81: =IF(Elfos!D59="Não",Elfos!C59, " ") | O81: =IF(Jhoira!D80="Não",Jhoira!C80, " ") | S81: =IF(Fractius!D80="Não",Fractius!C80, " ") | W81: =IF(Muzzio!D82="Não",Muzzio!C82, " ")
C82: =IF(Thrakiri!D83="Não",Thrakiri!C83, " ") | G82: =IF(Gitrog!D81="Não",Gitrog!C81, " ") | K82: =IF(Elfos!D82="Não",Elfos!C82, " ") | O82: =IF(Jhoira!D81="Não",Jhoira!C81, " ") -> Cyber Conversion | S82: =IF(Fractius!D81="Não",Fractius!C81, " ") | W82: =IF(Muzzio!D83="Não",Muzzio!C83, " ")
C83: =IF(Thrakiri!D84="Não",Thrakiri!C84, " ") | G83: =IF(Gitrog!D82="Não",Gitrog!C82, " ") -> Ondulações de Morte-Vida | K83: =IF(Elfos!D83="Não",Elfos!C83, " ") | O83: =IF(Jhoira!D82="Não",Jhoira!C82, " ") | S83: =IF(Fractius!D97="Não",Fractius!C97, " ") -> Rakdos Signet | W83: =IF(Muzzio!D85="Não",Muzzio!C85, " ")
C84: =IF(Thrakiri!D85="Não",Thrakiri!C85, " ") | G84: =IF(Gitrog!D84="Não",Gitrog!C84, " ") | K84: =IF(Elfos!D84="Não",Elfos!C84, " ") | O84: =IF(Jhoira!D83="Não",Jhoira!C83, " ") | S84: =IF(Fractius!D72="Não",Fractius!C72, " ") | W84: =IF(Muzzio!D86="Não",Muzzio!C86, " ")
C85: =IF(Thrakiri!D86="Não",Thrakiri!C86, " ") | G85: =IF(Gitrog!D85="Não",Gitrog!C85, " ") -> Titania, Voice of Gaea | K85: =IF(Elfos!D85="Não",Elfos!C85, " ") | O85: =IF(Jhoira!D84="Não",Jhoira!C84, " ") | S85: =IF(Fractius!D83="Não",Fractius!C83, " ") | W85: =IF(Muzzio!D87="Não",Muzzio!C87, " ")
C86: =IF(Thrakiri!D87="Não",Thrakiri!C87, " ") | G86: =IF(Gitrog!D86="Não",Gitrog!C86, " ") | K86: =IF(Elfos!D86="Não",Elfos!C86, " ") | O86: =IF(Jhoira!D85="Não",Jhoira!C85, " ") | S86: =IF(Fractius!D70="Não",Fractius!C70, " ") | W86: =IF(Muzzio!D88="Não",Muzzio!C88, " ")
C87: =IF(Thrakiri!D88="Não",Thrakiri!C88, " ") | G87: =IF(Gitrog!D87="Não",Gitrog!C87, " ") | K87: =IF(Elfos!D87="Não",Elfos!C87, " ") | O87: =IF(Jhoira!D86="Não",Jhoira!C86, " ") | S87: =IF(Fractius!D85="Não",Fractius!C85, " ") | W87: =IF(Muzzio!D89="Não",Muzzio!C89, " ")
C88: =IF(Thrakiri!D89="Não",Thrakiri!C89, " ") | G88: =IF(Gitrog!D88="Não",Gitrog!C88, " ") | K88: =IF(Elfos!D88="Não",Elfos!C88, " ") | O88: =IF(Jhoira!D87="Não",Jhoira!C87, " ") | S88: =IF(Fractius!D86="Não",Fractius!C86, " ") | W88: =IF(Muzzio!D90="Não",Muzzio!C90, " ") -> Rings of Brighthearth
C89: =IF(Thrakiri!D90="Não",Thrakiri!C90, " ") | G89: =IF(Gitrog!D89="Não",Gitrog!C89, " ") | K89: =IF(Elfos!D89="Não",Elfos!C89, " ") | O89: =IF(Jhoira!D88="Não",Jhoira!C88, " ") | S89: =IF(Fractius!D88="Não",Fractius!C88, " ") -> Thrumming Hivepool | W89: =IF(Muzzio!D91="Não",Muzzio!C91, " ")
C90: =IF(Thrakiri!D91="Não",Thrakiri!C91, " ") | G90: =IF(Gitrog!D90="Não",Gitrog!C90, " ") | K90: =IF(Elfos!D90="Não",Elfos!C90, " ") | O90: =IF(Jhoira!D89="Não",Jhoira!C89, " ") | S90: =IF(Fractius!D89="Não",Fractius!C89, " ") | W90: =IF(Muzzio!D92="Não",Muzzio!C92, " ")
C91: =IF(Thrakiri!D92="Não",Thrakiri!C92, " ") | G91: =IF(Gitrog!D91="Não",Gitrog!C91, " ") | K91: =IF(Elfos!D91="Não",Elfos!C91, " ") | O91: =IF(Jhoira!D90="Não",Jhoira!C90, " ") | S91: =IF(Fractius!D90="Não",Fractius!C90, " ") | W91: =IF(Muzzio!D93="Não",Muzzio!C93, " ")
C92: =IF(Thrakiri!D93="Não",Thrakiri!C93, " ") | G92: =IF(Gitrog!D92="Não",Gitrog!C92, " ") -> Crisol dos Mundos | K92: =IF(Elfos!D92="Não",Elfos!C92, " ") -> Dionus, Elvish Archdruid | O92: =IF(Jhoira!D91="Não",Jhoira!C91, " ") | S92: =IF(Fractius!D91="Não",Fractius!C91, " ") | W92: =IF(Muzzio!D94="Não",Muzzio!C94, " ") -> Gogo, Master of Mimicry
C93: =IF(Thrakiri!D94="Não",Thrakiri!C94, " ") | G93: =IF(Gitrog!D93="Não",Gitrog!C93, " ") | K93: =IF(Elfos!D93="Não",Elfos!C93, " ") | O93: =IF(Jhoira!D93="Não",Jhoira!C93, " ") | S93: =IF(Fractius!D92="Não",Fractius!C92, " ") | W93: =IF(Muzzio!D68="Não",Muzzio!C68, " ") -> Dauntless Scrapbot
C94: =IF(Thrakiri!D95="Não",Thrakiri!C95, " ") | G94: =IF(Gitrog!D94="Não",Gitrog!C94, " ") | K94: =IF(Elfos!D94="Não",Elfos!C94, " ") | O94: =IF(Jhoira!D94="Não",Jhoira!C94, " ") | S94: =IF(Fractius!D93="Não",Fractius!C93, " ") | W94: =IF(Muzzio!D95="Não",Muzzio!C95, " ")
C95: =IF(Thrakiri!D96="Não",Thrakiri!C96, " ") | G95: =IF(Gitrog!D95="Não",Gitrog!C95, " ") | K95: =IF(Elfos!D95="Não",Elfos!C95, " ") | O95: =IF(Jhoira!D95="Não",Jhoira!C95, " ") | S95: =IF(Fractius!D94="Não",Fractius!C94, " ") | W95: =IF(Muzzio!D96="Não",Muzzio!C96, " ")
C96: =IF(Thrakiri!D55="Não",Thrakiri!C55, " ") | G96: =IF(Gitrog!D96="Não",Gitrog!C96, " ") | K96: =IF(Elfos!D96="Não",Elfos!C96, " ") | O96: =IF(Jhoira!D96="Não",Jhoira!C96, " ") | S96: =IF(Fractius!D95="Não",Fractius!C95, " ") | W96: =IF(Muzzio!D97="Não",Muzzio!C97, " ")
C97: =IF(Thrakiri!D97="Não",Thrakiri!C97, " ") | G97: =IF(Gitrog!D97="Não",Gitrog!C97, " ") | K97: =IF(Elfos!D97="Não",Elfos!C97, " ") | O97: =IF(Jhoira!D97="Não",Jhoira!C97, " ") | S97: =IF(Fractius!D96="Não",Fractius!C96, " ") | W97: =IF(Muzzio!D98="Não",Muzzio!C98, " ") -> Chimil, o Sol Interior
C98: =IF(Thrakiri!D98="Não",Thrakiri!C98, " ") | G98: =IF(Gitrog!D98="Não",Gitrog!C98, " ") | K98: =IF(Elfos!D98="Não",Elfos!C98, " ") | O98: =IF(Jhoira!D99="Não",Jhoira!C99, " ") | S98: =IF(Fractius!D98="Não",Fractius!C98, " ") | W98: =IF(Muzzio!D99="Não",Muzzio!C99, " ")
C99: =IF(Thrakiri!D99="Não",Thrakiri!C99, " ") | G99: =IF(Gitrog!D99="Não",Gitrog!C99, " ") -> Entomb | K99: =IF(Elfos!D99="Não",Elfos!C99, " ") | O99: =IF(Jhoira!D100="Não",Jhoira!C100, " ") | S99: =IF(Fractius!D99="Não",Fractius!C99, " ") | W99: =IF(Muzzio!D100="Não",Muzzio!C100, " ")
C100: =IF(Thrakiri!D100="Não",Thrakiri!C100, " ") | G100: =IF(Gitrog!D100="Não",Gitrog!C100, " ") | K100: =IF(Elfos!D100="Não",Elfos!C100, " ") | O100: =IF(Jhoira!D101="Não",Jhoira!C101, " ") | S100: =IF(Fractius!D100="Não",Fractius!C100, " ") | W100: =IF(Muzzio!D54="Não",Muzzio!C54, " ") -> Pingente de Ampulheta de Gerrard
C101: =IF(Thrakiri!D101="Não",Thrakiri!C101, " ") | G101: =IF(Gitrog!D101="Não",Gitrog!C101, " ") | K101: =IF(Elfos!D101="Não",Elfos!C101, " ") | O101: =IF(Jhoira!D102="Não",Jhoira!C102, " ") | S101: =IF(Fractius!D101="Não",Fractius!C101, " ") | W101: =IF(Muzzio!D101="Não",Muzzio!C101, " ")
...

Sheet RESUMO2
A1: Rielle | E1: Alela | I1: Arcades | M1: Vial Ishai | Q1: Yuriko | U1: Zedruu
A3: Total | B3: {=_xlfn._xlws.SORT(C3:C101,1,-1,0)} -> Sokenzan, Crisol da Afronta | C3: =IF(Rielle!D3="Não",Rielle!C3, " ") | E3: Total | F3: {=_xlfn._xlws.SORT(G3:G101,1,-1,0)} -> Westvale Abbey | G3: =IF(Alela!D3="Não",Alela!C3, " ") | I3: Total | J3: {=_xlfn._xlws.SORT(K3:K101,1,-1,0)} -> Teyo, Geometric Tactician | K3: =IF(Arcades!D3="Não",Arcades!C3, " ") | M3: Total | N3: {=_xlfn._xlws.SORT(O3:O101,1,-1,0)} -> Watery Grave | O3: =IF(VialIshai!D3="Não",VialIshai!C3, " ") | Q3: Total | R3: {=_xlfn._xlws.SORT(S3:S101,1,-1,0)} -> Watery Grave | S3: =IF(Yuriko!D3="Não",Yuriko!C3, " ") | U3: Total | V3: {=_xlfn._xlws.SORT(W3:W101,1,-1,0)} -> Reliquary Tower | W3: =IF(Zedruu!D3="Não",Zedruu!C3, " ") -> Homeward Path
A4: =Rielle!G3 -> 7 | B4: Serenata das Estriges | C4: =IF(Rielle!D3="Não",Rielle!C4, " ") | E4: =Alela!G3 -> 5 | F4: Renewed Solidarity | G4: =IF(Alela!D3="Não",Alela!C4, " ") | I4: =Arcades!G3 -> 2 | J4: Alchemist's Refuge | K4: =IF(Arcades!D3="Não",Arcades!C4, " ") | M4: =VialIshai!G3 -> 11 | N4: Vontade Dominadora | O4: =IF(VialIshai!D3="Não",VialIshai!C4, " ") | Q4: =Yuriko!G3 -> 14 | R4: Valfenda | S4: =IF(Yuriko!D3="Não",Yuriko!C4, " ") | U4: =Zedruu!G3 -> 3 | V4: Homeward Path | W4: =IF(Zedruu!D3="Não",Zedruu!C4, " ") -> Reliquary Tower
B5: Ojer Pakpatiq, Era Profunda | C5: =IF(Rielle!D5="Não",Rielle!C5, " ") | F5: Olho de Ojer Taq | G5: =IF(Alela!D5="Não",Alela!C5, " ") | K5: =IF(Arcades!D5="Não",Arcades!C5, " ") | N5: Spectator Seating | O5: =IF(VialIshai!D5="Não",VialIshai!C5, " ") | R5: Temporal Trespass | S5: =IF(Yuriko!D5="Não",Yuriko!C5, " ") -> Shizo, Death's Storehouse | V5: Emergency Eject | W5: =IF(Zedruu!D5="Não",Zedruu!C5, " ")
B6: Collector's Vault | C6: =IF(Rielle!D6="Não",Rielle!C6, " ") | F6: Lagoa Espelhada | G6: =IF(Alela!D6="Não",Alela!C6, " ") | K6: =IF(Arcades!D6="Não",Arcades!C6, " ") | N6: Prismatic Strands | O6: =IF(VialIshai!D6="Não",VialIshai!C6, " ") | R6: Temporal Manipulation | S6: =IF(Yuriko!D6="Não",Yuriko!C6, " ") -> Sea Gate Restoration | V6: Árbitro Silencioso | W6: =IF(Zedruu!D6="Não",Zedruu!C6, " ")
B7: Careful Study | C7: =IF(Rielle!D7="Não",Rielle!C7, " ") | F7: Adagia, Windswept Bastion | G7: =IF(Alela!D7="Não",Alela!C7, " ") | K7: =IF(Arcades!D7="Não",Arcades!C7, " ") | N7: Polluted Delta | O7: =IF(VialIshai!D7="Não",VialIshai!C7, " ") | R7: Shizo, Death's Storehouse | S7: =IF(Yuriko!D7="Não",Yuriko!C7, " ") | W7: =IF(Zedruu!D7="Não",Zedruu!C7, " ")
B8: Baral, Chief of Compliance | C8: =IF(Rielle!D8="Não",Rielle!C8, " ") | G8: =IF(Alela!D8="Não",Alela!C8, " ") | K8: =IF(Arcades!D8="Não",Arcades!C8, " ") | N8: Mandate of Peace | O8: =IF(VialIshai!D8="Não",VialIshai!C8, " ") | R8: Sea Gate Restoration | S8: =IF(Yuriko!D8="Não",Yuriko!C8, " ") -> Morphic Pool | W8: =IF(Zedruu!D8="Não",Zedruu!C8, " ")
B9: Afundar em Estupor | C9: =IF(Rielle!D9="Não",Rielle!C9, " ") | G9: =IF(Alela!D9="Não",Alela!C9, " ") | K9: =IF(Arcades!D9="Não",Arcades!C9, " ") | N9: Luxury Suite | O9: =IF(VialIshai!D9="Não",VialIshai!C9, " ") | R9: Satoru, the Infiltrator | S9: =IF(Yuriko!D9="Não",Yuriko!C9, " ") | W9: =IF(Zedruu!D9="Não",Zedruu!C9, " ")
C10: =IF(Rielle!D10="Não",Rielle!C10, " ") | G10: =IF(Alela!D10="Não",Alela!C10, " ") | K10: =IF(Arcades!D10="Não",Arcades!C10, " ") | N10: Chronomantic Escape | O10: =IF(VialIshai!D10="Não",VialIshai!C10, " ") | R10: Mystic Reflection | S10: =IF(Yuriko!D10="Não",Yuriko!C10, " ") | W10: =IF(Zedruu!D10="Não",Zedruu!C10, " ")
C11: =IF(Rielle!D11="Não",Rielle!C11, " ") | G11: =IF(Alela!D11="Não",Alela!C11, " ") | K11: =IF(Arcades!D11="Não",Arcades!C11, " ") | N11: Batwing Brume | O11: =IF(VialIshai!D11="Não",VialIshai!C11, " ") | R11: Morphic Pool | S11: =IF(Yuriko!D11="Não",Yuriko!C11, " ") | W11: =IF(Zedruu!D11="Não",Zedruu!C11, " ")
C12: =IF(Rielle!D12="Não",Rielle!C12, " ") | G12: =IF(Alela!D12="Não",Alela!C12, " ") | K12: =IF(Arcades!D12="Não",Arcades!C12, " ") | N12: Arid Mesa | O12: =IF(VialIshai!D12="Não",VialIshai!C12, " ") -> Polluted Delta | R12: Louisoix's Sacrifice | S12: =IF(Yuriko!D12="Não",Yuriko!C12, " ") -> Creeping Tar Pit | W12: =IF(Zedruu!D12="Não",Zedruu!C12, " ")
C13: =IF(Rielle!D13="Não",Rielle!C13, " ") | G13: =IF(Alela!D13="Não",Alela!C13, " ") | K13: =IF(Arcades!D13="Não",Arcades!C13, " ") | N13: Amphibian Downpour | O13: =IF(VialIshai!D13="Não",VialIshai!C13, " ") | R13: Faerie Slumber Party | S13: =IF(Yuriko!D13="Não",Yuriko!C13, " ") | W13: =IF(Zedruu!D13="Não",Zedruu!C13, " ")
C14: =IF(Rielle!D14="Não",Rielle!C14, " ") | G14: =IF(Alela!D14="Não",Alela!C14, " ") | K14: =IF(Arcades!D14="Não",Arcades!C14, " ") | O14: =IF(VialIshai!D14="Não",VialIshai!C14, " ") | R14: Drowned Catacomb | S14: =IF(Yuriko!D14="Não",Yuriko!C14, " ") | W14: =IF(Zedruu!D14="Não",Zedruu!C14, " ")
C15: =IF(Rielle!D15="Não",Rielle!C15, " ") | G15: =IF(Alela!D15="Não",Alela!C15, " ") | K15: =IF(Arcades!D15="Não",Arcades!C15, " ") | O15: =IF(VialIshai!D15="Não",VialIshai!C15, " ") | R15: Dour Port-Mage | S15: =IF(Yuriko!D15="Não",Yuriko!C15, " ") | W15: =IF(Zedruu!D15="Não",Zedruu!C15, " ")
C16: =IF(Rielle!D16="Não",Rielle!C16, " ") -> Sokenzan, Crisol da Afronta | G16: =IF(Alela!D16="Não",Alela!C16, " ") | K16: =IF(Arcades!D16="Não",Arcades!C16, " ") | O16: =IF(VialIshai!D16="Não",VialIshai!C16, " ") | R16: Creeping Tar Pit | S16: =IF(Yuriko!D16="Não",Yuriko!C16, " ") | W16: =IF(Zedruu!D16="Não",Zedruu!C16, " ")
C17: =IF(Rielle!D17="Não",Rielle!C17, " ") | G17: =IF(Alela!D17="Não",Alela!C17, " ") | K17: =IF(Arcades!D17="Não",Arcades!C17, " ") | O17: =IF(VialIshai!D17="Não",VialIshai!C17, " ") | S17: =IF(Yuriko!D17="Não",Yuriko!C17, " ") | W17: =IF(Zedruu!D17="Não",Zedruu!C17, " ")
C18: =IF(Rielle!D18="Não",Rielle!C18, " ") -> Afundar em Estupor | G18: =IF(Alela!D18="Não",Alela!C18, " ") -> Westvale Abbey | K18: =IF(Arcades!D18="Não",Arcades!C18, " ") | O18: =IF(VialIshai!D18="Não",VialIshai!C18, " ") | S18: =IF(Yuriko!D18="Não",Yuriko!C18, " ") -> Watery Grave | W18: =IF(Zedruu!D18="Não",Zedruu!C18, " ")
C19: =IF(Rielle!D19="Não",Rielle!C19, " ") | G19: =IF(Alela!D19="Não",Alela!C19, " ") | K19: =IF(Arcades!D19="Não",Arcades!C19, " ") | O19: =IF(VialIshai!D19="Não",VialIshai!C19, " ") -> Arid Mesa | S19: =IF(Yuriko!D19="Não",Yuriko!C19, " ") -> Drowned Catacomb | W19: =IF(Zedruu!D19="Não",Zedruu!C19, " ")
C20: =IF(Rielle!D20="Não",Rielle!C20, " ") | G20: =IF(Alela!D20="Não",Alela!C20, " ") | K20: =IF(Arcades!D20="Não",Arcades!C20, " ") | O20: =IF(VialIshai!D20="Não",VialIshai!C20, " ") | S20: =IF(Yuriko!D20="Não",Yuriko!C20, " ") -> Valfenda | W20: =IF(Zedruu!D20="Não",Zedruu!C20, " ")
C21: =IF(Rielle!D21="Não",Rielle!C21, " ") | G21: =IF(Alela!D21="Não",Alela!C21, " ") | K21: =IF(Arcades!D21="Não",Arcades!C21, " ") | O21: =IF(VialIshai!D21="Não",VialIshai!C21, " ") | S21: =IF(Yuriko!D21="Não",Yuriko!C21, " ") | W21: =IF(Zedruu!D21="Não",Zedruu!C21, " ")
C22: =IF(Rielle!D22="Não",Rielle!C22, " ") | G22: =IF(Alela!D35="Não",Alela!C35, " ") | K22: =IF(Arcades!D22="Não",Arcades!C22, " ") -> Alchemist's Refuge | O22: =IF(VialIshai!D22="Não",VialIshai!C22, " ") -> Watery Grave | S22: =IF(Yuriko!D22="Não",Yuriko!C22, " ") | W22: =IF(Zedruu!D22="Não",Zedruu!C22, " ")
C23: =IF(Rielle!D23="Não",Rielle!C23, " ") | G23: =IF(Alela!D22="Não",Alela!C22, " ") | K23: =IF(Arcades!D23="Não",Arcades!C23, " ") | O23: =IF(VialIshai!D23="Não",VialIshai!C23, " ") | S23: =IF(Yuriko!D23="Não",Yuriko!C23, " ") | W23: =IF(Zedruu!D23="Não",Zedruu!C23, " ")
C24: =IF(Rielle!D24="Não",Rielle!C24, " ") | G24: =IF(Alela!D23="Não",Alela!C23, " ") -> Lagoa Espelhada | K24: =IF(Arcades!D24="Não",Arcades!C24, " ") | O24: =IF(VialIshai!D24="Não",VialIshai!C24, " ") | S24: =IF(Yuriko!D24="Não",Yuriko!C24, " ") | W24: =IF(Zedruu!D24="Não",Zedruu!C24, " ")
C25: =IF(Rielle!D25="Não",Rielle!C25, " ") | G25: =IF(Alela!D24="Não",Alela!C24, " ") -> Adagia, Windswept Bastion | K25: =IF(Arcades!D25="Não",Arcades!C25, " ") | O25: =IF(VialIshai!D25="Não",VialIshai!C25, " ") | S25: =IF(Yuriko!D25="Não",Yuriko!C25, " ") | W25: =IF(Zedruu!D25="Não",Zedruu!C25, " ")
C26: =IF(Rielle!D26="Não",Rielle!C26, " ") | G26: =IF(Alela!D25="Não",Alela!C25, " ") | K26: =IF(Arcades!D26="Não",Arcades!C26, " ") | O26: =IF(VialIshai!D26="Não",VialIshai!C26, " ") | S26: =IF(Yuriko!D26="Não",Yuriko!C26, " ") | W26: =IF(Zedruu!D26="Não",Zedruu!C26, " ")
C27: =IF(Rielle!D27="Não",Rielle!C27, " ") | G27: =IF(Alela!D28="Não",Alela!C28, " ") | K27: =IF(Arcades!D27="Não",Arcades!C27, " ") | O27: =IF(VialIshai!D27="Não",VialIshai!C27, " ") | S27: =IF(Yuriko!D27="Não",Yuriko!C27, " ") | W27: =IF(Zedruu!D27="Não",Zedruu!C27, " ")
C28: =IF(Rielle!D28="Não",Rielle!C28, " ") | G28: =IF(Alela!D29="Não",Alela!C29, " ") | K28: =IF(Arcades!D28="Não",Arcades!C28, " ") | O28: =IF(VialIshai!D28="Não",VialIshai!C28, " ") | S28: =IF(Yuriko!D28="Não",Yuriko!C28, " ") | W28: =IF(Zedruu!D28="Não",Zedruu!C28, " ")
C29: =IF(Rielle!D29="Não",Rielle!C29, " ") | G29: =IF(Alela!D30="Não",Alela!C30, " ") | K29: =IF(Arcades!D29="Não",Arcades!C29, " ") | O29: =IF(VialIshai!D29="Não",VialIshai!C29, " ") | S29: =IF(Yuriko!D29="Não",Yuriko!C29, " ") | W29: =IF(Zedruu!D29="Não",Zedruu!C29, " ")
C30: =IF(Rielle!D30="Não",Rielle!C30, " ") | G30: =IF(Alela!D27="Não",Alela!C27, " ") | K30: =IF(Arcades!D30="Não",Arcades!C30, " ") | O30: =IF(VialIshai!D30="Não",VialIshai!C30, " ") | S30: =IF(Yuriko!D30="Não",Yuriko!C30, " ") | W30: =IF(Zedruu!D30="Não",Zedruu!C30, " ")
C31: =IF(Rielle!D31="Não",Rielle!C31, " ") | G31: =IF(Alela!D31="Não",Alela!C31, " ") | K31: =IF(Arcades!D31="Não",Arcades!C31, " ") | O31: =IF(VialIshai!D31="Não",VialIshai!C31, " ") | S31: =IF(Yuriko!D31="Não",Yuriko!C31, " ") | W31: =IF(Zedruu!D31="Não",Zedruu!C31, " ")
C32: =IF(Rielle!D32="Não",Rielle!C32, " ") | G32: =IF(Alela!D32="Não",Alela!C32, " ") | K32: =IF(Arcades!D32="Não",Arcades!C32, " ") | O32: =IF(VialIshai!D34="Não",VialIshai!C34, " ") | S32: =IF(Yuriko!D32="Não",Yuriko!C32, " ") | W32: =IF(Zedruu!D32="Não",Zedruu!C32, " ")
C33: =IF(Rielle!D33="Não",Rielle!C33, " ") | G33: =IF(Alela!D34="Não",Alela!C34, " ") | K33: =IF(Arcades!D33="Não",Arcades!C33, " ") | O33: =IF(VialIshai!D35="Não",VialIshai!C35, " ") | S33: =IF(Yuriko!D33="Não",Yuriko!C33, " ") | W33: =IF(Zedruu!D33="Não",Zedruu!C33, " ")
C34: =IF(Rielle!D34="Não",Rielle!C34, " ") | G34: =IF(Alela!D26="Não",Alela!C26, " ") | K34: =IF(Arcades!D34="Não",Arcades!C34, " ") | O34: =IF(VialIshai!D36="Não",VialIshai!C36, " ") | S34: =IF(Yuriko!D34="Não",Yuriko!C34, " ") | W34: =IF(Zedruu!D34="Não",Zedruu!C34, " ")
C35: =IF(Rielle!D35="Não",Rielle!C35, " ") | G35: =IF(Alela!D36="Não",Alela!C36, " ") | K35: =IF(Arcades!D35="Não",Arcades!C35, " ") | O35: =IF(VialIshai!D37="Não",VialIshai!C37, " ") | S35: =IF(Yuriko!D35="Não",Yuriko!C35, " ") | W35: =IF(Zedruu!D35="Não",Zedruu!C35, " ")
C36: =IF(Rielle!D36="Não",Rielle!C36, " ") | G36: =IF(Alela!D37="Não",Alela!C37, " ") | K36: =IF(Arcades!D36="Não",Arcades!C36, " ") | O36: =IF(VialIshai!D38="Não",VialIshai!C38, " ") | S36: =IF(Yuriko!D36="Não",Yuriko!C36, " ") | W36: =IF(Zedruu!D36="Não",Zedruu!C36, " ")
C37: =IF(Rielle!D89="Não",Rielle!C89, " ") -> Baral, Chief of Compliance | G37: =IF(Alela!D38="Não",Alela!C38, " ") | K37: =IF(Arcades!D88="Não",Arcades!C88, " ") | O37: =IF(VialIshai!D39="Não",VialIshai!C39, " ") | S37: =IF(Yuriko!D37="Não",Yuriko!C37, " ") -> Satoru, the Infiltrator | W37: =IF(Zedruu!D37="Não",Zedruu!C37, " ")
C38: =IF(Rielle!D38="Não",Rielle!C38, " ") | G38: =IF(Alela!D39="Não",Alela!C39, " ") | K38: =IF(Arcades!D37="Não",Arcades!C37, " ") | O38: =IF(VialIshai!D40="Não",VialIshai!C40, " ") | S38: =IF(Yuriko!D38="Não",Yuriko!C38, " ") | W38: =IF(Zedruu!D38="Não",Zedruu!C38, " ")
C39: =IF(Rielle!D94="Não",Rielle!C94, " ") | G39: =IF(Alela!D40="Não",Alela!C40, " ") | K39: =IF(Arcades!D38="Não",Arcades!C38, " ") | O39: =IF(VialIshai!D41="Não",VialIshai!C41, " ") | S39: =IF(Yuriko!D39="Não",Yuriko!C39, " ") | W39: =IF(Zedruu!D39="Não",Zedruu!C39, " ")
C40: =IF(Rielle!D39="Não",Rielle!C39, " ") | G40: =IF(Alela!D41="Não",Alela!C41, " ") | K40: =IF(Arcades!D39="Não",Arcades!C39, " ") | O40: =IF(VialIshai!D42="Não",VialIshai!C42, " ") | S40: =IF(Yuriko!D40="Não",Yuriko!C40, " ") | W40: =IF(Zedruu!D40="Não",Zedruu!C40, " ")
C41: =IF(Rielle!D40="Não",Rielle!C40, " ") | G41: =IF(Alela!D42="Não",Alela!C42, " ") | K41: =IF(Arcades!D40="Não",Arcades!C40, " ") | O41: =IF(VialIshai!D43="Não",VialIshai!C43, " ") | S41: =IF(Yuriko!D42="Não",Yuriko!C42, " ") | W41: =IF(Zedruu!D41="Não",Zedruu!C41, " ")
C42: =IF(Rielle!D41="Não",Rielle!C41, " ") | G42: =IF(Alela!D43="Não",Alela!C43, " ") | K42: =IF(Arcades!D41="Não",Arcades!C41, " ") | O42: =IF(VialIshai!D44="Não",VialIshai!C44, " ") | S42: =IF(Yuriko!D43="Não",Yuriko!C43, " ") | W42: =IF(Zedruu!D42="Não",Zedruu!C42, " ")
C43: =IF(Rielle!D42="Não",Rielle!C42, " ") | G43: =IF(Alela!D45="Não",Alela!C45, " ") | K43: =IF(Arcades!D42="Não",Arcades!C42, " ") | O43: =IF(VialIshai!D46="Não",VialIshai!C46, " ") | S43: =IF(Yuriko!D44="Não",Yuriko!C44, " ") | W43: =IF(Zedruu!D43="Não",Zedruu!C43, " ")
C44: =IF(Rielle!D43="Não",Rielle!C43, " ") | G44: =IF(Alela!D46="Não",Alela!C46, " ") | K44: =IF(Arcades!D43="Não",Arcades!C43, " ") -> Teyo, Geometric Tactician | O44: =IF(VialIshai!D47="Não",VialIshai!C47, " ") | S44: =IF(Yuriko!D45="Não",Yuriko!C45, " ") | W44: =IF(Zedruu!D44="Não",Zedruu!C44, " ")
C45: =IF(Rielle!D44="Não",Rielle!C44, " ") | G45: =IF(Alela!D47="Não",Alela!C47, " ") | K45: =IF(Arcades!D78="Não",Arcades!C78, " ") | O45: =IF(VialIshai!D48="Não",VialIshai!C48, " ") | S45: =IF(Yuriko!D46="Não",Yuriko!C46, " ") | W45: =IF(Zedruu!D45="Não",Zedruu!C45, " ")
C46: =IF(Rielle!D45="Não",Rielle!C45, " ") | G46: =IF(Alela!D49="Não",Alela!C49, " ") | K46: =IF(Arcades!D54="Não",Arcades!C54, " ") | O46: =IF(VialIshai!D49="Não",VialIshai!C49, " ") | S46: =IF(Yuriko!D47="Não",Yuriko!C47, " ") | W46: =IF(Zedruu!D48="Não",Zedruu!C48, " ")
C47: =IF(Rielle!D46="Não",Rielle!C46, " ") | G47: =IF(Alela!D50="Não",Alela!C50, " ") | K47: =IF(Arcades!D44="Não",Arcades!C44, " ") | O47: =IF(VialIshai!D50="Não",VialIshai!C50, " ") | S47: =IF(Yuriko!D48="Não",Yuriko!C48, " ") | W47: =IF(Zedruu!D49="Não",Zedruu!C49, " ")
C48: =IF(Rielle!D47="Não",Rielle!C47, " ") -> Careful Study | G48: =IF(Alela!D51="Não",Alela!C51, " ") | K48: =IF(Arcades!D45="Não",Arcades!C45, " ") | O48: =IF(VialIshai!D51="Não",VialIshai!C51, " ") | S48: =IF(Yuriko!D49="Não",Yuriko!C49, " ") | W48: =IF(Zedruu!D50="Não",Zedruu!C50, " ")
C49: =IF(Rielle!D48="Não",Rielle!C48, " ") | G49: =IF(Alela!D52="Não",Alela!C52, " ") | K49: =IF(Arcades!D46="Não",Arcades!C46, " ") | O49: =IF(VialIshai!D52="Não",VialIshai!C52, " ") | S49: =IF(Yuriko!D50="Não",Yuriko!C50, " ") | W49: =IF(Zedruu!D51="Não",Zedruu!C51, " ")
C50: =IF(Rielle!D49="Não",Rielle!C49, " ") | G50: =IF(Alela!D53="Não",Alela!C53, " ") | K50: =IF(Arcades!D77="Não",Arcades!C77, " ") | O50: =IF(VialIshai!D53="Não",VialIshai!C53, " ") | S50: =IF(Yuriko!D51="Não",Yuriko!C51, " ") | W50: =IF(Zedruu!D52="Não",Zedruu!C52, " ")
C51: =IF(Rielle!D50="Não",Rielle!C50, " ") | G51: =IF(Alela!D54="Não",Alela!C54, " ") | K51: =IF(Arcades!D80="Não",Arcades!C80, " ") | O51: =IF(VialIshai!D54="Não",VialIshai!C54, " ") | S51: =IF(Yuriko!D52="Não",Yuriko!C52, " ") | W51: =IF(Zedruu!D53="Não",Zedruu!C53, " ")
C52: =IF(Rielle!D51="Não",Rielle!C51, " ") | G52: =IF(Alela!D55="Não",Alela!C55, " ") | K52: =IF(Arcades!D47="Não",Arcades!C47, " ") | O52: =IF(VialIshai!D55="Não",VialIshai!C55, " ") | S52: =IF(Yuriko!D53="Não",Yuriko!C53, " ") | W52: =IF(Zedruu!D54="Não",Zedruu!C54, " ")
C53: =IF(Rielle!D52="Não",Rielle!C52, " ") | G53: =IF(Alela!D56="Não",Alela!C56, " ") | K53: =IF(Arcades!D81="Não",Arcades!C81, " ") | O53: =IF(VialIshai!D58="Não",VialIshai!C58, " ") | S53: =IF(Yuriko!D54="Não",Yuriko!C54, " ") | W53: =IF(Zedruu!D55="Não",Zedruu!C55, " ")
C54: =IF(Rielle!D53="Não",Rielle!C53, " ") | G54: =IF(Alela!D57="Não",Alela!C57, " ") | K54: =IF(Arcades!D79="Não",Arcades!C79, " ") | O54: =IF(VialIshai!D59="Não",VialIshai!C59, " ") | S54: =IF(Yuriko!D55="Não",Yuriko!C55, " ") | W54: =IF(Zedruu!D56="Não",Zedruu!C56, " ")
C55: =IF(Rielle!D54="Não",Rielle!C54, " ") | G55: =IF(Alela!D58="Não",Alela!C58, " ") | K55: =IF(Arcades!D49="Não",Arcades!C49, " ") | O55: =IF(VialIshai!D95="Não",VialIshai!C95, " ") | S55: =IF(Yuriko!D56="Não",Yuriko!C56, " ") | W55: =IF(Zedruu!D47="Não",Zedruu!C47, " ")
C56: =IF(Rielle!D55="Não",Rielle!C55, " ") | G56: =IF(Alela!D59="Não",Alela!C59, " ") | K56: =IF(Arcades!D50="Não",Arcades!C50, " ") | O56: =IF(VialIshai!D56="Não",VialIshai!C56, " ") | S56: =IF(Yuriko!D57="Não",Yuriko!C57, " ") | W56: =IF(Zedruu!D57="Não",Zedruu!C57, " ")
C57: =IF(Rielle!D56="Não",Rielle!C56, " ") | G57: =IF(Alela!D62="Não",Alela!C62, " ") | K57: =IF(Arcades!D51="Não",Arcades!C51, " ") | O57: =IF(VialIshai!D97="Não",VialIshai!C97, " ") | S57: =IF(Yuriko!D58="Não",Yuriko!C58, " ") | W57: =IF(Zedruu!D58="Não",Zedruu!C58, " ")
C58: =IF(Rielle!D57="Não",Rielle!C57, " ") | G58: =IF(Alela!D63="Não",Alela!C63, " ") | K58: =IF(Arcades!D94="Não",Arcades!C94, " ") | O58: =IF(VialIshai!D60="Não",VialIshai!C60, " ") | S58: =IF(Yuriko!D59="Não",Yuriko!C59, " ") | W58: =IF(Zedruu!D59="Não",Zedruu!C59, " ")
C59: =IF(Rielle!D58="Não",Rielle!C58, " ") | G59: =IF(Alela!D64="Não",Alela!C64, " ") | K59: =IF(Arcades!D52="Não",Arcades!C52, " ") | O59: =IF(VialIshai!D61="Não",VialIshai!C61, " ") | S59: =IF(Yuriko!D60="Não",Yuriko!C60, " ") | W59: =IF(Zedruu!D60="Não",Zedruu!C60, " ") -> Emergency Eject
C60: =IF(Rielle!D60="Não",Rielle!C60, " ") -> Collector's Vault | G60: =IF(Alela!D65="Não",Alela!C65, " ") | K60: =IF(Arcades!D53="Não",Arcades!C53, " ") | O60: =IF(VialIshai!D84="Não",VialIshai!C84, " ") | S60: =IF(Yuriko!D61="Não",Yuriko!C61, " ") | W60: =IF(Zedruu!D61="Não",Zedruu!C61, " ")
C61: =IF(Rielle!D61="Não",Rielle!C61, " ") | G61: =IF(Alela!D48="Não",Alela!C48, " ") -> Olho de Ojer Taq | K61: =IF(Arcades!D48="Não",Arcades!C48, " ") | O61: =IF(VialIshai!D85="Não",VialIshai!C85, " ") | S61: =IF(Yuriko!D62="Não",Yuriko!C62, " ") | W61: =IF(Zedruu!D62="Não",Zedruu!C62, " ")
C62: =IF(Rielle!D62="Não",Rielle!C62, " ") | G62: =IF(Alela!D33="Não",Alela!C33, " ") | K62: =IF(Arcades!D55="Não",Arcades!C55, " ") | O62: =IF(VialIshai!D62="Não",VialIshai!C62, " ") -> Vontade Dominadora | S62: =IF(Yuriko!D63="Não",Yuriko!C63, " ") | W62: =IF(Zedruu!D66="Não",Zedruu!C66, " ")
C63: =IF(Rielle!D63="Não",Rielle!C63, " ") | G63: =IF(Alela!D100="Não",Alela!C100, " ") | K63: =IF(Arcades!D95="Não",Arcades!C95, " ") | O63: =IF(VialIshai!D91="Não",VialIshai!C91, " ") | S63: =IF(Yuriko!D64="Não",Yuriko!C64, " ") | W63: =IF(Zedruu!D67="Não",Zedruu!C67, " ")
C64: =IF(Rielle!D64="Não",Rielle!C64, " ") | G64: =IF(Alela!D66="Não",Alela!C66, " ") | K64: =IF(Arcades!D56="Não",Arcades!C56, " ") | O64: =IF(VialIshai!D57="Não",VialIshai!C57, " ") | S64: =IF(Yuriko!D65="Não",Yuriko!C65, " ") | W64: =IF(Zedruu!D70="Não",Zedruu!C70, " ")
C65: =IF(Rielle!D65="Não",Rielle!C65, " ") | G65: =IF(Alela!D67="Não",Alela!C67, " ") | K65: =IF(Arcades!D57="Não",Arcades!C57, " ") | O65: =IF(VialIshai!D63="Não",VialIshai!C63, " ") | S65: =IF(Yuriko!D66="Não",Yuriko!C66, " ") -> Faerie Slumber Party | W65: =IF(Zedruu!D71="Não",Zedruu!C71, " ")
C66: =IF(Rielle!D66="Não",Rielle!C66, " ") | G66: =IF(Alela!D68="Não",Alela!C68, " ") | K66: =IF(Arcades!D58="Não",Arcades!C58, " ") | O66: =IF(VialIshai!D64="Não",VialIshai!C64, " ") | S66: =IF(Yuriko!D67="Não",Yuriko!C67, " ") | W66: =IF(Zedruu!D90="Não",Zedruu!C90, " ")
C67: =IF(Rielle!D67="Não",Rielle!C67, " ") | G67: =IF(Alela!D69="Não",Alela!C69, " ") | K67: =IF(Arcades!D59="Não",Arcades!C59, " ") | O67: =IF(VialIshai!D65="Não",VialIshai!C65, " ") -> Amphibian Downpour | S67: =IF(Yuriko!D68="Não",Yuriko!C68, " ") | W67: =IF(Zedruu!D91="Não",Zedruu!C91, " ")
C68: =IF(Rielle!D68="Não",Rielle!C68, " ") | G68: =IF(Alela!D61="Não",Alela!C61, " ") | K68: =IF(Arcades!D60="Não",Arcades!C60, " ") | O68: =IF(VialIshai!D66="Não",VialIshai!C66, " ") | S68: =IF(Yuriko!D69="Não",Yuriko!C69, " ") | W68: =IF(Zedruu!D92="Não",Zedruu!C92, " ")
C69: =IF(Rielle!D69="Não",Rielle!C69, " ") -> Serenata das Estriges | G69: =IF(Alela!D44="Não",Alela!C44, " ") | K69: =IF(Arcades!D61="Não",Arcades!C61, " ") | O69: =IF(VialIshai!D67="Não",VialIshai!C67, " ") | S69: =IF(Yuriko!D70="Não",Yuriko!C70, " ") | W69: =IF(Zedruu!D93="Não",Zedruu!C93, " ")
C70: =IF(Rielle!D70="Não",Rielle!C70, " ") | G70: =IF(Alela!D70="Não",Alela!C70, " ") | K70: =IF(Arcades!D62="Não",Arcades!C62, " ") | O70: =IF(VialIshai!D68="Não",VialIshai!C68, " ") | S70: =IF(Yuriko!D71="Não",Yuriko!C71, " ") -> Louisoix's Sacrifice | W70: =IF(Zedruu!D94="Não",Zedruu!C94, " ")
C71: =IF(Rielle!D71="Não",Rielle!C71, " ") | G71: =IF(Alela!D71="Não",Alela!C71, " ") | K71: =IF(Arcades!D63="Não",Arcades!C63, " ") | O71: =IF(VialIshai!D69="Não",VialIshai!C69, " ") | S71: =IF(Yuriko!D72="Não",Yuriko!C72, " ") | W71: =IF(Zedruu!D69="Não",Zedruu!C69, " ")
C72: =IF(Rielle!D72="Não",Rielle!C72, " ") | G72: =IF(Alela!D72="Não",Alela!C72, " ") | K72: =IF(Arcades!D64="Não",Arcades!C64, " ") | O72: =IF(VialIshai!D70="Não",VialIshai!C70, " ") | S72: =IF(Yuriko!D73="Não",Yuriko!C73, " ") -> Mystic Reflection | W72: =IF(Zedruu!D95="Não",Zedruu!C95, " ")
C73: =IF(Rielle!D73="Não",Rielle!C73, " ") | G73: =IF(Alela!D73="Não",Alela!C73, " ") | K73: =IF(Arcades!D65="Não",Arcades!C65, " ") | O73: =IF(VialIshai!D71="Não",VialIshai!C71, " ") | S73: =IF(Yuriko!D74="Não",Yuriko!C74, " ") | W73: =IF(Zedruu!D96="Não",Zedruu!C96, " ")
C74: =IF(Rielle!D74="Não",Rielle!C74, " ") | G74: =IF(Alela!D74="Não",Alela!C74, " ") | K74: =IF(Arcades!D75="Não",Arcades!C75, " ") | O74: =IF(VialIshai!D45="Não",VialIshai!C45, " ") | S74: =IF(Yuriko!D75="Não",Yuriko!C75, " ") | W74: =IF(Zedruu!D72="Não",Zedruu!C72, " ")
C75: =IF(Rielle!D75="Não",Rielle!C75, " ") | G75: =IF(Alela!D75="Não",Alela!C75, " ") | K75: =IF(Arcades!D66="Não",Arcades!C66, " ") | O75: =IF(VialIshai!D72="Não",VialIshai!C72, " ") | S75: =IF(Yuriko!D76="Não",Yuriko!C76, " ") | W75: =IF(Zedruu!D73="Não",Zedruu!C73, " ")
C76: =IF(Rielle!D76="Não",Rielle!C76, " ") | G76: =IF(Alela!D99="Não",Alela!C99, " ") | K76: =IF(Arcades!D67="Não",Arcades!C67, " ") | O76: =IF(VialIshai!D73="Não",VialIshai!C73, " ") | S76: =IF(Yuriko!D77="Não",Yuriko!C77, " ") | W76: =IF(Zedruu!D74="Não",Zedruu!C74, " ")
C77: =IF(Rielle!D77="Não",Rielle!C77, " ") | G77: =IF(Alela!D76="Não",Alela!C76, " ") | K77: =IF(Arcades!D68="Não",Arcades!C68, " ") | O77: =IF(VialIshai!D74="Não",VialIshai!C74, " ") | S77: =IF(Yuriko!D78="Não",Yuriko!C78, " ") | W77: =IF(Zedruu!D46="Não",Zedruu!C46, " ")
C78: =IF(Rielle!D78="Não",Rielle!C78, " ") | G78: =IF(Alela!D77="Não",Alela!C77, " ") | K78: =IF(Arcades!D69="Não",Arcades!C69, " ") | O78: =IF(VialIshai!D75="Não",VialIshai!C75, " ") | S78: =IF(Yuriko!D79="Não",Yuriko!C79, " ") | W78: =IF(Zedruu!D75="Não",Zedruu!C75, " ")
C79: =IF(Rielle!D79="Não",Rielle!C79, " ") | G79: =IF(Alela!D78="Não",Alela!C78, " ") | K79: =IF(Arcades!D70="Não",Arcades!C70, " ") | O79: =IF(VialIshai!D76="Não",VialIshai!C76, " ") | S79: =IF(Yuriko!D80="Não",Yuriko!C80, " ") | W79: =IF(Zedruu!D76="Não",Zedruu!C76, " ")
C80: =IF(Rielle!D80="Não",Rielle!C80, " ") | G80: =IF(Alela!D79="Não",Alela!C79, " ") | K80: =IF(Arcades!D71="Não",Arcades!C71, " ") | O80: =IF(VialIshai!D77="Não",VialIshai!C77, " ") | S80: =IF(Yuriko!D81="Não",Yuriko!C81, " ") | W80: =IF(Zedruu!D77="Não",Zedruu!C77, " ")
C81: =IF(Rielle!D81="Não",Rielle!C81, " ") | G81: =IF(Alela!D80="Não",Alela!C80, " ") | K81: =IF(Arcades!D72="Não",Arcades!C72, " ") | O81: =IF(VialIshai!D78="Não",VialIshai!C78, " ") | S81: =IF(Yuriko!D82="Não",Yuriko!C82, " ") | W81: =IF(Zedruu!D78="Não",Zedruu!C78, " ")
C82: =IF(Rielle!D82="Não",Rielle!C82, " ") | G82: =IF(Alela!D81="Não",Alela!C81, " ") | K82: =IF(Arcades!D73="Não",Arcades!C73, " ") | O82: =IF(VialIshai!D79="Não",VialIshai!C79, " ") | S82: =IF(Yuriko!D83="Não",Yuriko!C83, " ") | W82: =IF(Zedruu!D79="Não",Zedruu!C79, " ")
C83: =IF(Rielle!D83="Não",Rielle!C83, " ") | G83: =IF(Alela!D82="Não",Alela!C82, " ") | K83: =IF(Arcades!D90="Não",Arcades!C90, " ") | O83: =IF(VialIshai!D83="Não",VialIshai!C83, " ") -> Chronomantic Escape | S83: =IF(Yuriko!D84="Não",Yuriko!C84, " ") -> Temporal Trespass | W83: =IF(Zedruu!D80="Não",Zedruu!C80, " ")
C84: =IF(Rielle!D84="Não",Rielle!C84, " ") | G84: =IF(Alela!D83="Não",Alela!C83, " ") | K84: =IF(Arcades!D74="Não",Arcades!C74, " ") | O84: =IF(VialIshai!D99="Não",VialIshai!C99, " ") | S84: =IF(Yuriko!D85="Não",Yuriko!C85, " ") | W84: =IF(Zedruu!D81="Não",Zedruu!C81, " ")
C85: =IF(Rielle!D85="Não",Rielle!C85, " ") | G85: =IF(Alela!D84="Não",Alela!C84, " ") | K85: =IF(Arcades!D76="Não",Arcades!C76, " ") | O85: =IF(VialIshai!D80="Não",VialIshai!C80, " ") | S85: =IF(Yuriko!D86="Não",Yuriko!C86, " ") | W85: =IF(Zedruu!D82="Não",Zedruu!C82, " ")
C86: =IF(Rielle!D86="Não",Rielle!C86, " ") | G86: =IF(Alela!D85="Não",Alela!C85, " ") | K86: =IF(Arcades!D82="Não",Arcades!C82, " ") | O86: =IF(VialIshai!D81="Não",VialIshai!C81, " ") | S86: =IF(Yuriko!D87="Não",Yuriko!C87, " ") -> Temporal Manipulation | W86: =IF(Zedruu!D83="Não",Zedruu!C83, " ")
C87: =IF(Rielle!D87="Não",Rielle!C87, " ") | G87: =IF(Alela!D86="Não",Alela!C86, " ") | K87: =IF(Arcades!D83="Não",Arcades!C83, " ") | O87: =IF(VialIshai!D32="Não",VialIshai!C32, " ") -> Luxury Suite | S87: =IF(Yuriko!D88="Não",Yuriko!C88, " ") | W87: =IF(Zedruu!D84="Não",Zedruu!C84, " ")
C88: =IF(Rielle!D59="Não",Rielle!C59, " ") | G88: =IF(Alela!D87="Não",Alela!C87, " ") | K88: =IF(Arcades!D84="Não",Arcades!C84, " ") | O88: =IF(VialIshai!D33="Não",VialIshai!C33, " ") -> Spectator Seating | S88: =IF(Yuriko!D89="Não",Yuriko!C89, " ") | W88: =IF(Zedruu!D86="Não",Zedruu!C86, " ")
C89: =IF(Rielle!D88="Não",Rielle!C88, " ") | G89: =IF(Alela!D88="Não",Alela!C88, " ") | K89: =IF(Arcades!D85="Não",Arcades!C85, " ") | O89: =IF(VialIshai!D82="Não",VialIshai!C82, " ") | S89: =IF(Yuriko!D90="Não",Yuriko!C90, " ") | W89: =IF(Zedruu!D68="Não",Zedruu!C68, " ")
C90: =IF(Rielle!D90="Não",Rielle!C90, " ") | G90: =IF(Alela!D89="Não",Alela!C89, " ") | K90: =IF(Arcades!D86="Não",Arcades!C86, " ") | O90: =IF(VialIshai!D86="Não",VialIshai!C86, " ") -> Mandate of Peace | S90: =IF(Yuriko!D91="Não",Yuriko!C91, " ") | W90: =IF(Zedruu!D88="Não",Zedruu!C88, " ") -> Árbitro Silencioso
C91: =IF(Rielle!D91="Não",Rielle!C91, " ") -> Ojer Pakpatiq, Era Profunda | G91: =IF(Alela!D90="Não",Alela!C90, " ") -> Renewed Solidarity | K91: =IF(Arcades!D87="Não",Arcades!C87, " ") | O91: =IF(VialIshai!D94="Não",VialIshai!C94, " ") | S91: =IF(Yuriko!D92="Não",Yuriko!C92, " ") | W91: =IF(Zedruu!D63="Não",Zedruu!C63, " ")
C92: =IF(Rielle!D37="Não",Rielle!C37, " ") | G92: =IF(Alela!D91="Não",Alela!C91, " ") | K92: =IF(Arcades!D89="Não",Arcades!C89, " ") | O92: =IF(VialIshai!D87="Não",VialIshai!C87, " ") -> Prismatic Strands | S92: =IF(Yuriko!D93="Não",Yuriko!C93, " ") | W92: =IF(Zedruu!D85="Não",Zedruu!C85, " ")
C93: =IF(Rielle!D92="Não",Rielle!C92, " ") | G93: =IF(Alela!D92="Não",Alela!C92, " ") | K93: =IF(Arcades!D91="Não",Arcades!C91, " ") | O93: =IF(VialIshai!D88="Não",VialIshai!C88, " ") | S93: =IF(Yuriko!D94="Não",Yuriko!C94, " ") | W93: =IF(Zedruu!D87="Não",Zedruu!C87, " ")
C94: =IF(Rielle!D93="Não",Rielle!C93, " ") | G94: =IF(Alela!D93="Não",Alela!C93, " ") | K94: =IF(Arcades!D92="Não",Arcades!C92, " ") | O94: =IF(VialIshai!D89="Não",VialIshai!C89, " ") | S94: =IF(Yuriko!D95="Não",Yuriko!C95, " ") | W94: =IF(Zedruu!D65="Não",Zedruu!C65, " ")
C95: =IF(Rielle!D95="Não",Rielle!C95, " ") | G95: =IF(Alela!D94="Não",Alela!C94, " ") | K95: =IF(Arcades!D93="Não",Arcades!C93, " ") | O95: =IF(VialIshai!D90="Não",VialIshai!C90, " ") | S95: =IF(Yuriko!D41="Não",Yuriko!C41, " ") | W95: =IF(Zedruu!D64="Não",Zedruu!C64, " ")
C96: =IF(Rielle!D96="Não",Rielle!C96, " ") | G96: =IF(Alela!D95="Não",Alela!C95, " ") | K96: =IF(Arcades!D96="Não",Arcades!C96, " ") | O96: =IF(VialIshai!D96="Não",VialIshai!C96, " ") | S96: =IF(Yuriko!D96="Não",Yuriko!C96, " ") | W96: =IF(Zedruu!D89="Não",Zedruu!C89, " ")
C97: =IF(Rielle!D97="Não",Rielle!C97, " ") | G97: =IF(Alela!D96="Não",Alela!C96, " ") | K97: =IF(Arcades!D97="Não",Arcades!C97, " ") | O97: =IF(VialIshai!D92="Não",VialIshai!C92, " ") -> Batwing Brume | S97: =IF(Yuriko!D97="Não",Yuriko!C97, " ") | W97: =IF(Zedruu!D97="Não",Zedruu!C97, " ")
C98: =IF(Rielle!D98="Não",Rielle!C98, " ") | G98: =IF(Alela!D97="Não",Alela!C97, " ") | K98: =IF(Arcades!D98="Não",Arcades!C98, " ") | O98: =IF(VialIshai!D93="Não",VialIshai!C93, " ") | S98: =IF(Yuriko!D98="Não",Yuriko!C98, " ") | W98: =IF(Zedruu!D98="Não",Zedruu!C98, " ")
C99: =IF(Rielle!D99="Não",Rielle!C99, " ") | G99: =IF(Alela!D98="Não",Alela!C98, " ") | K99: =IF(Arcades!D99="Não",Arcades!C99, " ") | O99: =IF(VialIshai!D98="Não",VialIshai!C98, " ") | S99: =IF(Yuriko!D99="Não",Yuriko!C99, " ") | W99: =IF(Zedruu!D99="Não",Zedruu!C99, " ")
C100: =IF(Rielle!D100="Não",Rielle!C100, " ") | G100: =IF(Alela!D101="Não",Alela!C101, " ") | K100: =IF(Arcades!D100="Não",Arcades!C100, " ") | O100: =IF(VialIshai!D100="Não",VialIshai!C100, " ") | S100: =IF(Yuriko!D100="Não",Yuriko!C100, " ") -> Dour Port-Mage | W100: =IF(Zedruu!D100="Não",Zedruu!C100, " ")
C101: =IF(Rielle!D101="Não",Rielle!C101, " ") | G101: =IF(Alela!D60="Não",Alela!C60, " ") | K101: =IF(Arcades!D101="Não",Arcades!C101, " ") | O101: =IF(VialIshai!D101="Não",VialIshai!C101, " ") | S101: =IF(Yuriko!D101="Não",Yuriko!C101, " ") | W101: =IF(Zedruu!D101="Não",Zedruu!C101, " ")
...

Sheet RESUMO3
A1: Inalla | E1: Carlos | I1: Oona | M1: Kresh | Q1: Akiri | U1: Breya
A3: Total | B3: {=_xlfn._xlws.SORT(C3:C101,1,-1,0)} -> Saw in Half | C3: =IF(Inalla!D3="Não",Inalla!C3, "") | E3: Total | F3: {=_xlfn._xlws.SORT(G3:G101,1,-1,0)} -> Vault of the Archangel | G3: =IF(Carlos!D3="Não",Carlos!C3, " ") | I3: Total | J3: {=_xlfn._xlws.SORT(K3:K101,1,-1,0)} -> Unstoppable Plan | K3: =IF(Oona!D3="Não",Oona!C3, " ") -> Jidoor, Aristocratic Capital // Overture | M3: Total | N3: {=_xlfn._xlws.SORT(O3:O101,1,-1,0)} -> The Masamune | O3: =IF(Kresh!D3="Não",Kresh!C3, " ") | Q3: Total | R3: {=_xlfn._xlws.SORT(S3:S101,1,-1,0)} -> Stoneforge Mystic | S3: =IF(Akiri!D3="Não",Akiri!C3, " ") | U3: Total | V3: {=_xlfn._xlws.SORT(W3:W101,1,-1,0)} -> Weapons Manufacturing | W3: =IF(Breya!D3="Não",Breya!C3, " ")
A4: =Inalla!G3 -> 13 | B4: Reliquary Tower | C4: =IF(Inalla!D3="Não",Inalla!C3, "") | E4: =Carlos!G3 -> 17 | F4: Unholy Annex // Ritual Chamber | G4: =IF(Carlos!D3="Não",Carlos!C4, " ") | I4: =Oona!G3 -> 9 | J4: Três Passos à Frente | K4: =IF(Oona!D3="Não",Oona!C4, " ") -> Santuário Místico | M4: =Kresh!G3 -> 9 | N4: Saqueador Amaldiçoado | O4: =IF(Kresh!D3="Não",Kresh!C4, " ") | Q4: =Akiri!G3 -> 12 | R4: Lightning Greaves | S4: =IF(Akiri!D3="Não",Akiri!C4, " ") | U4: =Breya!G3 -> 6 | V4: The Mycosynth Gardens | W4: =IF(Breya!D3="Não",Breya!C4, " ")
B5: Negociador de Almas do Viveiro | C5: =IF(Inalla!D5="Não",Inalla!C5, "") | F5: Terramorphic Expanse | G5: =IF(Carlos!D5="Não",Carlos!C5, " ") | J5: The Eternity Elevator | K5: =IF(Oona!D5="Não",Oona!C5, " ") | N5: Red XIII, Proud Warrior | O5: =IF(Kresh!D5="Não",Kresh!C5, " ") | R5: Kellan, the Fae-Blooded // Birthright Boon | S5: =IF(Akiri!D5="Não",Akiri!C5, " ") | V5: Reflecting Pool | W5: =IF(Breya!D5="Não",Breya!C5, " ")
B6: Molten Echoes | C6: =IF(Inalla!D6="Não",Inalla!C6, "") | F6: Takenuma, Charco Abandonado | G6: =IF(Carlos!D6="Não",Carlos!C6, " ") -> Terramorphic Expanse | J6: Sonic Screwdriver | K6: =IF(Oona!D6="Não",Oona!C6, " ") | N6: Pain for All | O6: =IF(Kresh!D6="Não",Kresh!C6, " ") | R6: Jitte Perdida | S6: =IF(Akiri!D6="Não",Akiri!C6, " ") | V6: Long-Range Sensor | W6: =IF(Breya!D6="Não",Breya!C6, " ")
B7: Mistbind Clique | C7: =IF(Inalla!D7="Não",Inalla!C7, "") | F7: Sorin da Casa Markov | G7: =IF(Carlos!D7="Não",Carlos!C7, " ") | J7: Season of Weaving | K7: =IF(Oona!D7="Não",Oona!C7, " ") | N7: Nibelheim Aflame | O7: =IF(Kresh!D7="Não",Kresh!C7, " ") | R7: Firion, Wild Rose Warrior | S7: =IF(Akiri!D7="Não",Akiri!C7, " ") | V7: Daretti, Ingenious Iconoclast | W7: =IF(Breya!D7="Não",Breya!C7, " ")
B8: Merchant of Secrets | C8: =IF(Inalla!D8="Não",Inalla!C8, "") | F8: Mother of runes | G8: =IF(Carlos!D8="Não",Carlos!C8, " ") -> Bojuka Bog | J8: Scour for Scrap | K8: =IF(Oona!D8="Não",Oona!C8, " ") | N8: Jenova, Ancient Calamity | O8: =IF(Kresh!D8="Não",Kresh!C8, " ") | R8: Espada de Verdade e Justiça | S8: =IF(Akiri!D8="Não",Akiri!C8, " ") | V8: Adagia, Windswept Bastion | W8: =IF(Breya!D8="Não",Breya!C8, " ")
B9: Glasspool Mimic | C9: =IF(Inalla!D9="Não",Inalla!C9, "") | F9: Keen Duelist | G9: =IF(Carlos!D9="Não",Carlos!C9, " ") | J9: Santuário Místico | K9: =IF(Oona!D9="Não",Oona!C9, " ") | N9: High-Society Hunter | O9: =IF(Kresh!D9="Não",Kresh!C9, " ") | R9: Espada de Luz e Sombra | S9: =IF(Akiri!D9="Não",Akiri!C9, " ") | W9: =IF(Breya!D9="Não",Breya!C9, " ") -> The Mycosynth Gardens
B10: Dour Port-Mage | C10: =IF(Inalla!D10="Não",Inalla!C10, "") -> Reliquary Tower | F10: Hierofante de Elenda | G10: =IF(Carlos!D10="Não",Carlos!C10, " ") | J10: Moonlit Meditation | K10: =IF(Oona!D10="Não",Oona!C10, " ") | N10: Chandra's Ignition | O10: =IF(Kresh!D10="Não",Kresh!C10, " ") | R10: Espada de Fogo e Gelo | S10: =IF(Akiri!D10="Não",Akiri!C10, " ") | W10: =IF(Breya!D10="Não",Breya!C10, " ")
B11: Diário de Tarrian | C11: =IF(Inalla!D11="Não",Inalla!C11, "") | F11: Haliya, Guided by Light | G11: =IF(Carlos!D11="Não",Carlos!C11, " ") | J11: Jidoor, Aristocratic Capital // Overture | K11: =IF(Oona!D11="Não",Oona!C11, " ") | N11: Bugenhagen, Wise Elder | O11: =IF(Kresh!D11="Não",Kresh!C11, " ") | R11: Espada de Banquete e Fome | S11: =IF(Akiri!D11="Não",Akiri!C11, " ") | W11: =IF(Breya!D11="Não",Breya!C11, " ") -> Reflecting Pool
B12: Burnt Offering | C12: =IF(Inalla!D12="Não",Inalla!C12, "") | F12: Guia das Almas | G12: =IF(Carlos!D12="Não",Carlos!C12, " ") | J12: Invasion of Segovia | K12: =IF(Oona!D12="Não",Oona!C12, " ") | O12: =IF(Kresh!D12="Não",Kresh!C12, " ") | R12: Espada da Riqueza e do Poder | S12: =IF(Akiri!D12="Não",Akiri!C12, " ") | W12: =IF(Breya!D12="Não",Breya!C12, " ")
B13: Bojuka Bog | C13: =IF(Inalla!D13="Não",Inalla!C13, "") | F13: Giver of Runes | G13: =IF(Carlos!D13="Não",Carlos!C13, " ") -> Vault of the Archangel | K13: =IF(Oona!D13="Não",Oona!C13, " ") | O13: =IF(Kresh!D13="Não",Kresh!C13, " ") | R13: Cloud, Midgar Mercenary | S13: =IF(Akiri!D13="Não",Akiri!C13, " ") | W13: =IF(Breya!D13="Não",Breya!C13, " ")
B14: Arcane Signet | C14: =IF(Inalla!D14="Não",Inalla!C14, "") | F14: Exemplar of Light | G14: =IF(Carlos!D14="Não",Carlos!C14, " ") | K14: =IF(Oona!D14="Não",Oona!C14, " ") | O14: =IF(Kresh!D14="Não",Kresh!C14, " ") | R14: Cid, Freeflier Pilot | S14: =IF(Akiri!D14="Não",Akiri!C14, " ") | W14: =IF(Breya!D14="Não",Breya!C14, " ")
B15: Arcane Lighthouse | C15: =IF(Inalla!D15="Não",Inalla!C15, "") | F15: Evolving Wilds | G15: =IF(Carlos!D15="Não",Carlos!C15, " ") | K15: =IF(Oona!D15="Não",Oona!C15, " ") | O15: =IF(Kresh!D15="Não",Kresh!C15, " ") | S15: =IF(Akiri!D15="Não",Akiri!C15, " ") | W15: =IF(Breya!D15="Não",Breya!C15, " ")
C16: =IF(Inalla!D16="Não",Inalla!C16, "") | F16: Enduring Innocence | G16: =IF(Carlos!D16="Não",Carlos!C16, " ") | K16: =IF(Oona!D16="Não",Oona!C16, " ") | O16: =IF(Kresh!D16="Não",Kresh!C16, " ") | S16: =IF(Akiri!D16="Não",Akiri!C16, " ") | W16: =IF(Breya!D16="Não",Breya!C16, " ")
C17: =IF(Inalla!D17="Não",Inalla!C17, "") | F17: Bojuka Bog | G17: =IF(Carlos!D17="Não",Carlos!C17, " ") -> Takenuma, Charco Abandonado | K17: =IF(Oona!D17="Não",Oona!C17, " ") | O17: =IF(Kresh!D17="Não",Kresh!C17, " ") | S17: =IF(Akiri!D17="Não",Akiri!C17, " ") | W17: =IF(Breya!D17="Não",Breya!C17, " ")
C18: =IF(Inalla!D18="Não",Inalla!C18, "") | F18: Autoridade dos Cônsules | G18: =IF(Carlos!D18="Não",Carlos!C18, " ") | K18: =IF(Oona!D18="Não",Oona!C18, " ") | O18: =IF(Kresh!D18="Não",Kresh!C18, " ") | S18: =IF(Akiri!D18="Não",Akiri!C18, " ") | W18: =IF(Breya!D30="Não",Breya!C30, " ")
C19: =IF(Inalla!D19="Não",Inalla!C19, "") -> Bojuka Bog | F19: Ascensão do Avernus | G19: =IF(Carlos!D19="Não",Carlos!C19, " ") | K19: =IF(Oona!D19="Não",Oona!C19, " ") | O19: =IF(Kresh!D19="Não",Kresh!C19, " ") | S19: =IF(Akiri!D19="Não",Akiri!C19, " ") | W19: =IF(Breya!D19="Não",Breya!C19, " ")
C20: =IF(Inalla!D20="Não",Inalla!C20, "") -> Arcane Lighthouse | G20: =IF(Carlos!D20="Não",Carlos!C20, " ") | K20: =IF(Oona!D20="Não",Oona!C20, " ") | O20: =IF(Kresh!D20="Não",Kresh!C20, " ") | S20: =IF(Akiri!D20="Não",Akiri!C20, " ") | W20: =IF(Breya!D20="Não",Breya!C20, " ")
C21: =IF(Inalla!D21="Não",Inalla!C21, "") | G21: =IF(Carlos!D21="Não",Carlos!C21, " ") | K21: =IF(Oona!D21="Não",Oona!C21, " ") | O21: =IF(Kresh!D21="Não",Kresh!C21, " ") | S21: =IF(Akiri!D21="Não",Akiri!C21, " ") | W21: =IF(Breya!D22="Não",Breya!C22, " ")
C22: =IF(Inalla!D22="Não",Inalla!C22, "") | G22: =IF(Carlos!D22="Não",Carlos!C22, " ") | K22: =IF(Oona!D22="Não",Oona!C22, " ") | O22: =IF(Kresh!D22="Não",Kresh!C22, " ") | S22: =IF(Akiri!D22="Não",Akiri!C22, " ") | W22: =IF(Breya!D24="Não",Breya!C24, " ")
C23: =IF(Inalla!D23="Não",Inalla!C23, "") -> Glasspool Mimic | G23: =IF(Carlos!D23="Não",Carlos!C23, " ") | K23: =IF(Oona!D23="Não",Oona!C23, " ") | O23: =IF(Kresh!D23="Não",Kresh!C23, " ") | S23: =IF(Akiri!D23="Não",Akiri!C23, " ") | W23: =IF(Breya!D23="Não",Breya!C23, " ")
C24: =IF(Inalla!D24="Não",Inalla!C24, "") | G24: =IF(Carlos!D24="Não",Carlos!C24, " ") | K24: =IF(Oona!D24="Não",Oona!C24, " ") | O24: =IF(Kresh!D24="Não",Kresh!C24, " ") | S24: =IF(Akiri!D24="Não",Akiri!C24, " ") | W24: =IF(Breya!D31="Não",Breya!C31, " ") -> Adagia, Windswept Bastion
C25: =IF(Inalla!D25="Não",Inalla!C25, "") | G25: =IF(Carlos!D25="Não",Carlos!C25, " ") -> Evolving Wilds | K25: =IF(Oona!D25="Não",Oona!C25, " ") | O25: =IF(Kresh!D25="Não",Kresh!C25, " ") | S25: =IF(Akiri!D25="Não",Akiri!C25, " ") | W25: =IF(Breya!D32="Não",Breya!C32, " ")
C26: =IF(Inalla!D26="Não",Inalla!C26, "") | G26: =IF(Carlos!D26="Não",Carlos!C26, " ") | K26: =IF(Oona!D26="Não",Oona!C26, " ") | O26: =IF(Kresh!D26="Não",Kresh!C26, " ") | S26: =IF(Akiri!D26="Não",Akiri!C26, " ") | W26: =IF(Breya!D33="Não",Breya!C33, " ")
C27: =IF(Inalla!D27="Não",Inalla!C27, "") | G27: =IF(Carlos!D27="Não",Carlos!C27, " ") | K27: =IF(Oona!D27="Não",Oona!C27, " ") | O27: =IF(Kresh!D27="Não",Kresh!C27, " ") | S27: =IF(Akiri!D27="Não",Akiri!C27, " ") | W27: =IF(Breya!D25="Não",Breya!C25, " ")
C28: =IF(Inalla!D28="Não",Inalla!C28, "") | G28: =IF(Carlos!D28="Não",Carlos!C28, " ") | K28: =IF(Oona!D28="Não",Oona!C28, " ") | O28: =IF(Kresh!D28="Não",Kresh!C28, " ") | S28: =IF(Akiri!D28="Não",Akiri!C28, " ") | W28: =IF(Breya!D29="Não",Breya!C29, " ")
C29: =IF(Inalla!D29="Não",Inalla!C29, "") | G29: =IF(Carlos!D29="Não",Carlos!C29, " ") | K29: =IF(Oona!D29="Não",Oona!C29, " ") | O29: =IF(Kresh!D29="Não",Kresh!C29, " ") | S29: =IF(Akiri!D29="Não",Akiri!C29, " ") | W29: =IF(Breya!D34="Não",Breya!C34, " ")
C30: =IF(Inalla!D30="Não",Inalla!C30, "") | G30: =IF(Carlos!D30="Não",Carlos!C30, " ") | K30: =IF(Oona!D30="Não",Oona!C30, " ") | O30: =IF(Kresh!D30="Não",Kresh!C30, " ") | S30: =IF(Akiri!D30="Não",Akiri!C30, " ") | W30: =IF(Breya!D35="Não",Breya!C35, " ")
C31: =IF(Inalla!D31="Não",Inalla!C31, "") | G31: =IF(Carlos!D31="Não",Carlos!C31, " ") | K31: =IF(Oona!D31="Não",Oona!C31, " ") | O31: =IF(Kresh!D31="Não",Kresh!C31, " ") | S31: =IF(Akiri!D31="Não",Akiri!C31, " ") | W31: =IF(Breya!D21="Não",Breya!C21, " ")
C32: =IF(Inalla!D32="Não",Inalla!C32, "") | G32: =IF(Carlos!D32="Não",Carlos!C32, " ") | K32: =IF(Oona!D32="Não",Oona!C32, " ") | O32: =IF(Kresh!D32="Não",Kresh!C32, " ") | S32: =IF(Akiri!D32="Não",Akiri!C32, " ") | W32: =IF(Breya!D26="Não",Breya!C26, " ")
C33: =IF(Inalla!D33="Não",Inalla!C33, "") | G33: =IF(Carlos!D33="Não",Carlos!C33, " ") | K33: =IF(Oona!D33="Não",Oona!C33, " ") | O33: =IF(Kresh!D33="Não",Kresh!C33, " ") | S33: =IF(Akiri!D33="Não",Akiri!C33, " ") | W33: =IF(Breya!D28="Não",Breya!C28, " ")
C34: =IF(Inalla!D34="Não",Inalla!C34, "") | G34: =IF(Carlos!D34="Não",Carlos!C34, " ") | K34: =IF(Oona!D34="Não",Oona!C34, " ") | O34: =IF(Kresh!D34="Não",Kresh!C34, " ") | S34: =IF(Akiri!D34="Não",Akiri!C34, " ") | W34: =IF(Breya!D36="Não",Breya!C36, " ")
C35: =IF(Inalla!D35="Não",Inalla!C35, "") | G35: =IF(Carlos!D35="Não",Carlos!C35, " ") | K35: =IF(Oona!D35="Não",Oona!C35, " ") | O35: =IF(Kresh!D35="Não",Kresh!C35, " ") | S35: =IF(Akiri!D35="Não",Akiri!C35, " ") | W35: =IF(Breya!D27="Não",Breya!C27, " ")
C36: =IF(Inalla!D36="Não",Inalla!C36, "") | G36: =IF(Carlos!D36="Não",Carlos!C36, " ") | K36: =IF(Oona!D36="Não",Oona!C36, " ") | O36: =IF(Kresh!D36="Não",Kresh!C36, " ") | S36: =IF(Akiri!D36="Não",Akiri!C36, " ") | W36: =IF(Breya!D18="Não",Breya!C18, " ")
C37: =IF(Inalla!D37="Não",Inalla!C37, "") | G37: =IF(Carlos!D37="Não",Carlos!C37, " ") | K37: =IF(Oona!D49="Não",Oona!C49, " ") -> The Eternity Elevator | O37: =IF(Kresh!D37="Não",Kresh!C37, " ") | S37: =IF(Akiri!D37="Não",Akiri!C37, " ") | W37: =IF(Breya!D37="Não",Breya!C37, " ")
C38: =IF(Inalla!D46="Não",Inalla!C46, "") | G38: =IF(Carlos!D42="Não",Carlos!C42, " ") | K38: =IF(Oona!D38="Não",Oona!C38, " ") | O38: =IF(Kresh!D38="Não",Kresh!C38, " ") | S38: =IF(Akiri!D38="Não",Akiri!C38, " ") | W38: =IF(Breya!D38="Não",Breya!C38, " ")
C39: =IF(Inalla!D47="Não",Inalla!C47, "") | G39: =IF(Carlos!D43="Não",Carlos!C43, " ") | K39: =IF(Oona!D50="Não",Oona!C50, " ") | O39: =IF(Kresh!D39="Não",Kresh!C39, " ") | S39: =IF(Akiri!D39="Não",Akiri!C39, " ") | W39: =IF(Breya!D46="Não",Breya!C46, " ")
C40: =IF(Inalla!D74="Não",Inalla!C74, "") -> Mistbind Clique | G40: =IF(Carlos!D44="Não",Carlos!C44, " ") | K40: =IF(Oona!D39="Não",Oona!C39, " ") | O40: =IF(Kresh!D40="Não",Kresh!C40, " ") | S40: =IF(Akiri!D40="Não",Akiri!C40, " ") -> Cid, Freeflier Pilot | W40: =IF(Breya!D40="Não",Breya!C40, " ")
C41: =IF(Inalla!D56="Não",Inalla!C56, "") | G41: =IF(Carlos!D45="Não",Carlos!C45, " ") | K41: =IF(Oona!D40="Não",Oona!C40, " ") | O41: =IF(Kresh!D41="Não",Kresh!C41, " ") | S41: =IF(Akiri!D41="Não",Akiri!C41, " ") | W41: =IF(Breya!D41="Não",Breya!C41, " ")
C42: =IF(Inalla!D57="Não",Inalla!C57, "") | G42: =IF(Carlos!D46="Não",Carlos!C46, " ") -> Unholy Annex // Ritual Chamber | K42: =IF(Oona!D41="Não",Oona!C41, " ") | O42: =IF(Kresh!D42="Não",Kresh!C42, " ") | S42: =IF(Akiri!D42="Não",Akiri!C42, " ") | W42: =IF(Breya!D42="Não",Breya!C42, " ")
C43: =IF(Inalla!D48="Não",Inalla!C48, "") | G43: =IF(Carlos!D47="Não",Carlos!C47, " ") -> Enduring Innocence | K43: =IF(Oona!D42="Não",Oona!C42, " ") | O43: =IF(Kresh!D43="Não",Kresh!C43, " ") | S43: =IF(Akiri!D43="Não",Akiri!C43, " ") | W43: =IF(Breya!D43="Não",Breya!C43, " ")
C44: =IF(Inalla!D49="Não",Inalla!C49, "") -> Dour Port-Mage | G44: =IF(Carlos!D48="Não",Carlos!C48, " ") -> Keen Duelist | K44: =IF(Oona!D43="Não",Oona!C43, " ") | O44: =IF(Kresh!D44="Não",Kresh!C44, " ") | S44: =IF(Akiri!D44="Não",Akiri!C44, " ") | W44: =IF(Breya!D44="Não",Breya!C44, " ")
C45: =IF(Inalla!D50="Não",Inalla!C50, "") -> Merchant of Secrets | G45: =IF(Carlos!D49="Não",Carlos!C49, " ") | K45: =IF(Oona!D44="Não",Oona!C44, " ") | O45: =IF(Kresh!D45="Não",Kresh!C45, " ") | S45: =IF(Akiri!D46="Não",Akiri!C46, " ") | W45: =IF(Breya!D45="Não",Breya!C45, " ")
C46: =IF(Inalla!D42="Não",Inalla!C42, "") -> Arcane Signet | G46: =IF(Carlos!D50="Não",Carlos!C50, " ") | K46: =IF(Oona!D51="Não",Oona!C51, " ") | O46: =IF(Kresh!D46="Não",Kresh!C46, " ") -> Bugenhagen, Wise Elder | S46: =IF(Akiri!D47="Não",Akiri!C47, " ") | W46: =IF(Breya!D84="Não",Breya!C84, " ")
C47: =IF(Inalla!D55="Não",Inalla!C55, "") | G47: =IF(Carlos!D51="Não",Carlos!C51, " ") | K47: =IF(Oona!D45="Não",Oona!C45, " ") -> Sonic Screwdriver | O47: =IF(Kresh!D47="Não",Kresh!C47, " ") | S47: =IF(Akiri!D49="Não",Akiri!C49, " ") | W47: =IF(Breya!D94="Não",Breya!C94, " ")
C48: =IF(Inalla!D72="Não",Inalla!C72, "") | G48: =IF(Carlos!D67="Não",Carlos!C67, " ") -> Guia das Almas | K48: =IF(Oona!D52="Não",Oona!C52, " ") | O48: =IF(Kresh!D48="Não",Kresh!C48, " ") | S48: =IF(Akiri!D75="Não",Akiri!C75, " ") | W48: =IF(Breya!D48="Não",Breya!C48, " ")
C49: =IF(Inalla!D73="Não",Inalla!C73, "") | G49: =IF(Carlos!D52="Não",Carlos!C52, " ") -> Exemplar of Light | K49: =IF(Oona!D53="Não",Oona!C53, " ") | O49: =IF(Kresh!D49="Não",Kresh!C49, " ") | S49: =IF(Akiri!D76="Não",Akiri!C76, " ") -> Espada de Luz e Sombra | W49: =IF(Breya!D64="Não",Breya!C64, " ")
C50: =IF(Inalla!D51="Não",Inalla!C51, "") | G50: =IF(Carlos!D38="Não",Carlos!C38, " ") | K50: =IF(Oona!D54="Não",Oona!C54, " ") | O50: =IF(Kresh!D50="Não",Kresh!C50, " ") | S50: =IF(Akiri!D50="Não",Akiri!C50, " ") | W50: =IF(Breya!D63="Não",Breya!C63, " ")
C51: =IF(Inalla!D52="Não",Inalla!C52, "") | G51: =IF(Carlos!D39="Não",Carlos!C39, " ") | K51: =IF(Oona!D46="Não",Oona!C46, " ") | O51: =IF(Kresh!D51="Não",Kresh!C51, " ") | S51: =IF(Akiri!D51="Não",Akiri!C51, " ") -> Cloud, Midgar Mercenary | W51: =IF(Breya!D50="Não",Breya!C50, " ")
C52: =IF(Inalla!D53="Não",Inalla!C53, "") | G52: =IF(Carlos!D40="Não",Carlos!C40, " ") | K52: =IF(Oona!D47="Não",Oona!C47, " ") | O52: =IF(Kresh!D52="Não",Kresh!C52, " ") | S52: =IF(Akiri!D55="Não",Akiri!C55, " ") | W52: =IF(Breya!D51="Não",Breya!C51, " ")
C53: =IF(Inalla!D54="Não",Inalla!C54, "") | G53: =IF(Carlos!D41="Não",Carlos!C41, " ") | K53: =IF(Oona!D48="Não",Oona!C48, " ") | O53: =IF(Kresh!D53="Não",Kresh!C53, " ") | S53: =IF(Akiri!D52="Não",Akiri!C52, " ") | W53: =IF(Breya!D52="Não",Breya!C52, " ")
C54: =IF(Inalla!D58="Não",Inalla!C58, "") | G54: =IF(Carlos!D53="Não",Carlos!C53, " ") | K54: =IF(Oona!D55="Não",Oona!C55, " ") | O54: =IF(Kresh!D54="Não",Kresh!C54, " ") | S54: =IF(Akiri!D53="Não",Akiri!C53, " ") | W54: =IF(Breya!D53="Não",Breya!C53, " ") -> Long-Range Sensor
C55: =IF(Inalla!D96="Não",Inalla!C96, "") | G55: =IF(Carlos!D54="Não",Carlos!C54, " ") | K55: =IF(Oona!D37="Não",Oona!C37, " ") | O55: =IF(Kresh!D55="Não",Kresh!C55, " ") | S55: =IF(Akiri!D56="Não",Akiri!C56, " ") | W55: =IF(Breya!D56="Não",Breya!C56, " ")
C56: =IF(Inalla!D59="Não",Inalla!C59, "") | G56: =IF(Carlos!D55="Não",Carlos!C55, " ") -> Giver of Runes | K56: =IF(Oona!D56="Não",Oona!C56, " ") | O56: =IF(Kresh!D56="Não",Kresh!C56, " ") | S56: =IF(Akiri!D57="Não",Akiri!C57, " ") -> Firion, Wild Rose Warrior | W56: =IF(Breya!D57="Não",Breya!C57, " ")
C57: =IF(Inalla!D60="Não",Inalla!C60, "") | G57: =IF(Carlos!D56="Não",Carlos!C56, " ") | K57: =IF(Oona!D57="Não",Oona!C57, " ") | O57: =IF(Kresh!D57="Não",Kresh!C57, " ") | S57: =IF(Akiri!D45="Não",Akiri!C45, " ") | W57: =IF(Breya!D58="Não",Breya!C58, " ")
C58: =IF(Inalla!D61="Não",Inalla!C61, "") | G58: =IF(Carlos!D57="Não",Carlos!C57, " ") | K58: =IF(Oona!D58="Não",Oona!C58, " ") | O58: =IF(Kresh!D58="Não",Kresh!C58, " ") -> Pain for All | S58: =IF(Akiri!D54="Não",Akiri!C54, " ") -> Kellan, the Fae-Blooded // Birthright Boon | W58: =IF(Breya!D59="Não",Breya!C59, " ")
C59: =IF(Inalla!D62="Não",Inalla!C62, "") | G59: =IF(Carlos!D58="Não",Carlos!C58, " ") | K59: =IF(Oona!D59="Não",Oona!C59, " ") | O59: =IF(Kresh!D59="Não",Kresh!C59, " ") | S59: =IF(Akiri!D48="Não",Akiri!C48, " ") -> Stoneforge Mystic | W59: =IF(Breya!D60="Não",Breya!C60, " ")
C60: =IF(Inalla!D63="Não",Inalla!C63, "") | G60: =IF(Carlos!D59="Não",Carlos!C59, " ") | K60: =IF(Oona!D61="Não",Oona!C61, " ") | O60: =IF(Kresh!D60="Não",Kresh!C60, " ") | S60: =IF(Akiri!D58="Não",Akiri!C58, " ") | W60: =IF(Breya!D61="Não",Breya!C61, " ")
C61: =IF(Inalla!D64="Não",Inalla!C64, "") | G61: =IF(Carlos!D60="Não",Carlos!C60, " ") -> Mother of runes | K61: =IF(Oona!D62="Não",Oona!C62, " ") -> Três Passos à Frente | O61: =IF(Kresh!D61="Não",Kresh!C61, " ") | S61: =IF(Akiri!D59="Não",Akiri!C59, " ") | W61: =IF(Breya!D65="Não",Breya!C65, " ")
C62: =IF(Inalla!D65="Não",Inalla!C65, "") | G62: =IF(Carlos!D61="Não",Carlos!C61, " ") | K62: =IF(Oona!D87="Não",Oona!C87, " ") | O62: =IF(Kresh!D62="Não",Kresh!C62, " ") | S62: =IF(Akiri!D60="Não",Akiri!C60, " ") | W62: =IF(Breya!D66="Não",Breya!C66, " ")
C63: =IF(Inalla!D80="Não",Inalla!C80, "") -> Burnt Offering | G63: =IF(Carlos!D62="Não",Carlos!C62, " ") | K63: =IF(Oona!D85="Não",Oona!C85, " ") -> Invasion of Segovia | O63: =IF(Kresh!D63="Não",Kresh!C63, " ") | S63: =IF(Akiri!D61="Não",Akiri!C61, " ") | W63: =IF(Breya!D67="Não",Breya!C67, " ")
C64: =IF(Inalla!D66="Não",Inalla!C66, "") | G64: =IF(Carlos!D63="Não",Carlos!C63, " ") | K64: =IF(Oona!D63="Não",Oona!C63, " ") | O64: =IF(Kresh!D64="Não",Kresh!C64, " ") | S64: =IF(Akiri!D62="Não",Akiri!C62, " ") | W64: =IF(Breya!D68="Não",Breya!C68, " ")
C65: =IF(Inalla!D67="Não",Inalla!C67, "") | G65: =IF(Carlos!D64="Não",Carlos!C64, " ") | K65: =IF(Oona!D60="Não",Oona!C60, " ") | O65: =IF(Kresh!D65="Não",Kresh!C65, " ") | S65: =IF(Akiri!D63="Não",Akiri!C63, " ") | W65: =IF(Breya!D55="Não",Breya!C55, " ")
C66: =IF(Inalla!D68="Não",Inalla!C68, "") | G66: =IF(Carlos!D65="Não",Carlos!C65, " ") | K66: =IF(Oona!D64="Não",Oona!C64, " ") | O66: =IF(Kresh!D66="Não",Kresh!C66, " ") | S66: =IF(Akiri!D64="Não",Akiri!C64, " ") | W66: =IF(Breya!D62="Não",Breya!C62, " ")
C67: =IF(Inalla!D70="Não",Inalla!C70, "") | G67: =IF(Carlos!D66="Não",Carlos!C66, " ") | K67: =IF(Oona!D75="Não",Oona!C75, " ") | O67: =IF(Kresh!D67="Não",Kresh!C67, " ") | S67: =IF(Akiri!D65="Não",Akiri!C65, " ") | W67: =IF(Breya!D69="Não",Breya!C69, " ")
C68: =IF(Inalla!D71="Não",Inalla!C71, "") | G68: =IF(Carlos!D68="Não",Carlos!C68, " ") | K68: =IF(Oona!D65="Não",Oona!C65, " ") | O68: =IF(Kresh!D68="Não",Kresh!C68, " ") -> Saqueador Amaldiçoado | S68: =IF(Akiri!D66="Não",Akiri!C66, " ") | W68: =IF(Breya!D70="Não",Breya!C70, " ")
C69: =IF(Inalla!D83="Não",Inalla!C83, "") | G69: =IF(Carlos!D69="Não",Carlos!C69, " ") | K69: =IF(Oona!D66="Não",Oona!C66, " ") | O69: =IF(Kresh!D69="Não",Kresh!C69, " ") | S69: =IF(Akiri!D67="Não",Akiri!C67, " ") | W69: =IF(Breya!D54="Não",Breya!C54, " ")
C70: =IF(Inalla!D69="Não",Inalla!C69, "") | G70: =IF(Carlos!D70="Não",Carlos!C70, " ") | K70: =IF(Oona!D67="Não",Oona!C67, " ") | O70: =IF(Kresh!D70="Não",Kresh!C70, " ") | S70: =IF(Akiri!D68="Não",Akiri!C68, " ") | W70: =IF(Breya!D71="Não",Breya!C71, " ")
C71: =IF(Inalla!D75="Não",Inalla!C75, "") | G71: =IF(Carlos!D71="Não",Carlos!C71, " ") | K71: =IF(Oona!D68="Não",Oona!C68, " ") | O71: =IF(Kresh!D71="Não",Kresh!C71, " ") | S71: =IF(Akiri!D69="Não",Akiri!C69, " ") | W71: =IF(Breya!D72="Não",Breya!C72, " ")
C72: =IF(Inalla!D76="Não",Inalla!C76, "") -> Negociador de Almas do Viveiro | G72: =IF(Carlos!D72="Não",Carlos!C72, " ") -> Sorin da Casa Markov | K72: =IF(Oona!D69="Não",Oona!C69, " ") | O72: =IF(Kresh!D72="Não",Kresh!C72, " ") | S72: =IF(Akiri!D70="Não",Akiri!C70, " ") | W72: =IF(Breya!D74="Não",Breya!C74, " ")
C73: =IF(Inalla!D77="Não",Inalla!C77, "") | G73: =IF(Carlos!D73="Não",Carlos!C73, " ") -> Autoridade dos Cônsules | K73: =IF(Oona!D70="Não",Oona!C70, " ") | O73: =IF(Kresh!D73="Não",Kresh!C73, " ") -> Chandra's Ignition | S73: =IF(Akiri!D71="Não",Akiri!C71, " ") | W73: =IF(Breya!D96="Não",Breya!C96, " ")
C74: =IF(Inalla!D78="Não",Inalla!C78, "") | G74: =IF(Carlos!D74="Não",Carlos!C74, " ") -> Haliya, Guided by Light | K74: =IF(Oona!D71="Não",Oona!C71, " ") | O74: =IF(Kresh!D74="Não",Kresh!C74, " ") | S74: =IF(Akiri!D72="Não",Akiri!C72, " ") | W74: =IF(Breya!D49="Não",Breya!C49, " ")
C75: =IF(Inalla!D79="Não",Inalla!C79, "") | G75: =IF(Carlos!D75="Não",Carlos!C75, " ") | K75: =IF(Oona!D72="Não",Oona!C72, " ") | O75: =IF(Kresh!D75="Não",Kresh!C75, " ") | S75: =IF(Akiri!D73="Não",Akiri!C73, " ") | W75: =IF(Breya!D77="Não",Breya!C77, " ")
C76: =IF(Inalla!D43="Não",Inalla!C43, "") | G76: =IF(Carlos!D76="Não",Carlos!C76, " ") | K76: =IF(Oona!D74="Não",Oona!C74, " ") | O76: =IF(Kresh!D76="Não",Kresh!C76, " ") | S76: =IF(Akiri!D74="Não",Akiri!C74, " ") -> Espada de Verdade e Justiça | W76: =IF(Breya!D75="Não",Breya!C75, " ")
C77: =IF(Inalla!D44="Não",Inalla!C44, "") | G77: =IF(Carlos!D77="Não",Carlos!C77, " ") | K77: =IF(Oona!D77="Não",Oona!C77, " ") | O77: =IF(Kresh!D77="Não",Kresh!C77, " ") -> Nibelheim Aflame | S77: =IF(Akiri!D77="Não",Akiri!C77, " ") -> Espada de Fogo e Gelo | W77: =IF(Breya!D79="Não",Breya!C79, " ")
C78: =IF(Inalla!D97="Não",Inalla!C97, "") | G78: =IF(Carlos!D78="Não",Carlos!C78, " ") | K78: =IF(Oona!D78="Não",Oona!C78, " ") | O78: =IF(Kresh!D78="Não",Kresh!C78, " ") | S78: =IF(Akiri!D78="Não",Akiri!C78, " ") -> Espada de Banquete e Fome | W78: =IF(Breya!D80="Não",Breya!C80, " ") -> Weapons Manufacturing
C79: =IF(Inalla!D38="Não",Inalla!C38, "") | G79: =IF(Carlos!D79="Não",Carlos!C79, " ") | K79: =IF(Oona!D79="Não",Oona!C79, " ") | O79: =IF(Kresh!D79="Não",Kresh!C79, " ") | S79: =IF(Akiri!D79="Não",Akiri!C79, " ") | W79: =IF(Breya!D39="Não",Breya!C39, " ")
C80: =IF(Inalla!D39="Não",Inalla!C39, "") | G80: =IF(Carlos!D80="Não",Carlos!C80, " ") | K80: =IF(Oona!D80="Não",Oona!C80, " ") | O80: =IF(Kresh!D80="Não",Kresh!C80, " ") | S80: =IF(Akiri!D80="Não",Akiri!C80, " ") | W80: =IF(Breya!D83="Não",Breya!C83, " ")
C81: =IF(Inalla!D40="Não",Inalla!C40, "") | G81: =IF(Carlos!D81="Não",Carlos!C81, " ") | K81: =IF(Oona!D81="Não",Oona!C81, " ") -> Season of Weaving | O81: =IF(Kresh!D81="Não",Kresh!C81, " ") | S81: =IF(Akiri!D81="Não",Akiri!C81, " ") | W81: =IF(Breya!D85="Não",Breya!C85, " ")
C82: =IF(Inalla!D41="Não",Inalla!C41, "") | G82: =IF(Carlos!D82="Não",Carlos!C82, " ") | K82: =IF(Oona!D82="Não",Oona!C82, " ") | O82: =IF(Kresh!D82="Não",Kresh!C82, " ") -> High-Society Hunter | S82: =IF(Akiri!D82="Não",Akiri!C82, " ") | W82: =IF(Breya!D95="Não",Breya!C95, " ")
C83: =IF(Inalla!D45="Não",Inalla!C45, "") | G83: =IF(Carlos!D83="Não",Carlos!C83, " ") | K83: =IF(Oona!D83="Não",Oona!C83, " ") | O83: =IF(Kresh!D83="Não",Kresh!C83, " ") | S83: =IF(Akiri!D83="Não",Akiri!C83, " ") | W83: =IF(Breya!D73="Não",Breya!C73, " ")
C84: =IF(Inalla!D88="Não",Inalla!C88, "") | G84: =IF(Carlos!D84="Não",Carlos!C84, " ") | K84: =IF(Oona!D84="Não",Oona!C84, " ") -> Unstoppable Plan | O84: =IF(Kresh!D84="Não",Kresh!C84, " ") | S84: =IF(Akiri!D86="Não",Akiri!C86, " ") | W84: =IF(Breya!D86="Não",Breya!C86, " ")
C85: =IF(Inalla!D89="Não",Inalla!C89, "") | G85: =IF(Carlos!D85="Não",Carlos!C85, " ") | K85: =IF(Oona!D86="Não",Oona!C86, " ") | O85: =IF(Kresh!D85="Não",Kresh!C85, " ") | S85: =IF(Akiri!D87="Não",Akiri!C87, " ") -> Jitte Perdida | W85: =IF(Breya!D87="Não",Breya!C87, " ")
C86: =IF(Inalla!D90="Não",Inalla!C90, "") | G86: =IF(Carlos!D86="Não",Carlos!C86, " ") | K86: =IF(Oona!D99="Não",Oona!C99, " ") | O86: =IF(Kresh!D86="Não",Kresh!C86, " ") | S86: =IF(Akiri!D84="Não",Akiri!C84, " ") -> Espada da Riqueza e do Poder | W86: =IF(Breya!D88="Não",Breya!C88, " ")
C87: =IF(Inalla!D91="Não",Inalla!C91, "") | G87: =IF(Carlos!D87="Não",Carlos!C87, " ") | K87: =IF(Oona!D88="Não",Oona!C88, " ") | O87: =IF(Kresh!D87="Não",Kresh!C87, " ") -> Jenova, Ancient Calamity | S87: =IF(Akiri!D85="Não",Akiri!C85, " ") | W87: =IF(Breya!D92="Não",Breya!C92, " ")
C88: =IF(Inalla!D92="Não",Inalla!C92, "") | G88: =IF(Carlos!D88="Não",Carlos!C88, " ") | K88: =IF(Oona!D89="Não",Oona!C89, " ") | O88: =IF(Kresh!D88="Não",Kresh!C88, " ") | S88: =IF(Akiri!D88="Não",Akiri!C88, " ") | W88: =IF(Breya!D89="Não",Breya!C89, " ")
C89: =IF(Inalla!D93="Não",Inalla!C93, "") | G89: =IF(Carlos!D89="Não",Carlos!C89, " ") | K89: =IF(Oona!D90="Não",Oona!C90, " ") | O89: =IF(Kresh!D89="Não",Kresh!C89, " ") | S89: =IF(Akiri!D89="Não",Akiri!C89, " ") | W89: =IF(Breya!D90="Não",Breya!C90, " ")
C90: =IF(Inalla!D94="Não",Inalla!C94, "") -> Saw in Half | G90: =IF(Carlos!D90="Não",Carlos!C90, " ") | K90: =IF(Oona!D91="Não",Oona!C91, " ") | O90: =IF(Kresh!D90="Não",Kresh!C90, " ") -> The Masamune | S90: =IF(Akiri!D90="Não",Akiri!C90, " ") | W90: =IF(Breya!D76="Não",Breya!C76, " ")
C91: =IF(Inalla!D98="Não",Inalla!C98, "") | G91: =IF(Carlos!D91="Não",Carlos!C91, " ") -> Ascensão do Avernus | K91: =IF(Oona!D92="Não",Oona!C92, " ") | O91: =IF(Kresh!D91="Não",Kresh!C91, " ") -> Red XIII, Proud Warrior | S91: =IF(Akiri!D91="Não",Akiri!C91, " ") | W91: =IF(Breya!D91="Não",Breya!C91, " ")
C92: =IF(Inalla!D81="Não",Inalla!C81, "") -> Molten Echoes | G92: =IF(Carlos!D92="Não",Carlos!C92, " ") | K92: =IF(Oona!D73="Não",Oona!C73, " ") | O92: =IF(Kresh!D92="Não",Kresh!C92, " ") | S92: =IF(Akiri!D92="Não",Akiri!C92, " ") -> Lightning Greaves | W92: =IF(Breya!D97="Não",Breya!C97, " ")
C93: =IF(Inalla!D100="Não",Inalla!C100, "") | G93: =IF(Carlos!D93="Não",Carlos!C93, " ") | K93: =IF(Oona!D93="Não",Oona!C93, " ") -> Scour for Scrap | O93: =IF(Kresh!D93="Não",Kresh!C93, " ") | S93: =IF(Akiri!D93="Não",Akiri!C93, " ") | W93: =IF(Breya!D78="Não",Breya!C78, " ")
C94: =IF(Inalla!D82="Não",Inalla!C82, "") | G94: =IF(Carlos!D94="Não",Carlos!C94, " ") | K94: =IF(Oona!D94="Não",Oona!C94, " ") | O94: =IF(Kresh!D94="Não",Kresh!C94, " ") | S94: =IF(Akiri!D94="Não",Akiri!C94, " ") | W94: =IF(Breya!D93="Não",Breya!C93, " ")
C95: =IF(Inalla!D84="Não",Inalla!C84, "") | G95: =IF(Carlos!D95="Não",Carlos!C95, " ") | K95: =IF(Oona!D95="Não",Oona!C95, " ") | O95: =IF(Kresh!D95="Não",Kresh!C95, " ") | S95: =IF(Akiri!D95="Não",Akiri!C95, " ") | W95: =IF(Breya!D98="Não",Breya!C98, " ")
C96: =IF(Inalla!D85="Não",Inalla!C85, "") | G96: =IF(Carlos!D96="Não",Carlos!C96, " ") | K96: =IF(Oona!D96="Não",Oona!C96, " ") | O96: =IF(Kresh!D96="Não",Kresh!C96, " ") | S96: =IF(Akiri!D96="Não",Akiri!C96, " ") | W96: =IF(Breya!D99="Não",Breya!C99, " ")
C97: =IF(Inalla!D99="Não",Inalla!C99, "") | G97: =IF(Carlos!D97="Não",Carlos!C97, " ") | K97: =IF(Oona!D97="Não",Oona!C97, " ") | O97: =IF(Kresh!D97="Não",Kresh!C97, " ") | S97: =IF(Akiri!D97="Não",Akiri!C97, " ") | W97: =IF(Breya!D100="Não",Breya!C100, " ")
C98: =IF(Inalla!D86="Não",Inalla!C86, "") | G98: =IF(Carlos!D98="Não",Carlos!C98, " ") | K98: =IF(Oona!D98="Não",Oona!C98, " ") | O98: =IF(Kresh!D98="Não",Kresh!C98, " ") | S98: =IF(Akiri!D98="Não",Akiri!C98, " ") | W98: =IF(Breya!D82="Não",Breya!C82, " ")
C99: =IF(Inalla!D87="Não",Inalla!C87, "") | G99: =IF(Carlos!D99="Não",Carlos!C99, " ") | K99: =IF(Oona!D100="Não",Oona!C100, " ") | O99: =IF(Kresh!D99="Não",Kresh!C99, " ") | S99: =IF(Akiri!D99="Não",Akiri!C99, " ") | W99: =IF(Breya!D101="Não",Breya!C101, " ")
C100: =IF(Inalla!D95="Não",Inalla!C95, "") | G100: =IF(Carlos!D100="Não",Carlos!C100, " ") | K100: =IF(Oona!D101="Não",Oona!C101, " ") | O100: =IF(Kresh!D100="Não",Kresh!C100, " ") | S100: =IF(Akiri!D100="Não",Akiri!C100, " ") | W100: =IF(Breya!D47="Não",Breya!C47, " ")
C101: =IF(Inalla!D101="Não",Inalla!C101, "") -> Diário de Tarrian | G101: =IF(Carlos!D101="Não",Carlos!C101, " ") -> Hierofante de Elenda | K101: =IF(Oona!D76="Não",Oona!C76, " ") -> Moonlit Meditation | O101: =IF(Kresh!D101="Não",Kresh!C101, " ") | S101: =IF(Akiri!D101="Não",Akiri!C101, " ") | W101: =IF(Breya!D81="Não",Breya!C81, " ") -> Daretti, Ingenious Iconoclast
...

Sheet RESUMO4
A1: Rani | E1: Sisay | I1: OWA | M1: Narset Mill | Q1: Kumena | U1: Zimone e Dina
A3: Total | B3: {=_xlfn._xlws.SORT(C3:C101,1,-1,0)} -> Xantcha, Agente Adormecida | C3: =IF(Rani!D3="Não",Rani!C3, "") -> Rogue's Passage | E3: Total | F3: {=_xlfn._xlws.SORT(G3:G101,1,-1,0)} -> Vronos, Masked Inquisitor | G3: =IF(Sisay!D3="Não",Sisay!C3, "") | I3: Total | J3: {=_xlfn._xlws.SORT(K3:K101,1,-1,0)} -> Warren Soultrader | K3: =IF(OWA!D3="Não",OWA!C3, "") | M3: Total | N3: {=_xlfn._xlws.SORT(O3:O101,1,-1,0)} -> Zellix, Sanity Flayer | O3: =IF(Narset!D3="Não",Narset!C3,"") | Q3: Total | R3: {=_xlfn._xlws.SORT(S3:S101,1,-1,0)} -> Vanquisher's Banner | S3: =IF(Kumena!D3="Não",Kumena!C3,"") -> Reliquary Tower | U3: Total | V3: {=_xlfn._xlws.SORT(W3:W101,1,-1,0)} -> Zagoth Triome | W3: =IF(Zimone!D3="Não",Zimone!C3,"")
A4: =Rani!G3 -> 20 | B4: Trenzalore Clocktower | C4: =IF(Rani!D3="Não",Rani!C3, "") -> Rogue's Passage | E4: =Sisay!G3 -> 11 | F4: Ripples of Potential | G4: =IF(Sisay!D3="Não",Sisay!C3, "") | I4: =OWA!G3 -> 7 | J4: Susur Secundi, Void Altar | K4: =IF(OWA!D3="Não",OWA!C3, "") | M4: =Narset!G3 -> 32 | N4: World at War | O4: =IF(Narset!D3="Não",Narset!C4,"") | Q4: =Kumena!G3 -> 26 | R4: Tishana, Voice of Thunder | S4: =IF(Kumena!D3="Não",Kumena!C4,"") -> Command Tower | U4: =Zimone!G3 -> 17 | V4: Three Visits | W4: =IF(Zimone!D3="Não",Zimone!C4,"")
B5: Thought Vessel | C5: =IF(Rani!D5="Não",Rani!C5, "") | F5: Oko, Thief of Crowns | G5: =IF(Sisay!D5="Não",Sisay!C5, "") | J5: Stridehangar Automaton | K5: =IF(OWA!D5="Não",OWA!C5, "") | N5: Windcrag Siege | O5: =IF(Narset!D5="Não",Narset!C5,"") | R5: Throne of the God-Pharaoh | S5: =IF(Kumena!D5="Não",Kumena!C5,"") | V5: Thousand-Year Elixir | W5: =IF(Zimone!D5="Não",Zimone!C5,"")
B6: Sulfur Falls | C6: =IF(Rani!D6="Não",Rani!C6, "") | F6: O Dínamo Peregrino | G6: =IF(Sisay!D6="Não",Sisay!C6, "") | J6: Scattered Groves | K6: =IF(OWA!D6="Não",OWA!C6, "") | N6: Training Center | O6: =IF(Narset!D6="Não",Narset!C6,"") | R6: Surgespanner | S6: =IF(Kumena!D6="Não",Kumena!C6,"") | V6: Teferi's Ageless Insight | W6: =IF(Zimone!D6="Não",Zimone!C6,"")
B7: Sol Ring | C7: =IF(Rani!D7="Não",Rani!C7, "") | F7: Nicol Bolas, God-Pharaoh | G7: =IF(Sisay!D7="Não",Sisay!C7, "") | J7: Promessa de Aclazotz | K7: =IF(OWA!D7="Não",OWA!C7, "") | N7: The Water Crystal | O7: =IF(Narset!D7="Não",Narset!C7,"") -> Sokenzan, Crucible of Defiance | R7: Summon: Leviathan | S7: =IF(Kumena!D7="Não",Kumena!C7,"") | V7: Sothera, the Supervoid | W7: =IF(Zimone!D7="Não",Zimone!C7,"")
B8: Rogue's Passage | C8: =IF(Rani!D8="Não",Rani!C8, "") -> Archway of Innovation | F8: Lolth, Rainha Aranha | G8: =IF(Sisay!D8="Não",Sisay!C8, "") | J8: Illustrious Wanderglyph | K8: =IF(OWA!D8="Não",OWA!C8, "") | N8: Subjugar a Horda | O8: =IF(Narset!D8="Não",Narset!C8,"") -> Slayers' Stronghold | R8: Stonybrook Banneret | S8: =IF(Kumena!D8="Não",Kumena!C8,"") | V8: Scalding Tarn | W8: =IF(Zimone!D8="Não",Zimone!C8,"")
B9: Rogue's Passage | C9: =IF(Rani!D9="Não",Rani!C9, "") -> Trenzalore Clocktower | F9: Kaya the Inexorable | G9: =IF(Sisay!D9="Não",Sisay!C9, "") | J9: Dollmaker's Shop // Porcelain Gallery | K9: =IF(OWA!D9="Não",OWA!C9, "") | N9: Spectator Seating | O9: =IF(Narset!D9="Não",Narset!C9,"") -> Sea of Clouds | R9: Sol Ring | S9: =IF(Kumena!D9="Não",Kumena!C9,"") | V9: Polluted Delta | W9: =IF(Zimone!D9="Não",Zimone!C9,"") -> Fabled Passage
B10: Reliquary Tower | C10: =IF(Rani!D10="Não",Rani!C10, "") -> Havengul Laboratory | F10: Karn Liberated | G10: =IF(Sisay!D10="Não",Sisay!C10, "") | K10: =IF(OWA!D10="Não",OWA!C10, "") -> Scattered Groves | N10: Spark Double | O10: =IF(Narset!D10="Não",Narset!C10,"") -> Training Center | R10: Singer of Swift Rivers | S10: =IF(Kumena!D10="Não",Kumena!C10,"") | V10: Oathsworn Vampire | W10: =IF(Zimone!D10="Não",Zimone!C10,"") -> Bala Ged Recovery
B11: Life of the Party | C11: =IF(Rani!D11="Não",Rani!C11, "") -> Bojuka Bog | F11: Freyalise, Llanowar's Fury | G11: =IF(Sisay!D11="Não",Sisay!C11, "") | K11: =IF(OWA!D11="Não",OWA!C11, "") | N11: Sol Ring | O11: =IF(Narset!D11="Não",Narset!C11,"") -> Spectator Seating | R11: Simic Charm | S11: =IF(Kumena!D11="Não",Kumena!C11,"") | V11: Misty Rainforest | W11: =IF(Zimone!D11="Não",Zimone!C11,"")
B12: Havengul Laboratory | C12: =IF(Rani!D12="Não",Rani!C12, "") -> Reliquary Tower | F12: Elspeth, Sun's Champion | G12: =IF(Sisay!D12="Não",Sisay!C12, "") | K12: =IF(OWA!D12="Não",OWA!C12, "") | N12: Sokenzan, Crucible of Defiance | O12: =IF(Narset!D12="Não",Narset!C12,"") | R12: Seahunter | S12: =IF(Kumena!D12="Não",Kumena!C12,"") | V12: Marvin, Murderous Mimic | W12: =IF(Zimone!D12="Não",Zimone!C12,"")
B13: Gallifrey Council Chamber | C13: =IF(Rani!D13="Não",Rani!C13, "") -> Access Tunnel | F13: Commodore Guff | G13: =IF(Sisay!D13="Não",Sisay!C13, "") | K13: =IF(OWA!D13="Não",OWA!C13, "") | N13: Smuggler's Share | O13: =IF(Narset!D13="Não",Narset!C13,"") -> Clifftop Retreat | R13: Reliquary Tower | S13: =IF(Kumena!D13="Não",Kumena!C13,"") | V13: Jadar, Ghoulcaller of Nephalia | W13: =IF(Zimone!D13="Não",Zimone!C13,"")
B14: Frenzied Gorespawn | C14: =IF(Rani!D14="Não",Rani!C14, "") | G14: =IF(Sisay!D14="Não",Sisay!C14, "") | K14: =IF(OWA!D14="Não",OWA!C14, "") | N14: Slayers' Stronghold | O14: =IF(Narset!D14="Não",Narset!C14,"") | R14: Metallic Mimic | S14: =IF(Kumena!D14="Não",Kumena!C14,"") | V14: Horizon Explorer | W14: =IF(Zimone!D14="Não",Zimone!C14,"") -> Zagoth Triome
B15: Fellwar Stone | C15: =IF(Rani!D15="Não",Rani!C15, "") -> Drowned Catacomb | G15: =IF(Sisay!D15="Não",Sisay!C15, "") | K15: =IF(OWA!D15="Não",OWA!C15, "") | N15: Slash the Ranks | O15: =IF(Narset!D15="Não",Narset!C15,"") | R15: Merrow Harbinger | S15: =IF(Kumena!D15="Não",Kumena!C15,"") | V15: Grave Pact | W15: =IF(Zimone!D15="Não",Zimone!C15,"")
B16: Equilíbrio de Poderes | C16: =IF(Rani!D16="Não",Rani!C16, "") -> Sulfur Falls | G16: =IF(Sisay!D16="Não",Sisay!C16, "") | K16: =IF(OWA!D16="Não",OWA!C16, "") | N16: Sea of Clouds | O16: =IF(Narset!D16="Não",Narset!C16,"") | R16: Merrow Commerce | S16: =IF(Kumena!D16="Não",Kumena!C16,"") | V16: Fabled Passage | W16: =IF(Zimone!D16="Não",Zimone!C16,"") -> Breeding Pool
B17: Dúplice Debochada | C17: =IF(Rani!D17="Não",Rani!C17, "") -> Gallifrey Council Chamber | G17: =IF(Sisay!D17="Não",Sisay!C17, "") | K17: =IF(OWA!D17="Não",OWA!C17, "") | N17: Sculpted Sunburst | O17: =IF(Narset!D17="Não",Narset!C17,"") -> Adarkar Wastes | R17: Master of the Pearl Trident | S17: =IF(Kumena!D17="Não",Kumena!C17,"") | V17: Breeding Pool | W17: =IF(Zimone!D17="Não",Zimone!C17,"")
B18: Drowned Catacomb | C18: =IF(Rani!D18="Não",Rani!C18, "") | G18: =IF(Sisay!D18="Não",Sisay!C18, "") | K18: =IF(OWA!D18="Não",OWA!C18, "") | N18: Relentless Assault | O18: =IF(Narset!D18="Não",Narset!C18,"") | R18: Lullmage Mentor | S18: =IF(Kumena!D18="Não",Kumena!C18,"") | V18: Bloodstained Mire | W18: =IF(Zimone!D18="Não",Zimone!C18,"") -> Bloodstained Mire
B19: Cyber Conversion | C19: =IF(Rani!D85="Não",Rani!C85, "") | G19: =IF(Sisay!D19="Não",Sisay!C19, "") | K19: =IF(OWA!D19="Não",OWA!C19, "") | N19: Reforge the Soul | O19: =IF(Narset!D19="Não",Narset!C19,"") | R19: Lord of Atlantis | S19: =IF(Kumena!D19="Não",Kumena!C19,"") | V19: Bala Ged Recovery | W19: =IF(Zimone!D19="Não",Zimone!C19,"") -> Scalding Tarn
B20: Counterspell | C20: =IF(Rani!D19="Não",Rani!C19, "") | G20: =IF(Sisay!D20="Não",Sisay!C20, "") | K20: =IF(OWA!D20="Não",OWA!C20, "") | N20: Psychic Corrosion | O20: =IF(Narset!D20="Não",Narset!C20,"") | R20: Kodama's Reach | S20: =IF(Kumena!D20="Não",Kumena!C20,"") | V20: Ancient Greenwarden | W20: =IF(Zimone!D20="Não",Zimone!C20,"") -> Polluted Delta
B21: Bojuka Bog | C21: =IF(Rani!D20="Não",Rani!C20, "") | G21: =IF(Sisay!D21="Não",Sisay!C21, "") | K21: =IF(OWA!D21="Não",OWA!C21, "") | N21: Monastery Siege | O21: =IF(Narset!D21="Não",Narset!C21,"") | R21: Herald of Secret Streams | S21: =IF(Kumena!D21="Não",Kumena!C21,"") | W21: =IF(Zimone!D21="Não",Zimone!C21,"")
B22: Archway of Innovation | C22: =IF(Rani!D21="Não",Rani!C21, "") | G22: =IF(Sisay!D22="Não",Sisay!C22, "") | K22: =IF(OWA!D22="Não",OWA!C22, "") | N22: Memory Erosion | O22: =IF(Narset!D22="Não",Narset!C22,"") -> Jidoor, Aristocratic Capital | R22: Harvest Season | S22: =IF(Kumena!D22="Não",Kumena!C22,"") | W22: =IF(Zimone!D22="Não",Zimone!C22,"")
B23: Access Tunnel | C23: =IF(Rani!D22="Não",Rani!C22, "") | G23: =IF(Sisay!D23="Não",Sisay!C23, "") | K23: =IF(OWA!D23="Não",OWA!C23, "") | N23: Maddening Cacophony | O23: =IF(Narset!D23="Não",Narset!C23,"") | R23: Hakbal da Alma Crescente | S23: =IF(Kumena!D23="Não",Kumena!C23,"") | W23: =IF(Zimone!D23="Não",Zimone!C23,"")
C24: =IF(Rani!D23="Não",Rani!C23, "") | G24: =IF(Sisay!D24="Não",Sisay!C24, "") | K24: =IF(OWA!D24="Não",OWA!C24, "") | N24: Lightning Greaves | O24: =IF(Narset!D24="Não",Narset!C24,"") | R24: Emperor Mihail II | S24: =IF(Kumena!D24="Não",Kumena!C24,"") | W24: =IF(Zimone!D24="Não",Zimone!C24,"")
C25: =IF(Rani!D24="Não",Rani!C24, "") | G25: =IF(Sisay!D25="Não",Sisay!C25, "") | K25: =IF(OWA!D25="Não",OWA!C25, "") | N25: Khorvath's Fury | O25: =IF(Narset!D25="Não",Narset!C25,"") | R25: Deeproot Historian | S25: =IF(Kumena!D25="Não",Kumena!C25,"") | W25: =IF(Zimone!D25="Não",Zimone!C25,"")
C26: =IF(Rani!D25="Não",Rani!C25, "") | G26: =IF(Sisay!D26="Não",Sisay!C26, "") | K26: =IF(OWA!D26="Não",OWA!C26, "") | N26: Jidoor, Aristocratic Capital | O26: =IF(Narset!D26="Não",Narset!C26,"") | R26: Coralhelm Commander | S26: =IF(Kumena!D26="Não",Kumena!C26,"") | W26: =IF(Zimone!D26="Não",Zimone!C26,"") -> Misty Rainforest
C27: =IF(Rani!D26="Não",Rani!C26, "") | G27: =IF(Sisay!D27="Não",Sisay!C27, "") | K27: =IF(OWA!D27="Não",OWA!C27, "") -> Susur Secundi, Void Altar | N27: Irenicus's Vile Duplication | O27: =IF(Narset!D27="Não",Narset!C27,"") | R27: Command Tower | S27: =IF(Kumena!D27="Não",Kumena!C27,"") | W27: =IF(Zimone!D27="Não",Zimone!C27,"")
C28: =IF(Rani!D27="Não",Rani!C27, "") | G28: =IF(Sisay!D28="Não",Sisay!C28, "") | K28: =IF(OWA!D28="Não",OWA!C28, "") | N28: Incendiary Command | O28: =IF(Narset!D28="Não",Narset!C28,"") | R28: Call to the Kindred | S28: =IF(Kumena!D28="Não",Kumena!C28,"") | W28: =IF(Zimone!D28="Não",Zimone!C28,"")
C29: =IF(Rani!D28="Não",Rani!C28, "") | G29: =IF(Sisay!D29="Não",Sisay!C29, "") | K29: =IF(OWA!D30="Não",OWA!C30, "") | N29: Ghostly Prison | O29: =IF(Narset!D29="Não",Narset!C29,"") | R29: Beast Within | S29: =IF(Kumena!D29="Não",Kumena!C29,"") | W29: =IF(Zimone!D29="Não",Zimone!C29,"")
C30: =IF(Rani!D29="Não",Rani!C29, "") | G30: =IF(Sisay!D30="Não",Sisay!C30, "") | K30: =IF(OWA!D31="Não",OWA!C31, "") | N30: Genji Glove | O30: =IF(Narset!D30="Não",Narset!C30,"") | S30: =IF(Kumena!D30="Não",Kumena!C30,"") | W30: =IF(Zimone!D30="Não",Zimone!C30,"")
C31: =IF(Rani!D30="Não",Rani!C30, "") | G31: =IF(Sisay!D31="Não",Sisay!C31, "") | K31: =IF(OWA!D32="Não",OWA!C32, "") | N31: Full Throttle | O31: =IF(Narset!D31="Não",Narset!C31,"") | S31: =IF(Kumena!D31="Não",Kumena!C31,"") | W31: =IF(Zimone!D31="Não",Zimone!C31,"")
C32: =IF(Rani!D31="Não",Rani!C31, "") | G32: =IF(Sisay!D32="Não",Sisay!C32, "") | K32: =IF(OWA!D33="Não",OWA!C33, "") | N32: Clifftop Retreat | O32: =IF(Narset!D32="Não",Narset!C32,"") | S32: =IF(Kumena!D32="Não",Kumena!C32,"") | W32: =IF(Zimone!D33="Não",Zimone!C33,"")
C33: =IF(Rani!D32="Não",Rani!C32, "") | G33: =IF(Sisay!D33="Não",Sisay!C33, "") | K33: =IF(OWA!D69="Não",OWA!C69, "") | N33: Aligned Heart | O33: =IF(Narset!D33="Não",Narset!C33,"") | S33: =IF(Kumena!D33="Não",Kumena!C33,"") | W33: =IF(Zimone!D34="Não",Zimone!C34,"")
C34: =IF(Rani!D33="Não",Rani!C33, "") | G34: =IF(Sisay!D34="Não",Sisay!C34, "") | K34: =IF(OWA!D34="Não",OWA!C34, "") | N34: Adarkar Wastes | O34: =IF(Narset!D34="Não",Narset!C34,"") | S34: =IF(Kumena!D34="Não",Kumena!C34,"") | W34: =IF(Zimone!D35="Não",Zimone!C35,"")
C35: =IF(Rani!D34="Não",Rani!C34, "") | G35: =IF(Sisay!D35="Não",Sisay!C35, "") | K35: =IF(OWA!D35="Não",OWA!C35, "") | O35: =IF(Narset!D35="Não",Narset!C35,"") | S35: =IF(Kumena!D35="Não",Kumena!C35,"") | W35: =IF(Zimone!D36="Não",Zimone!C36,"")
C36: =IF(Rani!D35="Não",Rani!C35, "") | G36: =IF(Sisay!D36="Não",Sisay!C36, "") | K36: =IF(OWA!D37="Não",OWA!C37, "") | O36: =IF(Narset!D36="Não",Narset!C36,"") | S36: =IF(Kumena!D36="Não",Kumena!C36,"") -> Sol Ring | W36: =IF(Zimone!D37="Não",Zimone!C37,"")
C37: =IF(Rani!D36="Não",Rani!C36, "") | G37: =IF(Sisay!D37="Não",Sisay!C37, "") | K37: =IF(OWA!D65="Não",OWA!C65, "") | O37: =IF(Narset!D37="Não",Narset!C37,"") | S37: =IF(Kumena!D37="Não",Kumena!C37,"") | W37: =IF(Zimone!D38="Não",Zimone!C38,"")
C38: =IF(Rani!D37="Não",Rani!C37, "") | G38: =IF(Sisay!D38="Não",Sisay!C38, "") | K38: =IF(OWA!D38="Não",OWA!C38, "") | O38: =IF(Narset!D38="Não",Narset!C38,"") -> Sol Ring | S38: =IF(Kumena!D38="Não",Kumena!C38,"") | W38: =IF(Zimone!D39="Não",Zimone!C39,"")
C39: =IF(Rani!D38="Não",Rani!C38, "") | G39: =IF(Sisay!D39="Não",Sisay!C39, "") | K39: =IF(OWA!D39="Não",OWA!C39, "") | O39: =IF(Narset!D39="Não",Narset!C39,"") | S39: =IF(Kumena!D39="Não",Kumena!C39,"") | W39: =IF(Zimone!D40="Não",Zimone!C40,"")
C40: =IF(Rani!D39="Não",Rani!C39, "") | G40: =IF(Sisay!D40="Não",Sisay!C40, "") | K40: =IF(OWA!D40="Não",OWA!C40, "") | O40: =IF(Narset!D40="Não",Narset!C40,"") | S40: =IF(Kumena!D40="Não",Kumena!C40,"") | W40: =IF(Zimone!D41="Não",Zimone!C41,"")
C41: =IF(Rani!D40="Não",Rani!C40, "") | G41: =IF(Sisay!D41="Não",Sisay!C41, "") | K41: =IF(OWA!D77="Não",OWA!C77, "") | O41: =IF(Narset!D41="Não",Narset!C41,"") | S41: =IF(Kumena!D41="Não",Kumena!C41,"") | W41: =IF(Zimone!D42="Não",Zimone!C42,"")
C42: =IF(Rani!D41="Não",Rani!C41, "") -> Sol Ring | G42: =IF(Sisay!D42="Não",Sisay!C42, "") | K42: =IF(OWA!D95="Não",OWA!C95, "") | O42: =IF(Narset!D42="Não",Narset!C42,"") | S42: =IF(Kumena!D42="Não",Kumena!C42,"") | W42: =IF(Zimone!D43="Não",Zimone!C43,"") -> Three Visits
C43: =IF(Rani!D42="Não",Rani!C42, "") | G43: =IF(Sisay!D43="Não",Sisay!C43, "") | K43: =IF(OWA!D41="Não",OWA!C41, "") | O43: =IF(Narset!D43="Não",Narset!C43,"") | S43: =IF(Kumena!D43="Não",Kumena!C43,"") -> Kodama's Reach | W43: =IF(Zimone!D44="Não",Zimone!C44,"")
C44: =IF(Rani!D43="Não",Rani!C43, "") | G44: =IF(Sisay!D44="Não",Sisay!C44, "") | K44: =IF(OWA!D42="Não",OWA!C42, "") | O44: =IF(Narset!D45="Não",Narset!C45,"") -> The Water Crystal | S44: =IF(Kumena!D44="Não",Kumena!C44,"") | W44: =IF(Zimone!D45="Não",Zimone!C45,"")
C45: =IF(Rani!D44="Não",Rani!C44, "") | G45: =IF(Sisay!D45="Não",Sisay!C45, "") | K45: =IF(OWA!D43="Não",OWA!C43, "") | O45: =IF(Narset!D46="Não",Narset!C46,"") | S45: =IF(Kumena!D45="Não",Kumena!C45,"") -> Harvest Season | W45: =IF(Zimone!D46="Não",Zimone!C46,"")
C46: =IF(Rani!D45="Não",Rani!C45, "") | G46: =IF(Sisay!D46="Não",Sisay!C46, "") | K46: =IF(OWA!D44="Não",OWA!C44, "") | O46: =IF(Narset!D47="Não",Narset!C47,"") | S46: =IF(Kumena!D46="Não",Kumena!C46,"") | W46: =IF(Zimone!D47="Não",Zimone!C47,"")
C47: =IF(Rani!D46="Não",Rani!C46, "") | G47: =IF(Sisay!D47="Não",Sisay!C47, "") | K47: =IF(OWA!D36="Não",OWA!C36, "") | O47: =IF(Narset!D48="Não",Narset!C48,"") -> Smuggler's Share | S47: =IF(Kumena!D47="Não",Kumena!C47,"") -> Vanquisher's Banner | W47: =IF(Zimone!D48="Não",Zimone!C48,"")
C48: =IF(Rani!D47="Não",Rani!C47, "") -> Fellwar Stone | G48: =IF(Sisay!D48="Não",Sisay!C48, "") | K48: =IF(OWA!D45="Não",OWA!C45, "") | O48: =IF(Narset!D93="Não",Narset!C93,"") -> Slash the Ranks | S48: =IF(Kumena!D48="Não",Kumena!C48,"") | W48: =IF(Zimone!D49="Não",Zimone!C49,"")
C49: =IF(Rani!D48="Não",Rani!C48, "") -> Thought Vessel | G49: =IF(Sisay!D49="Não",Sisay!C49, "") | K49: =IF(OWA!D74="Não",OWA!C74, "") | O49: =IF(Narset!D49="Não",Narset!C49,"") | S49: =IF(Kumena!D49="Não",Kumena!C49,"") | W49: =IF(Zimone!D50="Não",Zimone!C50,"")
C50: =IF(Rani!D49="Não",Rani!C49, "") | G50: =IF(Sisay!D50="Não",Sisay!C50, "") -> Lolth, Rainha Aranha | K50: =IF(OWA!D49="Não",OWA!C49, "") | O50: =IF(Narset!D50="Não",Narset!C50,"") -> Monastery Siege | S50: =IF(Kumena!D50="Não",Kumena!C50,"") | W50: =IF(Zimone!D51="Não",Zimone!C51,"")
C51: =IF(Rani!D50="Não",Rani!C50, "") | G51: =IF(Sisay!D51="Não",Sisay!C51, "") | K51: =IF(OWA!D50="Não",OWA!C50, "") | O51: =IF(Narset!D97="Não",Narset!C97,"") -> Sculpted Sunburst | S51: =IF(Kumena!D51="Não",Kumena!C51,"") | W51: =IF(Zimone!D52="Não",Zimone!C52,"") -> Teferi's Ageless Insight
C52: =IF(Rani!D51="Não",Rani!C51, "") | G52: =IF(Sisay!D52="Não",Sisay!C52, "") | K52: =IF(OWA!D51="Não",OWA!C51, "") | O52: =IF(Narset!D51="Não",Narset!C51,"") | S52: =IF(Kumena!D52="Não",Kumena!C52,"") -> Seahunter | W52: =IF(Zimone!D53="Não",Zimone!C53,"")
C53: =IF(Rani!D52="Não",Rani!C52, "") | G53: =IF(Sisay!D53="Não",Sisay!C53, "") | K53: =IF(OWA!D94="Não",OWA!C94, "") | O53: =IF(Narset!D52="Não",Narset!C52,"") | S53: =IF(Kumena!D53="Não",Kumena!C53,"") -> Call to the Kindred | W53: =IF(Zimone!D90="Não",Zimone!C90,"")
C54: =IF(Rani!D53="Não",Rani!C53, "") | G54: =IF(Sisay!D54="Não",Sisay!C54, "") | K54: =IF(OWA!D52="Não",OWA!C52, "") | O54: =IF(Narset!D53="Não",Narset!C53,"") | S54: =IF(Kumena!D54="Não",Kumena!C54,"") | W54: =IF(Zimone!D54="Não",Zimone!C54,"")
C55: =IF(Rani!D54="Não",Rani!C54, "") | G55: =IF(Sisay!D55="Não",Sisay!C55, "") -> Commodore Guff | K55: =IF(OWA!D53="Não",OWA!C53, "") | O55: =IF(Narset!D54="Não",Narset!C54,"") | S55: =IF(Kumena!D55="Não",Kumena!C55,"") | W55: =IF(Zimone!D55="Não",Zimone!C55,"")
C56: =IF(Rani!D55="Não",Rani!C55, "") | G56: =IF(Sisay!D56="Não",Sisay!C56, "") | K56: =IF(OWA!D54="Não",OWA!C54, "") | O56: =IF(Narset!D55="Não",Narset!C55,"") | S56: =IF(Kumena!D56="Não",Kumena!C56,"") | W56: =IF(Zimone!D56="Não",Zimone!C56,"")
C57: =IF(Rani!D56="Não",Rani!C56, "") | G57: =IF(Sisay!D57="Não",Sisay!C57, "") | K57: =IF(OWA!D64="Não",OWA!C64, "") | O57: =IF(Narset!D56="Não",Narset!C56,"") -> Incendiary Command | S57: =IF(Kumena!D57="Não",Kumena!C57,"") | W57: =IF(Zimone!D57="Não",Zimone!C57,"")
C58: =IF(Rani!D57="Não",Rani!C57, "") | G58: =IF(Sisay!D58="Não",Sisay!C58, "") | K58: =IF(OWA!D87="Não",OWA!C87, "") | O58: =IF(Narset!D57="Não",Narset!C57,"") -> Khorvath's Fury | S58: =IF(Kumena!D58="Não",Kumena!C58,"") | W58: =IF(Zimone!D58="Não",Zimone!C58,"")
C59: =IF(Rani!D58="Não",Rani!C58, "") | G59: =IF(Sisay!D59="Não",Sisay!C59, "") | K59: =IF(OWA!D46="Não",OWA!C46, "") | O59: =IF(Narset!D58="Não",Narset!C58,"") -> Reforge the Soul | S59: =IF(Kumena!D59="Não",Kumena!C59,"") | W59: =IF(Zimone!D59="Não",Zimone!C59,"")
C60: =IF(Rani!D59="Não",Rani!C59, "") | G60: =IF(Sisay!D60="Não",Sisay!C60, "") | K60: =IF(OWA!D29="Não",OWA!C29, "") | O60: =IF(Narset!D59="Não",Narset!C59,"") | S60: =IF(Kumena!D60="Não",Kumena!C60,"") -> Tishana, Voice of Thunder | W60: =IF(Zimone!D60="Não",Zimone!C60,"") -> Jadar, Ghoulcaller of Nephalia
C61: =IF(Rani!D60="Não",Rani!C60, "") | G61: =IF(Sisay!D61="Não",Sisay!C61, "") | K61: =IF(OWA!D48="Não",OWA!C48, "") | O61: =IF(Narset!D60="Não",Narset!C60,"") | S61: =IF(Kumena!D61="Não",Kumena!C61,"") | W61: =IF(Zimone!D61="Não",Zimone!C61,"")
C62: =IF(Rani!D61="Não",Rani!C61, "") | G62: =IF(Sisay!D62="Não",Sisay!C62, "") -> Kaya the Inexorable | K62: =IF(OWA!D55="Não",OWA!C55, "") | O62: =IF(Narset!D61="Não",Narset!C61,"") | S62: =IF(Kumena!D62="Não",Kumena!C62,"") -> Emperor Mihail II | W62: =IF(Zimone!D62="Não",Zimone!C62,"")
C63: =IF(Rani!D62="Não",Rani!C62, "") | G63: =IF(Sisay!D63="Não",Sisay!C63, "") -> Elspeth, Sun's Champion | K63: =IF(OWA!D56="Não",OWA!C56, "") | O63: =IF(Narset!D44="Não",Narset!C44,"") | S63: =IF(Kumena!D63="Não",Kumena!C63,"") -> Coralhelm Commander | W63: =IF(Zimone!D63="Não",Zimone!C63,"")
C64: =IF(Rani!D63="Não",Rani!C63, "") | G64: =IF(Sisay!D64="Não",Sisay!C64, "") -> Freyalise, Llanowar's Fury | K64: =IF(OWA!D57="Não",OWA!C57, "") | O64: =IF(Narset!D62="Não",Narset!C62,"") | S64: =IF(Kumena!D64="Não",Kumena!C64,"") -> Hakbal da Alma Crescente | W64: =IF(Zimone!D65="Não",Zimone!C65,"")
C65: =IF(Rani!D64="Não",Rani!C64, "") -> Counterspell | G65: =IF(Sisay!D65="Não",Sisay!C65, "") | K65: =IF(OWA!D58="Não",OWA!C58, "") | O65: =IF(Narset!D63="Não",Narset!C63,"") | S65: =IF(Kumena!D65="Não",Kumena!C65,"") -> Master of the Pearl Trident | W65: =IF(Zimone!D66="Não",Zimone!C66,"")
C66: =IF(Rani!D65="Não",Rani!C65, "") -> Cyber Conversion | G66: =IF(Sisay!D66="Não",Sisay!C66, "") | K66: =IF(OWA!D59="Não",OWA!C59, "") | O66: =IF(Narset!D64="Não",Narset!C64,"") -> Memory Erosion | S66: =IF(Kumena!D66="Não",Kumena!C66,"") | W66: =IF(Zimone!D67="Não",Zimone!C67,"")
C67: =IF(Rani!D66="Não",Rani!C66, "") | G67: =IF(Sisay!D67="Não",Sisay!C67, "") | K67: =IF(OWA!D93="Não",OWA!C93, "") | O67: =IF(Narset!D65="Não",Narset!C65,"") | S67: =IF(Kumena!D67="Não",Kumena!C67,"") | W67: =IF(Zimone!D68="Não",Zimone!C68,"")
C68: =IF(Rani!D67="Não",Rani!C67, "") | G68: =IF(Sisay!D68="Não",Sisay!C68, "") | K68: =IF(OWA!D60="Não",OWA!C60, "") | O68: =IF(Narset!D95="Não",Narset!C95,"") -> Subjugar a Horda | S68: =IF(Kumena!D68="Não",Kumena!C68,"") | W68: =IF(Zimone!D69="Não",Zimone!C69,"")
C69: =IF(Rani!D68="Não",Rani!C68, "") | G69: =IF(Sisay!D69="Não",Sisay!C69, "") | K69: =IF(OWA!D61="Não",OWA!C61, "") | O69: =IF(Narset!D96="Não",Narset!C96,"") | S69: =IF(Kumena!D69="Não",Kumena!C69,"") -> Lord of Atlantis | W69: =IF(Zimone!D32="Não",Zimone!C32,"")
C70: =IF(Rani!D69="Não",Rani!C69, "") | G70: =IF(Sisay!D70="Não",Sisay!C70, "") | K70: =IF(OWA!D91="Não",OWA!C91, "") | O70: =IF(Narset!D66="Não",Narset!C66,"") -> Psychic Corrosion | S70: =IF(Kumena!D70="Não",Kumena!C70,"") -> Metallic Mimic | W70: =IF(Zimone!D70="Não",Zimone!C70,"")
C71: =IF(Rani!D70="Não",Rani!C70, "") | G71: =IF(Sisay!D71="Não",Sisay!C71, "") | K71: =IF(OWA!D62="Não",OWA!C62, "") -> Warren Soultrader | O71: =IF(Narset!D67="Não",Narset!C67,"") | S71: =IF(Kumena!D71="Não",Kumena!C71,"") | W71: =IF(Zimone!D71="Não",Zimone!C71,"")
C72: =IF(Rani!D71="Não",Rani!C71, "") | G72: =IF(Sisay!D72="Não",Sisay!C72, "") -> Oko, Thief of Crowns | K72: =IF(OWA!D66="Não",OWA!C66, "") -> Dollmaker's Shop // Porcelain Gallery | O72: =IF(Narset!D68="Não",Narset!C68,"") | S72: =IF(Kumena!D72="Não",Kumena!C72,"") -> Lullmage Mentor | W72: =IF(Zimone!D72="Não",Zimone!C72,"") -> Oathsworn Vampire
C73: =IF(Rani!D72="Não",Rani!C72, "") | G73: =IF(Sisay!D73="Não",Sisay!C73, "") -> Nicol Bolas, God-Pharaoh | K73: =IF(OWA!D88="Não",OWA!C88, "") -> Promessa de Aclazotz | O73: =IF(Narset!D69="Não",Narset!C69,"") | S73: =IF(Kumena!D73="Não",Kumena!C73,"") | W73: =IF(Zimone!D73="Não",Zimone!C73,"")
C74: =IF(Rani!D73="Não",Rani!C73, "") | G74: =IF(Sisay!D74="Não",Sisay!C74, "") -> Vronos, Masked Inquisitor | K74: =IF(OWA!D67="Não",OWA!C67, "") | O74: =IF(Narset!D70="Não",Narset!C70,"") | S74: =IF(Kumena!D74="Não",Kumena!C74,"") | W74: =IF(Zimone!D74="Não",Zimone!C74,"")
C75: =IF(Rani!D74="Não",Rani!C74, "") | G75: =IF(Sisay!D75="Não",Sisay!C75, "") | K75: =IF(OWA!D79="Não",OWA!C79, "") | O75: =IF(Narset!D71="Não",Narset!C71,"") | S75: =IF(Kumena!D75="Não",Kumena!C75,"") -> Stonybrook Banneret | W75: =IF(Zimone!D75="Não",Zimone!C75,"")
C76: =IF(Rani!D75="Não",Rani!C75, "") | G76: =IF(Sisay!D76="Não",Sisay!C76, "") | K76: =IF(OWA!D85="Não",OWA!C85, "") | O76: =IF(Narset!D72="Não",Narset!C72,"") -> Maddening Cacophony | S76: =IF(Kumena!D76="Não",Kumena!C76,"") | W76: =IF(Zimone!D76="Não",Zimone!C76,"")
C77: =IF(Rani!D76="Não",Rani!C76, "") | G77: =IF(Sisay!D77="Não",Sisay!C77, "") -> Karn Liberated | K77: =IF(OWA!D68="Não",OWA!C68, "") | O77: =IF(Narset!D73="Não",Narset!C73,"") | S77: =IF(Kumena!D77="Não",Kumena!C77,"") -> Herald of Secret Streams | W77: =IF(Zimone!D77="Não",Zimone!C77,"") -> Horizon Explorer
C78: =IF(Rani!D77="Não",Rani!C77, "") | G78: =IF(Sisay!D78="Não",Sisay!C78, "") | K78: =IF(OWA!D84="Não",OWA!C84, "") | O78: =IF(Narset!D79="Não",Narset!C79,"") -> Spark Double | S78: =IF(Kumena!D78="Não",Kumena!C78,"") | W78: =IF(Zimone!D78="Não",Zimone!C78,"") -> Ancient Greenwarden
C79: =IF(Rani!D78="Não",Rani!C78, "") | G79: =IF(Sisay!D79="Não",Sisay!C79, "") | K79: =IF(OWA!D71="Não",OWA!C71, "") | O79: =IF(Narset!D74="Não",Narset!C74,"") | S79: =IF(Kumena!D79="Não",Kumena!C79,"") -> Merrow Harbinger | W79: =IF(Zimone!D79="Não",Zimone!C79,"")
C80: =IF(Rani!D79="Não",Rani!C79, "") -> Dúplice Debochada | G80: =IF(Sisay!D80="Não",Sisay!C80, "") | K80: =IF(OWA!D72="Não",OWA!C72, "") | O80: =IF(Narset!D75="Não",Narset!C75,"") | S80: =IF(Kumena!D80="Não",Kumena!C80,"") | W80: =IF(Zimone!D80="Não",Zimone!C80,"")
C81: =IF(Rani!D80="Não",Rani!C80, "") | G81: =IF(Sisay!D81="Não",Sisay!C81, "") | K81: =IF(OWA!D75="Não",OWA!C75, "") | O81: =IF(Narset!D76="Não",Narset!C76,"") -> Zellix, Sanity Flayer | S81: =IF(Kumena!D81="Não",Kumena!C81,"") | W81: =IF(Zimone!D81="Não",Zimone!C81,"")
C82: =IF(Rani!D81="Não",Rani!C81, "") -> Life of the Party | G82: =IF(Sisay!D82="Não",Sisay!C82, "") | K82: =IF(OWA!D76="Não",OWA!C76, "") | O82: =IF(Narset!D77="Não",Narset!C77,"") | S82: =IF(Kumena!D82="Não",Kumena!C82,"") | W82: =IF(Zimone!D82="Não",Zimone!C82,"")
C83: =IF(Rani!D82="Não",Rani!C82, "") | G83: =IF(Sisay!D83="Não",Sisay!C83, "") | K83: =IF(OWA!D73="Não",OWA!C73, "") | O83: =IF(Narset!D80="Não",Narset!C80,"") | S83: =IF(Kumena!D83="Não",Kumena!C83,"") -> Deeproot Historian | W83: =IF(Zimone!D83="Não",Zimone!C83,"")
C84: =IF(Rani!D83="Não",Rani!C83, "") -> Frenzied Gorespawn | G84: =IF(Sisay!D84="Não",Sisay!C84, "") | K84: =IF(OWA!D81="Não",OWA!C81, "") | O84: =IF(Narset!D99="Não",Narset!C99,"") -> World at War | S84: =IF(Kumena!D84="Não",Kumena!C84,"") -> Surgespanner | W84: =IF(Zimone!D64="Não",Zimone!C64,"")
C85: =IF(Rani!D84="Não",Rani!C84, "") | G85: =IF(Sisay!D85="Não",Sisay!C85, "") | K85: =IF(OWA!D70="Não",OWA!C70, "") -> Stridehangar Automaton | O85: =IF(Narset!D78="Não",Narset!C78,"") -> Aligned Heart | S85: =IF(Kumena!D85="Não",Kumena!C85,"") -> Singer of Swift Rivers | W85: =IF(Zimone!D84="Não",Zimone!C84,"")
C86: =IF(Rani!D86="Não",Rani!C86, "") | G86: =IF(Sisay!D86="Não",Sisay!C86, "") | K86: =IF(OWA!D80="Não",OWA!C80, "") | O86: =IF(Narset!D81="Não",Narset!C81,"") -> Windcrag Siege | S86: =IF(Kumena!D86="Não",Kumena!C86,"") | W86: =IF(Zimone!D85="Não",Zimone!C85,"") -> Grave Pact
C87: =IF(Rani!D87="Não",Rani!C87, "") | G87: =IF(Sisay!D87="Não",Sisay!C87, "") -> Ripples of Potential | K87: =IF(OWA!D82="Não",OWA!C82, "") | O87: =IF(Narset!D82="Não",Narset!C82,"") | S87: =IF(Kumena!D87="Não",Kumena!C87,"") -> Throne of the God-Pharaoh | W87: =IF(Zimone!D86="Não",Zimone!C86,"") -> Sothera, the Supervoid
C88: =IF(Rani!D88="Não",Rani!C88, "") | G88: =IF(Sisay!D88="Não",Sisay!C88, "") -> O Dínamo Peregrino | K88: =IF(OWA!D86="Não",OWA!C86, "") | O88: =IF(Narset!D83="Não",Narset!C83,"") -> Irenicus's Vile Duplication | S88: =IF(Kumena!D88="Não",Kumena!C88,"") | W88: =IF(Zimone!D87="Não",Zimone!C87,"")
C89: =IF(Rani!D89="Não",Rani!C89, "") | G89: =IF(Sisay!D89="Não",Sisay!C89, "") | K89: =IF(OWA!D83="Não",OWA!C83, "") -> Illustrious Wanderglyph | O89: =IF(Narset!D84="Não",Narset!C84,"") | S89: =IF(Kumena!D89="Não",Kumena!C89,"") -> Simic Charm | W89: =IF(Zimone!D88="Não",Zimone!C88,"")
C90: =IF(Rani!D90="Não",Rani!C90, "") | G90: =IF(Sisay!D90="Não",Sisay!C90, "") | K90: =IF(OWA!D89="Não",OWA!C89, "") | O90: =IF(Narset!D85="Não",Narset!C85,"") | S90: =IF(Kumena!D90="Não",Kumena!C90,"") | W90: =IF(Zimone!D89="Não",Zimone!C89,"")
C91: =IF(Rani!D91="Não",Rani!C91, "") | G91: =IF(Sisay!D91="Não",Sisay!C91, "") | K91: =IF(OWA!D92="Não",OWA!C92, "") | O91: =IF(Narset!D86="Não",Narset!C86,"") | S91: =IF(Kumena!D91="Não",Kumena!C91,"") | W91: =IF(Zimone!D91="Não",Zimone!C91,"")
C92: =IF(Rani!D92="Não",Rani!C92, "") | G92: =IF(Sisay!D92="Não",Sisay!C92, "") | K92: =IF(OWA!D47="Não",OWA!C47, "") | O92: =IF(Narset!D87="Não",Narset!C87,"") | S92: =IF(Kumena!D92="Não",Kumena!C92,"") | W92: =IF(Zimone!D92="Não",Zimone!C92,"")
C93: =IF(Rani!D93="Não",Rani!C93, "") -> Xantcha, Agente Adormecida | G93: =IF(Sisay!D93="Não",Sisay!C93, "") | K93: =IF(OWA!D96="Não",OWA!C96, "") | O93: =IF(Narset!D88="Não",Narset!C88,"") | S93: =IF(Kumena!D93="Não",Kumena!C93,"") -> Merrow Commerce | W93: =IF(Zimone!D93="Não",Zimone!C93,"")
C94: =IF(Rani!D94="Não",Rani!C94, "") | G94: =IF(Sisay!D94="Não",Sisay!C94, "") | K94: =IF(OWA!D78="Não",OWA!C78, "") | O94: =IF(Narset!D94="Não",Narset!C94,"") | S94: =IF(Kumena!D94="Não",Kumena!C94,"") -> Summon: Leviathan | W94: =IF(Zimone!D94="Não",Zimone!C94,"")
C95: =IF(Rani!D95="Não",Rani!C95, "") | G95: =IF(Sisay!D95="Não",Sisay!C95, "") | K95: =IF(OWA!D97="Não",OWA!C97, "") | O95: =IF(Narset!D89="Não",Narset!C89,"") -> Lightning Greaves | S95: =IF(Kumena!D95="Não",Kumena!C95,"") | W95: =IF(Zimone!D95="Não",Zimone!C95,"")
C96: =IF(Rani!D96="Não",Rani!C96, "") | G96: =IF(Sisay!D96="Não",Sisay!C96, "") | K96: =IF(OWA!D90="Não",OWA!C90, "") | O96: =IF(Narset!D90="Não",Narset!C90,"") | S96: =IF(Kumena!D96="Não",Kumena!C96,"") | W96: =IF(Zimone!D96="Não",Zimone!C96,"")
C97: =IF(Rani!D97="Não",Rani!C97, "") | G97: =IF(Sisay!D97="Não",Sisay!C97, "") | K97: =IF(OWA!D98="Não",OWA!C98, "") | O97: =IF(Narset!D91="Não",Narset!C91,"") | S97: =IF(Kumena!D97="Não",Kumena!C97,"") | W97: =IF(Zimone!D97="Não",Zimone!C97,"")
C98: =IF(Rani!D98="Não",Rani!C98, "") | G98: =IF(Sisay!D98="Não",Sisay!C98, "") | K98: =IF(OWA!D63="Não",OWA!C63, "") | O98: =IF(Narset!D92="Não",Narset!C92,"") -> Ghostly Prison | S98: =IF(Kumena!D98="Não",Kumena!C98,"") | W98: =IF(Zimone!D98="Não",Zimone!C98,"") -> Marvin, Murderous Mimic
C99: =IF(Rani!D99="Não",Rani!C99, "") | G99: =IF(Sisay!D99="Não",Sisay!C99, "") | K99: =IF(OWA!D99="Não",OWA!C99, "") | O99: =IF(Narset!D98="Não",Narset!C98,"") -> Full Throttle | S99: =IF(Kumena!D99="Não",Kumena!C99,"") | W99: =IF(Zimone!D99="Não",Zimone!C99,"")
C100: =IF(Rani!D100="Não",Rani!C100, "") -> Equilíbrio de Poderes | G100: =IF(Sisay!D100="Não",Sisay!C100, "") | K100: =IF(OWA!D100="Não",OWA!C100, "") | O100: =IF(Narset!D100="Não",Narset!C100,"") -> Relentless Assault | S100: =IF(Kumena!D100="Não",Kumena!C100,"") | W100: =IF(Zimone!D100="Não",Zimone!C100,"")
C101: =IF(Rani!D101="Não",Rani!C101, "") | G101: =IF(Sisay!D101="Não",Sisay!C101, "") | K101: =IF(OWA!D101="Não",OWA!C101, "") | O101: =IF(Narset!D101="Não",Narset!C101,"") -> Genji Glove | S101: =IF(Kumena!D101="Não",Kumena!C101,"") -> Beast Within | W101: =IF(Zimone!D101="Não",Zimone!C101,"") -> Thousand-Year Elixir
...

Sheet RESUMO5
A1: Baylen | E1: Tayan | I1: Jhoira Bichão | M1: Piratas
A3: Total | B3: {=_xlfn._xlws.SORT(C3:C101,1,-1,0)} -> Warleader's Call | C3: =IF(Baylen!D3="Não",Baylen!C3, "") | E3: Total | F3: {=_xlfn._xlws.SORT(G3:G101,1,-1,0)} -> Zack Fair | G3: =IF(Tayam!D3="Não",Tayam!C3, "") -> Tayam, Enigma Luminoso | I3: Total | J3: {=_xlfn._xlws.SORT(K3:K101,1,-1,0)} -> Valfenda | K3: =IF(Bichão!D3="Não",Bichão!C3, "") | M3: Total | N3: {=_xlfn._xlws.SORT(O3:O101,1,-1,0)} -> Xorn | O3: =IF(Piratas!D3="Não",Piratas!C3, "")
A4: =Baylen!G3 -> 34 | B4: Virtue of Loyalty | C4: =IF(Baylen!D3="Não",Baylen!C3, "") | E4: =Tayam!G4 -> 56 | F4: Winding Constrictor | G4: =IF(Tayam!D5="Não",Tayam!C5, "") -> Llanowar Reborn | I4: =Bichão!G4 -> 20 | J4: Ulamog's Dreadsire | K4: =IF(Bichão!D5="Não",Bichão!C5, "") | M4: =Piratas!G5 -> 71 | N4: Weftstalker Ardent | O4: =IF(Piratas!D6="Não",Piratas!C6, "") -> Access Tunnel
B5: Time of Need | C5: =IF(Baylen!D5="Não",Baylen!C5, "") -> The Shire | F5: Warden of the Grove | G5: =IF(Tayam!D6="Não",Tayam!C6, "") -> Command Tower | J5: Ulamog, o Profanador | K5: =IF(Bichão!D6="Não",Bichão!C6, "") | N5: Warkite Marauder | O5: =IF(Piratas!D7="Não",Piratas!C7, "") -> Bojuka Bog
B6: The Shire | C6: =IF(Baylen!D6="Não",Baylen!C6, "") | F6: Unbreakable Formation | G6: =IF(Tayam!D7="Não",Tayam!C7, "") -> Exotic Orchard | J6: Trenzalore Clocktower | K6: =IF(Bichão!D7="Não",Bichão!C7, "") -> Exotic Orchard | N6: Walk the Plank | O6: =IF(Piratas!D8="Não",Piratas!C8, "") -> Treasure Vault
B7: Teferi's Protection | C7: =IF(Baylen!D7="Não",Baylen!C7, "") -> Castle Ardenvale | F7: Tromell, Seymour's Butler | G7: =IF(Tayam!D8="Não",Tayam!C8, "") -> Canopy Vista | J7: Thran Dynamo | K7: =IF(Bichão!D8="Não",Bichão!C8, "") | N7: Vaan, Street Thief | O7: =IF(Piratas!D9="Não",Piratas!C9, "") -> Reliquary Tower
B8: Sunscorched Divide | C8: =IF(Baylen!D8="Não",Baylen!C8, "") | F8: Thunderous Velocipede | G8: =IF(Tayam!D9="Não",Tayam!C9, "") -> Deceptive Landscape | J8: Thought Vessel | K8: =IF(Bichão!D9="Não",Bichão!C9, "") -> Valfenda | N8: Treasure Vault | O8: =IF(Piratas!D10="Não",Piratas!C10, "") -> Mines of Moria
B9: Sheltering Landscape | C9: =IF(Baylen!D9="Não",Baylen!C9, "") -> Gavony Township | F9: Thran Vigil | G9: =IF(Tayam!D10="Não",Tayam!C10, "") | J9: The Tenth Doctor | K9: =IF(Bichão!D10="Não",Bichão!C10, "") -> Mistrise Village | N9: Treasure Map | O9: =IF(Piratas!D11="Não",Piratas!C11, "") -> Archway of Innovation
B10: Seedborn Muse | C10: =IF(Baylen!D10="Não",Baylen!C10, "") -> Rogue's Passage | F10: Terrasymbiosis | G10: =IF(Tayam!D11="Não",Tayam!C11, "") | J10: Temple of the False God | K10: =IF(Bichão!D11="Não",Bichão!C11, "") -> Temple of the False God | N10: Timestream Navigator | O10: =IF(Piratas!D12="Não",Piratas!C12, "") -> Exotic Orchard
B11: Second Harvest | C11: =IF(Baylen!D11="Não",Baylen!C11, "") | F11: Tayam, Enigma Luminoso | G11: =IF(Tayam!D12="Não",Tayam!C12, "") | J11: Sol Talisman | K11: =IF(Bichão!D12="Não",Bichão!C12, "") -> Trenzalore Clocktower | N11: Time Sieve | O11: =IF(Piratas!D13="Não",Piratas!C13, "") -> Command Tower
B12: Rogue's Passage | C12: =IF(Baylen!D12="Não",Baylen!C12, "") | F12: Syr Vondam, Sunstar Exemplar | G12: =IF(Tayam!D13="Não",Tayam!C13, "") | J12: Rotating Fireplace | K12: =IF(Bichão!D13="Não",Bichão!C13, "") | N12: The Indomitable | O12: =IF(Piratas!D14="Não",Piratas!C14, "") -> Path of Ancestry
B13: Purphoros, God of the Forge | C13: =IF(Baylen!D13="Não",Baylen!C13, "") -> Sheltering Landscape | F13: Summon: Ixion | G13: =IF(Tayam!D14="Não",Tayam!C14, "") | J13: Rise of the Eldrazi | K13: =IF(Bichão!D14="Não",Bichão!C14, "") | N13: Temple of Malice | O13: =IF(Piratas!D15="Não",Piratas!C15, "")
B14: Prosperous Partnership | C14: =IF(Baylen!D14="Não",Baylen!C14, "") -> Mossfire Valley | F14: Summon: Fenrir | G14: =IF(Tayam!D15="Não",Tayam!C15, "") | J14: Mox Tantalite | K14: =IF(Bichão!D15="Não",Bichão!C15, "") | N14: Temple of Epiphany | O14: =IF(Piratas!D16="Não",Piratas!C16, "") -> Secluded Courtyard
B15: Nature's Lore | C15: =IF(Baylen!D15="Não",Baylen!C15, "") | F15: Stocking the Pantry | G15: =IF(Tayam!D16="Não",Tayam!C16, "") | J15: Mistrise Village | K15: =IF(Bichão!D16="Não",Bichão!C16, "") | N15: Temple of Deceit | O15: =IF(Piratas!D17="Não",Piratas!C17, "") -> Seething Landscape
B16: Mossfire Valley | C16: =IF(Baylen!D16="Não",Baylen!C16, "") -> Sunscorched Divide | F16: Sphere Grid | G16: =IF(Tayam!D17="Não",Tayam!C17, "") | J16: Kozilek, the Broken Reality | K16: =IF(Bichão!D17="Não",Bichão!C17, "") | N16: Storm the Vault | O16: =IF(Piratas!D18="Não",Piratas!C18, "") -> Spire of Industry
... B22: Generous Gift | C22: =IF(Baylen!D22="Não",Baylen!C22, "") -> Karplusan Forest | F22: Reyhan, Last of the Abzan | G22: =IF(Tayam!D23="Não",Tayam!C23, "") | J22: Arcane Signet | K22: =IF(Bichão!D23="Não",Bichão!C23, "") | N22: Seething Landscape | O22: =IF(Piratas!D24="Não",Piratas!C24, "") -> Fabled Passage
B23: Gavony Township | C23: =IF(Baylen!D23="Não",Baylen!C23, "") -> Brushland | F23: Retribution of the Ancients | G23: =IF(Tayam!D24="Não",Tayam!C24, "") | K23: =IF(Bichão!D24="Não",Bichão!C24, "") | N23: Secluded Courtyard | O23: =IF(Piratas!D25="Não",Piratas!C25, "")
B24: Farseek | C24: =IF(Baylen!D24="Não",Baylen!C24, "") | F24: Resourceful Defense | G24: =IF(Tayam!D25="Não",Tayam!C25, "") | K24: =IF(Bichão!D25="Não",Bichão!C25, "") | N24: Reliquary Tower | O24: =IF(Piratas!D26="Não",Piratas!C26, "")
B25: Farmer Cotton | C25: =IF(Baylen!D25="Não",Baylen!C25, "") | F25: Protection Magic | G25: =IF(Tayam!D26="Não",Tayam!C26, "") | K25: =IF(Bichão!D26="Não",Bichão!C26, "") | N25: Reckless Fireweaver | O25: =IF(Piratas!D27="Não",Piratas!C27, "")
B26: Exalted Sunborn | C26: =IF(Baylen!D26="Não",Baylen!C26, "") | F26: Patrolling Peacemaker | G26: =IF(Tayam!D27="Não",Tayam!C27, "") | K26: =IF(Bichão!D27="Não",Bichão!C27, "") | N26: Ramirez DePietro, Pillager | O26: =IF(Piratas!D28="Não",Piratas!C28, "")
B27: Elesh Norn | C27: =IF(Baylen!D27="Não",Baylen!C27, "") | F27: Ozolith, the Shattered Spire | G27: =IF(Tayam!D28="Não",Tayam!C28, "") | K27: =IF(Bichão!D28="Não",Bichão!C28, "") | N27: Rain of Riches | O27: =IF(Piratas!D29="Não",Piratas!C29, "")
B28: Crash the Party | C28: =IF(Baylen!D28="Não",Baylen!C28, "") | F28: Metastatic Evangel | G28: =IF(Tayam!D29="Não",Tayam!C29, "") | K28: =IF(Bichão!D29="Não",Bichão!C29, "") | N28: Professional Face-Breaker | O28: =IF(Piratas!D30="Não",Piratas!C30, "")
B29: Cinder Glade | C29: =IF(Baylen!D29="Não",Baylen!C29, "") | F29: Managorger Hydra | G29: =IF(Tayam!D30="Não",Tayam!C30, "") | K29: =IF(Bichão!D30="Não",Bichão!C30, "") | N29: Path of Ancestry | O29: =IF(Piratas!D31="Não",Piratas!C31, "")
B30: Champions from Beyond | C30: =IF(Baylen!D30="Não",Baylen!C30, "") | F30: Maester Seymour | G30: =IF(Tayam!D31="Não",Tayam!C31, "") | K30: =IF(Bichão!D31="Não",Bichão!C31, "") | N30: Mines of Moria | O30: =IF(Piratas!D32="Não",Piratas!C32, "")
B31: Castle Ardenvale | C31: =IF(Baylen!D31="Não",Baylen!C31, "") | F31: Llanowar Reborn | G31: =IF(Tayam!D32="Não",Tayam!C32, "") | K31: =IF(Bichão!D32="Não",Bichão!C32, "") | N31: Malcolm, the Eyes | O31: =IF(Piratas!D33="Não",Piratas!C33, "")
B32: Canopy Vista | C32: =IF(Baylen!D32="Não",Baylen!C32, "") | F32: Lae'zel, Vlaakith's Champion | G32: =IF(Tayam!D33="Não",Tayam!C33, "") | K32: =IF(Bichão!D33="Não",Bichão!C33, "") | N32: Malcolm, Alluring Scoundrel | O32: =IF(Piratas!D34="Não",Piratas!C34, "")
B33: Brushland | C33: =IF(Baylen!D33="Não",Baylen!C33, "") | F33: Kutzil, Malamet Exemplar | G33: =IF(Tayam!D34="Não",Tayam!C34, "") | K33: =IF(Bichão!D34="Não",Bichão!C34, "") | N33: Lightning-Rig Crew | O33: =IF(Piratas!D35="Não",Piratas!C35, "")
B34: Boros Charm | C34: =IF(Baylen!D34="Não",Baylen!C34, "") | F34: Inspiring Call | G34: =IF(Tayam!D35="Não",Tayam!C35, "") | K34: =IF(Bichão!D35="Não",Bichão!C35, "") | N34: Leyline of Transformation | O34: =IF(Piratas!D36="Não",Piratas!C36, "")
... B36: Artifact Mutation | C36: =IF(Baylen!D36="Não",Baylen!C36, "") | F36: Hollowmurk Siege | G36: =IF(Tayam!D37="Não",Tayam!C37, "") | K36: =IF(Bichão!D37="Não",Bichão!C37, "") | N36: Kitesail Larcenist | O36: =IF(Piratas!D38="Não",Piratas!C38, "")
C37: =IF(Baylen!D37="Não",Baylen!C37, "") | F37: Hardened Scales | G37: =IF(Tayam!D38="Não",Tayam!C38, "") | K37: =IF(Bichão!D38="Não",Bichão!C38, "") | N37: Kitesail Freebooter | O37: =IF(Piratas!D39="Não",Piratas!C39, "")
C38: =IF(Baylen!D38="Não",Baylen!C38, "") | F38: Gyre Sage | G38: =IF(Tayam!D39="Não",Tayam!C39, "") -> Song of Freyalise | K38: =IF(Bichão!D39="Não",Bichão!C39, "") | N38: Invert Polarity | O38: =IF(Piratas!D40="Não",Piratas!C40, "")
C39: =IF(Baylen!D39="Não",Baylen!C39, "") -> Nature's Lore | F39: Felothar, Dawn of the Abzan | G39: =IF(Tayam!D40="Não",Tayam!C40, "") -> Incubation Druid | K39: =IF(Bichão!D40="Não",Bichão!C40, "") -> Arcane Signet | N39: Hostage Taker | O39: =IF(Piratas!D41="Não",Piratas!C41, "")
C40: =IF(Baylen!D40="Não",Baylen!C40, "") -> Farseek | F40: Exotic Orchard | G40: =IF(Tayam!D41="Não",Tayam!C41, "") -> Gyre Sage | K40: =IF(Bichão!D41="Não",Bichão!C41, "") -> Izzet Signet | N40: Hedron Detonator | O40: =IF(Piratas!D42="Não",Piratas!C42, "")
C41: =IF(Baylen!D41="Não",Baylen!C41, "") | F41: Duskshell Crawler | G41: =IF(Tayam!D42="Não",Tayam!C42, "") -> Summon: Fenrir | K41: =IF(Bichão!D42="Não",Bichão!C42, "") -> Thought Vessel | N41: Guild Artisan | O41: =IF(Piratas!D43="Não",Piratas!C43, "") -> The Indomitable
C42: =IF(Baylen!D42="Não",Baylen!C42, "") | F42: Devoted Druid | G42: =IF(Tayam!D43="Não",Tayam!C43, "") -> Devoted Druid | K42: =IF(Bichão!D43="Não",Bichão!C43, "") | N42: Go for the Throat | O42: =IF(Piratas!D44="Não",Piratas!C44, "") -> Bident of Thassa
C43: =IF(Baylen!D43="Não",Baylen!C43, "") | F43: Dever Além da Morte | G43: =IF(Tayam!D44="Não",Tayam!C44, "") -> Rishkar, Peema Renegade | K43: =IF(Bichão!D44="Não",Bichão!C44, "") -> Gilded Lotus | N43: Glint-Horn Buccaneer | O43: =IF(Piratas!D45="Não",Piratas!C45, "") -> Treasure Map
C44: =IF(Baylen!D44="Não",Baylen!C44, "") -> Time of Need | F44: Deceptive Landscape | G44: =IF(Tayam!D46="Não",Tayam!C46, "") | K44: =IF(Bichão!D45="Não",Bichão!C45, "") -> Rotating Fireplace | N44: Gemcutter Buccaneer | O44: =IF(Piratas!D46="Não",Piratas!C46, "") -> Coastal Piracy
C45: =IF(Baylen!D45="Não",Baylen!C45, "") | F45: Conclave Mentor | G45: =IF(Tayam!D47="Não",Tayam!C47, "") -> Sakura-Tribe Elder | K45: =IF(Bichão!D46="Não",Bichão!C46, "") -> Sol Talisman | N45: Forerunner of the Coalition | O45: =IF(Piratas!D47="Não",Piratas!C47, "") -> Distant Melody
C46: =IF(Baylen!D46="Não",Baylen!C46, "") -> Jetmir, Nexus of Revels | F46: Command Tower | G46: =IF(Tayam!D48="Não",Tayam!C48, "") -> Armored Scrapgorger | K46: =IF(Bichão!D47="Não",Bichão!C47, "") -> Thran Dynamo | N46: Fabled Passage | O46: =IF(Piratas!D48="Não",Piratas!C48, "") -> Laughing Jasper Flint
C47: =IF(Baylen!D80="Não",Baylen!C80, "") -> Marcha dos Canonizados | F47: Champion of Lambholt | G47: =IF(Tayam!D49="Não",Tayam!C49, "") -> Terrasymbiosis | K47: =IF(Bichão!D48="Não",Bichão!C48, "") -> Mox Tantalite | N47: Exotic Orchard | O47: =IF(Piratas!D49="Não",Piratas!C49, "") -> Forerunner of the Coalition
C48: =IF(Baylen!D47="Não",Baylen!C47, "") -> Purphoros, God of the Forge | F48: Canopy Vista | G48: =IF(Tayam!D50="Não",Tayam!C50, "") -> Stocking the Pantry | K48: =IF(Bichão!D49="Não",Bichão!C49, "") | N48: Evolving Wilds | O48: =IF(Piratas!D50="Não",Piratas!C50, "")
C49: =IF(Baylen!D48="Não",Baylen!C48, "") -> Warleader's Call | F49: Cankerbloom | G49: =IF(Tayam!D51="Não",Tayam!C51, "") -> Kutzil, Malamet Exemplar | K49: =IF(Bichão!D50="Não",Bichão!C50, "") | N49: Emberwilde Captain | O49: =IF(Piratas!D51="Não",Piratas!C51, "") -> Malcolm, the Eyes
C50: =IF(Baylen!D49="Não",Baylen!C49, "") | F50: Bulwark Ox | G50: =IF(Tayam!D52="Não",Tayam!C52, "") | K50: =IF(Bichão!D51="Não",Bichão!C51, "") | N50: Distant Melody | O50: =IF(Piratas!D52="Não",Piratas!C52, "") -> Emberwilde Captain
C51: =IF(Baylen!D50="Não",Baylen!C50, "") | F51: Branching Evolution | G51: =IF(Tayam!D53="Não",Tayam!C53, "") | K51: =IF(Bichão!D52="Não",Bichão!C52, "") | N51: Departed Deckhand | O51: =IF(Piratas!D53="Não",Piratas!C53, "") -> Leyline of Transformation
C52: =IF(Baylen!D51="Não",Baylen!C51, "") -> Prosperous Partnership | F52: Botanical Brawler | G52: =IF(Tayam!D54="Não",Tayam!C54, "") -> Maester Seymour | K52: =IF(Bichão!D53="Não",Bichão!C53, "") -> Rise of the Eldrazi | N52: Deadeye Tracker | O52: =IF(Piratas!D54="Não",Piratas!C54, "") -> Captain's Hook
C53: =IF(Baylen!D52="Não",Baylen!C52, "") | F53: Basking Broodscale | G53: =IF(Tayam!D59="Não",Tayam!C59, "") -> Felothar, Dawn of the Abzan | K53: =IF(Bichão!D54="Não",Bichão!C54, "") | N53: Cutthroat Negotiator | O53: =IF(Piratas!D55="Não",Piratas!C55, "")
C54: =IF(Baylen!D53="Não",Baylen!C53, "") | F54: Arwen, Weaver of Hope | G54: =IF(Tayam!D60="Não",Tayam!C60, "") -> Arwen, Weaver of Hope | K54: =IF(Bichão!D55="Não",Bichão!C55, "") | N54: Command Tower | O54: =IF(Piratas!D56="Não",Piratas!C56, "") -> Spyglass Siren
C55: =IF(Baylen!D54="Não",Baylen!C54, "") | F55: Armored Scrapgorger | G55: =IF(Tayam!D61="Não",Tayam!C61, "") -> Anafenza, Kin-Tree Spirit | K55: =IF(Bichão!D56="Não",Bichão!C56, "") | N55: Coercive Recruiter | O55: =IF(Piratas!D57="Não",Piratas!C57, "") -> Changeling Outcast
C56: =IF(Baylen!D55="Não",Baylen!C55, "") | F56: Ardbert, Warrior of Darkness | G56: =IF(Tayam!D62="Não",Tayam!C62, "") -> Botanical Brawler | K56: =IF(Bichão!D57="Não",Bichão!C57, "") | N56: Coastline Marauders | O56: =IF(Piratas!D58="Não",Piratas!C58, "") -> Siren Stormtamer
C57: =IF(Baylen!D56="Não",Baylen!C56, "") -> Crash the Party | F57: Anafenza, Kin-Tree Spirit | G57: =IF(Tayam!D63="Não",Tayam!C63, "") -> Champion of Lambholt | K57: =IF(Bichão!D58="Não",Bichão!C58, "") | N57: Coastal Piracy | O57: =IF(Piratas!D59="Não",Piratas!C59, "") -> Kitesail Freebooter
C58: =IF(Baylen!D57="Não",Baylen!C57, "") | F58: Abzan Falconer | G58: =IF(Tayam!D64="Não",Tayam!C64, "") -> Warden of the Grove | K58: =IF(Bichão!D59="Não",Bichão!C59, "") | N58: Changeling Outcast | O58: =IF(Piratas!D60="Não",Piratas!C60, "") -> Departed Deckhand
C59: =IF(Baylen!D60="Não",Baylen!C60, "") | G59: =IF(Tayam!D65="Não",Tayam!C65, "") -> Managorger Hydra | K59: =IF(Bichão!D60="Não",Bichão!C60, "") | N59: Captain's Hook | O59: =IF(Piratas!D61="Não",Piratas!C61, "") -> Malcolm, Alluring Scoundrel
C60: =IF(Baylen!D59="Não",Baylen!C59, "") -> Second Harvest | G60: =IF(Tayam!D66="Não",Tayam!C66, "") | K60: =IF(Bichão!D61="Não",Bichão!C61, "") | N60: Captain Vargus Wrath | O60: =IF(Piratas!D62="Não",Piratas!C62, "") -> Warkite Marauder
C61: =IF(Baylen!D61="Não",Baylen!C61, "") | G61: =IF(Tayam!D67="Não",Tayam!C67, "") -> Duskshell Crawler | K61: =IF(Bichão!D62="Não",Bichão!C62, "") | N61: Captain Storm, Cosmium Raider | O61: =IF(Piratas!D63="Não",Piratas!C63, "") -> Broadside Bombardiers
C62: =IF(Baylen!D62="Não",Baylen!C62, "") | G62: =IF(Tayam!D68="Não",Tayam!C68, "") -> Shelinda, Yevon Acolyte | K62: =IF(Bichão!D63="Não",Bichão!C63, "") | N62: Broadside Bombardiers | O62: =IF(Piratas!D64="Não",Piratas!C64, "") -> Breeches, Eager Pillager
C63: =IF(Baylen!D63="Não",Baylen!C63, "") | G63: =IF(Tayam!D69="Não",Tayam!C69, "") -> Ardbert, Warrior of Darkness | K63: =IF(Bichão!D64="Não",Bichão!C64, "") | N63: Breeches, the Blastmaker | O63: =IF(Piratas!D65="Não",Piratas!C65, "") -> Kitesail Larcenist
C64: =IF(Baylen!D64="Não",Baylen!C64, "") | G64: =IF(Tayam!D74="Não",Tayam!C74, "") -> Metastatic Evangel | K64: =IF(Bichão!D65="Não",Bichão!C65, "") -> Emrakul, um Novo Mundo | N64: Breeches, Eager Pillager | O64: =IF(Piratas!D66="Não",Piratas!C66, "") -> Storm Fleet Negotiator
C65: =IF(Baylen!D65="Não",Baylen!C65, "") | G65: =IF(Tayam!D75="Não",Tayam!C75, "") -> Conclave Mentor | K65: =IF(Bichão!D66="Não",Bichão!C66, "") | N65: Breeches, Brazen Plunderer | O65: =IF(Piratas!D67="Não",Piratas!C67, "") -> Cutthroat Negotiator
C66: =IF(Baylen!D66="Não",Baylen!C66, "") | G66: =IF(Tayam!D76="Não",Tayam!C76, "") -> Reyhan, Last of the Abzan | K66: =IF(Bichão!D67="Não",Bichão!C67, "") | N66: Bojuka Bog | O66: =IF(Piratas!D68="Não",Piratas!C68, "") -> Coastline Marauders
C67: =IF(Baylen!D67="Não",Baylen!C67, "") | G67: =IF(Tayam!D77="Não",Tayam!C77, "") -> Lae'zel, Vlaakith's Champion | K67: =IF(Bichão!D68="Não",Bichão!C68, "") -> Kozilek, the Broken Reality | N67: Bident of Thassa | O67: =IF(Piratas!D69="Não",Piratas!C69, "") -> Admiral Beckett Brass
C68: =IF(Baylen!D68="Não",Baylen!C68, "") | G68: =IF(Tayam!D78="Não",Tayam!C78, "") -> Branching Evolution | K68: =IF(Bichão!D69="Não",Bichão!C69, "") | N68: Back in Town | O68: =IF(Piratas!D70="Não",Piratas!C70, "") -> Captain Vargus Wrath
C69: =IF(Baylen!D69="Não",Baylen!C69, "") | G69: =IF(Tayam!D79="Não",Tayam!C79, "") -> Ozolith, the Shattered Spire | K69: =IF(Bichão!D70="Não",Bichão!C70, "") | N69: Archway of Innovation | O69: =IF(Piratas!D71="Não",Piratas!C71, "") -> Captain Storm, Cosmium Raider
C70: =IF(Baylen!D70="Não",Baylen!C70, "") | G70: =IF(Tayam!D80="Não",Tayam!C80, "") | K70: =IF(Bichão!D71="Não",Bichão!C71, "") -> Ulamog, o Profanador | N70: Amphin Mutineer | O70: =IF(Piratas!D72="Não",Piratas!C72, "") -> Gemcutter Buccaneer
C71: =IF(Baylen!D71="Não",Baylen!C71, "") | G71: =IF(Tayam!D81="Não",Tayam!C81, "") -> Hardened Scales | K71: =IF(Bichão!D72="Não",Bichão!C72, "") | N71: Admiral Beckett Brass | O71: =IF(Piratas!D73="Não",Piratas!C73, "") -> Timestream Navigator
C72: =IF(Baylen!D72="Não",Baylen!C72, "") | G72: =IF(Tayam!D82="Não",Tayam!C82, "") -> Basking Broodscale | K72: =IF(Bichão!D73="Não",Bichão!C73, "") | N72: Access Tunnel | O72: =IF(Piratas!D74="Não",Piratas!C74, "") -> Ramirez DePietro, Pillager
C73: =IF(Baylen!D73="Não",Baylen!C73, "") | G73: =IF(Tayam!D83="Não",Tayam!C83, "") -> Winding Constrictor | K73: =IF(Bichão!D74="Não",Bichão!C74, "") | O73: =IF(Piratas!D75="Não",Piratas!C75, "") -> Glint-Horn Buccaneer
C74: =IF(Baylen!D74="Não",Baylen!C74, "") -> Jacked Rabbit | G74: =IF(Tayam!D84="Não",Tayam!C84, "") -> Resourceful Defense | K74: =IF(Bichão!D75="Não",Bichão!C75, "") | O74: =IF(Piratas!D76="Não",Piratas!C76, "") -> Breeches, the Blastmaker
C75: =IF(Baylen!D75="Não",Baylen!C75, "") | G75: =IF(Tayam!D85="Não",Tayam!C85, "") -> Scholar of New Horizons | K75: =IF(Bichão!D76="Não",Bichão!C76, "") | O75: =IF(Piratas!D77="Não",Piratas!C77, "") -> Breeches, Brazen Plunderer
C76: =IF(Baylen!D76="Não",Baylen!C76, "") | G76: =IF(Tayam!D86="Não",Tayam!C86, "") -> Hollowmurk Siege | K76: =IF(Bichão!D77="Não",Bichão!C77, "") | O76: =IF(Piratas!D78="Não",Piratas!C78, "") -> Coercive Recruiter
C77: =IF(Baylen!D77="Não",Baylen!C77, "") | G77: =IF(Tayam!D70="Não",Tayam!C70, "") -> Abzan Falconer | K77: =IF(Bichão!D78="Não",Bichão!C78, "") | O77: =IF(Piratas!D79="Não",Piratas!C79, "") -> Lightning-Rig Crew
C78: =IF(Baylen!D78="Não",Baylen!C78, "") -> Farmer Cotton | G78: =IF(Tayam!D71="Não",Tayam!C71, "") | K78: =IF(Bichão!D79="Não",Bichão!C79, "") | O78: =IF(Piratas!D80="Não",Piratas!C80, "") -> Amphin Mutineer
C79: =IF(Baylen!D79="Não",Baylen!C79, "") -> Champions from Beyond | G79: =IF(Tayam!D72="Não",Tayam!C72, "") -> Thran Vigil | K79: =IF(Bichão!D80="Não",Bichão!C80, "") | O79: =IF(Piratas!D81="Não",Piratas!C81, "") -> Hedron Detonator
C80: =IF(Baylen!D81="Não",Baylen!C81, "") | G80: =IF(Tayam!D73="Não",Tayam!C73, "") -> Patrolling Peacemaker | K80: =IF(Bichão!D81="Não",Bichão!C81, "") | O80: =IF(Piratas!D82="Não",Piratas!C82, "") -> Weftstalker Ardent
C81: =IF(Baylen!D58="Não",Baylen!C58, "") -> Exalted Sunborn | G81: =IF(Tayam!D55="Não",Tayam!C55, "") -> Thunderous Velocipede | K81: =IF(Bichão!D82="Não",Bichão!C82, "") -> Ulamog's Dreadsire | O81: =IF(Piratas!D83="Não",Piratas!C83, "") -> Reckless Fireweaver
C82: =IF(Baylen!D82="Não",Baylen!C82, "") -> Boros Charm | G82: =IF(Tayam!D56="Não",Tayam!C56, "") -> Sphere Grid | K82: =IF(Bichão!D83="Não",Bichão!C83, "") | O82: =IF(Piratas!D84="Não",Piratas!C84, "")
C83: =IF(Baylen!D83="Não",Baylen!C83, "") -> Teferi's Protection | G83: =IF(Tayam!D57="Não",Tayam!C57, "") -> Tromell, Seymour's Butler | K83: =IF(Bichão!D84="Não",Bichão!C84, "") | O83: =IF(Piratas!D85="Não",Piratas!C85, "") -> Xorn
C84: =IF(Baylen!D84="Não",Baylen!C84, "") | G84: =IF(Tayam!D58="Não",Tayam!C58, "") | K84: =IF(Bichão!D85="Não",Bichão!C85, "") | O84: =IF(Piratas!D86="Não",Piratas!C86, "")
C85: =IF(Baylen!D85="Não",Baylen!C85, "") | G85: =IF(Tayam!D87="Não",Tayam!C87, "") -> Protection Magic | K85: =IF(Bichão!D86="Não",Bichão!C86, "") | O85: =IF(Piratas!D87="Não",Piratas!C87, "") -> Professional Face-Breaker
C86: =IF(Baylen!D86="Não",Baylen!C86, "") -> Lightning Greaves | G86: =IF(Tayam!D88="Não",Tayam!C88, "") -> Dever Além da Morte | K86: =IF(Bichão!D87="Não",Bichão!C87, "") | O86: =IF(Piratas!D88="Não",Piratas!C88, "") -> Vaan, Street Thief
C87: =IF(Baylen!D87="Não",Baylen!C87, "") -> Virtue of Loyalty | G87: =IF(Tayam!D89="Não",Tayam!C89, "") -> Inspiring Call | K87: =IF(Bichão!D88="Não",Bichão!C88, "") | O87: =IF(Piratas!D89="Não",Piratas!C89, "") -> Back in Town
C88: =IF(Baylen!D88="Não",Baylen!C88, "") | G88: =IF(Tayam!D90="Não",Tayam!C90, "") -> Unbreakable Formation | K88: =IF(Bichão!D89="Não",Bichão!C89, "") -> The Tenth Doctor | O88: =IF(Piratas!D90="Não",Piratas!C90, "") -> Guild Artisan
C89: =IF(Baylen!D89="Não",Baylen!C89, "") -> Seedborn Muse | G89: =IF(Tayam!D91="Não",Tayam!C91, "") -> Bulwark Ox | K89: =IF(Bichão!D90="Não",Bichão!C90, "") | O89: =IF(Piratas!D91="Não",Piratas!C91, "") -> Storm the Vault
C90: =IF(Baylen!D90="Não",Baylen!C90, "") | G90: =IF(Tayam!D92="Não",Tayam!C92, "") -> Zack Fair | K90: =IF(Bichão!D91="Não",Bichão!C91, "") | O90: =IF(Piratas!D92="Não",Piratas!C92, "") -> Rain of Riches
C91: =IF(Baylen!D91="Não",Baylen!C91, "") | G91: =IF(Tayam!D93="Não",Tayam!C93, "") -> Summon: Ixion | K91: =IF(Bichão!D92="Não",Bichão!C92, "") | O91: =IF(Piratas!D93="Não",Piratas!C93, "") -> Time Sieve
C92: =IF(Baylen!D92="Não",Baylen!C92, "") | G92: =IF(Tayam!D94="Não",Tayam!C94, "") -> Cankerbloom | K92: =IF(Bichão!D93="Não",Bichão!C93, "") | O92: =IF(Piratas!D94="Não",Piratas!C94, "")
C93: =IF(Baylen!D93="Não",Baylen!C93, "") -> Elesh Norn | G93: =IF(Tayam!D95="Não",Tayam!C95, "") | K93: =IF(Bichão!D94="Não",Bichão!C94, "") | O93: =IF(Piratas!D95="Não",Piratas!C95, "")
C94: =IF(Baylen!D94="Não",Baylen!C94, "") -> Aura Mutation | G94: =IF(Tayam!D96="Não",Tayam!C96, "") | K94: =IF(Bichão!D95="Não",Bichão!C95, "") | O94: =IF(Piratas!D96="Não",Piratas!C96, "")
C95: =IF(Baylen!D95="Não",Baylen!C95, "") -> Artifact Mutation | G95: =IF(Tayam!D97="Não",Tayam!C97, "") | K95: =IF(Bichão!D96="Não",Bichão!C96, "") | O95: =IF(Piratas!D97="Não",Piratas!C97, "") -> Invert Polarity
C96: =IF(Baylen!D96="Não",Baylen!C96, "") | G96: =IF(Tayam!D98="Não",Tayam!C98, "") | K96: =IF(Bichão!D97="Não",Bichão!C97, "") | O96: =IF(Piratas!D98="Não",Piratas!C98, "") -> Walk the Plank
C97: =IF(Baylen!D97="Não",Baylen!C97, "") -> Generous Gift | G97: =IF(Tayam!D99="Não",Tayam!C99, "") -> Retribution of the Ancients | K97: =IF(Bichão!D98="Não",Bichão!C98, "") -> Inevitable Betrayal | O97: =IF(Piratas!D99="Não",Piratas!C99, "") -> Go for the Throat
C98: =IF(Baylen!D98="Não",Baylen!C98, "") | G98: =IF(Tayam!D45="Não",Tayam!C45, "") | K98: =IF(Bichão!D99="Não",Bichão!C99, "") | O98: =IF(Piratas!D100="Não",Piratas!C100, "") -> Deadeye Tracker
C99: =IF(Baylen!D99="Não",Baylen!C99, "") | G99: =IF(Tayam!D100="Não",Tayam!C100, "") | K99: =IF(Bichão!D100="Não",Bichão!C100, "") | O99: =IF(Piratas!D101="Não",Piratas!C101, "") -> Shoot the Sheriff
C100: =IF(Baylen!D100="Não",Baylen!C100, "") | G100: =IF(Tayam!D101="Não",Tayam!C101, "") -> Syr Vondam, Sunstar Exemplar | K100: =IF(Bichão!D101="Não",Bichão!C101, "") | O100: =IF(Piratas!D102="Não",Piratas!C102, "") -> Hostage Taker
C101: =IF(Baylen!D101="Não",Baylen!C101, "") | G101: =IF(Tayam!D102="Não",Tayam!C102, "") | K101: =IF(Bichão!D102="Não",Bichão!C102, "") | O101: =IF(Piratas!D103="Não",Piratas!C103, "")
C102: =IF(Baylen!D103="Não",Baylen!C103, "")
C103: =IF(Inalla!D103="Não",Inalla!C103, "")

Sheet Piratas
A1: Pirataria
A2: Função | B2: Carta Atual | C2: Carta Ideal | D2: Carta Final
A3: Commander | B3: Vial Smasher the Fierce | C3: Vial Smasher the Fierce | D3: =IF(B3=C3, "Sim", "Não") -> Sim
A4: Commander | C4: Malcolm, Navegador da Hipervisão | D4: =IF(B4=C4, "Sim", "Não") -> Não
A5: Terreno | C5: Rogue's Passage | D5: =IF(B5=C5, "Sim", "Não") -> Não | F5: Mudanças Faltando | G5: =COUNTIF(D5:D106,"Não") -> 71
A6: Terreno | C6: Access Tunnel | D6: =IF(B6=C6, "Sim", "Não") -> Não | F6: Total de Cartas | G6: =SUM(G9:G27) -> 98
A7: Terreno | C7: Bojuka Bog | D7: =IF(B7=C7, "Sim", "Não") -> Não
A8: Terreno | C8: Treasure Vault | D8: =IF(B8=C8, "Sim", "Não") -> Não | F8: Funções
A9: Terreno | C9: Reliquary Tower | D9: =IF(B9=C9, "Sim", "Não") -> Não | F9: Terreno | G9: =COUNTIF(A:A,F9) -> 37
A10: Terreno | C10: Mines of Moria | D10: =IF(B10=C10, "Sim", "Não") -> Não | F10: Planejamento | G10: =COUNTIF(A:A,F10) -> 11 | H10: Draw
A11: Terreno | C11: Archway of Innovation | D11: =IF(B11=C11, "Sim", "Não") -> Não | F11: Enlistamento | G11: =COUNTIF(A:A,F11) -> 2 | H11: Todo Mundo é Pirata
A12: Terreno | C12: Exotic Orchard | D12: =IF(B12=C12, "Sim", "Não") -> Não | F12: Marujo | G12: =COUNTIF(A:A,F12) -> 14 | H12: Piratas pra Bater
A13: Terreno | C13: Command Tower | D13: =IF(B13=C13, "Sim", "Não") -> Não | F13: Bucaneiro | G13: =COUNTIF(A:A,F13) -> 4 | H13: Pump
A14: Terreno | C14: Path of Ancestry | D14: =IF(B14=C14, "Sim", "Não") -> Não | F14: Oficial | G14: =COUNTIF(A:A,F14) -> 8 | H14: Piratas pra Putaria
A15: Terreno | B15: Unclaimed Territory | C15: Unclaimed Territory | D15: =IF(B15=C15, "Sim", "Não") -> Sim | F15: Lavagem | G15: =COUNTIF(A:A,F15) -> 4 | H15: Tesouros
A16: Terreno | C16: Secluded Courtyard | D16: =IF(B16=C16, "Sim", "Não") -> Não | F16: Recruta | G16: =COUNTIF(A:A,F16) -> 4 | H16: Dano
A17: Terreno | C17: Seething Landscape | D17: =IF(B17=C17, "Sim", "Não") -> Não | F17: Boa Vida | G17: =COUNTIF(A:A,F17) -> 8 | H17: Suporte
A18: Terreno | C18: Spire of Industry | D18: =IF(B18=C18, "Sim", "Não") -> Não | F18: Prancha | G18: =COUNTIF(A:A,F18) -> 6 | H18: Remoção
A19: Terreno | C19: Temple of Deceit | D19: =IF(B19=C19, "Sim", "Não") -> Não
A20: Terreno | C20: Temple of Malice | D20: =IF(B20=C20, "Sim", "Não") -> Não
A21: Terreno | C21: Temple of Epiphany | D21: =IF(B21=C21, "Sim", "Não") -> Não
A22: Terreno | B22: Terramorphic Expanse | C22: Terramorphic Expanse | D22: =IF(B22=C22, "Sim", "Não") -> Sim
A23: Terreno | C23: Evolving Wilds | D23: =IF(B23=C23, "Sim", "Não") -> Não
A24: Terreno | C24: Fabled Passage | D24: =IF(B24=C24, "Sim", "Não") -> Não
A25: Terreno | B25: Island | C25: Island | D25: =IF(B25=C25, "Sim", "Não") -> Sim
A26: Terreno | B26: Island | C26: Island | D26: =IF(B26=C26, "Sim", "Não") -> Sim
A27: Terreno | B27: Island | C27: Island | D27: =IF(B27=C27, "Sim", "Não") -> Sim
A28: Terreno | B28: Island | C28: Island | D28: =IF(B28=C28, "Sim", "Não") -> Sim
A29: Terreno | B29: Island | C29: Island | D29: =IF(B29=C29, "Sim", "Não") -> Sim
A30: Terreno | B30: Island | C30: Island | D30: =IF(B30=C30, "Sim", "Não") -> Sim
A31: Terreno | B31: Swamp | C31: Swamp | D31: =IF(B31=C31, "Sim", "Não") -> Sim
A32: Terreno | B32: Swamp | C32: Swamp | D32: =IF(B32=C32, "Sim", "Não") -> Sim
A33: Terreno | B33: Swamp | C33: Swamp | D33: =IF(B33=C33, "Sim", "Não") -> Sim
A34: Terreno | B34: Swamp | C34: Swamp | D34: =IF(B34=C34, "Sim", "Não") -> Sim
A35: Terreno | B35: Swamp | C35: Swamp | D35: =IF(B35=C35, "Sim", "Não") -> Sim
A36: Terreno | B36: Mountain | C36: Mountain | D36: =IF(B36=C36, "Sim", "Não") -> Sim
... A43: Planejamento | B43: Akal Pakal, First Among Equals | C43: The Indomitable | D43: =IF(B43=C43, "Sim", "Não") -> Não
A44: Planejamento | C44: Bident of Thassa | D44: =IF(B44=C44, "Sim", "Não") -> Não
A45: Planejamento | C45: Treasure Map | D45: =IF(B45=C45, "Sim", "Não") -> Não
A46: Planejamento | C46: Coastal Piracy | D46: =IF(B46=C46, "Sim", "Não") -> Não
A47: Planejamento | C47: Distant Melody | D47: =IF(B47=C47, "Sim", "Não") -> Não
A48: Planejamento | C48: Laughing Jasper Flint | D48: =IF(B48=C48, "Sim", "Não") -> Não
A49: Planejamento | C49: Forerunner of the Coalition | D49: =IF(B49=C49, "Sim", "Não") -> Não
A50: Planejamento | B50: Rogues Class | C50: Rogues Class | D50: =IF(B50=C50, "Sim", "Não") -> Sim
A51: Planejamento | C51: Malcolm, the Eyes | D51: =IF(B51=C51, "Sim", "Não") -> Não
A52: Planejamento | C52: Emberwilde Captain | D52: =IF(B52=C52, "Sim", "Não") -> Não
A53: Enlistamento | C53: Leyline of Transformation | D53: =IF(B53=C53, "Sim", "Não") -> Não
A54: Enlistamento | C54: Captain's Hook | D54: =IF(B54=C54, "Sim", "Não") -> Não
A55: Marujo | B55: Spectral Sailor | C55: Spectral Sailor | D55: =IF(B55=C55, "Sim", "Não") -> Sim
A56: Marujo | C56: Spyglass Siren | D56: =IF(B56=C56, "Sim", "Não") -> Não
A57: Marujo | C57: Changeling Outcast | D57: =IF(B57=C57, "Sim", "Não") -> Não
A58: Marujo | C58: Siren Stormtamer | D58: =IF(B58=C58, "Sim", "Não") -> Não
A59: Marujo | C59: Kitesail Freebooter | D59: =IF(B59=C59, "Sim", "Não") -> Não
A60: Marujo | C60: Departed Deckhand | D60: =IF(B60=C60, "Sim", "Não") -> Não
A61: Marujo | C61: Malcolm, Alluring Scoundrel | D61: =IF(B61=C61, "Sim", "Não") -> Não
A62: Marujo | C62: Warkite Marauder | D62: =IF(B62=C62, "Sim", "Não") -> Não
A63: Marujo | C63: Broadside Bombardiers | D63: =IF(B63=C63, "Sim", "Não") -> Não
A64: Marujo | C64: Breeches, Eager Pillager | D64: =IF(B64=C64, "Sim", "Não") -> Não
A65: Marujo | C65: Kitesail Larcenist | D65: =IF(B65=C65, "Sim", "Não") -> Não
A66: Marujo | C66: Storm Fleet Negotiator | D66: =IF(B66=C66, "Sim", "Não") -> Não
A67: Marujo | C67: Cutthroat Negotiator | D67: =IF(B67=C67, "Sim", "Não") -> Não
... A83: Recruta | C83: Reckless Fireweaver | D83: =IF(B83=C83, "Sim", "Não") -> Não
A84: Recruta | B84: Mayhem Devil | C84: Mayhem Devil | D84: =IF(B84=C84, "Sim", "Não") -> Sim
A85: Lavagem | C85: Xorn | D85: =IF(B85=C85, "Sim", "Não") -> Não
A86: Lavagem | B86: Academy Manufactor | C86: Academy Manufactor | D86: =IF(B86=C86, "Sim", "Não") -> Sim
A87: Lavagem | C87: Professional Face-Breaker | D87: =IF(B87=C87, "Sim", "Não") -> Não
A88: Lavagem | C88: Vaan, Street Thief | D88: =IF(B88=C88, "Sim", "Não") -> Não
A89: Boa Vida | C89: Back in Town | D89: =IF(B89=C89, "Sim", "Não") -> Não
A90: Boa Vida | C90: Guild Artisan | D90: =IF(B90=C90, "Sim", "Não") -> Não
A91: Boa Vida | C91: Storm the Vault | D91: =IF(B91=C91, "Sim", "Não") -> Não
A92: Boa Vida | C92: Rain of Riches | D92: =IF(B92=C92, "Sim", "Não") -> Não
A93: Boa Vida | B93: Ameoboid Changeling | C93: Time Sieve | D93: =IF(B93=C93, "Sim", "Não") -> Não
A94: Boa Vida | B94: Revel in Riches | C94: Revel in Riches | D94: =IF(B94=C94, "Sim", "Não") -> Sim
A95: Boa Vida | B95: Exsanguinate | C95: Exsanguinate | D95: =IF(B95=C95, "Sim", "Não") -> Sim
A96: Boa Vida | B96: Torment of Hailfire | C96: Torment of Hailfire | D96: =IF(B96=C96, "Sim", "Não") -> Sim
A97: Prancha | C97: Invert Polarity | D97: =IF(B97=C97, "Sim", "Não") -> Não
A98: Prancha | C98: Walk the Plank | D98: =IF(B98=C98, "Sim", "Não") -> Não
A99: Prancha | C99: Go for the Throat | D99: =IF(B99=C99, "Sim", "Não") -> Não
A100: Prancha | C100: Deadeye Tracker | D100: =IF(B100=C100, "Sim", "Não") -> Não
A101: Prancha | C101: Shoot the Sheriff | D101: =IF(B101=C101, "Sim", "Não") -> Não
A102: Prancha | C102: Hostage Taker | D102: =IF(B102=C102, "Sim", "Não") -> Não

Sheet Rani
A1: The Rani's Force
A2: Função | B2: Carta Atual | C2: Carta Ideal | D2: Carta Final
A3: Terreno | B3: Zona de Emergência | C3: Rogue's Passage | D3: =IF(B3=C3, "Sim", "Não") -> Não | F3: Mudanças Faltando | G3: =COUNTIF(D3:D105,"Não") -> 20
A4: Terreno | B4: Command Tower | C4: Command Tower | D4: =IF(B4=C4, "Sim", "Não") -> Sim | F4: Total de Cartas | G4: =SUM(G7:G25) -> 99
A5: Terreno | B5: Exotic Orchard | C5: Exotic Orchard | D5: =IF(B5=C5, "Sim", "Não") -> Sim
A6: Terreno | B6: Paisagem Infinita | C6: Paisagem Infinita | D6: =IF(B6=C6, "Sim", "Não") -> Sim | F6: Funções
A7: Terreno | B7: Kazuul's Fury | C7: Kazuul's Fury | D7: =IF(B7=C7, "Sim", "Não") -> Sim | F7: Terreno | G7: =COUNTIF(A:A,F7) -> 38
A8: Terreno | B8: Terras em Desenvolvimento | C8: Archway of Innovation | D8: =IF(B8=C8, "Sim", "Não") -> Não | F8: Ramp | G8: =COUNTIF(A:A,F8) -> 10
A9: Terreno | B9: Escória Fundida | C9: Trenzalore Clocktower | D9: =IF(B9=C9, "Sim", "Não") -> Não | F9: Draw | G9: =COUNTIF(A:A,F9) -> 8
A10: Terreno | B10: Recifes de Nau-Terror | C10: Havengul Laboratory | D10: =IF(B10=C10, "Sim", "Não") -> Não | F10: Controle | G10: =COUNTIF(A:A,F10) -> 8
A11: Terreno | B11: Charneca Estéril | C11: Bojuka Bog | D11: =IF(B11=C11, "Sim", "Não") -> Não | F11: War | G11: =COUNTIF(A:A,F11) -> 18
A12: Terreno | B12: Panorama de Grixis | C12: Reliquary Tower | D12: =IF(B12=C12, "Sim", "Não") -> Não | F12: Suporte | G12: =COUNTIF(A:A,F12) -> 17
A13: Terreno | B13: Mountain | C13: Access Tunnel | D13: =IF(B13=C13, "Sim", "Não") -> Não
A14: Terreno | B14: Dragonskull Summit | C14: Dragonskull Summit | D14: =IF(B14=C14, "Sim", "Não") -> Sim
A15: Terreno | B15: Swamp | C15: Drowned Catacomb | D15: =IF(B15=C15, "Sim", "Não") -> Não
A16: Terreno | B16: Island | C16: Sulfur Falls | D16: =IF(B16=C16, "Sim", "Não") -> Não
A17: Terreno | B17: Island | C17: Gallifrey Council Chamber | D17: =IF(B17=C17, "Sim", "Não") -> Não
A18: Terreno | B18: Island | C18: Island | D18: =IF(B18=C18, "Sim", "Não") -> Sim
A19: Terreno | B19: Island | C19: Island | D19: =IF(B19=C19, "Sim", "Não") -> Sim
A20: Terreno | B20: Island | C20: Island | D20: =IF(B20=C20, "Sim", "Não") -> Sim
A21: Terreno | B21: Island | C21: Island | D21: =IF(B21=C21, "Sim", "Não") -> Sim
A22: Terreno | B22: Island | C22: Island | D22: =IF(B22=C22, "Sim", "Não") -> Sim
A23: Terreno | B23: Island | C23: Island | D23: =IF(B23=C23, "Sim", "Não") -> Sim
A24: Terreno | B24: Island | C24: Island | D24: =IF(B24=C24, "Sim", "Não") -> Sim
... A55: Draw | B55: Marchesa's Decree | C55: Marchesa's Decree | D55: =IF(B55=C55, "Sim", "Não") -> Sim
A56: Draw | B56: Clackbridge Troll | C56: Clackbridge Troll | D56: =IF(B56=C56, "Sim", "Não") -> Sim | E56: Firkraag, Cunning Instigator
A57: Draw | B57: Karazikar, the Eye Tyrant | C57: Karazikar, the Eye Tyrant | D57: =IF(B57=C57, "Sim", "Não") -> Sim
A58: Draw | B58: Hateful Eidolon | C58: Hateful Eidolon | D58: =IF(B58=C58, "Sim", "Não") -> Sim
A59: Controle | B59: Tragic Slip | C59: Tragic Slip | D59: =IF(B59=C59, "Sim", "Não") -> Sim
A60: Controle | B60: Terminate | C60: Terminate | D60: =IF(B60=C60, "Sim", "Não") -> Sim
A61: Controle | B61: Sudden Spoiling | C61: Sudden Spoiling | D61: =IF(B61=C61, "Sim", "Não") -> Sim
A62: Controle | B62: Rakdos Charm | C62: Rakdos Charm | D62: =IF(B62=C62, "Sim", "Não") -> Sim
A63: Controle | B63: Negate | C63: Negate | D63: =IF(B63=C63, "Sim", "Não") -> Sim
A64: Controle | B64: Countersquall | C64: Counterspell | D64: =IF(B64=C64, "Sim", "Não") -> Não
A65: Controle | B65: Counterflux | C65: Cyber Conversion | D65: =IF(B65=C65, "Sim", "Não") -> Não
A66: Controle | B66: Maestros Confluence | C66: Maestros Confluence | D66: =IF(B66=C66, "Sim", "Não") -> Sim
A67: War | B67: Red Death, Shipwrecker | C67: Red Death, Shipwrecker | D67: =IF(B67=C67, "Sim", "Não") -> Sim
A68: War | B68: Hot Pursuit | C68: Hot Pursuit | D68: =IF(B68=C68, "Sim", "Não") -> Sim
... A79: War | B79: Espião-mestre Goblin | C79: Dúplice Debochada | D79: =IF(B79=C79, "Sim", "Não") -> Não
A80: War | B80: Coronation of Chaos | C80: Coronation of Chaos | D80: =IF(B80=C80, "Sim", "Não") -> Sim | E80: Bothersome Quasit
A81: War | B81: Rite of the Raging Storm | C81: Life of the Party | D81: =IF(B81=C81, "Sim", "Não") -> Não
A82: War | B82: Sontaran General | C82: Sontaran General | D82: =IF(B82=C82, "Sim", "Não") -> Sim | E82: Ghoulish Impetus
A83: War | B83: Ginete Bronco Exaltado | C83: Frenzied Gorespawn | D83: =IF(B83=C83, "Sim", "Não") -> Não
A84: War | B84: Geode Rager | C84: Geode Rager | D84: =IF(B84=C84, "Sim", "Não") -> Sim
A85: Suporte | B85: Strionic Resonator | C85: Strionic Resonator | D85: =IF(B85=C85, "Sim", "Não") -> Sim
A86: Suporte | B86: Gossip's Talent | C86: Gossip's Talent | D86: =IF(B86=C86, "Sim", "Não") -> Sim
A87: Suporte | B87: Sword Coast Sailor | C87: Sword Coast Sailor | D87: =IF(B87=C87, "Sim", "Não") -> Sim
A88: Suporte | B88: Erdwal Illuminator | C88: Erdwal Illuminator | D88: =IF(B88=C88, "Sim", "Não") -> Sim
A89: Suporte | B89: Agitator Ant | C89: Agitator Ant | D89: =IF(B89=C89, "Sim", "Não") -> Sim
A90: Suporte | B90: Kazuul, Tyrant of the Cliffs | C90: Kazuul, Tyrant of the Cliffs | D90: =IF(B90=C90, "Sim", "Não") -> Sim
A91: Suporte | B91: Royal Assassin | C91: Royal Assassin | D91: =IF(B91=C91, "Sim", "Não") -> Sim
A92: Suporte | B92: Revenge of Ravens | C92: Revenge of Ravens | D92: =IF(B92=C92, "Sim", "Não") -> Sim
A93: Suporte | B93: Fumiko, the Lowblood | C93: Xantcha, Agente Adormecida | D93: =IF(B93=C93, "Sim", "Não") -> Não
A94: Suporte | B94: Hissing Miasma | C94: Hissing Miasma | D94: =IF(B94=C94, "Sim", "Não") -> Sim
... A101: Suporte | B101: Martha Jones | C101: Martha Jones | D101: =IF(B101=C101, "Sim", "Não") -> Sim

Sheet Bichão
A1: Jhoira Bichão
A2: Função | B2: Carta Atual | C2: Carta Ideal | D2: Carta Final
A3: Commander | B3: Jhoira of the Ghitu | C3: Jhoira of the Ghitu | D3: =IF(B3=C3, "Sim", "Não") -> Sim
A4: Terreno | B4: Colina da Rocha Espinhosa | C4: Colina da Rocha Espinhosa | D4: =IF(B4=C4, "Sim", "Não") -> Sim | F4: Mudanças Faltando | G4: =COUNTIF(D4:D106,"Não") -> 20
A5: Terreno | B5: Torre do Relicário | C5: Torre do Relicário | D5: =IF(B5=C5, "Sim", "Não") -> Sim | F5: Total de Cartas | G5: =SUM(G8:G27) -> 94
A6: Terreno | B6: Sulfur Falls | C6: Sulfur Falls | D6: =IF(B6=C6, "Sim", "Não") -> Sim
A7: Terreno | B7: Montanha | C7: Exotic Orchard | D7: =IF(B7=C7, "Sim", "Não") -> Não | F7: Funções
A8: Terreno | B8: Command Tower | C8: Command Tower | D8: =IF(B8=C8, "Sim", "Não") -> Sim | F8: Terreno | G8: =COUNTIF(A:A,F8) -> 35
A9: Terreno | B9: Montanha | C9: Valfenda | D9: =IF(B9=C9, "Sim", "Não") -> Não | F9: Ramp | G9: =COUNTIF(A:A,F9) -> 10
A10: Terreno | B10: Ilha | C10: Mistrise Village | D10: =IF(B10=C10, "Sim", "Não") -> Não | F10: Draw | G10: =COUNTIF(A:A,F10) -> 5
A11: Terreno | B11: Ilha | C11: Temple of the False God | D11: =IF(B11=C11, "Sim", "Não") -> Não | F11: Controle | G11: =COUNTIF(A:A,F11) -> 5
A12: Terreno | B12: Ilha | C12: Trenzalore Clocktower | D12: =IF(B12=C12, "Sim", "Não") -> Não | F12: Bichão | G12: =COUNTIF(A:A,F12) -> 19
A13: Terreno | B13: Ilha | C13: Ilha | D13: =IF(B13=C13, "Sim", "Não") -> Sim | F13: Suporte | G13: =COUNTIF(A:A,F13) -> 20
A14: Terreno | B14: Ilha | C14: Ilha | D14: =IF(B14=C14, "Sim", "Não") -> Sim
A15: Terreno | B15: Ilha | C15: Ilha | D15: =IF(B15=C15, "Sim", "Não") -> Sim
A16: Terreno | B16: Ilha | C16: Ilha | D16: =IF(B16=C16, "Sim", "Não") -> Sim
A17: Terreno | B17: Ilha | C17: Ilha | D17: =IF(B17=C17, "Sim", "Não") -> Sim
A18: Terreno | B18: Ilha | C18: Ilha | D18: =IF(B18=C18, "Sim", "Não") -> Sim
A19: Terreno | B19: Ilha | C19: Ilha | D19: =IF(B19=C19, "Sim", "Não") -> Sim
A20: Terreno | B20: Ilha | C20: Ilha | D20: =IF(B20=C20, "Sim", "Não") -> Sim
A21: Terreno | B21: Ilha | C21: Ilha | D21: =IF(B21=C21, "Sim", "Não") -> Sim
A22: Terreno | B22: Ilha | C22: Ilha | D22: =IF(B22=C22, "Sim", "Não") -> Sim
A23: Terreno | B23: Ilha | C23: Ilha | D23: =IF(B23=C23, "Sim", "Não") -> Sim
A24: Terreno | B24: Ilha | C24: Ilha | D24: =IF(B24=C24, "Sim", "Não") -> Sim
A25: Terreno | B25: Ilha | C25: Ilha | D25: =IF(B25=C25, "Sim", "Não") -> Sim
... A39: Ramp | B39: Sol Ring | C39: Sol Ring | D39: =IF(B39=C39, "Sim", "Não") -> Sim
A40: Ramp | C40: Arcane Signet | D40: =IF(B40=C40, "Sim", "Não") -> Não
A41: Ramp | C41: Izzet Signet | D41: =IF(B41=C41, "Sim", "Não") -> Não
A42: Ramp | C42: Thought Vessel | D42: =IF(B42=C42, "Sim", "Não") -> Não
A43: Ramp | B43: Curse of Opulence | C43: Curse of Opulence | D43: =IF(B43=C43, "Sim", "Não") -> Sim
A44: Ramp | C44: Gilded Lotus | D44: =IF(B44=C44, "Sim", "Não") -> Não
A45: Ramp | C45: Rotating Fireplace | D45: =IF(B45=C45, "Sim", "Não") -> Não
A46: Ramp | C46: Sol Talisman | D46: =IF(B46=C46, "Sim", "Não") -> Não
A47: Ramp | C47: Thran Dynamo | D47: =IF(B47=C47, "Sim", "Não") -> Não
A48: Ramp | C48: Mox Tantalite | D48: =IF(B48=C48, "Sim", "Não") -> Não
A49: Draw | B49: Rhystic Study | C49: Rhystic Study | D49: =IF(B49=C49, "Sim", "Não") -> Sim
A50: Draw | B50: Academy Loremaster | C50: Academy Loremaster | D50: =IF(B50=C50, "Sim", "Não") -> Sim
A51: Draw | B51: Visão Transbordante | C51: Visão Transbordante | D51: =IF(B51=C51, "Sim", "Não") -> Sim
A52: Draw | B52: Arcanis, o Onipotente | C52: Arcanis, o Onipotente | D52: =IF(B52=C52, "Sim", "Não") -> Sim
A53: Draw | C53: Rise of the Eldrazi | D53: =IF(B53=C53, "Sim", "Não") -> Não
A54: Global | B54: Obliterate | C54: Obliterate | D54: =IF(B54=C54, "Sim", "Não") -> Sim
A55: Global | B55: Worldfire | C55: Worldfire | D55: =IF(B55=C55, "Sim", "Não") -> Sim
A56: Global | B56: Apocalipse | C56: Apocalipse | D56: =IF(B56=C56, "Sim", "Não") -> Sim
A57: Global | B57: Jokulhaups | C57: Jokulhaups | D57: =IF(B57=C57, "Sim", "Não") -> Sim
A58: Global | B58: Decree of Annihilation | C58: Decree of Annihilation | D58: =IF(B58=C58, "Sim", "Não") -> Sim
A59: Controle | B59: An Offer You Can't Refuse | C59: An Offer You Can't Refuse | D59: =IF(B59=C59, "Sim", "Não") -> Sim
A60: Controle | B60: Negação Vorticosa | C60: Negação Vorticosa | D60: =IF(B60=C60, "Sim", "Não") -> Sim
A61: Controle | B61: Chaos Warp | C61: Chaos Warp | D61: =IF(B61=C61, "Sim", "Não") -> Sim
A62: Controle | B62: Negate | C62: Negate | D62: =IF(B62=C62, "Sim", "Não") -> Sim
A63: Controle | B63: Counterspell | C63: Counterspell | D63: =IF(B63=C63, "Sim", "Não") -> Sim
A64: Bichão | B64: Emrakul, the Promised End | C64: Emrakul, the Promised End | D64: =IF(B64=C64, "Sim", "Não") -> Sim
A65: Bichão | C65: Emrakul, um Novo Mundo | D65: =IF(B65=C65, "Sim", "Não") -> Não
A66: Bichão | B66: Kozilek, Butcher of Truth | C66: Kozilek, Butcher of Truth | D66: =IF(B66=C66, "Sim", "Não") -> Sim
A67: Bichão | B67: Kozilek, the Great Distortion | C67: Kozilek, the Great Distortion | D67: =IF(B67=C67, "Sim", "Não") -> Sim
A68: Bichão | C68: Kozilek, the Broken Reality | D68: =IF(B68=C68, "Sim", "Não") -> Não
A69: Bichão | B69: Ulamog, the Infinite Gyre | C69: Ulamog, the Infinite Gyre | D69: =IF(B69=C69, "Sim", "Não") -> Sim
A70: Bichão | B70: Ulamog, the Ceaseless Hunger | C70: Ulamog, the Ceaseless Hunger | D70: =IF(B70=C70, "Sim", "Não") -> Sim
A71: Bichão | C71: Ulamog, o Profanador | D71: =IF(B71=C71, "Sim", "Não") -> Não
A72: Bichão | B72: Etali, Tormenta Primordial | C72: Etali, Tormenta Primordial | D72: =IF(B72=C72, "Sim", "Não") -> Sim
A73: Bichão | B73: Blightsteel Colossus | C73: Blightsteel Colossus | D73: =IF(B73=C73, "Sim", "Não") -> Sim
A74: Bichão | B74: Pathrazer of Ulamog | C74: Pathrazer of Ulamog | D74: =IF(B74=C74, "Sim", "Não") -> Sim
A75: Bichão | B75: Void Winnower | C75: Void Winnower | D75: =IF(B75=C75, "Sim", "Não") -> Sim
A76: Bichão | B76: Jin-Gitaxias, Core Augur | C76: Jin-Gitaxias, Core Augur | D76: =IF(B76=C76, "Sim", "Não") -> Sim
A77: Bichão | B77: It That Betrays | C77: It That Betrays | D77: =IF(B77=C77, "Sim", "Não") -> Sim
A78: Bichão | B78: Omniscience | C78: Omniscience | D78: =IF(B78=C78, "Sim", "Não") -> Sim
A79: Bichão | B79: Aminatou's Augury | C79: Aminatou's Augury | D79: =IF(B79=C79, "Sim", "Não") -> Sim
A80: Bichão | B80: Consecrated Sphinx | C80: Consecrated Sphinx | D80: =IF(B80=C80, "Sim", "Não") -> Sim
A81: Bichão | B81: Nezahal, Primal Tide | C81: Nezahal, Primal Tide | D81: =IF(B81=C81, "Sim", "Não") -> Sim
A82: Bichão | C82: Ulamog's Dreadsire | D82: =IF(B82=C82, "Sim", "Não") -> Não
A83: Suporte | B83: Blasphemous Act | C83: Blasphemous Act | D83: =IF(B83=C83, "Sim", "Não") -> Sim
A84: Suporte | B84: Whelming Wave | C84: Whelming Wave | D84: =IF(B84=C84, "Sim", "Não") -> Sim
A85: Suporte | B85: Consuming Tide | C85: Consuming Tide | D85: =IF(B85=C85, "Sim", "Não") -> Sim
A86: Suporte | B86: Chain Reaction | C86: Chain Reaction | D86: =IF(B86=C86, "Sim", "Não") -> Sim
A87: Suporte | B87: Devastation Tide | C87: Devastation Tide | D87: =IF(B87=C87, "Sim", "Não") -> Sim
A88: Suporte | B88: Brumas do Paradoxo | C88: Brumas do Paradoxo | D88: =IF(B88=C88, "Sim", "Não") -> Sim
A89: Suporte | C89: The Tenth Doctor | D89: =IF(B89=C89, "Sim", "Não") -> Não
A90: Suporte | B90: Wibbly-Wobbly, Timey-wimey | C90: Wibbly-Wobbly, Timey-wimey | D90: =IF(B90=C90, "Sim", "Não") -> Sim
A91: Suporte | B91: Elemental da Fenda | C91: Elemental da Fenda | D91: =IF(B91=C91, "Sim", "Não") -> Sim
A92: Suporte | B92: Medalhão da Fúria | C92: Medalhão da Fúria | D92: =IF(B92=C92, "Sim", "Não") -> Sim
A93: Suporte | B93: Clockspinning | C93: Clockspinning | D93: =IF(B93=C93, "Sim", "Não") -> Sim
A94: Suporte | B94: Timecrafting | C94: Timecrafting | D94: =IF(B94=C94, "Sim", "Não") -> Sim
A95: Suporte | B95: Jhoira's Timebug | C95: Jhoira's Timebug | D95: =IF(B95=C95, "Sim", "Não") -> Sim
A96: Suporte | B96: Time Beetle | C96: Time Beetle | D96: =IF(B96=C96, "Sim", "Não") -> Sim
A97: Suporte | B97: Hit the Mother Lode | C97: Hit the Mother Lode | D97: =IF(B97=C97, "Sim", "Não") -> Sim
A98: Suporte | C98: Inevitable Betrayal | D98: =IF(B98=C98, "Sim", "Não") -> Não
A99: Suporte | B99: Sibylline Soothsayer | C99: Sibylline Soothsayer | D99: =IF(B99=C99, "Sim", "Não") -> Sim
A100: Suporte | B100: Propaganda | C100: Propaganda | D100: =IF(B100=C100, "Sim", "Não") -> Sim
A101: Suporte | B101: Crawlspace | C101: Crawlspace | D101: =IF(B101=C101, "Sim", "Não") -> Sim
A102: Suporte | B102: Presságio da Calamidade | C102: Presságio da Calamidade | D102: =IF(B102=C102, "Sim", "Não") -> Sim

Sheet OWA
A1: Othelm e Wernog | I1: Roubadas
A2: Função | B2: Carta Atual | C2: Carta Ideal | D2: Carta Final | I2: Original | J2: Deck
A3: Terreno | B3: Castle Ardenvale | C3: Castle Ardenvale | D3: =IF(B3=C3, "Sim", "Não") -> Sim | F3: Mudanças Faltando | G3: =COUNTIF(D3:D100,"Não") -> 7
A4: Terreno | B4: Gavony Township | C4: Gavony Township | D4: =IF(B4=C4, "Sim", "Não") -> Sim | F4: Total de Cartas | G4: =SUM(G7:G25) -> 98
A5: Terreno | B5: Westvale Abbey | C5: Westvale Abbey | D5: =IF(B5=C5, "Sim", "Não") -> Sim
A6: Terreno | B6: Vitu-Ghazi, the City-Tree | C6: Vitu-Ghazi, the City-Tree | D6: =IF(B6=C6, "Sim", "Não") -> Sim | F6: Funções
A7: Terreno | B7: Grove of the Guardian | C7: Grove of the Guardian | D7: =IF(B7=C7, "Sim", "Não") -> Sim | F7: Terreno | G7: =COUNTIF(A:A,F7) -> 34
A8: Terreno | B8: Havengul Laboratory | C8: Havengul Laboratory | D8: =IF(B8=C8, "Sim", "Não") -> Sim | F8: Ramp | G8: =COUNTIF(A:A,F8) -> 12
A9: Terreno | B9: Canopy Vista | C9: Canopy Vista | D9: =IF(B9=C9, "Sim", "Não") -> Sim | F9: Draw | G9: =COUNTIF(A:A,F9) -> 6
A10: Terreno | B10: Portão da Guilda Orzhov | C10: Scattered Groves | D10: =IF(B10=C10, "Sim", "Não") -> Não | F10: Vida | G10: =COUNTIF(A:A,F10) -> 4
A11: Terreno | B11: Isolated Chapel | C11: Isolated Chapel | D11: =IF(B11=C11, "Sim", "Não") -> Sim | F11: Recursão | G11: =COUNTIF(A:A,F11) -> 6
A12: Terreno | B12: Woodland Cemetery | C12: Woodland Cemetery | D12: =IF(B12=C12, "Sim", "Não") -> Sim | F12: Remoção | G12: =COUNTIF(A:A,F12) -> 5
A13: Terreno | B13: Sunpetal Grove | C13: Sunpetal Grove | D13: =IF(B13=C13, "Sim", "Não") -> Sim | F13: Sacrifício | G13: =COUNTIF(A:A,F13) -> 5
A14: Terreno | B14: Brushland | C14: Brushland | D14: =IF(B14=C14, "Sim", "Não") -> Sim | F14: Tokens | G14: =COUNTIF(A:A,F14) -> 22
A15: Terreno | B15: Caves of Koilos | C15: Caves of Koilos | D15: =IF(B15=C15, "Sim", "Não") -> Sim | F15: Utilidades | G15: =COUNTIF(A:A,F15) -> 4
A16: Terreno | B16: Llanowar Wastes | C16: Llanowar Wastes | D16: =IF(B16=C16, "Sim", "Não") -> Sim
A17: Terreno | B17: Command Tower | C17: Command Tower | D17: =IF(B17=C17, "Sim", "Não") -> Sim
A18: Terreno | B18: Exotic Orchard | C18: Exotic Orchard | D18: =IF(B18=C18, "Sim", "Não") -> Sim
A19: Terreno | B19: Mirrodin's Core | C19: Mirrodin's Core | D19: =IF(B19=C19, "Sim", "Não") -> Sim
A20: Terreno | B20: High Market | C20: High Market | D20: =IF(B20=C20, "Sim", "Não") -> Sim
A21: Terreno | B21: Bojuka Bog | C21: Bojuka Bog | D21: =IF(B21=C21, "Sim", "Não") -> Sim
A22: Terreno | B22: Temple of Plenty | C22: Temple of Plenty | D22: =IF(B22=C22, "Sim", "Não") -> Sim
A23: Terreno | B23: Temple of Malady | C23: Temple of Malady | D23: =IF(B23=C23, "Sim", "Não") -> Sim
A24: Terreno | B24: Temple of Silence | C24: Temple of Silence | D24: =IF(B24=C24, "Sim", "Não") -> Sim
A25: Terreno | B25: Recuperação de Bala Ged | C25: Recuperação de Bala Ged | D25: =IF(B25=C25, "Sim", "Não") -> Sim
A26: Terreno | B26: Reliquary Tower | C26: Reliquary Tower | D26: =IF(B26=C26, "Sim", "Não") -> Sim
A27: Terreno | B27: Swamp | C27: Susur Secundi, Void Altar | D27: =IF(B27=C27, "Sim", "Não") -> Não
... A100: Remoção | B100: The Battle of Bywater | C100: The Battle of Bywater | D100: =IF(B100=C100, "Sim", "Não") -> Sim

Sheet Zimone
A1: Zimone e Dinah
A2: Função | B2: Carta Atual | C2: Carta Ideal | D2: Carta Final
A3: Terreno | B3: Field of the Dead | C3: Field of the Dead | D3: =IF(B3=C3, "Sim", "Não") -> Sim | F3: Mudanças Faltando | G3: =COUNTIF(D3:D100,"Não") -> 17
A4: Terreno | B4: Reliquary Tower | C4: Reliquary Tower | D4: =IF(B4=C4, "Sim", "Não") -> Sim | F4: Total de Cartas | G4: =SUM(G7:G25) -> 99
A5: Terreno | B5: Khalni Garden | C5: Khalni Garden | D5: =IF(B5=C5, "Sim", "Não") -> Sim
A6: Terreno | B6: Simic Growth Chamber | C6: Simic Growth Chamber | D6: =IF(B6=C6, "Sim", "Não") -> Sim | F6: Funções
A7: Terreno | B7: Golgari Rot Farm | C7: Golgari Rot Farm | D7: =IF(B7=C7, "Sim", "Não") -> Sim | F7: Terreno | G7: =COUNTIF(A:A,F7) -> 36
A8: Terreno | B8: Dimir Aqueduct | C8: Dimir Aqueduct | D8: =IF(B8=C8, "Sim", "Não") -> Sim | F8: Ramp | G8: =COUNTIF(A:A,F8) -> 9
A9: Terreno | C9: Fabled Passage | D9: =IF(B9=C9, "Sim", "Não") -> Não | F9: Draw | G9: =COUNTIF(A:A,F9) -> 9
A10: Terreno | C10: Bala Ged Recovery | D10: =IF(B10=C10, "Sim", "Não") -> Não | F10: Value | G10: =COUNTIF(A:A,F10) -> 10
A11: Terreno | B11: Command Tower | C11: Command Tower | D11: =IF(B11=C11, "Sim", "Não") -> Sim | F11: Untap | G11: =COUNTIF(A:A,F11) -> 5
A12: Terreno | B12: Exotic Orchard | C12: Exotic Orchard | D12: =IF(B12=C12, "Sim", "Não") -> Sim | F12: Controle | G12: =COUNTIF(A:A,F12) -> 13
A13: Terreno | B13: Bojuka Bog | C13: Bojuka Bog | D13: =IF(B13=C13, "Sim", "Não") -> Sim | F13: Return | G13: =COUNTIF(A:A,F13) -> 4
A14: Terreno | C14: Zagoth Triome | D14: =IF(B14=C14, "Sim", "Não") -> Não | F14: Token | G14: =COUNTIF(A:A,F14) -> 13
A15: Terreno | B15: Watery Grave | C15: Watery Grave | D15: =IF(B15=C15, "Sim", "Não") -> Sim
A16: Terreno | C16: Breeding Pool | D16: =IF(B16=C16, "Sim", "Não") -> Não
A17: Terreno | B17: Overgrown Tomb | C17: Overgrown Tomb | D17: =IF(B17=C17, "Sim", "Não") -> Sim
A18: Terreno | C18: Bloodstained Mire | D18: =IF(B18=C18, "Sim", "Não") -> Não
A19: Terreno | C19: Scalding Tarn | D19: =IF(B19=C19, "Sim", "Não") -> Não
A20: Terreno | C20: Polluted Delta | D20: =IF(B20=C20, "Sim", "Não") -> Não
A21: Terreno | B21: Windswept Heath | C21: Windswept Heath | D21: =IF(B21=C21, "Sim", "Não") -> Sim
A22: Terreno | B22: Marsh Flats | C22: Marsh Flats | D22: =IF(B22=C22, "Sim", "Não") -> Sim
A23: Terreno | B23: Wooded Foothills | C23: Wooded Foothills | D23: =IF(B23=C23, "Sim", "Não") -> Sim
A24: Terreno | B24: Flooded Strand | C24: Flooded Strand | D24: =IF(B24=C24, "Sim", "Não") -> Sim
A25: Terreno | B25: Verdant Catacombs | C25: Verdant Catacombs | D25: =IF(B25=C25, "Sim", "Não") -> Sim
A26: Terreno | C26: Misty Rainforest | D26: =IF(B26=C26, "Sim", "Não") -> Não
A27: Terreno | B27: Yavimaya, Berço de Crescimento | C27: Yavimaya, Berço de Crescimento | D27: =IF(B27=C27, "Sim", "Não") -> Sim
A28: Terreno | B28: Island | C28: Island | D28: =IF(B28=C28, "Sim", "Não") -> Sim
A29: Terreno | B29: Island | C29: Island | D29: =IF(B29=C29, "Sim", "Não") -> Sim
A30: Terreno | B30: Island | C30: Island | D30: =IF(B30=C30, "Sim", "Não") -> Sim
A31: Terreno | B31: Swamp | C31: Swamp | D31: =IF(B31=C31, "Sim", "Não") -> Sim
A32: Terreno | B32: Swamp | C32: Swamp | D32: =IF(B32=C32, "Sim", "Não") -> Sim
A33: Terreno | B33: Swamp | C33: Swamp | D33: =IF(B33=C33, "Sim", "Não") -> Sim
A34: Terreno | B34: Swamp | C34: Swamp | D34: =IF(B34=C34, "Sim", "Não") -> Sim
A35: Terreno | B35: Forest | C35: Forest | D35: =IF(B35=C35, "Sim", "Não") -> Sim
A36: Terreno | B36: Forest | C36: Forest | D36: =IF(B36=C36, "Sim", "Não") -> Sim
A37: Terreno | B37: Forest | C37: Forest | D37: =IF(B37=C37, "Sim", "Não") -> Sim
A38: Terreno | B38: Forest | C38: Forest | D38: =IF(B38=C38, "Sim", "Não") -> Sim
... A42: Ramp | B42: Farseek | C42: Farseek | D42: =IF(B42=C42, "Sim", "Não") -> Sim
A43: Ramp | C43: Three Visits | D43: =IF(B43=C43, "Sim", "Não") -> Não
A44: Ramp | B44: Entish Restoration | C44: Entish Restoration | D44: =IF(B44=C44, "Sim", "Não") -> Sim
A45: Ramp | B45: Farhaven Elf | C45: Farhaven Elf | D45: =IF(B45=C45, "Sim", "Não") -> Sim
A46: Ramp | B46: Wood Elves | C46: Wood Elves | D46: =IF(B46=C46, "Sim", "Não") -> Sim
A47: Ramp | B47: Birds of Paradise | C47: Birds of Paradise | D47: =IF(B47=C47, "Sim", "Não") -> Sim
A48: Draw | B48: Ecological Appreciation | C48: Ecological Appreciation | D48: =IF(B48=C48, "Sim", "Não") -> Sim
A49: Draw | B49: Morbid Opportunist | C49: Morbid Opportunist | D49: =IF(B49=C49, "Sim", "Não") -> Sim
A50: Draw | B50: Tatyova, Benthic Druid | C50: Tatyova, Benthic Druid | D50: =IF(B50=C50, "Sim", "Não") -> Sim
A51: Draw | B51: Tireless Tracker | C51: Tireless Tracker | D51: =IF(B51=C51, "Sim", "Não") -> Sim
A52: Draw | B52: A Ascensão da Onda Faminta | C52: Teferi's Ageless Insight | D52: =IF(B52=C52, "Sim", "Não") -> Não
A53: Draw | B53: Phyrexian Arena | C53: Phyrexian Arena | D53: =IF(B53=C53, "Sim", "Não") -> Sim
A54: Draw | B54: Chord of Calling | C54: Chord of Calling | D54: =IF(B54=C54, "Sim", "Não") -> Sim
A55: Draw | B55: Wight of the Reliquary | C55: Wight of the Reliquary | D55: =IF(B55=C55, "Sim", "Não") -> Sim
... A59: Token | B59: Springheart Nantuko | C59: Springheart Nantuko | D59: =IF(B59=C59, "Sim", "Não") -> Sim
A60: Token | C60: Jadar, Ghoulcaller of Nephalia | D60: =IF(B60=C60, "Sim", "Não") -> Não
A61: Token | B61: Chatterfang, Squirrel General | C61: Chatterfang, Squirrel General | D61: =IF(B61=C61, "Sim", "Não") -> Sim
A62: Token | B62: Scute Swarm | C62: Scute Swarm | D62: =IF(B62=C62, "Sim", "Não") -> Sim
A63: Token | B63: Minn, Wily Illusionist | C63: Minn, Wily Illusionist | D63: =IF(B63=C63, "Sim", "Não") -> Sim
A64: Token | B64: Ophiomancer | C64: Ophiomancer | D64: =IF(B64=C64, "Sim", "Não") -> Sim
A65: Token | B65: Chasm Skulker | C65: Chasm Skulker | D65: =IF(B65=C65, "Sim", "Não") -> Sim
A66: Token | B66: Kraken do Nadir | C66: Kraken do Nadir | D66: =IF(B66=C66, "Sim", "Não") -> Sim
A67: Token | B67: Nemata, Primeval Warden | C67: Nemata, Primeval Warden | D67: =IF(B67=C67, "Sim", "Não") -> Sim
A68: Token | B68: Zimone, Mystery Unraveler | C68: Zimone, Mystery Unraveler | D68: =IF(B68=C68, "Sim", "Não") -> Sim
A69: Token | B69: Homunculus Horde | C69: Homunculus Horde | D69: =IF(B69=C69, "Sim", "Não") -> Sim
A70: Return | B70: Bloodghast | C70: Bloodghast | D70: =IF(B70=C70, "Sim", "Não") -> Sim
A71: Return | B71: Reassembling Skeleton | C71: Reassembling Skeleton | D71: =IF(B71=C71, "Sim", "Não") -> Sim
A72: Return | C72: Oathsworn Vampire | D72: =IF(B72=C72, "Sim", "Não") -> Não
A73: Return | B73: Nether Traitor | C73: Nether Traitor | D73: =IF(B73=C73, "Sim", "Não") -> Sim
A74: Value | B74: Lotus Cobra | C74: Lotus Cobra | D74: =IF(B74=C74, "Sim", "Não") -> Sim
A75: Value | B75: Tireless Provisioner | C75: Tireless Provisioner | D75: =IF(B75=C75, "Sim", "Não") -> Sim
A76: Value | B76: Amulet of Vigor | C76: Amulet of Vigor | D76: =IF(B76=C76, "Sim", "Não") -> Sim
A77: Value | B77: Exploração de Cavernas | C77: Horizon Explorer | D77: =IF(B77=C77, "Sim", "Não") -> Não
A78: Value | C78: Ancient Greenwarden | D78: =IF(B78=C78, "Sim", "Não") -> Não
A79: Value | B79: Freestrider Lookout | C79: Freestrider Lookout | D79: =IF(B79=C79, "Sim", "Não") -> Sim
A80: Value | B80: Ashaya, Soul of the Wild | C80: Ashaya, Soul of the Wild | D80: =IF(B80=C80, "Sim", "Não") -> Sim
A81: Value | B81: Elvish Reclaimer | C81: Elvish Reclaimer | D81: =IF(B81=C81, "Sim", "Não") -> Sim
A82: Value | B82: Ramunap Excavator | C82: Ramunap Excavator | D82: =IF(B82=C82, "Sim", "Não") -> Sim
A83: Value | B83: Muldrotha, the Gravetide | C83: Muldrotha, the Gravetide | D83: =IF(B83=C83, "Sim", "Não") -> Sim
A84: Controle | B84: Dictate of Erebos | C84: Dictate of Erebos | D84: =IF(B84=C84, "Sim", "Não") -> Sim
A85: Controle | B85: Estudo Rístico | C85: Grave Pact | D85: =IF(B85=C85, "Sim", "Não") -> Não
A86: Controle | C86: Sothera, the Supervoid | D86: =IF(B86=C86, "Sim", "Não") -> Não
A87: Controle | B87: Negate | C87: Negate | D87: =IF(B87=C87, "Sim", "Não") -> Sim
A88: Controle | B88: Beast Within | C88: Beast Within | D88: =IF(B88=C88, "Sim", "Não") -> Sim
A89: Controle | B89: Insidious Fungus | C89: Insidious Fungus | D89: =IF(B89=C89, "Sim", "Não") -> Sim
A90: Controle | B90: Deprive | C90: Deprive | D90: =IF(B90=C90, "Sim", "Não") -> Sim
A91: Controle | B91: Assassin's Trophy | C91: Assassin's Trophy | D91: =IF(B91=C91, "Sim", "Não") -> Sim
A92: Controle | B92: Arcane Denial | C92: Arcane Denial | D92: =IF(B92=C92, "Sim", "Não") -> Sim
A93: Controle | B93: Toxic Deluge | C93: Toxic Deluge | D93: =IF(B93=C93, "Sim", "Não") -> Sim
A94: Controle | B94: Sultai Charm | C94: Sultai Charm | D94: =IF(B94=C94, "Sim", "Não") -> Sim
A95: Controle | B95: An Offer you Can't Refuse | C95: An Offer you Can't Refuse | D95: =IF(B95=C95, "Sim", "Não") -> Sim
A96: Controle | B96: Abrupt Decay | C96: Abrupt Decay | D96: =IF(B96=C96, "Sim", "Não") -> Sim
A97: Untap | B97: Quirion Ranger | C97: Quirion Ranger | D97: =IF(B97=C97, "Sim", "Não") -> Sim
A98: Untap | C98: Marvin, Murderous Mimic | D98: =IF(B98=C98, "Sim", "Não") -> Não
A99: Untap | B99: Scryb Ranger | C99: Scryb Ranger | D99: =IF(B99=C99, "Sim", "Não") -> Sim
A100: Untap | B100: Retreat to Coralhelm | C100: Retreat to Coralhelm | D100: =IF(B100=C100, "Sim", "Não") -> Sim
A101: Untap | C101: Thousand-Year Elixir | D101: =IF(B101=C101, "Sim", "Não") -> Não

Sheet Narset
A1: Narset Mill
A2: Função | B2: Carta Atual | C2: Carta Ideal | D2: Carta Final
A3: Terreno | B3: Command Tower | C3: Command Tower | D3: =IF(B3=C3, "Sim", "Não") -> Sim | F3: Mudanças Faltando | G3: =COUNTIF(D3:D105,"Não") -> 32
A4: Terreno | B4: Exotic Orchard | C4: Exotic Orchard | D4: =IF(B4=C4, "Sim", "Não") -> Sim | F4: Total de Cartas | G4: =SUM(G7:G24) -> 99
A5: Terreno | B5: Opal Palace | C5: Opal Palace | D5: =IF(B5=C5, "Sim", "Não") -> Sim
A6: Terreno | B6: Rogue's Passage | C6: Rogue's Passage | D6: =IF(B6=C6, "Sim", "Não") -> Sim | F6: Funções
A7: Terreno | B7: Plains | C7: Sokenzan, Crucible of Defiance | D7: =IF(B7=C7, "Sim", "Não") -> Não | F7: Terreno | G7: =COUNTIF(A:A,F7) -> 35
A8: Terreno | B8: Plains | C8: Slayers' Stronghold | D8: =IF(B8=C8, "Sim", "Não") -> Não | F8: Ramp | G8: =COUNTIF(A:A,F8) -> 8
A9: Terreno | B9: Mountain | C9: Sea of Clouds | D9: =IF(B9=C9, "Sim", "Não") -> Não | F9: Draw | G9: =COUNTIF(A:A,F9) -> 8
A10: Terreno | B10: Mountain | C10: Training Center | D10: =IF(B10=C10, "Sim", "Não") -> Não | F10: Wheel | G10: =COUNTIF(A:A,F10) -> 6
A11: Terreno | B11: Mountain | C11: Spectator Seating | D11: =IF(B11=C11, "Sim", "Não") -> Não | F11: Mill | G11: =COUNTIF(A:A,F11) -> 14
A12: Terreno | B12: Sulfur Falls | C12: Sulfur Falls | D12: =IF(B12=C12, "Sim", "Não") -> Sim | F12: Utility | G12: =COUNTIF(A:A,F12) -> 5
A13: Terreno | B13: Island | C13: Clifftop Retreat | D13: =IF(B13=C13, "Sim", "Não") -> Não | F13: Protection | G13: =COUNTIF(A:A,F13) -> 9
A14: Terreno | B14: Glacial Fortress | C14: Glacial Fortress | D14: =IF(B14=C14, "Sim", "Não") -> Sim | F14: Remoção | G14: =COUNTIF(A:A,F14) -> 5
A15: Terreno | B15: Shivan Reef | C15: Shivan Reef | D15: =IF(B15=C15, "Sim", "Não") -> Sim | F15: Army | G15: =COUNTIF(A:A,F15) -> 5
A16: Terreno | B16: Battlefield Forge | C16: Battlefield Forge | D16: =IF(B16=C16, "Sim", "Não") -> Sim | F16: Combate | G16: =COUNTIF(A:A,F16) -> 4
A17: Terreno | B17: Island | C17: Adarkar Wastes | D17: =IF(B17=C17, "Sim", "Não") -> Não
A18: Terreno | B18: Azorius Chancery | C18: Azorius Chancery | D18: =IF(B18=C18, "Sim", "Não") -> Sim
A19: Terreno | B19: Boros Garrison | C19: Boros Garrison | D19: =IF(B19=C19, "Sim", "Não") -> Sim
A20: Terreno | B20: Izzet Boilerworks | C20: Izzet Boilerworks | D20: =IF(B20=C20, "Sim", "Não") -> Sim
A21: Terreno | B21: Myriad Landscape | C21: Myriad Landscape | D21: =IF(B21=C21, "Sim", "Não") -> Sim
A22: Terreno | B22: Island | C22: Jidoor, Aristocratic Capital | D22: =IF(B22=C22, "Sim", "Não") -> Não
A23: Terreno | B23: Plains | C23: Plains | D23: =IF(B23=C23, "Sim", "Não") -> Sim
A24: Terreno | B24: Plains | C24: Plains | D24: =IF(B24=C24, "Sim", "Não") -> Sim
A25: Terreno | B25: Plains | C25: Plains | D25: =IF(B25=C25, "Sim", "Não") -> Sim
A26: Terreno | B26: Plains | C26: Plains | D26: =IF(B26=C26, "Sim", "Não") -> Sim
A27: Terreno | B27: Island | C27: Island | D27: =IF(B27=C27, "Sim", "Não") -> Sim
A28: Terreno | B28: Island | C28: Island | D28: =IF(B28=C28, "Sim", "Não") -> Sim
... A101: Combate | B101: Traumatize | C101: Genji Glove | D101: =IF(B101=C101, "Sim", "Não") -> Não

Sheet Baylen
A1: Baylen, o Coelho | I1: Roubadas
A2: Função | B2: Carta Atual | C2: Carta Ideal | D2: Carta Final | I2: Original | J2: Deck
A3: Terreno | B3: Khalni Garden | C3: Khalni Garden | D3: =IF(B3=C3, "Sim", "Não") -> Sim | F3: Mudanças Faltando | G3: =COUNTIF(D3:D101,"Não") -> 34
A4: Terreno | B4: Reliquary Tower | C4: Reliquary Tower | D4: =IF(B4=C4, "Sim", "Não") -> Sim | F4: Total de Cartas | G4: =SUM(G7:G25) -> 99
A5: Terreno | B5: Selesnya Sanctuary | C5: The Shire | D5: =IF(B5=C5, "Sim", "Não") -> Não
A6: Terreno | B6: Kher Keep | C6: Kher Keep | D6: =IF(B6=C6, "Sim", "Não") -> Sim | F6: Funções
A7: Terreno | B7: Terras em Desenvolvimento | C7: Castle Ardenvale | D7: =IF(B7=C7, "Sim", "Não") -> Não | F7: Terreno | G7: =COUNTIF(A:A,F7) -> 35
A8: Terreno | B8: Vitu-Ghazi, a Árvore-cidade | C8: Vitu-Ghazi, a Árvore-cidade | D8: =IF(B8=C8, "Sim", "Não") -> Sim | F8: Ramp | G8: =COUNTIF(A:A,F8) -> 6
A9: Terreno | B9: Gleba Gruul | C9: Gavony Township | D9: =IF(B9=C9, "Sim", "Não") -> Não | F9: Tutor | G9: =COUNTIF(A:A,F9) -> 2
A10: Terreno | B10: Panorama de Naya | C10: Rogue's Passage | D10: =IF(B10=C10, "Sim", "Não") -> Não | F10: InstaTokens | G10: =COUNTIF(A:A,F10) -> 5
A11: Terreno | B11: Command Tower | C11: Command Tower | D11: =IF(B11=C11, "Sim", "Não") -> Sim | F11: DoubleTokens | G11: =COUNTIF(A:A,F11) -> 4
A12: Terreno | B12: Exotic Orchard | C12: Exotic Orchard | D12: =IF(B12=C12, "Sim", "Não") -> Sim | F12: HighTokens | G12: =COUNTIF(A:A,F12) -> 9
A13: Terreno | B13: Núcleo de Mirrodin | C13: Sheltering Landscape | D13: =IF(B13=C13, "Sim", "Não") -> Não | F13: AlwaysTokens | G13: =COUNTIF(A:A,F13) -> 13
A14: Terreno | B14: Vastidão Morfoterrena | C14: Mossfire Valley | D14: =IF(B14=C14, "Sim", "Não") -> Não | F14: Remoção | G14: =COUNTIF(A:A,F14) -> 8
A15: Terreno | B15: Sungrass Prairie | C15: Sungrass Prairie | D15: =IF(B15=C15, "Sim", "Não") -> Sim | F15: Value | G15: =COUNTIF(A:A,F15) -> 7
A16: Terreno | B16: Forest | C16: Sunscorched Divide | D16: =IF(B16=C16, "Sim", "Não") -> Não | F16: Proteção | G16: =COUNTIF(A:A,F16) -> 5
A17: Terreno | B17: Plains | C17: Cinder Glade | D17: =IF(B17=C17, "Sim", "Não") -> Não | F17: KillMachine | G17: =COUNTIF(A:A,F17) -> 5
A18: Terreno | B18: Mountain | C18: Canopy Vista | D18: =IF(B18=C18, "Sim", "Não") -> Não
A19: Terreno | B19: Mina dos Anões | C19: Mina dos Anões | D19: =IF(B19=C19, "Sim", "Não") -> Sim
A20: Terreno | B20: Casinha de Doces | C20: Casinha de Doces | D20: =IF(B20=C20, "Sim", "Não") -> Sim
A21: Terreno | B21: Battlefield Forge | C21: Battlefield Forge | D21: =IF(B21=C21, "Sim", "Não") -> Sim
A22: Terreno | B22: Mountain | C22: Karplusan Forest | D22: =IF(B22=C22, "Sim", "Não") -> Não
A23: Terreno | B23: Plains | C23: Brushland | D23: =IF(B23=C23, "Sim", "Não") -> Não
A24: Terreno | B24: Forest | C24: Forest | D24: =IF(B24=C24, "Sim", "Não") -> Sim
A25: Terreno | B25: Forest | C25: Forest | D25: =IF(B25=C25, "Sim", "Não") -> Sim
A26: Terreno | B26: Forest | C26: Forest | D26: =IF(B26=C26, "Sim", "Não") -> Sim
A27: Terreno | B27: Forest | C27: Forest | D27: =IF(B27=C27, "Sim", "Não") -> Sim
A28: Terreno | B28: Forest | C28: Forest | D28: =IF(B28=C28, "Sim", "Não") -> Sim
A29: Terreno | B29: Forest | C29: Forest | D29: =IF(B29=C29, "Sim", "Não") -> Sim
... A92: Value | B92: Dazzling Theater // Prop Room | C92: Dazzling Theater // Prop Room | D92: =IF(B92=C92, "Sim", "Não") -> Sim
A93: Value | B93: Midnight Guard | C93: Elesh Norn | D93: =IF(B93=C93, "Sim", "Não") -> Não | E93: OwA
A94: Remoção | B94: Garra Krosana | C94: Aura Mutation | D94: =IF(B94=C94, "Sim", "Não") -> Não
A95: Remoção | B95: Scavenging Ooze | C95: Artifact Mutation | D95: =IF(B95=C95, "Sim", "Não") -> Não
A96: Remoção | B96: Beast Within | C96: Beast Within | D96: =IF(B96=C96, "Sim", "Não") -> Sim
A97: Remoção | B97: Crib Swap | C97: Generous Gift | D97: =IF(B97=C97, "Sim", "Não") -> Não
A98: Remoção | B98: Sundering Growth | C98: Sundering Growth | D98: =IF(B98=C98, "Sim", "Não") -> Sim
A99: Remoção | B99: Pest Infestation | C99: Pest Infestation | D99: =IF(B99=C99, "Sim", "Não") -> Sim
A100: Remoção | B100: Nature's Claim | C100: Nature's Claim | D100: =IF(B100=C100, "Sim", "Não") -> Sim
A101: Remoção | B101: Swords to Plowshares | C101: Swords to Plowshares | D101: =IF(B101=C101, "Sim", "Não") -> Sim

Sheet Thrakiri
A1: Thrasios e Akiri
A2: Função | B2: Carta Atual | C2: Carta Ideal | D2: Carta Final
A3: Terreno | B3: Great Furnace | C3: Great Furnace | D3: =IF(B3=C3, "Sim", "Não") -> Sim | F3: Mudanças Faltando | G3: =COUNTIF(D3:D105,"Não") -> 6
A4: Terreno | B4: Ancient Den | C4: Ancient Den | D4: =IF(B4=C4, "Sim", "Não") -> Sim | F4: Total de Cartas | G4: =SUM(G7:G28) -> 98
A5: Terreno | B5: Seat of the Synod | C5: Seat of the Synod | D5: =IF(B5=C5, "Sim", "Não") -> Sim
A6: Terreno | B6: Tree of Tales | C6: Tree of Tales | D6: =IF(B6=C6, "Sim", "Não") -> Sim | F6: Funções
A7: Terreno | B7: Darksteel Citadel | C7: Darksteel Citadel | D7: =IF(B7=C7, "Sim", "Não") -> Sim | F7: Terreno | G7: =COUNTIF(A:A,F7) -> 34
A8: Terreno | B8: Feira dos Inventores | C8: Feira dos Inventores | D8: =IF(B8=C8, "Sim", "Não") -> Sim | F8: Ramp | G8: =COUNTIF(A:A,F8) -> 20
A9: Terreno | B9: Urza's Saga | C9: Urza's Saga | D9: =IF(B9=C9, "Sim", "Não") -> Sim | F9: Tutor | G9: =COUNTIF(A:A,F9) -> 8
A10: Terreno | B10: Kessig Wolf Run | C10: Kessig Wolf Run | D10: =IF(B10=C10, "Sim", "Não") -> Sim | F10: Engine | G10: =COUNTIF(A:A,F10) -> 17
A11: Terreno | B11: Ruína Enterrada | C11: Ruína Enterrada | D11: =IF(B11=C11, "Sim", "Não") -> Sim | F11: Remoção | G11: =COUNTIF(A:A,F11) -> 12
A12: Terreno | B12: Command Tower | C12: Command Tower | D12: =IF(B12=C12, "Sim", "Não") -> Sim | F12: Combo | G12: =COUNTIF(A:A,F12) -> 3
A13: Terreno | B13: Pomar Exótico | C13: Pomar Exótico | D13: =IF(B13=C13, "Sim", "Não") -> Sim | F13: Utilidade | G13: =COUNTIF(A:A,F13) -> 4
A14: Terreno | B14: Alchemist's Refuge | C14: Alchemist's Refuge | D14: =IF(B14=C14, "Sim", "Não") -> Sim
A15: Terreno | B15: Cidade de Bronze | C15: Cidade de Bronze | D15: =IF(B15=C15, "Sim", "Não") -> Sim
A16: Terreno | B16: Torre do Relicário | C16: Torre do Relicário | D16: =IF(B16=C16, "Sim", "Não") -> Sim
A17: Terreno | B17: Lanterna Cromática | C17: Uthros, Titanic Godcore | D17: =IF(B17=C17, "Sim", "Não") -> Não
A18: Terreno | B18: Spire of Industry | C18: Spire of Industry | D18: =IF(B18=C18, "Sim", "Não") -> Sim
A19: Terreno | B19: Ilha | C19: The Mycosynth Gardens | D19: =IF(B19=C19, "Sim", "Não") -> Não
A20: Terreno | B20: Ruínas da Academia | C20: Ruínas da Academia | D20: =IF(B20=C20, "Sim", "Não") -> Sim
A21: Terreno | B21: Glacial Fortress | C21: Glacial Fortress | D21: =IF(B21=C21, "Sim", "Não") -> Sim
A22: Terreno | B22: Sunpetal Grove | C22: Sunpetal Grove | D22: =IF(B22=C22, "Sim", "Não") -> Sim
A23: Terreno | B23: Spire Garden | C23: Spire Garden | D23: =IF(B23=C23, "Sim", "Não") -> Sim
A24: Terreno | B24: Clifftop Retreat | C24: Clifftop Retreat | D24: =IF(B24=C24, "Sim", "Não") -> Sim
A25: Terreno | B25: Sulfur Falls | C25: Sulfur Falls | D25: =IF(B25=C25, "Sim", "Não") -> Sim
... A100: Utilidade | B100: Saheeli Rai | C100: Saheeli Rai | D100: =IF(B100=C100, "Sim", "Não") -> Sim

Sheet Gitrog
A1: The Gitrog Monster
A2: Função | B2: Carta Atual | C2: Carta Ideal | D2: Carta Final
A3: Terreno | B3: Myriad Landscape | C3: Myriad Landscape | D3: =IF(B3=C3, "Sim", "Não") -> Sim | F3: Mudanças Faltando | G3: =COUNTIF(D3:D106,"Não") -> 12
A4: Terreno | B4: Command Tower | C4: Command Tower | D4: =IF(B4=C4, "Sim", "Não") -> Sim | F4: Total de Cartas | G4: =SUM(G7:G24) -> 99
A5: Terreno | B5: Argoth, Sanctum of Nature | C5: Argoth, Sanctum of Nature | D5: =IF(B5=C5, "Sim", "Não") -> Sim
A6: Terreno | B6: Overgrown Tomb | C6: Overgrown Tomb | D6: =IF(B6=C6, "Sim", "Não") -> Sim | F6: Funções
A7: Terreno | B7: Llanowar Wastes | C7: Llanowar Wastes | D7: =IF(B7=C7, "Sim", "Não") -> Sim | F7: Terreno | G7: =COUNTIF(A:A,F7) -> 38
A8: Terreno | B8: Woodland Cemetery | C8: Woodland Cemetery | D8: =IF(B8=C8, "Sim", "Não") -> Sim | F8: Ramp | G8: =COUNTIF(A:A,F8) -> 17
A9: Terreno | B9: Golgari Rot Farm | C9: Golgari Rot Farm | D9: =IF(B9=C9, "Sim", "Não") -> Sim | F9: Value | G9: =COUNTIF(A:A,F9) -> 17
A10: Terreno | B10: Tainted Wood | C10: Tainted Wood | D10: =IF(B10=C10, "Sim", "Não") -> Sim | F10: Tutor | G10: =COUNTIF(A:A,F10) -> 9
A11: Terreno | B11: Crystal Vein | C11: Crystal Vein | D11: =IF(B11=C11, "Sim", "Não") -> Sim | F11: Combo | G11: =COUNTIF(A:A,F11) -> 6
A12: Terreno | B12: Dakmor Salvage | C12: Dakmor Salvage | D12: =IF(B12=C12, "Sim", "Não") -> Sim | F12: Controle | G12: =COUNTIF(A:A,F12) -> 8
A13: Terreno | B13: Swamp | C13: Phyrexian Tower | D13: =IF(B13=C13, "Sim", "Não") -> Não | F13: Descarte | G13: =COUNTIF(A:A,F13) -> 4
A14: Terreno | B14: Peat Bog | C14: Peat Bog | D14: =IF(B14=C14, "Sim", "Não") -> Sim
A15: Terreno | B15: Hickory Woodlot | C15: Hickory Woodlot | D15: =IF(B15=C15, "Sim", "Não") -> Sim
A16: Terreno | B16: Ash Barrens | C16: Ash Barrens | D16: =IF(B16=C16, "Sim", "Não") -> Sim
A17: Terreno | B17: Forest | C17: Petrified Field | D17: =IF(B17=C17, "Sim", "Não") -> Não
A18: Terreno | B18: Forest | C18: Ancient Tomb | D18: =IF(B18=C18, "Sim", "Não") -> Não
A19: Terreno | B19: Demolition Field | C19: Demolition Field | D19: =IF(B19=C19, "Sim", "Não") -> Sim
A20: Terreno | B20: Ghost Quarter | C20: Ghost Quarter | D20: =IF(B20=C20, "Sim", "Não") -> Sim
A21: Terreno | B21: Strip Mine | C21: Strip Mine | D21: =IF(B21=C21, "Sim", "Não") -> Sim
A22: Terreno | B22: Blasted Landscape | C22: Blasted Landscape | D22: =IF(B22=C22, "Sim", "Não") -> Sim
A23: Terreno | B23: Fabled Passage | C23: Fabled Passage | D23: =IF(B23=C23, "Sim", "Não") -> Sim
A24: Terreno | B24: Wall of Roots | C24: Takenuma, Charco Abandonado | D24: =IF(B24=C24, "Sim", "Não") -> Não
